Workbook

Sheet Read me first!
B2: User Warning
C3: This database was assembled largely from information received from all the air districts in California except the Bay Area AQMD, with supplemental information supplied by the California Department of Corrections, The Office of Energy Assessments of the California Department of General Services, PG&E, Silicon Valley Power, and a major telecommunications company operating in the state. The user of this inventory needs to be aware of several assumptions made in assembling elements of the database, as well as several known limitations. These include:
C4: • Only BUGs with generating capacities greater than 300 kW are included in the inventory database.
C5: • Data on BUGs in the Bay Area AQMD (BAAQMD) is limited to that supplied by PG&E, Silicon Valley Power, and the major telecommunications company. The inventory most certainly does not include all BUGs in the jurisdiction of the BAAQMD. Although the BAAQMD provided a database of permitted engines in August 2003, it did not contain information on equipment location needed for this database. Therefore, no information provided by BAAQMD is included in this database.
C6: • Facility name, address, and contact information in the data supplied by PG&E are not included in this database as PG&E considers this customer information to be sensitive and privileged.
C7: • The top 14 district sources supplied data generally current though October 2003. The exceptions include the San Diego County APCD data which reflect applications through August 2003, and the Sacramento Metropolitan AQMD and El Dorado County AQMD data which reflect applications through September 2003. The table in the sheet tabbed "How Current" summarizes the timing of the most recent updates from the various data sources.
C8: • NOx and PM emissions factors were taken from the ARB OFFROAD model, and represent average emission factors for corresponding engine ratings and year of manufacture. Emission factors are noted only for diesel-fueled BUGs with known permit application years. The permit application year was assumed to be the BUG year of manufacture.
C9: • Missing numbers in sequence within a data source are the result of cancellations and deletions
B11: Database Structure
C12: The database is contained in the sheet tabbed "Inventory." Each BUG record contains the following information, when available from the data source, arranged in columns:
C13: • Record Number: A number assigned by TIAX/NCI for tracking purposes
C14: • Data Source: A 2 or 3 letter code that corresponds to the source of the data; the table below indicates data sources corresponding to each code
C15: • Facility Name: The BUG owner and facility name
C16: • Permit Application Number: The air district application number for the BUG's air permit
C17: • Permit Application Year: The year the initial air permit application was submitted
C18: • Permit Number: The air district number of the air permit issued
C19: • Engine Description: All information describing the BUG's engine received from the data source
C20: • Primary Fuel: The BUG's primary fuel
C21: • Manufacturer: The manufacturer of the BUG's engine
C22: • Model: The model number of the BUG's engine
C23: • Generator Capacity: The stated or estimated BUG generation capacity (kW); if the capacity was stated by the data source, this is the value used; if the data source only gave the BUG engine's hp or bhp rating, then the generator capacity is calculated from the stated hp or bhp rating using a conversion factor of 0.67 kW/hp
... C33: • PM Emission Factor: Estimated particulate (PM) emission factor (g/bhp-hr); see last item under User Warning above
B35: Data Source Codes
B37: Code | C37: Data Source
B38: AMA | C38: Amador County APCD
B39: AV | C39: Antelope Valley APCD
B40: BTT | C40: Butte County AQMD
B41: CLS | C41: Colusa County APCD
B42: CSC | C42: Silicon Valley Power (City of Santa Clara)
B43: DOC | C43: California Department of Corrections
B44: DWP | C44: Los Angeles Department of Water and Power
B45: EDC | C45: El Dorado County APCD
B46: FRV | C46: Feather River AQMD
B47: GB | C47: Great Basin Unified APCD
B48: GLN | C48: Glenn County APCD
... B70: YS | C70: Yolo Solano AQMD

Sheet How Current
B2: Source | C2: Number of BUGs | D2: Total MW | E2: Database Current Through:
B3: Air Districts
B4: South Coast AQMD | C4: =COUNT(Inventory!K2:K2234) -> 2233 | D4: =SUM(Inventory!K2:K2234)/1000 -> 1844.8673 | E4: October 2003
B5: San Diego County APCD | C5: =COUNT(Inventory!K2762:K3378) -> 617 | D5: =SUM(Inventory!K2762:K3378)/1000 -> 433.19867 | E5: August 2003
B6: San Joaquin Valley Unified APCD | C6: =COUNT(Inventory!K2235:K2761) -> 527 | D6: =SUM(Inventory!K2235:K2761)/1000 -> 402.31967 | E6: October 2003
B7: Sacramento Metropolitan AQMD | C7: =COUNT(Inventory!K3513:K3871) -> 359 | D7: =SUM(Inventory!K3513:K3871)/1000 -> 298.19267 | E7: September 2003
B8: Monterey Bay Unified APCD | C8: =COUNT(Inventory!K3379:K3512) -> 134 | D8: =SUM(Inventory!K3379:K3512)/1000 -> 88.134 | E8: October 2003
B9: Yolo/Solano AQMD | C9: =COUNT(Inventory!K3949:K4038) -> 90 | D9: =SUM(Inventory!K3949:K4038)/1000 -> 74.947333 | E9: October 2003
B10: Ventura County APCD | C10: =COUNT(Inventory!K4208:K4273) -> 66 | D10: =SUM(Inventory!K4208:K4273)/1000 -> 60.324333 | E10: October 2003
B11: Mojave Desert AQMD | C11: =COUNT(Inventory!K3872:K3948) -> 77 | D11: =SUM(Inventory!K3872:K3948)/1000 -> 46.193333 | E11: October 2003
B12: Placer County APCD | C12: =COUNT(Inventory!K4341:K4380) -> 40 | D12: =SUM(Inventory!K4341:K4380)/1000 -> 44.865667 | E12: October 2003
B13: San Luis Obispo County APCD | C13: =COUNT(Inventory!K4139:K4177) -> 39 | D13: =SUM(Inventory!K4139:K4177)/1000 -> 30.523333 | E13: October 2003
B14: Antelope Valley APCD | C14: =COUNT(Inventory!K4039:K4083) -> 45 | D14: =SUM(Inventory!K4039:K4083)/1000 -> 27.451333 | E14: October 2003
B15: Kern County APCD | C15: =COUNT(Inventory!K4287:K4325) -> 39 | D15: =SUM(Inventory!K4287:K4325)/1000 -> 18.102667 | E15: October 2003
B16: El Dorado County AQMD | C16: =COUNT(Inventory!K4084:K4117) -> 34 | D16: =SUM(Inventory!K4084:K4117)/1000 -> 22.215333 | E16: September 2003
B17: Feather River AQMD | C17: =COUNT(Inventory!K4178:K4198) -> 21 | D17: =SUM(Inventory!K4178:K4198)/1000 -> 14.6 | E17: October 2003
B18: Imperial County APCD | C18: =COUNT(Inventory!K4202:K4207) -> 6 | D18: =SUM(Inventory!K4202:K4207)/1000 -> 9.6513333 | E18: April 2001
B19: Butte County AQMD | C19: =COUNT(Inventory!K4393:K4405) -> 13 | D19: =SUM(Inventory!K4393:K4405)/1000 -> 9.1493333 | E19: April 2001
B20: Great Basin Unified APCD | C20: =COUNT(Inventory!K4118:K4128) -> 11 | D20: =SUM(Inventory!K4118:K4128)/1000 -> 7.9853333 | E20: March 2001
B21: Santa Barbara County APCD | C21: =COUNT(Inventory!K4274:K4286) -> 13 | D21: =SUM(Inventory!K4274:K4286)/1000 -> 7.8 | E21: March 2001, poor recordkeeping prior to 2001
B22: Amador County APCD | C22: =COUNT(Inventory!K4129:K4136) -> 8 | D22: =SUM(Inventory!K4129:K4136)/1000 -> 6.949 | E22: April 2001
B23: Shasta County AQMD | C23: =COUNT(Inventory!K4381:K4389) -> 9 | D23: =SUM(Inventory!K4381:K4389)/1000 -> 6.4096667 | E23: April 2001
B24: Lake County AQMD | C24: =COUNT(Inventory!K4326:K4333) -> 8 | D24: =SUM(Inventory!K4326:K4333)/1000 -> 3.87 | E24: April 2001
B25: Mendocino County AQMD | C25: =COUNT(Inventory!K4337:K4339) -> 3 | D25: =SUM(Inventory!K4337:K4339)/1000 -> 2.25 | E25: April 2001
B26: Glenn County APCD | C26: =COUNT(Inventory!K4199:K4201) -> 3 | D26: =SUM(Inventory!K4199:K4201)/1000 -> 1.529 | E26: April 2001
B27: Mariposa County APCD | C27: =COUNT(Inventory!K4334:K4336) -> 3 | D27: =SUM(Inventory!K4334:K4336)/1000 -> 1.12 | E27: April 2001
B28: Tehama County APCD | C28: =COUNT(Inventory!K4390:K4392) -> 3 | D28: =SUM(Inventory!K4390:K4392)/1000 -> 0.98333333 | E28: April 2001
B29: North Coast Unified AQMD | C29: =COUNT(Inventory!K4340) -> 1 | D29: =SUM(Inventory!K4340)/1000 -> 0.75 | E29: April 2001
B30: Colusa County APCD | C30: =COUNT(Inventory!K4137:K4138) -> 2 | D30: =SUM(Inventory!K4137:K4138)/1000 -> 0.7 | E30: April 2001
B32: Other Sources
B33: Pacific Gas & Electric | C33: =COUNT(Inventory!K4448:K4803) -> 356 | D33: =SUM(Inventory!K4448:K4803)/1000 -> 295.1772 | E33: March 2003
B34: California Department of Corrections | C34: =COUNT(Inventory!K4818:K4847) -> 30 | D34: =SUM(Inventory!K4818:K4847)/1000 -> 36.9 | E34: May 2000
B35: Silicon Valley Power | C35: =COUNT(Inventory!K4406:K4447) -> 42 | D35: =SUM(Inventory!K4406:K4447)/1000 -> 35.725 | E35: April 2001
B36: Major Telecommunications Company | C36: =COUNT(Inventory!K4848:K4907) -> 60 | D36: =SUM(Inventory!K4848:K4907)/1000 -> 33.215 | E36: April 2001
B37: Office of Energy Assessments-California Department of General Services | C37: =COUNT(Inventory!K4811:K4817) -> 7 | D37: =SUM(Inventory!K4811:K4817)/1000 -> 8.3733333 | E37: March 2001
B38: Los Angeles Dept. of Water and Power | C38: =COUNT(Inventory!K4804:K4810) -> 7 | D38: =SUM(Inventory!K4804:K4810)/1000 -> 5.76 | E38: April 2001
B39: Totals | C39: =SUM(C4:C38) -> 4906 | D39: =SUM(D4:D38) -> 3880.2332

Sheet Inventory
A1: Record Number | B1: Data Source | C1: Facility Name | D1: Permit Application Number | E1: Permit Application Year | F1: Permit Number | G1: Engine Description | H1: Primary Fuel | I1: Manufacturer | J1: Model | K1: Generator Capacity (kW) | L1: Stated Generator Capacity (kW) | M1: Stated Engine Rating (hp) | N1: Stated Engine Rating (bhp) | O1: Facility Address | P1: City | Q1: Zip Code | R1: Contact Person | S1: Contact Phone Number | T1: NOx Emission Factor (g/bhp-hr) | U1: PM Emission Factor (g/bhp-hr)
A2: 1 | B2: SC | C2: 1875/1925 CENTURY PARK EAST CO | D2: 296382 | E2: 1994 | F2: D85615 | G2: ICE, CATERPILLAR, DIESEL, EMR, MODEL 3412, SN 3857846, TURBOCHARGED, AFTERCOOLED, 12 CYL, 755 BHP | H2: Diesel | I2: Caterpillar | J2: 3412 | K2: =L2+M2*(2/3)+N2*(2/3) -> 503.33333 | N2: 755 | O2: 1875 CENTURY PARK E | P2: LOS ANGELES | Q2: 90067 | R2: DIEHR STEVE | S2: (310) 2030330 | T2: 8.17 | U2: 0.38
A3: 4 | B3: SC | C3: 20TH CENTURY FOX FILM CORP | D3: 330888 | E3: 1997 | F3: F8683 | G3: ICE, CUMMINS, DIESEL, EMR, MODEL QST30-G2, TURBOCHARGED, AFTERCOOLED, 12 CYL, 800 KW, EMR | H3: Diesel | I3: Cummins | J3: QST30-G2 | K3: =L3+M3*(2/3)+N3*(2/3) -> 800 | L3: 800 | O3: 10201 W PICO BLVD BLDG 99 | P3: LOS ANGELES | Q3: 90064-2651 | R3: CANDLER TREVOR | S3: (310) 3696623 | T3: 8.17 | U3: 0.38
A4: 5 | B4: SC | C4: 20TH CENTURY INSURANCE CO | D4: 361864 | E4: 1999 | F4: F23017 | G4: ICE, CUMMINS, DIESEL, EMR, MODEL KTA50-G9, EMR TURBOCHARGED, AFTERCOOLED, 16 CYL, 1500 KW | H4: Diesel | I4: Cummins | J4: KTA50-G9 | K4: =L4+M4*(2/3)+N4*(2/3) -> 1500 | L4: 1500 | O4: 6301 OWENSMOUTH AVE | P4: WOODLAND HILLS | Q4: 91367-2286 | R4: LANDGRAF BERNARD | S4: (818) 7043091 | T4: 8.17 | U4: 0.38
A5: 7 | B5: SC | C5: 360 NETWORKS (USA) INC | D5: 377563 | E5: 2000 | F5: F35656 | G5: ICE, CATERPILLAR, DIESEL, 12 CYL, TURBOCHARGED, AFTERCOOLED, MODEL 3512B DITA, SN 8RM00626, 1500 KW, EMR | H5: Diesel | I5: Caterpillar | J5: 3512B DITA | K5: =L5+M5*(2/3)+N5*(2/3) -> 1500 | L5: 1500 | O5: 600 W 7 TH ST | P5: LOS ANGELES | Q5: 90017 | R5: WALKER RICHARD | S5: (541) 3187392 | T5: 6.9 | U5: 0.4
A6: 8 | B6: SC | C6: 360 NETWORKS (USA) INC | D6: 377564 | E6: 2000 | F6: F35657 | G6: ICE, CATERPILLAR, DIESEL, 12 CYL, TURBOCHARGED, AFTERCOOLED, MODEL 3512B DITA, SN 8RM00627, 1500 KW, EMR | H6: Diesel | I6: Caterpillar | J6: 3512B DITA | K6: =L6+M6*(2/3)+N6*(2/3) -> 1500 | L6: 1500 | O6: 600 W 7 TH ST | P6: LOS ANGELES | Q6: 90017 | R6: WALKER RICHARD | S6: (541) 3187392 | T6: 6.9 | U6: 0.4
A7: 9 | B7: SC | C7: 360 NETWORKS (USA) INC | D7: 377566 | E7: 2000 | F7: F35661 | G7: ICE, CATERPILLAR, DIESEL, 12 CYL, TURBOCHARGED, AFTERCOOLED, MODEL 3512B DITA, SN 8RM00628, 1500 KW, EMR | H7: Diesel | I7: Caterpillar | J7: 3512B DITA | K7: =L7+M7*(2/3)+N7*(2/3) -> 1500 | L7: 1500 | O7: 600 W 7 TH ST | P7: LOS ANGELES | Q7: 90017 | R7: WALKER RICHARD | S7: (541) 3187392 | T7: 6.9 | U7: 0.4
A8: 10 | B8: SC | C8: 450 NORTH BRAND LLC | D8: 363450 | E8: 1999 | F8: F23702 | G8: ICE, DETROIT DIESEL, 12 CYL, TURBOCHARGED, AFTERCOOLED, MODEL 12V-92TA, SN 12VF013933, 830 BHP, EMR | H8: Diesel | I8: Detroit Diesel | J8: 12V-92TA | K8: =L8+M8*(2/3)+N8*(2/3) -> 553.33333 | N8: 830 | O8: 450 N BRAND BLVD | P8: GLENDALE | Q8: 91209 | R8: TEEGARDEN CATHY | S8: (818) 2422152 | T8: 8.17 | U8: 0.38
A9: 12 | B9: SC | C9: 4MC-BURBANK, INC. | D9: 357595 | E9: 1999 | F9: F21411 | G9: ICE, CATERPILLAR, 12 CYL, TURBOCHARGED, AFTERCOOLED, MODEL 3512 DITA, 1250 KW, DIESEL, EMR | H9: Diesel | I9: Caterpillar | J9: 3512 DITA | K9: =L9+M9*(2/3)+N9*(2/3) -> 1250 | L9: 1250 | O9: 2901 W ALAMEDA AVE | P9: BURBANK | Q9: 91505 | R9: TABB JOHN | S9: (818) 8407207 | T9: 8.17 | U9: 0.38
A10: 13 | B10: SC | C10: 550 NORTH BRAND OWNER'S CORP | D10: 286105 | E10: 1993 | F10: D77793 | G10: ICE, CATERPILLAR, 12 CYL, TURBOCHARGED, AFTERCOOLED, MODEL 3412, SN 81205336, 558 BHP, DIESEL, EMR | H10: Diesel | I10: Caterpillar | J10: 3412 | K10: =L10+M10*(2/3)+N10*(2/3) -> 372 | N10: 558 | O10: 550 N BRAND BLVD | P10: GLENDALE | Q10: 91203 | R10: ROSS JUNE | S10: (818) 2426550 | T10: 8.17 | U10: 0.38
A11: 14 | B11: SC | C11: 600 ANTON BLV ASSOC,SO COAST PLZ TWN CTR | D11: 260878 | E11: 1991 | F11: D51286 | G11: ICE, CATERPILLAR, 8 CYL, DIESEL, EMR, MODEL 3508/750, SN 23203472, TURBOCHARGED, AFTERCOOLED, 1098 BHP | H11: Diesel | I11: Caterpillar | J11: 3508 | K11: =L11+M11*(2/3)+N11*(2/3) -> 732 | N11: 1098 | O11: 600 ANTON BLVD | P11: COSTA MESA | Q11: 92626 | R11: SUTTON DON | S11: (714) 4352133 | T11: 8.17 | U11: 0.38
A12: 15 | B12: SC | C12: 611 W 6TH ST ASSOC LLC/METCOM MGMT LLC | D12: 368199 | E12: 2000 | F12: F33277 | G12: ICE, CATERPILLAR, 12 CYL, DIESEL, EMR, MODEL 3412DIT, SN 81Z02794, TURBOCHARGED, AFTERCOOLED, 755 BHP | H12: Diesel | I12: Caterpillar | J12: 3412 DIT | K12: =L12+M12*(2/3)+N12*(2/3) -> 503.33333 | N12: 755 | O12: 611 W 6TH ST | P12: LOS ANGELES | Q12: 90017 | R12: KOILE STEPHEN | S12: (213) 6239989 | T12: 6.9 | U12: 0.4
A13: 16 | B13: SC | C13: 611 W 6TH ST ASSOC LLC/METCOM MGMT LLC | D13: 368200 | E13: 2000 | F13: F33278 | G13: ICE, DETROIT DIESEL, 16 CYL, TURBOCHARGED, AFTERCOOLED, MODEL 7163-7400, SN 16V3328, 700 BHP, EMR, DIESEL | H13: Diesel | I13: Detroit Diesel | J13: 7163-7400 | K13: =L13+M13*(2/3)+N13*(2/3) -> 466.66667 | N13: 700 | O13: 611 W 6TH ST | P13: LOS ANGELES | Q13: 90017 | R13: KOILE STEPHEN | S13: (213) 6239989 | T13: 6.9 | U13: 0.4
A14: 17 | B14: SC | C14: 6300 WILSHIRE ASSOCIATES | D14: 261846 | E14: 1992 | F14: D48429 | G14: ICE, DETROIT DIESEL, 12 CYL, TURBOCHARGED, AFTERCOOLED, MODEL 8123-7405, SN 12VF013933, 830 BHP, EMR, DIESEL | H14: Diesel | I14: Detroit Diesel | J14: 8123-7405 | K14: =L14+M14*(2/3)+N14*(2/3) -> 553.33333 | N14: 830 | O14: 6300 WILSHIRE BLVD #1115 | P14: LOS ANGELES | Q14: 90048-5213 | R14: O'KEEFE KEN | S14: (323) 6555443 | T14: 8.17 | U14: 0.38
A15: 18 | B15: SC | C15: AT & T WIRELESS | D15: 366410 | E15: 2000 | F15: F31366 | G15: ICE, CUMMINS, DIESEL, MODEL KTA19-G4, TURBOCHARGED, AFTERCOOLED, EMERGENCY ELECTRICAL GENERATION, 755 BHP | H15: Diesel | I15: Cummins | J15: KTA19-G4 | K15: =L15+M15*(2/3)+N15*(2/3) -> 503.33333 | N15: 755 | O15: 301 N CRESCENT WAY | P15: ANAHEIM | Q15: 92805 | R15: WALDEN BARBARA | S15: (925) 2241488 | T15: 6.9 | U15: 0.4
A16: 19 | B16: SC | C16: AB CELLULAR HOLDING/AT&T WIRELESS | D16: 374313 | E16: 2000 | F16: F34169 | G16: ICE, CUMMINS, MODEL N14 G2, SN 12004341, DIESEL, 6 CYL, TURBOCHARGED, AFTERCOOLED, 535 BHP, EMR | H16: Diesel | I16: Cummins | J16: N14-G2 | K16: =L16+M16*(2/3)+N16*(2/3) -> 356.66667 | N16: 535 | O16: 4135 GARNER RD | P16: RIVERSIDE | Q16: 92501 | R16: WALDEN BARBARA | S16: (925) 2241488 | T16: 6.9 | U16: 0.4
A17: 20 | B17: SC | C17: AB CELLULAR HOLDING/AT&T WIRELESS | D17: 374315 | E17: 2000 | F17: F34172 | G17: ICE, CUMMINS, MODEL N14 G2, SN 12004388, DIESEL, 6 CYL, TURBOCHARGED, AFTERCOOLED, 535 BHP, EMR | H17: Diesel | I17: Cummins | J17: N14-G2 | K17: =L17+M17*(2/3)+N17*(2/3) -> 356.66667 | N17: 535 | O17: 4135 GARNER RD | P17: RIVERSIDE | Q17: 92501 | R17: WALDEN BARBARA | S17: (925) 2241488 | T17: 6.9 | U17: 0.4
A18: 21 | B18: SC | C18: AB CELLULAR HOLDING/AT&T WIRELESS | D18: 374317 | E18: 2000 | F18: F34174 | G18: ICE, CUMMINS, MODEL QSX15-G9, SN 14009139, DIESEL, 6 CYL, TURBOCHARGED, AFTERCOOLED, 765 BHP, EMR | H18: Diesel | I18: Cummins | J18: QSX15-G9 | K18: =L18+M18*(2/3)+N18*(2/3) -> 510 | N18: 765 | O18: 4135 GARNER RD | P18: RIVERSIDE | Q18: 92501 | R18: WALDEN BARBARA | S18: (925) 2241488 | T18: 6.9 | U18: 0.4
A19: 22 | B19: SC | C19: ABLESTIK LABORATORIES | D19: 379682 | E19: 2001 | F19: F37050 | G19: ICE, DETROIT DIESEL, 12 CYL, TURBOCHARGED, AFTERCOOLED, MODEL T123-7K36 (12V-4000), 2200 BHP, DIESEL, EMR | H19: Diesel | I19: Detroit Diesel | J19: T123-7K36 | K19: =L19+M19*(2/3)+N19*(2/3) -> 1466.6667 | N19: 2200 | O19: 20021 SUSANA RD | P19: RANCHO DOMINGUEZ | Q19: 90221 | R19: GEBREYESUS YARED | S19: (310) 6055764 | T19: 6.9 | U19: 0.4
A20: 32 | B20: SC | C20: ACADEMY MOTION PICTURES OF ARTS &SCIENCE | D20: 340677 | E20: 1998 | F20: F14027 | G20: ICE, CUMMINS, 6 CYL, TURBOCHARGED, AFTERCOOLED, MODEL NTA855-G3, 535 BHP, DIESEL, EMR | H20: Diesel | I20: Cummins | J20: NTA855-G3 | K20: =L20+M20*(2/3)+N20*(2/3) -> 356.66667 | N20: 535 | O20: 8949 WILSHIRE BLVD | P20: BEVERLY HILLS | Q20: 90210 | R20: EDWARDS DOUG | S20: (213) 2788990 | T20: 6.9 | U20: 0.4
A21: 33 | B21: SC | C21: AETNA LIFE INSURANCE CO . | D21: 345974 | E21: 1998 | F21: F16616 | G21: ICE, CUMMINS, 6 CYL, TURBOCHARGED, AFTERCOOLED, MODEL NTA855-G3, 535 BHP, DIESEL, EMR | H21: Diesel | I21: Cummins | J21: NTA855-G3 | K21: =L21+M21*(2/3)+N21*(2/3) -> 356.66667 | N21: 535 | O21: 251 S LAKE AVE | P21: PASADENA | Q21: 91125 | R21: ALVARADO ARMAND V | S21: (626) 7925161 | T21: 6.9 | U21: 0.4
A22: 34 | B22: SC | C22: AETNA LIFE INSURANCE COMPANY | D22: 290657 | E22: 1994 | F22: D81346 | G22: ICE, CATERPILLAR, MODEL D348PCTA, SN JO3053, 600KW, DIESEL, 12 CYL, AFTERCOOLED, EMR, | H22: Diesel | I22: Caterpillar | J22: D348 PCTA | K22: =L22+M22*(2/3)+N22*(2/3) -> 600 | L22: 600 | O22: 225 S LAKE AVE | P22: PASADENA | Q22: 91101 | R22: ALVARADO ARMAND | S22: (626) 7925161 | T22: 8.17 | U22: 0.38
A23: 35 | B23: SC | C23: AGGREKO INC | D23: 168559 | E23: 1988 | F23: D37004 | G23: ICE, CUMMINS, 6 CYL, TURBOCHARGED, AFTERCOOLED, MODEL KTTA-19-G, 620 BHP, DIESEL. | H23: Diesel | I23: Cummins | J23: KTTA19-G | K23: =L23+M23*(2/3)+N23*(2/3) -> 413.33333 | N23: 620 | O23: VARIOUS LOCATIONS IN SCAQMD | P23: SANTA FE SPRINGS | Q23: 90670-4995 | R23: ONEILL PETER | S23: (310) 8027972 | T23: 8.17 | U23: 0.38
A24: 36 | B24: SC | C24: AGGREKO INC | D24: 168560 | E24: 1988 | F24: D37005 | G24: ICE, CUMMINS, 6 CYL, TURBOCHARGED, AFTERCOOLED, MODEL KTTA-19-G, 620 BHP, DIESEL. | H24: Diesel | I24: Cummins | J24: KTTA19-G | K24: =L24+M24*(2/3)+N24*(2/3) -> 413.33333 | N24: 620 | O24: VARIOUS LOCATIONS IN SCAQMD | P24: SANTA FE SPRINGS | Q24: 90670-4995 | R24: ONEILL PETER | S24: (310) 8027972 | T24: 8.17 | U24: 0.38
A25: 37 | B25: SC | C25: AGGREKO INC | D25: 168561 | E25: 1988 | F25: D37006 | G25: ICE, CUMMINS, 6 CYL, TURBOCHARGED, AFTERCOOLED, MODEL KTTA-19-G, 620 BHP, DIESEL. | H25: Diesel | I25: Cummins | J25: KTTA19-G | K25: =L25+M25*(2/3)+N25*(2/3) -> 413.33333 | N25: 620 | O25: VARIOUS LOCATIONS IN SCAQMD | P25: SANTA FE SPRINGS | Q25: 90670-4995 | R25: ONEILL PETER | S25: (310) 8027972 | T25: 8.17 | U25: 0.38
A26: 40 | B26: SC | C26: AGGREKO INC | D26: 299501 | E26: 1995 | F26: D96673 | G26: ICE, CUMMINS, PORTABLE, MODEL P 6558, SN 37140831, DIESEL, 6 CYL, TURBOCHARGED, AFTERCOOLED, 620 BHP | H26: Diesel | I26: Cummins | J26: P 6558 | K26: =L26+M26*(2/3)+N26*(2/3) -> 413.33333 | N26: 620 | O26: VARIOUS LOCATIONS IN SCAQMD | P26: SANTA FE SPRINGS | Q26: 90670-4995 | R26: ONEILL PETER | S26: (310) 8027972 | T26: 8.17 | U26: 0.38
A27: 49 | B27: SC | C27: AGL INVESTMENTS #5 | D27: 363379 | E27: 1999 | F27: F32814 | G27: ICE, CATERPILLAR, MODEL 3412, SN 81Z06828, 724 BHP, DIESEL, 12 CYL, TURBOCHARGED, AFTERCOOLED, EMR, | H27: Diesel | I27: Caterpillar | J27: 3412 | K27: =L27+M27*(2/3)+N27*(2/3) -> 482.66667 | N27: 724 | O27: 555 ANTON BLVD | P27: COSTA MESA | Q27: 92626 | R27: HUNTER JAMES | S27: (714) 7084350 | T27: 6.9 | U27: 0.4
A28: 50 | B28: SC | C28: AGUINAGA FERTILIZER CO INC | D28: 378015 | E28: 2000 | F28: F36126 | G28: ICE, PORTABLE, CATERPILLAR, MODEL 3412E DITA, SN 4CR00600, TURBOCHARGED, AFTERCOOLED, DIESEL, 750 BHP, TUB GRINDER DRIVER | H28: Diesel | I28: Caterpillar | J28: 3412E DITA | K28: =L28+M28*(2/3)+N28*(2/3) -> 500 | N28: 750 | O28: 7992 IRVINE BLVD | P28: IRVINE | Q28: 92718 | R28: AGUINAGA ROGER | S28: (949) 7869558 | T28: 6.9 | U28: 0.4
A29: 54 | B29: SC | C29: VERIZON WIRELESS/TUSTIN MTSO | D29: 288928 | E29: 1994 | F29: D79916 | G29: ICE, CUMMINS, 6 CYL, TURBOCHARGED, AFTERCOOLED, MODEL KTA19-G2, 600 BHP, DIESEL, EMERGENCY ELECTRICAL GENERATION | H29: Diesel | I29: Cummins | J29: KTA19-G2 | K29: =L29+M29*(2/3)+N29*(2/3) -> 400 | N29: 600 | O29: 2792 WALNUT AVE | P29: TUSTIN | Q29: 92782 | R29: CARR WILLIAM | S29: (714) 6733182 | T29: 8.17 | U29: 0.38
A30: 55 | B30: SC | C30: ALCATEL INDUSTRIES | D30: 371907 | E30: 2000 | F30: F32665 | G30: ICE, CATERPILLAR, 12 CYL, TURBOCHARGED, AFTERCOOLED, MODEL 3412 DITA, 600 KW, DIESEL, EMR | H30: Diesel | I30: Caterpillar | J30: 3412 DITA | K30: =L30+M30*(2/3)+N30*(2/3) -> 600 | L30: 600 | O30: 26801 W AGOURA | P30: CALABASAS | Q30: 91301 | R30: CHRISTIE BRIAN | S30: (818) 8785123 | T30: 6.9 | U30: 0.4
A31: 56 | B31: SC | C31: ALCON SURGICAL INC | D31: 378534 | E31: 2000 | F31: F36552 | G31: ICE, CUMMINS,16 CYL, TURBOCHARGED, AFTERCOOLED, MODEL KTA50-G9, 2220 BHP, DIESEL, EMR | H31: Diesel | I31: Cummins | J31: KTA50-G9 | K31: =L31+M31*(2/3)+N31*(2/3) -> 1480 | N31: 2220 | O31: 15800 ALTON PKY | P31: IRVINE | Q31: 92718 | R31: BRUNDAGE BRANDON | S31: (949) 7536495 | T31: 6.9 | U31: 0.4
A32: 57 | B32: SC | C32: ALISO WATER MGMT AGENCY | D32: 10680A | E32: 1981 | F32: M30351 | G32: ICE, DETROIT DIESEL, TWO-CYCLE, WATER COOLED, 12 CYL, MODEL 7123 7305, 350KW, SN 12VA060486, EMR | H32: Diesel | I32: Detroit Diesel | J32: 7123-7305 | K32: =L32+M32*(2/3)+N32*(2/3) -> 350 | L32: 350 | O32: 515 FOREST AVE | P32: LAGUNA BEACH | Q32: 92653 | T32: 12 | U32: 0.53
A33: 58 | B33: SC | C33: ALL STATE INSURANCE CO | D33: 376547 | E33: 2000 | F33: F36888 | G33: ICE, CATERPILLAR, MODEL 3512BDITA, 1500 KW, DIESEL, 12 CYL, TURBOCHARGED, AFTERCOOLED, EMR | H33: Diesel | I33: Caterpillar | J33: 3512B DITA | K33: =L33+M33*(2/3)+N33*(2/3) -> 1500 | L33: 1500 | O33: 21950 E COPLEY DR | P33: DIAMOND BAR | Q33: 91765 | R33: SCOTT HELEN | S33: (909) 6126794 | T33: 6.9 | U33: 0.4
A34: 59 | B34: SC | C34: ALLEGIANCE HEALTHCARE CORPORATION | D34: 325847 | E34: 1997 | F34: F6087 | G34: ICE, CATERPILLAR, MODEL 3412TA, 749 BHP, DIESEL, 12 CYL, FOUR CYCLE, TURBOCHARGED, AFTERCOOLED, EMR, | H34: Diesel | I34: Caterpillar | J34: 3412 TA | K34: =L34+M34*(2/3)+N34*(2/3) -> 499.33333 | N34: 749 | O34: 4551 E PHILADELPHIA ST | P34: ONTARIO | Q34: 91761 | R34: VU KENNETH | S34: (909) 9743648 | T34: 6.9 | U34: 0.4
A35: 60 | B35: SC | C35: ALLEGIANCE TELECOM INC | D35: 362791 | E35: 1999 | F35: F24498 | G35: ICE, KOHLER, MODEL 750ROZD, DIESEL, TURBOCHARGED, AFTERCOOLED, 1170 BHP, EMR | H35: Diesel | I35: Kohler | J35: 750 ROZD | K35: =L35+M35*(2/3)+N35*(2/3) -> 780 | N35: 1170 | O35: 818 W 7TH ST STE 320 | P35: LOS ANGELES | Q35: 90017 | R35: CHING TED | S35: (213) 8910600 | T35: 8.17 | U35: 0.38
A36: 61 | B36: SC | C36: ALLERGAN INC UNIT #1 | D36: 263600 | E36: 1992 | F36: D60073 | G36: ICE, CATERPILLAR, MODEL 3412 DT, SN 38506732, DIESEL, EMR, 12 CYL, 545 BHP, TURBOCHARGED, AFTERCOOLED | H36: Diesel | I36: Caterpillar | J36: 3412 DT | K36: =L36+M36*(2/3)+N36*(2/3) -> 363.33333 | N36: 545 | O36: 18600 VON KARMAN | P36: IRVINE | Q36: 92715-1513 | R36: REED JON | S36: (714) 9556785 | T36: 8.17 | U36: 0.38
A37: 62 | B37: SC | C37: ALLERGAN INC UNIT #1 | D37: 263601 | E37: 1992 | F37: D60074 | G37: ICE, DETROIT DIESEL, MODEL 12V92T, SN 12VF002698, DIESEL, EMR, 8 CYL, 741 BHP, TURBOCHARGED, AFTERCOOLED | H37: Diesel | I37: Detroit Diesel | J37: 12V-92T | K37: =L37+M37*(2/3)+N37*(2/3) -> 494 | N37: 741 | O37: 18600 VON KARMAN | P37: IRVINE | Q37: 92715 | R37: REED JON | S37: (714) 9556785 | T37: 8.17 | U37: 0.38
A38: 63 | B38: SC | C38: ALPHA THERAPEUTIC CORP | D38: 292033 | E38: 1994 | F38: D82426 | G38: ICE, CUMMINS, 16 CYL, TURBOCHARGED, AFTERCOOLED, MODEL KTTA-50-G2, SN K930526551, 2220 BHP, DIESEL, EMR | H38: Diesel | I38: Cummins | J38: KTTA50-G2 | K38: =L38+M38*(2/3)+N38*(2/3) -> 1480 | N38: 2220 | O38: 5555 VALLEY BLVD | P38: LOS ANGELES | Q38: 90032-3548 | R38: ENRIQUEZ MATHILDE | S38: (213) 2277644 | T38: 8.17 | U38: 0.38
A39: 64 | B39: SC | C39: ALPHA THERAPEUTIC CORP | D39: 292034 | E39: 1994 | F39: D82427 | G39: ICE, CUMMINS, 16 CYL, TURBOCHARGED, AFTERCOOLED, MODEL KTTA50-G2, SN K930525356, 2220 BHP, DIESEL, EMR | H39: Diesel | I39: Cummins | J39: KTTA50-G2 | K39: =L39+M39*(2/3)+N39*(2/3) -> 1480 | N39: 2220 | O39: 5555 VALLEY BLVD | P39: LOS ANGELES | Q39: 90032-3548 | R39: ENRIQUEZ MATHILDE | S39: (213) 2277644 | T39: 8.17 | U39: 0.38
A40: 65 | B40: SC | C40: ALPHA THERAPEUTIC CORP | D40: 317427 | E40: 1996 | F40: F00711 | G40: ICE, CATERPILLAR,MODEL 3516 DITA, TURBOCHARGED, AFTERCOOLED, 16 CYL, 2000 KW, EMR, DIESEL | H40: Diesel | I40: Caterpillar | J40: 3516 DITA | K40: =L40+M40*(2/3)+N40*(2/3) -> 2000 | L40: 2000 | O40: 5555 VALLEY BLVD | P40: LOS ANGELES | Q40: 90032 | R40: ENRIQUEZ MATHILDE | S40: (213) 2277644 | T40: 8.17 | U40: 0.38
A41: 66 | B41: SC | C41: AMBULATORY CARE CENTER | D41: 372106 | E41: 2000 | F41: F34082 | G41: ICE, DETROIT DIESEL,MODEL 8123-7400, DIESEL, EMR,16 CYL, 1095 BHP, TURBOCHARGED, AFTERCOOLED | H41: Diesel | I41: Detroit Diesel | J41: 8123-7400 | K41: =L41+M41*(2/3)+N41*(2/3) -> 730 | N41: 1095 | O41: 25751 MC BEAN PKY | P41: VALENCIA | Q41: 91355 | R41: GRUND JACK | S41: (818) 5945800 | T41: 6.9 | U41: 0.4
A42: 67 | B42: SC | C42: AMERICAN BROADCASTING CO | D42: 128640 | E42: 1985 | F42: M44624 | G42: ENGINE NO. 3, ICE, CUMMINS, TURBOCHARGED, AFTERCOOLED, EMERGENCY ELECTRICAL GENERATION, DIESEL, MODEL VTA-1710-GS2, 12 CYL, 900 BHP | H42: Diesel | I42: Cummins | J42: VTA1710-GS2 | K42: =L42+M42*(2/3)+N42*(2/3) -> 600 | N42: 900 | O42: 4151 PROSPECT AVE | P42: LOS ANGELES | Q42: 90027 | R42: ROUTT G. | S42: (213) 5574370 | T42: 11 | U42: 0.53
A43: 68 | B43: SC | C43: AMERICAN BROADCASTING CO | D43: 128642 | E43: 1985 | F43: M44651 | G43: ENGINE NO. 2, ICE, CUMMINS, TURBOCHARGED, AFTERCOOLED, EMERGENCY ELECTRICAL GENERATION, DIESEL, MODEL VTA-1710-GS1, 12 CYL, 760 BHP | H43: Diesel | I43: Cummins | J43: VTA1710-GS1 | K43: =L43+M43*(2/3)+N43*(2/3) -> 506.66667 | N43: 760 | O43: 4151 PROSPECT AVE | P43: LOS ANGELES | Q43: 90027 | R43: ROUTT G. | S43: (213) 5574370 | T43: 11 | U43: 0.53
A44: 69 | B44: SC | C44: AMERICAN BROADCASTING CO | D44: 202288 | E44: 1989 | F44: D23738 | G44: ICE, CUMMINS, DIESEL, EMERGENCY ELECTRICAL GENERATION, MODEL VTA-1710-GS2, TURBOCHARGED, AFTERCOOLED, 12 CYL, 882 BHP | H44: Diesel | I44: Cummins | J44: VTA1710-GS2 | K44: =L44+M44*(2/3)+N44*(2/3) -> 588 | N44: 882 | O44: 4151 PROSPECT AVE | P44: LOS ANGELES | Q44: 90027 | R44: ROUTT G. | S44: (213) 5574370 | T44: 8.17 | U44: 0.38
A45: 70 | B45: SC | C45: AMERICAN CABLEVISION/MEDIAONE DBA | D45: 338165 | E45: 1998 | F45: F12959 | G45: ICE, CATERPILLAR, 6 CYL, TURBOCHARGED, AFTERCOOLED, MODEL 3406 DITA, 350 KW, SN 4ZR03510, DIESEL, EMR | H45: Diesel | I45: Caterpillar | J45: 3406 DITA | K45: =L45+M45*(2/3)+N45*(2/3) -> 350 | L45: 350 | O45: 1970 E GRAND AVE | P45: EL SEGUNDO | Q45: 90245 | R45: FELDSTEIN BARRY | S45: (310) 2163606 | T45: 6.9 | U45: 0.4
A46: 71 | B46: SC | C46: AMERICAN HONDA MOTOR CO INC | D46: 155361 | E46: 1987 | F46: M59153 | G46: ICE, MITSUBISHI, DIESEL, EMERGENCY ELECTRICAL GENERATION, MODEL S12N-PTA-2, SN 20535, 12 CYL, 1450 BHP, TURBOCHARGED, AFTERCOOLED | H46: Diesel | I46: Mitsubishi | J46: S12N-PTA2 | K46: =L46+M46*(2/3)+N46*(2/3) -> 966.66667 | N46: 1450 | O46: 700 VAN NESS AVE | P46: TORRANCE | Q46: 90501-1490 | R46: HARMON CHARLES | S46: (310) 7814011 | T46: 11 | U46: 0.53
A47: 72 | B47: SC | C47: AMERICAN HONDA MOTOR CO INC | D47: 221149 | E47: 1990 | F47: D36531 | G47: ICE, CATERPILLAR, DIESEL, MODEL 3406, 6 CYL, 518 BHP, EMR, TURBOCHARGED, AFTERCOOLED | H47: Diesel | I47: Caterpillar | J47: 3406 | K47: =L47+M47*(2/3)+N47*(2/3) -> 345.33333 | N47: 518 | O47: 700 VAN NESS AVE | P47: TORRANCE | Q47: 90501-1490 | R47: HARMON CHARLES | S47: (310) 7814011 | T47: 8.17 | U47: 0.38
A48: 73 | B48: SC | C48: AMERICAN HONDA MOTOR CO INC | D48: 229281 | E48: 1990 | F48: D28728 | G48: ICE, CATERPILLAR, DIESEL, MODEL 3512, 16 CYL, 2149 BHP, TURBOCHARGED, AFTERCOOLED, EMERGENCY ELECTRICAL GENERATION | H48: Diesel | I48: Caterpillar | J48: 3512 | K48: =L48+M48*(2/3)+N48*(2/3) -> 1432.6667 | N48: 2149 | O48: 700 VAN NESS AVE | P48: TORRANCE | Q48: 90501-1490 | R48: HARMON CHARLES | S48: (310) 7814011 | T48: 8.17 | U48: 0.38
A49: 74 | B49: SC | C49: AMERICAN PROCUREMENT & LOGISTICS CO. | D49: 335939 | E49: 1998 | F49: F11536 | G49: ICE, CUMMINS, 16 CYL, TURBOCHARGED, AFTERCOOLED, MODEL KTA50-G3, SN B970631820, 1850 BHP, DIESEL, EMR | H49: Diesel | I49: Cummins | J49: KTA50-G3 | K49: =L49+M49*(2/3)+N49*(2/3) -> 1233.3333 | N49: 1850 | O49: 777 S HARBOR BLVD | P49: LA HABRA | Q49: 90631 | R49: HUNTER TOM | S49: (714) 5269608 | T49: 8.17 | U49: 0.38
A50: 75 | B50: SC | C50: AMERICAN SAVINGS BANK DBA WASHINGTON MUT | D50: 204593 | E50: 1989 | F50: D25556 | G50: ICE, CATERPILLAR, DIESEL, EMR, MODEL 3512TA, TURBOCHARGED, AFTERCOOLED, 12 CYL, 1125 BHP, | H50: Diesel | I50: Caterpillar | J50: 3512 TA | K50: =L50+M50*(2/3)+N50*(2/3) -> 750 | N50: 1125 | O50: 4150 N PALM ST | P50: FULLERTON | Q50: 92835-1079 | R50: WALKER BRIAN | S50: (949) 8334665 | T50: 8.17 | U50: 0.38
A51: 76 | B51: SC | C51: AMERICAN SAVINGS BANK, F. A. | D51: 332715 | E51: 1997 | F51: F9605 | G51: ICE, CUMMINS, DIESEL, EMR, MODEL VTA-28-GS1/CG1, TURBOCHARGED, AFTERCOOLED, 12 CYL, 760 BHP | H51: Diesel | I51: Cummins | J51: VTA28-GS1 | K51: =L51+M51*(2/3)+N51*(2/3) -> 506.66667 | N51: 760 | O51: 17875-77 VON KARMAN AVE | P51: IRVINE | Q51: 92814 | R51: THYS JIM | S51: (714) 2527111 | T51: 8.17 | U51: 0.38
A52: 78 | B52: SC | C52: AMERIGAS PROPANE L.P. | D52: 156115 | E52: 1987 | F52: M63527 | G52: ICE, FOR REFRIGERANT COMPRESSOR K2A, NATURAL GAS FIRED (RICH BURN), 500 BHP, EQUIPPED WITH KLEENAIRE NOX CATALYTIC MODEL KNVG67H FOR NOX CONTROL, | H52: Natural Gas | I52: N/A | J52: N/A | K52: =L52+M52*(2/3)+N52*(2/3) -> 333.33333 | N52: 500 | O52: 2110 N GAFFEY ST | P52: SAN PEDRO | Q52: 90731-1251 | R52: BLASER JIM | S52: (213) 8335275
A53: 79 | B53: SC | C53: AMERIGAS PROPANE L.P. | D53: 156116 | E53: 1987 | F53: M63528 | G53: ICE, FOR REFRIGERANT COMPRESSOR K2B, NATURAL GAS FIRED (RICH BURN), 500 BHP, EQUIPPED WITH KLEENAIRE NOX CATALYTIC MODEL KNVG67H FOR NOX CONTROL, | H53: Natural Gas | I53: N/A | J53: N/A | K53: =L53+M53*(2/3)+N53*(2/3) -> 333.33333 | N53: 500 | O53: 2110 N GAFFEY ST | P53: SAN PEDRO | Q53: 90731-1251 | R53: BLASER JIM | S53: (213) 8335275
A54: 80 | B54: SC | C54: AMERIGAS PROPANE L.P. | D54: 156117 | E54: 1987 | F54: M63529 | G54: ICE, FOR REFRIGERANT COMPRESSOR K2C, NATURAL GAS FIRED (RICH BURN), 500 BHP, EQUIPPED WITH KLEENAIRE NOX CATALYTIC MODEL KNVG67H FOR NOX CONTROL, | H54: Natural Gas | I54: N/A | J54: N/A | K54: =L54+M54*(2/3)+N54*(2/3) -> 333.33333 | N54: 500 | O54: 2110 N GAFFEY ST | P54: SAN PEDRO | Q54: 90731 | R54: BLASER JIM | S54: (213) 8335275
A55: 81 | B55: SC | C55: AMERISOURCE CORPORATION | D55: 367814 | E55: 2000 | F55: F37375 | G55: ICE, CUMMINS, EMR, MODEL KTA19-G4, DIESEL, 6 CYL, TURBOCHARGED, AFTERCOOLED, 755 BHP | H55: Diesel | I55: Cummins | J55: KTA19-G4 | K55: =L55+M55*(2/3)+N55*(2/3) -> 503.33333 | N55: 755 | O55: 11010 HOPKINS ST UNIT C | P55: MIRA LOMA | Q55: 91752 | R55: DUNBAR JOHN | S55: (909) 3600257 | T55: 6.9 | U55: 0.4
A56: 82 | B56: SC | C56: AMI TARZANA REGIONAL MEDICAL CENTER | D56: 273309 | E56: 1992 | F56: D72069 | G56: ICE, DETROIT DIESEL, MODEL 8163-7405, DIESEL, EMR TURBOCHARGED, AFTERCOOLED, 16 CYL, TWO-CYCLE, 1095 BHP | H56: Diesel | I56: Detroit Diesel | J56: 8163-7405 | K56: =L56+M56*(2/3)+N56*(2/3) -> 730 | N56: 1095 | O56: 18321 CLARK ST | P56: TARZANA | Q56: 91356-3501 | R56: LAZATIN LOU | S56: (818) 8810100 | T56: 8.17 | U56: 0.38
A57: 83 | B57: SC | C57: AMISUB, IRVINE MEDICAL CTR DBA | D57: 208224 | E57: 1989 | F57: D31480 | G57: ICE, CATERPILLAR, DIESEL, EMR, MODEL 3512, TURBOCHARGED, AFTERCOOLED, 12 CYL, 1779 BHP | H57: Diesel | I57: Caterpillar | J57: 3512 | K57: =L57+M57*(2/3)+N57*(2/3) -> 1186 | N57: 1779 | O57: 16178 1/2 SAND CANYON AVE | P57: IRVINE | Q57: 92618 | R57: NGUYEN NGUYEN | S57: (949) 7542345 | T57: 8.17 | U57: 0.38
A58: 84 | B58: SC | C58: AMPHASTAR PHARMACEUTICAL, INC | D58: 353296 | E58: 1999 | F58: F20492 | G58: ICE, CATERPILLAR, DIESEL, EMR, MODEL 3406 DITA, SN 4ZR05063, TURBOCHARGED, AFTERCOOLED, 6 CYL, 400 KW | H58: Diesel | I58: Caterpillar | J58: 3406 DITA | K58: =L58+M58*(2/3)+N58*(2/3) -> 400 | L58: 400 | O58: 11570 SIXTH ST | P58: RANCHO CUCAMONGA | Q58: 91730 | R58: LIAWATIDEWI JACOB | S58: (626) 4595259 | T58: 6.9 | U58: 0.4
A59: 85 | B59: SC | C59: ANAHEIM ANGELS, L.P./EDISON INTL FIELD | D59: 337753 | E59: 1998 | F59: F12739 | G59: ICE, CATERPILLAR, DIESEL, EMR, MODEL 3412 DITA, TURBOCHARGED, AFTERCOOLED, 12 CYL, 600 KW | H59: Diesel | I59: Caterpillar | J59: 3412 DITA | K59: =L59+M59*(2/3)+N59*(2/3) -> 600 | L59: 600 | O59: 2000 GENE AUTRY WAY | P59: ANAHEIM | Q59: 92806 | R59: UNLICH KEVIN | S59: (714) 9402009 | T59: 8.17 | U59: 0.38
A60: 87 | B60: SC | C60: ANAHEIM CITY PUBLIC UTILITIES DEPT | D60: 362959 | E60: 1999 | F60: F23540 | G60: ICE, CUMMINS, EMERGENCY ELECTRICAL GENERATION, MODEL KTA50-G9, SN 33144019, DIESEL, 16 CYL, TURBOCHARGED, AFTERCOOLED, 1500 KW | H60: Diesel | I60: Cummins | J60: KTA50-G9 | K60: =L60+M60*(2/3)+N60*(2/3) -> 1500 | L60: 1500 | O60: 1411 N TUSTIN AVE | P60: ANAHEIM | Q60: 92807 | R60: PEPITO FRANK | S60: (714) 7656826 | T60: 8.17 | U60: 0.38
A61: 90 | B61: SC | C61: ANAHEIM CITY, PUBLIC UTILITIES DEPT | D61: 259246 | E61: 1991 | F61: D49300 | G61: ICE, CATERPILLAR, DIESEL, EMERGENCY ELECTRICAL GENERATION, MODEL 3412 TA, TURBOCHARGED, AFTERCOOLED, 12 CYL, 675 BHP WITH A HOUSTON INDUSTRIAL SILENCING NON-SELECTIVE CATALYTIC REDUCTION SYSTEM MODEL DN/S-2/67010H. | H61: Diesel | I61: Caterpillar | J61: 3412 TA | K61: =L61+M61*(2/3)+N61*(2/3) -> 450 | N61: 675 | O61: 6751 WALNUT CANYON RD | P61: ANAHEIM | Q61: 92807 | R61: LIEN SHARON | S61: (714) 2544279 | T61: 8.17 | U61: 0.38
A62: 91 | B62: SC | C62: ANAHEIM HOTEL PARTNERSHIP,ANAHEIM HILTON | D62: 179807 | E62: 1988 | F62: D08047 | G62: ICE, NO. 1, CUMMINS, EMERGENCY ELECTRICAL GENERATION, MODEL KTA 3067-GS, SN 33105977, DIESEL, 16 CYL, TURBOCHARGED, AFTERCOOLED, 1490 BHP | H62: Diesel | I62: Cummins | J62: KTA3067-GS | K62: =L62+M62*(2/3)+N62*(2/3) -> 993.33333 | N62: 1490 | O62: 777 CONVENTION WAY | P62: ANAHEIM | Q62: 92802 | R62: KRUBL LEIGH | S62: (714) 7404374 | T62: 8.17 | U62: 0.38
A63: 92 | B63: SC | C63: ANAHEIM HOTEL PARTNERSHIP,ANAHEIM HILTON | D63: 179808 | E63: 1988 | F63: D07538 | G63: ICE, NO. 2, CUMMINS, EMERGENCY ELECTRICAL GENERATION, MODEL KTA 3067-GS, SN 33105978, DIESEL, 16 CYL, TURBOCHARGED, AFTERCOOLED, 1490 BHP | H63: Diesel | I63: Cummins | J63: KTA3067-GS | K63: =L63+M63*(2/3)+N63*(2/3) -> 993.33333 | N63: 1490 | O63: 777 CONVENTION WAY | P63: ANAHEIM | Q63: 92802 | R63: KRUBL LEIGH | S63: (714) 7404374 | T63: 8.17 | U63: 0.38
A64: 93 | B64: SC | C64: ANAHEIM MARRIOTT HOTEL | D64: 278190 | E64: 1993 | F64: D70318 | G64: ICE, DETROIT DIESEL, MODEL 12V-71T, DIESEL, EMR, TURBOCHARGED, AFTERCOOLED, 12 CYL, 630 BHP | H64: Diesel | I64: Detroit Diesel | J64: 12V-71T | K64: =L64+M64*(2/3)+N64*(2/3) -> 420 | N64: 630 | O64: 700 W CONVENTION WAY | P64: ANAHEIM | Q64: 92802-3483 | R64: WITT BARRY | S64: (714) 7508000 | T64: 8.17 | U64: 0.38
A65: 94 | B65: SC | C65: ANAHEIM MEMORIAL HOSPITAL | D65: 175703 | E65: 1988 | F65: D34807 | G65: ICE, DETROIT DIESEL, MODEL 12V-92TAB, DIESEL, EMR, TURBOCHARGED, AFTERCOOLED, 12 CYL, 830 BHP | H65: Diesel | I65: Detroit Diesel | J65: 12V-92TAB | K65: =L65+M65*(2/3)+N65*(2/3) -> 553.33333 | N65: 830 | O65: 1111 W LA PALMA AVE | P65: ANAHEIM | Q65: 92801 | R65: RUBINO CHRIS | S65: (714) 9996145 | T65: 8.17 | U65: 0.38
A66: 95 | B66: SC | C66: ANAHEIM MEMORIAL HOSPITAL | D66: 175912 | E66: 1988 | F66: D34809 | G66: ICE, DETROIT DIESEL, MODEL 7125-7305, DIESEL, EMR, TURBOCHARGED, AFTERCOOLED, 12 CYL, 630 BHP | H66: Diesel | I66: Detroit Diesel | J66: 7125-7305 | K66: =L66+M66*(2/3)+N66*(2/3) -> 420 | N66: 630 | O66: 1111 W LA PALMA AVE | P66: ANAHEIM | Q66: 92801 | R66: RUBINO CHRIS | S66: (714) 9996145 | T66: 8.17 | U66: 0.38
A67: 96 | B67: SC | C67: ANAHEIM MEMORIAL HOSPITAL | D67: 03870A | E67: 1990 | F67: S02642 | G67: ICE, DETROIT DIESEL, MODEL 7123-7300, SN 2149, FUEL-OIL SUPPLIED, 300 KW | H67: Diesel | I67: Detroit Diesel | J67: 7123-7300 | K67: =L67+M67*(2/3)+N67*(2/3) -> 300 | L67: 300 | O67: 1111 W LA PALMA AVE | P67: ANAHEIM | Q67: 92801 | R67: RUBINO CHRIS | S67: (714) 9996144 | T67: 8.17 | U67: 0.38
A68: 99 | B68: SC | C68: APOLLO WOOD RECOVERY, INC. | D68: 370743 | E68: 2000 | F68: F32056 | G68: ICE, CATERPILLAR, DIESEL, MODEL 3412ETTA, SN 4CR01168, TURBOCHARGED, AFTERCOOLED, 12 CYL, 750 BHP, OPERATING A WOOD GRINDER | H68: Diesel | I68: Caterpillar | J68: 3412 ETTA | K68: =L68+M68*(2/3)+N68*(2/3) -> 500 | N68: 750 | O68: 8640 CHERRY AVE | P68: FONTANA | Q68: 92335 | R68: HEANEY PATRICK | S68: (909) 3562735 | T68: 6.9 | U68: 0.4
A69: 100 | B69: SC | C69: ARARAT HOME OF LOS ANGELES INC | D69: 260659 | E69: 1992 | F69: D48620 | G69: ICE, CATERPILLAR, DIESEL, EMR, MODEL 3412 DITA, TURBOCHARGED, AFTERCOOLED, 12 CYL, 672 BHP | H69: Diesel | I69: Caterpillar | J69: 3412 DITA | K69: =L69+M69*(2/3)+N69*(2/3) -> 448 | N69: 672 | O69: 15105 MISSION HILLS RD | P69: MISSION HILLS | Q69: 91345 | R69: TAYLOR ROBERT | S69: (818) 3653000 | T69: 8.17 | U69: 0.38
A70: 102 | B70: SC | C70: ARCADIA CITY, WATER DIVISION | D70: 286404 | E70: 1993 | F70: D78082 | G70: ICE, DETROIT DIESEL, MODEL 8083-7416, DIESEL, EMR, TURBOCHARGED, AFTERCOOLED, 8 CYL, TWO-CYCLE, 611 BHP | H70: Diesel | I70: Detroit Diesel | J70: 8083-7416 | K70: =L70+M70*(2/3)+N70*(2/3) -> 407.33333 | N70: 611 | O70: 67 W ORANGE GROVE AVE | P70: ARCADIA | Q70: 91006 | R70: HOLCOMB HOWARD B. | S70: (818) 3035583 | T70: 8.17 | U70: 0.38
A71: 103 | B71: SC | C71: ARDEN REALTY FINANCE PARTNERSHIP, L.P. | D71: 333717 | E71: 1997 | F71: F10309 | G71: ICE, CATERPILLAR, DIESEL, EMR, MODEL 3412 TA, SN 81203793, TURBOCHARGED, AFTERCOOLED, 12 CYL, 675 BHP | H71: Diesel | I71: Caterpillar | J71: 3412 TA | K71: =L71+M71*(2/3)+N71*(2/3) -> 450 | N71: 675 | O71: 6100 WILSHIRE BLVD | P71: LOS ANGELES | Q71: 90048 | R71: KAMMINGA CHRIS | S71: (213) 9336100 | T71: 6.9 | U71: 0.4
A72: 104 | B72: SC | C72: ARDEN REALTY INC | D72: 363054 | E72: 1999 | F72: F23607 | G72: ICE, CATERPILLAR, DIESEL, EMR, MODEL 3412 DITA, SN 81Z2423, TURBOCHARGED, AFTERCOOLED, 12 CYL, 500 KW | H72: Diesel | I72: Caterpillar | J72: 3412 DITA | K72: =L72+M72*(2/3)+N72*(2/3) -> 500 | L72: 500 | O72: 6060 CENTER DR | P72: LOS ANGELES | Q72: 90045 | R72: SONDEREGGER DAVID | S72: (310) 4175330 | T72: 6.9 | U72: 0.4
A73: 105 | B73: SC | C73: ARDEN REALTY LIMITED PARTNERSHIP | D73: 375459 | E73: 2000 | F73: F35701 | G73: ICE, CUMMINS, EMR, MODEL QST30-G5, DIESEL, 12 CYL, TURBOCHARGED, AFTERCOOLED, 1490 BHP | H73: Diesel | I73: Cummins | J73: QST30-G5 | K73: =L73+M73*(2/3)+N73*(2/3) -> 993.33333 | N73: 1490 | O73: 6080 CENTER | P73: LOS ANGELES | Q73: 90045 | R73: UY MELINDA | S73: (310) 4175330 | T73: 6.9 | U73: 0.4
A74: 106 | B74: SC | C74: ARDEN REALTY, INC | D74: 369569 | E74: 2000 | F74: F32473 | G74: ICE, CATERPILLAR, DIESEL, EMR, MODEL 3406, SN 4RG00442, TURBOCHARGED, AFTERCOOLED, 6 CYL, 518 BHP | H74: Diesel | I74: Caterpillar | J74: 3406 | K74: =L74+M74*(2/3)+N74*(2/3) -> 345.33333 | N74: 518 | O74: 9665 WILSHIRE BLVD SUITE 805 | P74: BEVERLY HILLS | Q74: 90212 | R74: DANKO ZOU D | S74: (310) 2759665 | T74: 6.9 | U74: 0.4
A75: 108 | B75: SC | C75: ARROWHEAD POND OF ANAHEIM | D75: 324294 | E75: 1996 | F75: F5291 | G75: ICE, DETROIT DIESEL, MODEL 12V-149TI, 12 CYL, TURBOCHARGED, AFTERCOOLED, DIESEL, 1550 BHP, EMR | H75: Diesel | I75: Detroit Diesel | J75: 12V-149TI | K75: =L75+M75*(2/3)+N75*(2/3) -> 1033.3333 | N75: 1550 | O75: 2695 E KATELLA AVE | P75: ANAHEIM | Q75: 92806 | R75: PERDEW GARY | S75: (714) 7042480 | T75: 8.17 | U75: 0.38
A76: 109 | B76: SC | C76: ARROWHEAD REGIONAL MEDICAL CENTER | D76: 329665 | E76: 1997 | F76: F9236 | G76: ICE, DETROIT DIESEL, MODEL 9203-7K16, SN 376930, 20 CYL, TURBOCHARGED, AFTERCOOLED, DIESEL, 2925 BHP, EMR | H76: Diesel | I76: Detroit Diesel | J76: 9203-7K16 | K76: =L76+M76*(2/3)+N76*(2/3) -> 1950 | N76: 2925 | O76: 400 N PEPPER ST | P76: COLTON | Q76: 92324 | R76: MAINEZ LARRY | S76: (909) 8726004 | T76: 8.17 | U76: 0.38
A77: 110 | B77: SC | C77: ARROWHEAD REGIONAL MEDICAL CENTER | D77: 329670 | E77: 1997 | F77: F9242 | G77: ICE, DETROIT DIESEL, MODEL 9203-7K16 (20V-149TI DDEC), SN 377137, 20 CYL, TURBOCHARGED, AFTERCOOLED, DIESEL, 2925 BHP, EMERGENCY ELECTRICAL GENERATION | H77: Diesel | I77: Detroit Diesel | J77: 9203-7K16 | K77: =L77+M77*(2/3)+N77*(2/3) -> 1950 | N77: 2925 | O77: 400 N PEPPER ST | P77: COLTON | Q77: 92324 | R77: MAINEZ LARRY | S77: (909) 8726004 | T77: 8.17 | U77: 0.38
A78: 111 | B78: SC | C78: ARROWHEAD REGIONAL MEDICAL CENTER | D78: 329672 | E78: 1997 | F78: F9241 | G78: ICE, DETROIT DIESEL, MODEL 9203-7K16 (20V-149TI DDEC), SN 376841, 20 CYL, TURBOCHARGED, AFTERCOOLED, DIESEL, 2925 BHP, EMERGENCY ELECTRICAL GENERATION | H78: Diesel | I78: Detroit Diesel | J78: 9203-7K16 | K78: =L78+M78*(2/3)+N78*(2/3) -> 1950 | N78: 2925 | O78: 400 N PEPPER ST | P78: COLTON | Q78: 92324 | R78: MAINEZ LARRY | S78: (909) 8726004 | T78: 8.17 | U78: 0.38
A79: 112 | B79: SC | C79: ARROWHEAD REGIONAL MEDICAL CENTER | D79: 329674 | E79: 1997 | F79: F9240 | G79: ICE, DETROIT DIESEL, MODEL 9203-7K16 (20V-149TI DDEC), SN 376829, 20 CYL, TURBOCHARGED, AFTERCOOLED, DIESEL, 2925 BHP, EMERGENCY ELECTRICAL GENERATION | H79: Diesel | I79: Detroit Diesel | J79: 9203-7K16 | K79: =L79+M79*(2/3)+N79*(2/3) -> 1950 | N79: 2925 | O79: 400 N PEPPER ST | P79: COLTON | Q79: 92324 | R79: MAINEZ LARRY | S79: (909) 8726004 | T79: 8.17 | U79: 0.38
A80: 113 | B80: SC | C80: ARROWHEAD REGIONAL MEDICAL CENTER | D80: 329675 | E80: 1997 | F80: F9239 | G80: ICE, DETROIT DIESEL, MODEL 9203-7K16 (20V-149TI DDEC), SN 377270, 20 CYL, TURBOCHARGED, AFTERCOOLED, DIESEL, 2925 BHP, EMERGENCY ELECTRICAL GENERATION | H80: Diesel | I80: Detroit Diesel | J80: 9203-7K16 | K80: =L80+M80*(2/3)+N80*(2/3) -> 1950 | N80: 2925 | O80: 400 N PEPPER ST | P80: COLTON | Q80: 92324 | R80: MAINEZ LARRY | S80: (909) 8726004 | T80: 8.17 | U80: 0.38
A81: 114 | B81: SC | C81: ARROWHEAD REGIONAL MEDICAL CENTER | D81: 329677 | E81: 1997 | F81: F9238 | G81: ICE, DETROIT DIESEL, MODEL 9203-7K16 (20V-149TI DDEC), SN 377269, 20 CYL, TURBOCHARGED, AFTERCOOLED, DIESEL, 2925 BHP, EMERGENCY ELECTRICAL GENERATION | H81: Diesel | I81: Detroit Diesel | J81: 9203-7K16 | K81: =L81+M81*(2/3)+N81*(2/3) -> 1950 | N81: 2925 | O81: 400 N PEPPER ST | P81: COLTON | Q81: 92324 | R81: MAINEZ LARRY | S81: (909) 8726004 | T81: 8.17 | U81: 0.38
A82: 115 | B82: SC | C82: ARROWHEAD REGIONAL MEDICAL CENTER | D82: 329678 | E82: 1997 | F82: F9237 | G82: ICE, DETROIT DIESEL, MODEL 9203-7K16 (20V-149TI DDEC), SN 376317, 20 CYL, TURBOCHARGED, AFTERCOOLED, DIESEL, 2925 BHP, EMERGENCY ELECTRICAL GENERATION | H82: Diesel | I82: Detroit Diesel | J82: 9203-7K16 | K82: =L82+M82*(2/3)+N82*(2/3) -> 1950 | N82: 2925 | O82: 400 N PEPPER ST | P82: COLTON | Q82: 92324 | R82: MAINEZ LARRY | S82: (909) 8726004 | T82: 8.17 | U82: 0.38
A83: 120 | B83: SC | C83: AT & T COMM INC (SAN BERNARDINO) | D83: 174856 | E83: 1988 | F83: D12714 | G83: ICE, CATERPILLAR, DIESEL, EMR, MODEL 3508, TURBOCHARGED, AFTERCOOLED, 8 CYL, 900 KW | H83: Diesel | I83: Caterpillar | J83: 3508 | K83: =L83+M83*(2/3)+N83*(2/3) -> 900 | L83: 900 | O83: 455 2ND ST | P83: SAN BERNARDINO | Q83: 92401 | R83: WHYTE S | S83: (714) 8891989 | T83: 8.17 | U83: 0.38
A84: 121 | B84: SC | C84: AT & T COMM INC (SAN BERNARDINO) | D84: 174857 | E84: 1988 | F84: D12715 | G84: ICE, CATERPILLAR, DIESEL, EMR, MODEL 3508, 1336 BHP, TURBOCHARGED, AFTERCOOLED, 8 CYL, 900 KW | H84: Diesel | I84: Caterpillar | J84: 3508 | K84: =L84+M84*(2/3)+N84*(2/3) -> 900 | L84: 900 | O84: 455 2ND ST | P84: SAN BERNARDINO | Q84: 92401 | R84: WHYTE S | S84: (714) 8891989 | T84: 8.17 | U84: 0.38
A85: 122 | B85: SC | C85: AT & T COMM INC (SAN BERNARDINO) | D85: 174858 | E85: 1988 | F85: D12716 | G85: ICE, CATERPILLAR, DIESEL, EMR, MODEL 3508, 1336 BHP, TURBOCHARGED, AFTERCOOLED, 8 CYL, 900 KW | H85: Diesel | I85: Caterpillar | J85: 3508 | K85: =L85+M85*(2/3)+N85*(2/3) -> 900 | L85: 900 | O85: 455 2ND ST | P85: SAN BERNARDINO | Q85: 92401 | R85: WHYTE S | S85: (714) 8891989 | T85: 8.17 | U85: 0.38
A86: 123 | B86: SC | C86: AT & T COMM INC (SAN BERNARDINO) | D86: 174859 | E86: 1988 | F86: D12717 | G86: ICE, CATERPILLAR, DIESEL, EMR, MODEL 3508, 1336 BHP, TURBOCHARGED, AFTERCOOLED, 8 CYL, 900 KW | H86: Diesel | I86: Caterpillar | J86: 3508 | K86: =L86+M86*(2/3)+N86*(2/3) -> 900 | L86: 900 | O86: 455 2ND ST | P86: SAN BERNARDINO | Q86: 92401 | R86: WHYTE S | S86: (714) 8891989 | T86: 8.17 | U86: 0.38
A87: 124 | B87: SC | C87: AT & T WIRELESS | D87: 363510 | E87: 1999 | F87: F23772 | G87: ICE, CUMMINS, 6 CYL, TURBOCHARGED, AFTERCOOLED, MODEL KTA19-G4, DIESEL,EMR,755 BHP | H87: Diesel | I87: Cummins | J87: KTA19-G4 | K87: =L87+M87*(2/3)+N87*(2/3) -> 503.33333 | N87: 755 | O87: 15215 S BROADWAY | P87: GARDENA | Q87: 90247 | R87: CONNORS RAY | S87: (562) 9240000 | T87: 8.17 | U87: 0.38
A88: 125 | B88: SC | C88: AT & T WIRELESS SERVICES | D88: 363513 | E88: 1999 | F88: F23773 | G88: ICE, CUMMINS, 12 CYL, TURBOCHARGED, AFTERCOOLED, MODEL QST30-G1, DIESEL, EMR, 750 KW | H88: Diesel | I88: Cummins | J88: QST30-G1 | K88: =L88+M88*(2/3)+N88*(2/3) -> 750 | L88: 750 | O88: 6045 E SLAUSON | P88: COMMERCE | Q88: 90040 | R88: ROSE JIM | S88: (949) 2536024 | T88: 8.17 | U88: 0.38
A89: 126 | B89: SC | C89: AT&T COMM (EL MONTE) | D89: 316368 | E89: 1996 | F89: D99784 | G89: ICE, CATERPILLAR, DIESEL, EMR, MODEL 3512 DITA, SN 24Z06975, TURBOCHARGED, AFTERCOOLED, 12 CYL, 1250 KW | H89: Diesel | I89: Caterpillar | J89: 3512 DITA | K89: =L89+M89*(2/3)+N89*(2/3) -> 1250 | L89: 1250 | O89: 3640 EL MONTE AVE | P89: EL MONTE | Q89: 91105 | R89: MORRIS J M | S89: (213) 0000000 | T89: 8.17 | U89: 0.38
A90: 127 | B90: SC | C90: AT&T COMM (MISSION VIEJO) | D90: 371398 | E90: 2000 | F90: F32382 | G90: ICE, CATERPILLAR, DIESEL, EMR, MODEL 3412 DITA, SN 8RM00536, TURBOCHARGED, AFTERCOOLED, 12 CYL, 1250 KW | H90: Diesel | I90: Caterpillar | J90: 3412 DITA | K90: =L90+M90*(2/3)+N90*(2/3) -> 1250 | L90: 1250 | O90: 28302 MARGUERITE PKY | P90: MISSION VIEJO | Q90: 92692-3706 | R90: MOORE ADRIEN | S90: (714) 5208750 | T90: 6.9 | U90: 0.4
A91: 128 | B91: SC | C91: AT&T COMM (MISSION VIEJO) | D91: 371829 | E91: 2000 | F91: F32854 | G91: ICE, CATERPILLAR, DIESEL, EMR, MODEL 3512B DITA, SN 8RM00537, TURBOCHARGED, AFTERCOOLED, 12 CYL, 1250 KW | H91: Diesel | I91: Caterpillar | J91: 3512B DITA | K91: =L91+M91*(2/3)+N91*(2/3) -> 1250 | L91: 1250 | O91: 28302 MARGUERITE PKY | P91: MISSION VIEJO | Q91: 92692-3706 | R91: MOORE ADRIEN | S91: (714) 5208750 | T91: 6.9 | U91: 0.4
A92: 129 | B92: SC | C92: AT&T COMMUNICATIONS | D92: 230432 | E92: 1990 | F92: D31660 | G92: ICE, CATERPILLAR, DIESEL, MODEL D349, TURBOCHARGED, AFTERCOOLED, 16 CYL, 1100 BHP | H92: Diesel | I92: Caterpillar | J92: D349 | K92: =L92+M92*(2/3)+N92*(2/3) -> 733.33333 | N92: 1100 | O92: 1700 S BARDMAN AVE | P92: MALIBU | Q92: 90265 | R92: DOWNING ROBERT W | S92: (818) 9064771 | T92: 8.17 | U92: 0.38
A93: 132 | B93: SC | C93: AT&T CORP | D93: 371223 | E93: 2000 | F93: F34128 | G93: ICE, CATERPILLAR, DIESEL, EMR, MODEL 3512B-DITA, TURBOCHARGED, AFTERCOOLED, 12 CYL, 1807 BHP | H93: Diesel | I93: Caterpillar | J93: 3512B DITA | K93: =L93+M93*(2/3)+N93*(2/3) -> 1204.6667 | N93: 1807 | O93: 3640 EL MONTE AVE | P93: EL MONTE | Q93: 91731-2526 | R93: PLEASANT CAROL PLEASANT | S93: (213) 2368269 | T93: 6.9 | U93: 0.4
A94: 133 | B94: SC | C94: AUTOMATIC DATA PROCESSING, INC. | D94: 233916 | E94: 1990 | F94: D34587 | G94: ICE, CATERPILLAR, DIESEL, EMR, MODEL 3512, SN 3YF00476, TURBOCHARGED, AFTERCOOLED, 12 CYL, 2168 BHP | H94: Diesel | I94: Caterpillar | J94: 3512 | K94: =L94+M94*(2/3)+N94*(2/3) -> 1445.3333 | N94: 2168 | O94: 400 COVINA BLVD | P94: SAN DIMAS | Q94: 91773 | R94: SPEK KAREN | S94: (909) 5926411 | T94: 8.17 | U94: 0.38
A95: 136 | B95: SC | C95: B BRAUN MEDICAL, INC | D95: 345032 | E95: 1998 | F95: F22118 | G95: ICE, CUMMINS, DIESEL, EMR, MODEL KTTA19-G2, TURBOCHARGER, AFTERCOOLER, 750 BHP | H95: Diesel | I95: Cummins | J95: KTTA19-G2 | K95: =L95+M95*(2/3)+N95*(2/3) -> 500 | N95: 750 | O95: 2525 MCGAW AVE | P95: IRVINE | Q95: 91614-5895 | R95: SENKOVICH VLADO | S95: (949) 6602082 | T95: 6.9 | U95: 0.4
A96: 137 | B96: SC | C96: BANK OF AMERICA | D96: 343601 | E96: 1998 | F96: F19751 | G96: ICE, CATERPILLAR, DIESEL, EMR, MODEL 3412, SN 81Z16934, TURBOCHARGED, AFTERCOOLED, 12 CYL, 890 BHP | H96: Diesel | I96: Caterpillar | J96: 3412 | K96: =L96+M96*(2/3)+N96*(2/3) -> 593.33333 | N96: 890 | O96: 333 S BEAUDRY AVE W1 1 | P96: LOS ANGELES | Q96: 90017-1466 | R96: CORDERO ENSWINS | S96: (213) 3459388 | T96: 8.17 | U96: 0.38
A97: 138 | B97: SC | C97: BANK OF AMERICA | D97: 343602 | E97: 1998 | F97: F19752 | G97: ICE, CATERPILLAR, DIESEL, EMR, MODEL 3412, SN 6FA03383, TURBOCHARGED, AFTERCOOLED, 12 CYL, 890 BHP | H97: Diesel | I97: Caterpillar | J97: 3412 | K97: =L97+M97*(2/3)+N97*(2/3) -> 593.33333 | N97: 890 | O97: 333 S BEAUDRY AVE W1 1 | P97: LOS ANGELES | Q97: 90017 | R97: CORDERO ENSWINS | S97: (213) 3459388 | T97: 8.17 | U97: 0.38
A98: 139 | B98: SC | C98: BANK OF AMERICA | D98: 343603 | E98: 1998 | F98: F19753 | G98: ICE, CUMMINS, DIESEL, EMR, MODEL KTA 3067-GS, SN 33106, TURBOCHARGER, AFTERCOOLER, 1490 BHP, 16 CYL | H98: Diesel | I98: Cummins | J98: KTA3067-GS | K98: =L98+M98*(2/3)+N98*(2/3) -> 993.33333 | N98: 1490 | O98: 333 S BEAUDRY AVE W1 1 | P98: LOS ANGELES | Q98: 90017 | R98: CORDERO ENSWINS | S98: (213) 3459388 | T98: 8.17 | U98: 0.38
A99: 140 | B99: SC | C99: BANK OF AMERICA NT &SA | D99: 166329 | E99: 1988 | F99: D01430 | G99: ICE, DETROIT DIESEL, EMR, DIESEL, MODEL 4163-7305, SN 16E0006011, TURBOCHARGED, 12 CYL, 1350 BHP | H99: Diesel | I99: Detroit Diesel | J99: 4163-7305 | K99: =L99+M99*(2/3)+N99*(2/3) -> 900 | N99: 1350 | O99: 611 N BRAND BLVD | P99: GLENDALE | Q99: 91203 | R99: LUCEY R.A. | S99: (818) 5072455 | T99: 8.17 | U99: 0.38
A100: 141 | B100: SC | C100: BANK OF AMERICA NT &SA | D100: 166330 | E100: 1988 | F100: D01431 | G100: ICE, DETROIT DIESEL, EMR, DIESEL, MODEL 9163-7306, SN 16E0000342, TURBOCHARGED, 12 CYL, 1350 BHP | H100: Diesel | I100: Detroit Diesel | J100: 9163-7306 | K100: =L100+M100*(2/3)+N100*(2/3) -> 900 | N100: 1350 | O100: 611 N BRAND BLVD | P100: GLENDALE | Q100: 91203 | R100: LUCEY R.A. | S100: (818) 5072455 | T100: 8.17 | U100: 0.38
...
