Workbook

Sheet Summary Sheet
B1: Financial Reporting Reconciliation Worksheet | G1: SUMMARY
B4: Account Number
B5: Award Number
B6: Budget/Period End Date
B7: Indirect Cost Rate for Account | G7: 0.25
B10: NOTES FOR WORKSHEET COMPLETION:
B11: Please fill in the required shaded areas.
B13: Please place a Y in the column noted "IDC Y or N" for each transaction that indirect
B14: cost should be calculated on. The "Indirect Amount" column will then automatically
B15: calculate based on the rate entered above.
B17: Total Award: | H17: 0
B19: Total Expended on monthly statement as of budget/project end date | H19: 0
B21: Balance remaining on monthly statement as of budget/project end date: | H21: =H17-H19 -> 0
B23: Less:
B25: Total amount of charge adjustments from page 2 of this worksheet: | H25: ='Charge Adjustment Detail'!H30 -> 0
B26: **Include current system and other charge adjustments***
B28: Plus:
B30: Total amount of credit adjustments from page 3 of this worksheet: | H30: ='Credit Adjustment Detail'!H30 -> 0
B32: BALANCE TO BE REPORTED TO AGENCY: | H32: =-H25+H30 -> 0
C35: I, | E35: attest that the expenditures referenced in this
D36: Signature of Administrator
D37: Final Reconciliation Worksheet, are appropriate expenditures for the
D38: award number referenced above.

Sheet Charge Adjustment Detail
B1: Financial Reporting Reconciliation Worksheet | G1: CHARGE DETAIL
E3: Charge | F3: IDC | H3: Total Amount
B4: Object | E4: Adjustment | F4: Y or | G4: Indirect | H4: of Charge
B5: Code | D5: Description | F5: N | G5: Amount | H5: Adjustment
E6: 0 | F6: y | G6: =IF(F6="Y",E6*'Summary Sheet'!G7,0) -> 0 | H6: =E6+G6 -> 0
E7: 0 | F7: y | G7: =IF(F7="Y",E7*'Summary Sheet'!G7,0) -> 0 | H7: =E7+G7 -> 0
E8: 0 | F8: y | G8: =IF(F8="Y",E8*'Summary Sheet'!G7,0) -> 0 | H8: =E8+G8 -> 0
E9: 0 | F9: y | G9: =IF(F9="Y",E9*'Summary Sheet'!G7,0) -> 0 | H9: =E9+G9 -> 0
E10: 0 | F10: y | G10: =IF(F10="Y",E10*'Summary Sheet'!G7,0) -> 0 | H10: =E10+G10 -> 0
E11: 0 | F11: y | G11: =IF(F11="Y",E11*'Summary Sheet'!G7,0) -> 0 | H11: =E11+G11 -> 0
E12: 0 | F12: y | G12: =IF(F12="Y",E12*'Summary Sheet'!G7,0) -> 0 | H12: =E12+G12 -> 0
E13: 0 | F13: y | G13: =IF(F13="Y",E13*'Summary Sheet'!G7,0) -> 0 | H13: =E13+G13 -> 0
G14: =IF(F14="Y",E14*'Summary Sheet'!G7,0) -> 0 | H14: =E14+G14 -> 0
G15: =IF(F15="Y",E15*'Summary Sheet'!G7,0) -> 0 | H15: =E15+G15 -> 0
G16: =IF(F16="Y",E16*'Summary Sheet'!G7,0) -> 0 | H16: =E16+G16 -> 0
G17: =IF(F17="Y",E17*'Summary Sheet'!G7,0) -> 0 | H17: =E17+G17 -> 0
G18: =IF(F18="Y",E18*'Summary Sheet'!G7,0) -> 0 | H18: =E18+G18 -> 0
G19: =IF(F19="Y",E19*'Summary Sheet'!G7,0) -> 0 | H19: =E19+G19 -> 0
G20: =IF(F20="Y",E20*'Summary Sheet'!G7,0) -> 0 | H20: =E20+G20 -> 0
G21: =IF(F21="Y",E21*'Summary Sheet'!G7,0) -> 0 | H21: =E21+G21 -> 0
G22: =IF(F22="Y",E22*'Summary Sheet'!G7,0) -> 0 | H22: =E22+G22 -> 0
G23: =IF(F23="Y",E23*'Summary Sheet'!G7,0) -> 0 | H23: =E23+G23 -> 0
G24: =IF(F24="Y",E24*'Summary Sheet'!G7,0) -> 0 | H24: =E24+G24 -> 0
G25: =IF(F25="Y",E25*'Summary Sheet'!G7,0) -> 0 | H25: =E25+G25 -> 0
G26: =IF(F26="Y",E26*'Summary Sheet'!G7,0) -> 0 | H26: =E26+G26 -> 0
G27: =IF(F27="Y",E27*'Summary Sheet'!G7,0) -> 0 | H27: =E27+G27 -> 0
G28: =IF(F28="Y",E28*'Summary Sheet'!G7,0) -> 0 | H28: =E28+G28 -> 0
D30: TOTALS | E30: =SUM(E6:E28) -> 0 | G30: =SUM(G6:G28) -> 0 | H30: =SUM(H6:H28) -> 0

Sheet Credit Adjustment Detail
B1: Financial Reporting Reconciliation Worksheet | G1: CREDIT DETAIL
E3: Credit | F3: IDC | H3: Total Amount
B4: Object | E4: Adjustment | F4: Y or | G4: Indirect | H4: of Credit
B5: Code | D5: Description | E5: Amount | F5: N | G5: Amount | H5: Adjustment
E6: 0 | G6: =IF(F6="Y",E6*'Summary Sheet'!G7,0) -> 0 | H6: =E6+G6 -> 0
E7: 0 | G7: =IF(F7="Y",E7*'Summary Sheet'!G7,0) -> 0 | H7: =E7+G7 -> 0
E8: =(+E6+E7)*0.28 -> 0 | G8: =IF(F8="Y",E8*'Summary Sheet'!G7,0) -> 0 | H8: =E8+G8 -> 0
E9: 0 | G9: =IF(F9="Y",E9*'Summary Sheet'!G7,0) -> 0 | H9: =E9+G9 -> 0
E10: 0 | G10: =IF(F10="Y",E10*'Summary Sheet'!G7,0) -> 0 | H10: =E10+G10 -> 0
E11: 0 | G11: =IF(F11="Y",E11*'Summary Sheet'!G7,0) -> 0 | H11: =E11+G11 -> 0
E12: 0 | G12: =IF(F12="Y",E12*'Summary Sheet'!G7,0) -> 0 | H12: =E12+G12 -> 0
E13: 0 | G13: =IF(F13="Y",E13*'Summary Sheet'!G7,0) -> 0 | H13: =E13+G13 -> 0
E14: 0 | G14: =IF(F14="Y",E14*'Summary Sheet'!G7,0) -> 0 | H14: =E14+G14 -> 0
E15: 0 | G15: =IF(F15="Y",E15*'Summary Sheet'!G7,0) -> 0 | H15: =E15+G15 -> 0
E16: 0 | G16: =IF(F16="Y",E16*'Summary Sheet'!G7,0) -> 0 | H16: =E16+G16 -> 0
E17: 0 | G17: =IF(F17="Y",E17*'Summary Sheet'!G7,0) -> 0 | H17: =E17+G17 -> 0
E18: 0 | G18: =IF(F18="Y",E18*'Summary Sheet'!G7,0) -> 0 | H18: =E18+G18 -> 0
E19: 0 | G19: =IF(F19="Y",E19*'Summary Sheet'!G7,0) -> 0 | H19: =E19+G19 -> 0
E20: 0 | G20: =IF(F20="Y",E20*'Summary Sheet'!G7,0) -> 0 | H20: =E20+G20 -> 0
E21: 0 | G21: =IF(F21="Y",E21*'Summary Sheet'!G7,0) -> 0 | H21: =E21+G21 -> 0
E22: 0 | G22: =IF(F22="Y",E22*'Summary Sheet'!G7,0) -> 0 | H22: =E22+G22 -> 0
E23: 0 | G23: =IF(F23="Y",E23*'Summary Sheet'!G7,0) -> 0 | H23: =E23+G23 -> 0
E24: 0 | G24: =IF(F24="Y",E24*'Summary Sheet'!G7,0) -> 0 | H24: =E24+G24 -> 0
E25: 0 | G25: =IF(F25="Y",E25*'Summary Sheet'!G7,0) -> 0 | H25: =E25+G25 -> 0
E26: 0 | G26: =IF(F26="Y",E26*'Summary Sheet'!G7,0) -> 0 | H26: =E26+G26 -> 0
E27: 0 | G27: =IF(F27="Y",E27*'Summary Sheet'!G7,0) -> 0 | H27: =E27+G27 -> 0
E28: 0 | G28: =IF(F28="Y",E28*'Summary Sheet'!G7,0) -> 0 | H28: =E28+G28 -> 0
D30: TOTALS | E30: =SUM(E6:E29) -> 0 | G30: =SUM(G6:G28) -> 0 | H30: =SUM(H6:H28) -> 0
