Workbook
Name Maturity: 'Financial Model'!$D$153:$E$162
Name Maturity: #REF!
Name MaturitySchedule: 'Financial Model'!$D$153:$D$162
Name MaturitySchedule: #REF!
Name Retention: 'Financial Model'!$D$153:$F$162
Name Retention: #REF!
Name Statement_Date: #REF!

Sheet Begin Model

Sheet Model Assumptions
A1: Exhibit 1 Model Assumptions
A3: ASSUMPTIONS | B3: Lo | C3: Med | D3: Hi
A4: Duration of average loan (years) | B4: 0.5 | C4: 1.5 | D4: 2
A5: Amount of average loan | B5: 5 | C5: 10 | D5: 30
A6: Interest rate of average loan (excluding inflation) | B6: 0.35 | C6: 0.485 | D6: 0.65
A7: Default rate | B7: 0.05 | C7: 0.1 | D7: 0.15
A8: Required deposits by borrowers | B8: 0.05 | C8: 0.1 | D8: 0.2
A9: Loan advisors per office | B9: 2 | C9: 6 | D9: 7
A10: Loan advisor annual salary | B10: 12 | C10: 15 | D10: 20
A11: Growth Rate | B11: 0.05 | C11: 0.1 | D11: 0.15
A12: Tax Rate | B12: 0.05 | C12: 0.15 | D12: 0.3
A13: Discount Rate | B13: 0.15 | C13: 0.296 | D13: 0.35
A14: Growth in Terminal Value | B14: 0 | C14: 0.05 | D14: 0.1
A15: Application fee | B15: 15 | C15: 35 | D15: 50
... A33: Accounts payable (% SGA & Operating Expense) | B33: 0.04 | C33: 0.05 | D33: 0.06
A34: Interest on Debt from Ukrainian Investor | C34: 0
A36: Equipment | B36: Life | C36: Cost
A37: Computer (1 per staff member) | B37: 5 | C37: 1.5
A38: Office fixtures ($50,000 per branch) | B38: same | C38: 25
A39: Photocopier (1 per branch) | B39: same | C39: 10
A40: Automobile (1 per branch) | B40: 5 | C40: 5

Sheet Financial Model
A1: Exhibit 2 Financial Model
A3: NEWBANK PRO FORMA FINANCIAL INFORMATION
A4: (All dollar figures stated in '000USD 2001)
D6: 2001 | E6: 2002 | F6: 2003 | G6: 2004 | H6: 2005 | I6: 2006 | J6: 2007 | K6: 2008 | L6: 2009 | M6: 2010
D7: 1 | E7: 2 | F7: 3 | G7: 4 | H7: 5 | I7: 6 | J7: 7 | K7: 8 | L7: 9 | M7: 10
A9: LOAN PORTFOLIO DETAILS
B10: Beginning portfolio value | D10: 0 | E10: =D14 -> 1000 | F10: =E14 -> 3000 | G10: =F14 -> 5500 | H10: =G14 -> 9625 | I10: =H14 -> 13781.25 | J10: =I14 -> 17226.562 | K10: =J14 -> 20097.656 | L10: =K14 -> 22107.422 | M10: =L14 -> 24318.164
B11: Loans issued during period | D11: 1000 | E11: =D11*(1+E12) -> 2000 | F11: =E11*(1+F12) -> 3500 | G11: =F11*(1+G12) -> 6125 | H11: =G11*(1+H12) -> 7656.25 | I11: =H11*(1+I12) -> 9570.3125 | J11: =I11*(1+J12) -> 10527.344 | K11: =J11*(1+K12) -> 11580.078 | L11: =K11*(1+L12) -> 12738.086 | M11: =L11*(1+M12) -> 14011.895
B12: Growth in total value of loans issued | E12: 1 | F12: 0.75 | G12: 0.75 | H12: 0.25 | I12: 0.25 | J12: 0.1 | K12: 0.1 | L12: 0.1 | M12: 0.1
B13: Loans matured during period | D13: =-IF(ISERROR(VLOOKUP(D7,Maturity,2)),0,VLOOKUP(D7,Maturity,2)) -> 0 | E13: =-IF(ISERROR(VLOOKUP(E7,Maturity,2)),0,VLOOKUP(E7,Maturity,2)) -> 0 | F13: =-IF(ISERROR(VLOOKUP(F7,Maturity,2)),0,VLOOKUP(F7,Maturity,2)) -> -1000 | G13: =-IF(ISERROR(VLOOKUP(G7,Maturity,2)),0,VLOOKUP(G7,Maturity,2)) -> -2000 | H13: =-IF(ISERROR(VLOOKUP(H7,Maturity,2)),0,VLOOKUP(H7,Maturity,2)) -> -3500 | I13: =-IF(ISERROR(VLOOKUP(I7,Maturity,2)),0,VLOOKUP(I7,Maturity,2)) -> -6125 | J13: =-IF(ISERROR(VLOOKUP(J7,Maturity,2)),0,VLOOKUP(J7,Maturity,2)) -> -7656.25 | K13: =-IF(ISERROR(VLOOKUP(K7,Maturity,2)),0,VLOOKUP(K7,Maturity,2)) -> -9570.3125 | ... M13: =-IF(ISERROR(VLOOKUP(M7,Maturity,2)),0,VLOOKUP(M7,Maturity,2)) -> -11580.078
B14: End-of-year portfolio value | D14: =D10+D11 -> 1000 | E14: =E10+E11 -> 3000 | F14: =F10+F11+F13 -> 5500 | G14: =G10+G11+G13 -> 9625 | H14: =H10+H11+H13 -> 13781.25 | I14: =I10+I11+I13 -> 17226.562 | J14: =J10+J11+J13 -> 20097.656 | K14: =K10+K11+K13 -> 22107.422 | L14: =L10+L11+L13 -> 24318.164 | M14: =M10+M11+M13 -> 26749.98
B15: Average loan portfolio value | D15: =(D10+D14)/2 -> 500 | E15: =(E10+E14)/2 -> 2000 | F15: =(F10+F14)/2 -> 4250 | G15: =(G10+G14)/2 -> 7562.5 | H15: =(H10+H14)/2 -> 11703.125 | I15: =(I10+I14)/2 -> 15503.906 | J15: =(J10+J14)/2 -> 18662.109 | K15: =(K10+K14)/2 -> 21102.539 | ... M15: =(M10+M14)/2 -> 25534.072
A18: BORROWER DETAILS
B19: Creditors with loans outstanding from prior period | D19: 0 | E19: =D24 -> 100 | F19: =E24 -> 200 | G19: =F24 -> 350 | H19: =G24 -> 612.5 | I19: =H24 -> 765.625 | J19: =I24 -> 957.03125 | K19: =J24 -> 1052.7344 | L19: =K24 -> 1158.0078 | M19: =L24 -> 1273.8086
B20: Returning creditors (2nd or 3rd loan) | D20: ='Model Assumptions'!$C$29*-1*'Financial Model'!C23 -> 0 | E20: ='Model Assumptions'!$C$29*-1*'Financial Model'!D23 -> 0 | F20: ='Model Assumptions'!$C$29*-1*'Financial Model'!E23 -> 0 | G20: ='Model Assumptions'!$C$29*-1*'Financial Model'!F23 -> 50 | H20: ='Model Assumptions'!$C$29*-1*'Financial Model'!G23 -> 100 | I20: ='Model Assumptions'!$C$29*-1*'Financial Model'!H23 -> 175 | J20: ='Model Assumptions'!$C$29*-1*'Financial Model'!I23 -> 306.25 | K20: ='Model Assumptions'!$C$29*-1*'Financial Model'!J23 -> 382.8125 | ... M20: ='Model Assumptions'!$C$29*-1*'Financial Model'!L23 -> 526.36719
B21: First-time creditors added during period | D21: =D24-C24-D23-D20 -> 100 | E21: =E24-D24-E23-E20 -> 100 | F21: =F24-E24-F23-F20 -> 250 | G21: =G24-F24-G23-G20 -> 412.5 | H21: =H24-G24-H23-H20 -> 403.125 | I21: =I24-H24-I23-I20 -> 628.90625 | J21: =J24-I24-J23-J20 -> 555.07812 | K21: =K24-J24-K23-K20 -> 679.49219 | ... M21: =M24-L24-M23-M20 -> 759.02148
B22: Creditors defaulting during period
B23: Creditors with loans maturing during period | D23: =-1*IF(ISERROR(VLOOKUP(D7,Retention,3)),0,VLOOKUP(D7,Retention,3)) -> 0 | E23: =-1*IF(ISERROR(VLOOKUP(E7,Retention,3)),0,VLOOKUP(E7,Retention,3)) -> 0 | F23: =-1*IF(ISERROR(VLOOKUP(F7,Retention,3)),0,VLOOKUP(F7,Retention,3)) -> -100 | G23: =-1*IF(ISERROR(VLOOKUP(G7,Retention,3)),0,VLOOKUP(G7,Retention,3)) -> -200 | H23: =-1*IF(ISERROR(VLOOKUP(H7,Retention,3)),0,VLOOKUP(H7,Retention,3)) -> -350 | I23: =-1*IF(ISERROR(VLOOKUP(I7,Retention,3)),0,VLOOKUP(I7,Retention,3)) -> -612.5 | J23: =-1*IF(ISERROR(VLOOKUP(J7,Retention,3)),0,VLOOKUP(J7,Retention,3)) -> -765.625 | K23: =-1*IF(ISERROR(VLOOKUP(K7,Retention,3)),0,VLOOKUP(K7,Retention,3)) -> -957.03125 | ... M23: =-1*IF(ISERROR(VLOOKUP(M7,Retention,3)),0,VLOOKUP(M7,Retention,3)) -> -1158.0078
B24: Total current borrowers | D24: =D11/'Model Assumptions'!$C$5 -> 100 | E24: =E11/'Model Assumptions'!$C$5 -> 200 | F24: =F11/'Model Assumptions'!$C$5 -> 350 | G24: =G11/'Model Assumptions'!$C$5 -> 612.5 | H24: =H11/'Model Assumptions'!$C$5 -> 765.625 | I24: =I11/'Model Assumptions'!$C$5 -> 957.03125 | J24: =J11/'Model Assumptions'!$C$5 -> 1052.7344 | K24: =K11/'Model Assumptions'!$C$5 -> 1158.0078 | ... M24: =M11/'Model Assumptions'!$C$5 -> 1401.1895
A26: OPERATIONAL DETAILS
B27: Number of Branches | D27: 1 | E27: 3 | F27: 4 | G27: 7 | H27: 10 | I27: 13 | J27: 15 | K27: 17 | L27: 20 | M27: 24
B28: Staffing
B29: Senior Executives | D29: ='Model Assumptions'!$C$22 -> 1 | E29: ='Model Assumptions'!$C$22 -> 1 | F29: ='Model Assumptions'!$C$22 -> 1 | G29: ='Model Assumptions'!$C$22 -> 1 | H29: ='Model Assumptions'!$C$22 -> 1 | I29: ='Model Assumptions'!$C$22 -> 1 | J29: ='Model Assumptions'!$C$22 -> 1 | K29: ='Model Assumptions'!$C$22 -> 1 | ... M29: ='Model Assumptions'!$C$22 -> 1
B30: Branch Directors | D30: ='Model Assumptions'!$C$20*D27 -> 1 | E30: ='Model Assumptions'!$C$20*E27 -> 3 | F30: ='Model Assumptions'!$C$20*F27 -> 4 | G30: ='Model Assumptions'!$C$20*G27 -> 7 | H30: ='Model Assumptions'!$C$20*H27 -> 10 | I30: ='Model Assumptions'!$C$20*I27 -> 13 | J30: ='Model Assumptions'!$C$20*J27 -> 15 | K30: ='Model Assumptions'!$C$20*K27 -> 17 | ... M30: ='Model Assumptions'!$C$20*M27 -> 24
B31: Loan Advisors | D31: 4 | E31: =E27*'Model Assumptions'!$C$9 -> 18 | F31: =F27*'Model Assumptions'!$C$9 -> 24 | G31: =G27*'Model Assumptions'!$C$9 -> 42 | H31: =H27*'Model Assumptions'!$C$9 -> 60 | I31: =I27*'Model Assumptions'!$C$9 -> 78 | J31: =J27*'Model Assumptions'!$C$9 -> 90 | K31: =K27*'Model Assumptions'!$C$9 -> 102 | L31: =L27*'Model Assumptions'!$C$9 -> 120 | M31: =M27*'Model Assumptions'!$C$9 -> 144
B32: Loan advisor turnover | D32: =ROUNDDOWN(D31*'Model Assumptions'!$C$24,0) -> 0 | E32: =ROUNDDOWN(E31*'Model Assumptions'!$C$24,0) -> 2 | F32: =ROUNDDOWN(F31*'Model Assumptions'!$C$24,0) -> 3 | G32: =ROUNDDOWN(G31*'Model Assumptions'!$C$24,0) -> 6 | H32: =ROUNDDOWN(H31*'Model Assumptions'!$C$24,0) -> 9 | I32: =ROUNDDOWN(I31*'Model Assumptions'!$C$24,0) -> 11 | J32: =ROUNDDOWN(J31*'Model Assumptions'!$C$24,0) -> 13 | K32: =ROUNDDOWN(K31*'Model Assumptions'!$C$24,0) -> 15 | ... M32: =ROUNDDOWN(M31*'Model Assumptions'!$C$24,0) -> 21
B33: New loan advisors hired during period | D33: =D31-C31+D32 -> 4 | E33: =E31-D31+E32 -> 16 | F33: =F31-E31+F32 -> 9 | G33: =G31-F31+G32 -> 24 | H33: =H31-G31+H32 -> 27 | I33: =I31-H31+I32 -> 29 | J33: =J31-I31+J32 -> 25 | K33: =K31-J31+K32 -> 27 | ... M33: =M31-L31+M32 -> 45
B34: Total professional staff | D34: =D31+D30+D29 -> 6 | E34: =E31+E30+E29 -> 22 | F34: =F31+F30+F29 -> 29 | G34: =G31+G30+G29 -> 50 | H34: =H31+H30+H29 -> 71 | I34: =I31+I30+I29 -> 92 | J34: =J31+J30+J29 -> 106 | K34: =K31+K30+K29 -> 120 | ... M34: =M31+M30+M29 -> 169
C35: Administrative Coordinators | D35: =D34/'Model Assumptions'!$C$25 -> 2 | E35: =E34/'Model Assumptions'!$C$25 -> 7.3333333 | F35: =F34/'Model Assumptions'!$C$25 -> 9.6666667 | G35: =G34/'Model Assumptions'!$C$25 -> 16.666667 | H35: =H34/'Model Assumptions'!$C$25 -> 23.666667 | I35: =I34/'Model Assumptions'!$C$25 -> 30.666667 | J35: =J34/'Model Assumptions'!$C$25 -> 35.333333 | K35: =K34/'Model Assumptions'!$C$25 -> 40 | ... M35: =M34/'Model Assumptions'!$C$25 -> 56.333333
B36: Total employees | D36: =D35+D31+D30+D29 -> 8 | E36: =E35+E31+E30+E29 -> 29.333333 | F36: =F35+F31+F30+F29 -> 38.666667 | G36: =G35+G31+G30+G29 -> 66.666667 | H36: =H35+H31+H30+H29 -> 94.666667 | I36: =I35+I31+I30+I29 -> 122.66667 | J36: =J35+J31+J30+J29 -> 141.33333 | K36: =K35+K31+K30+K29 -> 160 | ... M36: =M35+M31+M30+M29 -> 225.33333
B38: New Creditors Per Advisor | D38: =D21/D31 -> 25 | E38: =E21/E31 -> 5.5555556 | F38: =F21/F31 -> 10.416667 | G38: =G21/G31 -> 9.8214286 | H38: =H21/H31 -> 6.71875 | I38: =I21/I31 -> 8.0629006 | J38: =J21/J31 -> 6.1675347 | K38: =K21/K31 -> 6.6616881 | ... M38: =M21/M31 -> 5.2709825
A40: NEWBANK PRO FORMA INCOME STATEMENT
A41: (All dollar figures stated in '000USD 2001)
D43: 2001 | E43: 2002 | F43: 2003 | G43: 2004 | H43: 2005 | I43: 2006 | J43: 2007 | K43: 2008 | L43: 2009 | M43: 2010
B44: Interest Income
C45: Application Fees | D45: =D21*'Model Assumptions'!$C$15*'Model Assumptions'!$C$16/1000 -> 10.5 | E45: =E21*'Model Assumptions'!$C$15*'Model Assumptions'!$C$16/1000 -> 10.5 | F45: =F21*'Model Assumptions'!$C$15*'Model Assumptions'!$C$16/1000 -> 26.25 | G45: =G21*'Model Assumptions'!$C$15*'Model Assumptions'!$C$16/1000 -> 43.3125 | H45: =H21*'Model Assumptions'!$C$15*'Model Assumptions'!$C$16/1000 -> 42.328125 | I45: =I21*'Model Assumptions'!$C$15*'Model Assumptions'!$C$16/1000 -> 66.035156 | J45: =J21*'Model Assumptions'!$C$15*'Model Assumptions'!$C$16/1000 -> 58.283203 | K45: =K21*'Model Assumptions'!$C$15*'Model Assumptions'!$C$16/1000 -> 71.34668 | ... M45: =M21*'Model Assumptions'!$C$15*'Model Assumptions'!$C$16/1000 -> 79.697256
C46: Interest Income on Short Term Investments | D46: =D82*'Model Assumptions'!$C$32 -> 2.3074782 | E46: =((D82+E82)/2)*'Model Assumptions'!$C$32 -> 12.632184 | F46: =((E82+F82)/2)*'Model Assumptions'!$C$32 -> 45.612639 | G46: =((F82+G82)/2)*'Model Assumptions'!$C$32 -> 38.040882 | H46: =((G82+H82)/2)*'Model Assumptions'!$C$32 -> 6.2382826 | I46: =((H82+I82)/2)*'Model Assumptions'!$C$32 -> 25.932497 | J46: =((I82+J82)/2)*'Model Assumptions'!$C$32 -> 180.50665 | K46: =((J82+K82)/2)*'Model Assumptions'!$C$32 -> 586.96797 | L46: =((K82+L82)/2)*'Model Assumptions'!$C$32 -> 1172.729 | M46: =((L82+M82)/2)*'Model Assumptions'!$C$32 -> 1836.427
C47: Interest Income on loans | D47: =((D10+D14)/2)*'Model Assumptions'!$C$6 -> 242.5 | E47: =((E10+E14)/2)*'Model Assumptions'!$C$6 -> 970 | F47: =((F10+F14)/2)*'Model Assumptions'!$C$6 -> 2061.25 | G47: =((G10+G14)/2)*'Model Assumptions'!$C$6 -> 3667.8125 | H47: =((H10+H14)/2)*'Model Assumptions'!$C$6 -> 5676.0156 | I47: =((I10+I14)/2)*'Model Assumptions'!$C$6 -> 7519.3945 | J47: =((J10+J14)/2)*'Model Assumptions'!$C$6 -> 9051.123 | K47: =((K10+K14)/2)*'Model Assumptions'!$C$6 -> 10234.731 | ... M47: =((M10+M14)/2)*'Model Assumptions'!$C$6 -> 12384.025
B48: Total Interest Income | D48: =SUM(D45:D47) -> 255.30748 | E48: =SUM(E45:E47) -> 993.13218 | F48: =SUM(F45:F47) -> 2133.1126 | G48: =SUM(G45:G47) -> 3749.1659 | H48: =SUM(H45:H47) -> 5724.582 | I48: =SUM(I45:I47) -> 7611.3622 | J48: =SUM(J45:J47) -> 9289.9129 | K48: =SUM(K45:K47) -> 10893.046 | ... M48: =SUM(M45:M47) -> 14300.149
B50: Interest Expense
C51: Interest on Required Savings Deposits | D51: =((C110+D110)/2)*'Model Assumptions'!$C$17 -> 2 | E51: =((D110+E110)/2)*'Model Assumptions'!$C$17 -> 8 | F51: =((E110+F110)/2)*'Model Assumptions'!$C$17 -> 17 | G51: =((F110+G110)/2)*'Model Assumptions'!$C$17 -> 30.25 | H51: =((G110+H110)/2)*'Model Assumptions'!$C$17 -> 46.8125 | I51: =((H110+I110)/2)*'Model Assumptions'!$C$17 -> 62.015625 | J51: =((I110+J110)/2)*'Model Assumptions'!$C$17 -> 74.648438 | K51: =((J110+K110)/2)*'Model Assumptions'!$C$17 -> 84.410156 | ... M51: =((L110+M110)/2)*'Model Assumptions'!$C$17 -> 102.13629
C52: Interest on Long-term Debt | D52: =((C111+D111)/2)*'Model Assumptions'!$C$34 -> 0 | E52: =((D111+E111)/2)*'Model Assumptions'!$C$34 -> 0 | F52: =((E111+F111)/2)*'Model Assumptions'!$C$34 -> 0 | G52: =((F111+G111)/2)*'Model Assumptions'!$C$34 -> 0 | H52: =((G111+H111)/2)*'Model Assumptions'!$C$34 -> 0 | I52: =((H111+I111)/2)*'Model Assumptions'!$C$34 -> 0 | J52: =((I111+J111)/2)*'Model Assumptions'!$C$34 -> 0 | K52: =((J111+K111)/2)*'Model Assumptions'!$C$34 -> 0 | ... M52: =((L111+M111)/2)*'Model Assumptions'!$C$34 -> 0
B53: Total Interest Expense | D53: =SUM(D51:D52) -> 2 | E53: =SUM(E51:E52) -> 8 | F53: =SUM(F51:F52) -> 17 | G53: =SUM(G51:G52) -> 30.25 | H53: =SUM(H51:H52) -> 46.8125 | I53: =SUM(I51:I52) -> 62.015625 | J53: =SUM(J51:J52) -> 74.648438 | K53: =SUM(K51:K52) -> 84.410156 | ... M53: =SUM(M51:M52) -> 102.13629
B55: Net Interest Income | D55: =D48-D53 -> 253.30748 | E55: =E48-E53 -> 985.13218 | F55: =F48-F53 -> 2116.1126 | G55: =G48-G53 -> 3718.9159 | H55: =H48-H53 -> 5677.7695 | I55: =I48-I53 -> 7549.3466 | J55: =J48-J53 -> 9215.2645 | K55: =K48-K53 -> 10808.636 | ... M55: =M48-M53 -> 14198.013
C56: Provision for Loan Losses | D56: =-D84 -> 100 | E56: =-(E84-D84) -> 200 | F56: =-(F84-E84) -> 250 | G56: =-(G84-F84) -> 412.5 | H56: =-(H84-G84) -> 415.625 | I56: =-(I84-H84) -> 344.53125 | J56: =-(J84-I84) -> 287.10938 | K56: =-(K84-J84) -> 200.97656 | L56: =-(L84-K84) -> 221.07422 | M56: =-(M84-L84) -> 243.18164
B57: Net Interest Income after Provision for Loan Losses | D57: =D55-D56 -> 153.30748 | E57: =E55-E56 -> 785.13218 | F57: =F55-F56 -> 1866.1126 | G57: =G55-G56 -> 3306.4159 | H57: =H55-H56 -> 5262.1445 | I57: =I55-I56 -> 7204.8153 | J57: =J55-J56 -> 8928.1551 | K57: =K55-K56 -> 10607.659 | ... M57: =M55-M56 -> 13954.831
B59: Non-Interest Expenses
C60: Office Space Lease Expense | D60: =D27*'Model Assumptions'!$C$18 -> 50 | E60: =E27*'Model Assumptions'!$C$18 -> 150 | F60: =F27*'Model Assumptions'!$C$18 -> 200 | G60: =G27*'Model Assumptions'!$C$18 -> 350 | H60: =H27*'Model Assumptions'!$C$18 -> 500 | I60: =I27*'Model Assumptions'!$C$18 -> 650 | J60: =J27*'Model Assumptions'!$C$18 -> 750 | K60: =K27*'Model Assumptions'!$C$18 -> 850 | ... M60: =M27*'Model Assumptions'!$C$18 -> 1200
C61: Salary Expense | D61: =D31*'Model Assumptions'!$C$10+'Financial Model'!D35*'Model Assumptions'!$C$26+'Financial Model'!D30*'Model Assumptions'!$C$21+D29*'Model Assumptions'!$C$23 -> 160 | E61: =E31*'Model Assumptions'!$C$10+'Financial Model'!E35*'Model Assumptions'!$C$26+'Financial Model'!E30*'Model Assumptions'!$C$21+E29*'Model Assumptions'!$C$23 -> 460 | F61: =F31*'Model Assumptions'!$C$10+'Financial Model'!F35*'Model Assumptions'!$C$26+'Financial Model'!F30*'Model Assumptions'!$C$21+F29*'Model Assumptions'!$C$23 -> 592.5 | G61: =G31*'Model Assumptions'!$C$10+'Financial Model'!G35*'Model Assumptions'!$C$26+'Financial Model'!G30*'Model Assumptions'!$C$21+G29*'Model Assumptions'!$C$23 -> 990 | H61: =H31*'Model Assumptions'!$C$10+'Financial Model'!H35*'Model Assumptions'!$C$26+'Financial Model'!H30*'Model Assumptions'!$C$21+H29*'Model Assumptions'!$C$23 -> 1387.5 | I61: =I31*'Model Assumptions'!$C$10+'Financial Model'!I35*'Model Assumptions'!$C$26+'Financial Model'!I30*'Model Assumptions'!$C$21+I29*'Model Assumptions'!$C$23 -> 1785 | J61: =J31*'Model Assumptions'!$C$10+'Financial Model'!J35*'Model Assumptions'!$C$26+'Financial Model'!J30*'Model Assumptions'!$C$21+J29*'Model Assumptions'!$C$23 -> 2050 | K61: =K31*'Model Assumptions'!$C$10+'Financial Model'!K35*'Model Assumptions'!$C$26+'Financial Model'!K30*'Model Assumptions'!$C$21+K29*'Model Assumptions'!$C$23 -> 2315 | ... M61: =M31*'Model Assumptions'!$C$10+'Financial Model'!M35*'Model Assumptions'!$C$26+'Financial Model'!M30*'Model Assumptions'!$C$21+M29*'Model Assumptions'!$C$23 -> 3242.5
C62: Depreciation | D62: =-D88+C88 -> 5.7 | E62: =-E88+D88 -> 21.6 | F62: =-F88+E88 -> 35.7 | G62: =-G88+F88 -> 57.3 | H62: =-H88+G88 -> 86.7 | I62: =-I88+H88 -> 116.1 | J62: =-J88+I88 -> 125.5 | K62: =-K88+J88 -> 123.9 | ... M62: =-M88+L88 -> 28.7
C63: Marketing Expense | D63: =E11*'Model Assumptions'!$C$27 -> 30 | E63: =F11*'Model Assumptions'!$C$27 -> 52.5 | F63: =G11*'Model Assumptions'!$C$27 -> 91.875 | G63: =H11*'Model Assumptions'!$C$27 -> 114.84375 | H63: =I11*'Model Assumptions'!$C$27 -> 143.55469 | I63: =J11*'Model Assumptions'!$C$27 -> 157.91016 | J63: =K11*'Model Assumptions'!$C$27 -> 173.70117 | K63: =L11*'Model Assumptions'!$C$27 -> 191.07129 | L63: =M11*'Model Assumptions'!$C$27 -> 210.17842 | M63: =M11*'Model Assumptions'!$C$27 -> 210.17842
C64: Recruiting and Training Expense | D64: ='Model Assumptions'!$C$28+'Model Assumptions'!$C$19*'Financial Model'!D31-'Financial Model'!C31 -> 45 | E64: ='Model Assumptions'!$C$28+'Model Assumptions'!$C$19*'Financial Model'!E31-'Financial Model'!D31 -> 111 | F64: ='Model Assumptions'!$C$28+'Model Assumptions'!$C$19*'Financial Model'!F31-'Financial Model'!E31 -> 127 | G64: ='Model Assumptions'!$C$28+'Model Assumptions'!$C$19*'Financial Model'!G31-'Financial Model'!F31 -> 211 | H64: ='Model Assumptions'!$C$28+'Model Assumptions'!$C$19*'Financial Model'!H31-'Financial Model'!G31 -> 283 | I64: ='Model Assumptions'!$C$28+'Model Assumptions'!$C$19*'Financial Model'!I31-'Financial Model'!H31 -> 355 | J64: ='Model Assumptions'!$C$28+'Model Assumptions'!$C$19*'Financial Model'!J31-'Financial Model'!I31 -> 397 | K64: ='Model Assumptions'!$C$28+'Model Assumptions'!$C$19*'Financial Model'!K31-'Financial Model'!J31 -> 445 | ... M64: ='Model Assumptions'!$C$28+'Model Assumptions'!$C$19*'Financial Model'!M31-'Financial Model'!L31 -> 625
C65: Legal / Accounting Expense | D65: =D11*'Model Assumptions'!$C$30+'Model Assumptions'!C31 -> 105 | E65: =E11*'Model Assumptions'!$C$30 -> 10 | F65: =F11*'Model Assumptions'!$C$30 -> 17.5 | G65: =G11*'Model Assumptions'!$C$30 -> 30.625 | H65: =H11*'Model Assumptions'!$C$30 -> 38.28125 | I65: =I11*'Model Assumptions'!$C$30 -> 47.851562 | J65: =J11*'Model Assumptions'!$C$30 -> 52.636719 | K65: =K11*'Model Assumptions'!$C$30 -> 57.900391 | L65: =L11*'Model Assumptions'!$C$30 -> 63.69043 | M65: =M11*'Model Assumptions'!$C$30 -> 70.059473
B66: Total Non-Interest Expenses | D66: =SUM(D60:D65) -> 395.7 | E66: =SUM(E60:E65) -> 805.1 | F66: =SUM(F60:F65) -> 1064.575 | G66: =SUM(G60:G65) -> 1753.7687 | H66: =SUM(H60:H65) -> 2439.0359 | I66: =SUM(I60:I65) -> 3111.8617 | J66: =SUM(J60:J65) -> 3548.8379 | K66: =SUM(K60:K65) -> 3982.8717 | ... M66: =SUM(M60:M65) -> 5376.4379
B68: Earnings before Income Taxes | D68: =D57-D66 -> -242.39252 | E68: =E57-E66 -> -19.967816 | F68: =F57-F66 -> 801.53764 | G68: =G57-G66 -> 1552.6471 | H68: =H57-H66 -> 2823.1086 | I68: =I57-I66 -> 4092.9536 | J68: =J57-J66 -> 5379.3172 | K68: =K57-K66 -> 6624.7877 | ... M68: =M57-M66 -> 8578.3935
B70: Income Tax Expense | D70: =IF(D$68*'Model Assumptions'!$C$12+C71<0,0,D68*'Model Assumptions'!$C$12+C71) -> 0 | E70: =IF(E$68*'Model Assumptions'!$C$12+D71<0,0,E68*'Model Assumptions'!$C$12+D71) -> 0 | F70: =IF(F$68*'Model Assumptions'!$C$12+E71<0,0,F68*'Model Assumptions'!$C$12+E71) -> 80.876595 | G70: =IF(G$68*'Model Assumptions'!$C$12+F71<0,0,G68*'Model Assumptions'!$C$12+F71) -> 232.89707 | H70: =IF(H$68*'Model Assumptions'!$C$12+G71<0,0,H68*'Model Assumptions'!$C$12+G71) -> 423.46629 | I70: =IF(I$68*'Model Assumptions'!$C$12+H71<0,0,I68*'Model Assumptions'!$C$12+H71) -> 613.94304 | J70: =IF(J$68*'Model Assumptions'!$C$12+I71<0,0,J68*'Model Assumptions'!$C$12+I71) -> 806.89758 | K70: =IF(K$68*'Model Assumptions'!$C$12+J71<0,0,K68*'Model Assumptions'!$C$12+J71) -> 993.71815 | ... M70: =IF(M$68*'Model Assumptions'!$C$12+L71<0,0,M68*'Model Assumptions'!$C$12+L71) -> 1286.759
B71: Loss Carryforward (cumulative 5yr max) | D71: =IF(D$68*'Model Assumptions'!$C$12+C71>0,0,D68*'Model Assumptions'!$C$12+C71) -> -36.358878 | E71: =IF(E$68*'Model Assumptions'!$C$12+D71>0,0,E68*'Model Assumptions'!$C$12+D71) -> -39.354051 | F71: =IF(F$68*'Model Assumptions'!$C$12+E71>0,0,F68*'Model Assumptions'!$C$12+E71) -> 0 | G71: =IF(G$68*'Model Assumptions'!$C$12+F71>0,0,G68*'Model Assumptions'!$C$12+F71) -> 0 | H71: =IF(H$68*'Model Assumptions'!$C$12+G71>0,0,H68*'Model Assumptions'!$C$12+G71) -> 0 | I71: =IF(I$68*'Model Assumptions'!$C$12+H71>0,0,I68*'Model Assumptions'!$C$12+H71) -> 0 | J71: =IF(J$68*'Model Assumptions'!$C$12+I71>0,0,J68*'Model Assumptions'!$C$12+I71) -> 0 | K71: =IF(K$68*'Model Assumptions'!$C$12+J71>0,0,K68*'Model Assumptions'!$C$12+J71) -> 0 | ... M71: =IF(M$68*'Model Assumptions'!$C$12+L71>0,0,M68*'Model Assumptions'!$C$12+L71) -> 0
B73: Net Income | D73: =D68+D70 -> -242.39252 | E73: =E68+E70 -> -19.967816 | F73: =F68+F70 -> 882.41423 | G73: =G68+G70 -> 1785.5442 | H73: =H68+H70 -> 3246.5749 | I73: =I68+I70 -> 4706.8966 | J73: =J68+J70 -> 6186.2148 | K73: =K68+K70 -> 7618.5058 | ... M73: =M68+M70 -> 9865.1526
A76: NEWBANK PRO FORMA BALANCE SHEET
A77: (All dollar figures stated in '000USD 2001)
D79: 2001 | E79: 2002 | F79: 2003 | G79: 2004 | H79: 2005 | I79: 2006 | J79: 2007 | K79: 2008 | L79: 2009 | M79: 2010
B81: ASSETS
B82: Cash & Short Term Investments | D82: =D149 -> 25.638646 | E82: =E149 -> 255.07655 | F82: =F149 -> 758.53765 | G82: =G149 -> 86.815286 | H82: =H149 -> 51.813217 | I82: =I149 -> 524.46449 | J82: =J149 -> 3486.7944 | K82: =K149 -> 9556.9382 | ... M82: =M149 -> 24305.784
B83: Loan Portfolio | D83: =D14 -> 1000 | E83: =E14 -> 3000 | F83: =F14 -> 5500 | G83: =G14 -> 9625 | H83: =H14 -> 13781.25 | I83: =I14 -> 17226.562 | J83: =J14 -> 20097.656 | K83: =K14 -> 22107.422 | ... M83: =M14 -> 26749.98
B84: Less: Loan Loss Allowance | D84: =-D83*'Model Assumptions'!$C$7 -> -100 | E84: =-E83*'Model Assumptions'!$C$7 -> -300 | F84: =-F83*'Model Assumptions'!$C$7 -> -550 | G84: =-G83*'Model Assumptions'!$C$7 -> -962.5 | H84: =-H83*'Model Assumptions'!$C$7 -> -1378.125 | I84: =-I83*'Model Assumptions'!$C$7 -> -1722.6562 | J84: =-J83*'Model Assumptions'!$C$7 -> -2009.7656 | K84: =-K83*'Model Assumptions'!$C$7 -> -2210.7422 | ... M84: =-M83*'Model Assumptions'!$C$7 -> -2674.998
C85: Net Loan Portfolio | D85: =D83+D84 -> 900 | E85: =E83+E84 -> 2700 | F85: =F83+F84 -> 4950 | G85: =G83+G84 -> 8662.5 | H85: =H83+H84 -> 12403.125 | I85: =I83+I84 -> 15503.906 | J85: =J83+J84 -> 18087.891 | K85: =K83+K84 -> 19896.68 | ... M85: =M83+M84 -> 24074.982
B87: Property and Equipment | D87: =D89+D100 -> 52 | E87: =E89+E100 -> 164 | F87: =F89+F100 -> 218 | G87: =G89+G100 -> 380 | H87: =H89+H100 -> 542 | I87: =I89+I100 -> 704 | J87: =J89+J100 -> 812 | K87: =K89+K100 -> 920 | ... M87: =M89+M100 -> 1298
B88: Less: Accumulated depreciation | D88: =(D99+D101) -> -5.7 | E88: =(E99+E101) -> -27.3 | F88: =(F99+F101) -> -63 | G88: =(G99+G101) -> -120.3 | H88: =(H99+H101) -> -207 | I88: =(I99+I101) -> -323.1 | J88: =(J99+J101) -> -448.6 | K88: =(K99+K101) -> -572.5 | ... M88: =(M99+M101) -> -628.9
B89: Computers and office equipment | D89: =D36*'Model Assumptions'!$C$37+('Model Assumptions'!$C$38+'Model Assumptions'!$C$39)*'Financial Model'!D27 -> 47 | E89: =E36*'Model Assumptions'!$C$37+('Model Assumptions'!$C$38+'Model Assumptions'!$C$39)*'Financial Model'!E27 -> 149 | F89: =F36*'Model Assumptions'!$C$37+('Model Assumptions'!$C$38+'Model Assumptions'!$C$39)*'Financial Model'!F27 -> 198 | G89: =G36*'Model Assumptions'!$C$37+('Model Assumptions'!$C$38+'Model Assumptions'!$C$39)*'Financial Model'!G27 -> 345 | H89: =H36*'Model Assumptions'!$C$37+('Model Assumptions'!$C$38+'Model Assumptions'!$C$39)*'Financial Model'!H27 -> 492 | I89: =I36*'Model Assumptions'!$C$37+('Model Assumptions'!$C$38+'Model Assumptions'!$C$39)*'Financial Model'!I27 -> 639 | J89: =J36*'Model Assumptions'!$C$37+('Model Assumptions'!$C$38+'Model Assumptions'!$C$39)*'Financial Model'!J27 -> 737 | K89: =K36*'Model Assumptions'!$C$37+('Model Assumptions'!$C$38+'Model Assumptions'!$C$39)*'Financial Model'!K27 -> 835 | ... M89: =M36*'Model Assumptions'!$C$37+('Model Assumptions'!$C$38+'Model Assumptions'!$C$39)*'Financial Model'!M27 -> 1178
B90: Newly acquired equiptment | D90: =D36*'Model Assumptions'!$C$37+('Model Assumptions'!$C$38+'Model Assumptions'!$C$39)*'Financial Model'!D27 -> 47 | E90: =(E36-D36)*'Model Assumptions'!$C$37+('Model Assumptions'!$C$38+'Model Assumptions'!$C$39)*('Financial Model'!E27-'Financial Model'!D27) -> 102 | F90: =(F36-E36)*'Model Assumptions'!$C$37+('Model Assumptions'!$C$38+'Model Assumptions'!$C$39)*('Financial Model'!F27-'Financial Model'!E27) -> 49 | G90: =(G36-F36)*'Model Assumptions'!$C$37+('Model Assumptions'!$C$38+'Model Assumptions'!$C$39)*('Financial Model'!G27-'Financial Model'!F27) -> 147 | H90: =(H36-G36)*'Model Assumptions'!$C$37+('Model Assumptions'!$C$38+'Model Assumptions'!$C$39)*('Financial Model'!H27-'Financial Model'!G27) -> 147 | I90: =(I36-H36)*'Model Assumptions'!$C$37+('Model Assumptions'!$C$38+'Model Assumptions'!$C$39)*('Financial Model'!I27-'Financial Model'!H27) -> 147 | J90: =(J36-I36)*'Model Assumptions'!$C$37+('Model Assumptions'!$C$38+'Model Assumptions'!$C$39)*('Financial Model'!J27-'Financial Model'!I27) -> 98 | K90: =(K36-J36)*'Model Assumptions'!$C$37+('Model Assumptions'!$C$38+'Model Assumptions'!$C$39)*('Financial Model'!K27-'Financial Model'!J27) -> 98 | L90: =(L36-K36)*'Model Assumptions'!$C$37+('Model Assumptions'!$C$38+'Model Assumptions'!$C$39)*('Financial Model'!L27-'Financial Model'!K27) -> 147 | M90: =(M36-L36)*'Model Assumptions'!$C$37+('Model Assumptions'!$C$38+'Model Assumptions'!$C$39)*('Financial Model'!M27-'Financial Model'!L27) -> 196
B91: Replacement equiptment | E91: =E89-E97 -> 0 | F91: =F89-F97 -> 0 | G91: =G89-G97 -> 0 | H91: =H89-H97 -> 0 | I91: =I89-I97 -> 0 | J91: =J89-J97 -> 47 | K91: =K89-K97 -> 149 | L91: =L89-L97 -> 198 | M91: =M89-M97 -> 345
B92: 1 yr old equiptment | E92: =D90 -> 47 | F92: =E90 -> 102 | G92: =F90 -> 49 | H92: =G90 -> 147 | I92: =H90 -> 147 | J92: =I90 -> 147 | K92: =J90 -> 98 | L92: =K90 -> 98 | M92: =L90 -> 147
B93: 2 yr old equiptment | F93: =E92 -> 47 | G93: =F92 -> 102 | H93: =G92 -> 49 | I93: =H92 -> 147 | J93: =I92 -> 147 | K93: =J92 -> 147 | L93: =K92 -> 98 | M93: =L92 -> 98
B94: 3 yr old equiptment | G94: =F93 -> 47 | H94: =G93 -> 102 | I94: =H93 -> 49 | J94: =I93 -> 147 | K94: =J93 -> 147 | L94: =K93 -> 147 | M94: =L93 -> 98
B95: 4 yr old equiptment | H95: =G94 -> 47 | I95: =H94 -> 102 | J95: =I94 -> 49 | K95: =J94 -> 147 | L95: =K94 -> 147 | M95: =L94 -> 147
B96: 5 yr old equiptment | I96: =H95 -> 47 | J96: =I95 -> 102 | K96: =J95 -> 49 | L96: =K95 -> 147 | M96: =L95 -> 147
D97: =D96+D95+D94+D93+D92+D90 -> 47 | E97: =E96+E95+E94+E93+E92+E90 -> 149 | F97: =F96+F95+F94+F93+F92+F90 -> 198 | G97: =G96+G95+G94+G93+G92+G90 -> 345 | H97: =H96+H95+H94+H93+H92+H90 -> 492 | I97: =I96+I95+I94+I93+I92+I90 -> 639 | J97: =J96+J95+J94+J93+J92+J90 -> 690 | K97: =K96+K95+K94+K93+K92+K90 -> 686 | ... M97: =M96+M95+M94+M93+M92+M90 -> 833
B98: Equiptment Written Off | D98: =C96 -> 0 | E98: =D96 -> 0 | F98: =E96 -> 0 | G98: =F96 -> 0 | H98: =G96 -> 0 | I98: =H96 -> 0 | J98: =I96 -> 47 | K98: =J96 -> 102 | L98: =K97 -> 686 | M98: =L97 -> 784
B99: Less: Accumulated depreciation | D99: =-(SUM(D92:D96)-D98+SUM(D90:D91)/2)/'Model Assumptions'!$B$37+C99 -> -4.7 | E99: =-(SUM(E92:E96)-E98+SUM(E90:E91)/2)/'Model Assumptions'!$B$37+D99 -> -24.3 | F99: =-(SUM(F92:F96)-F98+SUM(F90:F91)/2)/'Model Assumptions'!$B$37+E99 -> -59 | G99: =-(SUM(G92:G96)-G98+SUM(G90:G91)/2)/'Model Assumptions'!$B$37+F99 -> -113.3 | H99: =-(SUM(H92:H96)-H98+SUM(H90:H91)/2)/'Model Assumptions'!$B$37+G99 -> -197 | I99: =-(SUM(I92:I96)-I98+SUM(I90:I91)/2)/'Model Assumptions'!$B$37+H99 -> -310.1 | J99: =-(SUM(J92:J96)-J98+SUM(J90:J91)/2)/'Model Assumptions'!$B$37+I99 -> -433.6 | K99: =-(SUM(K92:K96)-K98+SUM(K90:K91)/2)/'Model Assumptions'!$B$37+J99 -> -555.5 | ... M99: =-(SUM(M92:M96)-M98+SUM(M90:M91)/2)/'Model Assumptions'!$B$37+L99 -> -604.9
B100: Branch office vehicles | D100: ='Model Assumptions'!$C$40*'Financial Model'!D27 -> 5 | E100: ='Model Assumptions'!$C$40*'Financial Model'!E27 -> 15 | F100: ='Model Assumptions'!$C$40*'Financial Model'!F27 -> 20 | G100: ='Model Assumptions'!$C$40*'Financial Model'!G27 -> 35 | H100: ='Model Assumptions'!$C$40*'Financial Model'!H27 -> 50 | I100: ='Model Assumptions'!$C$40*'Financial Model'!I27 -> 65 | J100: ='Model Assumptions'!$C$40*'Financial Model'!J27 -> 75 | K100: ='Model Assumptions'!$C$40*'Financial Model'!K27 -> 85 | ... M100: ='Model Assumptions'!$C$40*'Financial Model'!M27 -> 120
B101: Less: Accumulated depreciation | D101: =-D100/'Model Assumptions'!$B$40 -> -1 | E101: =-E100/'Model Assumptions'!$B$40 -> -3 | F101: =-F100/'Model Assumptions'!$B$40 -> -4 | G101: =-G100/'Model Assumptions'!$B$40 -> -7 | H101: =-H100/'Model Assumptions'!$B$40 -> -10 | I101: =-I100/'Model Assumptions'!$B$40 -> -13 | J101: =-J100/'Model Assumptions'!$B$40 -> -15 | K101: =-K100/'Model Assumptions'!$B$40 -> -17 | ... M101: =-M100/'Model Assumptions'!$B$40 -> -24
B102: Net Property and Equiptment | D102: =D87+D88 -> 46.3 | E102: =E87+E88 -> 136.7 | F102: =F87+F88 -> 155 | G102: =G87+G88 -> 259.7 | H102: =H87+H88 -> 335 | I102: =I87+I88 -> 380.9 | J102: =J87+J88 -> 363.4 | K102: =K87+K88 -> 347.5 | ... M102: =M87+M88 -> 669.1
B103: Other Assets | D103: =-D71*'Model Assumptions'!$C$12 -> 5.4538317 | E103: =-E71*'Model Assumptions'!$C$12 -> 5.9031076 | F103: =-F71*'Model Assumptions'!$C$12 -> 0 | G103: =-G71*'Model Assumptions'!$C$12 -> 0 | H103: =-H71*'Model Assumptions'!$C$12 -> 0 | I103: =-I71*'Model Assumptions'!$C$12 -> 0 | J103: =-J71*'Model Assumptions'!$C$12 -> 0 | K103: =-K71*'Model Assumptions'!$C$12 -> 0 | ... M103: =-M71*'Model Assumptions'!$C$12 -> 0
B105: Total Assets | D105: =D103+D102+D85+D82 -> 977.39248 | E105: =E103+E102+E85+E82 -> 3097.6797 | F105: =F103+F102+F85+F82 -> 5863.5376 | G105: =G103+G102+G85+G82 -> 9009.0153 | H105: =H103+H102+H85+H82 -> 12789.938 | I105: =I103+I102+I85+I82 -> 16409.271 | J105: =J103+J102+J85+J82 -> 21938.085 | K105: =K103+K102+K85+K82 -> 29801.118 | ... M105: =M103+M102+M85+M82 -> 49049.866
B107: LIABILITIES
B109: Accounts Payable | D109: =(C66+D66)*'Model Assumptions'!$C$33 -> 19.785 | E109: =(D66+E66)*'Model Assumptions'!$C$33 -> 60.04 | F109: =(E66+F66)*'Model Assumptions'!$C$33 -> 93.48375 | G109: =(F66+G66)*'Model Assumptions'!$C$33 -> 140.91719 | H109: =(G66+H66)*'Model Assumptions'!$C$33 -> 209.64023 | I109: =(H66+I66)*'Model Assumptions'!$C$33 -> 277.54488 | J109: =(I66+J66)*'Model Assumptions'!$C$33 -> 333.03498 | K109: =(J66+K66)*'Model Assumptions'!$C$33 -> 376.58548 | ... M109: =(L66+M66)*'Model Assumptions'!$C$33 -> 495.67534
B110: Required Savings Deposits | D110: =D83*'Model Assumptions'!$C$8 -> 100 | E110: =E83*'Model Assumptions'!$C$8 -> 300 | F110: =F83*'Model Assumptions'!$C$8 -> 550 | G110: =G83*'Model Assumptions'!$C$8 -> 962.5 | H110: =H83*'Model Assumptions'!$C$8 -> 1378.125 | I110: =I83*'Model Assumptions'!$C$8 -> 1722.6562 | J110: =J83*'Model Assumptions'!$C$8 -> 2009.7656 | K110: =K83*'Model Assumptions'!$C$8 -> 2210.7422 | ... M110: =M83*'Model Assumptions'!$C$8 -> 2674.998
B111: Long-term Debt | D111: 1100 | E111: 2500 | F111: 2500 | G111: 2500 | H111: 2500 | I111: 1000 | J111: 0 | K111: 0 | L111: 0 | M111: 0
B112: Total Liabilities | D112: =SUM(D109:D111) -> 1219.785 | E112: =SUM(E109:E111) -> 2860.04 | F112: =SUM(F109:F111) -> 3143.4837 | G112: =SUM(G109:G111) -> 3603.4172 | H112: =SUM(H109:H111) -> 4087.7652 | I112: =SUM(I109:I111) -> 3000.2011 | J112: =SUM(J109:J111) -> 2342.8006 | K112: =SUM(K109:K111) -> 2587.3277 | ... M112: =SUM(M109:M111) -> 3170.6734
B114: EQUITY
C115: Retained Earnings | D115: =D73 -> -242.39252 | E115: =E73+D115 -> -262.36034 | F115: =F73+E115 -> 620.0539 | G115: =G73+F115 -> 2405.5981 | H115: =H73+G115 -> 5652.173 | I115: =I73+H115 -> 10359.07 | J115: =J73+I115 -> 16545.284 | K115: =K73+J115 -> 24163.79 | L115: =L73+K115 -> 32964.04 | M115: =M73+L115 -> 42829.193
C116: Equity to Common Shareholders | D116: 0 | E116: 500 | F116: 2100 | G116: 3000 | H116: 3050 | I116: =H116 -> 3050 | J116: =I116 -> 3050 | K116: =J116 -> 3050 | L116: =K116 -> 3050 | M116: =L116 -> 3050
B117: Total Equity | D117: =SUM(D115:D116) -> -242.39252 | E117: =SUM(E115:E116) -> 237.63966 | F117: =SUM(F115:F116) -> 2720.0539 | G117: =SUM(G115:G116) -> 5405.5981 | H117: =SUM(H115:H116) -> 8702.173 | I117: =SUM(I115:I116) -> 13409.07 | J117: =SUM(J115:J116) -> 19595.284 | K117: =SUM(K115:K116) -> 27213.79 | ... M117: =SUM(M115:M116) -> 45879.193
B118: TOTAL LIABILITIES AND EQUITY | D118: =D117+D112 -> 977.39248 | E118: =E117+E112 -> 3097.6797 | F118: =F117+F112 -> 5863.5376 | G118: =G117+G112 -> 9009.0153 | H118: =H117+H112 -> 12789.938 | I118: =I117+I112 -> 16409.271 | J118: =J117+J112 -> 21938.085 | K118: =K117+K112 -> 29801.118 | ... M118: =M117+M112 -> 49049.866
A121: NEWBANK PRO FORMA STATEMENT OF CASH FLOWS
A122: (All dollar figures stated in '000USD 2001)
D124: 2001 | E124: 2002 | F124: 2003 | G124: 2004 | H124: 2005 | I124: 2006 | J124: 2007 | K124: 2008 | L124: 2009 | M124: 2010
A126: Cash Flows from Operating Activities:
C127: Net Income | D127: =D73 -> -242.39252 | E127: =E73 -> -19.967816 | F127: =F73 -> 882.41423 | G127: =G73 -> 1785.5442 | H127: =H73 -> 3246.5749 | I127: =I73 -> 4706.8966 | J127: =J73 -> 6186.2148 | K127: =K73 -> 7618.5058 | ... M127: =M73 -> 9865.1526
C128: Provision for Loan Losses | D128: =D56 -> 100 | E128: =E56 -> 200 | F128: =F56 -> 250 | G128: =G56 -> 412.5 | H128: =H56 -> 415.625 | I128: =I56 -> 344.53125 | J128: =J56 -> 287.10938 | K128: =K56 -> 200.97656 | ... M128: =M56 -> 243.18164
...

Sheet NPV Calculation
A1: Exhibit 3 NPV Calculation
A3: NEWBANK NET PRESENT VALUE OF CASH FLOWS CALCULATION
A4: (All dollar figures stated in '000USD 2001)
O5: Terminal
D6: 2000 | E6: 2001 | F6: 2002 | G6: 2003 | H6: 2004 | I6: 2005 | J6: 2006 | K6: 2007 | L6: 2008 | M6: 2009 | N6: 2010 | O6: Value
B7: Net Income | E7: ='Financial Model'!D73 -> -242.39252 | F7: ='Financial Model'!E73 -> -19.967816 | G7: ='Financial Model'!F73 -> 882.41423 | H7: ='Financial Model'!G73 -> 1785.5442 | I7: ='Financial Model'!H73 -> 3246.5749 | J7: ='Financial Model'!I73 -> 4706.8966 | K7: ='Financial Model'!J73 -> 6186.2148 | L7: ='Financial Model'!K73 -> 7618.5058 | ... N7: ='Financial Model'!M73 -> 9865.1526
A8: Add Non Cash Expenses:
B9: Depreciation | E9: ='Financial Model'!D62 -> 5.7 | F9: ='Financial Model'!E62 -> 21.6 | G9: ='Financial Model'!F62 -> 35.7 | H9: ='Financial Model'!G62 -> 57.3 | I9: ='Financial Model'!H62 -> 86.7 | J9: ='Financial Model'!I62 -> 116.1 | K9: ='Financial Model'!J62 -> 125.5 | L9: ='Financial Model'!K62 -> 123.9 | ... N9: ='Financial Model'!M62 -> 28.7
B10: Provision for Loan Losses | E10: ='Financial Model'!D56 -> 100 | F10: ='Financial Model'!E56 -> 200 | G10: ='Financial Model'!F56 -> 250 | H10: ='Financial Model'!G56 -> 412.5 | I10: ='Financial Model'!H56 -> 415.625 | J10: ='Financial Model'!I56 -> 344.53125 | K10: ='Financial Model'!J56 -> 287.10938 | L10: ='Financial Model'!K56 -> 200.97656 | ... N10: ='Financial Model'!M56 -> 243.18164
A11: Less Change in Net Working Capital: | E11: ='Financial Model'!D131+'Financial Model'!D132+'Financial Model'!D134+'Financial Model'!D135 -> -885.66883 | F11: ='Financial Model'!E131+'Financial Model'!E132+'Financial Model'!E134+'Financial Model'!E135 -> -1760.1943 | G11: ='Financial Model'!F131+'Financial Model'!F132+'Financial Model'!F134+'Financial Model'!F135 -> -2210.6531 | H11: ='Financial Model'!G131+'Financial Model'!G132+'Financial Model'!G134+'Financial Model'!G135 -> -3665.0666 | I11: ='Financial Model'!H131+'Financial Model'!H132+'Financial Model'!H134+'Financial Model'!H135 -> -3671.902 | J11: ='Financial Model'!I131+'Financial Model'!I132+'Financial Model'!I134+'Financial Model'!I135 -> -3032.8766 | K11: ='Financial Model'!J131+'Financial Model'!J132+'Financial Model'!J134+'Financial Model'!J135 -> -2528.4943 | L11: ='Financial Model'!K131+'Financial Model'!K132+'Financial Model'!K134+'Financial Model'!K135 -> -1765.2386 | ... N11: ='Financial Model'!M131+'Financial Model'!M132+'Financial Model'!M134+'Financial Model'!M135 -> -2118.9565
A12: Less Capital Expenditures: | E12: ='Financial Model'!D139 -> -52 | F12: ='Financial Model'!E139 -> -112 | G12: ='Financial Model'!F139 -> -54 | H12: ='Financial Model'!G139 -> -162 | I12: ='Financial Model'!H139 -> -162 | J12: ='Financial Model'!I139 -> -162 | K12: ='Financial Model'!J139 -> -108 | L12: ='Financial Model'!K139 -> -108 | ... N12: ='Financial Model'!M139 -> -216
B13: Free Cash Flows | E13: =SUM(E7:E12) -> -1074.3614 | F13: =SUM(F7:F12) -> -1670.5621 | G13: =SUM(G7:G12) -> -1096.5389 | H13: =SUM(H7:H12) -> -1571.7224 | I13: =SUM(I7:I12) -> -85.002069 | J13: =SUM(J7:J12) -> 1972.6513 | K13: =SUM(K7:K12) -> 3962.3299 | L13: =SUM(L7:L12) -> 6070.1438 | ... N13: =SUM(N7:N12) -> 7802.0777 | O13: =N13*(1+'Model Assumptions'!C11)/('Model Assumptions'!C13-'Model Assumptions'!C11) -> 43787.171
A15: Present Value of Free Cash Flows | E15: =E13/(1+'Model Assumptions'!$C$13)^('NPV Calculation'!E6-'NPV Calculation'!$D$6) -> -828.98253 | F15: =F13/(1+'Model Assumptions'!$C$13)^('NPV Calculation'!F6-'NPV Calculation'!$D$6) -> -994.60954 | G15: =G13/(1+'Model Assumptions'!$C$13)^('NPV Calculation'!G6-'NPV Calculation'!$D$6) -> -503.74302 | H15: =H13/(1+'Model Assumptions'!$C$13)^('NPV Calculation'!H6-'NPV Calculation'!$D$6) -> -557.12908 | I15: =I13/(1+'Model Assumptions'!$C$13)^('NPV Calculation'!I6-'NPV Calculation'!$D$6) -> -23.249011 | J15: =J13/(1+'Model Assumptions'!$C$13)^('NPV Calculation'!J6-'NPV Calculation'!$D$6) -> 416.31332 | K15: =K13/(1+'Model Assumptions'!$C$13)^('NPV Calculation'!K6-'NPV Calculation'!$D$6) -> 645.23158 | L15: =L13/(1+'Model Assumptions'!$C$13)^('NPV Calculation'!L6-'NPV Calculation'!$D$6) -> 762.70917 | ... N15: =N13/(1+'Model Assumptions'!$C$13)^('NPV Calculation'!N6-'NPV Calculation'!$D$6) -> 583.66044 | O15: =O13/(1+'Model Assumptions'!$C$13-'Model Assumptions'!$C$14)^('NPV Calculation'!N6-'NPV Calculation'!$D$6) -> 4854.7455
A16: Sum of PV Cash Flows | D16: =SUM(E15:O15) -> 5028.4471
A18: Cost of Project - Debt | E18: =IF(-'Financial Model'!D143<0,-'Financial Model'!D143,0) -> -1100 | F18: =IF(-'Financial Model'!E143<0,-'Financial Model'!E143,0) -> -1400 | G18: =IF(-'Financial Model'!F143<0,-'Financial Model'!F143,0) -> 0 | H18: =IF(-'Financial Model'!G143<0,-'Financial Model'!G143,0) -> 0 | I18: =IF(-'Financial Model'!H143<0,-'Financial Model'!H143,0) -> 0 | J18: =IF(-'Financial Model'!I143<0,-'Financial Model'!I143,0) -> 0 | K18: =IF(-'Financial Model'!J143<0,-'Financial Model'!J143,0) -> 0 | L18: =IF(-'Financial Model'!K143<0,-'Financial Model'!K143,0) -> 0 | ... N18: =IF(-'Financial Model'!M143<0,-'Financial Model'!M143,0) -> 0
A19: Cost of Project - Equity | E19: =IF(-'Financial Model'!D144<0,-'Financial Model'!D144,0) -> 0 | F19: =IF(-'Financial Model'!E144<0,-'Financial Model'!E144,0) -> -500 | G19: =IF(-'Financial Model'!F144<0,-'Financial Model'!F144,0) -> -1600 | H19: =IF(-'Financial Model'!G144<0,-'Financial Model'!G144,0) -> -900 | I19: =IF(-'Financial Model'!H144<0,-'Financial Model'!H144,0) -> -50 | J19: =IF(-'Financial Model'!I144<0,-'Financial Model'!I144,0) -> 0 | K19: =IF(-'Financial Model'!J144<0,-'Financial Model'!J144,0) -> 0 | L19: =IF(-'Financial Model'!K144<0,-'Financial Model'!K144,0) -> 0 | ... N19: =IF(-'Financial Model'!M144<0,-'Financial Model'!M144,0) -> 0
B20: Total Capital Expenditures | E20: =IF(-'Financial Model'!D145<0,-'Financial Model'!D145,0) -> -1100 | F20: =IF(-'Financial Model'!E145<0,-'Financial Model'!E145,0) -> -1900 | G20: =IF(-'Financial Model'!F145<0,-'Financial Model'!F145,0) -> -1600 | H20: =IF(-'Financial Model'!G145<0,-'Financial Model'!G145,0) -> -900 | I20: =IF(-'Financial Model'!H145<0,-'Financial Model'!H145,0) -> -50 | J20: =IF(-'Financial Model'!I145<0,-'Financial Model'!I145,0) -> 0 | K20: =IF(-'Financial Model'!J145<0,-'Financial Model'!J145,0) -> 0 | L20: =IF(-'Financial Model'!K145<0,-'Financial Model'!K145,0) -> 0 | ... N20: =IF(-'Financial Model'!M145<0,-'Financial Model'!M145,0) -> 0
A22: Present Value of Project Costs | E22: =E20/(1+$H$28)^(E6-$D$6) -> -1043.8909 | F22: =F20/(1+$H$28)^(F6-$D$6) -> -1711.112 | G22: =G20/(1+$H$28)^(G6-$D$6) -> -1367.4367 | H22: =H20/(1+$H$28)^(H6-$D$6) -> -729.9484 | I22: =I20/(1+$H$28)^(I6-$D$6) -> -38.484165 | J22: =J20/(1+$H$28)^(J6-$D$6) -> 0 | K22: =K20/(1+$H$28)^(K6-$D$6) -> 0 | L22: =L20/(1+$H$28)^(L6-$D$6) -> 0 | ... N22: =N20/(1+$H$28)^(N6-$D$6) -> 0
A23: Sum of PV Project Costs | D23: =SUM(E22:N22) -> -4890.872
A25: NPV | D25: =D16+D23 -> 137.57504
E26: =E16 -> 0
A28: (1) | B28: Discounted at 30 year US T Bond rate. | H28: 0.05375

Sheet End Model

Sheet Goldman Integrated Model
A1: Exhibit 4 Goldman Integrated Model
A3: Sovereign Yield Spread | H3: New Bank Cost of Capital
B4: Ukraine | C4: US | D4: Sovereign | E4: Date of Ukrainian Issue
A5: 98 day/90 day | B5: 0.175 | C5: 0.0483 | D5: =B5-C5 -> 0.1267 | E5: 36942 | H5: Beta x Risk Premium | K5: =D22*C24 -> 0.0578
A6: 126-day/4 mo. | B6: 0.1698 | C6: 0.0475 | D6: =B6-C6 -> 0.1223 | E6: 36950 | H6: +
A7: 182 day/180 day | B7: 0.189 | C7: 0.0469 | D7: =B7-C7 -> 0.1421 | E7: 36942 | H7: Risk free Rate | K7: =B11 -> 0.045
A8: 217-day/7 mo. | B8: 0.1797 | C8: 0.0467 | D8: =B8-C8 -> 0.133 | E8: 36950 | H8: +
D9: =AVERAGE(D5:D8) -> 0.131025 | H9: Sovereign Yield Spread | K9: =D9 -> 0.131025
H10: Total CoC | K10: =SUM(K5:K9) -> 0.233825
A11: Risk-free Rate | B11: 0.045 | C11: Based on 1 year Treasury Bond
A14: Estimated Market Beta
A15: Regional Banks | D15: 0.67 | E15: Yardville National Bank
D16: 0.75 | E16: Bank of the Ozarks
D17: 0.31 | E17: Farquier Bankshares Inc
D18: 0.72 | E18: Belmont Bancorp
D19: 0.44 | E19: Acadiana BancShares, Inc.
A20: Ave. Reg. Bank Beta | D20: =AVERAGE(D15:D19) -> 0.578
A21: Premium for Microfinancing | D21: x 2 | E21: Accounts for elevated risk of microfinancing
A22: Overall Estimated Beta | D22: =D20*2 -> 1.156
A24: Historical US Risk Premium | C24: 0.05 | D24: Approximation
