Workbook
Name Advertising: 'CASHnew.XLS'!$N$22
Name Baked_Goods_Sales: 'CASHnew.XLS'!#REF!
Name Baking_Inventory: 'CASHnew.XLS'!$N$18
Name Bank_Fees: 'CASHnew.XLS'!$N$24
Name Bank_Fees: 'INC-STMT.XLS'!$N$33
Name Consignment_Sales: 'CASHnew.XLS'!#REF!
Name Cost_of_Sales: 'CASH_YR2.XLS'!$N$18:$N$24
Name Cost_of_Sales: 'CASH_YR3.XLS'!$N$20:$N$26
Name Cost_of_Sales: 'CASHnew.XLS'!$N$16:$N$22
Name Cost_of_Sales: 'INC-STMT.XLS'!$N$26:$N$31
Name Courses: 'CASHnew.XLS'!#REF!
Name depreciables: 'CASHnew.XLS'!$N$15:$N$15
Name depreciables: 'INC-STMT.XLS'!$N$25:$N$25
Name Drawings: 'CASHnew.XLS'!$N$34
Name Drawings: 'F-BALANC.XLS'!$N$42
Name Equipment: 'CASHnew.XLS'!$N$15:$N$15
Name Equipment: 'F-BALANC.XLS'!$N$19:$N$20
Name Equipment_Depreciation: 'F-BALANC.XLS'!$F$5
Name Fixed_Assets: 'F-BALANC.XLS'!$B$14:$B$15
Name Fixed_Assets: 'INC-STMT.XLS'!$B$20:$B$21
Name Fixed_Costs: 'CASH_YR2.XLS'!$N$22:$N$31,'CASH_YR2.XLS'!$N$33
Name Fixed_Costs: 'CASH_YR3.XLS'!$N$24:$N$33,'CASH_YR3.XLS'!$N$35
Name Fixed_Costs: 'CASHnew.XLS'!$N$22:$N$31,'CASHnew.XLS'!$N$33
Name Fixed_Costs: 'F-BALANC.XLS'!$N$26:$N$37,'F-BALANC.XLS'!$N$39
Name Fixed_Costs: 'INC-STMT.XLS'!$N$29:$N$38,'INC-STMT.XLS'!$N$40
Name Improvements: 'CASHnew.XLS'!#REF!
Name Improvements: 'F-BALANC.XLS'!$N$21
Name Insurance: 'CASHnew.XLS'!$N$26
Name Insurance: 'INC-STMT.XLS'!$N$35
Name Inventory_99: 'F-BALANC.XLS'!$B$9:$B$10
Name Leasehold_Depreciation: 'F-BALANC.XLS'!$H$3
Name Legal__accntng_costs: 'CASHnew.XLS'!$N$25
Name Licenses: 'CASHnew.XLS'!$N$27
Name Loan_Payment: 'CASHnew.XLS'!$N$32
Name Loan_Payment: 'F-BALANC.XLS'!$N$40
Name loans: 'CASHnew.XLS'!$N$8:$N$9
Name loans: 'F-BALANC.XLS'!$N$11:$N$13
Name Misc.: 'CASHnew.XLS'!$N$33
Name Net_Cash: 'CASHnew.XLS'!$N$39
Name Other_Sales_Costs: 'CASHnew.XLS'!$N$20:$N$21
Name Rent: 'CASHnew.XLS'!$N$29
Name Repairs___Maint.: 'CASHnew.XLS'!$N$31
Name sales: 'CASHnew.XLS'!$N$5:$N$6
Name sales: 'INC-STMT.XLS'!$N$6:$N$8
Name Tea_Inventory: 'CASHnew.XLS'!$N$17
Name Tea_Room_Sales: 'CASHnew.XLS'!$N$5
Name Telephone: 'CASHnew.XLS'!$N$28
Name Utilities: 'CASHnew.XLS'!$N$30
Name Yarn_Inventory: 'CASHnew.XLS'!$N$16
Name Yarn_Price_Ratio: 'F-BALANC.XLS'!$H$7
Name Yarn_Shop_Sales: 'CASHnew.XLS'!$N$6

Sheet CASHnew.XLS
A1: Projected Cash Flow for A. Sample
A2: November 2001 - October 2002
B3: NOV | C3: DEC | D3: JAN | E3: FEB | F3: MAR | G3: APR | H3: MAY | I3: JUN | J3: JUL | K3: AUG | L3: SEP | M3: OCT | N3: TOTAL
A4: REVENUE
A5: Sales | N5: =SUM(B5:M5) -> 0
A6: Retail Sales | N6: =SUM(B6:M6) -> 0
A8: PARO Loan | N8: =SUM(B8:M8) -> 0
N9: =SUM(B9) -> 0
A10: Cash Equity | N10: =SUM(B10:M10) -> 0
A11: Total Cash In | B11: =SUM(B5:B10) -> 0 | C11: =SUM(C5:C10) -> 0 | D11: =SUM(D5:D10) -> 0 | E11: =SUM(E5:E10) -> 0 | F11: =SUM(F5:F10) -> 0 | G11: =SUM(G5:G10) -> 0 | H11: =SUM(H5:H10) -> 0 | I11: =SUM(I5:I10) -> 0 | ... M11: =SUM(M5:M10) -> 0 | N11: =SUM(B11:M11) -> 0
A13: EXPENSES
A14: Retail Inventory | N14: =SUM(B14:M14) -> 0
A15: Equipment& Software | N15: =SUM(B15:M15) -> 0
A16: Product Supplies | N16: =SUM(B16:M16) -> 0
A17: Office Supplies | N17: =SUM(B17:M17) -> 0
A18: Internet | N18: =SUM(B18:M18) -> 0
A19: Loan Maintenance Fee | N19: =SUM(B19:M19) -> 0
A20: Travel & Parking | N20: =SUM(B20:M20) -> 0
A21: Membership Fees | N21: =SUM(B21:M21) -> 0
A22: Seminars | N22: =SUM(B22:M22) -> 0
A23: Advertising | N23: =SUM(B23:M23) -> 0
A24: Bank Fees | N24: =SUM(B24:M24) -> 0
A25: Bookkeeping | N25: =SUM(B25:M25) -> 0
... A34: Drawings | N34: =SUM(B34:M34) -> 0
A36: Total Expenses | B36: =SUM(B14:B34) -> 0 | C36: =SUM(C14:C34) -> 0 | D36: =SUM(D14:D34) -> 0 | E36: =SUM(E14:E34) -> 0 | F36: =SUM(F14:F34) -> 0 | G36: =SUM(G14:G34) -> 0 | H36: =SUM(H14:H34) -> 0 | I36: =SUM(I14:I34) -> 0 | ... N36: =SUM(N14:N34) -> 0
A38: Net Cash | B38: =SUM(B11-B36) -> 0 | C38: =SUM(C11-C36) -> 0 | D38: =SUM(D11-D36) -> 0 | E38: =SUM(E11-E36) -> 0 | F38: =SUM(F11-F36) -> 0 | G38: =SUM(G11-G36) -> 0 | H38: =SUM(H11-H36) -> 0 | I38: =SUM(I11-I36) -> 0 | ... N38: =SUM(N11-N36) -> 0
A39: Surplus (Deficit) | B39: =B38 -> 0 | C39: =C38 -> 0 | D39: =D38 -> 0 | E39: =E38 -> 0 | F39: =F38 -> 0 | G39: =G38 -> 0 | H39: =H38 -> 0 | I39: =I38 -> 0 | ... M39: =M38 -> 0 | N39: =SUM(B39:M39) -> 0
A41: Cumulative | B41: =B39 -> 0 | C41: =SUM(B41,C38) -> 0 | D41: =SUM(C41,D38) -> 0 | E41: =SUM(D41,E38) -> 0 | F41: =SUM(E41,F38) -> 0 | G41: =SUM(F41,G38) -> 0 | H41: =SUM(G41,H38) -> 0 | I41: =SUM(H41,I38) -> 0 | J41: =SUM(I41,J38) -> 0 | ... M41: =SUM(L41,M38) -> 0
A44: *No principal payment required in Year 1, only interest (at 9.5%)

Sheet F-BALANC.XLS
A1: Projected Balance Sheet as of October 31,2002
A3: ASSETS | E3: LIABILITIES
A5: Current Assets: | E5: Loans Payable | F5: 0
A6: Cash | B6: ='CASHnew.XLS'!M41 -> 0 | E6: Accounts Payable | F6: 0
A7: Inventory | B7: 0 | E7: Total Liabilities
E9: OWNER'S EQUITY
A10: Accounts Receivable | B10: 0
A11: TOTAL CURRENT ASSETS | C11: =SUM(B6:B10) -> 0 | E11: Capital, A. Sample | F11: 0
A13: Fixed Assets: | E13: Income for the Year | F13: ='INC-STMT.XLS'!B31 -> 0
A14: Location Improvements | B14: 0 | H14: =SUM(G11:G13)+G5+G6 -> 0
A15: Equipment | B15: 0 | E15: Less Owner's Drawings | F15: =CASHnew.XLS!Drawings -> 0
A16: TOTAL FIXED ASSETS | C16: =SUM(B14:B15) -> 0
A18: TOTAL ASSETS | C18: =C11+B14+B15 -> 0 | E18: TOTAL LIABILITIES/OWNER'S EQUITY | G18: =SUM(G14-F15) -> 0
A21: The Balance Sheet as of October 31, 2003
A23: ASSETS | E23: LIABILITIES
A25: Current Assets: | E25: Loans Payable | F25: 0
A26: Cash | B26: ='CASH_YR2.XLS'!$N$41 -> 0 | E26: Accounts Payable | F26: 0
A27: Inventory | B27: 0 | E27: TOTAL LIABILITES | G27: =SUM(F25:F26) -> 0
A29: TOTAL CURRENT ASSETS | C29: =SUM(B26:B27) -> 0 | E29: OWNER'S EQUITY
E31: Capital, A. Sample | F31: ='CASH_YR2.XLS'!$N$10-SUM(F5:F6)+SUM(B9:B10)+SUM(B14:B15) -> 0
A32: Fixed Assets: | E32: Income for the year | F32: ='INC-STMT.XLS'!$C$31 -> 0
A33: Location Improvements | B33: 0 | G33: =SUM(F31:F32)+G27 -> 0
A34: Equipment | B34: 0 | E34: Less Owner's Drawings | F34: ='CASH_YR2.XLS'!N34 -> 0
A35: TOTAL FIXED ASSETS | C35: =SUM(B33:B34) -> 0
A37: TOTAL ASSETS | C37: =C31+B33+B34 -> 0 | E37: TOTAL LIABILITIES/OWNER'S EQUITY | G37: =G33-F34 -> 0
A39: The Balance Sheet as of October 31, 2004
A41: ASSETS | E41: LIABILITIES
A43: Current Assets: | E43: Loans Payable | F43: 0
A44: Cash | B44: ='CASH_YR3.XLS'!$N$43 -> 0 | E44: Accounts Payable
A45: Inventory | B45: 0 | E45: TOTAL LIABILITIES | G45: =SUM(G43:G44) -> 0
E47: OWNER'S EQUITY
A48: TOTAL CURRENT ASSETS
E49: Capital, A. Sample | F49: ='CASH_YR3.XLS'!N12-SUM(F25:F26)+SUM(B27:B29)+SUM(B33:B34) -> 0
A50: Fixed Assets: | E50: Income for the year | F50: ='INC-STMT.XLS'!$D$31 -> 0
A51: Location Improvements | B51: 0 | G51: =SUM(F49:F50)+F43 -> 0
A52: Equipment | B52: 0 | E52: Less Owner's Drawings | F52: 0
A53: TOTAL FIXED ASSETS
A55: TOTAL ASSETS | C55: =C49+B51+B52 -> 0 | E55: TOTAL LIABILITIES/OWNER'S EQUITY | G55: =G51-F52 -> 0

Sheet INC-STMT.XLS
A1: Projected Income Statement
A2: Year ending October 31, | B2: 2002 | C2: 2003 | D2: 2004
A4: SALES | B4: =Tea_Room_Sales+Yarn_Shop_Sales -> 0 | C4: =SUM('CASH_YR2.XLS'!$N$5:$N$6) -> 0 | D4: =SUM('CASH_YR3.XLS'!$N$6:$N$8) -> 0
A5: Cost of Goods Sold | B5: =(Yarn_Shop_Sales*0.5)+Yarn_Inventory -> 0 | C5: ='CASH_YR2.XLS'!N16+('CASH_YR2.XLS'!N6*0.5) -> 0 | D5: ='CASH_YR3.XLS'!N18+'CASH_YR3.XLS'!N7*0.5 -> 0
A6: GROSS PROFIT | B6: =SUM(B4-B5) -> 0 | C6: =SUM(C4-C5) -> 0 | D6: =SUM(D4-D5) -> 0
A8: OPERATING EXPENSES
A10: Product Supplies | B10: ='CASHnew.XLS'!N17 -> 0 | C10: ='CASH_YR2.XLS'!N17 -> 0 | D10: ='CASH_YR3.XLS'!N19 -> 0
A11: Office Supplies | B11: ='CASHnew.XLS'!N18 -> 0 | C11: ='CASH_YR2.XLS'!N18 -> 0 | D11: ='CASH_YR3.XLS'!N20 -> 0
A12: Internet | B12: ='CASHnew.XLS'!N19 -> 0 | C12: ='CASH_YR2.XLS'!N19 -> 0 | D12: ='CASH_YR3.XLS'!N21 -> 0
A13: Loan Maintenance Fee | B13: ='CASHnew.XLS'!N20 -> 0 | C13: ='CASH_YR2.XLS'!N20 -> 0 | D13: ='CASH_YR3.XLS'!N22 -> 0
A14: Travel & Parking | B14: ='CASHnew.XLS'!N21 -> 0 | C14: ='CASH_YR2.XLS'!N21 -> 0 | D14: ='CASH_YR3.XLS'!N23 -> 0
A15: Membership Fees | B15: ='CASHnew.XLS'!N22 -> 0 | C15: ='CASH_YR2.XLS'!N22 -> 0 | D15: ='CASH_YR3.XLS'!N24 -> 0
A16: Seminars | B16: ='CASHnew.XLS'!N23 -> 0 | C16: ='CASH_YR2.XLS'!N23 -> 0 | D16: ='CASH_YR3.XLS'!N25 -> 0
A17: Advertising | B17: ='CASHnew.XLS'!N24 -> 0 | C17: ='CASH_YR2.XLS'!N24 -> 0 | D17: ='CASH_YR3.XLS'!N26 -> 0
A18: Bank Fees | B18: ='CASHnew.XLS'!N25 -> 0 | C18: ='CASH_YR2.XLS'!N25 -> 0 | D18: ='CASH_YR3.XLS'!N27 -> 0
A19: Bookkeeping | B19: ='CASHnew.XLS'!N26 -> 0 | C19: ='CASH_YR2.XLS'!N26 -> 0 | D19: ='CASH_YR3.XLS'!N28 -> 0
A20: Insurance | B20: ='CASHnew.XLS'!N27 -> 0 | C20: ='CASH_YR2.XLS'!N27 -> 0 | D20: ='CASH_YR3.XLS'!N29 -> 0
A21: Licenses | B21: ='CASHnew.XLS'!N28 -> 0 | C21: ='CASH_YR2.XLS'!N28 -> 0 | D21: ='CASH_YR3.XLS'!N30 -> 0
... A23: Rent | B23: ='CASHnew.XLS'!N30 -> 0 | C23: ='CASH_YR2.XLS'!N30 -> 0 | D23: ='CASH_YR3.XLS'!N32 -> 0
A24: Celluar Phone | B24: =Misc. -> 0 | C24: ='CASH_YR2.XLS'!N33 -> 0 | D24: ='CASH_YR3.XLS'!N35 -> 0
A25: Utilities | B25: =Misc. -> 0 | C25: ='CASH_YR2.XLS'!N33 -> 0 | D25: ='CASH_YR3.XLS'!N35 -> 0
A26: Depreciation*
A27: Interest**
A29: TOTAL EXPENSES | B29: =SUM(B10:B27) -> 0 | C29: =SUM(C10:C27) -> 0 | D29: =SUM(D10:D27) -> 0
A31: NET PROFIT (before taxes) | B31: =SUM(B6-B29) -> 0 | C31: =SUM(C6-C29) -> 0 | D31: =SUM(D6-D29) -> 0
A34: *Deprecation of Location Improvements at 20%
A35: Depreciation of Equipment at 30%
A37: ** Interest only in Year 1, and
A38: Year 2 & 3 interest payable at 8.5% for a term of 36months

Sheet CASH_YR2.XLS
A1: Projected Cash Flow for A. Sample
A2: Year Two-November 1 2002 - October 31 2003
B3: NOV | C3: DEC | D3: JAN | E3: FEB | F3: MAR | G3: APR | H3: MAY | I3: JUN | J3: JUL | K3: AUG | L3: SEP | M3: OCT | N3: TOTAL
A4: REVENUE
A5: Sales | N5: =SUM(B5:M5) -> 0
A6: Retail Sales | N6: =SUM(B6:M6) -> 0
N7: =SUM(B7:M7) -> 0
N8: =SUM(B8:M8) -> 0
N9: =SUM(B9:M9) -> 0
A10: Cash Equity | N10: =SUM(B10:M10) -> 0
A11: Total Cash In | N11: =SUM(B11:M11) -> 0
A13: EXPENSES
A14: Retail Inventory | N14: =SUM(B14:M14) -> 0
A15: Equipment & Software | N15: =SUM(B15:M15) -> 0
A16: Product Supplies | N16: =SUM(B16:M16) -> 0
A17: Office Supplies | N17: =SUM(B17:M17) -> 0
A18: Internet | N18: =SUM(B18:M18) -> 0
A19: Loan Maintenance fee | N19: =SUM(B19:M19) -> 0
A20: Travel & Parking | N20: =SUM(B20:M20) -> 0
A21: Membership Fees | N21: =SUM(B21:M21) -> 0
A22: Seminars | N22: =SUM(B22:M22) -> 0
A23: Advertising | N23: =SUM(B23:M23) -> 0
A24: Bank Fees | N24: =SUM(B24:M24) -> 0
A25: Bookkeeping
A26: Insurance | N26: =SUM(B26:M26) -> 0
A27: Licences | N27: =SUM(C27:M27) -> 0
A28: Telephone | N28: =SUM(B28:M28) -> 0
A29: Rent | N29: =SUM(B29:M29) -> 0
A30: Utilities | N30: =SUM(B30:M30) -> 0
A31: Location Improvement | N31: =SUM(B31:M31) -> 0
A32: Loan Payment | N32: =SUM(B32:M32) -> 0
A33: Cellular Phone | N33: =SUM(B33:M33) -> 0
A34: Drawings | N34: =SUM(B34:M34) -> 0
N35: =SUM(B35:M35) -> 0
N36: =SUM(B36:M36) -> 0
A38: Total Expenses | B38: =SUM(B14:B36) -> 0 | C38: =SUM(C14:C36) -> 0 | D38: =SUM(D14:D36) -> 0 | E38: =SUM(E14:E36) -> 0 | F38: =SUM(F14:F36) -> 0 | G38: =SUM(G14:G36) -> 0 | H38: =SUM(H14:H36) -> 0 | I38: =SUM(I14:I36) -> 0 | ... N38: =SUM(N14:N36) -> 0
A40: Net Cash | B40: =SUM(B11-B38) -> 0 | C40: =SUM(C11-C38) -> 0 | D40: =SUM(D11-D38) -> 0 | E40: =SUM(E11-E38) -> 0 | F40: =SUM(F11-F38) -> 0 | G40: =SUM(G11-G38) -> 0 | H40: =SUM(H11-H38) -> 0 | I40: =SUM(I11-I38) -> 0 | ... N40: =SUM(N11-N38) -> 0
A41: Surplus (Deficit) | B41: =B40 -> 0 | C41: =C40 -> 0 | D41: =D40 -> 0 | E41: =E40 -> 0 | F41: =F40 -> 0 | G41: =G40 -> 0 | H41: =H40 -> 0 | I41: =I40 -> 0 | ... M41: =M40 -> 0 | N41: =SUM(B41:M41) -> 0
A43: Cumulative | B43: =B41 -> 0 | C43: =SUM(B43,C40) -> 0 | D43: =SUM(C43,D40) -> 0 | E43: =SUM(D43,E40) -> 0 | F43: =SUM(E43,F40) -> 0 | G43: =SUM(F43,G40) -> 0 | H43: =SUM(G43,H40) -> 0 | I43: =SUM(H43,I40) -> 0 | J43: =SUM(I43,J40) -> 0 | ... M43: =SUM(L43,M40) -> 0

Sheet CASH_YR3.XLS
A1: Projected Cash Flow for A. Sample
A2: Year Three- November 1 2003 - October 31 2004
B4: NOV | C4: DEC | D4: JAN | E4: FED | F4: MAR | G4: APR | H4: MAY | I4: JUN | J4: JUL | K4: AUG | L4: SEPT | M4: OCT | N4: TOTAL
A5: REVENUE
A6: Sales | N6: =SUM(B6:M6) -> 0
A7: Retail Sales | N7: =SUM(B7:M7) -> 0
N8: =SUM(B8:M8) -> 0
N10: =SUM(B10) -> 0
N11: =SUM(B11) -> 0
A12: Cash Equity | N12: =SUM(B12) -> 0
A13: Total Cash In | N13: =SUM(B13:M13) -> 0
A15: EXPENSES
A16: Retail Inventory | N16: =SUM(B16:M16) -> 0
A17: Equipment&Software | N17: =SUM(B17:M17) -> 0
A18: Product Supplies | N18: =SUM(B18:M18) -> 0
A19: Office Supplies | N19: =SUM(B19:M19) -> 0
A20: Internet | N20: =SUM(B20:M20) -> 0
A21: Loan Maintenance fee | N21: =SUM(B21:M21) -> 0
A22: Travel & Parking | N22: =SUM(B22:M22) -> 0
A23: Membership Fees | N23: =SUM(B23:M23) -> 0
A24: Seminars | N24: =SUM(B24:M24) -> 0
A25: Advertising | N25: =SUM(B25:M25) -> 0
A26: Bank Fees | N26: =SUM(B26:M26) -> 0
A27: Bookkeeping
A28: Insurance | N28: =SUM(B28:M28) -> 0
A29: Licenses | N29: =SUM(B29:M29) -> 0
A30: Telephone | N30: =SUM(B30:M30) -> 0
A31: Rent | N31: =SUM(B31:M31) -> 0
A32: Utilities | N32: =SUM(B32:M32) -> 0
A33: Location Improvement | N33: =SUM(B33:M33) -> 0
A34: Loan Payment | N34: =SUM(B34:M34) -> 0
A35: Cellular Phone | N35: =SUM(B35:M35) -> 0
A36: Drawings | N36: =SUM(B36:M36) -> 0
N37: =SUM(B37:M37) -> 0
N38: =SUM(B38:M38) -> 0
A40: Total Expenses | B40: =SUM(B16:B38) -> 0 | C40: =SUM(C16:C38) -> 0 | D40: =SUM(D16:D38) -> 0 | E40: =SUM(E16:E38) -> 0 | F40: =SUM(F16:F38) -> 0 | G40: =SUM(G16:G38) -> 0 | H40: =SUM(H16:H38) -> 0 | I40: =SUM(I16:I38) -> 0 | ... N40: =SUM(N16:N38) -> 0
A42: Net Cash | B42: =SUM(B13-B40) -> 0 | C42: =SUM(C13-C40) -> 0 | D42: =SUM(D13-D40) -> 0 | E42: =SUM(E13-E40) -> 0 | F42: =SUM(F13-F40) -> 0 | G42: =SUM(G13-G40) -> 0 | H42: =SUM(H13-H40) -> 0 | I42: =SUM(I13-I40) -> 0 | ... N42: =SUM(N13-N40) -> 0
A43: Surplus (Deficit) | B43: =B42 -> 0 | C43: =C42 -> 0 | D43: =D42 -> 0 | E43: =E42 -> 0 | F43: =F42 -> 0 | G43: =G42 -> 0 | H43: =H42 -> 0 | I43: =I42 -> 0 | ... M43: =M42 -> 0 | N43: =SUM(B43:M43) -> 0
A45: Cumulative | B45: =B43 -> 0 | C45: =SUM(B45,C42) -> 0 | D45: =SUM(C45,D42) -> 0 | E45: =SUM(D45,E42) -> 0 | F45: =SUM(E45,F42) -> 0 | G45: =SUM(F45,G42) -> 0 | H45: =SUM(G45,H42) -> 0 | I45: =SUM(H45,I42) -> 0 | J45: =SUM(I45,J42) -> 0 | ... M45: =SUM(L45,M42) -> 0
