Workbook

Sheet Project summary
A1: Activity Proposal Form (APF)
A2: This form should be completed in line with the University's Costing & Pricing guidelines and sent to Accounting Services and RIS (Tanya Davies)
A3: University details
A4: Project Proposer/Manager | G4: Tel
A5: School/Support Service | G5: Email
A6: Name of activity
A7: Rationale for undertaking activity
A11: Client Organisation
A12: Organisation Name | G12: Tel
A13: Name of contact | G13: Email
A14: Position within organisation
A15: Address
H16: Post Code
A17: Is Bournemouth University the lead organisation | E17: If no, who is?
A19: Timing | E19: Business Activity Area
A20: Proposed start date | E20: Students & Learning | I20: [ ]
A21: Completion date | E21: Research | I21: [ ]
A22: Duration | E22: Enterprise | I22: [ ]
A23: Account Code | E23: Other | I23: [ ]
A25: Specialist Advice
A26: Please put an X in the box to indicate which of the following are relevant to this proposal
A27: You are strongly advised to consult with the relevant named staff (see comment boxes)
A29: IPR/Copyright/Exclusivity/Confidentiality | B29: [ ] | C29: Procurement | F29: [ ]
A30: Tax/VAT issues | B30: [ ] | C30: Marketing | F30: [ ]
A31: General Costings | B31: [ ] | C31: Learning Resources | F31: [ ]
A32: Insurance/indemnity/liability | B32: [ ] | C32: Health & Safety | F32: [ ]
A33: Space requirements | B33: [ ] | C33: IT Equipment/Services | F33: [ ]
A34: Staffing/Evaluations/Recruitment | B34: [ ] | C34: Others please state
A36: Risk Assessment (financial, reputation etc)
A41: Financial Summary (Note; this section is automatically linked to detailed financial account page 2, and does not need to be separately filled in)
A43: Price to client | B43: =SUM('Financial summary'!J4) -> 1750
A45: Total staff costs | B45: =SUM('Financial summary'!I44) -> 696.08
A46: Total non pay costs | B46: =SUM('Financial summary'!I61) -> 100
A47: Total expenditure | B47: =SUM(B45:B46) -> 796.08
A49: Corporate overheads | B49: =SUM('Financial summary'!I63) -> 398.04 | D49: Overhead recovery achieved | G49: ='Financial summary'!$I$64 -> 0.5
A50: Total cost of activity | B50: =SUM(B47:B49) -> 1194.12
A51: Surplus/deficit | B51: =SUM(B43-B50) -> 555.88 | D51: Profit margin | G51: ='Financial summary'!$J$67 -> 0.31764571
A53: Proposal Authorisation
A55: I confirm that this proposal has been developed in line with the University's Costing and Pricing procedures and that the benefits, costs and outcomes are
A56: accurately represented.
A58: Proposer's Signature | H58: Date
A60: Authorised Contract Signatory | H60: Date
A62: A copy of the bid is attached | B62: YES | C62: NO
A64: Confirmation of proposal acceptance
A66: I confirm that the proposal has been accepted by the client. Any changes to the profile of the proposal are attached
A68: Proposer's Signature | H68: Date
A70: Authorised Contract Signatory | H70: Date
A72: A copy of the contract is attached | B72: Yes | C72: No

Sheet Staffing plan
A1: Staffing Plan (Note: all staff costs should include on-costs.e.g. Pension, National Insurance
A3: Account code | B3: Member of staff's name | C3: Nature of work to be undertaken | D3: Hours/days/FTE | E3: Cost per hr/day/FTE | F3: Total cost | G3: Payment to staff
A4: Existing staff to contribute as part of their balanced workload
A5: 22 xx | B5: Employed academic
A6: 2210 | B6: J Bloggs | C6: Consultancy | D6: 1 day | E6: 210.54 | F6: 210.54 | G6: None
B8: Total employed academic | F8: =SUM(F6:F7) -> 210.54
A9: 23 xx | B9: Employed researcher
B11: Total employed research
A12: 24 xx | B12: Employed tech/demo
B14: Total employed tech/demo
A15: 25 xx | B15: Employed administrative
B17: Total employed administrative
A18: Existing staff to contribute - covered by replacement funding
A19: 22 xx | B19: Employed academic
B22: Total employed administrative
A23: 23 xx | B23: Employed researcher
B25: Total employed research
A26: 24 xx | B26: Employed tech\demo
B28: Total employed tech/demo
A29: 25 xx | B29: Employed administrative
B31: Total employed administrative
A32: Existing staff to contribute with additional payments made
A33: 22 xx | B33: Employed academic FT
A34: 2210 | B34: J Smith | C34: Consultancy | D34: 1 day | E34: 210.54 | F34: 210.54 | G34: 210.54
B35: C Smith | C35: Consultancy | D35: 0.5 day | E35: 350 | F35: =E35*0.5 -> 175 | G35: 175
B36: Total employed FT academic | F36: =SUM(F34:F35) -> 385.54
A37: 22 xx | B37: Employed academic PT
B39: Total employed PT academic
A40: 23 xx | B40: Employed researcher
B42: Total employed research
A43: 24 xx | B43: Employed tech\demo
B45: Total employed tech/demo
A46: 25 xx | B46: Employed administrative
B48: Total employed administrative
A49: Additional staff to be engaged
A50: 22 xx | B50: Employed academic FT
B52: Total employed FT academic
A53: 22 xx | B53: Employed academic PT
B55: Total employed PT academic
A56: 23 xx | B56: Employed researcher
B58: Total employed research
A59: 24 xx | B59: Employed tech\demo
B61: Total employed tech/demo
A62: 25 xx | B62: Employed administrative
B64: Total employed administrative
A65: Non-contract staff e.g.
A66: 33 xx | B66: Bought-in (agency admin)
A67: 3323 | B67: D Duck | C67: Admin support | D67: 1 day | E67: 100 | F67: 100 | G67: 100
A68: 33 xx | B68: Bought-in (short term lecturer)

Sheet Financial summary
A1: Financial plan
A2: Details of income and expenditure
I3: COSTING (£) | J3: PRICING (£)
A4: Income to the University (excluding any VAT payment) | J4: =(J10 +J11)+J1 -> 1750
A6: Choose either option (1) or (2)
A7: (1) Discretionary pricing
B8: Number of days of work to be undertaken | G8: 3
B9: Price per day | G9: 550
A10: Total price to the client (excluding expenses) | G10: =G8*G9 -> 1650 | J10: =G10 -> 1650
A11: Estimated expenses to be recovered | G11: 100 | J11: 100
A12: Cost of VAT if applicable | G12: =J4*0.175 -> 306.25
A14: (2) Fixed price (I.e. where the University has little or no discretion on pricing e.g. TCS; some research contracts)
B15: Income to be received | J15: 0
A17: Expenditure
A18: Staffing (Note: all staff costs should include on-costs.e.g. Pension, National Insurance.
B19: Existing staff to contribute as part of their balanced workload
A20: 22 xx | B20: Employed academic | I20: ='Staffing plan'!$F$8 -> 210.54
A21: 23 xx | B21: Employed researcher
A22: 24 xx | B22: Employed tech\demo
A23: 25 xx | B23: Employed administrative
B24: Existing staff to contribute - covered by replacement funding
A25: 22 xx | B25: Employed academic
A26: 23 xx | B26: Employed researcher
A27: 24 xx | B27: Employed tech\demo
A28: 25 xx | B28: Employed administrative
B29: Existing staff to contribute with additional payments made
A30: 22 xx | B30: Employed academic FT | I30: ='Staffing plan'!$F$36 -> 385.54
A31: 22 xx | B31: Employed academic PT
A32: 23 xx | B32: Employed researcher
A33: 24 xx | B33: Employed tech\demo
A34: 25 xx | B34: Employed administrative
B35: Additional staff to be engaged
A36: 22 xx | B36: Employed academic FT | I36: ='Staffing plan'!$F$52 -> 0
A37: 22 xx | B37: Employed academic PT
A38: 23 xx | B38: Employed researcher
A39: 24 xx | B39: Employed tech\demo
A40: 25 xx | B40: Employed administrative
B41: Non-contract staff e.g.
A42: 33 xx | B42: Bought-in (agency admin) | I42: ='Staffing plan'!$F$67 -> 100
A43: 33 xx | B43: Bought-in (short term lecturer)
B44: Total staff costs | I44: =SUM(I20:I43) -> 696.08
A45: Non pay costs (attributed to activity)
A46: 3 Other staff costs e.g.
A47: 32 xx | B47: Staff Development
A48: 35 xx | B48: Staff recruitment
A49: 36 xx | B49: Staff travel
A50: 4 Student costs e.g.
A51: 47 xx | B51: Stationery and reprographics | I51: 100
A52: 5 Academic Support
A53: 5 xxx
A54: 6 Administration
A55: 6 xxx
A56: 7 Premises
A57: 7 xxx
A58: Balance sheet
A59: B110 | B59: Capital equipment, IT & other (over £1000)
B61: Total non-pay costs | I61: =SUM(I47:I60) -> 100
B62: Total expenditure (I.e. total staff costs and total non-pay costs) | I62: =I44+I61 -> 796.08
B63: Corporate Overheads (Normally 50%, but see comment box.) | I63: =I62*0.5 -> 398.04
B64: Corporate Overheads achieved | I64: =I63/I62 -> 0.5
B65: Total Costs | G65: = staff + non-staff + overhead = | I65: =SUM(I44+I61+I63) -> 1194.12
B66: Surplus generated (I.e. income - total costs) | J66: =J4-I65 -> 555.88
B67: Margin (I.e. profit divided by total income as a %) | J67: =J66/J4 -> 0.31764571
