Workbook

Sheet Explanation
A1: =Report!A1 -> Summary of Data from CAS Professional Skills Survey 2002
A2: Explanation of Data/Report
A4: Specific Skills
A6: Importance
A7: Average Value of Survey Categories:
A8: 4 | B8: Critical
A9: 3 | B9: Important
A10: 2 | B10: Somewhat
A11: 1 | B11: Low
A12: 0 | B12: Not Important
A14: Where Should Be Taught
A15: % of Total Respondents (338)
A16: Did not show responses that were:
B17: Blank
B18: Not Familiar
B19: Data Error
A20: May not sum to 100% due to exclusion of Blank, Not Familiar, and Data Error.
A22: Use It
A23: Responses to "Have I used this?"
A24: Excluded responses that were:
B25: Blank
B26: Not Familiar
B27: Data Error
A28: Recalculated as % of "I use it" / ("I use it" + "I do not use it")
A31: General Questions
A33: May not sum to 100% due to exclusion of No Opinion, Blank, and Data Error.
A35: Question #4 - respondents were allowed to reply more than once.
B36: Percentages are to total number of replies (653).
B37: Does not sum to 100% due to those that were left blank.

Sheet Report
A1: Summary of Data from CAS Professional Skills Survey 2002
A3: Specific Skills
D5: Where Should Be Taught
A6: Item # | B6: Topic | C6: Importance | D6: Basic Ed | E6: Continuing Ed | F6: Non-CAS | G6: Use It
B8: Basic Mathematics
A9: 1A | B9: Basic Calculus - One Variable | C9: =(4*Data!B8+3*Data!C8+2*Data!D8+1*Data!E8)/(SUM(Data!B8:F8)) -> 2.8867925 | D9: =Data!H8/Data!$J$3 -> 0.48816568 | E9: =Data!I8/Data!$J$3 -> 0.0029585799 | F9: =Data!J8/Data!$J$3 -> 0.43195266 | G9: =Data!L8/(Data!L8+Data!M8) -> 0.7980456
A10: 1B | B10: Basic Calculus - Many Variables | C10: =(4*Data!B9+3*Data!C9+2*Data!D9+1*Data!E9)/(SUM(Data!B9:F9)) -> 2.5 | D10: =Data!H9/Data!$J$3 -> 0.46745562 | E10: =Data!I9/Data!$J$3 -> 0.020710059 | F10: =Data!J9/Data!$J$3 -> 0.43786982 | G10: =Data!L9/(Data!L9+Data!M9) -> 0.55409836
A11: 1C | B11: Basic Differential Equations | C11: =(4*Data!B10+3*Data!C10+2*Data!D10+1*Data!E10)/(SUM(Data!B10:F10)) -> 1.8360129 | D11: =Data!H10/Data!$J$3 -> 0.29585799 | E11: =Data!I10/Data!$J$3 -> 0.047337278 | F11: =Data!J10/Data!$J$3 -> 0.55325444 | G11: =Data!L10/(Data!L10+Data!M10) -> 0.27666667
A12: 1D | B12: Linear Algebra | C12: =(4*Data!B11+3*Data!C11+2*Data!D11+1*Data!E11)/(SUM(Data!B11:F11)) -> 2.5047619 | D12: =Data!H11/Data!$J$3 -> 0.43491124 | E12: =Data!I11/Data!$J$3 -> 0.017751479 | F12: =Data!J11/Data!$J$3 -> 0.4556213 | G12: =Data!L11/(Data!L11+Data!M11) -> 0.63815789
A13: 1E | B13: Algebraic Manipulation of Equations | C13: =(4*Data!B12+3*Data!C12+2*Data!D12+1*Data!E12)/(SUM(Data!B12:F12)) -> 3.5394322 | D13: =Data!H12/Data!$J$3 -> 0.4704142 | E13: =Data!I12/Data!$J$3 -> 0.0029585799 | F13: =Data!J12/Data!$J$3 -> 0.44674556 | G13: =Data!L12/(Data!L12+Data!M12) -> 0.96688742
B15: Probability
A16: 2A | B16: Bayes Theorem | C16: =(4*Data!B15+3*Data!C15+2*Data!D15+1*Data!E15)/(SUM(Data!B15:F15)) -> 3.168254 | D16: =Data!H15/Data!$J$3 -> 0.79289941 | E16: =Data!I15/Data!$J$3 -> 0.01183432 | F16: =Data!J15/Data!$J$3 -> 0.11538462 | G16: =Data!L15/(Data!L15+Data!M15) -> 0.82178218
A17: 2B | B17: Discrete Distributions | C17: =(4*Data!B16+3*Data!C16+2*Data!D16+1*Data!E16)/(SUM(Data!B16:F16)) -> 3.5362776 | D17: =Data!H16/Data!$J$3 -> 0.83136095 | E17: =Data!I16/Data!$J$3 -> 0.0029585799 | F17: =Data!J16/Data!$J$3 -> 0.088757396 | G17: =Data!L16/(Data!L16+Data!M16) -> 0.96052632
A18: 2C | B18: Continuous Univariate Distributions | C18: =(4*Data!B17+3*Data!C17+2*Data!D17+1*Data!E17)/(SUM(Data!B17:F17)) -> 3.4416404 | D18: =Data!H17/Data!$J$3 -> 0.83431953 | E18: =Data!I17/Data!$J$3 -> 0.0059171598 | F18: =Data!J17/Data!$J$3 -> 0.079881657 | G18: =Data!L17/(Data!L17+Data!M17) -> 0.92434211
A19: 2D | B19: Multi-variate Distributions | C19: =(4*Data!B18+3*Data!C18+2*Data!D18+1*Data!E18)/(SUM(Data!B18:F18)) -> 3.2397476 | D19: =Data!H18/Data!$J$3 -> 0.80473373 | E19: =Data!I18/Data!$J$3 -> 0.032544379 | F19: =Data!J18/Data!$J$3 -> 0.082840237 | G19: =Data!L18/(Data!L18+Data!M18) -> 0.77887789
B21: Microeconomics
A22: 3A | B22: Supply, Demand, Market Equilibrium | C22: =(4*Data!B21+3*Data!C21+2*Data!D21+1*Data!E21)/(SUM(Data!B21:F21)) -> 2.9905063 | D22: =Data!H21/Data!$J$3 -> 0.65680473 | E22: =Data!I21/Data!$J$3 -> 0.062130178 | F22: =Data!J21/Data!$J$3 -> 0.20118343 | G22: =Data!L21/(Data!L21+Data!M21) -> 0.69023569
A23: 3B | B23: Comparative Advantage & Trade Gains | C23: =(4*Data!B22+3*Data!C22+2*Data!D22+1*Data!E22)/(SUM(Data!B22:F22)) -> 2.5 | D23: =Data!H22/Data!$J$3 -> 0.48224852 | E23: =Data!I22/Data!$J$3 -> 0.11242604 | F23: =Data!J22/Data!$J$3 -> 0.21893491 | G23: =Data!L22/(Data!L22+Data!M22) -> 0.45864662
A24: 3C | B24: Consumer Behavior | C24: =(4*Data!B23+3*Data!C23+2*Data!D23+1*Data!E23)/(SUM(Data!B23:F23)) -> 2.724026 | D24: =Data!H23/Data!$J$3 -> 0.56804734 | E24: =Data!I23/Data!$J$3 -> 0.10059172 | F24: =Data!J23/Data!$J$3 -> 0.21893491 | G24: =Data!L23/(Data!L23+Data!M23) -> 0.58419244
A25: 3D | B25: Behavior of Firms | C25: =(4*Data!B24+3*Data!C24+2*Data!D24+1*Data!E24)/(SUM(Data!B24:F24)) -> 2.9775641 | D25: =Data!H24/Data!$J$3 -> 0.66272189 | E25: =Data!I24/Data!$J$3 -> 0.068047337 | F25: =Data!J24/Data!$J$3 -> 0.17455621 | G25: =Data!L24/(Data!L24+Data!M24) -> 0.67006803
A26: 3E | B26: Types of Markets | C26: =(4*Data!B25+3*Data!C25+2*Data!D25+1*Data!E25)/(SUM(Data!B25:F25)) -> 2.6805112 | D26: =Data!H25/Data!$J$3 -> 0.59763314 | E26: =Data!I25/Data!$J$3 -> 0.073964497 | F26: =Data!J25/Data!$J$3 -> 0.23372781 | G26: =Data!L25/(Data!L25+Data!M25) -> 0.53378378
A27: 3F | B27: Utility Theory | C27: =(4*Data!B26+3*Data!C26+2*Data!D26+1*Data!E26)/(SUM(Data!B26:F26)) -> 2.9041534 | D27: =Data!H26/Data!$J$3 -> 0.65680473 | E27: =Data!I26/Data!$J$3 -> 0.073964497 | F27: =Data!J26/Data!$J$3 -> 0.17455621 | G27: =Data!L26/(Data!L26+Data!M26) -> 0.62289562
A28: 3G | B28: Game Theory | C28: =(4*Data!B27+3*Data!C27+2*Data!D27+1*Data!E27)/(SUM(Data!B27:F27)) -> 2.3862069 | D28: =Data!H27/Data!$J$3 -> 0.42899408 | E28: =Data!I27/Data!$J$3 -> 0.17455621 | F28: =Data!J27/Data!$J$3 -> 0.23076923 | G28: =Data!L27/(Data!L27+Data!M27) -> 0.35869565
B30: Macroeconomics
A31: 4A | B31: National Income Accounting | C31: =(4*Data!B30+3*Data!C30+2*Data!D30+1*Data!E30)/(SUM(Data!B30:F30)) -> 2.2727273 | D31: =Data!H30/Data!$J$3 -> 0.4704142 | E31: =Data!I30/Data!$J$3 -> 0.085798817 | F31: =Data!J30/Data!$J$3 -> 0.34023669 | G31: =Data!L30/(Data!L30+Data!M30) -> 0.34576271
A32: 4B | B32: Aggregate Supply and Demand | C32: =(4*Data!B31+3*Data!C31+2*Data!D31+1*Data!E31)/(SUM(Data!B31:F31)) -> 2.4512987 | D32: =Data!H31/Data!$J$3 -> 0.52071006 | E32: =Data!I31/Data!$J$3 -> 0.082840237 | F32: =Data!J31/Data!$J$3 -> 0.28994083 | G32: =Data!L31/(Data!L31+Data!M31) -> 0.35958904
A33: 4C | B33: Inflation, Interest Rates, Federal Reserve | C33: =(4*Data!B32+3*Data!C32+2*Data!D32+1*Data!E32)/(SUM(Data!B32:F32)) -> 3.1785714 | D33: =Data!H32/Data!$J$3 -> 0.68047337 | E33: =Data!I32/Data!$J$3 -> 0.047337278 | F33: =Data!J32/Data!$J$3 -> 0.16863905 | G33: =Data!L32/(Data!L32+Data!M32) -> 0.82491582
A34: 4D | B34: Money Supply | C34: =(4*Data!B33+3*Data!C33+2*Data!D33+1*Data!E33)/(SUM(Data!B33:F33)) -> 2.3036304 | D34: =Data!H33/Data!$J$3 -> 0.44378698 | E34: =Data!I33/Data!$J$3 -> 0.1183432 | F34: =Data!J33/Data!$J$3 -> 0.31952663 | G34: =Data!L33/(Data!L33+Data!M33) -> 0.23529412
A35: 4E | B35: Keynesian Economics | C35: =(4*Data!B34+3*Data!C34+2*Data!D34+1*Data!E34)/(SUM(Data!B34:F34)) -> 2.0637584 | D35: =Data!H34/Data!$J$3 -> 0.3816568 | E35: =Data!I34/Data!$J$3 -> 0.13905325 | F35: =Data!J34/Data!$J$3 -> 0.34911243 | G35: =Data!L34/(Data!L34+Data!M34) -> 0.1443662
A36: 4F | B36: The Multiplier Effects | C36: =(4*Data!B35+3*Data!C35+2*Data!D35+1*Data!E35)/(SUM(Data!B35:F35)) -> 2.1653543 | D36: =Data!H35/Data!$J$3 -> 0.37278107 | E36: =Data!I35/Data!$J$3 -> 0.097633136 | F36: =Data!J35/Data!$J$3 -> 0.29289941 | G36: =Data!L35/(Data!L35+Data!M35) -> 0.19685039
B38: Interest Theory
A39: 5A | B39: Present Value, Future Value - Discrete | C39: =(4*Data!B38+3*Data!C38+2*Data!D38+1*Data!E38)/(SUM(Data!B38:F38)) -> 3.8673139 | D39: =Data!H38/Data!$J$3 -> 0.87869822 | E39: =Data!I38/Data!$J$3 -> 0.0059171598 | F39: =Data!J38/Data!$J$3 -> 0.017751479 | G39: =Data!L38/(Data!L38+Data!M38) -> 0.98996656
A40: 5B | B40: Present Value, Future Value - Continuous | C40: =(4*Data!B39+3*Data!C39+2*Data!D39+1*Data!E39)/(SUM(Data!B39:F39)) -> 3.6096774 | D40: =Data!H39/Data!$J$3 -> 0.85798817 | E40: =Data!I39/Data!$J$3 -> 0.020710059 | F40: =Data!J39/Data!$J$3 -> 0.023668639 | G40: =Data!L39/(Data!L39+Data!M39) -> 0.80808081
A41: 5C | B41: Bond Yields, Sinking Funds, Annuities | C41: =(4*Data!B40+3*Data!C40+2*Data!D40+1*Data!E40)/(SUM(Data!B40:F40)) -> 3.0844156 | D41: =Data!H40/Data!$J$3 -> 0.76627219 | E41: =Data!I40/Data!$J$3 -> 0.053254438 | F41: =Data!J40/Data!$J$3 -> 0.071005917 | G41: =Data!L40/(Data!L40+Data!M40) -> 0.60204082
A42: 5D | B42: Amortization & Depreciation | C42: =(4*Data!B41+3*Data!C41+2*Data!D41+1*Data!E41)/(SUM(Data!B41:F41)) -> 2.8762215 | D42: =Data!H41/Data!$J$3 -> 0.70710059 | E42: =Data!I41/Data!$J$3 -> 0.071005917 | F42: =Data!J41/Data!$J$3 -> 0.10650888 | G42: =Data!L41/(Data!L41+Data!M41) -> 0.57142857
B44: Basic Finance
A45: 6A | B45: NPV, Internal Rate of Return, etc. | C45: =(4*Data!B44+3*Data!C44+2*Data!D44+1*Data!E44)/(SUM(Data!B44:F44)) -> 3.7096774 | D45: =Data!H44/Data!$J$3 -> 0.85207101 | E45: =Data!I44/Data!$J$3 -> 0.014792899 | F45: =Data!J44/Data!$J$3 -> 0.026627219 | G45: =Data!L44/(Data!L44+Data!M44) -> 0.92929293
A46: 6B | B46: Risk vs. Return | C46: =(4*Data!B45+3*Data!C45+2*Data!D45+1*Data!E45)/(SUM(Data!B45:F45)) -> 3.3300971 | D46: =Data!H45/Data!$J$3 -> 0.79881657 | E46: =Data!I45/Data!$J$3 -> 0.062130178 | F46: =Data!J45/Data!$J$3 -> 0.035502959 | G46: =Data!L45/(Data!L45+Data!M45) -> 0.67918089
A47: 6C | B47: Capital Budgeting | C47: =(4*Data!B46+3*Data!C46+2*Data!D46+1*Data!E46)/(SUM(Data!B46:F46)) -> 3.0488599 | D47: =Data!H46/Data!$J$3 -> 0.69230769 | E47: =Data!I46/Data!$J$3 -> 0.12426036 | F47: =Data!J46/Data!$J$3 -> 0.073964497 | G47: =Data!L46/(Data!L46+Data!M46) -> 0.58843537
A48: 6D | B48: Efficient Markets | C48: =(4*Data!B47+3*Data!C47+2*Data!D47+1*Data!E47)/(SUM(Data!B47:F47)) -> 2.717608 | D48: =Data!H47/Data!$J$3 -> 0.63313609 | E48: =Data!I47/Data!$J$3 -> 0.13609467 | F48: =Data!J47/Data!$J$3 -> 0.10650888 | G48: =Data!L47/(Data!L47+Data!M47) -> 0.32068966
A49: 6E | B49: Types of Securities | C49: =(4*Data!B48+3*Data!C48+2*Data!D48+1*Data!E48)/(SUM(Data!B48:F48)) -> 3.0459016 | D49: =Data!H48/Data!$J$3 -> 0.70710059 | E49: =Data!I48/Data!$J$3 -> 0.11242604 | F49: =Data!J48/Data!$J$3 -> 0.076923077 | G49: =Data!L48/(Data!L48+Data!M48) -> 0.58983051
A50: 6F | B50: Option Pricing | C50: =(4*Data!B49+3*Data!C49+2*Data!D49+1*Data!E49)/(SUM(Data!B49:F49)) -> 2.5766667 | D50: =Data!H49/Data!$J$3 -> 0.57988166 | E50: =Data!I49/Data!$J$3 -> 0.19822485 | F50: =Data!J49/Data!$J$3 -> 0.088757396 | G50: =Data!L49/(Data!L49+Data!M49) -> 0.3125
A51: 6G | B51: Corporate Financing | C51: =(4*Data!B50+3*Data!C50+2*Data!D50+1*Data!E50)/(SUM(Data!B50:F50)) -> 2.9240924 | D51: =Data!H50/Data!$J$3 -> 0.67751479 | E51: =Data!I50/Data!$J$3 -> 0.12721893 | F51: =Data!J50/Data!$J$3 -> 0.082840237 | G51: =Data!L50/(Data!L50+Data!M50) -> 0.38831615
A52: 6H | B52: Financial Performance Ratios | C52: =(4*Data!B51+3*Data!C51+2*Data!D51+1*Data!E51)/(SUM(Data!B51:F51)) -> 3.3039216 | D52: =Data!H51/Data!$J$3 -> 0.73076923 | E52: =Data!I51/Data!$J$3 -> 0.079881657 | F52: =Data!J51/Data!$J$3 -> 0.059171598 | G52: =Data!L51/(Data!L51+Data!M51) -> 0.75257732
B54: Advanced Finance
A55: 7A | B55: Optimal Portfolio Construction | C55: =(4*Data!B54+3*Data!C54+2*Data!D54+1*Data!E54)/(SUM(Data!B54:F54)) -> 2.6666667 | D55: =Data!H54/Data!$J$3 -> 0.5295858 | E55: =Data!I54/Data!$J$3 -> 0.24852071 | F55: =Data!J54/Data!$J$3 -> 0.076923077 | G55: =Data!L54/(Data!L54+Data!M54) -> 0.4084507
A56: 7B | B56: Security Risk | C56: =(4*Data!B55+3*Data!C55+2*Data!D55+1*Data!E55)/(SUM(Data!B55:F55)) -> 2.7123288 | D56: =Data!H55/Data!$J$3 -> 0.53550296 | E56: =Data!I55/Data!$J$3 -> 0.24260355 | F56: =Data!J55/Data!$J$3 -> 0.068047337 | G56: =Data!L55/(Data!L55+Data!M55) -> 0.38732394
A57: 7C | B57: Derivatives and Options | C57: =(4*Data!B56+3*Data!C56+2*Data!D56+1*Data!E56)/(SUM(Data!B56:F56)) -> 2.2302405 | D57: =Data!H56/Data!$J$3 -> 0.36390533 | E57: =Data!I56/Data!$J$3 -> 0.3816568 | F57: =Data!J56/Data!$J$3 -> 0.1035503 | G57: =Data!L56/(Data!L56+Data!M56) -> 0.19642857
A58: 7D | B58: Asset-backed Securities | C58: =(4*Data!B57+3*Data!C57+2*Data!D57+1*Data!E57)/(SUM(Data!B57:F57)) -> 2.2871972 | D58: =Data!H57/Data!$J$3 -> 0.35798817 | E58: =Data!I57/Data!$J$3 -> 0.36390533 | F58: =Data!J57/Data!$J$3 -> 0.10650888 | G58: =Data!L57/(Data!L57+Data!M57) -> 0.22142857
A59: 7E | B59: Hedging Strategies | C59: =(4*Data!B58+3*Data!C58+2*Data!D58+1*Data!E58)/(SUM(Data!B58:F58)) -> 2.209622 | D59: =Data!H58/Data!$J$3 -> 0.35207101 | E59: =Data!I58/Data!$J$3 -> 0.35502959 | F59: =Data!J58/Data!$J$3 -> 0.13313609 | G59: =Data!L58/(Data!L58+Data!M58) -> 0.17605634
A60: 7F | B60: Models for Valuing Stocks | C60: =(4*Data!B59+3*Data!C59+2*Data!D59+1*Data!E59)/(SUM(Data!B59:F59)) -> 2.1972789 | D60: =Data!H59/Data!$J$3 -> 0.36982249 | E60: =Data!I59/Data!$J$3 -> 0.31952663 | F60: =Data!J59/Data!$J$3 -> 0.15976331 | G60: =Data!L59/(Data!L59+Data!M59) -> 0.16607774
A61: 7G | B61: Models for Valuing Bonds | C61: =(4*Data!B60+3*Data!C60+2*Data!D60+1*Data!E60)/(SUM(Data!B60:F60)) -> 2.3356164 | D61: =Data!H60/Data!$J$3 -> 0.39349112 | E61: =Data!I60/Data!$J$3 -> 0.29881657 | F61: =Data!J60/Data!$J$3 -> 0.14792899 | G61: =Data!L60/(Data!L60+Data!M60) -> 0.21276596
A62: 7H | B62: Types of Fixed Income Securities | C62: =(4*Data!B61+3*Data!C61+2*Data!D61+1*Data!E61)/(SUM(Data!B61:F61)) -> 2.5408163 | D62: =Data!H61/Data!$J$3 -> 0.49408284 | E62: =Data!I61/Data!$J$3 -> 0.24556213 | F62: =Data!J61/Data!$J$3 -> 0.10946746 | G62: =Data!L61/(Data!L61+Data!M61) -> 0.38297872
A63: 7I | B63: International Securities | C63: =(4*Data!B62+3*Data!C62+2*Data!D62+1*Data!E62)/(SUM(Data!B62:F62)) -> 2.003413 | D63: =Data!H62/Data!$J$3 -> 0.27810651 | E63: =Data!I62/Data!$J$3 -> 0.36390533 | F63: =Data!J62/Data!$J$3 -> 0.19230769 | G63: =Data!L62/(Data!L62+Data!M62) -> 0.13571429
A64: 7J | B64: Decision Trees | C64: =(4*Data!B63+3*Data!C63+2*Data!D63+1*Data!E63)/(SUM(Data!B63:F63)) -> 2.4169611 | D64: =Data!H63/Data!$J$3 -> 0.42307692 | E64: =Data!I63/Data!$J$3 -> 0.26331361 | F64: =Data!J63/Data!$J$3 -> 0.13017751 | G64: =Data!L63/(Data!L63+Data!M63) -> 0.29963899
B66: Actuarial Models
A67: 8A | B67: Deterministic vs. Stochastic Models | C67: =(4*Data!B66+3*Data!C66+2*Data!D66+1*Data!E66)/(SUM(Data!B66:F66)) -> 3.3216783 | D67: =Data!H66/Data!$J$3 -> 0.75443787 | E67: =Data!I66/Data!$J$3 -> 0.056213018 | F67: =Data!J66/Data!$J$3 -> 0.0088757396 | G67: =Data!L66/(Data!L66+Data!M66) -> 0.76029963
A68: 8B | B68: Evaluation of Various Cash Flow Principles | C68: =(4*Data!B67+3*Data!C67+2*Data!D67+1*Data!E67)/(SUM(Data!B67:F67)) -> 3.1283019 | D68: =Data!H67/Data!$J$3 -> 0.67751479 | E68: =Data!I67/Data!$J$3 -> 0.076923077 | F68: =Data!J67/Data!$J$3 -> 0.020710059 | G68: =Data!L67/(Data!L67+Data!M67) -> 0.60956175
A69: 8C | B69: Life Contingencies | C69: =(4*Data!B68+3*Data!C68+2*Data!D68+1*Data!E68)/(SUM(Data!B68:F68)) -> 1.9557823 | D69: =Data!H68/Data!$J$3 -> 0.53254438 | E69: =Data!I68/Data!$J$3 -> 0.14201183 | F69: =Data!J68/Data!$J$3 -> 0.18047337 | G69: =Data!L68/(Data!L68+Data!M68) -> 0.4676259
A70: 8D | B70: Pension Math | C70: =(4*Data!B69+3*Data!C69+2*Data!D69+1*Data!E69)/(SUM(Data!B69:F69)) -> 1.5120275 | D70: =Data!H69/Data!$J$3 -> 0.32248521 | E70: =Data!I69/Data!$J$3 -> 0.23964497 | F70: =Data!J69/Data!$J$3 -> 0.26331361 | G70: =Data!L69/(Data!L69+Data!M69) -> 0.22743682
A71: 8E | B71: Frequency Distributions | C71: =(4*Data!B70+3*Data!C70+2*Data!D70+1*Data!E70)/(SUM(Data!B70:F70)) -> 3.6428571 | D71: =Data!H70/Data!$J$3 -> 0.82544379 | E71: =Data!I70/Data!$J$3 -> 0.0088757396 | F71: =Data!J70/Data!$J$3 -> 0.017751479 | G71: =Data!L70/(Data!L70+Data!M70) -> 0.92170819
A72: 8F | B72: Severity Distributions | C72: =(4*Data!B71+3*Data!C71+2*Data!D71+1*Data!E71)/(SUM(Data!B71:F71)) -> 3.6564626 | D72: =Data!H71/Data!$J$3 -> 0.83431953 | E72: =Data!I71/Data!$J$3 -> 0.014792899 | F72: =Data!J71/Data!$J$3 -> 0.0088757396 | G72: =Data!L71/(Data!L71+Data!M71) -> 0.92553191
A73: 8G | B73: Deductibles, Policy Limits, Coinsurance | C73: =(4*Data!B72+3*Data!C72+2*Data!D72+1*Data!E72)/(SUM(Data!B72:F72)) -> 3.759322 | D73: =Data!H72/Data!$J$3 -> 0.84615385 | E73: =Data!I72/Data!$J$3 -> 0.0088757396 | F73: =Data!J72/Data!$J$3 -> 0 | G73: =Data!L72/(Data!L72+Data!M72) -> 0.91459075
A74: 8H | B74: Contingent Cash Flows | C74: =(4*Data!B73+3*Data!C73+2*Data!D73+1*Data!E73)/(SUM(Data!B73:F73)) -> 3.5 | D74: =Data!H73/Data!$J$3 -> 0.78106509 | E74: =Data!I73/Data!$J$3 -> 0.053254438 | F74: =Data!J73/Data!$J$3 -> 0 | G74: =Data!L73/(Data!L73+Data!M73) -> 0.71111111
A75: 8I | B75: Discrete Markov Chains | C75: =(4*Data!B74+3*Data!C74+2*Data!D74+1*Data!E74)/(SUM(Data!B74:F74)) -> 2.1875 | D75: =Data!H74/Data!$J$3 -> 0.21597633 | E75: =Data!I74/Data!$J$3 -> 0.21597633 | F75: =Data!J74/Data!$J$3 -> 0.094674556 | G75: =Data!L74/(Data!L74+Data!M74) -> 0.14054054
A76: 8J | B76: Brownian Motion | C76: =(4*Data!B75+3*Data!C75+2*Data!D75+1*Data!E75)/(SUM(Data!B75:F75)) -> 1.9388889 | D76: =Data!H75/Data!$J$3 -> 0.19526627 | E76: =Data!I75/Data!$J$3 -> 0.18934911 | F76: =Data!J75/Data!$J$3 -> 0.15088757 | G76: =Data!L75/(Data!L75+Data!M75) -> 0.1420765
A77: 8K | B77: Aggregate Loss Distributions | C77: =(4*Data!B76+3*Data!C76+2*Data!D76+1*Data!E76)/(SUM(Data!B76:F76)) -> 2.8687259 | D77: =Data!H76/Data!$J$3 -> 0.52071006 | E77: =Data!I76/Data!$J$3 -> 0.18343195 | F77: =Data!J76/Data!$J$3 -> 0.038461538 | G77: =Data!L76/(Data!L76+Data!M76) -> 0.51587302
A78: 8L | B78: Simulation | C78: =(4*Data!B77+3*Data!C77+2*Data!D77+1*Data!E77)/(SUM(Data!B77:F77)) -> 3.3087719 | D78: =Data!H77/Data!$J$3 -> 0.65088757 | E78: =Data!I77/Data!$J$3 -> 0.1183432 | F78: =Data!J77/Data!$J$3 -> 0.041420118 | G78: =Data!L77/(Data!L77+Data!M77) -> 0.78731343
B80: Actuarial Modeling
A81: 9A | B81: Parameter Estimation | C81: =(4*Data!B80+3*Data!C80+2*Data!D80+1*Data!E80)/(SUM(Data!B80:F80)) -> 3.3114187 | D81: =Data!H80/Data!$J$3 -> 0.78106509 | E81: =Data!I80/Data!$J$3 -> 0.047337278 | F81: =Data!J80/Data!$J$3 -> 0.01183432 | G81: =Data!L80/(Data!L80+Data!M80) -> 0.73214286
A82: 9B | B82: Censored, Truncated, Shifted Data | C82: =(4*Data!B81+3*Data!C81+2*Data!D81+1*Data!E81)/(SUM(Data!B81:F81)) -> 3.3923611 | D82: =Data!H81/Data!$J$3 -> 0.78106509 | E82: =Data!I81/Data!$J$3 -> 0.047337278 | F82: =Data!J81/Data!$J$3 -> 0.0088757396 | G82: =Data!L81/(Data!L81+Data!M81) -> 0.76086957
A83: 9C | B83: Goodness of Fit Measures | C83: =(4*Data!B82+3*Data!C82+2*Data!D82+1*Data!E82)/(SUM(Data!B82:F82)) -> 3.3680556 | D83: =Data!H82/Data!$J$3 -> 0.79881657 | E83: =Data!I82/Data!$J$3 -> 0.026627219 | F83: =Data!J82/Data!$J$3 -> 0.014792899 | G83: =Data!L82/(Data!L82+Data!M82) -> 0.81654676
A84: 9D | B84: Regression Analysis | C84: =(4*Data!B83+3*Data!C83+2*Data!D83+1*Data!E83)/(SUM(Data!B83:F83)) -> 3.5422535 | D84: =Data!H83/Data!$J$3 -> 0.78402367 | E84: =Data!I83/Data!$J$3 -> 0.023668639 | F84: =Data!J83/Data!$J$3 -> 0.014792899 | G84: =Data!L83/(Data!L83+Data!M83) -> 0.90942029
A85: 9E | B85: Time Series and Forecasts | C85: =(4*Data!B84+3*Data!C84+2*Data!D84+1*Data!E84)/(SUM(Data!B84:F84)) -> 3.1188811 | D85: =Data!H84/Data!$J$3 -> 0.73668639 | E85: =Data!I84/Data!$J$3 -> 0.085798817 | F85: =Data!J84/Data!$J$3 -> 0.014792899 | G85: =Data!L84/(Data!L84+Data!M84) -> 0.65467626
A86: 9F | B86: Classical Credibility | C86: =(4*Data!B85+3*Data!C85+2*Data!D85+1*Data!E85)/(SUM(Data!B85:F85)) -> 3.5277778 | D86: =Data!H85/Data!$J$3 -> 0.81065089 | E86: =Data!I85/Data!$J$3 -> 0.017751479 | F86: =Data!J85/Data!$J$3 -> 0.0059171598 | G86: =Data!L85/(Data!L85+Data!M85) -> 0.95357143
A87: 9G | B87: Bayesian Credibility | C87: =(4*Data!B86+3*Data!C86+2*Data!D86+1*Data!E86)/(SUM(Data!B86:F86)) -> 3.4947735 | D87: =Data!H86/Data!$J$3 -> 0.81656805 | E87: =Data!I86/Data!$J$3 -> 0.01183432 | F87: =Data!J86/Data!$J$3 -> 0.0059171598 | G87: =Data!L86/(Data!L86+Data!M86) -> 0.79569892
A88: 9H | B88: Buhlmann Straub Credibility | C88: =(4*Data!B87+3*Data!C87+2*Data!D87+1*Data!E87)/(SUM(Data!B87:F87)) -> 3.0875576 | D88: =Data!H87/Data!$J$3 -> 0.55325444 | E88: =Data!I87/Data!$J$3 -> 0.062130178 | F88: =Data!J87/Data!$J$3 -> 0.023668639 | G88: =Data!L87/(Data!L87+Data!M87) -> 0.44954128
A89: 9I | B89: Model Validation through Simulation | C89: =(4*Data!B88+3*Data!C88+2*Data!D88+1*Data!E88)/(SUM(Data!B88:F88)) -> 3.3472222 | D89: =Data!H88/Data!$J$3 -> 0.72189349 | E89: =Data!I88/Data!$J$3 -> 0.097633136 | F89: =Data!J88/Data!$J$3 -> 0.01183432 | G89: =Data!L88/(Data!L88+Data!M88) -> 0.69642857
A90: 9J | B90: Analysis of Variance | C90: =(4*Data!B89+3*Data!C89+2*Data!D89+1*Data!E89)/(SUM(Data!B89:F89)) -> 2.8701754 | D90: =Data!H89/Data!$J$3 -> 0.68934911 | E90: =Data!I89/Data!$J$3 -> 0.065088757 | F90: =Data!J89/Data!$J$3 -> 0.073964497 | G90: =Data!L89/(Data!L89+Data!M89) -> 0.54151625
A91: 9K | B91: Hypothesis Testing | C91: =(4*Data!B90+3*Data!C90+2*Data!D90+1*Data!E90)/(SUM(Data!B90:F90)) -> 2.8701754 | D91: =Data!H90/Data!$J$3 -> 0.68934911 | E91: =Data!I90/Data!$J$3 -> 0.065088757 | F91: =Data!J90/Data!$J$3 -> 0.073964497 | G91: =Data!L90/(Data!L90+Data!M90) -> 0.54151625
B93: Intro to P/C Insurance and Ratemaking
A94: 10A | B94: Basic Coverages and Contract Language | C94: =(4*Data!B93+3*Data!C93+2*Data!D93+1*Data!E93)/(SUM(Data!B93:F93)) -> 3.6575342 | D94: =Data!H93/Data!$J$3 -> 0.81360947 | E94: =Data!I93/Data!$J$3 -> 0.01183432 | F94: =Data!J93/Data!$J$3 -> 0.026627219 | G94: =Data!L93/(Data!L93+Data!M93) -> 0.9893617
A95: 10B | B95: Insurance Company Operations | C95: =(4*Data!B94+3*Data!C94+2*Data!D94+1*Data!E94)/(SUM(Data!B94:F94)) -> 3.609589 | D95: =Data!H94/Data!$J$3 -> 0.78106509 | E95: =Data!I94/Data!$J$3 -> 0.017751479 | F95: =Data!J94/Data!$J$3 -> 0.050295858 | G95: =Data!L94/(Data!L94+Data!M94) -> 0.98566308
A96: 10C | B96: Insurance Data Capture | C96: =(4*Data!B95+3*Data!C95+2*Data!D95+1*Data!E95)/(SUM(Data!B95:F95)) -> 3.0862069 | D96: =Data!H95/Data!$J$3 -> 0.68639053 | E96: =Data!I95/Data!$J$3 -> 0.088757396 | F96: =Data!J95/Data!$J$3 -> 0.076923077 | G96: =Data!L95/(Data!L95+Data!M95) -> 0.87588652
A97: 10D | B97: Ratemaking Techniques | C97: =(4*Data!B96+3*Data!C96+2*Data!D96+1*Data!E96)/(SUM(Data!B96:F96)) -> 3.9310345 | D97: =Data!H96/Data!$J$3 -> 0.84615385 | E97: =Data!I96/Data!$J$3 -> 0.0029585799 | F97: =Data!J96/Data!$J$3 -> 0 | G97: =Data!L96/(Data!L96+Data!M96) -> 0.99293286
A98: 10E | B98: Loss Development | C98: =(4*Data!B97+3*Data!C97+2*Data!D97+1*Data!E97)/(SUM(Data!B97:F97)) -> 3.9385666 | D98: =Data!H97/Data!$J$3 -> 0.84911243 | E98: =Data!I97/Data!$J$3 -> 0.0088757396 | F98: =Data!J97/Data!$J$3 -> 0 | G98: =Data!L97/(Data!L97+Data!M97) -> 0.98939929
A99: 10F | B99: Exposure Trending, Frequency, Severity | C99: =(4*Data!B98+3*Data!C98+2*Data!D98+1*Data!E98)/(SUM(Data!B98:F98)) -> 3.9522184 | D99: =Data!H98/Data!$J$3 -> 0.85207101 | E99: =Data!I98/Data!$J$3 -> 0.0059171598 | F99: =Data!J98/Data!$J$3 -> 0 | G99: =Data!L98/(Data!L98+Data!M98) -> 0.99644128
A100: 10G | B100: Trend Determination | C100: =(4*Data!B99+3*Data!C99+2*Data!D99+1*Data!E99)/(SUM(Data!B99:F99)) -> 3.8219178 | D100: =Data!H99/Data!$J$3 -> 0.83431953 | E100: =Data!I99/Data!$J$3 -> 0.020710059 | F100: =Data!J99/Data!$J$3 -> 0.0029585799 | G100: =Data!L99/(Data!L99+Data!M99) -> 0.98939929
A101: 10H | B101: Class and Territory Relativities | C101: =(4*Data!B100+3*Data!C100+2*Data!D100+1*Data!E100)/(SUM(Data!B100:F100)) -> 3.7671233 | D101: =Data!H100/Data!$J$3 -> 0.83727811 | E101: =Data!I100/Data!$J$3 -> 0.014792899 | F101: =Data!J100/Data!$J$3 -> 0.0059171598 | G101: =Data!L100/(Data!L100+Data!M100) -> 0.93617021
A102: 10I | B102: Credibility, Complement, Off-Balance | C102: =(4*Data!B101+3*Data!C101+2*Data!D101+1*Data!E101)/(SUM(Data!B101:F101)) -> 3.8253425 | D102: =Data!H101/Data!$J$3 -> 0.84023669 | E102: =Data!I101/Data!$J$3 -> 0.0088757396 | F102: =Data!J101/Data!$J$3 -> 0.0088757396 | G102: =Data!L101/(Data!L101+Data!M101) -> 0.97163121
A103: 10J | B103: Underwriting Expenses | C103: =(4*Data!B102+3*Data!C102+2*Data!D102+1*Data!E102)/(SUM(Data!B102:F102)) -> 3.6952055 | D103: =Data!H102/Data!$J$3 -> 0.82544379 | E103: =Data!I102/Data!$J$3 -> 0.014792899 | F103: =Data!J102/Data!$J$3 -> 0.017751479 | G103: =Data!L102/(Data!L102+Data!M102) -> 0.97879859
A104: 10K | B104: Profit, Contingency, Risk Load | C104: =(4*Data!B103+3*Data!C103+2*Data!D103+1*Data!E103)/(SUM(Data!B103:F103)) -> 3.8482759 | D104: =Data!H103/Data!$J$3 -> 0.84911243 | E104: =Data!I103/Data!$J$3 -> 0.0059171598 | F104: =Data!J103/Data!$J$3 -> 0 | G104: =Data!L103/(Data!L103+Data!M103) -> 0.9751773
A105: 10L | B105: Surplus Allocation | C105: =(4*Data!B104+3*Data!C104+2*Data!D104+1*Data!E104)/(SUM(Data!B104:F104)) -> 3.3195876 | D105: =Data!H104/Data!$J$3 -> 0.72189349 | E105: =Data!I104/Data!$J$3 -> 0.10946746 | F105: =Data!J104/Data!$J$3 -> 0.017751479 | G105: =Data!L104/(Data!L104+Data!M104) -> 0.82078853
... A112: 10S | B112: Supply and Demand Issues | C112: =(4*Data!B111+3*Data!C111+2*Data!D111+1*Data!E111)/(SUM(Data!B111:F111)) -> 3.1958042 | D112: =Data!H111/Data!$J$3 -> 0.65976331 | E112: =Data!I111/Data!$J$3 -> 0.13313609 | F112: =Data!J111/Data!$J$3 -> 0.044378698 | G112: =Data!L111/(Data!L111+Data!M111) -> 0.74087591
B114: Loss Reserving Techniques
A115: 11A | B115: Constituents of Reserves | C115: =(4*Data!B114+3*Data!C114+2*Data!D114+1*Data!E114)/(SUM(Data!B114:F114)) -> 3.9310345 | D115: =Data!H114/Data!$J$3 -> 0.84023669 | E115: =Data!I114/Data!$J$3 -> 0.0029585799 | F115: =Data!J114/Data!$J$3 -> 0.0029585799 | G115: =Data!L114/(Data!L114+Data!M114) -> 0.98220641
A116: 11B | B116: Basic Reserving Techniques | C116: =(4*Data!B115+3*Data!C115+2*Data!D115+1*Data!E115)/(SUM(Data!B115:F115)) -> 3.9651568 | D116: =Data!H115/Data!$J$3 -> 0.84319527 | E116: =Data!I115/Data!$J$3 -> 0.0029585799 | F116: =Data!J115/Data!$J$3 -> 0 | G116: =Data!L115/(Data!L115+Data!M115) -> 0.97857143
A117: 11C | B117: Changes in Loss Climates | C117: =(4*Data!B116+3*Data!C116+2*Data!D116+1*Data!E116)/(SUM(Data!B116:F116)) -> 3.8013937 | D117: =Data!H116/Data!$J$3 -> 0.84023669 | E117: =Data!I116/Data!$J$3 -> 0.0059171598 | F117: =Data!J116/Data!$J$3 -> 0.0029585799 | G117: =Data!L116/(Data!L116+Data!M116) -> 0.9
A118: 11D | B118: Data Capture, Data Problems | C118: =(4*Data!B117+3*Data!C117+2*Data!D117+1*Data!E117)/(SUM(Data!B117:F117)) -> 3.6413793 | D118: =Data!H117/Data!$J$3 -> 0.74556213 | E118: =Data!I117/Data!$J$3 -> 0.073964497 | F118: =Data!J117/Data!$J$3 -> 0.029585799 | G118: =Data!L117/(Data!L117+Data!M117) -> 0.95373665
A119: 11E | B119: Loss Triggers | C119: =(4*Data!B118+3*Data!C118+2*Data!D118+1*Data!E118)/(SUM(Data!B118:F118)) -> 3.7474048 | D119: =Data!H118/Data!$J$3 -> 0.83136095 | E119: =Data!I118/Data!$J$3 -> 0.017751479 | F119: =Data!J118/Data!$J$3 -> 0.0029585799 | G119: =Data!L118/(Data!L118+Data!M118) -> 0.85714286
...

Sheet Data
A1: Summary of Data from CAS Professional Skills Survey 2002
H3: Total Taking Survey | J3: 338
A5: Item # | B5: Critical | C5: Important | D5: Somewhat | E5: Low | F5: Not Important | H5: Basic Ed | I5: Continuing Ed | J5: Non-CAS | L5: Use It | M5: Don't Use It
A8: 1A | B8: 107 | C8: 112 | D8: 62 | E8: 30 | F8: 7 | H8: 165 | I8: 1 | J8: 146 | L8: 245 | M8: 62
A9: 1B | B9: 67 | C9: 105 | D9: 79 | E9: 54 | F9: 13 | H9: 158 | I9: 7 | J9: 148 | L9: 169 | M9: 136
A10: 1C | B10: 27 | C10: 67 | D10: 81 | E10: 100 | F10: 36 | H10: 100 | I10: 16 | J10: 187 | L10: 83 | M10: 217
A11: 1D | B11: 75 | C11: 103 | D11: 66 | E11: 48 | F11: 23 | H11: 147 | I11: 6 | J11: 154 | L11: 194 | M11: 110
A12: 1E | B12: 213 | C12: 71 | D12: 24 | E12: 9 | F12: 0 | H12: 159 | I12: 1 | J12: 151 | L12: 292 | M12: 10
A15: 2A | B15: 135 | C15: 116 | D15: 48 | E15: 14 | F15: 2 | H15: 268 | I15: 4 | J15: 39 | L15: 249 | M15: 54
A16: 2B | B16: 197 | C16: 94 | D16: 25 | E16: 1 | F16: 0 | H16: 281 | I16: 1 | J16: 30 | L16: 292 | M16: 12
A17: 2C | B17: 175 | C17: 109 | D17: 31 | E17: 2 | F17: 0 | H17: 282 | I17: 2 | J17: 27 | L17: 281 | M17: 23
A18: 2D | B18: 146 | C18: 112 | D18: 48 | E18: 11 | F18: 0 | H18: 272 | I18: 11 | J18: 28 | L18: 236 | M18: 67
A21: 3A | B21: 94 | C21: 141 | D21: 66 | E21: 14 | F21: 1 | H21: 222 | I21: 21 | J21: 68 | L21: 205 | M21: 92
A22: 3B | B22: 39 | C22: 107 | D22: 96 | E22: 26 | F22: 10 | H22: 163 | I22: 38 | J22: 74 | L22: 122 | M22: 144
A23: 3C | B23: 63 | C23: 132 | D23: 84 | E23: 23 | F23: 6 | H23: 192 | I23: 34 | J23: 74 | L23: 170 | M23: 121
... A204: 18N | B204: 78 | C204: 117 | D204: 65 | E204: 16 | F204: 4 | H204: 12 | I204: 109 | J204: 158 | L204: 212 | M204: 46
A208: 1 | B208: Basic Subjects | C208: Keep on Syllabus | D208: Credit for University Courses | E208: Background Reading
B209: Calculus | C209: 110 | D209: 112 | E209: 67
B210: Probability | C210: 218 | D210: 59 | E210: 12
B211: Economics | C211: 160 | D211: 96 | E211: 33
B212: Regression | C212: 245 | D212: 31 | E212: 13
B213: Forecasting | C213: 228 | D213: 31 | E213: 29
B214: Time Series | C214: 195 | D214: 42 | E214: 47
B215: Interest Theory | C215: 249 | D215: 29 | E215: 10
B216: Finance | C216: 217 | D216: 56 | E216: 15
A218: 2 | B218: Would credit for university courses negatively affect the FCAS designation? | H218: Yes | I218: No
H219: 129 | I219: 141
A221: 3 | B221: How long should travel time be (based on first full-time casualty employment)?
C222: <4 | D222: 6
C223: 4 | D223: 7
C224: 5 | D224: 60
C225: 6 | D225: 47
C226: 7 | D226: 69
C227: 8 | D227: 48
C228: 9 | D228: 3
C229: 10 | D229: 22
C230: >10 | D230: =4+2 -> 6
A232: 4 | B232: Methods to reduce travel time:
B233: Reduce exams | E233: 66
B234: Reduce topics | E234: 110
B235: Reduce study time needed per exam | E235: 83
B236: Reduce breadth/depth of material | E236: 119
B237: More lenient pass marks | E237: 74
B238: Alternative learning methods (seminars, on-line courses, etc.) | E238: 99
B239: (Total replies, including blank) | E239: 653
H241: Yes | I241: No
A242: 5 | B242: Should we reduce amount of life contingencies on our exams? | H242: 170 | I242: 61
A245: 6 | B245: Should CAS exams test emerging areas of practice? | H245: 99 | I245: 144
A247: 7 | B247: Should we give exam credit for non-actuarial designations (CPCU, CFA)? | H247: 110 | I247: 156
A249: 8 | B249: Should we introduce basic ratemaking, reserving, policy forms earlier? | H249: 203 | I249: 60
A251: 9 | B251: Any duties not covered that the CAS should address? | H251: 43 | I251: 150
