Workbook

Sheet Technology Definitions
B1: Technology Planner
A3: Technology | D3: Avg
A4: Categories | B4: Definitions | C4: Examples | D4: Life
A6: HIGH-TECH > | B6: Items that use application software that is primarily bit-processor reliant. | C6: P.C.'s, Laptops & any | D6: 3 Years
B7: Includes all types of administrative, end-user or any technology training: and | C7: associated software
B8: any implementation, installation or integration costs
A11: MID-RANGE TECHNOLOGY > | B11: Items that use platform based applications that may be bit processor reliant; | C11: Servers (all types) | D11: 4-5 Years
B12: but that don't have upgrades as often as "High Tech".
B13: Also includes all types of administrative, end-user or any technology training. | C13: Server Based Platform Software | D13: 0 Years
A15: INFRASTRUCTURE > | B15: Items that provide "backbone" to an entire network; but, inclusive of all structure | C15: Structured Cabling, Fiber, NIC's, | D15: 7+ Years
B16: necessary and including the NIC (Network Interface Card) to the end-user device. | C16: Wireless Transmitters &
C17: Receivers & Any Associated
C18: Connectors or Connecting
C19: Devices.

Sheet Financial Overview
B1: Technology Plan Investment Analysis
B3: (What's the "real" cost of implementing your Technology Plan)
A5: Number of Students in District/Campus | E5: 82000
A7: Number of Buildings in District | E7: 129
A9: Average # of Rooms (Admin & Class) in Building | E9: 30
A11: Current School/District General Fund Revenue | E11: 400000000
A13: Operating Budget Per Student Per Year | E13: =E11/E5 -> 4878.0488
A15: Operating Budget Per Student Per Day (Calendar Year) | E15: =E11/E5/365 -> 13.364517
A17: Current Return on Invested Capital (Opportunity Cost) | E17: 0.055
A19: Annual Compounded Interest Multiplier (Usually .75-.90) | E19: 0.0075
A21: Current Interest & Admin Fee of Educational Bond | E21: 0.06
A23: Current Cost of Successful Referendum (Usually 2%-4% of Bond Value) | E23: 0.005
A25: What do you believe is the useful life of High-Tech Equipment?
A26: (I.e., P.C.'s, Laptops, etc. - Usually 2-4 years) | E26: 3
A28: What do you believe is the useful life of Mid-Range Tech Equipment?
A29: (I.e., Servers, etc. - Usually 3-5 years) | E29: 4
A31: Annual Expected Technology Capital Budgeted | E31: 25000000
A33: Annual Solution Consulting, Design, RFP Creation & Completion Fees
A34: (Either In-house support or outsourced - (Usually 1-4% of the Project)) | E34: 0.03
A36: Annual "Loaded" Cost of On-Site Implementation Mgrs (In-House or Outsourced) | E36: =66*40000 -> 2640000
A38: Annual Cost Reduction (Not Depreciation) in High-End Technology | E38: 0.15002
A40: Annual Cost Reduction (Not Depreciation) in Mid-Range Technology | E40: 0.1
A42: Technology Goal - Average # of P.C.'s per Room (Include Labs in Average) | E42: 5
A44: WAN Connectivity Costs to Bell for Connecting Schools (Monthly, per Location) | E44: 400
A46: Connectivity Costs to "Bell" for Connecting Schools (Annually for District) | E46: =E44*E7*12 -> 619200
A48: Yr | C48: High-Tech | D48: Mid-Tech | E48: Infrastructure
A49: 1 | B49: Investment Mix | C49: 0 | D49: 0 | E49: 1
A50: =A49+1 -> 2 | B50: Investment Mix | C50: 0 | D50: 0 | E50: 1
A51: =A50+1 -> 3 | B51: Investment Mix | C51: 0 | D51: 0 | E51: 1
A52: =A51+1 -> 4 | B52: Investment Mix | C52: 0 | D52: 0 | E52: 1
A53: =A52+1 -> 5 | B53: Investment Mix | C53: 0 | D53: 0 | E53: 1
A54: 1 | B54: Investment | C54: =E31*C49 -> 0 | D54: =E31*D49 -> 0 | E54: =E31*E49 -> 25000000
A55: =A54+1 -> 2 | B55: Investment | C55: =E31*C50 -> 0 | D55: =D50*E31 -> 0 | E55: =E31*E50 -> 25000000
A56: =A55+1 -> 3 | B56: Investment | C56: =E31*C51 -> 0 | D56: =D51*E31 -> 0 | E56: =E31*E51 -> 25000000
A57: =A56+1 -> 4 | B57: Investment | C57: =C52*E31 -> 0 | D57: =D52*E31 -> 0 | E57: =E52*E31 -> 25000000
A58: =A57+1 -> 5 | B58: Investment | C58: =C53*E31 -> 0 | D58: =E31*D53 -> 0 | E58: =E53*E31 -> 25000000
B60: Technology Plan Investment Analysis
B62: (What's the "real" cost of implementing your Technology Plan)
B64: Primary | C64: Cash Purchase | D64: Cash Purchase | E64: Lucent "Low-Risk"
A65: Yr | B65: Purchase | C65: Using Capital | D65: Using Bonds | E65: Funding Program
A67: 1 | B67: High-Tech, Mid-Range Tech, Infrastructure & Training | C67: =E31 -> 25000000 | D67: =E31*5 -> 125000000 | E67: =-SUM(E54:E58)*E17 -> -6875000
A68: =A67+1 -> 2 | B68: High-Tech, Mid-Range Tech, Infrastructure & Training | C68: =E31 -> 25000000 | E68: =(((SUM(E54:E58)*0.75)*C113)+((SUM(D54:D58)*C114))+((SUM(C54:C58)*C115)))*12 -> 21363750
A69: =A68+1 -> 3 | B69: High-Tech, Mid-Range Tech, Infrastructure & Training | C69: =E31 -> 25000000 | E69: =E68 -> 21363750
A70: =A69+1 -> 4 | B70: High-Tech, Mid-Range Tech, Infrastructure & Training | C70: =E31 -> 25000000 | E70: =E69-((SUM(C54:C58)*C115*12))*(3*E38) -> 21363750
A71: =A70+1 -> 5 | B71: High-Tech, Mid-Range Tech, Infrastructure & Training | C71: =E31 -> 25000000 | E71: =E70-(((SUM(D54:D58)*C114*12)*(4*E40))) -> 21363750
A72: Subtotal | C72: =SUM(C67:C71) -> 125000000 | D72: =SUM(D67:D71) -> 125000000 | E72: =SUM(E68:E71) -> 85455000
A73: (+)
A74: Operating Expenses for Wide Area Network | C74: =(E46*5)+'Infrastructure Cost Analysis'!F42 -> 3612000 | D74: =C74 -> 3612000 | E74: =D74 -> 3612000
A75: (+)
A76: Solution Consulting, Design, RFP Design & Compl Fees | C76: =C72*E34 -> 3750000 | D76: =C72*E34 -> 3750000 | E76: 0
A77: (+)
A78: Interest Lost on Capital (Loss of Opportunity Costs) | C78: =C72*(E17+E19) -> 7812500 | D78: N/A | E78: N/A
A79: (+)
A80: Total Interest & Admin Fee Paid on "Initial" Bonds | C80: N/A | D80: =D72*0.94 -> 117500000 | E80: N/A
A81: (+)
A82: 1st Referendum Costs | C82: N/A | D82: =D72*E23 -> 625000 | E82: N/A
A83: (+)
A84: Cost of On-Site Implement. Mgr (In-House or Outsourced) | C84: =5*E36 -> 13200000 | D84: =E36*2 -> 5280000 | E84: =D84 -> 5280000
A85: (+)
A86: Replace on 1st day of year 4 for all year 1 "High-Tech" | C86: =(C54)-(C54*(E38*E26)) -> 0 | D86: Below | E86: Included above
A87: (+)
A88: Replace on 1st day of year 5 for all year 2 "High-Tech" | C88: =(C55)-(C55*(E38*E26)) -> 0 | D88: Below | E88: Included above
A89: (+)
A90: Replace on last day of year 5 for all year 1 "Mid-Tech" | C90: =(D54)-(D54*(E40*E29)) -> 0 | D90: Below | E90: Included above
A91: (+)
A92: Additional Bonds for years 4-9 Technology Replacement | C92: 0 | D92: =((SUM(C54:C58)+(SUM(D54:D58)))*0.75) -> 0 | E92: N/A
A93: (+)
A94: Total Interest (& Admin Fee) Paid on "Technology Replacement" Bonds | C94: N/A | D94: =D92*0.94 -> 0 | E94: N/A
A95: (+)
A96: Referendum Costs | C96: N/A | D96: =D92*E23 -> 0 | E96: N/A
A97: (-)
A98: LAN Infrastructure Savings (If done in 1st Yr - 25% Reduct) | C98: N/A | D98: =-((C67*E49)+(C68*E50)+(C69*E51)+(C70*E52)+(C71*E53))*0.25 -> -31250000 | E98: Included above
A99: (-)
A100: Savings (Operating & Capital) for LAN & WAN Infrastructure
A101: If done in 1st Yr, & Converted to Wireless vs. Wired | C101: N/A | D101: ='Infrastructure Cost Analysis'!J30+'Infrastructure Cost Analysis'!L43 -> -14262240 | E101: =D101 -> -14262240
A103: Total Expense | C103: =SUM(C72:C101) -> 153374500 | D103: =SUM(D72:D101) -> 210254760 | E103: =SUM(E72:E101)-E67 -> 86959760
A105: Reduction Using Lucent's Low-Risk Funding Program Over Using Budgeted Capital > | E105: =(E103/C103)-1 -> -0.43302335
A107: Reduction Using Lucent' s Low-Risk Funding Over Using Capital From Bonds > | E107: =(E103/D103)-1 -> -0.58640765
A110: Total Cost Per Student, Per Day Using Lucent "Lo-Risk" Tax-Exempt Funds > | E110: =E103/E5/(365*5) -> 0.5810876
A112: % of Current District Operating Budget That Should be Moved to Cover Technology Plan > | E112: =E110/E15 -> 0.04347988
C113: 0.01899
C114: 0.01667
C115: 0.02465

Sheet Infrastructure Cost Analysis
F1: Network Estimator
F2: (What's the "real" cost of implementing or adding to your network?)
A3: LOCAL AREA NETWORK | N3: Lucent "Lo-Risk"
A4: # of P.C.'s | B4: =B6*B5 -> 23220 | N4: Tax-Exempt Funds or
A5: # of P.C.'s per Room | B5: 6 | N5: Int Bearing Escrow
A6: # of Rooms | B6: ='Financial Overview'!E9*'Financial Overview'!E7 -> 3870 | E6: Unit Costs | I6: Total Costs | O6: Daily
A7: # of Students | B7: ='Financial Overview'!E5 -> 82000 | D7: Wired PC's | F7: Wireless | H7: Wired PC's | J7: Wireless | M7: Mo. Cost | O7: Student Cost
A8: Network Interface Card | D8: 100 | F8: 179 | H8: =D8*B4 -> 2322000 | J8: =F8*B4 -> 4156380 | M8: =J8*0.01899 -> 78929.656 | O8: =M8/30/B7 -> 0.032085226
A9: Network Interface Card (Hardware & Software) Installation | D9: 50 | F9: 50 | H9: =D9*B4 -> 1161000 | J9: =F9*B4 -> 1161000 | M9: =J9*0.01899 -> 22047.39 | O9: =M9/30/B7 -> 0.0089623537
A10: Desktop & Server Integr. & Testing (I.e., IP addressing & "ping") | D10: 100 | F10: 100 | H10: =D10*B4 -> 2322000 | J10: =F10*B4 -> 2322000 | M10: =J10*0.01899 -> 44094.78 | O10: =M10/30/B7 -> 0.017924707
A11: Wireless Access Points | D11: N/A | F11: 995 | H11: N/A | J11: =(B6/5)*F11 -> 770130 | M11: =J11*0.01667 -> 12838.067 | O11: =M11/30/B7 -> 0.0052187265
A12: Wireless Access Point Installation | D12: N/A | F12: 375 | H12: N/A | J12: =(B6/5)*F12 -> 290250 | M12: =J12*0.01667 -> 4838.4675 | O12: =M12/30/B7 -> 0.0019668567
A13: Structured Cabling (Cat 5E) | D13: 225 | F13: N/A | H13: =D13*B4 -> 5224500 | J13: N/A
A14: Wire Molding | D14: 25 | F14: N/A | H14: =D14*B4 -> 580500 | J14: N/A
A15: Electrical Wire & Outlets | D15: 125 | F15: N/A | H15: =D15*B4 -> 2902500 | J15: N/A
A16: Electrical "Main Amp Service" Upgrade (per room wired) | D16: 50 | F16: N/A | H16: =D16*B6 -> 193500 | J16: N/A
A17: Lightning Protection | D17: 25 | F17: ? | H17: =D17*B4 -> 580500 | J17: ? | M17: ? | O17: ?
A18: Hubs & Ethernet Switches | D18: =B4*50 -> 1161000 | F18: N/A | H18: =D18 -> 1161000 | J18: N/A
A19: Counterspace & Carpentry (Per 9 sq ft of material & labor) | D19: 25 | F19: N/A | H19: =D19*B4 -> 580500 | J19: N/A
A20: Desktop/Classroom Security (Key locks installed on all doors ) | D20: 200 | F20: N/A | H20: =D20*B6 -> 774000 | J20: N/A
A21: Sprinkler System upgrade (if necessary, per classroom) | D21: ? | F21: N/A | H21: ? | J21: N/A
A22: Physical "Footprint" Loss in Classroom | D22: ? | F22: N/A | H22: ? | J22: N/A
A23: HVAC (Air conditioning upgrade due to BTU displacement) | D23: ? | F23: N/A | H23: ? | J23: N/A
A24: Asbestos Abatement or Sealing | D24: ? | F24: N/A | H24: ? | J24: N/A
A25: Loss of Mobility - More fixed devices | D25: ? | F25: N/A | H25: ? | J25: N/A
A26: Internet Access/Use Training | D26: ? | F26: ? | H26: ? | J26: Included With Mobility | M26: ? | O26: ?
A27: Mobility carts | D27: N/A | F27: ? | H27: N/A | J27: ? | M27: ? | O27: ?
A28: Totals | H28: =SUM(H8:H27) -> 17802000 | J28: =SUM(J8:J27) -> 8699760 | M28: =SUM(M8:M27) -> 162748.36 | N28: =SUM(N8:N27) -> 0 | O28: =SUM(O8:O27) -> 0.06615787
A30: Wireless vs. Wired Savings > | J30: =-(H28-J28) -> -9102240 | L30: =J30/H28 -> -0.51130435 | M30: < Minimum Reductions
A32: WIDE AREA NETWORK | N32: With Lucent Low-Risk
A33: # of Locations | B33: ='Financial Overview'!E7 -> 129 | N33: Funding Program
A34: Students in coverage area | B34: ='Financial Overview'!E5 -> 82000 | E34: Hardware & Install Costs | K34: Monthly Costs | O34: Daily
D35: Per Drop | F35: Total | H35: PLUS > | J35: Unit | L35: Total | M35: Mo. Cost | O35: Student Cost
A36: WaveLan | D36: 7000 | F36: =B33*D36 -> 903000 | J36: 0 | M36: =F36*0.01899 -> 17147.97 | O36: =M36/30/B34 -> 0.0069707195
A38: Frame Relay (Both sides, 4 channel, 256K bandwidth) | D38: 4000 | F38: =D38*B33 -> 516000 | J38: 400 | L38: =J38*B33 -> 51600
A39: Wireless vs. Wired Savings (5 year amortization) | L39: =F36-(F38+(L38*60)) -> -2709000
A40: Reduction % | L40: =-(F36/L39+1) -> -0.66666667
A42: Point-To-Point T-1's (Both sides) | D42: 4000 | F42: =D42*B33 -> 516000 | J42: 600 | L42: =J42*B33 -> 77400
A43: Wireless vs. Wired Savings (5 year amortization) | L43: =F40-(F42+(L42*60)) -> -5160000
A44: Reduction % | L44: =-(F36/L43+1) -> -0.825
A46: Fiber Network | D46: 250000 | F46: =D46*B33 -> 32250000 | J46: 0 | L46: 0
A47: Wireless vs. Wired Savings (5 year amortization) | L47: =F36-F46 -> -31347000
A48: Reduction % | L48: =-(F36/L47+1) -> -0.97119342
