Workbook

Sheet Read Me First

Sheet (1)Tbl.Cnts

Sheet (2)Instructions

Sheet (3)TVM
D7: Input
D9: YEARS | E9: 0 | H9: =IF(E16>0,"BOP","EOP") -> EOP
D10: P/YR | E10: 12 | H10: =IF(E16=0,0,"") -> 0 | J10: =E13 -> 0
D11: N | E11: =E9*E10 -> 0 | H11: 1 | J11: =E14 -> 0
D12: I/YR | E12: 0
D13: PV | E13: 0
D14: PMT | E14: 0
D15: FV | E15: 0 | H15: =E11 -> 0 | J15: =J11 -> 0 | K15: + | M15: =E15 -> 0
D16: Beg 1/End 0 | E16: 0
J18: =E12 -> 0

Sheet (4)NPV-IRR Annual
F8: EOY | G8: Cash Flows | H8: + | I8: Sale Proceeds
F9: 0 | G9: 0
F10: 1 | G10: 0 | H10: + | I10: 0
F11: 2 | G11: 0 | H11: + | I11: 0
F12: 3 | G12: 0 | H12: + | I12: 0
F13: 4 | G13: 0 | H13: + | I13: 0
F14: 5 | G14: 0 | H14: + | I14: 0
F15: 6 | G15: 0 | H15: + | I15: 0
F16: 7 | G16: 0 | H16: + | I16: 0
F17: 8 | G17: 0 | H17: + | I17: 0
F18: 9 | G18: 0 | H18: + | I18: 0
F19: 10 | G19: 0 | H19: + | I19: 0
D21: NPV @ | E21: 0 | F21: = | G21: 0
E23: IRR | F23: = | G23: 0
F54: 0 | G54: =G9 -> 0
F55: 1 | G55: =G10+I10 -> 0
F56: 2 | G56: =G11+I11 -> 0
F57: 3 | G57: =G12+I12 -> 0
F58: 4 | G58: =G13+I13 -> 0
F59: 5 | G59: =G14+I14 -> 0
F60: 6 | G60: =G15+I15 -> 0
F61: 7 | G61: =G16+I16 -> 0
F62: 8 | G62: =G17+I17 -> 0
F63: 9 | G63: =G18+I18 -> 0
F64: 10 | G64: =G19+I19 -> 0
G66: =NPV(E21,G55:G64)+G54 -> 0
G68: =IF(G54=0,0,IRR(G54:G64,0.1)) -> 0

Sheet (5)NPV-IRR Annuities
D7: Payments Per Year | G7: 1 | H7: Amount
G8: CF 0 | H8: 0 | I8: # of Times
G9: CF 1 | H9: 0 | I9: 1
G10: CF 2 | H10: 0 | I10: 1
G11: CF 3 | H11: 0 | I11: 1
G12: CF 4 | H12: 0 | I12: 1
G13: CF 5 | H13: 0 | I13: 1
G14: CF 6 | H14: 0 | I14: 1
G15: CF 7 | H15: 0 | I15: 1
G16: CF 8 | H16: 0 | I16: 1
G17: CF 9 | H17: 0 | I17: 1
G18: CF 10 | H18: 0 | I18: 1
G19: CF 11 | H19: 0 | I19: 1
G20: CF 12 | H20: 0 | I20: 1
... G23: CF 15 | H23: 0 | I23: 1
E25: NPV @ | F25: 0 | G25: = | H25: 0
F27: IRR | G27: = | H27: 0
D33: 2
D35: =SUM(D33:D33) -> 2
G36: 0 | I36: =H8 -> 0
G37: 1 | H37: =PV($H$52/$G$7,I9,H9,,0) -> 0 | I37: =PV($H$52/$G$7,0,,H37,0) -> 0 | L37: =SUM(I37:I51)+I36 -> 0 | M37: =IF(OR(ISERROR(L37),$H$52>7),"error","no error") -> no error
G38: 2 | H38: =PV($H$52/$G$7,I10,H10,,0) -> 0 | I38: =PV($H$52/$G$7,SUM($I$9:I9),,H38,0) -> 0
G39: 3 | H39: =PV($H$52/$G$7,I11,H11,,0) -> 0 | I39: =PV($H$52/$G$7,SUM($I$9:I10),,H39,0) -> 0
G40: 4 | H40: =PV($H$52/$G$7,I12,H12,,0) -> 0 | I40: =PV($H$52/$G$7,SUM($I$9:I11),,H40,0) -> 0
G41: 5 | H41: =PV($H$52/$G$7,I13,H13,,0) -> 0 | I41: =PV($H$52/$G$7,SUM($I$9:I12),,H41,0) -> 0
G42: 6 | H42: =PV($H$52/$G$7,I14,H14,,0) -> 0 | I42: =PV($H$52/$G$7,SUM($I$9:I13),,H42,0) -> 0
G43: 7 | H43: =PV($H$52/$G$7,I15,H15,,0) -> 0 | I43: =PV($H$52/$G$7,SUM($I$9:I14),,H43,0) -> 0
G44: 8 | H44: =PV($H$52/$G$7,I16,H16,,0) -> 0 | I44: =PV($H$52/$G$7,SUM($I$9:I15),,H44,0) -> 0
G45: 9 | H45: =PV($H$52/$G$7,I17,H17,,0) -> 0 | I45: =PV($H$52/$G$7,SUM($I$9:I16),,H45,0) -> 0
G46: 10 | H46: =PV($H$52/$G$7,I18,H18,,0) -> 0 | I46: =PV($H$52/$G$7,SUM($I$9:I17),,H46,0) -> 0
G47: 11 | H47: =PV($H$52/$G$7,I19,H19,,0) -> 0 | I47: =PV($H$52/$G$7,SUM($I$9:I18),,H47,0) -> 0
G48: 12 | H48: =PV($H$52/$G$7,I20,H20,,0) -> 0 | I48: =PV($H$52/$G$7,SUM($I$9:I19),,H48,0) -> 0
G49: 13 | H49: =PV($H$52/$G$7,I21,H21,,0) -> 0 | I49: =PV($H$52/$G$7,SUM($I$9:I20),,H49,0) -> 0
... G51: 15 | H51: =PV($H$52/$G$7,I23,H23,,0) -> 0 | I51: =PV($H$52/$G$7,SUM($I$9:I22),,H51,0) -> 0
H52: 0

Sheet (6)Amortization Schedule
E6: 0
E7: 0
E8: 0
E9: 0
E10: =IF(E8=0,0,IF(E8>0,ROUND(-PMT(E9/E6,E7*E6,E8,0,0),2),IF(E8<0,ROUND(PMT(E9/E6,E7*E6,E8,0,0),2)))) -> 0
A15: =IF(I15<10,0,1) -> 0 | C15: =IF(E8<0,E8*-1,E8) -> 0 | E15: =IF($E$9=0,0,ROUND(C15*($E$9/$E$6),2)) -> 0 | G15: =IF(C15<10,0,$E$10-E15) -> 0 | I15: =IF(C15-G15<10,0,C15-G15) -> 0
A16: =IF(I15<10,0,(A15+1)) -> 0 | C16: =I15 -> 0 | E16: =IF($E$9=0,0,ROUND(C16*($E$9/$E$6),2)) -> 0 | G16: =IF(C16<10,0,$E$10-E16) -> 0 | I16: =IF(C16-G16<10,0,C16-G16) -> 0
A17: =IF(I16<10,0,(A16+1)) -> 0 | C17: =I16 -> 0 | E17: =IF($E$9=0,0,ROUND(C17*($E$9/$E$6),2)) -> 0 | G17: =IF(C17<10,0,$E$10-E17) -> 0 | I17: =IF(C17-G17<10,0,C17-G17) -> 0
A18: =IF(I17<10,0,(A17+1)) -> 0 | C18: =I17 -> 0 | E18: =IF($E$9=0,0,ROUND(C18*($E$9/$E$6),2)) -> 0 | G18: =IF(C18<10,0,$E$10-E18) -> 0 | I18: =IF(C18-G18<10,0,C18-G18) -> 0
A19: =IF(I18<10,0,(A18+1)) -> 0 | C19: =I18 -> 0 | E19: =IF($E$9=0,0,ROUND(C19*($E$9/$E$6),2)) -> 0 | G19: =IF(C19<10,0,$E$10-E19) -> 0 | I19: =IF(C19-G19<10,0,C19-G19) -> 0
A20: =IF(I19<10,0,(A19+1)) -> 0 | C20: =I19 -> 0 | E20: =IF($E$9=0,0,ROUND(C20*($E$9/$E$6),2)) -> 0 | G20: =IF(C20<10,0,$E$10-E20) -> 0 | I20: =IF(C20-G20<10,0,C20-G20) -> 0
A21: =IF(I20<10,0,(A20+1)) -> 0 | C21: =I20 -> 0 | E21: =IF($E$9=0,0,ROUND(C21*($E$9/$E$6),2)) -> 0 | G21: =IF(C21<10,0,$E$10-E21) -> 0 | I21: =IF(C21-G21<10,0,C21-G21) -> 0
A22: =IF(I21<10,0,(A21+1)) -> 0 | C22: =I21 -> 0 | E22: =IF($E$9=0,0,ROUND(C22*($E$9/$E$6),2)) -> 0 | G22: =IF(C22<10,0,$E$10-E22) -> 0 | I22: =IF(C22-G22<10,0,C22-G22) -> 0
A23: =IF(I22<10,0,(A22+1)) -> 0 | C23: =I22 -> 0 | E23: =IF($E$9=0,0,ROUND(C23*($E$9/$E$6),2)) -> 0 | G23: =IF(C23<10,0,$E$10-E23) -> 0 | I23: =IF(C23-G23<10,0,C23-G23) -> 0
A24: =IF(I23<10,0,(A23+1)) -> 0 | C24: =I23 -> 0 | E24: =IF($E$9=0,0,ROUND(C24*($E$9/$E$6),2)) -> 0 | G24: =IF(C24<10,0,$E$10-E24) -> 0 | I24: =IF(C24-G24<10,0,C24-G24) -> 0
A25: =IF(I24<10,0,(A24+1)) -> 0 | C25: =I24 -> 0 | E25: =IF($E$9=0,0,ROUND(C25*($E$9/$E$6),2)) -> 0 | G25: =IF(C25<10,0,$E$10-E25) -> 0 | I25: =IF(C25-G25<10,0,C25-G25) -> 0
A26: =IF(I25<10,0,(A25+1)) -> 0 | C26: =I25 -> 0 | E26: =IF($E$9=0,0,ROUND(C26*($E$9/$E$6),2)) -> 0 | G26: =IF(C26<10,0,$E$10-E26) -> 0 | I26: =IF(C26-G26<10,0,C26-G26) -> 0
A27: =IF(I26<10,0,(A26+1)) -> 0 | C27: =I26 -> 0 | E27: =IF($E$9=0,0,ROUND(C27*($E$9/$E$6),2)) -> 0 | G27: =IF(C27<10,0,$E$10-E27) -> 0 | I27: =IF(C27-G27<10,0,C27-G27) -> 0
... A374: =IF(I373<10,0,(A373+1)) -> 0 | C374: =I373 -> 0 | E374: =IF($E$9=0,0,ROUND(C374*($E$9/$E$6),2)) -> 0 | G374: =IF(C374<10,0,$E$10-E374) -> 0 | I374: =IF(C374-G374<10,0,C374-G374) -> 0
E375: =IF($E$9=0,0,ROUND(C375*($E$9/$E$6),2)) -> 0
E376: =IF($E$9=0,0,ROUND(C376*($E$9/$E$6),2)) -> 0
E377: =IF($E$9=0,0,ROUND(C377*($E$9/$E$6),2)) -> 0
E378: =IF($E$9=0,0,ROUND(C378*($E$9/$E$6),2)) -> 0
E379: =IF($E$9=0,0,ROUND(C379*($E$9/$E$6),2)) -> 0
E380: =IF($E$9=0,0,ROUND(C380*($E$9/$E$6),2)) -> 0
E381: =IF($E$9=0,0,ROUND(C381*($E$9/$E$6),2)) -> 0
E382: =IF($E$9=0,0,ROUND(C382*($E$9/$E$6),2)) -> 0
E383: =IF($E$9=0,0,ROUND(C383*($E$9/$E$6),2)) -> 0
E384: =IF($E$9=0,0,ROUND(C384*($E$9/$E$6),2)) -> 0
E385: =IF($E$9=0,0,ROUND(C385*($E$9/$E$6),2)) -> 0
E386: =IF($E$9=0,0,ROUND(C386*($E$9/$E$6),2)) -> 0
... E824: =IF($E$9=0,0,ROUND(C824*($E$9/$E$6),2)) -> 0

Sheet (7)Annual Summary
A6: Payments Per Year | E6: ='(6)Amortization Schedule'!E6 -> 0 | I6: =E10*E6 -> 0
A7: Amortization Period(Years) | E7: ='(6)Amortization Schedule'!E7 -> 0
A8: Loan Amount | E8: =IF('(6)Amortization Schedule'!E8<0,'(6)Amortization Schedule'!E8*-1,'(6)Amortization Schedule'!E8) -> 0
A9: Annual Interest Rate | E9: ='(6)Amortization Schedule'!E9 -> 0
A10: Periodic Payment | E10: ='(6)Amortization Schedule'!E10 -> 0 | I10: 0
I11: 0
I12: 0
I13: 0
A15: =IF(I15<10,0,1) -> 0 | C15: =E8 -> 0 | E15: =IF($E$6=12,SUM('(6)Amortization Schedule'!E15:E26),IF($E$6=2,SUM('(6)Amortization Schedule'!E15:E16),IF($E$6=4,SUM('(6)Amortization Schedule'!E15:E18),IF($E$6=1,'(6)Amortization Schedule'!E15,0)))) -> 0 | G15: =IF(C15<10,0,($E$10*$E$6)-E15) -> 0 | I15: =ROUND(IF(C15-G15<10,0,C15-G15),2) -> 0
A16: =IF(I15<10,0,(A15+1)) -> 0 | C16: =I15 -> 0 | E16: =IF($E$6=12,SUM('(6)Amortization Schedule'!E27:E38),IF($E$6=2,SUM('(6)Amortization Schedule'!E17:E18),IF($E$6=4,SUM('(6)Amortization Schedule'!E19:E22),IF($E$6=1,'(6)Amortization Schedule'!E16,0)))) -> 0 | G16: =IF(C16<10,0,($E$10*$E$6)-E16) -> 0 | I16: =ROUND(IF(C16-G16<10,0,C16-G16),2) -> 0
A17: =IF(I16<10,0,(A16+1)) -> 0 | C17: =I16 -> 0 | E17: =IF($E$6=12,SUM('(6)Amortization Schedule'!E39:E50),IF($E$6=2,SUM('(6)Amortization Schedule'!E19:E20),IF($E$6=4,SUM('(6)Amortization Schedule'!E23:E26),IF($E$6=1,'(6)Amortization Schedule'!E17,0)))) -> 0 | G17: =IF(C17<10,0,($E$10*$E$6)-E17) -> 0 | I17: =ROUND(IF(C17-G17<10,0,C17-G17),2) -> 0
A18: =IF(I17<10,0,(A17+1)) -> 0 | C18: =I17 -> 0 | E18: =IF($E$6=12,SUM('(6)Amortization Schedule'!E51:E62),IF($E$6=2,SUM('(6)Amortization Schedule'!E21:E22),IF($E$6=4,SUM('(6)Amortization Schedule'!E27:E30),IF($E$6=1,'(6)Amortization Schedule'!E18,0)))) -> 0 | G18: =IF(C18<10,0,($E$10*$E$6)-E18) -> 0 | I18: =ROUND(IF(C18-G18<10,0,C18-G18),2) -> 0
A19: =IF(I18<10,0,(A18+1)) -> 0 | C19: =I18 -> 0 | E19: =IF($E$6=12,SUM('(6)Amortization Schedule'!E63:E74),IF($E$6=2,SUM('(6)Amortization Schedule'!E23:E24),IF($E$6=4,SUM('(6)Amortization Schedule'!E31:E34),IF($E$6=1,'(6)Amortization Schedule'!E19,0)))) -> 0 | G19: =IF(C19<10,0,($E$10*$E$6)-E19) -> 0 | I19: =ROUND(IF(C19-G19<10,0,C19-G19),2) -> 0
A20: =IF(I19<10,0,(A19+1)) -> 0 | C20: =I19 -> 0 | E20: =IF($E$6=12,SUM('(6)Amortization Schedule'!E75:E86),IF($E$6=2,SUM('(6)Amortization Schedule'!E25:E26),IF($E$6=4,SUM('(6)Amortization Schedule'!E35:E38),IF($E$6=1,'(6)Amortization Schedule'!E20,0)))) -> 0 | G20: =IF(C20<10,0,($E$10*$E$6)-E20) -> 0 | I20: =ROUND(IF(C20-G20<10,0,C20-G20),2) -> 0
A21: =IF(I20<10,0,(A20+1)) -> 0 | C21: =I20 -> 0 | E21: =IF($E$6=12,SUM('(6)Amortization Schedule'!E87:E98),IF($E$6=2,SUM('(6)Amortization Schedule'!E27:E28),IF($E$6=4,SUM('(6)Amortization Schedule'!E39:E42),IF($E$6=1,'(6)Amortization Schedule'!E21,0)))) -> 0 | G21: =IF(C21<10,0,($E$10*$E$6)-E21) -> 0 | I21: =ROUND(IF(C21-G21<10,0,C21-G21),2) -> 0
A22: =IF(I21<10,0,(A21+1)) -> 0 | C22: =I21 -> 0 | E22: =IF($E$6=12,SUM('(6)Amortization Schedule'!E99:E110),IF($E$6=2,SUM('(6)Amortization Schedule'!E29:E30),IF($E$6=4,SUM('(6)Amortization Schedule'!E43:E46),IF($E$6=1,'(6)Amortization Schedule'!E22,0)))) -> 0 | G22: =IF(C22<10,0,($E$10*$E$6)-E22) -> 0 | I22: =ROUND(IF(C22-G22<10,0,C22-G22),2) -> 0
A23: =IF(I22<10,0,(A22+1)) -> 0 | C23: =I22 -> 0 | E23: =IF($E$6=12,SUM('(6)Amortization Schedule'!E111:E122),IF($E$6=2,SUM('(6)Amortization Schedule'!E31:E32),IF($E$6=4,SUM('(6)Amortization Schedule'!E47:E50),IF($E$6=1,'(6)Amortization Schedule'!E23,0)))) -> 0 | G23: =IF(C23<10,0,($E$10*$E$6)-E23) -> 0 | I23: =ROUND(IF(C23-G23<10,0,C23-G23),2) -> 0
A24: =IF(I23<10,0,(A23+1)) -> 0 | C24: =I23 -> 0 | E24: =IF($E$6=12,SUM('(6)Amortization Schedule'!E123:E134),IF($E$6=2,SUM('(6)Amortization Schedule'!E33:E34),IF($E$6=4,SUM('(6)Amortization Schedule'!E51:E54),IF($E$6=1,'(6)Amortization Schedule'!E24,0)))) -> 0 | G24: =IF(C24<10,0,($E$10*$E$6)-E24) -> 0 | I24: =ROUND(IF(C24-G24<10,0,C24-G24),2) -> 0
A25: =IF(I24<10,0,(A24+1)) -> 0 | C25: =I24 -> 0 | E25: =IF($E$6=12,SUM('(6)Amortization Schedule'!E135:E146),IF($E$6=2,SUM('(6)Amortization Schedule'!E35:E36),IF($E$6=4,SUM('(6)Amortization Schedule'!E55:E58),IF($E$6=1,'(6)Amortization Schedule'!E25,0)))) -> 0 | G25: =IF(C25<10,0,($E$10*$E$6)-E25) -> 0 | I25: =ROUND(IF(C25-G25<10,0,C25-G25),2) -> 0
A26: =IF(I25<10,0,(A25+1)) -> 0 | C26: =I25 -> 0 | E26: =IF($E$6=12,SUM('(6)Amortization Schedule'!E147:E158),IF($E$6=2,SUM('(6)Amortization Schedule'!E37:E38),IF($E$6=4,SUM('(6)Amortization Schedule'!E59:E62),IF($E$6=1,'(6)Amortization Schedule'!E26,0)))) -> 0 | G26: =IF(C26<10,0,($E$10*$E$6)-E26) -> 0 | I26: =ROUND(IF(C26-G26<10,0,C26-G26),2) -> 0
A27: =IF(I26<10,0,(A26+1)) -> 0 | C27: =I26 -> 0 | E27: =IF($E$6=12,SUM('(6)Amortization Schedule'!E159:E170),IF($E$6=2,SUM('(6)Amortization Schedule'!E39:E40),IF($E$6=4,SUM('(6)Amortization Schedule'!E63:E66),IF($E$6=1,'(6)Amortization Schedule'!E27,0)))) -> 0 | G27: =IF(C27<10,0,($E$10*$E$6)-E27) -> 0 | I27: =ROUND(IF(C27-G27<10,0,C27-G27),2) -> 0
A28: =IF(I27<10,0,(A27+1)) -> 0 | C28: =I27 -> 0 | E28: =IF($E$6=12,SUM('(6)Amortization Schedule'!E171:E182),IF($E$6=2,SUM('(6)Amortization Schedule'!E41:E42),IF($E$6=4,SUM('(6)Amortization Schedule'!E67:E70),IF($E$6=1,'(6)Amortization Schedule'!E28,0)))) -> 0 | G28: =IF(C28<10,0,($E$10*$E$6)-E28) -> 0 | I28: =ROUND(IF(C28-G28<10,0,C28-G28),2) -> 0
A29: =IF(I28<10,0,(A28+1)) -> 0 | C29: =I28 -> 0 | E29: =IF($E$6=12,SUM('(6)Amortization Schedule'!E183:E194),IF($E$6=2,SUM('(6)Amortization Schedule'!E43:E44),IF($E$6=4,SUM('(6)Amortization Schedule'!E71:E74),IF($E$6=1,'(6)Amortization Schedule'!E29,0)))) -> 0 | G29: =IF(C29<10,0,($E$10*$E$6)-E29) -> 0 | I29: =ROUND(IF(C29-G29<10,0,C29-G29),2) -> 0
A30: =IF(I29<10,0,(A29+1)) -> 0 | C30: =I29 -> 0 | E30: =IF($E$6=12,SUM('(6)Amortization Schedule'!E195:E206),IF($E$6=2,SUM('(6)Amortization Schedule'!E45:E46),IF($E$6=4,SUM('(6)Amortization Schedule'!E75:E78),IF($E$6=1,'(6)Amortization Schedule'!E30,0)))) -> 0 | G30: =IF(C30<10,0,($E$10*$E$6)-E30) -> 0 | I30: =ROUND(IF(C30-G30<10,0,C30-G30),2) -> 0
A31: =IF(I30<10,0,(A30+1)) -> 0 | C31: =I30 -> 0 | E31: =IF($E$6=12,SUM('(6)Amortization Schedule'!E207:E218),IF($E$6=2,SUM('(6)Amortization Schedule'!E47:E48),IF($E$6=4,SUM('(6)Amortization Schedule'!E79:E82),IF($E$6=1,'(6)Amortization Schedule'!E31,0)))) -> 0 | G31: =IF(C31<10,0,($E$10*$E$6)-E31) -> 0 | I31: =ROUND(IF(C31-G31<10,0,C31-G31),2) -> 0
A32: =IF(I31<10,0,(A31+1)) -> 0 | C32: =I31 -> 0 | E32: =IF($E$6=12,SUM('(6)Amortization Schedule'!E219:E230),IF($E$6=2,SUM('(6)Amortization Schedule'!E49:E50),IF($E$6=4,SUM('(6)Amortization Schedule'!E83:E86),IF($E$6=1,'(6)Amortization Schedule'!E32,0)))) -> 0 | G32: =IF(C32<10,0,($E$10*$E$6)-E32) -> 0 | I32: =ROUND(IF(C32-G32<10,0,C32-G32),2) -> 0
A33: =IF(I32<10,0,(A32+1)) -> 0 | C33: =I32 -> 0 | E33: =IF($E$6=12,SUM('(6)Amortization Schedule'!E231:E242),IF($E$6=2,SUM('(6)Amortization Schedule'!E51:E52),IF($E$6=4,SUM('(6)Amortization Schedule'!E87:E90),IF($E$6=1,'(6)Amortization Schedule'!E33,0)))) -> 0 | G33: =IF(C33<10,0,($E$10*$E$6)-E33) -> 0 | I33: =ROUND(IF(C33-G33<10,0,C33-G33),2) -> 0
A34: =IF(I33<10,0,(A33+1)) -> 0 | C34: =I33 -> 0 | E34: =IF($E$6=12,SUM('(6)Amortization Schedule'!E243:E254),IF($E$6=2,SUM('(6)Amortization Schedule'!E53:E54),IF($E$6=4,SUM('(6)Amortization Schedule'!E91:E94),IF($E$6=1,'(6)Amortization Schedule'!E34,0)))) -> 0 | G34: =IF(C34<10,0,($E$10*$E$6)-E34) -> 0 | I34: =ROUND(IF(C34-G34<10,0,C34-G34),2) -> 0
A35: =IF(I34<10,0,(A34+1)) -> 0 | C35: =I34 -> 0 | E35: =IF($E$6=12,SUM('(6)Amortization Schedule'!E255:E266),IF($E$6=2,SUM('(6)Amortization Schedule'!E55:E56),IF($E$6=4,SUM('(6)Amortization Schedule'!E95:E98),IF($E$6=1,'(6)Amortization Schedule'!E35,0)))) -> 0 | G35: =IF(C35<10,0,($E$10*$E$6)-E35) -> 0 | I35: =ROUND(IF(C35-G35<10,0,C35-G35),2) -> 0
A36: =IF(I35<10,0,(A35+1)) -> 0 | C36: =I35 -> 0 | E36: =IF($E$6=12,SUM('(6)Amortization Schedule'!E267:E278),IF($E$6=2,SUM('(6)Amortization Schedule'!E57:E58),IF($E$6=4,SUM('(6)Amortization Schedule'!E99:E102),IF($E$6=1,'(6)Amortization Schedule'!E36,0)))) -> 0 | G36: =IF(C36<10,0,($E$10*$E$6)-E36) -> 0 | I36: =ROUND(IF(C36-G36<10,0,C36-G36),2) -> 0
A37: =IF(I36<10,0,(A36+1)) -> 0 | C37: =I36 -> 0 | E37: =IF($E$6=12,SUM('(6)Amortization Schedule'!E279:E290),IF($E$6=2,SUM('(6)Amortization Schedule'!E59:E60),IF($E$6=4,SUM('(6)Amortization Schedule'!E103:E106),IF($E$6=1,'(6)Amortization Schedule'!E37,0)))) -> 0 | G37: =IF(C37<10,0,($E$10*$E$6)-E37) -> 0 | I37: =ROUND(IF(C37-G37<10,0,C37-G37),2) -> 0
A38: =IF(I37<10,0,(A37+1)) -> 0 | C38: =I37 -> 0 | E38: =IF($E$6=12,SUM('(6)Amortization Schedule'!E291:E302),IF($E$6=2,SUM('(6)Amortization Schedule'!E61:E62),IF($E$6=4,SUM('(6)Amortization Schedule'!E107:E110),IF($E$6=1,'(6)Amortization Schedule'!E38,0)))) -> 0 | G38: =IF(C38<10,0,($E$10*$E$6)-E38) -> 0 | I38: =ROUND(IF(C38-G38<10,0,C38-G38),2) -> 0
A39: =IF(I38<10,0,(A38+1)) -> 0 | C39: =I38 -> 0 | E39: =IF($E$6=12,SUM('(6)Amortization Schedule'!E303:E314),IF($E$6=2,SUM('(6)Amortization Schedule'!E63:E64),IF($E$6=4,SUM('(6)Amortization Schedule'!E111:E114),IF($E$6=1,'(6)Amortization Schedule'!E39,0)))) -> 0 | G39: =IF(C39<10,0,($E$10*$E$6)-E39) -> 0 | I39: =ROUND(IF(C39-G39<10,0,C39-G39),2) -> 0
A40: =IF(I39<10,0,(A39+1)) -> 0 | C40: =I39 -> 0 | E40: =IF($E$6=12,SUM('(6)Amortization Schedule'!E315:E326),IF($E$6=2,SUM('(6)Amortization Schedule'!E65:E66),IF($E$6=4,SUM('(6)Amortization Schedule'!E115:E118),IF($E$6=1,'(6)Amortization Schedule'!E40,0)))) -> 0 | G40: =IF(C40<10,0,($E$10*$E$6)-E40) -> 0 | I40: =ROUND(IF(C40-G40<10,0,C40-G40),2) -> 0
A41: =IF(I40<10,0,(A40+1)) -> 0 | C41: =I40 -> 0 | E41: =IF($E$6=12,SUM('(6)Amortization Schedule'!E327:E338),IF($E$6=2,SUM('(6)Amortization Schedule'!E67:E68),IF($E$6=4,SUM('(6)Amortization Schedule'!E119:E122),IF($E$6=1,'(6)Amortization Schedule'!E41,0)))) -> 0 | G41: =IF(C41<10,0,($E$10*$E$6)-E41) -> 0 | I41: =ROUND(IF(C41-G41<10,0,C41-G41),2) -> 0
A42: =IF(I41<10,0,(A41+1)) -> 0 | C42: =I41 -> 0 | E42: =IF($E$6=12,SUM('(6)Amortization Schedule'!E339:E350),IF($E$6=2,SUM('(6)Amortization Schedule'!E69:E70),IF($E$6=4,SUM('(6)Amortization Schedule'!E123:E126),IF($E$6=1,'(6)Amortization Schedule'!E42,0)))) -> 0 | G42: =IF(C42<10,0,($E$10*$E$6)-E42) -> 0 | I42: =ROUND(IF(C42-G42<10,0,C42-G42),2) -> 0
A43: =IF(I42<10,0,(A42+1)) -> 0 | C43: =I42 -> 0 | E43: =IF($E$6=12,SUM('(6)Amortization Schedule'!E351:E362),IF($E$6=2,SUM('(6)Amortization Schedule'!E71:E72),IF($E$6=4,SUM('(6)Amortization Schedule'!E127:E130),IF($E$6=1,'(6)Amortization Schedule'!E43,0)))) -> 0 | G43: =IF(C43<10,0,($E$10*$E$6)-E43) -> 0 | I43: =ROUND(IF(C43-G43<10,0,C43-G43),2) -> 0
A44: =IF(I43<10,0,(A43+1)) -> 0 | C44: =I43 -> 0 | E44: =IF($E$6=12,SUM('(6)Amortization Schedule'!E363:E374),IF($E$6=2,SUM('(6)Amortization Schedule'!E73:E74),IF($E$6=4,SUM('(6)Amortization Schedule'!E131:E134),IF($E$6=1,'(6)Amortization Schedule'!E44,0)))) -> 0 | G44: =IF(C44<10,0,($E$10*$E$6)-E44) -> 0 | I44: =ROUND(IF(C44-G44<10,0,C44-G44),2) -> 0

Sheet (8)Statistics
B3: Item # | C3: Input
B4: 1
B5: =B4+1 -> 2
B6: =B5+1 -> 3
B7: =B6+1 -> 4
B8: =B7+1 -> 5
B9: =B8+1 -> 6
B10: =B9+1 -> 7
B11: =B10+1 -> 8
B12: =B11+1 -> 9 | E12: Mean =
B13: =B12+1 -> 10 | E13: Median =
B14: =B13+1 -> 11 | E14: Standard Deviation =
B15: =B14+1 -> 12
B16: =B15+1 -> 13
B17: =B16+1 -> 14
B18: =B17+1 -> 15
B19: =B18+1 -> 16
B20: =B19+1 -> 17
B21: =B20+1 -> 18
B22: =B21+1 -> 19
B23: =B22+1 -> 20
B24: =B23+1 -> 21
B25: =B24+1 -> 22
B26: =B25+1 -> 23
... B28: =B27+1 -> 25
