Workbook

Sheet Balance Sheet
A1: Advance Auto Parts, Inc. and Subsidiaries
A2: Consolidated Balance Sheets
A3: (in thousands)
F6: July 12, | H6: December 28, | J6: July 13,
F7: 2003 | H7: 2002 | J7: 2002
A9: Assets
A11: Current assets:
B12: Cash and cash equivalents | F12: 46074 | H12: 13885 | J12: 39544
B13: Receivables, net | F13: 93350 | H13: 102574 | J13: 118101
B14: Inventories, net | F14: 1079884 | H14: 1048803 | J14: 1074653
B15: Other current assets | F15: 34664 | H15: 20210 | J15: 49970
C16: Total current assets | F16: 1253972 | H16: 1185472 | J16: 1282268
B18: Property and equipment, net | F18: 711222 | H18: 728432 | J18: 715697
B19: Assets held for sale | F19: 24897 | H19: 28346 | J19: 46200
B20: Other assets, net | F20: 11997 | H20: 22975 | J20: 25933
F21: 2002088 | H21: 1965225 | J21: 2070098
A23: Liabilities and Stockholders' Equity
A25: Current liabilities:
B26: Bank overdrafts | F26: 14372 | H26: 869 | J26: 0
B27: Current portion of long-term debt | F27: 4577 | H27: 10690 | J27: 11549
B28: Accounts payable | F28: 591827 | H28: 470740 | J28: 585119
B29: Accrued expenses | F29: 207055 | H29: 208176 | J29: 209192
B30: Other current liabilities | F30: 44068 | H30: 32101 | J30: 39676
C31: Total current liabilities | F31: 861899 | H31: 722576 | J31: 845536
B33: Long-term debt | F33: 531512 | H33: 724832 | J33: 762270
B34: Other long-term liabilities | F34: 67698 | H34: 49461 | J34: 35400
B35: Total stockholders' equity | F35: 540979 | H35: 468356 | J35: 426892
F36: 2002088 | H36: 1965225 | J36: 2070098
A44: NOTE: These balance sheets do not include the footnotes required by generally accepted
A45: accounting principles for complete financial statements.

Sheet 2nd QTR 03
A1: Advance Auto Parts, Inc. and Subsidiaries
A2: Consolidated Statements of Operations
A3: Twelve Week Periods Ended
A4: (in thousands, except per share data)
D6: 37814
G7: Adjustment for
G8: Non-recurring | I8: Comparable | L8: GAAP | N8: Comparable | P8: GAAP | T8: Comparable
D9: GAAP | G9: Items | I9: 2003 | L9: Inc (Dcr) | N9: Inc (Dcr) | P9: $ Change | R9: % Change | T9: $ Change | V9: % Change
A11: Net sales | D11: 839168 | E11: 1 | G11: 0 | I11: 839168 | J11: =+I11/$I$11 -> 1 | L11: =+E11-'2nd QTR 02'!E11 -> 0 | N11: =+J11-'2nd QTR 02'!J11 -> 0 | P11: =+D11-'2nd QTR 02'!D11 -> 46451 | R11: =+P11/'2nd QTR 02'!$D11 -> 0.058597204 | T11: =+I11-'2nd QTR 02'!I11 -> 46451 | V11: =+T11/'2nd QTR 02'!$I11 -> 0.058597204
A13: Cost of sales, including purchasing and warehousing costs | D13: 457881 | E13: 0.54563687 | G13: 0 | I13: 457881 | J13: =+I13/$I$11 -> 0.54563687 | L13: =+E13-'2nd QTR 02'!E13 -> -0.014087472 | N13: =+J13-'2nd QTR 02'!J13 -> -0.014087472 | P13: =+D13-'2nd QTR 02'!D13 -> 14178 | R13: =+P13/'2nd QTR 02'!$D13 -> 0.031953807 | T13: =+I13-'2nd QTR 02'!I13 -> 14178 | V13: =+T13/'2nd QTR 02'!$I13 -> 0.031953807
B15: Gross profit | D15: 381287 | E15: 0.45436313 | G15: 0 | I15: 381287 | J15: =+I15/$I$11 -> 0.45436313 | L15: =+E15-'2nd QTR 02'!E15 -> 0.014087472 | N15: =+J15-'2nd QTR 02'!J15 -> 0.014087472 | P15: =+D15-'2nd QTR 02'!D15 -> 32273 | R15: =+P15/'2nd QTR 02'!$D15 -> 0.09246907 | T15: =+I15-'2nd QTR 02'!I15 -> 32273 | V15: =+T15/'2nd QTR 02'!$I15 -> 0.09246907
A17: Selling, general and administrative expenses | D17: 303310 | E17: 0.36144133 | G17: -2890 | H17: ( a ) | I17: 300420 | J17: =+I17/$I$11 -> 0.35799745 | L17: =+E17-'2nd QTR 02'!E17 -> -0.0066143546 | N17: =+J17-'2nd QTR 02'!J17 -> -0.00043437863 | P17: =+D17-'2nd QTR 02'!D17 -> 11546 | R17: =+P17/'2nd QTR 02'!$D17 -> 0.03957308 | T17: =+I17-'2nd QTR 02'!I17 -> 16285 | V17: =+T17/'2nd QTR 02'!$I17 -> 0.057314305
B19: Operating income | D19: 77977 | E19: 0.092921799 | G19: 2890 | I19: 80867 | J19: =+I19/$I$11 -> 0.096365686 | L19: =+E19-'2nd QTR 02'!E19 -> 0.020701826 | N19: =+J19-'2nd QTR 02'!J19 -> 0.01452185 | P19: =+D19-'2nd QTR 02'!D19 -> 20727 | R19: =+P19/'2nd QTR 02'!$D19 -> 0.36204367 | T19: =+I19-'2nd QTR 02'!I19 -> 15988 | V19: =+T19/'2nd QTR 02'!$I19 -> 0.24642797
A21: Other, net:
A22: Interest expense | D22: -7182 | E22: -0.008558477 | G22: 0 | I22: -7182 | J22: =+I22/$I$11 -> -0.008558477 | L22: =+E22-'2nd QTR 02'!E22 -> 0.015561102 | N22: =+J22-'2nd QTR 02'!J22 -> 0.015561102 | P22: =+D22-'2nd QTR 02'!D22 -> 11938 | R22: =+P22/'2nd QTR 02'!$D22 -> -0.62437238 | T22: =+I22-'2nd QTR 02'!I22 -> 11938 | V22: =+T22/'2nd QTR 02'!$I22 -> -0.62437238
A23: Loss on extinguishment of debt | D23: -254 | E23: -0.00030268075 | G23: 0 | I23: -254 | J23: =+I23/$I$11 -> -0.00030268075 | L23: =+E23-'2nd QTR 02'!E23 -> 0.01541289 | N23: =+J23-'2nd QTR 02'!J23 -> -0.00030268075 | P23: =+D23-'2nd QTR 02'!D23 -> 12204 | R23: =+P23/'2nd QTR 02'!$D23 -> -0.97961149 | T23: =+I23-'2nd QTR 02'!I23 -> -254 | V23: =+T23/'2nd QTR 02'!$I23 -> #DIV/0!
A24: Other income, net | D24: 121 | E24: 0.00014419044 | G24: 0 | I24: 121 | J24: =+I24/$I$11 -> 0.00014419044 | L24: =+E24-'2nd QTR 02'!E24 -> -0.00033138912 | N24: =+J24-'2nd QTR 02'!J24 -> -0.00033138912 | P24: =+D24-'2nd QTR 02'!D24 -> -256 | R24: =+P24/'2nd QTR 02'!$D24 -> -0.67904509 | T24: =+I24-'2nd QTR 02'!I24 -> -256 | V24: =+T24/'2nd QTR 02'!$I24 -> -0.67904509
B25: Total other, net | D25: -7315 | E25: -0.0087169673 | G25: 0 | I25: -7315 | J25: =+I25/$I$11 -> -0.0087169673 | L25: =+E25-'2nd QTR 02'!E25 -> 0.030642602 | N25: =+J25-'2nd QTR 02'!J25 -> 0.014927032 | P25: =+D25-'2nd QTR 02'!D25 -> 23886 | R25: =+P25/'2nd QTR 02'!$D25 -> -0.76555239 | T25: =+I25-'2nd QTR 02'!I25 -> 11428 | V25: =+T25/'2nd QTR 02'!$I25 -> -0.60972096
A27: Income before provision for income taxes | D27: 70662 | E27: 0.084204831 | G27: 2890 | I27: 73552 | J27: =+I27/$I$11 -> 0.087648719 | L27: =+E27-'2nd QTR 02'!E27 -> 0.051344429 | N27: =+J27-'2nd QTR 02'!J27 -> 0.029448882 | P27: =+D27-'2nd QTR 02'!D27 -> 44613 | R27: =+P27/'2nd QTR 02'!$D27 -> 1.7126569 | T27: =+I27-'2nd QTR 02'!I27 -> 27416 | V27: =+T27/'2nd QTR 02'!$I27 -> 0.59424311
A29: Provision for income taxes | D29: 27204 | E29: 0.032417823 | G29: 1112.65 | H29: ( b ) | I29: 28316.65 | J29: =+I29/$I$11 -> 0.03374372 | L29: =+E29-'2nd QTR 02'!E29 -> 0.019666741 | N29: =+J29-'2nd QTR 02'!J29 -> 0.011160937 | P29: =+D29-'2nd QTR 02'!D29 -> 17096 | R29: =+P29/'2nd QTR 02'!$D29 -> 1.6913336 | T29: =+I29-'2nd QTR 02'!I29 -> 10414.894 | V29: =+T29/'2nd QTR 02'!$I29 -> 0.58178058
A31: Net income | D31: 43458 | E31: 0.051787008 | G31: 1777.35 | I31: 45235.35 | J31: =+I31/$I$11 -> 0.053904999 | L31: =+E31-'2nd QTR 02'!E31 -> 0.031677688 | N31: =+J31-'2nd QTR 02'!J31 -> 0.018287945 | P31: =+D31-'2nd QTR 02'!D31 -> 27517 | R31: =+P31/'2nd QTR 02'!$D31 -> 1.7261778 | T31: =+I31-'2nd QTR 02'!I31 -> 17001.106 | V31: =+T31/'2nd QTR 02'!$I31 -> 0.6021449
A33: Net income per share:
B34: Basic | D34: 1.1891315 | G34: 0.048633229 | I34: 1.2377647 | P34: =+D34-'2nd QTR 02'!D34 -> 0.73864261 | R34: =+P34/'2nd QTR 02'!$D34 -> 1.6396467 | T34: =+I34-'2nd QTR 02'!I34 -> 0.43987167 | V34: =+T34/'2nd QTR 02'!$I34 -> 0.55129151
B35: Diluted | D35: 1.1615128 | G35: 0.047503675 | I35: 1.2090164 | P35: =+D35-'2nd QTR 02'!D35 -> 0.72527501 | R35: =+P35/'2nd QTR 02'!$D35 -> 1.6625682 | T35: =+I35-'2nd QTR 02'!I35 -> 0.43636458 | V35: =+T35/'2nd QTR 02'!$I35 -> 0.56476223
A38: Average common shares outstanding ( c ) | D38: 36546 | G38: 36546 | I38: 36546
A39: Dilutive effect of stock options | D39: 869 | G39: 869 | I39: 869
A40: Average common shares outstanding - assuming dilution | D40: 37415 | G40: 37415 | I40: 37415
A43: ( a ) Represents the non-recurring merger and integration expenses associated with the integration of the Discount Auto Parts operations.
A44: ( b ) This adjustment reflects the tax impact for the non-recurring items discussed above at a 38.5% effective tax rate.
A45: ( c ) Average common shares outstanding is calculated based on the weighted average number of shares outstanding for the quarter. At
A46: July 12, 2003, we had 36,686 shares outstanding.
A50: NOTE: These preliminary statements of operations have been prepared on a consistent basis with previously presented statements of operations
A51: and do not include the footnotes required by generally accepted accounting principles for complete financial statements.

Sheet YTD 03
A1: Advance Auto Parts, Inc. and Subsidiaries
A2: Consolidated Statements of Operations
A3: Twenty-Eight Week Periods Ended
A4: (in thousands, except per share data)
D6: 37814
G7: Adjustment for
G8: Non-recurring | I8: Comparable | L8: GAAP | N8: Comparable | P8: GAAP | T8: Comparable
D9: GAAP | G9: Items | I9: 2003 | L9: Inc (Dcr) | N9: Inc (Dcr) | P9: $ Change | R9: % Change | T9: $ Change | V9: % Change
A11: Net sales | D11: 1872705 | E11: 1 | G11: 0 | I11: 1872705 | J11: =+I11/$I$11 -> 1 | L11: =+E11-'2nd QTR 02'!E11 -> 0 | N11: =+J11-'2nd QTR 02'!J11 -> 0 | P11: =+D11-'2nd QTR 02'!D11 -> 1079988 | R11: =+P11/'2nd QTR 02'!$D11 -> 1.3623878 | T11: =+I11-'2nd QTR 02'!I11 -> 1079988 | V11: =+T11/'2nd QTR 02'!$I11 -> 1.3623878
A13: Cost of sales, including purchasing and warehousing costs | D13: 1023609 | E13: 0.54659383 | G13: 0 | I13: 1023609 | J13: =+I13/$I$11 -> 0.54659383 | L13: =+E13-'2nd QTR 02'!E13 -> -0.01313051 | N13: =+J13-'2nd QTR 02'!J13 -> -0.01313051 | P13: =+D13-'2nd QTR 02'!D13 -> 579906 | R13: =+P13/'2nd QTR 02'!$D13 -> 1.3069689 | T13: =+I13-'2nd QTR 02'!I13 -> 579906 | V13: =+T13/'2nd QTR 02'!$I13 -> 1.3069689
B15: Gross profit | D15: 849096 | E15: 0.45340617 | G15: 0 | I15: 849096 | J15: =+I15/$I$11 -> 0.45340617 | L15: =+E15-'2nd QTR 02'!E15 -> 0.01313051 | N15: =+J15-'2nd QTR 02'!J15 -> 0.01313051 | P15: =+D15-'2nd QTR 02'!D15 -> 500082 | R15: =+P15/'2nd QTR 02'!$D15 -> 1.4328422 | T15: =+I15-'2nd QTR 02'!I15 -> 500082 | V15: =+T15/'2nd QTR 02'!$I15 -> 1.4328422
A17: Selling, general and administrative expenses | D17: 696586 | E17: 0.37196782 | G17: -6271 | H17: ( a ) | I17: 690315 | J17: =+I17/$I$11 -> 0.36861919 | L17: =+E17-'2nd QTR 02'!E17 -> 0.003912135 | N17: =+J17-'2nd QTR 02'!J17 -> 0.010187366 | P17: =+D17-'2nd QTR 02'!D17 -> 404822 | R17: =+P17/'2nd QTR 02'!$D17 -> 1.3874981 | T17: =+I17-'2nd QTR 02'!I17 -> 406180 | V17: =+T17/'2nd QTR 02'!$I17 -> 1.4295317
B19: Operating income | D19: 152510 | E19: 0.081438347 | G19: 6271 | I19: 158781 | J19: =+I19/$I$11 -> 0.084786979 | L19: =+E19-'2nd QTR 02'!E19 -> 0.0092183746 | N19: =+J19-'2nd QTR 02'!J19 -> 0.0029431434 | P19: =+D19-'2nd QTR 02'!D19 -> 95260 | R19: =+P19/'2nd QTR 02'!$D19 -> 1.6639301 | T19: =+I19-'2nd QTR 02'!I19 -> 93902 | V19: =+T19/'2nd QTR 02'!$I19 -> 1.4473404
A21: Other, net:
A22: Interest expense | D22: -26749 | E22: -0.014283616 | G22: 0 | I22: -26749 | J22: =+I22/$I$11 -> -0.014283616 | L22: =+E22-'2nd QTR 02'!E22 -> 0.0098359621 | N22: =+J22-'2nd QTR 02'!J22 -> 0.0098359621 | P22: =+D22-'2nd QTR 02'!D22 -> -7629 | R22: =+P22/'2nd QTR 02'!$D22 -> 0.39900628 | T22: =+I22-'2nd QTR 02'!I22 -> -7629 | V22: =+T22/'2nd QTR 02'!$I22 -> 0.39900628
A23: Loss on extinguishment of debt | D23: -47141 | E23: -0.025172678 | G23: 46887 | H23: ( b ) | I23: -254 | J23: =+I23/$I$11 -> -0.00013563268 | L23: =+E23-'2nd QTR 02'!E23 -> -0.0094571074 | N23: =+J23-'2nd QTR 02'!J23 -> -0.00013563268 | P23: =+D23-'2nd QTR 02'!D23 -> -34683 | R23: =+P23/'2nd QTR 02'!$D23 -> 2.7839942 | T23: =+I23-'2nd QTR 02'!I23 -> -254 | V23: =+T23/'2nd QTR 02'!$I23 -> #DIV/0!
A24: Other income, net | D24: 239 | E24: 0.00012762288 | G24: 0 | I24: 239 | J24: =+I24/$I$11 -> 0.00012762288 | L24: =+E24-'2nd QTR 02'!E24 -> -0.00034795668 | N24: =+J24-'2nd QTR 02'!J24 -> -0.00034795668 | P24: =+D24-'2nd QTR 02'!D24 -> -138 | R24: =+P24/'2nd QTR 02'!$D24 -> -0.36604775 | T24: =+I24-'2nd QTR 02'!I24 -> -138 | V24: =+T24/'2nd QTR 02'!$I24 -> -0.36604775
B25: Total other, net | D25: -73651 | E25: -0.039328672 | G25: 46887 | I25: -26764 | J25: =+I25/$I$11 -> -0.014291626 | L25: =+E25-'2nd QTR 02'!E25 -> 3.0898055e-05 | N25: =+J25-'2nd QTR 02'!J25 -> 0.0093523728 | P25: =+D25-'2nd QTR 02'!D25 -> -42450 | R25: =+P25/'2nd QTR 02'!$D25 -> 1.3605333 | T25: =+I25-'2nd QTR 02'!I25 -> -8021 | V25: =+T25/'2nd QTR 02'!$I25 -> 0.42794643
A27: Income before provision for income taxes | D27: 78859 | E27: 0.042109676 | G27: 53158 | I27: 132017 | J27: =+I27/$I$11 -> 0.070495353 | L27: =+E27-'2nd QTR 02'!E27 -> 0.0092492727 | N27: =+J27-'2nd QTR 02'!J27 -> 0.012295516 | P27: =+D27-'2nd QTR 02'!D27 -> 52810 | R27: =+P27/'2nd QTR 02'!$D27 -> 2.0273331 | T27: =+I27-'2nd QTR 02'!I27 -> 85881 | V27: =+T27/'2nd QTR 02'!$I27 -> 1.8614748
A29: Provision for income taxes | D29: 30360 | E29: 0.016211843 | G29: 20465.83 | H29: ( c ) | I29: 50825.83 | J29: =+I29/$I$11 -> 0.027140329 | L29: =+E29-'2nd QTR 02'!E29 -> 0.0034607606 | N29: =+J29-'2nd QTR 02'!J29 -> 0.0045575461 | P29: =+D29-'2nd QTR 02'!D29 -> 20252 | R29: =+P29/'2nd QTR 02'!$D29 -> 2.0035615 | T29: =+I29-'2nd QTR 02'!I29 -> 32924.074 | V29: =+T29/'2nd QTR 02'!$I29 -> 1.8391533
A31: Net income | D31: 48499 | E31: 0.025897832 | G31: 32692.17 | I31: 81191.17 | J31: =+I31/$I$11 -> 0.043355024 | L31: =+E31-'2nd QTR 02'!E31 -> 0.0057885121 | N31: =+J31-'2nd QTR 02'!J31 -> 0.0077379701 | P31: =+D31-'2nd QTR 02'!D31 -> 32558 | R31: =+P31/'2nd QTR 02'!$D31 -> 2.0424064 | T31: =+I31-'2nd QTR 02'!I31 -> 52956.926 | V31: =+T31/'2nd QTR 02'!$I31 -> 1.8756276
A33: Net income per share:
B34: Basic | D34: 1.3405661 | G34: 0.9036478 | I34: 2.2442139 | P34: =+D34-'2nd QTR 02'!D34 -> 0.8900772 | R34: =+P34/'2nd QTR 02'!$D34 -> 1.9758028 | T34: =+I34-'2nd QTR 02'!I34 -> 1.4463208 | V34: =+T34/'2nd QTR 02'!$I34 -> 1.812675
B35: Diluted | D35: 1.3122024 | G35: 0.89452841 | I35: 2.1967308 | P35: =+D35-'2nd QTR 02'!D35 -> 0.87596463 | R35: =+P35/'2nd QTR 02'!$D35 -> 2.0079982 | T35: =+I35-'2nd QTR 02'!I35 -> 1.4240789 | V35: =+T35/'2nd QTR 02'!$I35 -> 1.8431056
A38: Average common shares outstanding ( d ) | D38: 36178 | G38: 36178 | I38: 36178
A39: Dilutive effect of stock options | D39: 782 | G39: 782 | I39: 782
A40: Average common shares outstanding - assuming dilution | D40: 36960 | G40: 36960 | I40: 36960
A43: ( a ) Represents the non-recurring merger and integration expenses associated with the integration of the Discount Auto Parts operations.
A44: ( b ) This adjustment reflects the deferred loan costs, unamortized discounts and the premiums paid upon the complete repurchase and
A45: retirement of our outstanding bonds during the first quarter of 2003.
A46: ( c ) This adjustment reflects the tax impact for the non-recurring items discussed above at a 38.5% effective tax rate.
A47: ( d ) Average common shares outstanding is calculated based on the weighted average number of shares outstanding for the quarter. At
A48: July 12, 2003, we had 36,686 shares outstanding.
A50: NOTE: These preliminary statements of operations have been prepared on a consistent basis with previously presented statements of operations
A51: and do not include the footnotes required by generally accepted accounting principles for complete financial statements.

Sheet 2nd QTR 02
A1: Advance Auto Parts, Inc. and Subsidiaries
A2: Consolidated Statements of Operations
A3: Twelve Week Periods Ended
A4: (in thousands, except per share data)
D6: 37450
G7: Adjustment for
G8: Non-recurring | I8: Comparable
D9: GAAP | G9: Items | I9: 2002
A11: Net sales | D11: 792717 | E11: 1 | G11: 0 | I11: 792717 | J11: =+I11/$I$11 -> 1
A13: Cost of sales, including purchasing and warehousing costs | D13: 443703 | E13: 0.55972434 | G13: 0 | I13: 443703 | J13: =+I13/$I$11 -> 0.55972434
B15: Gross profit | D15: 349014 | E15: 0.44027566 | G15: 0 | I15: 349014 | J15: =+I15/$I$11 -> 0.44027566
A17: Selling, general and administrative expenses | D17: 291764 | E17: 0.36805569 | G17: -7629 | H17: ( a ) | I17: 284135 | J17: =+I17/$I$11 -> 0.35843182
B19: Operating income | D19: 57250 | E19: 0.072219973 | G19: 7629 | I19: 64879 | J19: =+I19/$I$11 -> 0.081843836
A21: Other, net:
A22: Interest expense | D22: -19120 | E22: -0.024119579 | G22: 0 | I22: -19120 | J22: =+I22/$I$11 -> -0.024119579
A23: Loss on extinguishment of debt | D23: -12458 | E23: -0.015715571 | G23: 12458 | H23: ( b ) | I23: 0 | J23: =+I23/$I$11 -> 0
A24: Other income, net | D24: 377 | E24: 0.00047557956 | G24: 0 | I24: 377 | J24: =+I24/$I$11 -> 0.00047557956
B25: Total other, net | D25: -31201 | E25: -0.03935957 | G25: 12458 | I25: -18743 | J25: =+I25/$I$11 -> -0.023643999
A27: Income before provision for income taxes | D27: 26049 | E27: 0.032860403 | G27: 20087 | I27: 46136 | J27: =+I27/$I$11 -> 0.058199837
A29: Provision for income taxes | D29: 10108 | E29: 0.012751083 | G29: 7793.756 | H29: ( c ) | I29: 17901.756 | J29: =+I29/$I$11 -> 0.022582783
A31: Net income | D31: 15941 | E31: 0.02010932 | G31: 12293.244 | I31: 28234.244 | J31: =+I31/$I$11 -> 0.035617054
A33: Net income per share:
B34: Basic | D34: 0.45048889 | G34: 0.34740417 | I34: 0.79789307
B35: Diluted | D35: 0.43623775 | G35: 0.33 | I35: 0.77265185
A38: Average common shares outstanding ( d ) | D38: 35386 | G38: 35386 | I38: 35386
A39: Dilutive effect of stock options | D39: 1156 | G39: 1156 | I39: 1156
A40: Average common shares outstanding - assuming dilution | D40: 36542 | G40: 36542 | I40: 36542
A43: ( a ) Represents the non-recurring merger and integration expenses associated with the integration of the Discount Auto Parts operations.
A44: ( b ) This adjustment reflects the current and deferred loan costs associated with the Company's refinancing of the tranche B term loan under its senior credit
B45: facility and reflects the ratable portion of deferred loan costs and the premium paid upon the repurchase and retirement of outstanding bonds.
A46: ( c ) This adjustment reflects the tax impact for the non-recurring items discussed above at a 38.8% effective tax rate.
A47: ( d ) Average common shares outstanding is calculated based on the weighted average number of shares outstanding for the quarter. At
A48: July 13, 2002, we had 35,665 shares outstanding.
A50: NOTE: These preliminary statements of operations have been prepared on a consistent basis with previously presented statements of operations
A51: and do not include the footnotes required by generally accepted accounting principles for complete financial statements.

Sheet YTD 02
A1: Advance Auto Parts, Inc. and Subsidiaries
A2: Consolidated Statements of Operations
A3: Twenty-Eight Week Periods Ended
A4: (in thousands, except per share data)
D6: 37450
G7: Adjustment for
G8: Non-recurring | I8: Comparable
D9: GAAP | G9: Items | I9: 2002
A11: Net sales | D11: 1796804 | E11: 1 | G11: 0 | I11: 1796804 | J11: =+I11/$I$11 -> 1
A13: Cost of sales, including purchasing and warehousing costs | D13: 1011282 | E13: 0.56282266 | G13: 0 | I13: 1011282 | J13: =+I13/$I$11 -> 0.56282266
B15: Gross profit | D15: 785522 | E15: 0.43717734 | G15: 0 | I15: 785522 | J15: =+I15/$I$11 -> 0.43717734
A17: Selling, general and administrative expenses | D17: 679918 | E17: 0.3784041 | G17: -18194 | H17: ( a ) | I17: 661724 | J17: =+I17/$I$11 -> 0.36827834
B19: Operating income | D19: 105604 | E19: 0.058773244 | G19: 18194 | I19: 123798 | J19: =+I19/$I$11 -> 0.068899001
A21: Other, net:
A22: Interest expense | D22: -46718 | E22: -0.02600061 | G22: 0 | I22: -46718 | J22: =+I22/$I$11 -> -0.02600061
A23: Loss on extinguishment of debt | D23: -13724 | E23: -0.0076380061 | G23: 13724 | H23: ( b ) | I23: 0 | J23: =+I23/$I$11 -> 0
A24: Other income, net | D24: 650 | E24: 0.00036175342 | G24: 0 | I24: 650 | J24: =+I24/$I$11 -> 0.00036175342
B25: Total other, net | D25: -59792 | E25: -0.033276863 | G25: 13724 | I25: -46068 | J25: =+I25/$I$11 -> -0.025638857
A27: Income before provision for income taxes | D27: 45812 | E27: 0.025496381 | G27: 31918 | I27: 77730 | J27: =+I27/$I$11 -> 0.043260144
A29: Provision for income taxes | D29: 17775 | E29: 0.0098925648 | G29: 12384.184 | H29: ( c ) | I29: 30159.184 | J29: =+I29/$I$11 -> 0.016784905
A31: Net income | D31: 28037 | E31: 0.015603817 | G31: 19533.816 | I31: 47570.816 | J31: =+I31/$I$11 -> 0.026475239
A33: Net income per share:
B34: Basic | D34: 0.81271378 | G34: 0.56623039 | I34: 1.3789442
B35: Diluted | D35: 0.78513022 | G35: 0.54 | I35: 1.3321427
A38: Average common shares outstanding ( d ) | D38: 34498 | G38: 34498 | I38: 34498
A39: Dilutive effect of stock options | D39: 1212 | G39: 1212 | I39: 1212
A40: Average common shares outstanding - assuming dilution | D40: 35710 | G40: 35710 | I40: 35710
A43: ( a ) Represents the non-recurring merger and integration expenses associated with the integration of the Discount Auto Parts operations.
A44: ( b ) This adjustment reflects the current and deferred loan costs associated with the Company's refinancing of the tranche B term loan under its senior credit
B45: facility and reflects the ratable portion of deferred loan costs and the premium paid upon the repurchase and retirement of outstanding bonds.
A46: ( c ) This adjustment reflects the tax impact for the non-recurring items discussed above at a 38.8% effective tax rate.
A47: ( d ) Average common shares outstanding is calculated based on the weighted average number of shares outstanding for the quarter. At
A48: July 13, 2002, we had 35,665 shares outstanding.
A50: NOTE: These preliminary statements of operations have been prepared on a consistent basis with previously presented statements of operations
A51: and do not include the footnotes required by generally accepted accounting principles for complete financial statements.

Sheet Cash Flow
A1: Advance Auto Parts, Inc. and Subsidiaries
A2: Consolidated Statements of Cash Flows
A3: Twenty-Eight Week Periods Ended
A4: (in thousands, except per share data)
I7: July 12, | K7: July 13,
I8: 2003 | K8: 2002
A10: Cash flows from operating activities:
B11: Net income | I11: 48499 | K11: 28037
B12: Depreciation | I12: 53807 | K12: 48983
B13: Loss on extinguishment of debt | I13: 47141 | K13: 13724
B14: Provision for deferred income taxes | I14: 30142 | K14: 17706
B15: Other non-cash adjustments to net income | I15: 10742 | K15: 15764
B16: Decrease (increase) in :
C17: Receivables, net | I17: 9224 | K17: -24397
C18: Inventories, net | I18: -31081 | K18: -101427
C19: Other assets | I19: -18609 | K19: -18005
B20: Increase (decrease) in :
C21: Accounts payable | I21: 121087 | K21: 156078
C22: Accrued expenses | I22: 6687 | K22: 40589
C23: Other liabilities | I23: -1707 | K23: 4852
D24: Net cash provided by operating activities | I24: 275932 | K24: 181904
A26: Cash flows from investing activities:
B27: Purchases of property and equipment | I27: -50595 | K27: -46638
B28: Proceeds from sales of property and equipment | I28: 8974 | K28: 9410
D29: Net cash used in investing activities | I29: -41621 | K29: -37228
A31: Cash flows from financing activities:
B32: Increase in bank overdrafts | I32: 13503 | K32: -34748
B33: Early extinguishment of debt, including debt related costs | I33: -551374 | K33: -429214
B34: Net borrowings under the credit facility | I34: 348300 | K34: 240000
B35: Payment of debt related costs | I35: -36895 | K35: -8098
B36: Proceeds from the exercise of stock options | I36: 18824 | K36: 16089
B37: Proceeds from the issuance of common stock | I37: 0 | K37: 88695
B38: Other net financing activities | I38: 5520 | K38: 4027
D39: Net cash used in financing activities | I39: -202122 | K39: -123249
A41: Increase in cash and cash equivalents | I41: 32189 | K41: 21427
A42: Cash and cash equivalents, beginning of period | I42: 13885 | K42: 18117
A43: Cash and cash equivalents, end of period | I43: 46074 | K43: 39544
B47: NOTE: These preliminary statements of cash flows have been prepared on a consistent basis with previously presented statements of
B48: cash flows and do not include the footnotes required by generally accepted accounting principles for complete financial statements.
