Workbook

Sheet Complete GAS Bank
A1: GAS Bank of Treatment Goals
A2: ID | B2: Topic | C2: Put X in box if goal selected | D2: Treatment Goal | E2: Most unfavorable treatment outcome thought likely | F2: Less than expected success with treatment | G2: Expected level of treatment success | H2: More than expected success with treatment | I2: Best anticipated success with treatment
A4: A1 | B4: Addiction | D4: Denial (Alcohol Related) | E4: Client does not think s/he has or has had any major problems due to drinking | F4: Client says maybe s/he has had problems due to drinking but nothing serious and nothing now | G4: Client says maybe s/he has current problems due to drinking but nothing s/he considers very serious | H4: Client can state 1 or 2 problems s/he wishes to work on | I4: Client is actively working on stated problems
A5: A2 | B5: Addiction | D5: Drug Use | E5: Gets arrested for possession or use of drugs or uses drugs almost every day | F5: No arrests for possession or use of drugs but uses them twice per week or more | G5: No arrest for possession or use of drugs but continues to use about 4 to 7 times per month | H5: No arrest for possession or use of drugs but uses them 1 to 3 times per month | I5: No arrests for possession or use and reports no drug usage
A6: A3 | B6: Addiction | D6: Drug Use Sponsor | E6: Does not attend group meetings and does not have a drug use sponsor | F6: Occasional attendance at group meetings, but does not have sponsor | G6: Occasional attendance at group meetings and finds and asks someone to be his/her sponsor | H6: Regular attendance at group meetings and less than daily contact with sponsor | I6: Daily attendance at group meetings and daily contact with sponsor
A7: A3a | B7: Addiction | D7: Index of Drug Involvement (IDI) | E7: Client scores a 40 or above indicating a clinically significant personal or social problem with drugs resulting in serious problems around the use and abuse of drugs | F7: Client scores between 20-39 indicating a clinically significant personal or social problem with drugs | G7: Client scores between 10-19, indicating a nonsignificant clinical personal or social problem with drugs | H7: Client scores between 5-9, indicating a nonsignificant clinical personal or social problem with drugs | I7: Client scores between 0-4 indicating a nonsignificant clinical personal or social problem with drugs
A8: A4 | B8: Addiction | D8: Individual Counseling for Drug Use | E8: No individual counseling for drug use | F8: Individual counseling for drug use sought | G8: Client can identify high risk people, places and things that influence drug use | H8: Client is making the attempt to change social setting (people, places, things) that influence drug use | I8: Client has changed social setting (people, places, things) that influence drug use
A9: A5 | B9: Addiction | D9: Individual Counseling: Understanding Drug Impact on Others | E9: No individual counseling for drug use | F9: Individual counseling for drug use sought | G9: Client can identify the consequences they/others have endured on behalf of his/her drug use | H9: Client is considering how to make amends to those who have been affected by his/her drug use | I9: Client has attempted to make amends to those who have been affected by his/her drug use
A10: A6 | B10: Addiction | D10: Substance Use | E10: Uses substances on a regular basis, no attempt to abstain. | F10: Attempts to abstain, but continues to use substances. | G10: Abstains from substance use, but doesn't attend group meetings. | H10: Abstains from use, and occasionally attends support group meetings. | I10: Complete abstinence and daily attendance in support groups.
A11: A7 | B11: Addiction | D11: Weekly Substance Abuse | E11: Uses substances at least weekly. Unable to abstain. | F11: Uses substances at least once a month. | G11: Has not used substances for at least _____ months. | H11: Has not used substances for ___ months and attending treatment. | I11: Has not used substances for ___ months, attends treatment and/or support groups.
A12: A8 | B12: Addiction | D12: ZCreate your own
A13: AC1 | B13: Affect/Cognition | D13: Anxiety (Clinical Anxiety Scale) | E13: Client scores a 50 or above indicating a significant level of phobic and/or anxiety reactions related to specific situations or events such as trembling, twitching, feeling shaky, aches, restlessness, fatigue, shortness of breath, tachycardia, sweating, dizziness, etc. | F13: Client scores 30-49 indicating a clinically significant level of phobic and/or anxiety reactions related to specific situations or events | G13: Client scores between 20-29 and is free of a clinically significant problem with anxiety or phobia | H13: Client scores between 10-19 and is free of a clinically significant problem with anxiety or phobia | I13: Client scores between 0-9 and is free of a clinically significant problem with anxiety or phobia
A14: AC1a | B14: Affect/Cognition | D14: Generalized Contentment Inventory | E14: A score of 70 or above indicating severe distress, possibly suicidal acting out | F14: A score between 31 and 69, indicating clinically significant nonpsychotic depression | G14: A score between 21-30, indicating client is free from clinical depression (nonpsychotic) | H14: A score between 11-20, indicating client is free from clinical depression (nonpsychotic) | I14: A score between 0-10, indicating client is free from clinical depression (nonpsychotic)
A15: AC2 | B15: Affect/Cognition | D15: Decision-Making | E15: Can consider alternatives but makes no decisions. | F15: Makes concrete plans, but no follow-through. | G15: Makes concrete plans, follows through with assistance. | H15: Makes concrete plans, follows through without assistance. | I15: Makes concrete plans, reaches goal without assistance.
A16: AC3 | B16: Affect/Cognition | D16: Depressed Mood | E16: Depressed mood most of the day, nearly every day for the past two months in which daily living activities are affected (eating, sleeping, working) | F16: Regular depressed mood within the past month in which daily living activities are affected (eating, sleeping, working) | G16: Occasional depressed mood within the past two weeks in which daily living activities are occasionally affected | H16: Some depression noted, but daily living activities are rarely affected | I16: Infrequent periods of depression that do not interfere with daily functioning.
A17: AC4 | B17: Affect/Cognition | D17: Depression Affecting Daily Activities | E17: Reported depression in which 5 or more of the following are reported: poor appetite; sleeplessness; low energy; low self esteem; poor concentration; hopelessness | F17: Reported depression in which 3-4 of the following are reported: poor appetite; sleeplessness; low energy; low self esteem; poor concentration; hopelessness | G17: Reported depression in which 1-2 of the following are reported: poor appetite; sleeplessness; low energy; low self esteem; poor concentration; hopelessness | H17: Sought treatment for depression; depression not reported in the past two weeks | I17: No depression; client feels better equipped to handle future episodes of depression
A18: AC5 | B18: Affect/Cognition | D18: Depression Diagnosis | E18: Has not followed through with professional diagnosis. No professional recommendations obtained. | F18: Professional diagnosis and does not agree to recommendations. | G18: Professional diagnosis obtained and agrees to professional recommendations for treatment. | H18: Has initiated recommended treatment. | I18: Ongoing treatment with reports of decreasing symptoms.
A19: AC6 | B19: Affect/Cognition | D19: Fear of Partner | E19: Client is fearful of partner, but is not seeking support | F19: Client is fearful of partner, but is considering seeking support | G19: Client is fearful of partner, but is actively seeking support | H19: Client is making changes to get out of a fearful environment | I19: Client is in a positive environment and is not fearful of partner
A20: AC7 | B20: Affect/Cognition | D20: Feelings About Self | E20: Client mostly reports negative feelings about self. | F20: Client reports more negative than positive feelings about self. | G20: Client reports positive and negative feelings about self equally. | H20: Client reports more positives about self than negatives. | I20: Client reports mostly positive feelings about self.
A21: AC9 | B21: Affect/Cognition | D21: Identifying Feelings | E21: Client is unable to identify feelings | F21: Client is able to identify feelings, but does not express feelings appropriately | G21: Client is able to identify and appropriately express feelings to counselor | H21: To counselor and in-home (parents and siblings) | I21: To counselor, in-home (parents and siblings), and out-of home (school)
A22: AC10 | B22: Affect/Cognition | D22: Nightmares | E22: Client reports frequent weekly nightmares | F22: Client reports several nightmares per week | G22: Client reports few nightmares per week and is beginning to use imagery rehearsal (or other cognitive restructuring) in which the nightmare is changed during waking hours | H22: Client reports nightmares have mostly subsided after using imagery rehearsal (or other cognitive restructuring) | I22: Client reports s/he has not had any nightmares within the past 30 days and is optimistic s/he can handle future nightmare episodes
A23: AC11 | B23: Affect/Cognition | D23: Nightmares | E23: Nightmares have increased. | F23: Nightmares have decreased by less than 25%. | G23: Nightmares have decreased by 25-50%. | H23: Nightmares have decreased by 51-75% | I23: All nightmares or almost all nightmares have subsided
A24: AC12 | B24: Affect/Cognition | D24: Index of Self Esteem (ISE) | E24: A score of 70 or above, indicating client has a significant self esteem problem, and is nearly always experiencing severe distress in which violence could be considered as a means of dealing | F24: A score between 31-69 indicating client has a significant self esteem problem | G24: A score between 21-30, indicating client is free from a significant self esteem problem | H24: A score between 11-20, indicating client is free from a significant self esteem problem | I24: A score between 0-10, indicating client is free from a significant self esteem problem
... A29: AC14 | B29: Affect/Cognition | D29: Suicidal thoughts | E29: Client reports suicidal thoughts frequently and has had more than ___ suicide attempt in the last ___ time period | F29: Client reports suicidal thoughts frequently and has made one suicidal attempt in the last __ time period. | G29: Client reports suicidal thoughts at least ___ times per month, but has not acted on thoughts. | H29: Client reports suicidal thoughts less than once every ___ and has not acted on thoughts. | I29: Client reports no suicidal thoughts.
A30: AC15 | B30: Affect/Cognition | D30: ZCreate your own
A31: B1 | B31: Behavior | D31: Ability to compromise | E31: 1 in 4 conflicts or less resolved with compromise | F31: About 1 in 3 conflicts resolved with compromise | G31: Youth and parents achieve acceptable compromise every other conflict | H31: Acceptable compromise almost every time (more than every other time) | I31: Acceptable compromise all the time
A32: B2 | B32: Behavior | D32: Anger Control | E32: Controls anger less than 25% of the time. | F32: Controls anger less than 50% of the time. | G32: Controls anger more than 50% of the time. | H32: Controls anger more than 75% of the time. | I32: Controls anger more than 75% of the time even when challenged by another angry individual or situation.
A33: B3 | B33: Behavior | D33: Anger: Physica/Verbal Retaliation | E33: Frequently client inappropriately expresses anger through verbal or physical retaliation | F33: Occasionally client inappropriately expresses anger through verbal or physical retaliation | G33: Client appropriately verbalizes his/her anger. Physical retaliation is infrequent. | H33: Occasionally client successfully uses self talk to "cool him/herself down" | I33: Client successfully uses self talk to "cool him/herself down". Client feels capable of handling future episodes of anger appropriately
A34: B3a | B34: Behavior | D34: Anxiety (Clinical Anxiety Scale) | E34: Client scores a 50 or above indicating a significant level of phobic and/or anxiety reactions related to specific situations or events such as trembling, twitching, feeling shaky, aches, restlessness, fatigue, shortness of breath, tachycardia, sweating, dizziness, etc. | F34: Client scores 30-49 indicating a clinically significant level of phobic and/or anxiety reactions related to specific situations or events | G34: Client scores between 20-29 and is free of a clinically significant problem with anxiety or phobia | H34: Client scores between 10-19 and is free of a clinically significant problem with anxiety or phobia | I34: Client scores between 0-9 and is free of a clinically significant problem with anxiety or phobia
A35: B4 | B35: Behavior | D35: Assaultive Behavior | E35: Patient has been isolated due to assaultive or destructive behavior | F35: Patient is destructive and assaultive every day | G35: 1 to 2 days free of assaultive behavior in last week | H35: 3 to 5 days free of assaultive behavior in last week | I35: 6 to 7 days free of assaultive behavior in last week
A36: B5 | B36: Behavior | D36: Assertiveness: Expressing Needs | E36: Rarely able to appropriately express needs and opinions | F36: Able to appropriately express needs and opinions some of the time | G36: Able to appropriately express needs and opinions some of the time, and is learning more appropriate ways of expression | H36: Able to appropriately express needs and opinions most of the time | I36: Able to appropriately express needs and opinions almost all of the time
A37: B6 | B37: Behavior | D37: Assertiveness: Learning Role Playing | E37: Client feels "walked over" by most people most of the time | F37: Client can identify situations in which s/he feels "walk over" | G37: Client is open to role-playing certain situations to increase assertiveness | H37: Client can role-play assertiveness and can transfer to real situations | I37: Client feels adequately prepared to handle future issues in which s/he will need to show assertiveness
A38: B7 | B38: Behavior | D38: Attention Seeking Behavior | E38: Spends less than 15 minutes in teacher/staff's company without inappropriate behaviors | F38: Spends at least 15 minutes in teacher/staff's company without inappropriate behaviors | G38: Spends at least 30 minutes in company of teacher/staff without inappropriate behaviors (poking, grabbing, screaming, or swearing) | H38: Spends at least 40 minutes | I38: At least 60 mins
A39: B8 | B39: Behavior | D39: Bedwetting | E39: Client wets the bed regularly | F39: Client wets the bed slightly less | G39: Client wets the bed 50% less | H39: Client rarely wets the bed | I39: Client has not wet the bed in the past 30 days
A40: B9 | B40: Behavior | D40: Bedwetting | E40: Wets to bed nightly. | F40: Wets to bed once a week. | G40: Child wets to bed once a month. | H40: Wets to bed less than once a month. | I40: No longer wets to bed.
A41: B10 | B41: Behavior | D41: Coping Skills | E41: Client reports no increase in ability to cope. | F41: Client reports minimal increase in ability to cope. | G41: Client reports an increased ability to cope with stressors after learning coping strategies. | H41: Client reports a significant increase in ability to cope. | I41: Client reports no major stressors and feels capable of coping with future stressors appropriately
A42: B11 | B42: Behavior | D42: Curfew | E42: Youth rarely comes home on time | F42: Youth comes home on time 2-3 times per week | G42: Youth comes home on time 4-5 times per week | H42: Youth comes home on time 6-7 times per week | I42: Youth has met curfew consistently for the past 4 weeks
... A65: B34 | B65: Behavior | D65: Verbal Aggression | E65: Verbal threats and verbal aggression used more than 5 times per week. | F65: Verbal threats and verbal aggression used at least once a week. | G65: Verbal threats & verbal aggression used less than once a week. | H65: Verbal threats and verbal aggression used less than once a month. | I65: Verbal threats and verbal aggression used less than once every 3 months.
A66: B35 | B66: Behavior | D66: ZCreate your own
A67: CC1 | B67: Child Care | D67: After School Care | E67: Children are not in after school care and no attempt to enroll. | F67: Children are enrolled in after school care but are attending infrequently (1 day per week). | G67: Children are in after school care and are attending most of the time | H67: Children are in after school care and are attending frequently | I67: Children are in after school care and are attending regularly
A68: CC2 | B68: Child Care | D68: Day Care | E68: No day care. | F68: Unsatisfactory day care (cost, location, etc.) | G68: Satisfactory day care obtained | H68: Satisfactory day care; list for assistance. | I68: Satisfactory day care with financial assistance.
A69: CC3 | B69: Child Care | D69: Day care/ school | E69: No daycare and/or children not attending school. | F69: Children in school Temporary day care. | G69: Obtained day care, and children attend school 15 days out of previous month. | H69: Obtained day care and children attend school 18 days out of previous month. | I69: Permanent day care, and children have perfect attendance (no unexcused absences)
A70: CC4 | B70: Child Care | D70: Day care: Head Start | E70: No child care or eligible for Head Start and not enrolled | F70: Temporary child care and/or child(ren) enrolled in Head Start but not attending and parent not participating | G70: N/A OR Obtained child care and/or child(ren) enrolled in Head Start or parent caring for child at home OR due to child’s age no childcare needed | H70: Attended day care for one month and/or child(ren) participating in Head Start. | I70: Attended day care for three months and/or full participation in Head Start by child and parent
A71: CC5 | B71: Child Care | D71: DayCare: Assistance | E71: Children are not in day care and no attempt to obtain assistance. | F71: Children are not in day care even with eligible assistance. | G71: Children are in day care with assistance from agency resources. | H71: Children are in day care with extended family assistance. | I71: Children are in day care with no assistance needed.
A72: CC6 | B72: Child Care | D72: Inadequate Supervision | E72: Frequent incident of inadequate supervision (more than 3 times per case period). | F72: Occasional incident of inadequate supervision (1-3 times per case period) | G72: No reports, incidents or observations of inadequate supervision. | H72: Children are provided adequate supervision by appropriate caretaker most of the time | I72: Adequate supervision is provided regularly
A73: CC7 | B73: Child Care | D73: ZCreate your own
A74: CW1 | B74: Child Welfare | D74: Child placement out of home | E74: No follow through on referrals. No placement options initiated. | F74: Referred client to placement resources. Client not accepted for placement | G74: Has applied for out of home placement. Decision pending. | H74: Child placed out of home. | I74: Child placed out of home and family engaged in services with placement resources
A75: CW2 | B75: Child Welfare | D75: Child welfare | E75: CPS referral and case opened by CPS | F75: CPS referral and case investigated only | G75: NO CPS referral in past 3 months | H75: No CPS referral in past year | I75: No CPS referrals in past 3 years
A76: CW3 | B76: Child Welfare | D76: Parent's self-control (child mental health) | E76: Parent reports having hit child as result of being angered | F76: Reports having wanted to hit but was able to restrain herself | G76: Parent reports she verbally reprimanded child but did not feel like hitting | H76: Parent reports she has learned more appropriate ways of handling anger and has changed inappropriate behavior | I76: Parent feels capable of handling anger in an appropriate manner and feels competent in handling future situations appropriately
A77: CW4 | B77: Child Welfare | D77: ZCreate your own
A78: C1 | B78: Communication | D78: Communication skills: Peers | E78: Client is unable to communicate appropriately with peers and has no friends | F78: Client is unable to communicate appropriately with peers and has few friends | G78: Client is able to communicate appropriately with peers and does so some of the time. Client reports having some friends | H78: Client is actively working on communication skills (such as listening, not interrupting, not self-effacing, not blaming) | I78: Client is appropriately and genuinely expressive and can send straight (nonconfusing) messages in their appropriate context.
A79: C2 | B79: Communication | D79: Conflict Resolution | E79: Conflicts are not resolved. Unable to discuss the issues. Can not reach agreement. | F79: Some conflicts are resolved. Much difficulty discussing the issues without fighting, yelling, blaming. Sometimes can reach agreement. | G79: Regular conflicts are resolved by talking and coming to some agreement. Still some difficulty. May be fighting, yelling, blaming. | H79: Most conflicts are resolved by talking and coming to agreement most of the time. No yelling, fighting, blaming. | I79: Conflicts are regularly resolved appropriately and client feels s/he has the skills to handle future conflicts appropriately
A80: C3 | B80: Communication | D80: Cursing or Disrespectful Language | E80: Client uses disrespectful language frequently | F80: Client uses disrespectful language some of the time | G80: Client uses disrespectful language occasionally, and is learning how to substitute more appropriate words for previously used curse words | H80: Client occasionally uses disrespectful language, more often substituting more appropriate words | I80: Client rarely uses disrespectful language, regularly substituting more appropriate words
A81: C4 | B81: Communication | D81: Decision-making | E81: Can consider alternatives but makes no decisions. | F81: Makes concrete plans, but no follow-through. | G81: Makes concrete plans, follows through with assistance. | H81: Makes concrete plans, follows through without assistance. | I81: Makes concrete plans, reaches goal without assistance.
A82: C5 | B82: Communication | D82: Interpersonal Relationships | E82: Feels uneasy talking to people | F82: Feels comfortable talking with people some of the time | G82: Feels comfortable talking with people most of the time | H82: Has started to initiate conversation (at least once in the last week) | I82: Has initiated more than one conversation in last week
A83: C6 | B83: Communication | D83: Problem-solving Skills | E83: In denial about problems | F83: Able to identify problems, but does not handle constructively | G83: Able to identify problem and handles constructively with guidance | H83: Able to identify problem and handles constructively without guidance at least half of the time | I83: Able to identify problem and handles constructively without guidance more than half of the time
A84: C7 | B84: Communication | D84: ZCreate your own
A85: CS1 | B85: Community Support | D85: Social Support | E85: Does not have any informal social support or is socially isolated | F85: Has minimal social support or does not contact social support—somewhat socially isolated | G85: Has adequate social support and is not isolated. | H85: Has social support system in place and seeks out additional support. | I85: Has social support system in place and seeks out additional social support and serves as a support network to others.
A86: CS2 | B86: Community Support | D86: Support Group Attendance | E86: No support group attended. | F86: Support group identified, but attendance minimal. | G86: Support group identified and able to attend 2 out of 4 meetings. | H86: Attends support group 3 out of 4 meetings. | I86: Regularly attends support group, rarely misses group
A87: CS3 | B87: Community Support | D87: ZCreate your own
A88: DV1 | B88: Domestic Violence | D88: Domestic Violence | E88: Frequent physical or verbal violence in home | F88: Occasional physical or verbal violence in home | G88: No physical violence in home, but occasional verbal violence | H88: No physical violence, occasional verbal violence, but members are learning better how to handle disagreements | I88: No physical or verbal violence in home. Members feel capable of handling future conflicts appropriately.
A89: DV2 | B89: Domestic Violence | D89: Domestic Violence Safety Plan | E89: No Safety Plan | F89: Considering safety plan, but no action taken | G89: “Safety Bag” packed and hidden containing necessities (medication, money, keys, important documents) in case of emergency | H89: “Safety Bag” packed and considering alternative living arrangements (shelter, family) | I89: Alternative living arrangements made; client feels safe
A90: DV3 | B90: Domestic Violence | D90: Domestic Violence: Legal/MH Intervention | E90: All forms of violence continue. No legal or MH intervention. | F90: Verbal violence continues. Legal and MH resources initiated but not maintained. | G90: No forms of violence continue. Legal and MH intervention initiated. | H90: No violence. Legal and MH intervention ongoing. | I90: No violence. Legal and MH intervention completed. Resolved.
A91: DV4 | B91: Domestic Violence | D91: Fearful of Partner | E91: Client is fearful of partner, but is not seeking support | F91: Client is fearful of partner, but is considering seeking support | G91: Client is fearful of partner, but is actively seeking support | H91: Client is making changes to get out of a fearful environment | I91: Client is in a positive environment and is not fearful of partner
A92: DV5 | B92: Domestic Violence | D92: Protective Order | E92: Did not seek protective order. | F92: Protective order requested, not obtained or not enforced. | G92: Papers filed for protective order. | H92: Protective order granted. | I92: Protective order granted and enforced.
A93: DV6 | B93: Domestic Violence | D93: ZCreate your own
A94: E1 | B94: Education | D94: Adult Education | E94: Did not enroll. Did not complete. | F94: Enrolled in educational or vocational program but did not complete. | G94: Enrolled and attending in educational or vocational program. | H94: Obtained GED/High School/Trade School | I94: Some college.
A95: E2 | B95: Education | D95: Adult education improvement | E95: Client has identified additional education or training, did not follow through with enrollment. | F95: Client has identified additional education or training, enrolled, and is not attending regularly. | G95: Client has identified additional education or training programs, enrolled & attending regularly. | H95: Client has completed program and is seeking job opportunities in this field. | I95: Client has completed additional education or training program and used this to obtain pay raise or new job in field.
A96: E3 | B96: Education | D96: Education: HS Diploma/GED | E96: No high school diploma and not enrolled in GED. | F96: Enrolled in H.S. or GED but has multiple unexcused absences. | G96: Attending H.S./GED classes and no unexcused absences. | H96: Obtained GED/H.S. or attending vocational school after. | I96: Enrolled in classes at community or 4 year college.
A97: E3a | B97: Education | D97: Education: HS Diploma/GED | E97: No high school diploma and not enrolled in GED. | F97: Has made some inquiries about H.S./GED program, but has not enrolled. | G97: Enrolled in H.S./GED program. | H97: Enrolled & attending H.S./GED program. | I97: Obtained H.S./GED.
A98: E4 | B98: Education | D98: Educational Future: College/Vocational School | E98: No decision about educational future; still ambivalent and aimless | F98: Decision to attend college or vocational school, but has not actually enrolled | G98: Enrolled in a vocational school or college but does not appear motivated for scholastic activity | H98: Enrolled in vocational or college and seems motivated for scholastic activity | I98: Enrolled in vocational or college and is maintaining acceptable grades
A99: E5 | B99: Education | D99: Father's education | E99: No high school diploma, not enrolled in GED classes, and not attending ESL classes, if applicable. | F99: Enrolled in GED class or High School or ESL classes and has multiple unexcused absences. | G99: Has no educational goals and/or attending ESL, GED, or High School classes with no unexcused absences. | H99: Obtained GED or has high school diploma or completed ESL classes. | I99: Enrolled in classes at a junior or 4-year college.
A100: E6 | B100: Education | D100: Mother's education | E100: No high school diploma, not enrolled in GED classes, and not attending ESL classes, if applicable. | F100: Enrolled in GED class or High School or ESL classes and has multiple unexcused absences. | G100: Has no educational goals and/or attending ESL, GED, or High School classes with no unexcused absences. | H100: Obtained GED or has high school diploma or completed ESL classes or attending a vocational school. | I100: Enrolled in classes at a junior or 4-year college.
A101: E7 | B101: Education | D101: ZCreate your own
A102: Em1 | B102: Employment | D102: Career Planning | E102: Has not chosen any preferred fields. | F102: One or more fields chosen but no planning. | G102: Selected one or more fields with plans for achieving at least one. | H102: Has followed through with plan (application, interview, etc.) | I102: Acquired job in a selected field.
A103: Em2 | B103: Employment | D103: Employment | E103: No Employment | F103: Less than 32 hours a week employment or employed 32+ hours a week | G103: Usually 32+ hours a week employment | H103: Consistently 32+ hours a week | I103: 32+ hours a week employment with full benefits.
A104: Em3 | B104: Employment | D104: Employment: Applications & Interviews | E104: No applications obtained | F104: Applications obtained. | G104: Applications submitted | H104: Interviews set | I104: Full time employment obtained
A105: Em4 | B105: Employment | D105: Employment: Applying and Maintaining | E105: Has not obtained employment and has not applied for employment. | F105: Has not obtained employment, but did apply for employment. | G105: Obtained employment. | H105: Maintained employment for at least 3months. | I105: Maintained employment for at least 6 months.
A106: Em5 | B106: Employment | D106: Employment: Pay Increase | E106: Pay not increased | F106: Pay increased by less than 3% | G106: Pay increased by 3-5% | H106: Pay increased by 6-10% | I106: Pay increased by more than 10%
A107: Em6 | B107: Employment | D107: Father's employment | E107: No employment or job training. | F107: Enrolled in job training with unexcused absences or sporadic employment search or unstable employment. | G107: Caring for non-school age child full-time or in job training program with no unexcused absences or actively seeking work. | H107: Stable full-time or part-time employment and receiving supplemental public assistance. | I107: Stable full-time or part-time employment and receiving no supplemental public assistance.
A108: Em7 | B108: Employment | D108: Maintaining Employment | E108: Has not worked since case opened. | F108: Has worked some, but not currently working. | G108: Currently working, changes jobs or first job. | H108: Currently working, has not changed jobs for at least 6 months. | I108: Currently working, has not changed jobs for at least 12 months.
A109: Em8 | B109: Employment | D109: Mother’s employment | E109: No employment or job training | F109: Enrolled in job training with unexcused absences or sporadic employment search or unstable employment | G109: Caring for non-school age child full-time or in job training program with no unexcused absences or actively seeking work OR Mother unavailable for employment | H109: Stable full-time or part-time employment and receiving and supplemental public assistance | I109: Stable full-time or part-time employment and receiving no supplemental public assistance
A110: Em9 | B110: Employment | D110: ZCreate your own
A111: FR1 | B111: Family Relationships | D111: Child's Attitude toward Father (CAF) | E111: Child (aged 12 & over) scores 70 or above indicating severe distress in relationship with his/her father. At this level there is a clear possibility that some form of violence could be considered as a means of dealing | F111: Child (aged 12 & over) scores 30-69 indicating a clinically significant problem between the father and child | G111: Child (aged 12 & over) scores between 20-29 indicating a nonsignificant issues between the father and child | H111: Child (aged 12 & over) scores between 10-19 indicating a nonsignificant issues between the father and child | I111: Child (aged 12 & over) scores between 0-9 indicating a nonsignificant issues between the father and child
A112: FR1a | B112: Family Relationships | D112: Child's Attitude toward Mother (CAM) | E112: Child (aged 12 & over) scores 70 or above indicating severe distress in relationship with his/her mother. At this level there is a clear possibility that some form of violence could be considered as a means of dealing | F112: Child (aged 12 & over) scores 30-69 indicating a clinically significant problem between the mother and child | G112: Child (aged 12 & over) scores between 20-29 indicating a nonsignificant issues between the mother and child | H112: Child (aged 12 & over) scores between 10-19 indicating a nonsignificant issues between the mother and child | I112: Child (aged 12 & over) scores between 0-9 indicating a nonsignificant issues between the mother and child
A113: FR1b | B113: Family Relationships | D113: Communication Skills | E113: Family rarely communicates appropriately with one another | F113: Family occasionally communicates appropriately with one another | G113: Family occasionally communicates appropriately with one another, and has expressed desire to better communicate | H113: Family often communicates appropriately with one another and has learned more appropriate ways of handling disagreements | I113: Family often communicates appropriately with one another, enjoys one another's company, and feels competent in handling future disagreements appropriately
A114: FR2 | B114: Family Relationships | D114: Compliance with household rules | E114: Youth rarely complies with family rules | F114: Youth complies with family rules some of the time | G114: Youth complies with most family rules | H114: Youth complies with most family rules and can occasionally appropriately discuss with parent(s) rules s/he feels should change | I114: Youth is accepting of parent(s) rules, even if in disagreement about them
A115: FR3 | B115: Family Relationships | D115: Consistent Consequences | E115: Consequences are not set for breaking rules | F115: Consequences are set for breaking rules, but are rarely followed through | G115: Consequences are set for breaking rules and are followed through some of the time | H115: Consequences are set for breaking rules and are followed through most of the time | I115: Consequences are set for breaking rules and are followed through all of the time
A116: FR4 | B116: Family Relationships | D116: Extended Family Relationships | E116: No contact with any extended family or Constant major conflicts with several or various extended family members. | F116: Some (less than once a month) contact with any extended family and some conflict with extended family members. | G116: Consistent positive contact (once a month) with extended family and no major conflict ongoing. | H116: Frequent (weekly) positive contact with several or various extended family members. | I116: More than weekly positive contact with various extended family members.,
A117: FR5 | B117: Family Relationships | D117: Family Communication | E117: All family members report poor family communication. No help sought | F117: Most family members report poor family communication. No help sought | G117: Some family members report poor family communication, but family is seeking help | H117: Some family members report family communication is improving with current therapeutic assistance | I117: Most family members report improved communication that has been maintained for at least 30 days
A118: FR6 | B118: Family Relationships | D118: Family Interactions | E118: Positive interactions with parents/siblings are rare (occurring less than once a week) | F118: Positive interactions with parents/siblings occur once a week | G118: Positive interactions with parents/siblings occur at least 2-6 times a week | H118: Positive interactions with parents/siblings occur daily | I118: Negative interactions with parents/siblings are rare (occurring less than once a week)
A119: FR6a | B119: Family Relationships | D119: Family Relations (Index of FR) | E119: Client scores 70 or above and is most likely experiencing severe distress. At this level there is a clear possibility that some form of violence could be considered as a means of dealing with problems | F119: Client scores 30-69 indicating significant family relationship problems | G119: Client scores between 20-29, and can be presumed to be free of a clinically significant problem | H119: Client scores between 10-19, and can be presumed to be free of a clinically significant problem | I119: Client scores between 0-9, and can be presumed to be free of a clinically significant problem
A120: FR7 | B120: Family Relationships | D120: Family Strengths | E120: Family is unable to identify any strengths. | F120: Family can only identify 1 strength. | G120: Family can identify more than 1 strength. | H120: Family can identify more than 3 strengths and uses them to resolve problems. | I120: Family can identify more than 5 strengths and uses them to resolve problems.
A121: FR8 | B121: Family Relationships | D121: Marital conflicts | E121: Husband and wife report they are mostly dissatisfied with their marriage | F121: Husband and wife report they are somewhat dissatisfied with their marriage | G121: Husband and wife report some satisfaction with their marriage, and have expressed the desire to make it better | H121: Husband and wife are actively working on making their marriage better | I121: Husband and wife are satisfied in their marriage and feel capable of handling future conflicts satisfactory
A122: FR9 | B122: Family Relationships | D122: Parent/Child Relationship | E122: Parent & child rarely have time together or most time is not positive. | F122: Parent & child have one-on-one time and family time less than once a week. Some time may be negative or conflictual. | G122: Parent & child have positive one-on-one time, and family time at least once a week. | H122: Parent & child have positive one-on-one time, and family time more than once a week. | I122: Parent & child have positive one-on-one time and family time every other day.
... A126: FR13 | B126: Family Relationships | D126: Sibling Relationship | E126: Siblings do not get along. Frequent conflict, no sharing or helping of each other. | F126: Siblings get along some of the time. Conflict more frequent than parent thinks OK. | G126: Siblings get along. May play together, talk to each other, help one another. Some typical sibling conflict. | H126: Siblings get along better than most. | I126: Siblings get along and regularly enjoy being together
A127: FR14 | B127: Family Relationships | D127: ZCreate your own
A128: G1 | B128: Gang Activity | D128: Gang Affiliation | E128: Youth is gang affiliated | F128: Youth is considering disengaging from gang related activity | G128: Youth is attempting to disengage from gang by not hanging out with gang members nor participating in gang-related activity | H128: Youth is completely disengaged from gang affiliation | I128: Youth is speaking out against gangs and gang related activities in schools and youth groups
A129: G2 | B129: Gang Activity | D129: ZCreate your own
A130: H1 | B130: Health | D130: Birth Control | E130: Engages in unprotected sex, uses no form of birth control. | F130: Uses birth control 25-50% of the time. | G130: Uses birth control more than 50% of the time. | H130: Engages in sex and uses birth control more than 75% of the time. | I130: Engages in sex and uses birth control 100% of the time.
...

Sheet Your selected list
A1: Instructions:
A2: 1. Select goals from the "Complete GAS Bank" worksheet (the first tab at bottom left). In that worksheet, put an "x" in column B next to the chosen goal.
A3: 2. Once goals have been selected, move to worksheet titled "Your selected list" (this worksheet). Select "x" through the filter (the blue arrow) from "Put X in box if goal selected". Your chosen goals from the previous worksheet will appear.
A4: 3. You can type in the information asked in rows 8 and 9 (just double click on the selected cell to open it for modifications). You can make any needed goal or outcome modifications on this worksheet. You can put needed comments about the client's treatment at the bottom of this form.
A5: 4. If you want to save this document, click on the save icon and you will be prompted to save with a different file name.
A6: 5. To print this worksheet out, simply click on the print icon.
A7: 6. After your personalized goalsheet is printed out, put a date (of initial assessment) in the OUTCOME box (in the light blue box) that most accurately describes your client's state at initial assessment for each goal, and put a date (of the exit interview) in the OUTCOME box (in the white box) that most accurately describes your client's state at exit for each goal. You will also have these two dates in row 9.
A8: Personalized Goals for: | E8: Case Number: | G8: Counselor's Name:
A9: Date of Initial Assessment: (date first seen) | E9: Date of Final Assessment: (date last seen) | G9: # of Sessions: (including initial assessment)
A10: Reason for Termination: (put X in appropriate box or write in reason in space provided) | D10: Noncompliance | E10: No Shows | F10: Completed TX | G10: Other: _____________________________ ___________________________________
A11: GAS Code | B11: Put X in box if goal selected | C11: Treatment Goal | D11: Most unfavorable treatment outcome thought likely | E11: Less than expected success with treatment | F11: Expected level of treatment success | G11: More than expected success with treatment | H11: Best anticipated success with treatment
A12: ='Complete GAS Bank'!A4 -> A1 | B12: ='Complete GAS Bank'!C4 -> 0 | C12: ='Complete GAS Bank'!D4 -> Denial (Alcohol Related) | D12: ='Complete GAS Bank'!E4 -> Client does not think s/he has or has had any major problems due to drinking | E12: ='Complete GAS Bank'!F4 -> Client says maybe s/he has had problems due to drinking but nothing serious and nothing now | F12: ='Complete GAS Bank'!G4 -> Client says maybe s/he has current problems due to drinking but nothing s/he considers very serious | G12: ='Complete GAS Bank'!H4 -> Client can state 1 or 2 problems s/he wishes to work on | H12: ='Complete GAS Bank'!I4 -> Client is actively working on stated problems
A13: ='Complete GAS Bank'!A5 -> A2 | B13: ='Complete GAS Bank'!C5 -> 0 | C13: ='Complete GAS Bank'!D5 -> Drug Use | D13: ='Complete GAS Bank'!E5 -> Gets arrested for possession or use of drugs or uses drugs almost every day | E13: ='Complete GAS Bank'!F5 -> No arrests for possession or use of drugs but uses them twice per week or more | F13: ='Complete GAS Bank'!G5 -> No arrest for possession or use of drugs but continues to use about 4 to 7 times per month | G13: ='Complete GAS Bank'!H5 -> No arrest for possession or use of drugs but uses them 1 to 3 times per month | H13: ='Complete GAS Bank'!I5 -> No arrests for possession or use and reports no drug usage
A14: ='Complete GAS Bank'!A6 -> A3 | B14: ='Complete GAS Bank'!C6 -> 0 | C14: ='Complete GAS Bank'!D6 -> Drug Use Sponsor | D14: ='Complete GAS Bank'!E6 -> Does not attend group meetings and does not have a drug use sponsor | E14: ='Complete GAS Bank'!F6 -> Occasional attendance at group meetings, but does not have sponsor | F14: ='Complete GAS Bank'!G6 -> Occasional attendance at group meetings and finds and asks someone to be his/her sponsor | G14: ='Complete GAS Bank'!H6 -> Regular attendance at group meetings and less than daily contact with sponsor | H14: ='Complete GAS Bank'!I6 -> Daily attendance at group meetings and daily contact with sponsor
A15: ='Complete GAS Bank'!A7 -> A3a | B15: ='Complete GAS Bank'!C7 -> 0 | C15: ='Complete GAS Bank'!D7 -> Index of Drug Involvement (IDI) | D15: ='Complete GAS Bank'!E7 -> Client scores a 40 or above indicating a clinically significant personal or social problem with drugs resulting in serious problems around the use and abuse of drugs | E15: ='Complete GAS Bank'!F7 -> Client scores between 20-39 indicating a clinically significant personal or social problem with drugs | F15: ='Complete GAS Bank'!G7 -> Client scores between 10-19, indicating a nonsignificant clinical personal or social problem with drugs | G15: ='Complete GAS Bank'!H7 -> Client scores between 5-9, indicating a nonsignificant clinical personal or social problem with drugs | H15: ='Complete GAS Bank'!I7 -> Client scores between 0-4 indicating a nonsignificant clinical personal or social problem with drugs
A16: ='Complete GAS Bank'!A8 -> A4 | B16: ='Complete GAS Bank'!C8 -> 0 | C16: ='Complete GAS Bank'!D8 -> Individual Counseling for Drug Use | D16: ='Complete GAS Bank'!E8 -> No individual counseling for drug use | E16: ='Complete GAS Bank'!F8 -> Individual counseling for drug use sought | F16: ='Complete GAS Bank'!G8 -> Client can identify high risk people, places and things that influence drug use | G16: ='Complete GAS Bank'!H8 -> Client is making the attempt to change social setting (people, places, things) that influence drug use | H16: ='Complete GAS Bank'!I8 -> Client has changed social setting (people, places, things) that influence drug use
A17: ='Complete GAS Bank'!A9 -> A5 | B17: ='Complete GAS Bank'!C9 -> 0 | C17: ='Complete GAS Bank'!D9 -> Individual Counseling: Understanding Drug Impact on Others | D17: ='Complete GAS Bank'!E9 -> No individual counseling for drug use | E17: ='Complete GAS Bank'!F9 -> Individual counseling for drug use sought | F17: ='Complete GAS Bank'!G9 -> Client can identify the consequences they/others have endured on behalf of his/her drug use | G17: ='Complete GAS Bank'!H9 -> Client is considering how to make amends to those who have been affected by his/her drug use | H17: ='Complete GAS Bank'!I9 -> Client has attempted to make amends to those who have been affected by his/her drug use
A18: ='Complete GAS Bank'!A10 -> A6 | B18: ='Complete GAS Bank'!C10 -> 0 | C18: ='Complete GAS Bank'!D10 -> Substance Use | D18: ='Complete GAS Bank'!E10 -> Uses substances on a regular basis, no attempt to abstain. | E18: ='Complete GAS Bank'!F10 -> Attempts to abstain, but continues to use substances. | F18: ='Complete GAS Bank'!G10 -> Abstains from substance use, but doesn't attend group meetings. | G18: ='Complete GAS Bank'!H10 -> Abstains from use, and occasionally attends support group meetings. | H18: ='Complete GAS Bank'!I10 -> Complete abstinence and daily attendance in support groups.
A19: ='Complete GAS Bank'!A11 -> A7 | B19: ='Complete GAS Bank'!C11 -> 0 | C19: ='Complete GAS Bank'!D11 -> Weekly Substance Abuse | D19: ='Complete GAS Bank'!E11 -> Uses substances at least weekly. Unable to abstain. | E19: ='Complete GAS Bank'!F11 -> Uses substances at least once a month. | F19: ='Complete GAS Bank'!G11 -> Has not used substances for at least _____ months. | G19: ='Complete GAS Bank'!H11 -> Has not used substances for ___ months and attending treatment. | H19: ='Complete GAS Bank'!I11 -> Has not used substances for ___ months, attends treatment and/or support groups.
A20: ='Complete GAS Bank'!A12 -> A8 | B20: ='Complete GAS Bank'!C12 -> 0 | C20: ='Complete GAS Bank'!D12 -> ZCreate your own | D20: ='Complete GAS Bank'!E12 -> 0 | E20: ='Complete GAS Bank'!F12 -> 0 | F20: ='Complete GAS Bank'!G12 -> 0 | G20: ='Complete GAS Bank'!H12 -> 0 | H20: ='Complete GAS Bank'!I12 -> 0
A21: ='Complete GAS Bank'!A13 -> AC1 | B21: ='Complete GAS Bank'!C13 -> 0 | C21: ='Complete GAS Bank'!D13 -> Anxiety (Clinical Anxiety Scale) | D21: ='Complete GAS Bank'!E13 -> Client scores a 50 or above indicating a significant level of phobic and/or anxiety reactions related to specific situations or events such as trembling, twitching, feeling shaky, aches, restlessness, fatigue, shortness of breath, tachycardia, sweating, dizziness, etc. | E21: ='Complete GAS Bank'!F13 -> Client scores 30-49 indicating a clinically significant level of phobic and/or anxiety reactions related to specific situations or events | F21: ='Complete GAS Bank'!G13 -> Client scores between 20-29 and is free of a clinically significant problem with anxiety or phobia | G21: ='Complete GAS Bank'!H13 -> Client scores between 10-19 and is free of a clinically significant problem with anxiety or phobia | H21: ='Complete GAS Bank'!I13 -> Client scores between 0-9 and is free of a clinically significant problem with anxiety or phobia
A22: ='Complete GAS Bank'!A14 -> AC1a | B22: ='Complete GAS Bank'!C14 -> 0 | C22: ='Complete GAS Bank'!D14 -> Generalized Contentment Inventory | D22: ='Complete GAS Bank'!E14 -> A score of 70 or above indicating severe distress, possibly suicidal acting out | E22: ='Complete GAS Bank'!F14 -> A score between 31 and 69, indicating clinically significant nonpsychotic depression | F22: ='Complete GAS Bank'!G14 -> A score between 21-30, indicating client is free from clinical depression (nonpsychotic) | G22: ='Complete GAS Bank'!H14 -> A score between 11-20, indicating client is free from clinical depression (nonpsychotic) | H22: ='Complete GAS Bank'!I14 -> A score between 0-10, indicating client is free from clinical depression (nonpsychotic)
A23: ='Complete GAS Bank'!A15 -> AC2 | B23: ='Complete GAS Bank'!C15 -> 0 | C23: ='Complete GAS Bank'!D15 -> Decision-Making | D23: ='Complete GAS Bank'!E15 -> Can consider alternatives but makes no decisions. | E23: ='Complete GAS Bank'!F15 -> Makes concrete plans, but no follow-through. | F23: ='Complete GAS Bank'!G15 -> Makes concrete plans, follows through with assistance. | G23: ='Complete GAS Bank'!H15 -> Makes concrete plans, follows through without assistance. | H23: ='Complete GAS Bank'!I15 -> Makes concrete plans, reaches goal without assistance.
... A104: ='Complete GAS Bank'!A96 -> E3 | B104: ='Complete GAS Bank'!C96 -> 0 | C104: ='Complete GAS Bank'!D96 -> Education: HS Diploma/GED | D104: ='Complete GAS Bank'!E96 -> No high school diploma and not enrolled in GED. | E104: ='Complete GAS Bank'!F96 -> Enrolled in H.S. or GED but has multiple unexcused absences. | F104: ='Complete GAS Bank'!G96 -> Attending H.S./GED classes and no unexcused absences. | G104: ='Complete GAS Bank'!H96 -> Obtained GED/H.S. or attending vocational school after. | H104: ='Complete GAS Bank'!I96 -> Enrolled in classes at community or 4 year college.
A105: ='Complete GAS Bank'!A98 -> E4 | B105: ='Complete GAS Bank'!C98 -> 0 | C105: ='Complete GAS Bank'!D98 -> Educational Future: College/Vocational School | D105: ='Complete GAS Bank'!E98 -> No decision about educational future; still ambivalent and aimless | E105: ='Complete GAS Bank'!F98 -> Decision to attend college or vocational school, but has not actually enrolled | F105: ='Complete GAS Bank'!G98 -> Enrolled in a vocational school or college but does not appear motivated for scholastic activity | G105: ='Complete GAS Bank'!H98 -> Enrolled in vocational or college and seems motivated for scholastic activity | H105: ='Complete GAS Bank'!I98 -> Enrolled in vocational or college and is maintaining acceptable grades
A106: ='Complete GAS Bank'!A99 -> E5 | B106: ='Complete GAS Bank'!C99 -> 0 | C106: ='Complete GAS Bank'!D99 -> Father's education | D106: ='Complete GAS Bank'!E99 -> No high school diploma, not enrolled in GED classes, and not attending ESL classes, if applicable. | E106: ='Complete GAS Bank'!F99 -> Enrolled in GED class or High School or ESL classes and has multiple unexcused absences. | F106: ='Complete GAS Bank'!G99 -> Has no educational goals and/or attending ESL, GED, or High School classes with no unexcused absences. | G106: ='Complete GAS Bank'!H99 -> Obtained GED or has high school diploma or completed ESL classes. | H106: ='Complete GAS Bank'!I99 -> Enrolled in classes at a junior or 4-year college.
A107: ='Complete GAS Bank'!A100 -> E6 | B107: ='Complete GAS Bank'!C100 -> 0 | C107: ='Complete GAS Bank'!D100 -> Mother's education | D107: ='Complete GAS Bank'!E100 -> No high school diploma, not enrolled in GED classes, and not attending ESL classes, if applicable. | E107: ='Complete GAS Bank'!F100 -> Enrolled in GED class or High School or ESL classes and has multiple unexcused absences. | F107: ='Complete GAS Bank'!G100 -> Has no educational goals and/or attending ESL, GED, or High School classes with no unexcused absences. | G107: ='Complete GAS Bank'!H100 -> Obtained GED or has high school diploma or completed ESL classes or attending a vocational school. | H107: ='Complete GAS Bank'!I100 -> Enrolled in classes at a junior or 4-year college.
A108: ='Complete GAS Bank'!A101 -> E7 | B108: ='Complete GAS Bank'!C101 -> 0 | C108: ='Complete GAS Bank'!D101 -> ZCreate your own | D108: ='Complete GAS Bank'!E101 -> 0 | E108: ='Complete GAS Bank'!F101 -> 0 | F108: ='Complete GAS Bank'!G101 -> 0 | G108: ='Complete GAS Bank'!H101 -> 0 | H108: ='Complete GAS Bank'!I101 -> 0
A109: ='Complete GAS Bank'!A102 -> Em1 | B109: ='Complete GAS Bank'!C102 -> 0 | C109: ='Complete GAS Bank'!D102 -> Career Planning | D109: ='Complete GAS Bank'!E102 -> Has not chosen any preferred fields. | E109: ='Complete GAS Bank'!F102 -> One or more fields chosen but no planning. | F109: ='Complete GAS Bank'!G102 -> Selected one or more fields with plans for achieving at least one. | G109: ='Complete GAS Bank'!H102 -> Has followed through with plan (application, interview, etc.) | H109: ='Complete GAS Bank'!I102 -> Acquired job in a selected field.
A110: ='Complete GAS Bank'!A103 -> Em2 | B110: ='Complete GAS Bank'!C103 -> 0 | C110: ='Complete GAS Bank'!D103 -> Employment | D110: ='Complete GAS Bank'!E103 -> No Employment | E110: ='Complete GAS Bank'!F103 -> Less than 32 hours a week employment or employed 32+ hours a week | F110: ='Complete GAS Bank'!G103 -> Usually 32+ hours a week employment | G110: ='Complete GAS Bank'!H103 -> Consistently 32+ hours a week | H110: ='Complete GAS Bank'!I103 -> 32+ hours a week employment with full benefits.
A111: ='Complete GAS Bank'!A104 -> Em3 | B111: ='Complete GAS Bank'!C104 -> 0 | C111: ='Complete GAS Bank'!D104 -> Employment: Applications & Interviews | D111: ='Complete GAS Bank'!E104 -> No applications obtained | E111: ='Complete GAS Bank'!F104 -> Applications obtained. | F111: ='Complete GAS Bank'!G104 -> Applications submitted | G111: ='Complete GAS Bank'!H104 -> Interviews set | H111: ='Complete GAS Bank'!I104 -> Full time employment obtained
A112: ='Complete GAS Bank'!A105 -> Em4 | B112: ='Complete GAS Bank'!C105 -> 0 | C112: ='Complete GAS Bank'!D105 -> Employment: Applying and Maintaining | D112: ='Complete GAS Bank'!E105 -> Has not obtained employment and has not applied for employment. | E112: ='Complete GAS Bank'!F105 -> Has not obtained employment, but did apply for employment. | F112: ='Complete GAS Bank'!G105 -> Obtained employment. | G112: ='Complete GAS Bank'!H105 -> Maintained employment for at least 3months. | H112: ='Complete GAS Bank'!I105 -> Maintained employment for at least 6 months.
A113: ='Complete GAS Bank'!A106 -> Em5 | B113: ='Complete GAS Bank'!C106 -> 0 | C113: ='Complete GAS Bank'!D106 -> Employment: Pay Increase | D113: ='Complete GAS Bank'!E106 -> Pay not increased | E113: ='Complete GAS Bank'!F106 -> Pay increased by less than 3% | F113: ='Complete GAS Bank'!G106 -> Pay increased by 3-5% | G113: ='Complete GAS Bank'!H106 -> Pay increased by 6-10% | H113: ='Complete GAS Bank'!I106 -> Pay increased by more than 10%
A114: ='Complete GAS Bank'!A107 -> Em6 | B114: ='Complete GAS Bank'!C107 -> 0 | C114: ='Complete GAS Bank'!D107 -> Father's employment | D114: ='Complete GAS Bank'!E107 -> No employment or job training. | E114: ='Complete GAS Bank'!F107 -> Enrolled in job training with unexcused absences or sporadic employment search or unstable employment. | F114: ='Complete GAS Bank'!G107 -> Caring for non-school age child full-time or in job training program with no unexcused absences or actively seeking work. | G114: ='Complete GAS Bank'!H107 -> Stable full-time or part-time employment and receiving supplemental public assistance. | H114: ='Complete GAS Bank'!I107 -> Stable full-time or part-time employment and receiving no supplemental public assistance.
A115: ='Complete GAS Bank'!A108 -> Em7 | B115: ='Complete GAS Bank'!C108 -> 0 | C115: ='Complete GAS Bank'!D108 -> Maintaining Employment | D115: ='Complete GAS Bank'!E108 -> Has not worked since case opened. | E115: ='Complete GAS Bank'!F108 -> Has worked some, but not currently working. | F115: ='Complete GAS Bank'!G108 -> Currently working, changes jobs or first job. | G115: ='Complete GAS Bank'!H108 -> Currently working, has not changed jobs for at least 6 months. | H115: ='Complete GAS Bank'!I108 -> Currently working, has not changed jobs for at least 12 months.
A116: ='Complete GAS Bank'!A109 -> Em8 | B116: ='Complete GAS Bank'!C109 -> 0 | C116: ='Complete GAS Bank'!D109 -> Mother’s employment | D116: ='Complete GAS Bank'!E109 -> No employment or job training | E116: ='Complete GAS Bank'!F109 -> Enrolled in job training with unexcused absences or sporadic employment search or unstable employment | F116: ='Complete GAS Bank'!G109 -> Caring for non-school age child full-time or in job training program with no unexcused absences or actively seeking work OR Mother unavailable for employment | G116: ='Complete GAS Bank'!H109 -> Stable full-time or part-time employment and receiving and supplemental public assistance | H116: ='Complete GAS Bank'!I109 -> Stable full-time or part-time employment and receiving no supplemental public assistance
... A142: ='Complete GAS Bank'!A135 -> H6 | B142: ='Complete GAS Bank'!C135 -> 0 | C142: ='Complete GAS Bank'!D135 -> Health Coverage | D142: ='Complete GAS Bank'!E135 -> Not eligible for CHIPS or Medicaid/no health coverage. | E142: ='Complete GAS Bank'!F135 -> Has not enrolled in CHIPS or Medicaid. | F142: ='Complete GAS Bank'!G135 -> Enrolled in CHIPS or Medicaid | G142: ='Complete GAS Bank'!H135 -> CHIPS or Medicaid obtained and utilized. | H142: ='Complete GAS Bank'!I135 -> Health coverage beyond CHIPS/Medicaid obtained.
A143: ='Complete GAS Bank'!A137 -> H7 | B143: ='Complete GAS Bank'!C137 -> 0 | C143: ='Complete GAS Bank'!D137 -> Hygiene | D143: ='Complete GAS Bank'!E137 -> Chronic hygiene problems. | E143: ='Complete GAS Bank'!F137 -> Occasional hygiene problems. | F143: ='Complete GAS Bank'!G137 -> Meets minimum hygiene. Working towards better hygiene | G143: ='Complete GAS Bank'!H137 -> Consistent proper hygiene. | H143: ='Complete GAS Bank'!I137 -> No school referrals or observations regarding hygiene. Hygiene not a problem for any family member.
A144: ='Complete GAS Bank'!A138 -> H8 | B144: ='Complete GAS Bank'!C138 -> 0 | C144: ='Complete GAS Bank'!D138 -> Medical Needs | D144: ='Complete GAS Bank'!E138 -> Medical problems go unaddressed. | E144: ='Complete GAS Bank'!F138 -> Plans made to address immediate medical problems. | F144: ='Complete GAS Bank'!G138 -> Immediate medical needs addressed. | G144: ='Complete GAS Bank'!H138 -> Progress made toward resolution of all medical needs. | H144: ='Complete GAS Bank'!I138 -> All medical needs resolved.
A145: ='Complete GAS Bank'!A139 -> H9 | B145: ='Complete GAS Bank'!C139 -> 0 | C145: ='Complete GAS Bank'!D139 -> Prenatal care | D145: ='Complete GAS Bank'!E139 -> No prenatal care | E145: ='Complete GAS Bank'!F139 -> Seeking prenatal care but have delayed access | F145: ='Complete GAS Bank'!G139 -> Client has prenatal care upon confirmation of pregnancy and attends all doctor appointments | G145: ='Complete GAS Bank'!H139 -> Client has prenatal care and also participates in parenting classes and/or child birth education classes | H145: ='Complete GAS Bank'!I139 -> Client has prenatal care in first trimester and also participates in parenting classes and/or child birth education classes
A146: ='Complete GAS Bank'!A140 -> H10 | B146: ='Complete GAS Bank'!C140 -> 0 | C146: ='Complete GAS Bank'!D140 -> Special Medical Needs | D146: ='Complete GAS Bank'!E140 -> None of the special medical needs met. | E146: ='Complete GAS Bank'!F140 -> Some special medical needs met. | F146: ='Complete GAS Bank'!G140 -> Most special needs are met. | G146: ='Complete GAS Bank'!H140 -> All special medical needs are met. | H146: ='Complete GAS Bank'!I140 -> All special needs met, and parent knows how to obtain future needs
A147: ='Complete GAS Bank'!A141 -> H11 | B147: ='Complete GAS Bank'!C141 -> 0 | C147: ='Complete GAS Bank'!D141 -> Taking Prescribed Medication | D147: ='Complete GAS Bank'!E141 -> Client takes prescribed amount of meds less than 3 times/week, and not at the prescribed time | E147: ='Complete GAS Bank'!F141 -> Client takes prescribed amount of meds at least 3 to 4 days/week, but not at the prescribed time | F147: ='Complete GAS Bank'!G141 -> Client takes prescribed amount of meds at prescribed time at least 3 to 4 days/week | G147: ='Complete GAS Bank'!H141 -> Client takes prescribed amount of meds at prescribed time at least 5 to 6 days/week | H147: ='Complete GAS Bank'!I141 -> Client takes prescribed amount of meds at prescribed time 7 days/week
A148: ='Complete GAS Bank'!A142 -> H12 | B148: ='Complete GAS Bank'!C142 -> 0 | C148: ='Complete GAS Bank'!D142 -> Unplanned Pregnancy | D148: ='Complete GAS Bank'!E142 -> Will not discuss options. Delaying any decision. | E148: ='Complete GAS Bank'!F142 -> Minimally discusses issue. Not actively seeking information on options. | F148: ='Complete GAS Bank'!G142 -> Actively seeking information on all options. | G148: ='Complete GAS Bank'!H142 -> Has made decision and discusses reasons for decision. | H148: ='Complete GAS Bank'!I142 -> Has made decision and followed through with decision.
A149: ='Complete GAS Bank'!A143 -> H13 | B149: ='Complete GAS Bank'!C143 -> 0 | C149: ='Complete GAS Bank'!D143 -> ZCreate your own | D149: ='Complete GAS Bank'!E143 -> 0 | E149: ='Complete GAS Bank'!F143 -> 0 | F149: ='Complete GAS Bank'!G143 -> 0 | G149: ='Complete GAS Bank'!H143 -> 0 | H149: ='Complete GAS Bank'!I143 -> 0
A150: ='Complete GAS Bank'!A144 -> L1 | B150: ='Complete GAS Bank'!C144 -> 0 | C150: ='Complete GAS Bank'!D144 -> Custody Issues | D150: ='Complete GAS Bank'!E144 -> No resource for legal. | E150: ='Complete GAS Bank'!F144 -> No legal action initiated but resource for legal identified. | F150: ='Complete GAS Bank'!G144 -> Legal action initiated to obtain custody. | G150: ='Complete GAS Bank'!H144 -> Court hearing held; final court decision not made. | H150: ='Complete GAS Bank'!I144 -> Obtained custody.
A151: ='Complete GAS Bank'!A145 -> L2 | B151: ='Complete GAS Bank'!C145 -> 0 | C151: ='Complete GAS Bank'!D145 -> Legal assistance for ___________ | D151: ='Complete GAS Bank'!E145 -> No legal assistance, referral or intervention. Problem remains | E151: ='Complete GAS Bank'!F145 -> Referral to legal assistance. Case not accepted. | F151: ='Complete GAS Bank'!G145 -> Legal assistance initiated. Outcome pending | G151: ='Complete GAS Bank'!H145 -> Legal assistance obtained and outcome somewhat favorable to client | H151: ='Complete GAS Bank'!I145 -> Legal assistance obtained and outcome very favorable to client.
A152: ='Complete GAS Bank'!A146 -> L3 | B152: ='Complete GAS Bank'!C146 -> 0 | C152: ='Complete GAS Bank'!D146 -> Paternity Testing | D152: ='Complete GAS Bank'!E146 -> No resources identified for paternity testing. | E152: ='Complete GAS Bank'!F146 -> Resources found but testing not scheduled. | F152: ='Complete GAS Bank'!G146 -> Resources found and testing scheduled. | G152: ='Complete GAS Bank'!H146 -> Paternity testing completed. | H152: ='Complete GAS Bank'!I146 -> Paternity results obtained.
A153: ='Complete GAS Bank'!A147 -> L4 | B153: ='Complete GAS Bank'!C147 -> 0 | C153: ='Complete GAS Bank'!D147 -> Probation Violation | D153: ='Complete GAS Bank'!E147 -> Probation violations reported in the past week | E153: ='Complete GAS Bank'!F147 -> No probation violations reported within the past week | F153: ='Complete GAS Bank'!G147 -> No probation violations reported within the past two weeks | G153: ='Complete GAS Bank'!H147 -> No probation violations reported within the past month | H153: ='Complete GAS Bank'!I147 -> No probation violations reported within the past 6 weeks
A154: ='Complete GAS Bank'!A148 -> L5 | B154: ='Complete GAS Bank'!C148 -> 0 | C154: ='Complete GAS Bank'!D148 -> ZCreate your own | D154: ='Complete GAS Bank'!E148 -> 0 | E154: ='Complete GAS Bank'!F148 -> 0 | F154: ='Complete GAS Bank'!G148 -> 0 | G154: ='Complete GAS Bank'!H148 -> 0 | H154: ='Complete GAS Bank'!I148 -> 0
... A169: ='Complete GAS Bank'!A163 -> MHS3 | B169: ='Complete GAS Bank'!C163 -> 0 | C169: ='Complete GAS Bank'!D163 -> Counseling Referral | D169: ='Complete GAS Bank'!E163 -> Counseling not initiated at all. No appointments scheduled. | E169: ='Complete GAS Bank'!F163 -> Slow to follow through after referred. Appointments scheduled but not kept. | F169: ='Complete GAS Bank'!G163 -> Follow through on referral to counseling. Services initiated. Has only had 1-3 appointments so far. | G169: ='Complete GAS Bank'!H163 -> Attends counseling regularly. Has not missed more than 1 appointment. | H169: ='Complete GAS Bank'!I163 -> Attends counseling and does not miss appointments.
A170: ='Complete GAS Bank'!A165 -> MHS4 | B170: ='Complete GAS Bank'!C165 -> 0 | C170: ='Complete GAS Bank'!D165 -> Delusions: Treatment | D170: ='Complete GAS Bank'!E165 -> Reports delusions, not seeking treatment | E170: ='Complete GAS Bank'!F165 -> Reports delusions, seeking treatment | F170: ='Complete GAS Bank'!G165 -> In treatment for reported delusions (involving situations such as being followed, poisoned, infected, loved at a distance, or deceived, or having a disease) | G170: ='Complete GAS Bank'!H165 -> Treatment (counseling and/or meds) reducing reported delusions | H170: ='Complete GAS Bank'!I165 -> Treatment (counseling and/or meds) eliminating reported delusions for at least a month
A171: ='Complete GAS Bank'!A166 -> MHS5 | B171: ='Complete GAS Bank'!C166 -> 0 | C171: ='Complete GAS Bank'!D166 -> Mental Health Needs | D171: ='Complete GAS Bank'!E166 -> No attempt to obtain professional diagnosis or intervention. | E171: ='Complete GAS Bank'!F166 -> Appointment scheduled for diagnosis, but not kept. | F171: ='Complete GAS Bank'!G166 -> Professional diagnosis obtained. | G171: ='Complete GAS Bank'!H166 -> Diagnosis obtained and ongoing treatment/medication initiated. | H171: ='Complete GAS Bank'!I166 -> Diagnosis obtained, has kept all appointments and followed through with all recommendations.
A172: ='Complete GAS Bank'!A167 -> MHS6 | B172: ='Complete GAS Bank'!C167 -> 0 | C172: ='Complete GAS Bank'!D167 -> Parental cooperation (child mental health) | D172: ='Complete GAS Bank'!E167 -> Pulls client out of treatment against program | E172: ='Complete GAS Bank'!F167 -> Parents overtly undermine program (e.g., tell patient "they're wrong. You don't have to do that.") | F172: ='Complete GAS Bank'!G167 -> Superficially cooperate, but during past week indirectly reinforce negative behaviors (e.g., "stick up for your rights.") | G172: ='Complete GAS Bank'!H167 -> Cooperative of child's treatment, but not actively seeking long term changes | H172: ='Complete GAS Bank'!I167 -> Cooperative of child's treatment and actively involved in long term changes
A173: ='Complete GAS Bank'!A168 -> NHS7 | B173: ='Complete GAS Bank'!C168 -> 0 | C173: ='Complete GAS Bank'!D168 -> ZCreate your own | D173: ='Complete GAS Bank'!E168 -> 0 | E173: ='Complete GAS Bank'!F168 -> 0 | F173: ='Complete GAS Bank'!G168 -> 0 | G173: ='Complete GAS Bank'!H168 -> 0 | H173: ='Complete GAS Bank'!I168 -> 0
A174: ='Complete GAS Bank'!A169 -> N1 | B174: ='Complete GAS Bank'!C169 -> 0 | C174: ='Complete GAS Bank'!D169 -> Clothing | D174: ='Complete GAS Bank'!E169 -> No progress toward obtaining clothes. | E174: ='Complete GAS Bank'!F169 -> Vouchers provided, no clothing. | F174: ='Complete GAS Bank'!G169 -> Some clothing obtained. | G174: ='Complete GAS Bank'!H169 -> Most clothing needs met. | H174: ='Complete GAS Bank'!I169 -> All clothing needs met.
A175: ='Complete GAS Bank'!A170 -> N2 | B175: ='Complete GAS Bank'!C170 -> 0 | C175: ='Complete GAS Bank'!D170 -> Financial Assistance | D175: ='Complete GAS Bank'!E170 -> Household income is unstable and family needs are consistently not met. Family requires outside assistance every month. | E175: ='Complete GAS Bank'!F170 -> Household income is unstable and family needs are marginally met. Family requires outside assistance every other month. | F175: ='Complete GAS Bank'!G170 -> Income varies, but stable. Family needs barely met with outside assistance once a month. | G175: ='Complete GAS Bank'!H170 -> Income is stable, but family relies on outside assistance no more than 1-3 times per case period. | H175: ='Complete GAS Bank'!I170 -> Income is stable and provides for all family needs.
A176: ='Complete GAS Bank'!A171 -> N3 | B176: ='Complete GAS Bank'!C171 -> 0 | C176: ='Complete GAS Bank'!D171 -> Financial Assistance | D176: ='Complete GAS Bank'!E171 -> No income and no savings | E176: ='Complete GAS Bank'!F171 -> Receive AFDC and Food Stamps. | F176: ='Complete GAS Bank'!G171 -> Receives Food Stamps and/or Medicaid only. | G176: ='Complete GAS Bank'!H171 -> Receiving Food Stamps only. Not receiving bus tokens and/or clothing vouchers. | H176: ='Complete GAS Bank'!I171 -> No assistance needed.
A177: ='Complete GAS Bank'!A172 -> N4 | B177: ='Complete GAS Bank'!C172 -> 0 | C177: ='Complete GAS Bank'!D172 -> Financial assistance for _______________ | D177: ='Complete GAS Bank'!E172 -> No financial assistance, referral or intervention. Problem remains | E177: ='Complete GAS Bank'!F172 -> Referral to financial assistance. Case not accepted. | F177: ='Complete GAS Bank'!G172 -> Financial assistance initiated. Outcome pending | G177: ='Complete GAS Bank'!H172 -> Financial assistance obtained and outcome somewhat favorable to client | H177: ='Complete GAS Bank'!I172 -> Financial assistance obtained and outcome very favorable to client.
A178: ='Complete GAS Bank'!A173 -> N5 | B178: ='Complete GAS Bank'!C173 -> 0 | C178: ='Complete GAS Bank'!D173 -> Food: Nutrition | D178: ='Complete GAS Bank'!E173 -> Family has nutritionally balanced meals less than 25% of the time. | E178: ='Complete GAS Bank'!F173 -> Family has nutritionally balanced meals 25-40% of the time. | F178: ='Complete GAS Bank'!G173 -> Family has nutritionally balanced meals 40-50% of the time. | G178: ='Complete GAS Bank'!H173 -> Family has nutritionally balanced meals over 50% of the time. | H178: ='Complete GAS Bank'!I173 -> Family has nutritionally balanced meals over 75% of the time.
A179: ='Complete GAS Bank'!A174 -> N6 | B179: ='Complete GAS Bank'!C174 -> 0 | C179: ='Complete GAS Bank'!D174 -> Food: Outside Assistance | D179: ='Complete GAS Bank'!E174 -> Family frequently requires outside assistance to meet food needs. | E179: ='Complete GAS Bank'!F174 -> Family maintains adequate food supply with outside assistance more than 1 time every 3months. | F179: ='Complete GAS Bank'!G174 -> Family maintains adequate food supply with outside assistance no more than once every 3 months. | G179: ='Complete GAS Bank'!H174 -> Family maintains adequate food supply with outside assistance no more than once every 6 months. | H179: ='Complete GAS Bank'!I174 -> Family no longer requires outside assistance to meet food needs.
A180: ='Complete GAS Bank'!A176 -> N7 | B180: ='Complete GAS Bank'!C176 -> 0 | C180: ='Complete GAS Bank'!D176 -> Furniture/Bedding | D180: ='Complete GAS Bank'!E176 -> Not enough adequate beds for family. | E180: ='Complete GAS Bank'!F176 -> Some beds, no linens, need new mattress. | F180: ='Complete GAS Bank'!G176 -> Each family member has adequate bed and at least one set of linen. Some beds shared with age appropriate members. | G180: ='Complete GAS Bank'!H176 -> Each family member has own bed and at least one set of linen. | H180: ='Complete GAS Bank'!I176 -> Each family member has own bed and more than one set of linen.
A181: ='Complete GAS Bank'!A177 -> N8 | B181: ='Complete GAS Bank'!C177 -> 0 | C181: ='Complete GAS Bank'!D177 -> Housing | D181: ='Complete GAS Bank'!E177 -> No housing arrangements | E181: ='Complete GAS Bank'!F177 -> Unstable housing. Has temporary arrangements only and those may change often. | F181: ='Complete GAS Bank'!G177 -> N/A OR Temporary housing arranged for 30 days or less AND on Section 8 OR a minor living with parents | G181: ='Complete GAS Bank'!H177 -> Has adequate housing for more than 30 days living with family or friends. | H181: ='Complete GAS Bank'!I177 -> Affordable housing obtained and signed a lease
A182: ='Complete GAS Bank'!A178 -> N9 | B182: ='Complete GAS Bank'!C178 -> 0 | C182: ='Complete GAS Bank'!D178 -> Personal hygiene/clothing | D182: ='Complete GAS Bank'!E178 -> Chronic hygiene problems and/or inappropriate clothing | E182: ='Complete GAS Bank'!F178 -> Occasional hygiene problems and/or inappropriate clothing | F182: ='Complete GAS Bank'!G178 -> Meets minimum hygiene and/or clothing standards | G182: ='Complete GAS Bank'!H178 -> Consistent proper hygiene and/or appropriate clothing | H182: ='Complete GAS Bank'!I178 -> No school referrals regarding hygiene and/or clothing
A183: ='Complete GAS Bank'!A179 -> N10 | B183: ='Complete GAS Bank'!C179 -> 0 | C183: ='Complete GAS Bank'!D179 -> Special Foods | D183: ='Complete GAS Bank'!E179 -> Dietary needs go unaddressed. | E183: ='Complete GAS Bank'!F179 -> Efforts made to address dietary needs, but diet remains inadequate. | F183: ='Complete GAS Bank'!G179 -> Dietary needs met to satisfaction. | G183: ='Complete GAS Bank'!H179 -> Dietary needs, and occasionally, preferences met. | H183: ='Complete GAS Bank'!I179 -> Dietary needs and preferences met.
A184: ='Complete GAS Bank'!A180 -> N11 | B184: ='Complete GAS Bank'!C180 -> 0 | C184: ='Complete GAS Bank'!D180 -> Transportation | D184: ='Complete GAS Bank'!E180 -> No transportation. | E184: ='Complete GAS Bank'!F180 -> Does not have reliable transportation, but is on bus line. Needs assistance for bus pass. | F184: ='Complete GAS Bank'!G180 -> Has reliable transportation or is on bus line & has bus pass. | G184: ='Complete GAS Bank'!H180 -> Has own reliable transportation. | H184: ='Complete GAS Bank'!I180 -> Has own reliable transportation and funds to support.
A185: ='Complete GAS Bank'!A181 -> N12 | B185: ='Complete GAS Bank'!C181 -> 0 | C185: ='Complete GAS Bank'!D181 -> Utility Assistance | D185: ='Complete GAS Bank'!E181 -> Family can not maintain monthly utilities and not eligible for community resources. | E185: ='Complete GAS Bank'!F181 -> Family can not maintain monthly utilities even with community resources. | F185: ='Complete GAS Bank'!G181 -> Family can maintain monthly utilities by utilizing community resources. | G185: ='Complete GAS Bank'!H181 -> Family can maintain monthly utilities independently | H185: ='Complete GAS Bank'!I181 -> Family has maintained monthly utilities independently for three months or more
A186: ='Complete GAS Bank'!A182 -> N13 | B186: ='Complete GAS Bank'!C182 -> 0 | C186: ='Complete GAS Bank'!D182 -> ZCreate your own | D186: ='Complete GAS Bank'!E182 -> 0 | E186: ='Complete GAS Bank'!F182 -> 0 | F186: ='Complete GAS Bank'!G182 -> 0 | G186: ='Complete GAS Bank'!H182 -> 0 | H186: ='Complete GAS Bank'!I182 -> 0
A187: ='Complete GAS Bank'!A183 -> P1 | B187: ='Complete GAS Bank'!C183 -> 0 | C187: ='Complete GAS Bank'!D183 -> Child's Attitude toward Father (CAF) | D187: ='Complete GAS Bank'!E183 -> Child (aged 12 & over) scores 70 or above indicating severe distress in relationship with his/her father. At this level there is a clear possibility that some form of violence could be considered as a means of dealing | E187: ='Complete GAS Bank'!F183 -> Child (aged 12 & over) scores 30-69 indicating a clinically significant problem between the father and child | F187: ='Complete GAS Bank'!G183 -> Child (aged 12 & over) scores between 20-29 indicating a nonsignificant issues between the father and child | G187: ='Complete GAS Bank'!H183 -> Child (aged 12 & over) scores between 10-19 indicating a nonsignificant issues between the father and child | H187: ='Complete GAS Bank'!I183 -> Child (aged 12 & over) scores between 0-9 indicating a nonsignificant issues between the father and child
A188: ='Complete GAS Bank'!A184 -> P1a | B188: ='Complete GAS Bank'!C184 -> 0 | C188: ='Complete GAS Bank'!D184 -> Child's Attitude toward Mother (CAM) | D188: ='Complete GAS Bank'!E184 -> Child (aged 12 & over) scores 70 or above indicating severe distress in relationship with his/her mother. At this level there is a clear possibility that some form of violence could be considered as a means of dealing | E188: ='Complete GAS Bank'!F184 -> Child (aged 12 & over) scores 30-69 indicating a clinically significant problem between the mother and child | F188: ='Complete GAS Bank'!G184 -> Child (aged 12 & over) scores between 20-29 indicating a nonsignificant issues between the mother and child | G188: ='Complete GAS Bank'!H184 -> Child (aged 12 & over) scores between 10-19 indicating a nonsignificant issues between the mother and child | H188: ='Complete GAS Bank'!I184 -> Child (aged 12 & over) scores between 0-9 indicating a nonsignificant issues between the mother and child
A189: ='Complete GAS Bank'!A185 -> P1b | B189: ='Complete GAS Bank'!C185 -> 0 | C189: ='Complete GAS Bank'!D185 -> Discipline: Inappropriate | D189: ='Complete GAS Bank'!E185 -> Parent continues to use excessive physical discipline as primary means of discipline. | E189: ='Complete GAS Bank'!F185 -> Parent uses physical discipline as primary means of discipline. | F189: ='Complete GAS Bank'!G185 -> Parent refrains from physical discipline. May use rarely, but appropriately. | G189: ='Complete GAS Bank'!H185 -> Parent does not use physical discipline and is learning more appropriate ways of discipline. | H189: ='Complete GAS Bank'!I185 -> Parent does not use physical discipline and applies positive discipline techniques.
A190: ='Complete GAS Bank'!A186 -> P2 | B190: ='Complete GAS Bank'!C186 -> 0 | C190: ='Complete GAS Bank'!D186 -> Discipline: Parenting Skills | D190: ='Complete GAS Bank'!E186 -> Parent received no instruction in parenting skills | E190: ='Complete GAS Bank'!F186 -> Parent received instruction in techniques, but does not apply. | F190: ='Complete GAS Bank'!G186 -> Parent learned and can apply at least 2 new discipline techniques. | G190: ='Complete GAS Bank'!H186 -> Parent learned and can apply more than 2 new discipline techniques. | H190: ='Complete GAS Bank'!I186 -> Parent can apply more than 5 new discipline techniques.
A191: ='Complete GAS Bank'!A187 -> P2a | B191: ='Complete GAS Bank'!C187 -> 0 | C191: ='Complete GAS Bank'!D187 -> Index of Parental Attitudes (IPA) | D191: ='Complete GAS Bank'!E187 -> Client scores 70 or above indicating severe distress in the parent-child relationship. At this level there is a clear possibility that some form of violence could be considered as a means of dealing | E191: ='Complete GAS Bank'!F187 -> Client scores 30-69 indicating a clinically significant problem between parent and child | F191: ='Complete GAS Bank'!G187 -> Client scores between 20-29, indicating nonsignificant issues between parent and child | G191: ='Complete GAS Bank'!H187 -> Client scores between 10-19, indicating nonsignificant issues between parent and child | H191: ='Complete GAS Bank'!I187 -> Client scores between 0-9, indicating nonsignificant issues between parent and child
... A230: ='Complete GAS Bank'!A226 -> SS4 | B230: ='Complete GAS Bank'!C226 -> 0 | C230: ='Complete GAS Bank'!D226 -> ZCreate your own | D230: ='Complete GAS Bank'!E226 -> 0 | E230: ='Complete GAS Bank'!F226 -> 0 | F230: ='Complete GAS Bank'!G226 -> 0 | G230: ='Complete GAS Bank'!H226 -> 0 | H230: ='Complete GAS Bank'!I226 -> 0
A231: ='Complete GAS Bank'!#REF! -> #REF! | B231: ='Complete GAS Bank'!#REF! -> #REF! | C231: ='Complete GAS Bank'!#REF! -> #REF! | D231: ='Complete GAS Bank'!#REF! -> #REF! | E231: ='Complete GAS Bank'!#REF! -> #REF! | F231: ='Complete GAS Bank'!#REF! -> #REF! | G231: ='Complete GAS Bank'!#REF! -> #REF! | H231: ='Complete GAS Bank'!#REF! -> #REF!
A232: ='Complete GAS Bank'!A227 -> 0 | B232: ='Complete GAS Bank'!C227 -> 0 | C232: ='Complete GAS Bank'!D227 -> 0 | D232: ='Complete GAS Bank'!E227 -> 0 | E232: ='Complete GAS Bank'!F227 -> 0 | F232: ='Complete GAS Bank'!G227 -> 0 | G232: ='Complete GAS Bank'!H227 -> 0 | H232: ='Complete GAS Bank'!I227 -> 0
A233: ='Complete GAS Bank'!A228 -> 0 | B233: ='Complete GAS Bank'!C228 -> 0 | C233: ='Complete GAS Bank'!D228 -> 0 | D233: ='Complete GAS Bank'!E228 -> 0 | E233: ='Complete GAS Bank'!F228 -> 0 | F233: ='Complete GAS Bank'!G228 -> 0 | G233: ='Complete GAS Bank'!H228 -> 0 | H233: ='Complete GAS Bank'!I228 -> 0
A234: ='Complete GAS Bank'!A229 -> 0 | B234: ='Complete GAS Bank'!C229 -> 0 | C234: ='Complete GAS Bank'!D229 -> 0 | D234: ='Complete GAS Bank'!E229 -> 0 | E234: ='Complete GAS Bank'!F229 -> 0 | F234: ='Complete GAS Bank'!G229 -> 0 | G234: ='Complete GAS Bank'!H229 -> 0 | H234: ='Complete GAS Bank'!I229 -> 0
A235: ='Complete GAS Bank'!A230 -> 0 | B235: ='Complete GAS Bank'!C230 -> 0 | C235: ='Complete GAS Bank'!D230 -> 0 | D235: ='Complete GAS Bank'!E230 -> 0 | E235: ='Complete GAS Bank'!F230 -> 0 | F235: ='Complete GAS Bank'!G230 -> 0 | G235: ='Complete GAS Bank'!H230 -> 0 | H235: ='Complete GAS Bank'!I230 -> 0
A236: ='Complete GAS Bank'!A231 -> 0 | B236: ='Complete GAS Bank'!C231 -> 0 | C236: ='Complete GAS Bank'!D231 -> 0 | D236: ='Complete GAS Bank'!E231 -> 0 | E236: ='Complete GAS Bank'!F231 -> 0 | F236: ='Complete GAS Bank'!G231 -> 0 | G236: ='Complete GAS Bank'!H231 -> 0 | H236: ='Complete GAS Bank'!I231 -> 0
A237: ='Complete GAS Bank'!A232 -> 0 | B237: ='Complete GAS Bank'!C232 -> 0 | C237: ='Complete GAS Bank'!D232 -> 0 | D237: ='Complete GAS Bank'!E232 -> 0 | E237: ='Complete GAS Bank'!F232 -> 0 | F237: ='Complete GAS Bank'!G232 -> 0 | G237: ='Complete GAS Bank'!H232 -> 0 | H237: ='Complete GAS Bank'!I232 -> 0
A238: ='Complete GAS Bank'!A233 -> 0 | B238: ='Complete GAS Bank'!C233 -> 0 | C238: ='Complete GAS Bank'!D233 -> 0 | D238: ='Complete GAS Bank'!E233 -> 0 | E238: ='Complete GAS Bank'!F233 -> 0 | F238: ='Complete GAS Bank'!G233 -> 0 | G238: ='Complete GAS Bank'!H233 -> 0 | H238: ='Complete GAS Bank'!I233 -> 0
A239: ='Complete GAS Bank'!A234 -> 0 | B239: ='Complete GAS Bank'!C234 -> 0 | C239: ='Complete GAS Bank'!D234 -> 0 | D239: ='Complete GAS Bank'!E234 -> 0 | E239: ='Complete GAS Bank'!F234 -> 0 | F239: ='Complete GAS Bank'!G234 -> 0 | G239: ='Complete GAS Bank'!H234 -> 0 | H239: ='Complete GAS Bank'!I234 -> 0
A240: ='Complete GAS Bank'!A235 -> 0 | B240: ='Complete GAS Bank'!C235 -> 0 | C240: ='Complete GAS Bank'!D235 -> 0 | D240: ='Complete GAS Bank'!E235 -> 0 | E240: ='Complete GAS Bank'!F235 -> 0 | F240: ='Complete GAS Bank'!G235 -> 0 | G240: ='Complete GAS Bank'!H235 -> 0 | H240: ='Complete GAS Bank'!I235 -> 0
A241: ='Complete GAS Bank'!A236 -> 0 | B241: ='Complete GAS Bank'!C236 -> 0 | C241: ='Complete GAS Bank'!D236 -> 0 | D241: ='Complete GAS Bank'!E236 -> 0 | E241: ='Complete GAS Bank'!F236 -> 0 | F241: ='Complete GAS Bank'!G236 -> 0 | G241: ='Complete GAS Bank'!H236 -> 0 | H241: ='Complete GAS Bank'!I236 -> 0
A242: ='Complete GAS Bank'!A237 -> 0 | B242: ='Complete GAS Bank'!C237 -> 0 | C242: ='Complete GAS Bank'!D237 -> 0 | D242: ='Complete GAS Bank'!E237 -> 0 | E242: ='Complete GAS Bank'!F237 -> 0 | F242: ='Complete GAS Bank'!G237 -> 0 | G242: ='Complete GAS Bank'!H237 -> 0 | H242: ='Complete GAS Bank'!I237 -> 0
A243: ='Complete GAS Bank'!A238 -> 0 | B243: ='Complete GAS Bank'!C238 -> 0 | C243: ='Complete GAS Bank'!D238 -> 0 | D243: ='Complete GAS Bank'!E238 -> 0 | E243: ='Complete GAS Bank'!F238 -> 0 | F243: ='Complete GAS Bank'!G238 -> 0 | G243: ='Complete GAS Bank'!H238 -> 0 | H243: ='Complete GAS Bank'!I238 -> 0
... A249: ='Complete GAS Bank'!A244 -> 0 | B249: ='Complete GAS Bank'!C244 -> 0 | C249: ='Complete GAS Bank'!D244 -> 0 | D249: ='Complete GAS Bank'!E244 -> 0 | E249: ='Complete GAS Bank'!F244 -> 0 | F249: ='Complete GAS Bank'!G244 -> 0 | G249: ='Complete GAS Bank'!H244 -> 0 | H249: ='Complete GAS Bank'!I244 -> 0
A250: Comments | B250: X | C250: Type any comment you have by clicking once in this cell, then start typing comments. If you do not have a comment, click on cell and hit "delete"
B251: x | C251: Client Signature______________________________
