Workbook
Name ClearAll: BalChg!ClearAll
Name ClearAll: CommBal!ClearAll
Name ClearAll: CommInc!ClearAll
Name ClearAll: Definitions!ClearAll
Name ClearAll: [0]!ClearAll
Name DialogFrame1_Show: BalChg!DialogFrame1_Show
Name DialogFrame1_Show: CommBal!DialogFrame1_Show
Name DialogFrame1_Show: CommInc!DialogFrame1_Show
Name DialogFrame1_Show: Definitions!DialogFrame1_Show
Name DialogFrame1_Show: [0]!DialogFrame1_Show
Name DialogFrame2_Show: BalChg!DialogFrame2_Show
Name DialogFrame2_Show: CommBal!DialogFrame2_Show
Name DialogFrame2_Show: CommInc!DialogFrame2_Show
Name DialogFrame2_Show: Definitions!DialogFrame2_Show
Name DialogFrame2_Show: [0]!DialogFrame2_Show
Name GoAssumptions: [0]!GoAssumptions
Name GoBalance: BalChg!GoBalance
Name GoBalance: CommBal!GoBalance
Name GoBalance: CommInc!GoBalance
Name GoBalance: Definitions!GoBalance
Name GoBalance: [0]!GoBalance
Name GoInstructions: BalChg!GoInstructions
Name GoInstructions: CommBal!GoInstructions
Name GoInstructions: CommInc!GoInstructions
Name GoInstructions: Definitions!GoInstructions
Name GoInstructions: [0]!GoInstructions
Name GoMainMenu: BalChg!GoMainMenu
Name GoMainMenu: CommBal!GoMainMenu
Name GoMainMenu: CommInc!GoMainMenu
Name GoMainMenu: Definitions!GoMainMenu
Name GoMainMenu: [0]!GoMainMenu
Name Initialize: [0]!Initialize
Name InitialViewer: [0]!InitialViewer
Name ViewA: BalChg!ViewA
Name ViewA: CommBal!ViewA
Name ViewA: CommInc!ViewA
Name ViewA: Definitions!ViewA
Name ViewA: [0]!ViewA
Name ViewB: BalChg!ViewB
Name ViewB: CommBal!ViewB
Name ViewB: CommInc!ViewB
Name ViewB: Definitions!ViewB
Name ViewB: [0]!ViewB
Name ViewC: BalChg!ViewC
Name ViewC: CommBal!ViewC
Name ViewC: CommInc!ViewC
Name ViewC: Definitions!ViewC
Name ViewC: [0]!ViewC
Name ViewD: BalChg!ViewD
Name ViewD: CommBal!ViewD
Name ViewD: CommInc!ViewD
Name ViewD: Definitions!ViewD
Name ViewD: [0]!ViewD
Name WarnYearOne: [0]!WarnYearOne

Sheet Instructions
B4: Instructions for Using HISTORY
B6: "Word has come down from the dean
B7: That with the aid of a teaching machine
B8: Ole' Oedipus Rex could have learned about sex
B9: Without ever disturbing the Queen."
G10: Lewis Spitz
B12: HISTORY is intended as a companion to ANALYSIS FOR FINANCIAL MANAGEMENT,
B13: 6th edition, by Robert C. Higgins. Some basic familiarity with Microsoft Excel will be helpful,
B14: but not necessary, to use this program.
B16: HISTORY produces a financial analysis of up to five years of user-supplied, historical
B17: financial data. Results appear in four, convenient tables of one page each. Balance sheet and
B18: income statement entries can be customized to a limited degree to reflect the reporting
B19: practices of individual companies. HISTORY can be used with its companion program,
B20: PROFORMA, to produce up to five-year forecasts of future financial performance and possible
B21: funding needs.
B23: Input
B24: Table | C24: Contents
B25: A | C25: Historical balance sheets 1-5 years
B26: B | C26: Historical income statements 1-5 years
B27: Output
B28: C | C28: Change in balance sheet accounts
B29: D | C29: Common-size balance sheets
B30: E | C30: Common-size income statements
B31: F | C31: Ratio and sustainable growth analysis
B33: INSTRUCTIONS FOR USE
B35: All of the worksheets in HISTORY are tied to the Main Menu, from which you selected the
B36: Instructions button. To launch the other worksheets, simply choose the appropriate button from
B37: the Main Menu. You can return to the Main Menu at any time by selecting the Main Menu
B38: button from any worksheet.
B40: You may want to begin by printing a copy of these instructions. To do so, use the regular
B41: Print command in your software. You can print any of the Output Tables this way.
B43: Enter Data
B44: Leave these instructions and return to the main menu by pressing the button at the top of
B45: this page. At the main menu, select Input Data. A dialog box will appear and you can
B46: enter the information about your company. After entered your data and hit "OK", you
B47: will go automatically to the Historical Balance Sheets so you can begin your analysis.
... B67: and rename this program.

Sheet Definitions
B5: DEFINITIONS OF RATIOS APPEARING IN TABLE F
B7: Return on equity = net income/total equity
B9: Return on assets = net income/total assets
B11: Return on invested capital = [(income before tax + interest expense)
B12: (1 - provision for tax/income before tax)]/(short term debt + other s.t. debt +
B13: current portion long term debt + long term debt & capital leases + minority interest + total equity)
B15: Profit margin = net income/net sales
B17: Gross margin = gross profit/net sales
B19: Assets to equity = total assets/total equity
B21: Tot. liabilities to assets = total liabilities/total assets
B23: Tot. liabilities to equity = total liabilities/total equity
B25: Long term debt to equity = (l.t. debt & capital leases + currrent portion l.t. debt)/total equity
... B48: Retention ratio = [(1 - common dividends)/net income]*100

Sheet MainMenu
A1: MAIN MENU | J1: History
E25: Copyright 2000, Irwin/McGraw-Hill.
E26: This computer program is protected by copyright law.

Sheet DData
B5: Month | C5: Date | D5: Analysis Years
B6: January | C6: 1 | D6: 1
B7: Februrary | C7: 2 | D7: 2
B8: March | C8: 3 | D8: 3
B9: April | C9: 4 | D9: 4
B10: May | C10: 5 | D10: 5
B11: June | C11: 6
B12: July | C12: 7
B13: August | C13: 8
B14: September | C14: 9
B15: October | C15: 10
B16: November | C16: 11
B17: December | C17: 12
C18: 13
C19: 14
C20: 15
C21: 16
C22: 17
C23: 18
C24: 19
C25: 20
C26: 21
C27: 22
C28: 23
C29: 24
... C36: 31

Sheet BalanceSheets
A1: Table A. Historical Balance Sheets
I2: Net sales | J2: =#REF! -> #REF!
D3: Spencer Sporting Goods | I3: Net plant | J3: =#REF! -> #REF!
I4: Long-term debt | J4: =#REF! -> #REF!
D5: (000 omitted) | I5: Owner's equity | J5: =#REF! -> #REF!
D6: December | E6: 31
A9: ASSETS | B9: 1994 | C9: 1995 | D9: 1996 | E9: 1997
A10: Cash | B10: 36 | C10: 33 | D10: 25 | E10: 15
A11: Securities
A12: Accounts receivable | B12: 402
A13: Inventory
A14: Other current assets
A16: Total current assets | B16: =B10+B11+B12+B13+B14 -> 438 | C16: =C10+C11+C12+C13+C14 -> 33 | D16: =D10+D11+D12+D13+D14 -> 25 | E16: =E10+E11+E12+E13+E14 -> 15 | F16: =F10+F11+F12+F13+F14 -> 0
A18: Net property, plant, etc.
A19: Other investments
A20: Other long-term assets
A22: Total Assets | B22: =B16+B18+B19+B20 -> 438 | C22: =C16+C18+C19+C20 -> 33 | D22: =D16+D18+D19+D20 -> 25 | E22: =E16+E18+E19+E20 -> 15 | F22: =F16+F18+F19+F20 -> 0
A24: LIABILITIES AND SHAREHOLDERS' EQUITY
A25: Short term debt
A26: Other short-term debt
A27: Accounts payable
A28: Accrued taxes
A29: Other accruals
A30: Current portion l-t. debt
A32: Total current liabilities | B32: =B25+B26+B27+B28+B29+B30 -> 0 | C32: =C25+C26+C27+C28+C29+C30 -> 0 | D32: =D25+D26+D27+D28+D29+D30 -> 0 | E32: =E25+E26+E27+E28+E29+E30 -> 0 | F32: =F25+F26+F27+F28+F29+F30 -> 0
A34: L-t. debt and capital leases
A35: Deferred taxes
A36: Other deferrals
A37: Minority interests
A38: Other long-term liabilities
A40: Total liabilities | B40: =B32+B34+B35+B36+B37+B38 -> 0 | C40: =C32+C34+C35+C36+C37+C38 -> 0 | D40: =D32+D34+D35+D36+D37+D38 -> 0 | E40: =E32+E34+E35+E36+E37+E38 -> 0 | F40: =F32+F34+F35+F36+F37+F38 -> 0
A42: Preferred stock
A43: Owners' equity
A44: Total equity | B44: =B42+B43 -> 0 | C44: =C42+C43 -> 0 | D44: =D42+D43 -> 0 | E44: =E42+E43 -> 0 | F44: =F42+F43 -> 0
A46: Total liabilities & equity | B46: =B40+B44 -> 0 | C46: =C40+C44 -> 0 | D46: =D40+D44 -> 0 | E46: =E40+E44 -> 0 | F46: =F40+F44 -> 0

Sheet Income
A1: Table B. Historical Income Statements
I2: Net sales | J2: =#REF! -> #REF!
D3: Spencer Sporting Goods | I3: Net plant | J3: =#REF! -> #REF!
I4: Long-term debt | J4: =#REF! -> #REF!
D5: (000 omitted) | I5: Owner's equity | J5: =#REF! -> #REF!
D6: December | E6: 31
B9: 1994 | C9: 1995 | D9: 1996 | E9: 1997
A10: Net sales
A11: Cost of goods sold
A13: Gross profit | B13: =B10-B11 -> 0 | C13: =C10-C11 -> 0 | D13: =D10-D11 -> 0 | E13: =E10-E11 -> 0 | F13: =F10-F11 -> 0
A15: Operating expenses
A17: Operating income | B17: =B13-B15 -> 0 | C17: =C13-C15 -> 0 | D17: =D13-D15 -> 0 | E17: =E13-E15 -> 0 | F17: =F13-F15 -> 0
A19: Non-op. income (expense)
A20: Interest income
A21: Interest expense
A23: Income before tax | B23: =B17+B19+B20-B21 -> 0 | C23: =C17+C19+C20-C21 -> 0 | D23: =D17+D19+D20-D21 -> 0 | E23: =E17+E19+E20-E21 -> 0 | F23: =F17+F19+F20-F21 -> 0
A24: Provision for tax
A26: Net income | B26: =B23-B24 -> 0 | C26: =C23-C24 -> 0 | D26: =D23-D24 -> 0 | E26: =E23-E24 -> 0 | F26: =F23-F24 -> 0
A28: Ex. gains (loss) net tax
A29: Other gains (losses)
A30: Preferred dividends
A32: Available for common | B32: =B26+B28+B29-B30 -> 0 | C32: =C26+C28+C29-C30 -> 0 | D32: =D26+D28+D29-D30 -> 0 | E32: =E26+E28+E29-E30 -> 0 | F32: =F26+F28+F29-F30 -> 0
A34: Common dividends
A36: Added to retained earnings | B36: =B32-B34 -> 0 | C36: =C32-C34 -> 0 | D36: =D32-D34 -> 0 | E36: =E32-E34 -> 0 | F36: =F32-F34 -> 0

Sheet BalChg
A1: Table C. Changes in Balance Sheet Accounts*
J2: Net sales | K2: =#REF! -> #REF!
D3: Spencer Sporting Goods | J3: Net plant | K3: =#REF! -> #REF!
J4: Long-term debt | K4: =#REF! -> #REF!
D5: (000 omitted) | J5: Owner's equity | K5: =#REF! -> #REF!
D6: December | E6: 31
A9: ASSETS | C9: 1995 | D9: 1996 | E9: 1997
A10: Cash | C10: =BalanceSheets!C10-BalanceSheets!B10 -> -3 | D10: =BalanceSheets!D10-BalanceSheets!C10 -> -8 | E10: =BalanceSheets!E10-BalanceSheets!D10 -> -10 | F10: =BalanceSheets!F10-BalanceSheets!E10 -> -15
A11: Securities | C11: =BalanceSheets!C11-BalanceSheets!B11 -> 0 | D11: =BalanceSheets!D11-BalanceSheets!C11 -> 0 | E11: =BalanceSheets!E11-BalanceSheets!D11 -> 0 | F11: =BalanceSheets!F11-BalanceSheets!E11 -> 0
A12: Accounts receivable | C12: =BalanceSheets!C12-BalanceSheets!B12 -> -402 | D12: =BalanceSheets!D12-BalanceSheets!C12 -> 0 | E12: =BalanceSheets!E12-BalanceSheets!D12 -> 0 | F12: =BalanceSheets!F12-BalanceSheets!E12 -> 0
A13: Inventory | C13: =BalanceSheets!C13-BalanceSheets!B13 -> 0 | D13: =BalanceSheets!D13-BalanceSheets!C13 -> 0 | E13: =BalanceSheets!E13-BalanceSheets!D13 -> 0 | F13: =BalanceSheets!F13-BalanceSheets!E13 -> 0
A14: Other current assets | C14: =BalanceSheets!C14-BalanceSheets!B14 -> 0 | D14: =BalanceSheets!D14-BalanceSheets!C14 -> 0 | E14: =BalanceSheets!E14-BalanceSheets!D14 -> 0 | F14: =BalanceSheets!F14-BalanceSheets!E14 -> 0
A16: Total current assets | C16: =C10+C11+C12+C13+C14 -> -405 | D16: =D10+D11+D12+D13+D14 -> -8 | E16: =E10+E11+E12+E13+E14 -> -10 | F16: =F10+F11+F12+F13+F14 -> -15
A18: Net property, plant, etc. | C18: =BalanceSheets!C18-BalanceSheets!B18 -> 0 | D18: =BalanceSheets!D18-BalanceSheets!C18 -> 0 | E18: =BalanceSheets!E18-BalanceSheets!D18 -> 0 | F18: =BalanceSheets!F18-BalanceSheets!E18 -> 0
A19: Other investments | C19: =BalanceSheets!C19-BalanceSheets!B19 -> 0 | D19: =BalanceSheets!D19-BalanceSheets!C19 -> 0 | E19: =BalanceSheets!E19-BalanceSheets!D19 -> 0 | F19: =BalanceSheets!F19-BalanceSheets!E19 -> 0
A20: Other long-term assets | C20: =BalanceSheets!C20-BalanceSheets!B20 -> 0 | D20: =BalanceSheets!D20-BalanceSheets!C20 -> 0 | E20: =BalanceSheets!E20-BalanceSheets!D20 -> 0 | F20: =BalanceSheets!F20-BalanceSheets!E20 -> 0
A22: Total Assets | C22: =C16+C18+C19+C20 -> -405 | D22: =D16+D18+D19+D20 -> -8 | E22: =E16+E18+E19+E20 -> -10 | F22: =F16+F18+F19+F20 -> -15
A24: LIABILITIES AND SHAREHOLDERS' EQUITY
A25: Short term debt | C25: =BalanceSheets!C25-BalanceSheets!B25 -> 0 | D25: =BalanceSheets!D25-BalanceSheets!C25 -> 0 | E25: =BalanceSheets!E25-BalanceSheets!D25 -> 0 | F25: =BalanceSheets!F25-BalanceSheets!E25 -> 0
A26: Other short-term debt | C26: =BalanceSheets!C26-BalanceSheets!B26 -> 0 | D26: =BalanceSheets!D26-BalanceSheets!C26 -> 0 | E26: =BalanceSheets!E26-BalanceSheets!D26 -> 0 | F26: =BalanceSheets!F26-BalanceSheets!E26 -> 0
A27: Accounts payable | C27: =BalanceSheets!C27-BalanceSheets!B27 -> 0 | D27: =BalanceSheets!D27-BalanceSheets!C27 -> 0 | E27: =BalanceSheets!E27-BalanceSheets!D27 -> 0 | F27: =BalanceSheets!F27-BalanceSheets!E27 -> 0
A28: Accrued taxes | C28: =BalanceSheets!C28-BalanceSheets!B28 -> 0 | D28: =BalanceSheets!D28-BalanceSheets!C28 -> 0 | E28: =BalanceSheets!E28-BalanceSheets!D28 -> 0 | F28: =BalanceSheets!F28-BalanceSheets!E28 -> 0
A29: Other accruals | C29: =BalanceSheets!C29-BalanceSheets!B29 -> 0 | D29: =BalanceSheets!D29-BalanceSheets!C29 -> 0 | E29: =BalanceSheets!E29-BalanceSheets!D29 -> 0 | F29: =BalanceSheets!F29-BalanceSheets!E29 -> 0
A30: Current portion l-t. debt | C30: =BalanceSheets!C30-BalanceSheets!B30 -> 0 | D30: =BalanceSheets!D30-BalanceSheets!C30 -> 0 | E30: =BalanceSheets!E30-BalanceSheets!D30 -> 0 | F30: =BalanceSheets!F30-BalanceSheets!E30 -> 0
A32: Total current liabilities | C32: =C26+C27+C28+C29+C30 -> 0 | D32: =D26+D27+D28+D29+D30 -> 0 | E32: =E26+E27+E28+E29+E30 -> 0 | F32: =F26+F27+F28+F29+F30 -> 0
A34: L-t. debt and capital leases | C34: =BalanceSheets!C34-BalanceSheets!B34 -> 0 | D34: =BalanceSheets!D34-BalanceSheets!C34 -> 0 | E34: =BalanceSheets!E34-BalanceSheets!D34 -> 0 | F34: =BalanceSheets!F34-BalanceSheets!E34 -> 0
A35: Deferred taxes | C35: =BalanceSheets!C35-BalanceSheets!B35 -> 0 | D35: =BalanceSheets!D35-BalanceSheets!C35 -> 0 | E35: =BalanceSheets!E35-BalanceSheets!D35 -> 0 | F35: =BalanceSheets!F35-BalanceSheets!E35 -> 0
A36: Other deferrals | C36: =BalanceSheets!C36-BalanceSheets!B36 -> 0 | D36: =BalanceSheets!D36-BalanceSheets!C36 -> 0 | E36: =BalanceSheets!E36-BalanceSheets!D36 -> 0 | F36: =BalanceSheets!F36-BalanceSheets!E36 -> 0
A37: Minority interests | C37: =BalanceSheets!C37-BalanceSheets!B37 -> 0 | D37: =BalanceSheets!D37-BalanceSheets!C37 -> 0 | E37: =BalanceSheets!E37-BalanceSheets!D37 -> 0 | F37: =BalanceSheets!F37-BalanceSheets!E37 -> 0
A38: Other long-term liabilities | C38: =BalanceSheets!C38-BalanceSheets!B38 -> 0 | D38: =BalanceSheets!D38-BalanceSheets!C38 -> 0 | E38: =BalanceSheets!E38-BalanceSheets!D38 -> 0 | F38: =BalanceSheets!F38-BalanceSheets!E38 -> 0
A40: Total liabilities | C40: =C32+C34+C35+C36+C37+C38 -> 0 | D40: =D32+D34+D35+D36+D37+D38 -> 0 | E40: =E32+E34+E35+E36+E37+E38 -> 0 | F40: =F32+F34+F35+F36+F37+F38 -> 0
A42: Preferred stock | C42: =BalanceSheets!C42-BalanceSheets!B42 -> 0 | D42: =BalanceSheets!D42-BalanceSheets!C42 -> 0 | E42: =BalanceSheets!E42-BalanceSheets!D42 -> 0 | F42: =BalanceSheets!F42-BalanceSheets!E42 -> 0
A43: Owners' equity | C43: =BalanceSheets!C43-BalanceSheets!B43 -> 0 | D43: =BalanceSheets!D43-BalanceSheets!C43 -> 0 | E43: =BalanceSheets!E43-BalanceSheets!D43 -> 0 | F43: =BalanceSheets!F43-BalanceSheets!E43 -> 0
A44: Total equity | C44: =BalanceSheets!C44-BalanceSheets!B44 -> 0 | D44: =BalanceSheets!D44-BalanceSheets!C44 -> 0 | E44: =BalanceSheets!E44-BalanceSheets!D44 -> 0 | F44: =BalanceSheets!F44-BalanceSheets!E44 -> 0
A46: Total liabilities & equity | C46: =C40+C44 -> 0 | D46: =D40+D44 -> 0 | E46: =E40+E44 -> 0 | F46: =F40+F44 -> 0
A48: *ASSETS: + (Positive) = Use and - (Negative) = Source ; LIABILITIES: + = Source, - = Use

Sheet CommBal
A1: Table D. Common Size Balance Sheets
I2: Net sales | J2: =#REF! -> #REF!
D3: Spencer Sporting Goods | I3: Net plant | J3: =#REF! -> #REF!
I4: Long-term debt | J4: =#REF! -> #REF!
D5: (000 omitted) | I5: Owner's equity | J5: =#REF! -> #REF!
D6: December | E6: 31
A9: ASSETS | B9: 1994 | C9: 1995 | D9: 1996 | E9: 1997
A10: Cash | B10: =BalanceSheets!B10/BalanceSheets!B$22 -> 0.082191781 | C10: =BalanceSheets!C10/BalanceSheets!C22 -> 1 | D10: =BalanceSheets!D10/BalanceSheets!D22 -> 1 | E10: =BalanceSheets!E10/BalanceSheets!E22 -> 1 | F10: =BalanceSheets!F10/BalanceSheets!F22 -> #DIV/0!
A11: Securities | B11: =BalanceSheets!B11/BalanceSheets!B$22 -> 0 | C11: =BalanceSheets!C11/BalanceSheets!C$22 -> 0 | D11: =BalanceSheets!D11/BalanceSheets!D$22 -> 0 | E11: =BalanceSheets!E11/BalanceSheets!E$22 -> 0 | F11: =BalanceSheets!F11/BalanceSheets!F$22 -> #DIV/0!
A12: Accounts receivable | B12: =BalanceSheets!B12/BalanceSheets!B$22 -> 0.91780822 | C12: =BalanceSheets!C12/BalanceSheets!C$22 -> 0 | D12: =BalanceSheets!D12/BalanceSheets!D$22 -> 0 | E12: =BalanceSheets!E12/BalanceSheets!E$22 -> 0 | F12: =BalanceSheets!F12/BalanceSheets!F$22 -> #DIV/0!
A13: Inventory | B13: =BalanceSheets!B13/BalanceSheets!B$22 -> 0 | C13: =BalanceSheets!C13/BalanceSheets!C$22 -> 0 | D13: =BalanceSheets!D13/BalanceSheets!D$22 -> 0 | E13: =BalanceSheets!E13/BalanceSheets!E$22 -> 0 | F13: =BalanceSheets!F13/BalanceSheets!F$22 -> #DIV/0!
A14: Other current assets | B14: =BalanceSheets!B14/BalanceSheets!B$22 -> 0 | C14: =BalanceSheets!C14/BalanceSheets!C$22 -> 0 | D14: =BalanceSheets!D14/BalanceSheets!D$22 -> 0 | E14: =BalanceSheets!E14/BalanceSheets!E$22 -> 0 | F14: =BalanceSheets!F14/BalanceSheets!F$22 -> #DIV/0!
A16: Total current assets | B16: =BalanceSheets!B16/BalanceSheets!B$22 -> 1 | C16: =BalanceSheets!C16/BalanceSheets!C$22 -> 1 | D16: =BalanceSheets!D16/BalanceSheets!D$22 -> 1 | E16: =BalanceSheets!E16/BalanceSheets!E$22 -> 1 | F16: =BalanceSheets!F16/BalanceSheets!F$22 -> #DIV/0!
A18: Net property, plant, etc. | B18: =BalanceSheets!B18/BalanceSheets!B$22 -> 0 | C18: =BalanceSheets!C18/BalanceSheets!C$22 -> 0 | D18: =BalanceSheets!D18/BalanceSheets!D$22 -> 0 | E18: =BalanceSheets!E18/BalanceSheets!E$22 -> 0 | F18: =BalanceSheets!F18/BalanceSheets!F$22 -> #DIV/0!
A19: Other investments | B19: =BalanceSheets!B19/BalanceSheets!B$22 -> 0 | C19: =BalanceSheets!C19/BalanceSheets!C$22 -> 0 | D19: =BalanceSheets!D19/BalanceSheets!D$22 -> 0 | E19: =BalanceSheets!E19/BalanceSheets!E$22 -> 0 | F19: =BalanceSheets!F19/BalanceSheets!F$22 -> #DIV/0!
A20: Other long-term assets | B20: =BalanceSheets!B20/BalanceSheets!B$22 -> 0 | C20: =BalanceSheets!C20/BalanceSheets!C$22 -> 0 | D20: =BalanceSheets!D20/BalanceSheets!D$22 -> 0 | E20: =BalanceSheets!E20/BalanceSheets!E$22 -> 0 | F20: =BalanceSheets!F20/BalanceSheets!F$22 -> #DIV/0!
A22: Total Assets | B22: =BalanceSheets!B22/BalanceSheets!B$22 -> 1 | C22: =BalanceSheets!C22/BalanceSheets!C$22 -> 1 | D22: =BalanceSheets!D22/BalanceSheets!D$22 -> 1 | E22: =BalanceSheets!E22/BalanceSheets!E$22 -> 1 | F22: =BalanceSheets!F22/BalanceSheets!F$22 -> #DIV/0!
A24: LIABILITIES AND SHAREHOLDERS' EQUITY
A25: Short term debt | B25: =BalanceSheets!B25/BalanceSheets!B$46 -> #DIV/0! | C25: =BalanceSheets!C25/BalanceSheets!C$46 -> #DIV/0! | D25: =BalanceSheets!D25/BalanceSheets!D$46 -> #DIV/0! | E25: =BalanceSheets!E25/BalanceSheets!E$46 -> #DIV/0! | F25: =BalanceSheets!F25/BalanceSheets!F$46 -> #DIV/0!
A26: Other short-term debt | B26: =BalanceSheets!B26/BalanceSheets!B$46 -> #DIV/0! | C26: =BalanceSheets!C26/BalanceSheets!C$46 -> #DIV/0! | D26: =BalanceSheets!D26/BalanceSheets!D$46 -> #DIV/0! | E26: =BalanceSheets!E26/BalanceSheets!E$46 -> #DIV/0! | F26: =BalanceSheets!F26/BalanceSheets!F$46 -> #DIV/0!
A27: Accounts payable | B27: =BalanceSheets!B27/BalanceSheets!B$46 -> #DIV/0! | C27: =BalanceSheets!C27/BalanceSheets!C$46 -> #DIV/0! | D27: =BalanceSheets!D27/BalanceSheets!D$46 -> #DIV/0! | E27: =BalanceSheets!E27/BalanceSheets!E$46 -> #DIV/0! | F27: =BalanceSheets!F27/BalanceSheets!F$46 -> #DIV/0!
A28: Accrued taxes | B28: =BalanceSheets!B28/BalanceSheets!B$46 -> #DIV/0! | C28: =BalanceSheets!C28/BalanceSheets!C$46 -> #DIV/0! | D28: =BalanceSheets!D28/BalanceSheets!D$46 -> #DIV/0! | E28: =BalanceSheets!E28/BalanceSheets!E$46 -> #DIV/0! | F28: =BalanceSheets!F28/BalanceSheets!F$46 -> #DIV/0!
A29: Other accruals | B29: =BalanceSheets!B29/BalanceSheets!B$46 -> #DIV/0! | C29: =BalanceSheets!C29/BalanceSheets!C$46 -> #DIV/0! | D29: =BalanceSheets!D29/BalanceSheets!D$46 -> #DIV/0! | E29: =BalanceSheets!E29/BalanceSheets!E$46 -> #DIV/0! | F29: =BalanceSheets!F29/BalanceSheets!F$46 -> #DIV/0!
A30: Current portion l-t. debt | B30: =BalanceSheets!B30/BalanceSheets!B$46 -> #DIV/0! | C30: =BalanceSheets!C30/BalanceSheets!C$46 -> #DIV/0! | D30: =BalanceSheets!D30/BalanceSheets!D$46 -> #DIV/0! | E30: =BalanceSheets!E30/BalanceSheets!E$46 -> #DIV/0! | F30: =BalanceSheets!F30/BalanceSheets!F$46 -> #DIV/0!
A32: Total current liabilities | B32: =BalanceSheets!B32/BalanceSheets!B$46 -> #DIV/0! | C32: =BalanceSheets!C32/BalanceSheets!C$46 -> #DIV/0! | D32: =BalanceSheets!D32/BalanceSheets!D$46 -> #DIV/0! | E32: =BalanceSheets!E32/BalanceSheets!E$46 -> #DIV/0! | F32: =BalanceSheets!F32/BalanceSheets!F$46 -> #DIV/0!
A34: L-t. debt and capital leases | B34: =BalanceSheets!B34/BalanceSheets!B$46 -> #DIV/0! | C34: =BalanceSheets!C34/BalanceSheets!C$46 -> #DIV/0! | D34: =BalanceSheets!D34/BalanceSheets!D$46 -> #DIV/0! | E34: =BalanceSheets!E34/BalanceSheets!E$46 -> #DIV/0! | F34: =BalanceSheets!F34/BalanceSheets!F$46 -> #DIV/0!
A35: Deferred taxes | B35: =BalanceSheets!B35/BalanceSheets!B$46 -> #DIV/0! | C35: =BalanceSheets!C35/BalanceSheets!C$46 -> #DIV/0! | D35: =BalanceSheets!D35/BalanceSheets!D$46 -> #DIV/0! | E35: =BalanceSheets!E35/BalanceSheets!E$46 -> #DIV/0! | F35: =BalanceSheets!F35/BalanceSheets!F$46 -> #DIV/0!
A36: Other deferrals | B36: =BalanceSheets!B36/BalanceSheets!B$46 -> #DIV/0! | C36: =BalanceSheets!C36/BalanceSheets!C$46 -> #DIV/0! | D36: =BalanceSheets!D36/BalanceSheets!D$46 -> #DIV/0! | E36: =BalanceSheets!E36/BalanceSheets!E$46 -> #DIV/0! | F36: =BalanceSheets!F36/BalanceSheets!F$46 -> #DIV/0!
A37: Minority interests | B37: =BalanceSheets!B37/BalanceSheets!B$46 -> #DIV/0! | C37: =BalanceSheets!C37/BalanceSheets!C$46 -> #DIV/0! | D37: =BalanceSheets!D37/BalanceSheets!D$46 -> #DIV/0! | E37: =BalanceSheets!E37/BalanceSheets!E$46 -> #DIV/0! | F37: =BalanceSheets!F37/BalanceSheets!F$46 -> #DIV/0!
A38: Other long-term liabilities | B38: =BalanceSheets!B38/BalanceSheets!B$46 -> #DIV/0! | C38: =BalanceSheets!C38/BalanceSheets!C$46 -> #DIV/0! | D38: =BalanceSheets!D38/BalanceSheets!D$46 -> #DIV/0! | E38: =BalanceSheets!E38/BalanceSheets!E$46 -> #DIV/0! | F38: =BalanceSheets!F38/BalanceSheets!F$46 -> #DIV/0!
... A46: Total liabilities & equity | B46: =BalanceSheets!B46/BalanceSheets!B$46 -> #DIV/0! | C46: =BalanceSheets!C46/BalanceSheets!C$46 -> #DIV/0! | D46: =BalanceSheets!D46/BalanceSheets!D$46 -> #DIV/0! | E46: =BalanceSheets!E46/BalanceSheets!E$46 -> #DIV/0! | F46: =BalanceSheets!F46/BalanceSheets!F$46 -> #DIV/0!

Sheet CommInc
A1: Table E. Common Size Income Statements
I2: Net sales | J2: =#REF! -> #REF!
D3: Spencer Sporting Goods | I3: Net plant | J3: =#REF! -> #REF!
I4: Long-term debt | J4: =#REF! -> #REF!
D5: (000 omitted) | I5: Owner's equity | J5: =#REF! -> #REF!
D6: December | E6: 31
B9: 1994 | C9: 1995 | D9: 1996 | E9: 1997
A10: Net sales | B10: =Income!B10/Income!B$10 -> #DIV/0! | C10: =Income!C10/Income!C$10 -> #DIV/0! | D10: =Income!D10/Income!D$10 -> #DIV/0! | E10: =Income!E10/Income!E$10 -> #DIV/0! | F10: =Income!F10/Income!F$10 -> #DIV/0!
A11: Cost of goods sold | B11: =Income!B11/Income!B$10 -> #DIV/0! | C11: =Income!C11/Income!C$10 -> #DIV/0! | D11: =Income!D11/Income!D$10 -> #DIV/0! | E11: =Income!E11/Income!E$10 -> #DIV/0! | F11: =Income!F11/Income!F$10 -> #DIV/0!
A13: Gross profit | B13: =Income!B13/Income!B$10 -> #DIV/0! | C13: =Income!C13/Income!C$10 -> #DIV/0! | D13: =Income!D13/Income!D$10 -> #DIV/0! | E13: =Income!E13/Income!E$10 -> #DIV/0! | F13: =Income!F13/Income!F$10 -> #DIV/0!
A15: Operating expenses | B15: =Income!B15/Income!B$10 -> #DIV/0! | C15: =Income!C15/Income!C$10 -> #DIV/0! | D15: =Income!D15/Income!D$10 -> #DIV/0! | E15: =Income!E15/Income!E$10 -> #DIV/0! | F15: =Income!F15/Income!F$10 -> #DIV/0!
A17: Operating income | B17: =Income!B17/Income!B$10 -> #DIV/0! | C17: =Income!C17/Income!C$10 -> #DIV/0! | D17: =Income!D17/Income!D$10 -> #DIV/0! | E17: =Income!E17/Income!E$10 -> #DIV/0! | F17: =Income!F17/Income!F$10 -> #DIV/0!
A19: Non-op. income (expense) | B19: =Income!B19/Income!B$10 -> #DIV/0! | C19: =Income!C19/Income!C$10 -> #DIV/0! | D19: =Income!D19/Income!D$10 -> #DIV/0! | E19: =Income!E19/Income!E$10 -> #DIV/0! | F19: =Income!F19/Income!F$10 -> #DIV/0!
A20: Interest income | B20: =Income!B20/Income!B$10 -> #DIV/0! | C20: =Income!C20/Income!C$10 -> #DIV/0! | D20: =Income!D20/Income!D$10 -> #DIV/0! | E20: =Income!E20/Income!E$10 -> #DIV/0! | F20: =Income!F20/Income!F$10 -> #DIV/0!
A21: Interest expense | B21: =Income!B21/Income!B$10 -> #DIV/0! | C21: =Income!C21/Income!C$10 -> #DIV/0! | D21: =Income!D21/Income!D$10 -> #DIV/0! | E21: =Income!E21/Income!E$10 -> #DIV/0! | F21: =Income!F21/Income!F$10 -> #DIV/0!
A23: Income before tax | B23: =Income!B23/Income!B$10 -> #DIV/0! | C23: =Income!C23/Income!C$10 -> #DIV/0! | D23: =Income!D23/Income!D$10 -> #DIV/0! | E23: =Income!E23/Income!E$10 -> #DIV/0! | F23: =Income!F23/Income!F$10 -> #DIV/0!
A24: Provision for tax | B24: =Income!B24/Income!B$10 -> #DIV/0! | C24: =Income!C24/Income!C$10 -> #DIV/0! | D24: =Income!D24/Income!D$10 -> #DIV/0! | E24: =Income!E24/Income!E$10 -> #DIV/0! | F24: =Income!F24/Income!F$10 -> #DIV/0!
A26: Net income | B26: =Income!B26/Income!B$10 -> #DIV/0! | C26: =Income!C26/Income!C$10 -> #DIV/0! | D26: =Income!D26/Income!D$10 -> #DIV/0! | E26: =Income!E26/Income!E$10 -> #DIV/0! | F26: =Income!F26/Income!F$10 -> #DIV/0!
A28: Ex. gains (loss) net tax | B28: =Income!B28/Income!B$10 -> #DIV/0! | C28: =Income!C28/Income!C$10 -> #DIV/0! | D28: =Income!D28/Income!D$10 -> #DIV/0! | E28: =Income!E28/Income!E$10 -> #DIV/0! | F28: =Income!F28/Income!F$10 -> #DIV/0!
... A36: Added to retained earnings | B36: =Income!B36/Income!B$10 -> #DIV/0! | C36: =Income!C36/Income!C$10 -> #DIV/0! | D36: =Income!D36/Income!D$10 -> #DIV/0! | E36: =Income!E36/Income!E$10 -> #DIV/0! | F36: =Income!F36/Income!F$10 -> #DIV/0!

Sheet Ratio
A1: Table F. Ratio and Sustainable Growth Analysis
C3: Spencer Sporting Goods
B6: 1994 | C6: 1995 | D6: 1996 | E6: 1997
A7: PROFITABILITY RATIOS:
A8: Return on equity (%) | B8: =Income!B26/BalanceSheets!B44 -> #DIV/0! | C8: =Income!C26/BalanceSheets!C44 -> #DIV/0! | D8: =Income!D26/BalanceSheets!D44 -> #DIV/0! | E8: =Income!E26/BalanceSheets!E44 -> #DIV/0! | F8: =Income!F26/BalanceSheets!F44 -> #DIV/0!
A9: Return on assets (%) | B9: =Income!B26/BalanceSheets!B22 -> 0 | C9: =Income!C26/BalanceSheets!C22 -> 0 | D9: =Income!D26/BalanceSheets!D22 -> 0 | E9: =Income!E26/BalanceSheets!E22 -> 0 | F9: =Income!F26/BalanceSheets!F22 -> #DIV/0!
A10: Return on inv. captial (%) | B10: =((Income!B23+Income!B21)*(1-Income!B24/Income!B23))/(BalanceSheets!B25+BalanceSheets!B26+BalanceSheets!B30+BalanceSheets!B34+BalanceSheets!B37+BalanceSheets!B44) -> #DIV/0! | C10: =((Income!C23+Income!C21)*(1-Income!C24/Income!C23))/(BalanceSheets!C25+BalanceSheets!C26+BalanceSheets!C30+BalanceSheets!C34+BalanceSheets!C37+BalanceSheets!C44) -> #DIV/0! | D10: =((Income!D23+Income!D21)*(1-Income!D24/Income!D23))/(BalanceSheets!D25+BalanceSheets!D26+BalanceSheets!D30+BalanceSheets!D34+BalanceSheets!D37+BalanceSheets!D44) -> #DIV/0! | E10: =((Income!E23+Income!E21)*(1-Income!E24/Income!E23))/(BalanceSheets!E25+BalanceSheets!E26+BalanceSheets!E30+BalanceSheets!E34+BalanceSheets!E37+BalanceSheets!E44) -> #DIV/0! | F10: =((Income!F23+Income!F21)*(1-Income!F24/Income!F23))/(BalanceSheets!F25+BalanceSheets!F26+BalanceSheets!F30+BalanceSheets!F34+BalanceSheets!F37+BalanceSheets!F44) -> #DIV/0!
A11: Profit margin (%) | B11: =Income!B26/Income!B10 -> #DIV/0! | C11: =Income!C26/Income!C10 -> #DIV/0! | D11: =Income!D26/Income!D10 -> #DIV/0! | E11: =Income!E26/Income!E10 -> #DIV/0! | F11: =Income!F26/Income!F10 -> #DIV/0!
A12: Gross margin (%) | B12: =Income!B13/Income!B10 -> #DIV/0! | C12: =Income!C13/Income!C10 -> #DIV/0! | D12: =Income!D13/Income!D10 -> #DIV/0! | E12: =Income!E13/Income!E10 -> #DIV/0! | F12: =Income!F13/Income!F10 -> #DIV/0!
A14: LEVERAGE & LIQUIDITY RATIOS:
A15: Assets to equity (%) | B15: =BalanceSheets!B22/BalanceSheets!B44 -> #DIV/0! | C15: =BalanceSheets!C22/BalanceSheets!C44 -> #DIV/0! | D15: =BalanceSheets!D22/BalanceSheets!D44 -> #DIV/0! | E15: =BalanceSheets!E22/BalanceSheets!E44 -> #DIV/0! | F15: =BalanceSheets!F22/BalanceSheets!F44 -> #DIV/0!
A16: Total liabilities to assets (%) | B16: =(BalanceSheets!B40/BalanceSheets!B22) -> 0 | C16: =(BalanceSheets!C40/BalanceSheets!C22) -> 0 | D16: =(BalanceSheets!D40/BalanceSheets!D22) -> 0 | E16: =(BalanceSheets!E40/BalanceSheets!E22) -> 0 | F16: =(BalanceSheets!F40/BalanceSheets!F22) -> #DIV/0!
A17: Total liabilities to equity (%) | B17: =(BalanceSheets!B40/BalanceSheets!B44) -> #DIV/0! | C17: =(BalanceSheets!C40/BalanceSheets!C44) -> #DIV/0! | D17: =(BalanceSheets!D40/BalanceSheets!D44) -> #DIV/0! | E17: =(BalanceSheets!E40/BalanceSheets!E44) -> #DIV/0! | F17: =(BalanceSheets!F40/BalanceSheets!F44) -> #DIV/0!
A18: Long term debt to equity (%) | B18: =(BalanceSheets!B34+BalanceSheets!B30)/BalanceSheets!B44 -> #DIV/0! | C18: =(BalanceSheets!C34+BalanceSheets!C30)/BalanceSheets!C44 -> #DIV/0! | D18: =(BalanceSheets!D34+BalanceSheets!D30)/BalanceSheets!D44 -> #DIV/0! | E18: =(BalanceSheets!E34+BalanceSheets!E30)/BalanceSheets!E44 -> #DIV/0! | F18: =(BalanceSheets!F34+BalanceSheets!F30)/BalanceSheets!F44 -> #DIV/0!
A19: Times interest earned (x) | B19: =(Income!B23+Income!B21)/Income!B21 -> #DIV/0! | C19: =(Income!C23+Income!C21)/Income!C21 -> #DIV/0! | D19: =(Income!D23+Income!D21)/Income!D21 -> #DIV/0! | E19: =(Income!E23+Income!E21)/Income!E21 -> #DIV/0! | F19: =(Income!F23+Income!F21)/Income!F21 -> #DIV/0!
A20: Times burden covered (x) | B20: =(Income!B23+Income!B21)/(Income!B21+BalanceSheets!B30/(1-Income!B24/Income!B23)) -> #DIV/0! | C20: =(Income!C23+Income!C21)/(Income!C21+BalanceSheets!C30/(1-Income!C24/Income!C23)) -> #DIV/0! | D20: =(Income!D23+Income!D21)/(Income!D21+BalanceSheets!D30/(1-Income!D24/Income!D23)) -> #DIV/0! | E20: =(Income!E23+Income!E21)/(Income!E21+BalanceSheets!E30/(1-Income!E24/Income!E23)) -> #DIV/0! | F20: =(Income!F23+Income!F21)/(Income!F21+BalanceSheets!F30/(1-Income!F24/Income!F23)) -> #DIV/0!
A21: Current ratio (x) | B21: =(BalanceSheets!B16/BalanceSheets!B32) -> #DIV/0! | C21: =(BalanceSheets!C16/BalanceSheets!C32) -> #DIV/0! | D21: =(BalanceSheets!D16/BalanceSheets!D32) -> #DIV/0! | E21: =(BalanceSheets!E16/BalanceSheets!E32) -> #DIV/0! | F21: =(BalanceSheets!F16/BalanceSheets!F32) -> #DIV/0!
A22: Acid test (x) | B22: =(BalanceSheets!B16-BalanceSheets!B13)/BalanceSheets!B32 -> #DIV/0! | C22: =(BalanceSheets!C16-BalanceSheets!C13)/BalanceSheets!C32 -> #DIV/0! | D22: =(BalanceSheets!D16-BalanceSheets!D13)/BalanceSheets!D32 -> #DIV/0! | E22: =(BalanceSheets!E16-BalanceSheets!E13)/BalanceSheets!E32 -> #DIV/0! | F22: =(BalanceSheets!F16-BalanceSheets!F13)/BalanceSheets!F32 -> #DIV/0!
A24: TURNOVER-CONTROL RATIOS:
A25: Asset turnover (x) | B25: =(Income!B10/BalanceSheets!B22) -> 0 | C25: =(Income!C10/BalanceSheets!C22) -> 0 | D25: =(Income!D10/BalanceSheets!D22) -> 0 | E25: =(Income!E10/BalanceSheets!E22) -> 0 | F25: =(Income!F10/BalanceSheets!F22) -> #DIV/0!
A26: Inventory turnover (x) | B26: =Income!B11/BalanceSheets!B13 -> #DIV/0! | C26: =Income!C11/BalanceSheets!C13 -> #DIV/0! | D26: =Income!D11/BalanceSheets!D13 -> #DIV/0! | E26: =Income!E11/BalanceSheets!E13 -> #DIV/0! | F26: =Income!F11/BalanceSheets!F13 -> #DIV/0!
A27: Collection period (days) | B27: =BalanceSheets!B12/(Income!B10/365) -> #DIV/0! | C27: =BalanceSheets!C12/(Income!C10/365) -> #DIV/0! | D27: =BalanceSheets!D12/(Income!D10/365) -> #DIV/0! | E27: =BalanceSheets!E12/(Income!E10/365) -> #DIV/0! | F27: =BalanceSheets!F12/(Income!F10/365) -> #DIV/0!
A28: Days sales in cash (days) | B28: =BalanceSheets!B10/(Income!B10/365) -> #DIV/0! | C28: =BalanceSheets!C10/(Income!C10/365) -> #DIV/0! | D28: =BalanceSheets!D10/(Income!D10/365) -> #DIV/0! | E28: =BalanceSheets!E10/(Income!E10/365) -> #DIV/0! | F28: =BalanceSheets!F10/(Income!F10/365) -> #DIV/0!
A29: Payables period (days) | B29: =BalanceSheets!B27/(Income!B11/365) -> #DIV/0! | C29: =BalanceSheets!C27/(Income!C11/365) -> #DIV/0! | D29: =BalanceSheets!D27/(Income!D11/365) -> #DIV/0! | E29: =BalanceSheets!E27/(Income!E11/365) -> #DIV/0! | F29: =BalanceSheets!F27/(Income!F11/365) -> #DIV/0!
A30: Fixed asset turnover (x) | B30: =Income!B10/BalanceSheets!B18 -> #DIV/0! | C30: =Income!C10/BalanceSheets!C18 -> #DIV/0! | D30: =Income!D10/BalanceSheets!D18 -> #DIV/0! | E30: =Income!E10/BalanceSheets!E18 -> #DIV/0! | F30: =Income!F10/BalanceSheets!F18 -> #DIV/0!
A32: Pro Forma Sustainable Growth Analysis
B34: 1994 | C34: 1995 | D34: 1996 | E34: 1997
A35: REQUIRED RATIOS:
A36: Profit margin (P) | B36: =B11 -> #DIV/0! | C36: =C11 -> #DIV/0! | D36: =D11 -> #DIV/0! | E36: =E11 -> #DIV/0! | F36: =F11 -> #DIV/0!
A37: Retention ratio (R) | B37: =1-(Income!B34/Income!B32) -> #DIV/0! | C37: =1-(Income!C34/Income!C32) -> #DIV/0! | D37: =1-(Income!D34/Income!D32) -> #DIV/0! | E37: =1-(Income!E34/Income!E32) -> #DIV/0! | F37: =1-(Income!F34/Income!F32) -> #DIV/0!
A38: Asset turnover (A) | B38: =B25 -> 0 | C38: =C25 -> 0 | D38: =D25 -> 0 | E38: =E25 -> 0 | F38: =F25 -> #DIV/0!
A39: Financial leverage# (T) | B39: n/a | C39: =(BalanceSheets!C22/BalanceSheets!B44) -> #DIV/0! | D39: =(BalanceSheets!D22/BalanceSheets!C44) -> #DIV/0! | E39: =(BalanceSheets!E22/BalanceSheets!D44) -> #DIV/0! | F39: =(BalanceSheets!F22/BalanceSheets!E44) -> #DIV/0!
A41: Sustainable growth rate (g*) | B41: n/a | C41: =C36*C37*C38*C39 -> #DIV/0! | D41: =D36*D37*D38*D39 -> #DIV/0! | E41: =E36*E37*E38*E39 -> #DIV/0! | F41: =F36*F37*F38*F39 -> #DIV/0!
A42: Actual growth rate (g) | B42: n/a | C42: =(Income!C10-Income!B10)/Income!B10 -> #DIV/0! | D42: =(Income!D10-Income!C10)/Income!C10 -> #DIV/0! | E42: =(Income!E10-Income!D10)/Income!D10 -> #DIV/0! | F42: =(Income!F10-Income!E10)/Income!E10 -> #DIV/0!
A44: #Defined as assets divided by beginning-of-period equity
