Workbook
Name book_price: Simple!$B$4
Name book_price2: 'Sensitivity Analysis'!$B$4
Name book_price2: Advanced!$B$4
Name books_sold: Simple!$B$8
Name books_sold2: 'Sensitivity Analysis'!$B$15
Name books_sold2: Advanced!$B$15
Name cost_intercept: Simple!#REF!
Name cost_intercept2: 'Sensitivity Analysis'!#REF!
Name cost_intercept2: Advanced!#REF!
Name cost_slope: Simple!#REF!
Name cost_slope2: 'Sensitivity Analysis'!#REF!
Name cost_slope2: Advanced!#REF!
Name demand_intercept: 'Sensitivity Analysis'!$B$11
Name demand_intercept: Advanced!$B$11
Name demand_slope: 'Sensitivity Analysis'!$B$12
Name demand_slope: Advanced!$B$12
Name num_pages: 'Sensitivity Analysis'!$B$44
Name profit: Simple!$B$15
Name profit2: 'Sensitivity Analysis'!$B$21
Name profit2: Advanced!$B$21
Name publish_cost: Simple!$B$13
Name publish_cost2: 'Sensitivity Analysis'!$B$19
Name publish_cost2: Advanced!$B$19
Name revenue: Simple!$B$12
Name revenue2: 'Sensitivity Analysis'!$B$18
Name revenue2: Advanced!$B$18
Name rights: Simple!$B$7
Name rights2: 'Sensitivity Analysis'!$B$7
Name rights2: Advanced!$B$7
Name salary: Simple!$B$9
Name salary2: 'Sensitivity Analysis'!$B$8
Name salary2: Advanced!$B$8
Name total_cost: Simple!$B$14
Name total_cost2: 'Sensitivity Analysis'!$B$20
Name total_cost2: Advanced!$B$20

Sheet Introduction

Sheet Publication_Costs
B3: Publication Costs ($)
B4: Copies Ordered | C4: Cost per page | D4: Cost per Book | E4: Total Cost
B5: 1 | C5: 0.025 | D5: =C5*$C$12 -> 3.75
B6: 251 | C6: 0.0225 | D6: =C6*$C$12 -> 3.375
B7: 501 | C7: 0.0201 | D7: =C7*$C$12 -> 3.015
B8: 801 | C8: 0.018 | D8: =C8*$C$12 -> 2.7
B9: 1001 | C9: 0.0165 | D9: =C9*$C$12 -> 2.475
B10: 1501 | C10: 0.015 | D10: =C10*$C$12 -> 2.25
B12: Number of Pages | C12: 150

Sheet Cost vs. Demand
B1: Price | C1: Qty. Sold | H1: Price | I1: Qty. Sold
B2: =INT(RAND()*35 + 1) -> 4 | C2: =-140*B2+5000 -> 4440 | D2: =RAND() -> 0.89007518 | E2: =NORMINV(D2,0,144) -> 176.67764 | F2: =C2+E2 -> 4616.6776 | H2: 31 | I2: 623.02091
B3: =INT(RAND()*35 + 1) -> 11 | C3: =-140*B3+5000 -> 3460 | D3: =RAND() -> 0.71195194 | E3: =NORMINV(D3,0,144) -> 80.509841 | F3: =C3+E3 -> 3540.5098 | H3: 18 | I3: 2399.7164
B4: =INT(RAND()*35 + 1) -> 2 | C4: =-140*B4+5000 -> 4720 | D4: =RAND() -> 0.24051198 | E4: =NORMINV(D4,0,144) -> -101.47055 | F4: =C4+E4 -> 4618.5294 | H4: 15 | I4: 2866.4963 | K4: Regression Line:
B5: =INT(RAND()*35 + 1) -> 6 | C5: =-140*B5+5000 -> 4160 | D5: =RAND() -> 0.66240407 | E5: =NORMINV(D5,0,144) -> 60.340784 | F5: =C5+E5 -> 4220.3408 | H5: 23 | I5: 2013.8197 | K5: Slope: | L5: =SLOPE(I2:I31,H2:H31) -> -141.23077
B6: =INT(RAND()*35 + 1) -> 15 | C6: =-140*B6+5000 -> 2900 | D6: =RAND() -> 0.8563741 | E6: =NORMINV(D6,0,144) -> 153.24045 | F6: =C6+E6 -> 3053.2404 | H6: 14 | I6: 3172.0651 | K6: Intercept: | L6: =INTERCEPT(I2:I31,H2:H31) -> 5025.9947
B7: =INT(RAND()*35 + 1) -> 26 | C7: =-140*B7+5000 -> 1360 | D7: =RAND() -> 0.8926796 | E7: =NORMINV(D7,0,144) -> 178.69034 | F7: =C7+E7 -> 1538.6903 | H7: 34 | I7: 156.32028
B8: =INT(RAND()*35 + 1) -> 26 | C8: =-140*B8+5000 -> 1360 | D8: =RAND() -> 0.05905198 | E8: =NORMINV(D8,0,144) -> -225.04056 | F8: =C8+E8 -> 1134.9594 | H8: 27 | I8: 1037.1128
B9: =INT(RAND()*35 + 1) -> 27 | C9: =-140*B9+5000 -> 1220 | D9: =RAND() -> 0.84236032 | E9: =NORMINV(D9,0,144) -> 144.60565 | F9: =C9+E9 -> 1364.6057 | H9: 34 | I9: 348.76092
B10: =INT(RAND()*35 + 1) -> 32 | C10: =-140*B10+5000 -> 520 | D10: =RAND() -> 0.8226283 | E10: =NORMINV(D10,0,144) -> 133.26161 | F10: =C10+E10 -> 653.26161 | H10: 28 | I10: 1066.4572
B11: =INT(RAND()*35 + 1) -> 21 | C11: =-140*B11+5000 -> 2060 | D11: =RAND() -> 0.10821743 | E11: =NORMINV(D11,0,144) -> -177.99319 | F11: =C11+E11 -> 1882.0068 | H11: 18 | I11: 2650.4336
B12: =INT(RAND()*35 + 1) -> 8 | C12: =-140*B12+5000 -> 3880 | D12: =RAND() -> 0.11257272 | E12: =NORMINV(D12,0,144) -> -174.66611 | F12: =C12+E12 -> 3705.3339 | H12: 34 | I12: 247.21286
B13: =INT(RAND()*35 + 1) -> 25 | C13: =-140*B13+5000 -> 1500 | D13: =RAND() -> 0.31057639 | E13: =NORMINV(D13,0,144) -> -71.167278 | F13: =C13+E13 -> 1428.8327 | H13: 28 | I13: 1128.6062
B14: =INT(RAND()*35 + 1) -> 33 | C14: =-140*B14+5000 -> 380 | D14: =RAND() -> 0.21160801 | E14: =NORMINV(D14,0,144) -> -115.32301 | F14: =C14+E14 -> 264.67699 | H14: 20 | I14: 2129.0506
B15: =INT(RAND()*35 + 1) -> 5 | C15: =-140*B15+5000 -> 4300 | D15: =RAND() -> 0.23002121 | E15: =NORMINV(D15,0,144) -> -106.38389 | F15: =C15+E15 -> 4193.6161 | H15: 31 | I15: 614.16327
B16: =INT(RAND()*35 + 1) -> 15 | C16: =-140*B16+5000 -> 2900 | D16: =RAND() -> 0.54001264 | E16: =NORMINV(D16,0,144) -> 14.467042 | F16: =C16+E16 -> 2914.467 | H16: 8 | I16: 3984.0895
B17: =INT(RAND()*35 + 1) -> 32 | C17: =-140*B17+5000 -> 520 | D17: =RAND() -> 0.32854188 | E17: =NORMINV(D17,0,144) -> -63.9278 | F17: =C17+E17 -> 456.0722 | H17: 8 | I17: 4056.4535
B18: =INT(RAND()*35 + 1) -> 21 | C18: =-140*B18+5000 -> 2060 | D18: =RAND() -> 0.016559436 | E18: =NORMINV(D18,0,144) -> -306.81206 | F18: =C18+E18 -> 1753.1879 | H18: 24 | I18: 1424.4024
... B31: =INT(RAND()*35 + 1) -> 4 | C31: =-140*B31+5000 -> 4440 | D31: =RAND() -> 0.14784306 | E31: =NORMINV(D31,0,144) -> -150.58499 | F31: =C31+E31 -> 4289.415 | H31: 19 | I31: 2211.9465

Sheet Simple
A1: Simple Model
A3: Decision Variables | C3: Names
A4: Book Price ($) | B4: 50 | C4: book_price
A6: Parameters
A7: Author's rights | B7: 0.25 | C7: rights
A8: Books Sold | B8: 1000 | C8: books_sold
A9: Internship Salary ($) | B9: 5000 | C9: salary
A11: Financial Results ($)
A12: Revenue | B12: =book_price*books_sold*rights -> 12500 | C12: revenue
A13: Publishing Cost | B13: =VLOOKUP(books_sold,Publication_Costs!B5:D10,3)*books_sold -> 2700 | C13: publish_cost
A14: Total Cost | B14: =publish_cost+salary -> 7700 | C14: total_cost
A15: Profit | B15: =revenue-total_cost -> 4800 | C15: profit
A17: Recommendation | B17: =IF(profit>0,"Write the book!","Do the internship") -> Write the book!

Sheet Advanced
A1: Advanced Model
A3: Decision Variables | C3: Names
A4: Book Price ($) | B4: 20 | C4: book_price2
A6: Parameters
A7: Author's rights | B7: 0.25 | C7: rights2
A8: Internship Salary ($) | B8: 5000 | C8: salary2
A9: Equation Coefficients
A10: Books Demand Equation
A11: Intercept | B11: ='Cost vs. Demand'!L6 -> 5025.9947 | C11: demand_intercept
A12: Slope (Linear Coefficient) | B12: ='Cost vs. Demand'!L5 -> -141.23077 | C12: demand_slope
A14: Physical Results | C14: =IF(books_sold2<0,"Book Price too high!","")
A15: Books Sold | B15: =book_price2*demand_slope+demand_intercept -> 2201.3794 | C15: books_sold2
A17: Financial Results ($)
A18: Revenue | B18: =books_sold2*book_price2*rights2 -> 11006.897 | C18: revenue2
A19: Publishing Cost | B19: =VLOOKUP(books_sold2,Publication_Costs!B5:D10,3)*books_sold2 -> 4953.1035 | C19: publish_cost2
A20: Total Cost | B20: =publish_cost2+salary2 -> 9953.1035 | C20: total_cost2 | E20: 10 | F20: 15 | G20: 20 | H20: 25 | I20: 30 | J20: 35
A21: Profit | B21: =revenue2-total_cost2 -> 1053.7932 | C21: profit2 | D21: =profit2 -> 1053.7932 | E21: -4096.5782 | F21: -638.70022 | G21: 1053.7932 | H21: 644.47634 | I21: -1461.0135 | J21: -4585.4107
A23: Recommendation | B23: =IF(profit2>0,"Write the book!","Do the internship") -> Write the book!
D25: =profit2 -> 1053.7932 | E25: 10 | F25: 15 | G25: 20 | H25: 25 | I25: 30 | J25: 35
D26: 0.1 | E26: -9517.1088 | F26: -7180.6499 | G26: -5550.3448 | H26: -4962.6194 | I26: -5011.8361 | J26: -5020.7295
D27: 0.2 | E27: -5903.4218 | F27: -2819.3501 | G27: -1147.5861 | H27: -1224.5556 | I27: -2644.621 | J27: -4730.517
D28: 0.25 | E28: -4096.5782 | F28: -638.70022 | G28: 1053.7932 | H28: 644.47634 | I28: -1461.0135 | J28: -4585.4107
D29: 0.4 | E29: 1323.9523 | F29: 5903.2495 | G29: 7657.9313 | H29: 6251.572 | I29: 2089.8091 | J29: -4150.092
D30: 0.5 | E30: 4937.6393 | F30: 10264.549 | G30: 12060.69 | H30: 9989.6358 | I30: 4457.0242 | J30: -3859.8795

Sheet Sensitivity Analysis
A1: Advanced Model
A3: Decision Variables | C3: Names
A4: Book Price ($) | B4: 20 | C4: book_price2
A6: Parameters
A7: Author's rights | B7: 0.25 | C7: rights2 | G7: Price
A8: Internship Salary ($) | B8: 5000 | C8: salary2 | F8: Profit | G8: 10 | H8: 15 | I8: 20 | J8: 25 | K8: 30 | L8: 35 | M8: 40
A9: Equation Coefficients
A10: Books Demand Equation
A11: Intercept | B11: ='Cost vs. Demand'!L6 -> 5025.9947 | C11: demand_intercept
A12: Slope (Linear Coefficient) | B12: ='Cost vs. Demand'!L5 -> -141.23077 | C12: demand_slope
A14: Physical Results | C14: =IF(books_sold2<0,"Book Price too high!","")
A15: Books Sold | B15: =book_price2*demand_slope+demand_intercept -> 2201.3794 | C15: books_sold2
A17: Financial Results ($)
A18: Revenue | B18: =books_sold2*book_price2*rights2 -> 11006.897 | C18: revenue2
A19: Publishing Cost | B19: =VLOOKUP(books_sold2,A37:C42,3)*books_sold2 -> 4953.1035 | C19: publish_cost2
A20: Total Cost | B20: =publish_cost2+salary2 -> 9953.1035 | C20: total_cost2 | G20: Price
A21: Profit | B21: =revenue2-total_cost2 -> 1053.7932 | C21: profit2 | E21: Profit | G21: 10 | H21: 15 | I21: 20 | J21: 25 | K21: 30 | L21: 35 | M21: 40
E22: Rights | F22: 0.1
A23: Recommendation | B23: =IF(profit2>0,"Write the book!","Do the internship") -> Write the book! | F23: 0.15
F24: 0.2
F25: 0.25
F26: 0.3
F27: 0.35
F28: 0.4
F29: 0.45
A35: Publication Costs ($)
A36: Copies Ordered | B36: Cost per page | C36: Cost per Book
A37: 1 | B37: 0.025 | C37: =B37*$B$44 -> 3.75
A38: 251 | B38: 0.0225 | C38: =B38*$B$44 -> 3.375
A39: 501 | B39: 0.0201 | C39: =B39*$B$44 -> 3.015
A40: 801 | B40: 0.018 | C40: =B40*$B$44 -> 2.7
A41: 1001 | B41: 0.0165 | C41: =B41*$B$44 -> 2.475 | G41: Baseline | H41: AllUp | I41: AllDown | J41: UpMore | K41: DownMore
A42: 1501 | B42: 0.015 | C42: =B42*$B$44 -> 2.25 | E42: book_price2 | G42: 20 | H42: 25 | I42: 15 | J42: 30 | K42: 15
E43: rights2 | G43: 25 | H43: 30 | I43: 20 | J43: 30 | K43: 20
A44: Number of Pages | B44: 150 | E44: num_pages | G44: 150 | H44: 200 | I44: 100 | J44: 200 | K44: 50
