Workbook

Sheet Instructions
A2: Dear Esteemed Clients,
B4: Thank you for your interest in obtaining the MSC status for your company. We will assist you in preparing
B5: the financial projection for the application.
B7: Should you need any assistance in preparing this financial projection, our contact are as follow
B9: Mohd. Zaffri Basir | D9: 03-8315 3171 | F9: zaffri@mdc.com.my
B10: Yong Chi Kin | D10: 03-8315 3178 | F10: chikin@mdc.com.my
B12: Kindly key-in the applying company's name below in the yellow-coloured cell below.
A16: Please proceed with the instructions below. Thank you.
A19: Instructions to complete the Financial Templates
A21: 1 | C21: Please fill-in all the "yellow" coloured cells in the following sheets:-
C22: a. Financial Summary
C23: b. P&L
C24: c. BS
C25: d. CFS
C26: e. Notes 2
C28: *Please do not fill-in the auto-linked "light green" coloured cells.
A31: 2 | C31: Please do not add or remove any row to/from the financial templates (5 sheets mentioned above in note 1) as this will affect the other tabs, which will result in failure to process the application accordingly. However, you are allowed to change the description/s of the expenses to be more reflective on your business actvities.
A33: 3 | C33: Please put "0" to item/s which is/are not applicable to your company.
A35: 4 | C35: Please state all the assumptions and important calculations used in the projections in "Notes" tab.
A37: 5 | B37: Table F2 | C37: Table F2: Breakdown of Revenue - The table is to show the source of revenue generation for the company. The revenue stream/s should be the same as the company's proposed MSC activities described in the business plan. Further working calculation of the revenue streams are necessary and kindly provide the workings in "Notes" tab.
A39: 6 | B39: Table F3 | C39: Table F3: R&D expenses - Please note that the underlying assumption used on the treatment of these expenses is such that the Hardware and Software acquisition for the purpose of Research and Development works will be capitalised in the Balance Sheet and subsequently amortised every year. The other R&D expenses as stipulated in Table F3 will be written-off completely in the Profit and Loss during the year they incurred.
A41: 7 | B41: Table F4 | C41: Table F4: Past Financial Performance - For the company that has been in operation for more than 1 year, please provide us with the audited Sales and the Profit before Tax figures.
A42: 8 | C42: Throughout this template, additional information / instruction can be found in the cell marked with the red triangle on the top righthand corner.
A43: 9 | C43: The coloured item contains hyperlink to different relevant section of the financial projection.
A44: 10 | C44: For easy printing of all the pages, press "Ctrl" + "Shift" simultaneously and and without releasing it, click on the sheet/tab you want to print. Then, click on "Print".
A47: Glossary of financial terms used in MSC status application
A49: 1. Sales are defined as proceeds which is derived from the provision of goods and/or services falling
A50: within the company's qualified MSC activities.
A51: Sales are further classified as Local ( all forms of revenue in Malaysia) and/or Export (all forms of
A52: revenue from overseas )
A54: 2. Net profit (loss) before tax is defined as profit or loss on qualified MSC activities before taxation.
A56: 3. Net Operating cash flow is defined as the net amounts of cash flowing in and out of business during
A57: the prescribed period to support the qualified MSC activities.
A58: { Formula : Net operating cash flow = Total cash inflow - Total cash outflow }
A60: 4. Liquid Assets is defined as cash or bank balance and is a component of Current Assets.
A62: 5. Stocks is defined as the goods and materials a company purchases to re-sell at a profit for the
A63: company's qualified MSC activities. It is a component of Current Assets.
... A111: Share Capital, Share Premium Account, Capital Reserves, Reserves and Retained Earnings.

Sheet Assessment Report
A2: =ProfitLoss!A2 -> Co. name: | B2: =ProfitLoss!B2 -> 0
A4: F1 : FINANCIAL PROJECTIONS
A6: Year | B6: ='Notes 2'!C5 -> 2002 | C6: =B6+1 -> 2003 | D6: =C6+1 -> 2004
A7: Sales (Local) | B7: ='Financial Summary'!B7 -> 10 | C7: ='Financial Summary'!C7 -> 40 | D7: ='Financial Summary'!D7 -> 90
A8: Sales (Exports) | B8: ='Financial Summary'!B8 -> 90 | C8: ='Financial Summary'!C8 -> 160 | D8: ='Financial Summary'!D8 -> 210
A9: Total Sales | B9: ='Financial Summary'!B9 -> 100 | C9: ='Financial Summary'!C9 -> 200 | D9: ='Financial Summary'!D9 -> 300
A10: Net profit (loss) before tax | B10: ='Financial Summary'!B10 -> 3264.5 | C10: ='Financial Summary'!C10 -> 5788.5111 | D10: ='Financial Summary'!D10 -> 25815.385
A11: Net operating cash flow | B11: ='Financial Summary'!B11 -> 45 | C11: ='Financial Summary'!C11 -> 151.66667 | D11: ='Financial Summary'!D11 -> 236.33333
A12: Assets | B12: ='Financial Summary'!B15+'Financial Summary'!B16 -> 9878.5 | C12: ='Financial Summary'!C15+'Financial Summary'!C16 -> 14829.9 | D12: ='Financial Summary'!D15+'Financial Summary'!D16 -> 34719.1
A13: Liabilities | B13: ='Financial Summary'!B17+'Financial Summary'!B18 -> 6687.6667 | C13: ='Financial Summary'!C17+'Financial Summary'!C18 -> 5855.3333 | D13: ='Financial Summary'!D17+'Financial Summary'!D18 -> 23
A14: Paid-up-Capital | B14: =BS!B44 -> 50 | C14: =BS!C44 -> 50 | D14: =BS!D44 -> 50
A15: R&D Investment ( at cost) | B15: =B88 -> 70 | C15: =C88 -> 140 | D15: =D88 -> 210
A16: Networth ( cumulative ) | B16: =BS!B53 -> 9999.1667 | C16: =BS!C53 -> 14952.344 | D16: =BS!D53 -> 34932.396
A18: F2 : Breakdown of Sales
A20: Item * | B20: =B6 -> 2002 | C20: =C6 -> 2003 | D20: =D6 -> 2004
A21: ='Financial Summary'!A26 -> Content Edition/Enhancement | B21: ='Financial Summary'!B26 -> 0 | C21: ='Financial Summary'!C26 -> 0 | D21: ='Financial Summary'!D26 -> 0
A22: ='Financial Summary'!A27 -> Interractive Services | B22: ='Financial Summary'!B27 -> 0 | C22: ='Financial Summary'!C27 -> 0 | D22: ='Financial Summary'!D27 -> 0
A23: ='Financial Summary'!A28 -> E-Commerce | B23: ='Financial Summary'!B28 -> 100 | C23: ='Financial Summary'!C28 -> 200 | D23: ='Financial Summary'!D28 -> 300
A24: ='Financial Summary'!A29 -> Software Integration | B24: ='Financial Summary'!B29 -> 0 | C24: ='Financial Summary'!C29 -> 0 | D24: ='Financial Summary'!D29 -> 0
A25: ='Financial Summary'!A30 -> Website Development Income | B25: ='Financial Summary'!B30 -> 0 | C25: ='Financial Summary'!C30 -> 0 | D25: ='Financial Summary'!D30 -> 0
A26: ='Financial Summary'!A31 -> Hosting Fees | B26: ='Financial Summary'!B31 -> 0 | C26: ='Financial Summary'!C31 -> 0 | D26: ='Financial Summary'!D31 -> 0
A27: ='Financial Summary'!A32 -> i-directory listing | B27: ='Financial Summary'!B32 -> 0 | C27: ='Financial Summary'!C32 -> 0 | D27: ='Financial Summary'!D32 -> 0
A28: ='Financial Summary'!A33 -> Sale of Portals | B28: ='Financial Summary'!B33 -> 0 | C28: ='Financial Summary'!C33 -> 0 | D28: ='Financial Summary'!D33 -> 0
A29: ='Financial Summary'!A34 -> Fulfillment charges | B29: ='Financial Summary'!B34 -> 0 | C29: ='Financial Summary'!C34 -> 0 | D29: ='Financial Summary'!D34 -> 0
A30: ='Financial Summary'!A35 -> Licensing | B30: ='Financial Summary'!B35 -> 0 | C30: ='Financial Summary'!C35 -> 0 | D30: ='Financial Summary'!D35 -> 0
A31: ='Financial Summary'!A36 -> Subscription | B31: ='Financial Summary'!B36 -> 0 | C31: ='Financial Summary'!C36 -> 0 | D31: ='Financial Summary'!D36 -> 0
A32: ='Financial Summary'!A37 -> Transaction Fee | B32: ='Financial Summary'!B37 -> 0 | C32: ='Financial Summary'!C37 -> 0 | D32: ='Financial Summary'!D37 -> 0
... A38: ='Financial Summary'!A43 -> Others :- | B38: ='Financial Summary'!B43 -> 0 | C38: ='Financial Summary'!C43 -> 0 | D38: ='Financial Summary'!D43 -> 0
A39: Total | B39: =SUM(B21:B38) -> 100 | C39: =SUM(C21:C38) -> 200 | D39: =SUM(D21:D38) -> 300
A42: F3 : Breakdown of Research & Development
A44: Item * | B44: =B20 -> 2002 | C44: =C20 -> 2003 | D44: =D20 -> 2004
A45: R&D staff salaries **
A46: ='Financial Summary'!A51 -> --R&D Electronic Engineers | B46: ='Financial Summary'!B51 -> 0 | C46: ='Financial Summary'!C51 -> 0 | D46: ='Financial Summary'!D51 -> 0
A47: ='Financial Summary'!A52 -> --R&D Embedded Software Engineers | B47: ='Financial Summary'!B52 -> 0 | C47: ='Financial Summary'!C52 -> 0 | D47: ='Financial Summary'!D52 -> 0
A48: ='Financial Summary'!A53 -> --R&D Software Engineer | B48: ='Financial Summary'!B53 -> 0 | C48: ='Financial Summary'!C53 -> 0 | D48: ='Financial Summary'!D53 -> 0
A49: ='Financial Summary'!A54 -> --R&D Quality & Security Engineer | B49: ='Financial Summary'!B54 -> 0 | C49: ='Financial Summary'!C54 -> 0 | D49: ='Financial Summary'!D54 -> 0
A50: ='Financial Summary'!A55 -> --Chief Designer | B50: ='Financial Summary'!B55 -> 0 | C50: ='Financial Summary'!C55 -> 0 | D50: ='Financial Summary'!D55 -> 0
A51: ='Financial Summary'!A56 -> --Web Designer | B51: ='Financial Summary'!B56 -> 10 | C51: ='Financial Summary'!C56 -> 20 | D51: ='Financial Summary'!D56 -> 30
A52: ='Financial Summary'!A57 -> --Web Engineer | B52: ='Financial Summary'!B57 -> 0 | C52: ='Financial Summary'!C57 -> 0 | D52: ='Financial Summary'!D57 -> 0
A53: ='Financial Summary'!A58 -> --Linguists | B53: ='Financial Summary'!B58 -> 0 | C53: ='Financial Summary'!C58 -> 0 | D53: ='Financial Summary'!D58 -> 0
A54: ='Financial Summary'!A59 -> --Language Translators | B54: ='Financial Summary'!B59 -> 0 | C54: ='Financial Summary'!C59 -> 0 | D54: ='Financial Summary'!D59 -> 0
A55: ='Financial Summary'!A60 -> --Content Developers | B55: ='Financial Summary'!B60 -> 0 | C55: ='Financial Summary'!C60 -> 0 | D55: ='Financial Summary'!D60 -> 0
A56: ='Financial Summary'!A61 -> --Others:-(please specify) | B56: ='Financial Summary'!B61 -> 0 | C56: ='Financial Summary'!C61 -> 0 | D56: ='Financial Summary'!D61 -> 0
A57: Sub-total | B57: =SUM(B46:B56) -> 10 | C57: =SUM(C46:C56) -> 20 | D57: =SUM(D46:D56) -> 30
B58: =B57/B88 -> 0.14285714 | C58: =C57/C88 -> 0.14285714 | D58: =D57/D88 -> 0.14285714
A59: Technology acquisitions - Hardware
A60: ='Financial Summary'!A64 -> --Computer Servers | B60: ='Financial Summary'!B64 -> 0 | C60: ='Financial Summary'!C64 -> 0 | D60: ='Financial Summary'!D64 -> 0
A61: ='Financial Summary'!A65 -> --Personal Computers | B61: ='Financial Summary'!B65 -> 0 | C61: ='Financial Summary'!C65 -> 0 | D61: ='Financial Summary'!D65 -> 0
A62: ='Financial Summary'!A66 -> --ISDN Lines Connection | B62: ='Financial Summary'!B66 -> 10 | C62: ='Financial Summary'!C66 -> 20 | D62: ='Financial Summary'!D66 -> 30
A63: ='Financial Summary'!A67 -> --Workstations Hardware & Accessories | B63: ='Financial Summary'!B67 -> 0 | C63: ='Financial Summary'!C67 -> 0 | D63: ='Financial Summary'!D67 -> 0
A64: ='Financial Summary'!A68 -> --Furniture & Fittings | B64: ='Financial Summary'!B68 -> 0 | C64: ='Financial Summary'!C68 -> 0 | D64: ='Financial Summary'!D68 -> 0
A65: ='Financial Summary'!A69 -> --Others:-(please specify) | B65: ='Financial Summary'!B69 -> 0 | C65: ='Financial Summary'!C69 -> 0 | D65: ='Financial Summary'!D69 -> 0
A66: Sub-total | B66: =SUM(B60:B65) -> 10 | C66: =SUM(C60:C65) -> 20 | D66: =SUM(D60:D65) -> 30
B67: =B66/B88 -> 0.14285714 | C67: =C66/C88 -> 0.14285714 | D67: =D66/D88 -> 0.14285714
A68: Technology acquisitions - Software
A69: ='Financial Summary'!A72 -> --Software Licencing for Windows NT | B69: ='Financial Summary'!B72 -> 0 | C69: ='Financial Summary'!C72 -> 0 | D69: ='Financial Summary'!D72 -> 0
A70: ='Financial Summary'!A73 -> --Software for Hardware Development | B70: ='Financial Summary'!B73 -> 10 | C70: ='Financial Summary'!C73 -> 20 | D70: ='Financial Summary'!D73 -> 30
A71: ='Financial Summary'!A74 -> --Design Tools | B71: ='Financial Summary'!B74 -> 0 | C71: ='Financial Summary'!C74 -> 0 | D71: ='Financial Summary'!D74 -> 0
A72: ='Financial Summary'!A75 -> --Others:-(please specify) | B72: ='Financial Summary'!B75 -> 0 | C72: ='Financial Summary'!C75 -> 0 | D72: ='Financial Summary'!D75 -> 0
A73: Sub-total | B73: =SUM(B69:B72) -> 10 | C73: =SUM(C69:C72) -> 20 | D73: =SUM(D69:D72) -> 30
B74: =B73/B88 -> 0.14285714 | C74: =C73/C88 -> 0.14285714 | D74: =D73/D88 -> 0.14285714
A75: Prototypes
A76: ='Financial Summary'!A78 -> --Content & Design Fee | B76: ='Financial Summary'!B78 -> 0 | C76: ='Financial Summary'!C78 -> 0 | D76: ='Financial Summary'!D78 -> 0
A77: ='Financial Summary'!A79 -> --Mould Making | B77: ='Financial Summary'!B79 -> 0 | C77: ='Financial Summary'!C79 -> 0 | D77: ='Financial Summary'!D79 -> 0
A78: ='Financial Summary'!A80 -> --Prototyping Costs | B78: ='Financial Summary'!B80 -> 10 | C78: ='Financial Summary'!C80 -> 20 | D78: ='Financial Summary'!D80 -> 30
A79: ='Financial Summary'!A81 -> --Others:-(please specify) | B79: ='Financial Summary'!B81 -> 0 | C79: ='Financial Summary'!C81 -> 0 | D79: ='Financial Summary'!D81 -> 0
A80: Sub-total | B80: =SUM(B76:B79) -> 10 | C80: =SUM(C76:C79) -> 20 | D80: =SUM(D76:D79) -> 30
B81: =B80/B88 -> 0.14285714 | C81: =C80/C88 -> 0.14285714 | D81: =D80/D88 -> 0.14285714
A82: Consumables / Incidental Costs | B82: ='Financial Summary'!B83 -> 10 | C82: ='Financial Summary'!C83 -> 20 | D82: ='Financial Summary'!D83 -> 30
B83: =B82/B88 -> 0.14285714 | C83: =C82/C88 -> 0.14285714 | D83: =D82/D88 -> 0.14285714
A84: Patenting & Copyrights | B84: ='Financial Summary'!B84 -> 10 | C84: ='Financial Summary'!C84 -> 20 | D84: ='Financial Summary'!D84 -> 30
B85: =B84/B88 -> 0.14285714 | C85: =C84/C88 -> 0.14285714 | D85: =D84/D88 -> 0.14285714
A86: Others:-(please specify) | B86: ='Financial Summary'!B85 -> 10 | C86: ='Financial Summary'!C85 -> 20 | D86: ='Financial Summary'!D85 -> 30
B87: =B86/B88 -> 0.14285714 | C87: =C86/C88 -> 0.14285714 | D87: =D86/D88 -> 0.14285714
A88: Grand Total | B88: =B57+B66+B73+B80+B82+B84+B86 -> 70 | C88: =C57+C66+C73+C80+C82+C84+C86 -> 140 | D88: =D57+D66+D73+D80+D82+D84+D86 -> 210
A90: F4 : PAST PERFORMANCE
A92: Past Perfomance | B92: ='Financial Summary'!B93 -> 1999 | C92: ='Financial Summary'!C93 -> 2000 | D92: ='Financial Summary'!D93 -> 2001
A93: Sales | B93: ='Financial Summary'!B94 -> 0 | C93: ='Financial Summary'!C94 -> 0 | D93: ='Financial Summary'!D94 -> 0
A95: Profit/Loss before tax | B95: ='Financial Summary'!B96 -> 0 | C95: ='Financial Summary'!C96 -> 0 | D95: ='Financial Summary'!D96 -> 0
A99: 3 Year Ruling - Threshold is set at RM | B99: =SUM(B95:D95)/'Financial Summary'!B92 -> #DIV/0!
A101: Total Sales | D101: =Notes!F52 -> 600
A102: Total R&D | D102: =Notes!F53 -> 420
A103: Percentage of R&D over Sales | D103: =Notes!F54 -> 0.7
A104: Tax Loss | D104: =Notes!F55 -> 124529.99
A105: OpEx | D105: =Notes!F56 -> 120
A106: CapEx | D106: =Notes!F57 -> 206.66667
A107: Total Export | D107: =Notes!F58 -> 460
A109: RATIO ANALYSIS | B109: ='Financial Summary'!B110 -> 2002 | C109: ='Financial Summary'!C110 -> 2003 | D109: ='Financial Summary'!D110 -> 2004
A111: Profitibility:
A112: Gross profit | B112: ='Financial Summary'!B113 -> 1 | C112: ='Financial Summary'!C113 -> 1 | D112: ='Financial Summary'!D113 -> 1
A113: Net profit | B113: ='Financial Summary'!B114 -> 32.645 | C113: ='Financial Summary'!C114 -> 28.942556 | D113: ='Financial Summary'!D114 -> 86.051284
A114: Return on capital employed | B114: ='Financial Summary'!B115 -> 0.33576131 | C114: ='Financial Summary'!C115 -> 0.39574619 | D114: ='Financial Summary'!D115 -> 0.74330238
A115: Asset turnover (times) | B115: ='Financial Summary'!B116 -> 0.010000833 | C115: ='Financial Summary'!C116 -> 0.013375829 | D115: ='Financial Summary'!D116 -> 0.0085880166
A117: Liquidity:
A118: Current ratio ( xx : 1) | B118: ='Financial Summary'!B119 -> 9461.8333 | C118: ='Financial Summary'!C119 -> 7256.6167 | D118: ='Financial Summary'!D119 -> 11500.811
A119: Quick ratio/Acid test ratio ( xx : 1) | B119: ='Financial Summary'!B120 -> 9461.8333 | C119: ='Financial Summary'!C120 -> 7256.6167 | D119: ='Financial Summary'!D120 -> 11500.811
A121: Financing:
A122: Gearing ratio ( xx : 1) | B122: ='Financial Summary'!B123 -> 2.0186164 | C122: ='Financial Summary'!C123 -> 0.64329335 | D122: ='Financial Summary'!D123 -> 0.00057286242
A123: Interest cover ( times) | B123: ='Financial Summary'!B124 -> 2799.1429 | C123: ='Financial Summary'!C124 -> 3618.8194 | D123: ='Financial Summary'!D124 -> 14342.881
A125: Investment:
...

Sheet Financial Summary
A1: Back To Instructions
A2: =ProfitLoss!A2 -> Co. name: | B2: =ProfitLoss!B2 -> 0
A4: F1 : FINANCIAL PROJECTIONS (RM)
A6: Year | B6: ='Notes 2'!C5 -> 2002 | C6: =B6+1 -> 2003 | D6: =C6+1 -> 2004
A7: Sales (Local) | B7: ='Notes 2'!$C$7*B9 -> 10 | C7: ='Notes 2'!$D$7*C9 -> 40 | D7: ='Notes 2'!$E$7*D9 -> 90
A8: Sales (Exports) | B8: =B9*'Notes 2'!$C$8 -> 90 | C8: =C9*'Notes 2'!$D$8 -> 160 | D8: =D9*'Notes 2'!$E$8 -> 210
A9: Total Sales | B9: =B44 -> 100 | C9: =C44 -> 200 | D9: =D44 -> 300
A10: Net profit (loss) before tax | B10: =ProfitLoss!B50 -> 3264.5 | C10: =ProfitLoss!C50 -> 5788.5111 | D10: =ProfitLoss!D50 -> 25815.385
A11: Net operating cash flow | B11: =CFS!B12 -> 45 | C11: =CFS!C12 -> 151.66667 | D11: =CFS!D12 -> 236.33333
A12: Liquid Assets | B12: =CFS!B32 -> 9441.8333 | C12: =CFS!C32 -> 14479.9 | D12: =CFS!D32 -> 34452.433
A13: Stocks ( Inventory) | B13: =BS!B29 -> 0 | C13: =BS!C29 -> 0 | D13: =BS!D29 -> 0
A14: Trade Debtors | B14: =BS!B26 -> 20 | C14: =BS!C26 -> 33.333333 | D14: =BS!D26 -> 50
A15: Current Assets | B15: =BS!B30 -> 9461.8333 | C15: =BS!C30 -> 14513.233 | D15: =BS!D30 -> 34502.433
A16: Fixed Assets (net) | B16: =BS!B23 -> 416.66667 | C16: =BS!C23 -> 316.66667 | D16: =BS!D23 -> 216.66667
A17: Current Liablities | B17: =BS!B37 -> 1 | C17: =BS!C37 -> 2 | D17: =BS!D37 -> 3
A18: Long-Term Liabilities | B18: =BS!B49+BS!B51 -> 6686.6667 | C18: =BS!C49+BS!C51 -> 5853.3333 | D18: =BS!D49+BS!D51 -> 20
A19: Paid-up-Capital | B19: =BS!B44 -> 50 | C19: =BS!C44 -> 50 | D19: =BS!D44 -> 50
A20: R&D Investment ( at cost) | B20: =B86 -> 70 | C20: =C86 -> 140 | D20: =D86 -> 210
A21: Networth ( cumulative ) | B21: =BS!B53 -> 9999.1667 | C21: =BS!C53 -> 14952.344 | D21: =BS!D53 -> 34932.396
A23: F2 : Breakdown of Sales (RM) | B23: Back to | C23: Intro | D23: ProfitLoss
A25: Item * | B25: =B6 -> 2002 | C25: =C6 -> 2003 | D25: =D6 -> 2004
A26: Content Edition/Enhancement
A27: Interractive Services
A28: E-Commerce | B28: 100 | C28: 200 | D28: 300
A29: Software Integration
A30: Website Development Income
A31: Hosting Fees
A32: i-directory listing
A33: Sale of Portals
A34: Fulfillment charges
A35: Licensing
A36: Subscription
A37: Transaction Fee
A38: Advertisement
A39: Data Centre Management
A40: Call Centre Management
... A43: Others :-
A44: Total | B44: =SUM(B26:B43) -> 100 | C44: =SUM(C26:C43) -> 200 | D44: =SUM(D26:D43) -> 300
A47: F3 : Breakdown of Research & Development (RM) | B47: Back to | C47: Intro | D47: Balance Sheet
A49: Item * | B49: =B25 -> 2002 | C49: =C25 -> 2003 | D49: =D25 -> 2004
A50: R&D staff salaries **
A51: --R&D Electronic Engineers
A52: --R&D Embedded Software Engineers
A53: --R&D Software Engineer
A54: --R&D Quality & Security Engineer
A55: --Chief Designer
A56: --Web Designer | B56: 10 | C56: 20 | D56: 30
A57: --Web Engineer
A58: --Linguists
A59: --Language Translators
A60: --Content Developers
A61: --Others:-(please specify)
A62: Sub-total | B62: =SUM(B51:B61) -> 10 | C62: =SUM(C51:C61) -> 20 | D62: =SUM(D51:D61) -> 30
A63: Technology acquisitions - Hardware
A64: --Computer Servers
A65: --Personal Computers
A66: --ISDN Lines Connection | B66: 10 | C66: 20 | D66: 30
A67: --Workstations Hardware & Accessories
A68: --Furniture & Fittings
A69: --Others:-(please specify)
A70: Sub-total | B70: =SUM(B64:B69) -> 10 | C70: =SUM(C64:C69) -> 20 | D70: =SUM(D64:D69) -> 30
A71: Technology acquisitions - Software
A72: --Software Licencing for Windows NT
A73: --Software for Hardware Development | B73: 10 | C73: 20 | D73: 30
A74: --Design Tools
A75: --Others:-(please specify)
A76: Sub-total | B76: =SUM(B72:B75) -> 10 | C76: =SUM(C72:C75) -> 20 | D76: =SUM(D72:D75) -> 30
A77: Prototypes
A78: --Content & Design Fee
A79: --Mould Making
A80: --Prototyping Costs | B80: 10 | C80: 20 | D80: 30
A81: --Others:-(please specify)
A82: Sub-total | B82: =SUM(B78:B81) -> 10 | C82: =SUM(C78:C81) -> 20 | D82: =SUM(D78:D81) -> 30
A83: Consumables / Incidental Costs | B83: 10 | C83: 20 | D83: 30
A84: Patenting & Copyrights | B84: 10 | C84: 20 | D84: 30
A85: Others:-(please specify) | B85: 10 | C85: 20 | D85: 30
A86: Grand Total | B86: =B62+B70+B76+B82+B83+B84+B85 -> 70 | C86: =C62+C70+C76+C82+C83+C84+C85 -> 140 | D86: =D62+D70+D76+D82+D83+D84+D85 -> 210
A87: * Please adjust the items according to the nature of your business
A88: ** For R&D staff salaries, please indicate (PT) for part-time or (FT) full-time .
A91: F4 : PAST FINANCIAL PERFORMANCE | B91: Back To Instructions
A92: No. of Audited Financial Statement (max. of 3 years) | B92: 0
A93: Past Perfomance | B93: =C93-1 -> 1999 | C93: =D93-1 -> 2000 | D93: ='Notes 2'!C5-1 -> 2001
A94: Sales
A96: Profit/Loss before tax
A99: Please fill in the above with the past years audited financial figures wherever applicable.
A102: Total Sales | D102: =Notes!F52 -> 600
A103: Total R&D | D103: =Notes!F53 -> 420
A104: Percentage of R&D over Sales | D104: =Notes!F54 -> 0.7
A105: Tax Loss | D105: =Notes!F55 -> 124529.99
A106: OpEx | D106: =Notes!F56 -> 120
A107: CapEx | D107: =Notes!F57 -> 206.66667
A108: Total Export | D108: =Notes!F58 -> 460
A110: RATIO ANALYSIS | B110: ='Notes 2'!C5 -> 2002 | C110: ='Notes 2'!D5 -> 2003 | D110: ='Notes 2'!E5 -> 2004
A112: Profitibility:
A113: Gross profit | B113: =Notes!G7 -> 1 | C113: =Notes!H7 -> 1 | D113: =Notes!I7 -> 1
A114: Net profit | B114: =Notes!G10 -> 32.645 | C114: =Notes!H10 -> 28.942556 | D114: =Notes!I10 -> 86.051284
A115: Return on capital employed | B115: =Notes!G13 -> 0.33576131 | C115: =Notes!H13 -> 0.39574619 | D115: =Notes!I13 -> 0.74330238
A116: Asset turnover (times) | B116: =Notes!G16 -> 0.010000833 | C116: =Notes!H16 -> 0.013375829 | D116: =Notes!I16 -> 0.0085880166
A118: Liquidity:
A119: Current ratio ( xx : 1) | B119: =Notes!G22 -> 9461.8333 | C119: =Notes!H22 -> 7256.6167 | D119: =Notes!I22 -> 11500.811
...

Sheet ProfitLoss
A1: PROFIT AND LOSS ACCOUNT | D1: Back To Instructions
A2: Co. name: | B2: ='Notes 2'!C4 -> 0
B4: PROJECTIONS
B5: ='Notes 2'!C5 -> 2002 | C5: =B5+1 -> 2003 | D5: =C5+1 -> 2004
B6: RM | C6: RM | D6: RM
A8: SALES | B8: ='Financial Summary'!B44 -> 100 | C8: ='Financial Summary'!C44 -> 200 | D8: ='Financial Summary'!D44 -> 300
A10: less: COST OF SALES
A12: GROSS PROFIT | B12: =B8-B10 -> 100 | C12: =C8-C10 -> 200 | D12: =D8-D10 -> 300
A13: less:
A14: General & Administrative Expenses
A15: Professional fees
A16: Directors' remuneration
A17: Insurance | B17: 12 | C17: 24 | D17: 36
A18: Medical fee
A19: Rental of premises
A20: Salaries,allowances & bonus | B20: 12 | C20: 12 | D20: 12
A21: Utilities
A22: Upkeep of office
A23: R & D expenses | B23: ='Financial Summary'!B62+'Financial Summary'!B83+'Financial Summary'!B84+'Financial Summary'!B85 -> 40 | C23: ='Financial Summary'!C62+'Financial Summary'!C83+'Financial Summary'!C84+'Financial Summary'!C85 -> 80 | D23: ='Financial Summary'!D62+'Financial Summary'!D83+'Financial Summary'!D84+'Financial Summary'!D85 -> 120
A24: Others:-
A25: Others:-
A26: Others:-
A28: Total G&A | B28: =SUM(B15:B27) -> 64 | C28: =SUM(C15:C27) -> 116 | D28: =SUM(D15:D27) -> 168
A29: Sales & Marketing Expenses
A30: Advertisement
A31: Entertainment
A32: Printing and stationery
A33: Salaries and commissions | B33: 12
A34: Tender fee
A35: Travelling expenses
A36: Upkeep of motor vehicle
A37: Others:-
A38: Others:-
A39: Others:-
A41: Total S&M | B41: =SUM(B30:B40) -> 12 | C41: =SUM(C30:C40) -> 0 | D41: =SUM(D30:D40) -> 0
A42: Other Income | B42: ='Notes 2'!D87+'Notes 2'!D95+'Notes 2'!D103 -> 3333.3333 | C42: ='Notes 2'!E87+'Notes 2'!E95+'Notes 2'!E103 -> 5833.3333 | D42: ='Notes 2'!F87+'Notes 2'!F95+'Notes 2'!F103 -> 25833.333
A43: PBDIT | B43: =B12-B28-B41+B42 -> 3357.3333 | C43: =C12-C28-C41+C42 -> 5917.3333 | D43: =D12-D28-D41+D42 -> 25965.333
A44: less: Amortisation of R&D | B44: =BS!B10 -> 8.3333333 | C44: =BS!C10 -> 27.222222 | D44: =BS!D10 -> 48.148148
A45: Depreciation | B45: ='Notes 2'!D51 -> 83.333333 | C45: ='Notes 2'!E51 -> 100 | D45: ='Notes 2'!F51 -> 100
A47: PBIT | B47: =B43-B44-B45 -> 3265.6667 | C47: =C43-C44-C45 -> 5790.1111 | D47: =D43-D44-D45 -> 25817.185
A48: less: Financial Charges | B48: =CFS!B23*'Notes 2'!$C$12*('Notes 2'!$C$15/12) -> 1.1666667 | C48: =(SUM(CFS!B23:C23)+CFS!B24)*'Notes 2'!$D$12 -> 1.6 | D48: =(SUM(CFS!B23:D23)+SUM(CFS!B24:C24))*'Notes 2'!$E$12 -> 1.8
A50: PROFIT / (LOSS) BEFORE TAXATION | B50: =B47-B48 -> 3264.5 | C50: =C47-C48 -> 5788.5111 | D50: =D47-D48 -> 25815.385
A51: LESS : TAXATION
A52: PROFIT / (LOSS) AFTER TAXATION | B52: =B50-B51 -> 3264.5 | C52: =C50-C51 -> 5788.5111 | D52: =D50-D51 -> 25815.385
A53: Minority Interest | B53: 0 | C53: 0 | D53: 0
A54: Distributable Profit | B54: =B52-B53 -> 3264.5 | C54: =C52-C53 -> 5788.5111 | D54: =D52-D53 -> 25815.385
A55: less: Dividend | B55: 2 | C55: 2 | D55: 2
A57: Retained Profit / (Loss) For The Year | B57: =B54-B55 -> 3262.5 | C57: =C54-C55 -> 5786.5111 | D57: =D54-D55 -> 25813.385
A58: Retained Profit / (Loss) B/fwd | B58: 0 | C58: =B59 -> 3262.5 | D58: =C59 -> 9049.0111
A59: Retained Profit / (Loss) C/fwd | B59: =B57+B58 -> 3262.5 | C59: =C57+C58 -> 9049.0111 | D59: =D57+D58 -> 34862.396

Sheet BS
A1: BALANCE SHEET | D1: Back To Instructions
A2: =ProfitLoss!A2 -> Co. name: | B2: =ProfitLoss!B2 -> 0
B4: PROJECTIONS
B5: ='Notes 2'!C5 -> 2002 | C5: =B5+1 -> 2003 | D5: =C5+1 -> 2004
B6: RM | C6: RM | D6: RM
A8: R&D (Gross) | B8: 0 | C8: =B11 -> 21.666667 | D8: =C11 -> 54.444444
A9: Addition | B9: ='Financial Summary'!B70+'Financial Summary'!B76+'Financial Summary'!B82 -> 30 | C9: ='Financial Summary'!C70+'Financial Summary'!C76+'Financial Summary'!C82 -> 60 | D9: ='Financial Summary'!D70+'Financial Summary'!D76+'Financial Summary'!D82 -> 90
A10: Amortisation | B10: =SUM(B8:B9)*'Notes 2'!$C$14*('Notes 2'!$C$15/12) -> 8.3333333 | C10: =SUM(C8:C9)*'Notes 2'!$C$14 -> 27.222222 | D10: =SUM(D8:D9)*'Notes 2'!$C$14 -> 48.148148
A11: Research & Development (net) | B11: =SUM(B8:B9)-B10 -> 21.666667 | C11: =SUM(C8:C9)-C10 -> 54.444444 | D11: =SUM(D8:D9)-D10 -> 96.296296
A13: Investment | B13: =-CFS!B15 -> 100 | C13: =B13-CFS!C15 -> 70 | D13: =C13-CFS!D15 -> 120
A15: FIXED ASSETS (net)
A16: ='Notes 2'!B21 -> Land & Buildings | B16: ='Notes 2'!D65 -> 83.333333 | C16: ='Notes 2'!E65 -> 63.333333 | D16: ='Notes 2'!F65 -> 43.333333
A17: ='Notes 2'!B22 -> Fixtures & Fittings | B17: ='Notes 2'!D66 -> 83.333333 | C17: ='Notes 2'!E66 -> 63.333333 | D17: ='Notes 2'!F66 -> 43.333333
A18: ='Notes 2'!B23 -> Office Equipment | B18: ='Notes 2'!D67 -> 83.333333 | C18: ='Notes 2'!E67 -> 63.333333 | D18: ='Notes 2'!F67 -> 43.333333
A19: ='Notes 2'!B24 -> Motor Vehicles | B19: ='Notes 2'!D68 -> 0 | C19: ='Notes 2'!E68 -> 0 | D19: ='Notes 2'!F68 -> 0
A20: ='Notes 2'!B25 -> Others | B20: ='Notes 2'!D69 -> 0 | C20: ='Notes 2'!E69 -> 0 | D20: ='Notes 2'!F69 -> 0
A21: ='Notes 2'!B26 -> Others | B21: ='Notes 2'!D70 -> 83.333333 | C21: ='Notes 2'!E70 -> 63.333333 | D21: ='Notes 2'!F70 -> 43.333333
A22: ='Notes 2'!B27 -> Others | B22: ='Notes 2'!D71 -> 83.333333 | C22: ='Notes 2'!E71 -> 63.333333 | D22: ='Notes 2'!F71 -> 43.333333
B23: =SUM(B15:B22) -> 416.66667 | C23: =SUM(C15:C22) -> 316.66667 | D23: =SUM(D15:D22) -> 216.66667
A25: CURRENT ASSETS
A26: Trade debtors | B26: =ProfitLoss!B8-CFS!B9 -> 20 | C26: =ProfitLoss!C8*('Notes 2'!$C$9/12) -> 33.333333 | D26: =ProfitLoss!D8*('Notes 2'!$C$9/12) -> 50
A27: Cash and bank balances | B27: =CFS!B32 -> 9441.8333 | C27: =CFS!C32 -> 14479.9 | D27: =CFS!D32 -> 34452.433
A28: Prepayments & Deposits | B28: 0 | C28: 0 | D28: 0
A29: Stocks (non-tradeable) | B29: 0 | C29: 0 | D29: 0
B30: =SUM(B25:B29) -> 9461.8333 | C30: =SUM(C25:C29) -> 14513.233 | D30: =SUM(D25:D29) -> 34502.433
A32: Less : Current Liabilities
A33: Other creditors | B33: =(ProfitLoss!B28+ProfitLoss!B41-ProfitLoss!B23-ProfitLoss!B20-ProfitLoss!B33)*('Notes 2'!$C$11/12) -> 1 | C33: =(ProfitLoss!C28+ProfitLoss!C41-ProfitLoss!C23-ProfitLoss!C20-ProfitLoss!C33)*('Notes 2'!$C$11/12) -> 2 | D33: =(ProfitLoss!D28+ProfitLoss!D41-ProfitLoss!D23-ProfitLoss!D20-ProfitLoss!D33)*('Notes 2'!$C$11/12) -> 3
A34: Trade Creditors | B34: =ProfitLoss!B10*('Notes 2'!$C$10/12) -> 0 | C34: =ProfitLoss!C10*('Notes 2'!$C$10/12) -> 0 | D34: =ProfitLoss!D10*('Notes 2'!$C$10/12) -> 0
A35: Accruals | B35: 0 | C35: 0 | D35: 0
A36: Short Term Loans | B36: 0 | C36: 0 | D36: 0
B37: =SUM(B32:B36) -> 1 | C37: =SUM(C32:C36) -> 2 | D37: =SUM(D32:D36) -> 3
A39: NET CURRENT ASSETS | B39: =B30-B37 -> 9460.8333 | C39: =C30-C37 -> 14511.233 | D39: =D30-D37 -> 34499.433
A40: NET ASSETS | B40: =B11+B23+B39+B13 -> 9999.1667 | C40: =C11+C23+C39+C13 -> 14952.344 | D40: =D11+D23+D39+D13 -> 34932.396
A43: Financed By :
A44: Share Capital ( Paid-up capital) | B44: =CFS!B20 -> 50 | C44: =B44+CFS!C20 -> 50 | D44: =C44+CFS!D20 -> 50
A45: Share Premium Reserves | B45: =CFS!B21 -> 0 | C45: =B45+CFS!C21 -> 0 | D45: =C45+CFS!D21 -> 0
A46: Retained Profit C/fwd | B46: =ProfitLoss!B59 -> 3262.5 | C46: =ProfitLoss!C59 -> 9049.0111 | D46: =ProfitLoss!D59 -> 34862.396
B47: =SUM(B44:B46) -> 3312.5 | C47: =SUM(C44:C46) -> 9099.0111 | D47: =SUM(D44:D46) -> 34912.396
A48: Long term liabilities
A49: Grants | B49: ='Notes 2'!D88+'Notes 2'!D96+'Notes 2'!D104 -> 6666.6667 | C49: ='Notes 2'!E88+'Notes 2'!E96+'Notes 2'!E104 -> 5833.3333 | D49: ='Notes 2'!F88+'Notes 2'!F96+'Notes 2'!F104 -> 0
A50: Debenture
A51: Long-term loans | B51: =CFS!B23+CFS!B24 -> 20 | C51: =SUM(CFS!B23:C23)+SUM(CFS!B24:C24) -> 20 | D51: =SUM(CFS!B23:D23)+SUM(CFS!B24:D24) -> 20
A53: SHAREHOLDERS' NETWORTH | B53: =SUM(B47:B51) -> 9999.1667 | C53: =SUM(C47:C51) -> 14952.344 | D53: =SUM(D47:D51) -> 34932.396
B55: =B40-B53 -> 0 | C55: =C40-C53 -> 0 | D55: =D40-D53 -> 0

Sheet CFS
A1: CASH FLOW STATEMENT | D1: Back To Instructions
A2: =ProfitLoss!A2 -> Co. name: | B2: =ProfitLoss!B2 -> 0
B4: PROJECTIONS
B5: ='Notes 2'!C5 -> 2002 | C5: =B5+1 -> 2003 | D5: =C5+1 -> 2004
B6: RM | C6: RM | D6: RM
A7: Cash flows from operating activities
A9: Cash receipts from customers | B9: =ProfitLoss!B8*(('Notes 2'!$C$15-'Notes 2'!$C$9)/'Notes 2'!$C$15) -> 80 | C9: =ProfitLoss!C8*((12-'Notes 2'!$C$9)/12)+ProfitLoss!B8*('Notes 2'!$C$9/'Notes 2'!$C$15) -> 186.66667 | D9: =ProfitLoss!D8*((12-'Notes 2'!$C$9)/12)+ProfitLoss!C8*('Notes 2'!$C$9/12) -> 283.33333
A10: Cash paid to suppliers | B10: =-ProfitLoss!B10*((12-'Notes 2'!$C$10)/12) -> 0 | C10: =-ProfitLoss!C10*((12-'Notes 2'!$C$10)/12)-ProfitLoss!B10*('Notes 2'!$C$10/12) -> 0 | D10: =-ProfitLoss!D10*((12-'Notes 2'!$C$10)/12)-ProfitLoss!C10*('Notes 2'!$C$10/12) -> 0
A11: Cash paid to operating expenses & employees | B11: =-(ProfitLoss!B28+ProfitLoss!B41-ProfitLoss!B23-ProfitLoss!B20-ProfitLoss!B33)*((12-'Notes 2'!$C$11)/12)-ProfitLoss!B20-ProfitLoss!B33 -> -35 | C11: =-(ProfitLoss!C28+ProfitLoss!C41-ProfitLoss!C23-ProfitLoss!C20-ProfitLoss!C33)*((12-'Notes 2'!$C$11)/12)-(ProfitLoss!B28+ProfitLoss!B41-ProfitLoss!B23-ProfitLoss!B20-ProfitLoss!B33)*('Notes 2'!$C$11/12)-ProfitLoss!C20-ProfitLoss!C33 -> -35 | D11: =-(ProfitLoss!D28+ProfitLoss!D41-ProfitLoss!D23-ProfitLoss!D20-ProfitLoss!D33)*((12-'Notes 2'!$C$11)/12)-(ProfitLoss!C28+ProfitLoss!C41-ProfitLoss!C23-ProfitLoss!C20-ProfitLoss!C33)*('Notes 2'!$C$11/12)-ProfitLoss!D20-ProfitLoss!D33 -> -47
A12: Net cash from/(used in) operating activities | B12: =SUM(B7:B11) -> 45 | C12: =SUM(C7:C11) -> 151.66667 | D12: =SUM(D7:D11) -> 236.33333
A14: Cash flows from investing activities
A15: Investment | B15: -100 | C15: 30 | D15: -50
A16: Purchase of fixed assets | B16: =-'Notes 2'!D29 -> -500 | C16: =-'Notes 2'!E29 -> 0 | D16: =-'Notes 2'!F29 -> 0
A17: Research & development | B17: =-'Financial Summary'!B86 -> -70 | C17: =-'Financial Summary'!C86 -> -140 | D17: =-'Financial Summary'!D86 -> -210
A18: Net cash from/( used in) investing activities | B18: =SUM(B13:B17) -> -670 | C18: =SUM(C13:C17) -> -110 | D18: =SUM(D13:D17) -> -260
A19: Cash flows from financing activities
A20: Issuance of share capital | B20: 50
A21: Share Premium
A22: Dividend Paid (-) | B22: -2 | C22: -2 | D22: -2
A23: Long term loan/borrowings (+) | B23: 20
A24: Repayment of loan (-)
A25: Grant | B25: 10000 | C25: 5000 | D25: 20000
A26: Interest income/(expense) | B26: =-ProfitLoss!B48 -> -1.1666667 | C26: =-ProfitLoss!C48 -> -1.6 | D26: =-ProfitLoss!D48 -> -1.8
A27: Net cash from/( used in) financing activities | B27: =SUM(B19:B26) -> 10066.833 | C27: =SUM(C19:C26) -> 4996.4 | D27: =SUM(D19:D26) -> 19996.2
A29: Net increase( decrease) in cash and cash equivalents | B29: =SUM(B12+B18+B27) -> 9441.8333 | C29: =SUM(C12+C18+C27) -> 5038.0667 | D29: =SUM(D12+D18+D27) -> 19972.533
A31: Cash and cash equivalents brought forward | B31: 0 | C31: =B32 -> 9441.8333 | D31: =C32 -> 14479.9
A32: Cash and cash equivalents carried forward | B32: =B29+B31 -> 9441.8333 | C32: =C29+C31 -> 14479.9 | D32: =D29+D31 -> 34452.433

Sheet Notes 2
A1: Back To Instructions
B2: Assumptions:-
A4: 1. | B4: Name of the Company | C4: =Instructions!B14 -> 0
A5: 2. | B5: Projection Start (year) | C5: 2002 | D5: =C5+1 -> 2003 | E5: =D5+1 -> 2004
B6: Sales (must total to 100%) | C6: =SUM(C7:C8) -> 1 | D6: =SUM(D7:D8) -> 1 | E6: =SUM(E7:E8) -> 1
B7: -expexted Local Sales (%) | C7: 0.1 | D7: 0.2 | E7: 0.3
B8: -expected Export Sales (%) | C8: 0.9 | D8: 0.8 | E8: 0.7
A9: 3. | B9: Trade Debtors Credit Period (month) | C9: 2
A10: 4. | B10: Trade Creditors Credit Period (month) | C10: 0
B11: Other Creditors Credit Period (month) | C11: 1
A12: 5. | B12: Interest Rate (%) | C12: 0.07 | D12: 0.08 | E12: 0.09
A13: 6. | B13: Depreciation Rate (%) | C13: refer to FA section below
A14: 7. | B14: Amortisation Rate (%) | C14: 0.33333333 | D14: Back to P&L
A15: 8. | B15: Period covered in 1st. Year (months) | C15: 10
A18: 9. | B18: Fixed Assets Calculation | D18: =C5 -> 2002 | E18: =D18+1 -> 2003 | F18: =E18+1 -> 2004
B20: Annual Acquisition: | C20: Back to Balance Sheet
B21: Land & Buildings | D21: 100 | E21: 0 | F21: 0
B22: Fixtures & Fittings | D22: 100 | E22: 0 | F22: 0
B23: Office Equipment | D23: 100 | E23: 0 | F23: 0
B24: Motor Vehicles | D24: 0 | E24: 0 | F24: 0
B25: Others | D25: 0 | E25: 0 | F25: 0
B26: Others | D26: 100 | E26: 0 | F26: 0
B27: Others | D27: 100 | E27: 0 | F27: 0
D29: =SUM(D21:D28) -> 500 | E29: =SUM(E21:E28) -> 0 | F29: =SUM(F21:F28) -> 0
B31: Gross Accumulated:
B32: =B21 -> Land & Buildings | D32: =D21 -> 100 | E32: =D32+E21 -> 100 | F32: =E32+F21 -> 100
B33: =B22 -> Fixtures & Fittings | D33: =D22 -> 100 | E33: =D33+E22 -> 100 | F33: =E33+F22 -> 100
B34: =B23 -> Office Equipment | D34: =D23 -> 100 | E34: =D34+E23 -> 100 | F34: =E34+F23 -> 100
B35: =B24 -> Motor Vehicles | D35: =D24 -> 0 | E35: =D35+E24 -> 0 | F35: =E35+F24 -> 0
B36: =B25 -> Others | D36: =D25 -> 0 | E36: =D36+E25 -> 0 | F36: =E36+F25 -> 0
B37: =B26 -> Others | D37: =D26 -> 100 | E37: =D37+E26 -> 100 | F37: =E37+F26 -> 100
B38: =B27 -> Others | D38: =D27 -> 100 | E38: =D38+E27 -> 100 | F38: =E38+F27 -> 100
D40: =SUM(D32:D39) -> 500 | E40: =SUM(E32:E39) -> 500 | F40: =SUM(F32:F39) -> 500
B42: Depreciation: | C42: % | F42: Back to P&L
B43: =B21 -> Land & Buildings | C43: 0.2 | D43: =D32*$C43*($C$15/12) -> 16.666667 | E43: =E32*$C43 -> 20 | F43: =F32*$C43 -> 20
B44: =B22 -> Fixtures & Fittings | C44: 0.2 | D44: =D33*$C44*($C$15/12) -> 16.666667 | E44: =E33*$C44 -> 20 | F44: =F33*$C44 -> 20
B45: =B23 -> Office Equipment | C45: 0.2 | D45: =D34*$C45*($C$15/12) -> 16.666667 | E45: =E34*$C45 -> 20 | F45: =F34*$C45 -> 20
B46: =B24 -> Motor Vehicles | C46: 0.2 | D46: =D35*$C46*($C$15/12) -> 0 | E46: =E35*$C46 -> 0 | F46: =F35*$C46 -> 0
B47: =B25 -> Others | C47: 0.2 | D47: =D36*$C47*($C$15/12) -> 0 | E47: =E36*$C47 -> 0 | F47: =F36*$C47 -> 0
B48: =B26 -> Others | C48: 0.2 | D48: =D37*$C48*($C$15/12) -> 16.666667 | E48: =E37*$C48 -> 20 | F48: =F37*$C48 -> 20
B49: =B27 -> Others | C49: 0.2 | D49: =D38*$C49*($C$15/12) -> 16.666667 | E49: =E38*$C49 -> 20 | F49: =F38*$C49 -> 20
D51: =SUM(D43:D50) -> 83.333333 | E51: =SUM(E43:E50) -> 100 | F51: =SUM(F43:F50) -> 100
B53: Accumulated Depreciation:
B54: =B21 -> Land & Buildings | D54: =D43 -> 16.666667 | E54: =D54+E43 -> 36.666667 | F54: =E54+F43 -> 56.666667
B55: =B22 -> Fixtures & Fittings | D55: =D44 -> 16.666667 | E55: =D55+E44 -> 36.666667 | F55: =E55+F44 -> 56.666667
B56: =B23 -> Office Equipment | D56: =D45 -> 16.666667 | E56: =D56+E45 -> 36.666667 | F56: =E56+F45 -> 56.666667
B57: =B24 -> Motor Vehicles | D57: =D46 -> 0 | E57: =D57+E46 -> 0 | F57: =E57+F46 -> 0
B58: =B25 -> Others | D58: =D47 -> 0 | E58: =D58+E47 -> 0 | F58: =E58+F47 -> 0
B59: =B26 -> Others | D59: =D48 -> 16.666667 | E59: =D59+E48 -> 36.666667 | F59: =E59+F48 -> 56.666667
B60: =B27 -> Others | D60: =D49 -> 16.666667 | E60: =D60+E49 -> 36.666667 | F60: =E60+F49 -> 56.666667
D62: =SUM(D54:D61) -> 83.333333 | E62: =SUM(E54:E61) -> 183.33333 | F62: =SUM(F54:F61) -> 283.33333
B64: Net Book Value:
B65: =B21 -> Land & Buildings | D65: =D32-D54 -> 83.333333 | E65: =E32-E54 -> 63.333333 | F65: =F32-F54 -> 43.333333
B66: =B22 -> Fixtures & Fittings | D66: =D33-D55 -> 83.333333 | E66: =E33-E55 -> 63.333333 | F66: =F33-F55 -> 43.333333
B67: =B23 -> Office Equipment | D67: =D34-D56 -> 83.333333 | E67: =E34-E56 -> 63.333333 | F67: =F34-F56 -> 43.333333
B68: =B24 -> Motor Vehicles | D68: =D35-D57 -> 0 | E68: =E35-E57 -> 0 | F68: =F35-F57 -> 0
B69: =B25 -> Others | D69: =D36-D58 -> 0 | E69: =E36-E58 -> 0 | F69: =F36-F58 -> 0
B70: =B26 -> Others | D70: =D37-D59 -> 83.333333 | E70: =E37-E59 -> 63.333333 | F70: =F37-F59 -> 43.333333
B71: =B27 -> Others | D71: =D38-D60 -> 83.333333 | E71: =E38-E60 -> 63.333333 | F71: =F38-F60 -> 43.333333
D73: =SUM(D65:D72) -> 416.66667 | E73: =SUM(E65:E72) -> 316.66667 | F73: =SUM(F65:F72) -> 216.66667
A75: Assumptions:- | C75: Back to :- | D75: P&L | E75: Cash Flow | F75: B Sheet
A77: Rental of Premises
A79: Cost of Sales
A82: Grant | C82: First Drawdown | D82: =D18 -> 2002 | E82: =E18 -> 2003 | F82: =F18 -> 2004 | G82: =F82+1 -> 2005 | H82: =G82+1 -> 2006
C83: No.of years to amortised | D83: 3
C84: Brought fwd | D84: 0 | E84: =D88 -> 6666.6667 | F84: =E88 -> 3333.3333
C85: Addition | D85: =CFS!B25 -> 10000
D86: =SUM(D84:D85) -> 10000 | E86: =SUM(E84:E85) -> 6666.6667 | F86: =SUM(F84:F85) -> 3333.3333
C87: P&L (Other Income) | D87: =D86/$D$83 -> 3333.3333 | E87: =IF(D88>0,(D85/$D$83),0) -> 3333.3333 | F87: =IF(E88>0,(D85/$D$83),0) -> 3333.3333
C88: carried fwd | D88: =D86-D87 -> 6666.6667 | E88: =E86-E87 -> 3333.3333 | F88: =F86-F87 -> 0
C90: Second Drawdown
C91: No.of years to amortised | D91: 2
C92: Brought fwd | D92: 0 | E92: =D96 -> 0 | F92: =E96 -> 2500 | G92: =F96 -> 0 | H92: =G96 -> 0
C93: Addition | E93: =CFS!C25 -> 5000
D94: =SUM(D92:D93) -> 0 | E94: =SUM(E92:E93) -> 5000 | F94: =SUM(F92:F93) -> 2500 | G94: =SUM(G92:G93) -> 0 | H94: =SUM(H92:H93) -> 0
C95: P&L (Other Income) | D95: =D94/$D$91 -> 0 | E95: =(E93/$D$91) -> 2500 | F95: =IF(E96>0,(E93/$D$91),0) -> 2500 | G95: =IF(F96>0,(E93/$D$91),0) -> 0 | H95: =IF(G96>0,(E93/$D$91),0) -> 0
C96: carried fwd | D96: =D94-D95 -> 0 | E96: =E94-E95 -> 2500 | F96: =F94-F95 -> 0 | G96: =G94-G95 -> 0 | H96: =H94-H95 -> 0
C98: Third Drawdown
C99: No.of years to amortised | D99: 1
C100: Brought fwd | D100: 0 | E100: =D104 -> 0 | F100: =E104 -> 0 | G100: =F104 -> 0 | H100: =G104 -> 0
C101: Addition | F101: =CFS!D25 -> 20000
D102: =SUM(D100:D101) -> 0 | E102: =SUM(E100:E101) -> 0 | F102: =SUM(F100:F101) -> 20000 | G102: =SUM(G100:G101) -> 0 | H102: =SUM(H100:H101) -> 0
C103: P&L (Other Income) | D103: =D102/$D$83 -> 0 | E103: =(E101/$D$83) -> 0 | F103: =(F101/$D$99) -> 20000 | G103: =IF(F104>0,(F101/$D$99),0) -> 0 | H103: =IF(G104>0,(F101/$D$99),0) -> 0
C104: carried fwd | D104: =D102-D103 -> 0 | E104: =E102-E103 -> 0 | F104: =F102-F103 -> 0 | G104: =G102-G103 -> 0 | H104: =H102-H103 -> 0

Sheet Notes
A2: =ProfitLoss!A2 -> Co. name: | C2: =ProfitLoss!B2 -> 0
G4: ='Notes 2'!C5 -> 2002 | H4: =G4+1 -> 2003 | I4: =H4+1 -> 2004
A5: Profitability Ratios
B7: Gross profit percentage | C7: Gross profit | D7: x 100% | G7: =ProfitLoss!B12/ProfitLoss!B8 -> 1 | H7: =ProfitLoss!C12/ProfitLoss!C8 -> 1 | I7: =ProfitLoss!D12/ProfitLoss!D8 -> 1
C8: Sales
B10: Net profit percentage | C10: Net profit | D10: x 100% | G10: =ProfitLoss!B50/ProfitLoss!B8 -> 32.645 | H10: =ProfitLoss!C50/ProfitLoss!C8 -> 28.942556 | I10: =ProfitLoss!D50/ProfitLoss!D8 -> 86.051284
C11: Sales
B13: Return on capital employed | C13: Operating profit | D13: x 100% | G13: =ProfitLoss!B43/BS!B40 -> 0.33576131 | H13: =ProfitLoss!C43/BS!C40 -> 0.39574619 | I13: =ProfitLoss!D43/BS!D40 -> 0.74330238
C14: Capital employed
B16: Asset turnover | C16: sales | G16: =ProfitLoss!B8/BS!B40 -> 0.010000833 | H16: =ProfitLoss!C8/BS!C40 -> 0.013375829 | I16: =ProfitLoss!D8/BS!D40 -> 0.0085880166
C17: Total assets less current liabilities
A20: Liquidity Ratios
B22: Current ratio | C22: Current assets | D22: :1 | G22: =BS!B30/BS!B37 -> 9461.8333 | H22: =BS!C30/BS!C37 -> 7256.6167 | I22: =BS!D30/BS!D37 -> 11500.811
C23: Current liabilities
B25: Quick ratio/Acid test ratio | C25: Current assets – Stock | D25: :1 | G25: =(BS!B30-BS!B29)/BS!B37 -> 9461.8333 | H25: =(BS!C30-BS!C29)/BS!C37 -> 7256.6167 | I25: =(BS!D30-BS!D29)/BS!D37 -> 11500.811
C26: Current liabilities
A29: Financing Ratios
B31: Gearing ratio | C31: Prior charge capital | D31: :1 | G31: =(BS!B36+BS!B49+BS!B51)/BS!B47 -> 2.0186164 | H31: =(BS!C36+BS!C49+BS!C51)/BS!C47 -> 0.64329335 | I31: =(BS!D36+BS!D49+BS!D51)/BS!D47 -> 0.00057286242
C32: Total capital
B34: Interest cover | C34: PBIT | G34: =ProfitLoss!B47/ProfitLoss!B48 -> 2799.1429 | H34: =ProfitLoss!C47/ProfitLoss!C48 -> 3618.8194 | I34: =ProfitLoss!D47/ProfitLoss!D48 -> 14342.881
C35: Interest payable
A38: Investment Ratios
B40: Earnings per share | C40: PAT, pref dividends & extraordinary items | G40: =ProfitLoss!B54/BS!B44 -> 65.29 | H40: =ProfitLoss!C54/BS!C44 -> 115.77022 | I40: =ProfitLoss!D54/BS!D44 -> 516.3077
C41: Ordinary shares
B43: Return on shareholders’ funds | C43: equity earnings | G43: =ProfitLoss!B54/BS!B47 -> 0.98550943 | H43: =ProfitLoss!C54/BS!C47 -> 0.63616925 | I43: =ProfitLoss!D54/BS!D47 -> 0.73943321
C44: BV of shareholders’ funds at the year end
B46: Dividend cover | C46: equity earnings | G46: =ProfitLoss!B54/ProfitLoss!B55 -> 1632.25 | H46: =ProfitLoss!C54/ProfitLoss!C55 -> 2894.2556 | I46: =ProfitLoss!D54/ProfitLoss!D55 -> 12907.693
C47: equity dividend
B49: ROI | C49: PBDIT | G49: =ProfitLoss!B43/BS!B53 -> 0.33576131 | H49: =ProfitLoss!C43/BS!C53 -> 0.39574619 | I49: =ProfitLoss!D43/BS!D53 -> 0.74330238
C50: Networth
C52: Total Sales | F52: =SUM(G52:I52) -> 600 | G52: ='Financial Summary'!B9 -> 100 | H52: ='Financial Summary'!C9 -> 200 | I52: ='Financial Summary'!D9 -> 300
C53: Total R&D | F53: =SUM(G53:I53) -> 420 | G53: ='Financial Summary'!B20 -> 70 | H53: ='Financial Summary'!C20 -> 140 | I53: ='Financial Summary'!D20 -> 210
C54: Percentage of R&D over Sales | F54: =F53/F52 -> 0.7
C55: Tax Loss | F55: =SUM(ProfitLoss!B50:D50)/0.28 -> 124529.99
C56: OpEx | F56: =SUM(G56:I56)/3 -> 120 | G56: =ProfitLoss!B28+ProfitLoss!B41 -> 76 | H56: =ProfitLoss!C28+ProfitLoss!C41 -> 116 | I56: =ProfitLoss!D28+ProfitLoss!D41 -> 168
C57: CapEx | F57: =SUM(G57:I57)/3 -> 206.66667 | G57: =-CFS!B16+'Financial Summary'!B70+'Financial Summary'!B76+'Financial Summary'!B81 -> 520 | H57: =-CFS!C16+'Financial Summary'!C70+'Financial Summary'!C76+'Financial Summary'!C81 -> 40 | I57: =-CFS!D16+'Financial Summary'!D70+'Financial Summary'!D76+'Financial Summary'!D81 -> 60
C58: Total Export | F58: =SUM(G58:I58) -> 460 | G58: ='Financial Summary'!B8 -> 90 | H58: ='Financial Summary'!C8 -> 160 | I58: ='Financial Summary'!D8 -> 210
B61: Return on capital employed | C61: EBIT / total assets less current liabilities at the end of the year.
B62: Return on capital employed | C62: = EBIT / total assets less current liabilities at the end of the year.
B63: Net profit margin | C63: = EBIT/sales.
B64: Asset turnover | C64: = sales /total assets less current liabilities.
B65: Current ratio | C65: = current assets/current liabilities including overdraft.
B66: Gearing | C66: = total debt including overdraft/shareholders’ funds.
B67: Interest cover | C67: = EBIT/interest.
B68: Return on shareholders’ funds | C68: = equity earnings / book value of shareholders’ funds at the end of the year.
B69: Dividend cover | C69: = equity earnings/equity dividend.
A72: Notes to the Accounts
A74: 1
A75: 2
A76: 3
A77: 4
A78: 5
A79: 6
A80: 7
A97: Please show all the relevant workings in this spreadsheet.
