Workbook
Name Belg: Dialogbox!$B$30
Name Change_names: '2001 Grossed'!$B$2
Name Country_Name: Help!$B$113
Name DATA_TYPES: Help!$B$56
Name Example: Help!$D$95:$D$131
Name Help: Help!$A$1
Name Structure: Help!$J$1

Sheet 2001
A1: Name | B1: Type | C1: Code | D1: Population '000s | E1: Libraries - Total Administrative Units | F1: Libraries - Service Points | G1: Collections - Books & Bound Periodicals | H1: Collections - Current Periodicals - Titles | I1: Collections - Current Periodicals - Subscriptions | J1: Collections - Manuscripts | K1: Collections - Microforms | L1: Collections - Audio-visual Materials | M1: Collections - CD-ROMs | N1: Additions - Books & Bound Periodicals | O1: Additions - Audio-visual Materials | P1: Facilities & Services - Percentage Stock on Open Access | Q1: Facilities & Services - Percentage Catalogue Records Automated | R1: Facilities & Services - Number of Workstations for users | S1: Facilities & Services - Number connected to the internet | T1: Use & Users - Registered Users | U1: Use & Users - Loan Transactions | V1: Use & Users - Number of Visits | W1: Use & Users - Number of virtual referrals and transactions | X1: Use & Users - Number of virtual visits to networked library services | Y1: Use & Users - Potential Total Population Served | Z1: Library Staff FTE - Trained Librarians | AA1: Library Staff FTE - Other Library Staff | AB1: Library Staff FTE - Total Staff | AC1: Recurrent Expenditure (Euros) - Staff | AD1: Recurrent Expenditure (Euros) - Acquisition of Stock | AE1: Recurrent Expenditure (Euros) - Electronic Information | AF1: Recurrent Expenditure (Euros) - Automation | AG1: Recurrent Expenditure (Euros) - Premises and Related Costs | AH1: Recurrent Expenditure (Euros) - New Buildings / Refurbishment | AI1: Recurrent Expenditure (Euros) - Other Expenditure | AJ1: Recurrent Expenditure (Euros) - TOTAL EXPENDITURE | AK1: Income - Public Funding | AL1: Income - Fees & Charges | AM1: Income - Other Income | AN1: Income - TOTAL INCOME | AO1: Capital Expenditure - New Buildings / Refurbishment | AP1: Capital Expenditure - Acquisition of Stock | AQ1: Capital Expenditure - Automation | AR1: Capital Expenditure - Other Capital Expenditure | AS1: Capital Expenditure - TOTAL CAPITAL PAYMENTS | AT1: Additions | AU1: Loans per visit | AV1: Cost per pop | AW1: Users per 1000 pop | AX1: visits per 1000 pop | AY1: Bookstock per 1000 pop | AZ1: Total stock per 1000 pop | BA1: AV materials per 1000 pop
A2: Bulgaria | B2: CEE | C2: C1 | D2: =+Y2/1000 -> 7819.633 | E2: 3757 | F2: 3757 | G2: 52004510 | H2: 16841 | K2: 84843 | L2: 852026 | N2: 280475 | O2: 5354 | P2: 80 | T2: 901512 | U2: 17999677 | V2: 8252063 | W2: 12021 | X2: 13754 | Y2: 7819633 | Z2: 2915 | AA2: 406 | AB2: 3321 | AC2: 3960297 | AD2: 543433 | AE2: 0 | AF2: 0 | AG2: 0 | AH2: 0 | AI2: 830890 | AJ2: 5334620 | AK2: 4721347 | AL2: 359705 | AM2: 253568 | AN2: 5334620 | AT2: =+N2+O2 -> 285829 | AU2: =+U2/V2 -> 2.1812336 | AV2: =+AJ2/Y2 -> 0.68220849 | AW2: =+T2/D2 -> 115.28828 | AX2: =+V2/D2 -> 1055.3005 | AY2: =+G2/D2 -> 6650.5052 | AZ2: =SUM(G2:M2)/D2 -> 6772.4687 | BA2: =+L2/D2 -> 108.95985
A3: Czech Republic | B3: CEE | C3: C2 | D3: =+Y3/1000 -> 10223.833 | E3: 6090 | F3: 7179 | G3: 54293396 | H3: 78645 | I3: 87177 | J3: 3951 | K3: 130796 | L3: 676032 | M3: 25018 | N3: 1667841 | O3: 22204 | P3: 76 | Q3: 46 | R3: 3166 | S3: 2116 | T3: 1466682 | U3: 69208089 | V3: 16485563 | W3: 68703 | X3: 48228 | Y3: 10223833 | Z3: 3807 | AA3: 594 | AB3: 4401 | AC3: 22656487 | AD3: 5164471 | AE3: 10916 | AF3: 358727 | AG3: 1333161 | AH3: 380860 | AI3: 14089619 | AJ3: 43994240 | AK3: 45846096 | AL3: 157236 | AM3: 172074 | AN3: 46175406 | AO3: 1044702 | AP3: 0 | AQ3: 0 | AR3: 2938566 | AS3: 3983268 | AT3: =+N3+O3 -> 1690045 | AU3: =+U3/V3 -> 4.1981028 | AV3: =+AJ3/Y3 -> 4.3031063 | AW3: =+T3/D3 -> 143.45716 | AX3: =+V3/D3 -> 1612.464 | AY3: =+G3/D3 -> 5310.4737 | AZ3: =SUM(G3:M3)/D3 -> 5408.4427 | BA3: =+L3/D3 -> 66.123146
A4: Estonia | B4: CEE | C4: C3 | D4: =+Y4/1000 -> 1431.553 | E4: 546 | F4: 664 | G4: 10986247 | H4: 16010 | I4: 17865 | J4: 87 | K4: 1600 | L4: 54302 | M4: 900 | N4: 535439 | O4: 4708 | P4: 75 | Q4: 5 | R4: 631 | S4: 603 | T4: 447834 | U4: 13503545 | V4: 6426415 | W4: 0 | X4: 0 | Y4: 1431553 | Z4: 1224 | AA4: 257 | AB4: 1481 | AC4: 5053889 | AD4: 3335506 | AE4: 0 | AF4: 446677 | AG4: 0 | AH4: 0 | AI4: 1928745 | AJ4: 10764818 | AK4: 13209526 | AL4: 0 | AM4: 269121 | AN4: 13478647 | AO4: 2513456 | AP4: 0 | AQ4: 101119 | AR4: 88273 | AS4: 2702849 | AT4: =+N4+O4 -> 540147 | AU4: =+U4/V4 -> 2.1012563 | AV4: =+AJ4/Y4 -> 7.5196783 | AW4: =+T4/D4 -> 312.83089 | AX4: =+V4/D4 -> 4489.1213 | AY4: =+G4/D4 -> 7674.3558 | AZ4: =SUM(G4:M4)/D4 -> 7737.7582 | BA4: =+L4/D4 -> 37.932232
A5: Hungary | B5: CEE | C5: C4 | D5: =+Y5/1000 -> 10017.547 | E5: 2470 | F5: 3003 | G5: 40714533 | H5: 44888 | L5: 1443321 | M5: 48915 | N5: 1079410 | O5: 70025 | T5: 1362096 | U5: 12554527 | V5: 16580105 | W5: 15962 | X5: 45618 | Y5: 10017547 | Z5: 3566 | AA5: 2166 | AB5: 5732 | AC5: 21484399 | AD5: 5045211 | AE5: 0 | AF5: 0 | AG5: 0 | AH5: 0 | AI5: 18160365 | AJ5: 44689975 | AK5: 30615395 | AL5: 0 | AM5: 14074580 | AN5: 44689975 | AT5: =+N5+O5 -> 1149435 | AU5: =+U5/V5 -> 0.75720431 | AV5: =+AJ5/Y5 -> 4.4611695 | AW5: =+T5/D5 -> 135.97101 | AX5: =+V5/D5 -> 1655.1063 | AY5: =+G5/D5 -> 4064.3216 | AZ5: =SUM(G5:M5)/D5 -> 4217.7648 | BA5: =+L5/D5 -> 144.07928
A6: Latvia | B6: CEE | C6: C5 | D6: =+Y6/1000 -> 2326.2 | E6: 920 | F6: 920 | G6: 11738720 | K6: 1358 | L6: 164674 | N6: 298116 | O6: 14554 | T6: 575148 | U6: 21104458 | V6: 6440086 | W6: 0 | X6: 0 | Y6: 2326200 | Z6: 1828 | AA6: 655 | AB6: 2483 | AC6: 5638690 | AD6: 1456082 | AE6: 0 | AF6: 0 | AG6: 0 | AH6: 0 | AI6: 3072809 | AJ6: 10167581 | AK6: 10126712 | AL6: 26955 | AM6: 13914 | AN6: 10167581 | AO6: 109075 | AP6: 6964 | AQ6: 34978 | AR6: 32330 | AS6: 183347 | AT6: =+N6+O6 -> 312670 | AU6: =+U6/V6 -> 3.277046 | AV6: =+AJ6/Y6 -> 4.3708972 | AW6: =+T6/D6 -> 247.24787 | AX6: =+V6/D6 -> 2768.5006 | AY6: =+G6/D6 -> 5046.3073 | AZ6: =SUM(G6:M6)/D6 -> 5117.6821 | BA6: =+L6/D6 -> 70.79099
A7: Lithuania | B7: CEE | C7: C6 | D7: =+Y7/1000 -> 3646.32 | E7: 66 | F7: 1432 | G7: 22471450 | J7: 9522 | K7: 1174 | L7: 245876 | M7: 1958 | N7: 916453 | O7: 4992 | P7: 96 | R7: 375 | S7: 66 | T7: 831741 | U7: 25190465 | V7: 9794035 | W7: 9376 | X7: 71675 | Y7: 3646320 | Z7: 3104 | AA7: 892 | AB7: 3996 | AC7: 9291103 | AD7: 1787983 | AE7: 145149 | AF7: 214887 | AG7: 506659 | AH7: 0 | AI7: 4400886 | AJ7: 16346667 | AK7: 15696957 | AL7: 441912 | AM7: 266475 | AN7: 16405344 | AT7: =+N7+O7 -> 921445 | AU7: =+U7/V7 -> 2.5720211 | AV7: =+AJ7/Y7 -> 4.4830588 | AW7: =+T7/D7 -> 228.10423 | AX7: =+V7/D7 -> 2686.0053 | AY7: =+G7/D7 -> 6162.7751 | AZ7: =SUM(G7:M7)/D7 -> 6233.6767 | BA7: =+L7/D7 -> 67.431273
A8: Poland | B8: CEE | C8: C7 | D8: =+Y8/1000 -> 38652 | E8: 9226 | F8: 3564 | G8: 135816403 | K8: 10379 | L8: 2596064 | N8: 3792692 | O8: 121162 | T8: 7219507 | U8: 188957087 | W8: 103292 | X8: 118293 | Y8: 38652000 | Z8: 11133 | AA8: 6688 | AB8: 17821 | AT8: =+N8+O8 -> 3913854 | AU8: =+U8/V8 -> #DIV/0! | AV8: =+AJ8/Y8 -> 0 | AW8: =+T8/D8 -> 186.78224 | AX8: =+V8/D8 -> 0 | AY8: =+G8/D8 -> 3513.826 | AZ8: =SUM(G8:M8)/D8 -> 3581.2596 | BA8: =+L8/D8 -> 67.165063
A9: Romania | B9: CEE | C9: C8 | D9: =+Y9/1000 -> 22104.442 | E9: 2814 | F9: 3190 | G9: 48716685 | H9: 8923 | I9: 10268 | J9: 69088 | K9: 9439 | L9: 305960 | M9: 4000 | N9: 1033452 | O9: 7300 | P9: 74 | Q9: 9 | R9: 288 | S9: 114 | T9: 2046676 | U9: 36324232 | V9: 16890884 | W9: 3676 | X9: 4316 | Y9: 22104442 | Z9: 4475 | AA9: 783 | AB9: 5257 | AC9: 9775415 | AD9: 1394188 | AE9: 3028 | AF9: 47040 | AG9: 101912 | AH9: 17291 | AI9: 2079678 | AJ9: 13418552 | AK9: 13015995 | AL9: 134186 | AM9: 268371 | AN9: 13418552 | AO9: 942312 | AP9: 60231 | AQ9: 307789 | AR9: 272292 | AS9: 1582624 | AT9: =+N9+O9 -> 1040752 | AU9: =+U9/V9 -> 2.1505229 | AV9: =+AJ9/Y9 -> 0.60705228 | AW9: =+T9/D9 -> 92.591163 | AX9: =+V9/D9 -> 764.13981 | AY9: =+G9/D9 -> 2203.9319 | AZ9: =SUM(G9:M9)/D9 -> 2222.3752 | BA9: =+L9/D9 -> 13.841562
A10: Slovak Rep | B10: CEE | C10: C9 | D10: =+Y10/1000 -> 5398.983 | E10: 2656 | F10: 2909 | G10: 18954167 | H10: 11271 | I10: 13335 | J10: 633 | K10: 100 | L10: 243788 | M10: 2058 | N10: 334372 | O10: 1686 | P10: 93 | Q10: 30 | R10: 160 | S10: 142 | T10: 678637 | U10: 24702257 | V10: 6843282 | W10: 4852 | X10: 8475 | Y10: 5398983 | Z10: 1585 | AA10: 211 | AB10: 1796 | AC10: 4007711 | AD10: 846135 | AE10: 0 | AF10: 0 | AG10: 0 | AH10: 0 | AI10: 3279804 | AJ10: 8133651 | AK10: 6826698 | AL10: 671913 | AM10: 635040 | AN10: 8133651 | AO10: 448943 | AP10: 0 | AQ10: 64424 | AR10: 83734 | AS10: 597102 | AT10: =+N10+O10 -> 336058 | AU10: =+U10/V10 -> 3.6097091 | AV10: =+AJ10/Y10 -> 1.5065154 | AW10: =+T10/D10 -> 125.69719 | AX10: =+V10/D10 -> 1267.5132 | AY10: =+G10/D10 -> 3510.6921 | AZ10: =SUM(G10:M10)/D10 -> 3560.921 | BA10: =+L10/D10 -> 45.15443
A11: Slovenia | B11: CEE | C11: C10 | D11: =+Y11/1000 -> 1988.348 | E11: 60 | F11: 256 | G11: 7087968 | H11: 11079 | I11: 27950 | J11: 13689 | K11: 719 | L11: 234315 | M11: 13843 | N11: 354622 | O11: 34022 | P11: 82 | Q11: 74 | R11: 675 | S11: 387 | T11: 486108 | U11: 21883936 | V11: 7830326 | W11: 0 | X11: 0 | Y11: 1988348 | Z11: 626 | AA11: 242 | AB11: 868 | AC11: 15399404 | AD11: 5863893 | AE11: 96704 | AF11: 794158 | AG11: 6797167 | AH11: 1467029 | AI11: 0 | AJ11: 30418356 | AK11: 22032865 | AL11: 3557514 | AM11: 3049829 | AN11: 28640208 | AO11: 2514440 | AP11: 160718 | AQ11: 821296 | AR11: 726577 | AS11: 4223031 | AT11: =+N11+O11 -> 388644 | AU11: =+U11/V11 -> 2.7947669 | AV11: =+AJ11/Y11 -> 15.298306 | AW11: =+T11/D11 -> 244.47833 | AX11: =+V11/D11 -> 3938.1064 | AY11: =+G11/D11 -> 3564.7522 | AZ11: =SUM(G11:M11)/D11 -> 3716.4334 | BA11: =+L11/D11 -> 117.84406
A12: Austria | B12: EU | C12: C11 | D12: =+Y12/1000 -> 8122.933 | E12: 993 | F12: 1825 | G12: 9432575 | P12: 100 | Q12: 72 | R12: 1852 | S12: 1852 | T12: 848586 | U12: 14275803 | V12: 5249111 | W12: 19868 | X12: 21718 | Y12: 8122933 | Z12: 667 | AA12: 532 | AB12: 1199 | AC12: 33403971 | AD12: 5639644 | AE12: 22031 | AF12: 776573 | AG12: 2915684 | AH12: 41276 | AI12: 8435044 | AJ12: 51234223 | AK12: 46302662 | AL12: 3252539 | AM12: 1679022 | AN12: 51234223 | AT12: =+N12+O12 -> 0 | AU12: =+U12/V12 -> 2.7196611 | AV12: =+AJ12/Y12 -> 6.3073551 | AW12: =+T12/D12 -> 104.46793 | AX12: =+V12/D12 -> 646.20883 | AY12: =+G12/D12 -> 1161.2277 | AZ12: =SUM(G12:M12)/D12 -> 1161.2277 | BA12: =+L12/D12 -> 0
A13: België Vlaamse Gemeenschap | B13: België Vlaamse Gemeenschap | C13: C12a | D13: =+Y13/1000 -> 6260.144 | E13: 309 | F13: 879 | G13: 21553143 | I13: 43967 | L13: 2235649 | M13: 129303 | N13: 1372535 | O13: 231928 | Q13: 98 | T13: 1713351 | U13: 53679183 | Y13: 6260144 | Z13: 1724 | AA13: 977 | AB13: 2701 | AC13: 92360814 | AD13: 18239528 | AE13: 3783959 | AF13: 0 | AG13: 0 | AH13: 20638480 | AI13: 21364633 | AJ13: 156387414 | AK13: 54231239 | AL13: 9258630 | AM13: 822122 | AN13: 64311991 | AT13: =+N13+O13 -> 1604463 | AU13: =+U13/V13 -> #DIV/0! | AV13: =+AJ13/Y13 -> 24.98144 | AW13: =+T13/D13 -> 273.69195 | AX13: =+V13/D13 -> 0 | AY13: =+G13/D13 -> 3442.9149 | AZ13: =SUM(G13:M13)/D13 -> 3827.7174 | BA13: =+L13/D13 -> 357.12421
A14: Belgique-Communauté française | B14: Belgique-Communauté française | C14: C12b | D14: =+Y14/1000 -> 4139.223 | E14: 175 | F14: 572 | G14: 12496226 | I14: 99387 | L14: 93862 | M14: 9803 | N14: 253157 | O14: 2701 | R14: 395 | T14: 790555 | Y14: 4139223 | Z14: 700 | AA14: 301 | AB14: 1001 | AC14: 35790136 | AD14: 5428064 | AE14: 0 | AF14: 0 | AG14: 5084090 | AH14: 1405423 | AI14: 1182478 | AJ14: 48890191 | AK14: 40035871 | AL14: 3293057 | AM14: 0 | AN14: 43328928 | AT14: =+N14+O14 -> 255858 | AU14: =+U14/V14 -> #DIV/0! | AV14: =+AJ14/Y14 -> 11.811442 | AW14: =+T14/D14 -> 190.99116 | AX14: =+V14/D14 -> 0 | AY14: =+G14/D14 -> 3018.9787 | AZ14: =SUM(G14:M14)/D14 -> 3068.0343 | BA14: =+L14/D14 -> 22.676237
A15: Belgium | B15: EU | C15: C12 | D15: =+Y15/1000 -> 10399.367 | E15: 485 | F15: 1451 | G15: 34049369 | I15: 143354 | L15: 2329511 | M15: 139106 | N15: 1625692 | O15: 234629 | Q15: 98 | T15: 2503906 | W15: 41891 | X15: 35445 | Y15: 10399367 | Z15: 2424 | AA15: 1278 | AB15: 3702 | AC15: 128150950 | AD15: 23667592 | AE15: 3783959 | AF15: 0 | AG15: 5084090 | AH15: 22043903 | AI15: 22547111 | AJ15: 205277605 | AK15: 203318996 | AL15: 8470710 | AM15: 5887384 | AN15: 217677090 | AT15: =+N15+O15 -> 1860321 | AU15: =+U15/V15 -> #DIV/0! | AV15: =+AJ15/Y15 -> 19.739433 | AW15: =+T15/D15 -> 240.77485 | AX15: =+V15/D15 -> 0 | AY15: =+G15/D15 -> 3274.1771 | AZ15: =SUM(G15:M15)/D15 -> 3525.3434 | BA15: =+L15/D15 -> 224.00508
A16: Denmark | B16: EU | C16: C13 | D16: =+Y16/1000 -> 5367.226 | E16: 244 | F16: 797 | G16: 27081405 | H16: 2834 | I16: 184810 | J16: 25951 | K16: 355 | L16: 2988653 | M16: 121535 | N16: 1543188 | O16: 378324 | P16: 89 | Q16: 73 | R16: 3590 | S16: 2551 | T16: 1880587 | U16: 71657119 | V16: 32971560 | W16: 875756 | X16: 11249571 | Y16: 5367226 | Z16: 2286 | AA16: 2792 | AB16: 5078 | AC16: 202488396 | AD16: 49767930 | AI16: 92690956 | AJ16: 344947282 | AK16: 344947282 | AN16: 344947282 | AT16: =+N16+O16 -> 1921512 | AU16: =+U16/V16 -> 2.1733008 | AV16: =+AJ16/Y16 -> 64.269193 | AW16: =+T16/D16 -> 350.38342 | AX16: =+V16/D16 -> 6143.1287 | AY16: =+G16/D16 -> 5045.6987 | AZ16: =SUM(G16:M16)/D16 -> 5665.0387 | BA16: =+L16/D16 -> 556.83383
A17: Eire | B17: EU | C17: C15 | D17: =+Y17/1000 -> 3802.333 | E17: 32 | F17: 360 | G17: 11528071 | H17: 12663 | I17: 1710 | J17: 12728 | K17: 21307 | L17: 348422 | M17: 3436 | N17: 1004393 | O17: 37824 | P17: 89 | Q17: 73 | R17: 1317 | S17: 835 | T17: 905397 | U17: 12046407 | V17: 20373338 | W17: 1860 | X17: 4708 | Y17: 3802333 | Z17: 295 | AA17: 1105 | AB17: 1400 | AC17: 34418420 | AD17: 9778592 | AE17: 0 | AF17: 1616215 | AG17: 8339853 | AH17: 0 | AI17: 6795565 | AJ17: 60948645 | AK17: 53279598 | AL17: 1560092 | AM17: 6108955 | AN17: 60948645 | AO17: 3882190 | AP17: 4544227 | AQ17: 2042719 | AR17: 1376111 | AS17: 11845247 | AT17: =+N17+O17 -> 1042217 | AU17: =+U17/V17 -> 0.59128293 | AV17: =+AJ17/Y17 -> 16.029276 | AW17: =+T17/D17 -> 238.11618 | AX17: =+V17/D17 -> 5358.1151 | AY17: =+G17/D17 -> 3031.8415 | AZ17: =SUM(G17:M17)/D17 -> 3137.11 | BA17: =+L17/D17 -> 91.633742
A18: Finland | B18: EU | C18: C16 | D18: =+Y18/1000 -> 5158.44 | E18: 436 | F18: 1117 | G18: 37073549 | I18: 97972 | L18: 4353661 | M18: 24086 | N18: 1597165 | O18: 344380 | P18: 100 | Q18: 100 | R18: 2633 | S18: 1370 | T18: 2384067 | U18: 102216649 | V18: 63922228 | W18: 186232 | X18: 194134 | Y18: 5158440 | Z18: 1493 | AA18: 2662 | AB18: 4155 | AC18: 133788467 | AD18: 41960202 | AE18: 0 | AF18: 0 | AG18: 0 | AH18: 0 | AI18: 62732665 | AJ18: 238481334 | AK18: 219279683 | AL18: 4525438 | AM18: 14676213 | AN18: 238481334 | AO18: 19549279 | AP18: 1249550 | AQ18: 6385416 | AR18: 5648995 | AS18: 32833240 | AT18: =+N18+O18 -> 1941545 | AU18: =+U18/V18 -> 1.5990783 | AV18: =+AJ18/Y18 -> 46.23129 | AW18: =+T18/D18 -> 462.16821 | AX18: =+V18/D18 -> 12391.775 | AY18: =+G18/D18 -> 7186.9691 | AZ18: =SUM(G18:M18)/D18 -> 8054.6188 | BA18: =+L18/D18 -> 843.98791
A19: France | B19: EU | C19: C17 | D19: =+Y19/1000 -> 59463.538 | E19: 3989 | F19: 3884 | G19: 152159231 | I19: 230713 | L19: 10231729 | M19: 216654 | N19: 7042112 | O19: 1011847 | P19: 85 | T19: 12025650 | U19: 310175619 | W19: 18939 | X19: 21692 | Y19: 59463538 | Z19: 7031 | AA19: 14498 | AB19: 21529 | AC19: 685948897 | AD19: 124603730 | AE19: 650962 | AF19: 16711785 | AG19: 57245238 | AH19: 27126 | AI19: 171025601 | AJ19: 1056213339 | AK19: 1022860539 | AL19: 27109539 | AM19: 6243261 | AN19: 1056213339 | AO19: 218371411 | AP19: 8895576 | AQ19: 45457951 | AR19: 40215347 | AS19: 312940285 | AT19: =+N19+O19 -> 8053959 | AU19: =+U19/V19 -> #DIV/0! | AV19: =+AJ19/Y19 -> 17.76237 | AW19: =+T19/D19 -> 202.2357 | AX19: =+V19/D19 -> 0 | AY19: =+G19/D19 -> 2558.8661 | AZ19: =SUM(G19:M19)/D19 -> 2738.4567 | BA19: =+L19/D19 -> 172.06728
A20: Greece | B20: EU | C20: C18 | D20: =+Y20/1000 -> 10824 | E20: 733 | F20: 829 | G20: 9907012 | H20: 164430 | I20: 126978 | J20: 1540926 | K20: 324200 | L20: 104669 | M20: 13776 | N20: 302533 | O20: 12523 | P20: 89 | Q20: 73 | R20: 5020 | S20: 2545 | T20: 2951314 | U20: 1994343 | V20: 2492594 | W20: 8912 | X20: 12469 | Y20: 10824000 | Z20: 1029 | AA20: 805 | AB20: 1834 | AC20: 42171895 | AD20: 9424764 | AE20: 50573 | AF20: 1298353 | AG20: 4447434 | AH20: 2108 | AI20: 13287131 | AJ20: 70682258 | AT20: =+N20+O20 -> 315056 | AU20: =+U20/V20 -> 0.80010744 | AV20: =+AJ20/Y20 -> 6.5301421 | AW20: =+T20/D20 -> 272.6639 | AX20: =+V20/D20 -> 230.284 | AY20: =+G20/D20 -> 915.28197 | AZ20: =SUM(G20:M20)/D20 -> 1125.4611 | BA20: =+L20/D20 -> 9.670085
A21: Iceland | B21: EFTA | C21: C19 | D21: =+Y21/1000 -> 281.31 | E21: 127 | F21: 133 | G21: 2067665 | I21: 94 | J21: 600 | K21: 3178 | L21: 70718 | M21: 880 | N21: 83407 | O21: 4962 | T21: 90696 | U21: 2233208 | V21: 842590 | W21: 497 | X21: 2192 | Y21: 281310 | Z21: 80 | AA21: 220 | AB21: 300 | AC21: 4801006 | AD21: 1665216 | AE21: 0 | AF21: 94929 | AG21: 675864 | AH21: 226685 | AI21: 1253994 | AJ21: 8717694 | AK21: 7937709 | AL21: 620304 | AM21: 159681 | AN21: 8717694 | AT21: =+N21+O21 -> 88369 | AU21: =+U21/V21 -> 2.6504089 | AV21: =+AJ21/Y21 -> 30.989634 | AW21: =+T21/D21 -> 322.40589 | AX21: =+V21/D21 -> 2995.2366 | AY21: =+G21/D21 -> 7350.1298 | AZ21: =SUM(G21:M21)/D21 -> 7618.4103 | BA21: =+L21/D21 -> 251.38815
A22: Italy | B22: EU | C22: C20 | D22: =+Y22/1000 -> 57843.667 | E22: 84 | F22: 6003 | G22: 42214563 | N22: 3993273 | W22: 457999 | X22: 500805 | Y22: 57843667 | Z22: 5984 | AA22: 17856 | AB22: 23840 | AT22: =+N22+O22 -> 3993273 | AU22: =+U22/V22 -> #DIV/0! | AV22: =+AJ22/Y22 -> 0 | AW22: =+T22/D22 -> 0 | AX22: =+V22/D22 -> 0 | AY22: =+G22/D22 -> 729.80441 | AZ22: =SUM(G22:M22)/D22 -> 729.80441 | BA22: =+L22/D22 -> 0
A23: Liechtenstein | B23: EFTA | C23: C21 | D23: =+Y23/1000 -> 33.322 | E23: 3 | F23: 3 | G23: 24588 | N23: 6087 | S23: 5 | U23: 80227 | W23: 1373 | X23: 1009 | Y23: 33322 | Z23: 2 | AA23: 3 | AB23: 5 | AT23: =+N23+O23 -> 6087 | AU23: =+U23/V23 -> #DIV/0! | AV23: =+AJ23/Y23 -> 0 | AW23: =+T23/D23 -> 0 | AX23: =+V23/D23 -> 0 | AY23: =+G23/D23 -> 737.89088 | AZ23: =SUM(G23:M23)/D23 -> 737.89088 | BA23: =+L23/D23 -> 0
A24: Luxembourg | B24: EU | C24: C22 | D24: =+Y24/1000 -> 457.333 | E24: 8 | F24: 8 | G24: 248480 | H24: 188 | I24: 173 | J24: 0 | K24: 0 | L24: 1530 | M24: 332 | N24: 10102 | O24: 114 | P24: 91 | Q24: 44 | R24: 52 | S24: 28 | T24: 37112 | U24: 129535 | V24: 78357 | W24: 2210 | X24: 3887 | Y24: 457333 | Z24: 18 | AA24: 5 | AB24: 23 | AC24: 1117927 | AD24: 257520 | AE24: 418 | AF24: 21 | AG24: 38878 | AH24: 41805 | AI24: 32997 | AJ24: 1489566 | AO24: 8895 | AP24: 453 | AQ24: 2300 | AR24: 1785 | AS24: 13433 | AT24: =+N24+O24 -> 10216 | AU24: =+U24/V24 -> 1.6531388 | AV24: =+AJ24/Y24 -> 3.2570709 | AW24: =+T24/D24 -> 81.148747 | AX24: =+V24/D24 -> 171.33467 | AY24: =+G24/D24 -> 543.32401 | AZ24: =SUM(G24:M24)/D24 -> 548.1848 | BA24: =+L24/D24 -> 3.3454835
A25: Netherlands | B25: EU | C25: C23 | D25: =+Y25/1000 -> 16250.667 | E25: 490 | F25: 1101 | G25: 42386215 | N25: 3817553 | U25: 197036000 | W25: 125021 | X25: 136747 | Y25: 16250667 | Z25: 2510 | AA25: 5898 | AB25: 8408 | AC25: 264286000 | AD25: 52415923 | AE25: 278786 | AF25: 35398000 | AG25: 72518000 | AH25: 12961 | AI25: 72677330 | AJ25: 497587000 | AK25: 338790000 | AL25: 61509000 | AM25: 97288000 | AN25: 497587000 | AT25: =+N25+O25 -> 3817553 | AU25: =+U25/V25 -> #DIV/0! | AV25: =+AJ25/Y25 -> 30.619482 | AW25: =+T25/D25 -> 0 | AX25: =+V25/D25 -> 0 | AY25: =+G25/D25 -> 2608.2754 | AZ25: =SUM(G25:M25)/D25 -> 2608.2754 | BA25: =+L25/D25 -> 0
A26: Norway | B26: EFTA | C26: C24 | D26: =+Y26/1000 -> 4551.248 | E26: 435 | F26: 1010 | G26: 20642273 | H26: 21003 | I26: 42093 | J26: 36521 | K26: 291716 | L26: 1319527 | M26: 15746 | N26: 860640 | O26: 149152 | P26: 82 | Q26: 79 | R26: 1714 | S26: 1369 | T26: 1319108 | U26: 23467666 | V26: 22684118 | W26: 113996 | X26: 142338 | Y26: 4551248 | Z26: 931 | AA26: 940 | AB26: 1871 | AC26: 76697660 | AD26: 17104294 | AE26: 0 | AF26: 3535708 | AG26: 11524607 | AH26: 0 | AI26: 15907166 | AJ26: 124769435 | AK26: 113606123 | AL26: 8877923 | AM26: 2285388 | AN26: 124769435 | AT26: =+N26+O26 -> 1009792 | AU26: =+U26/V26 -> 1.0345417 | AV26: =+AJ26/Y26 -> 27.414334 | AW26: =+T26/D26 -> 289.83435 | AX26: =+V26/D26 -> 4984.1534 | AY26: =+G26/D26 -> 4535.5193 | AZ26: =SUM(G26:M26)/D26 -> 4914.8891 | BA26: =+L26/D26 -> 289.92641
A27: Portugal | B27: EU | C27: C25 | D27: =+Y27/1000 -> 9832 | E27: 164 | F27: 278 | G27: 6389929 | K27: 2488 | L27: 172137 | N27: 391909 | O27: 24585 | R27: 780 | T27: 3117902 | U27: 1486378 | W27: 563 | X27: 1 | Y27: 9832000 | Z27: 792 | AA27: 531 | AB27: 1323 | AC27: 13100349 | AD27: 2747158 | AE27: 27 | AF27: 731 | AG27: 3440 | AH27: 2359 | AI27: 2576928 | AJ27: 18430992 | AK27: 18183890 | AL27: 245749 | AM27: 1353 | AN27: 18430992 | AO27: 3150666 | AP27: 0 | AQ27: 0 | AR27: 2401210 | AS27: 5551876 | AT27: =+N27+O27 -> 416494 | AU27: =+U27/V27 -> #DIV/0! | AV27: =+AJ27/Y27 -> 1.8745924 | AW27: =+T27/D27 -> 317.11778 | AX27: =+V27/D27 -> 0 | AY27: =+G27/D27 -> 649.91141 | AZ27: =SUM(G27:M27)/D27 -> 667.67229 | BA27: =+L27/D27 -> 17.507832
A28: Spain | B28: EU | C28: C26 | D28: =+Y28/1000 -> 39542.333 | E28: 4829 | F28: 5209 | G28: 42817561 | H28: 97230 | I28: 158931 | J28: 28069 | K28: 253527 | L28: 1583579 | M28: 125123 | N28: 2494800 | O28: 209169 | P28: 89 | Q28: 73 | R28: 2941 | S28: 462 | T28: 7524176 | U28: 27491212 | V28: 204131947 | W28: 126139 | X28: 5171 | Y28: 39542333 | Z28: 4139 | AA28: 2469 | AB28: 6608 | AC28: 132172221 | AD28: 30509153 | AE28: 0 | AF28: 0 | AG28: 0 | AH28: 0 | AI28: 26443101 | AJ28: 189124475 | AK28: 170920259 | AL28: 12006324 | AM28: 6197892 | AN28: 189124475 | AT28: =+N28+O28 -> 2703969 | AU28: =+U28/V28 -> 0.13467374 | AV28: =+AJ28/Y28 -> 4.7828355 | AW28: =+T28/D28 -> 190.28154 | AX28: =+V28/D28 -> 5162.3648 | AY28: =+G28/D28 -> 1082.8284 | AZ28: =SUM(G28:M28)/D28 -> 1139.6399 | BA28: =+L28/D28 -> 40.047688
A29: Sweden | B29: EU | C29: C27 | D29: =+Y29/1000 -> 8909.457 | E29: 291 | F29: 1592 | G29: 44330201 | H29: 67961 | I29: 106470 | J29: 0 | K29: 0 | L29: 2619965 | M29: 0 | N29: 2054539 | O29: 185836 | P29: 87 | U29: 81381984 | V29: 47575528 | W29: 0 | X29: 0 | Y29: 8909457 | Z29: 2304 | AA29: 2587 | AB29: 4891 | AC29: 169515820 | AD29: 44940745 | AE29: 414356 | AF29: 10637532 | AG29: 36438244 | AH29: 17266 | AI29: 86343291 | AJ29: 348307254 | AK29: 314780866 | AL29: 22111838 | AM29: 11414550 | AN29: 348307254 | AO29: 9558144 | AP29: 610936 | AQ29: 3121994 | AR29: 2761940 | AS29: 16053014 | AT29: =+N29+O29 -> 2240375 | AU29: =+U29/V29 -> 1.710585 | AV29: =+AJ29/Y29 -> 39.094106 | AW29: =+T29/D29 -> 0 | AX29: =+V29/D29 -> 5339.8909 | AY29: =+G29/D29 -> 4975.6344 | AZ29: =SUM(G29:M29)/D29 -> 5289.2782 | BA29: =+L29/D29 -> 294.06562
A30: Switzerland | B30: EFTA | C30: C28 | D30: =+Y30/1000 -> 7320.8 | E30: 41 | F30: 2009 | G30: 28656291 | N30: 1405787 | U30: 6328307 | V30: 34171127 | W30: 306137 | X30: 225252 | Y30: 7320800 | Z30: 1841 | AA30: 3476 | AB30: 5317 | AT30: =+N30+O30 -> 1405787 | AU30: =+U30/V30 -> 0.18519456 | AV30: =+AJ30/Y30 -> 0 | AW30: =+T30/D30 -> 0 | AX30: =+V30/D30 -> 4667.6766 | AY30: =+G30/D30 -> 3914.3661 | AZ30: =SUM(G30:M30)/D30 -> 3914.3661 | BA30: =+L30/D30 -> 0
A31: UK | B31: EU | C31: C29 | D31: =+Y31/1000 -> 60296.633 | E31: 208 | F31: 4614 | G31: 115962000 | H31: 85000 | I31: 105000 | J31: 118000 | K31: 6442000 | L31: 7348000 | M31: 113867 | N31: 11019000 | O31: 1485000 | P31: 89 | R31: 23200 | S31: 13500 | T31: 33837000 | U31: 417004000 | V31: 318226000 | W31: 0 | X31: 0 | Y31: 60296633 | Z31: 6200 | AA31: 19600 | AB31: 25800 | AC31: 826620033 | AD31: 197243503 | AE31: 1597132 | AF31: 63528612 | AG31: 170044367 | AH31: 0 | AI31: 246985005 | AJ31: 1506018653 | AK31: 1334604424 | AL31: 139547913 | AM31: 31866316 | AN31: 1506018653 | AO31: 58724874 | AP31: 4906772 | AQ31: 24511194 | AR31: 6656214 | AS31: 94799054 | AT31: =+N31+O31 -> 12504000 | AU31: =+U31/V31 -> 1.310402 | AV31: =+AJ31/Y31 -> 24.976828 | AW31: =+T31/D31 -> 561.17561 | AX31: =+V31/D31 -> 5277.6745 | AY31: =+G31/D31 -> 1923.192 | AZ31: =SUM(G31:M31)/D31 -> 2158.8911 | BA31: =+L31/D31 -> 121.86418
A32: Germany | B32: EU | C32: C31 | D32: =+Y32/1000 -> 82213.913 | E32: 9062 | F32: 10932 | G32: 104358906 | I32: 139018 | L32: 10598899 | P32: 94 | T32: 8302968 | U32: 307159562 | V32: 298975665 | W32: 334807 | X32: 365413 | Y32: 82213913 | Z32: 8787 | AA32: 4387 | AB32: 13174 | AC32: 472325169 | AD32: 97497066 | AE32: 0 | AF32: 0 | AG32: 0 | AH32: 0 | AI32: 157417476 | AJ32: 727239711 | AK32: 645041124 | AL32: 56472303 | AM32: 25726284 | AN32: 727239711 | AO32: 32759294 | AP32: 2093906 | AQ32: 10700229 | AR32: 9466185 | AS32: 55019614 | AT32: =+N32+O32 -> 0 | AU32: =+U32/V32 -> 1.0273731 | AV32: =+AJ32/Y32 -> 8.8457012 | AW32: =+T32/D32 -> 100.99225 | AX32: =+V32/D32 -> 3636.558 | AY32: =+G32/D32 -> 1269.3582 | AZ32: =SUM(G32:M32)/D32 -> 1399.9677 | BA32: =+L32/D32 -> 128.91856
A33: USA | B33: World - A | C33: C50 | D33: =+Y33/1000 -> 275828.33 | E33: 9202 | F33: 16491 | G33: 749041643 | I33: 1944263 | J33: 0 | L33: 47383632 | M33: 1198051 | N33: 17331991 | O33: 3685613 | P33: 100 | S33: 18534 | U33: 1753498549 | V33: 1129238333 | W33: 1419166 | X33: 7196227 | Y33: 275828333 | Z33: 41693 | AA33: 84796 | AB33: 126489 | AC33: 4036684649 | AD33: 968301302 | AE33: 12862 | AF33: 363475 | AG33: 1707992 | AH33: 1171344 | AI33: 1279429168 | AJ33: 6287670792 | AK33: 5721780421 | AL33: 306744066 | AM33: 259146305 | AN33: 6287670792 | AT33: =+N33+O33 -> 21017604 | AU33: =+U33/V33 -> 1.5528153 | AV33: =+AJ33/Y33 -> 22.795594 | AW33: =+T33/D33 -> 0 | AX33: =+V33/D33 -> 4093.9896 | AY33: =+G33/D33 -> 2715.6081 | AZ33: =SUM(G33:M33)/D33 -> 2898.787 | BA33: =+L33/D33 -> 171.78667
A34: Turkey | B34: World - B | C34: C42 | D34: =+Y34/1000 -> 67090.173 | E34: 1434 | F34: 1982 | G34: 12476310 | I34: 131 | J34: 157015 | K34: 7118 | L34: 112952 | M34: 597 | Q34: 11 | S34: 28 | T34: 375214 | U34: 3665856 | V34: 18830433 | W34: 4443 | X34: 22528 | Y34: 67090173 | Z34: 264 | AA34: 2579 | AB34: 2843 | AC34: 16227540 | AD34: 0 | AE34: 0 | AF34: 200232 | AG34: 19840909 | AH34: 2880809 | AI34: 0 | AJ34: 39149490 | AK34: 35713148 | AL34: 1993510 | AM34: 1442832 | AN34: 39149490 | AT34: =+N34+O34 -> 0 | AU34: =+U34/V34 -> 0.1946772 | AV34: =+AJ34/Y34 -> 0.58353539 | AW34: =+T34/D34 -> 5.592682 | AX34: =+V34/D34 -> 280.67349 | AY34: =+G34/D34 -> 185.9633 | AZ34: =SUM(G34:M34)/D34 -> 190.10419 | BA34: =+L34/D34 -> 1.6835849
A35: Australia | B35: World - A | C35: C70 | D35: =+Y35/1000 -> 19261.779 | Y35: 19261779 | AT35: =+N35+O35 -> 0 | AU35: =+U35/V35 -> #DIV/0! | AV35: =+AJ35/Y35 -> 0 | AW35: =+T35/D35 -> 0 | AX35: =+V35/D35 -> 0 | AY35: =+G35/D35 -> 0 | AZ35: =SUM(G35:M35)/D35 -> 0 | BA35: =+L35/D35 -> 0
A36: Japan | B36: World - A | C36: C41 | D36: =+Y36/1000 -> 127474.33 | E36: 1716 | F36: 2680 | G36: 295816511 | N36: 19517960 | T36: 38679751 | U36: 552624145 | W36: 1000371 | X36: 5072629 | Y36: 127474333 | Z36: 11808 | AA36: 15431 | AB36: 27239 | AC36: 805959446 | AD36: 366403788 | AE36: 15656 | AF36: 870078 | AG36: 2241585 | AH36: 319311 | AI36: 135161399 | AJ36: 1310971263 | AK36: 1195900900 | AL36: 66755249 | AM36: 48315114 | AN36: 1310971263 | AT36: =+N36+O36 -> 19517960 | AU36: =+U36/V36 -> #DIV/0! | AV36: =+AJ36/Y36 -> 10.284198 | AW36: =+T36/D36 -> 303.43168 | AX36: =+V36/D36 -> 0 | AY36: =+G36/D36 -> 2320.5967 | AZ36: =SUM(G36:M36)/D36 -> 2320.5967 | BA36: =+L36/D36 -> 0
A37: Korea | B37: World - A | C37: C40 | D37: =+Y37/1000 -> 49235 | Y37: 49235000 | AT37: =+N37+O37 -> 0 | AU37: =+U37/V37 -> #DIV/0! | AV37: =+AJ37/Y37 -> 0 | AW37: =+T37/D37 -> 0 | AX37: =+V37/D37 -> 0 | AY37: =+G37/D37 -> 0 | AZ37: =SUM(G37:M37)/D37 -> 0 | BA37: =+L37/D37 -> 0
A38: Canada | B38: World - A | C38: C51 | D38: =+Y38/1000 -> 31374.667 | E38: 2739 | F38: 910 | G38: 75032608 | I38: 150814 | U38: 331565367 | Y38: 31374667 | Z38: 6733 | AA38: 6616 | AB38: 13349 | AC38: 212115444 | AD38: 45849663 | AE38: 0 | AF38: 0 | AG38: 0 | AH38: 0 | AI38: 68846851 | AJ38: 326811958 | AK38: 298126073 | AL38: 16641413 | AM38: 12044472 | AN38: 326811958 | AO38: 18361785 | AP38: 906999 | AQ38: 4634923 | AR38: 4100384 | AS38: 28004091 | AT38: =+N38+O38 -> 0 | AU38: =+U38/V38 -> #DIV/0! | AV38: =+AJ38/Y38 -> 10.416428 | AW38: =+T38/D38 -> 0 | AX38: =+V38/D38 -> 0 | AY38: =+G38/D38 -> 2391.5029 | AZ38: =SUM(G38:M38)/D38 -> 2396.3098 | BA38: =+L38/D38 -> 0
A39: New Zealand | B39: World - A | C39: C71 | D39: =+Y39/1000 -> 3931 | Y39: 3931000 | AT39: =+N39+O39 -> 0 | AU39: =+U39/V39 -> #DIV/0! | AV39: =+AJ39/Y39 -> 0 | AW39: =+T39/D39 -> 0 | AX39: =+V39/D39 -> 0 | AY39: =+G39/D39 -> 0 | AZ39: =SUM(G39:M39)/D39 -> 0 | BA39: =+L39/D39 -> 0
A40: Mexico | B40: World - B | C40: C72 | D40: =+Y40/1000 -> 98961.882 | Y40: 98961882 | AT40: =+N40+O40 -> 0 | AU40: =+U40/V40 -> #DIV/0! | AV40: =+AJ40/Y40 -> 0 | AW40: =+T40/D40 -> 0 | AX40: =+V40/D40 -> 0 | AY40: =+G40/D40 -> 0 | AZ40: =SUM(G40:M40)/D40 -> 0 | BA40: =+L40/D40 -> 0
A41: CEE | B41: Totals | D41: =+Y41/1000 -> 103608.86 | E41: 28605 | F41: 26874 | G41: 402784079 | H41: 323201 | I41: 687048 | J41: 210088 | K41: 243840 | L41: 6816358 | M41: 167017 | N41: 10292872 | O41: 286007 | P41: 81 | Q41: 39 | R41: 8014 | S41: 4727 | T41: 16015941 | U41: 431428273 | V41: 146004455 | W41: 217882 | X41: 310359 | Y41: 103608859 | Z41: 34263 | AA41: 12894 | AB41: 47156 | AC41: 167629712 | AD41: 47670615 | AE41: 321941 | AF41: 2888925 | AG41: 10964806 | AH41: 2242821 | AI41: 93265985 | AJ41: 324984807 | AK41: 280753254 | AL41: 10791687 | AM41: 36615390 | AN41: 328160331 | AO41: 23908067 | AP41: 1034802 | AQ41: 5452959 | AR41: 7789586 | AS41: 38185416 | AT41: =+N41+O41 -> 10578879 | AU41: =+U41/V41 -> 2.954898 | AV41: =+AJ41/Y41 -> 3.1366508 | AW41: =+T41/D41 -> 154.58081 | AX41: =+V41/D41 -> 1409.1889 | AY41: =+G41/D41 -> 3887.5448 | AZ41: =SUM(G41:M41)/D41 -> 3969.0779 | BA41: =+L41/D41 -> 65.789336
A42: EU | B42: Totals | D42: =+Y42/1000 -> 378483.84 | E42: 22048 | F42: 40000 | G42: 679939067 | H42: 1452645 | I42: 1656639 | J42: 2716950 | K42: 14358304 | L42: 53745499 | M42: 1123385 | N42: 48246704 | O42: 6514160 | P42: 89 | Q42: 76 | R42: 129416 | S42: 68583 | T42: 99137149 | U42: 1853105375 | V42: 1798551507 | W42: 2200197 | X42: 12551761 | Y42: 378483840 | Z42: 45959 | AA42: 77005 | AB42: 122964 | AC42: 3754658460 | AD42: 827929987 | AE42: 7535950 | AF42: 148906550 | AG42: 421948731 | AH42: 22219544 | AI42: 1163805967 | AJ42: 6347005190 | AK42: 5725710915 | AL42: 397260083 | AM42: 236433677 | AN42: 6359404675 | AO42: 480209625 | AP42: 29208672 | AQ42: 127333721 | AR42: 96011849 | AS42: 732763867 | AT42: =+N42+O42 -> 54760864 | AU42: =+U42/V42 -> 1.0303321 | AV42: =+AJ42/Y42 -> 16.769554 | AW42: =+T42/D42 -> 261.93232 | AX42: =+V42/D42 -> 4751.9902 | AY42: =+G42/D42 -> 1796.4811 | AZ42: =SUM(G42:M42)/D42 -> 1994.7813 | BA42: =+L42/D42 -> 142.0021
A43: EFTA | B43: Totals | D43: =+Y43/1000 -> 12157.939 | E43: 607 | F43: 3155 | G43: 51478198 | H43: 63257 | I43: 120529 | J43: 104634 | K43: 830613 | L43: 3211732 | M43: 28613 | N43: 2353957 | O43: 378048 | P43: 82 | Q43: 81 | R43: 4358 | S43: 2728 | T43: 3638294 | U43: 32317443 | V43: 57679108 | W43: 422003 | X43: 370791 | Y43: 12157939 | Z43: 2854 | AA43: 4639 | AB43: 7493 | AC43: 275287706 | AD43: 85671386 | AE43: 0 | AF43: 7392514 | AG43: 39341437 | AH43: 11567452 | AI43: 67671250 | AJ43: 486931745 | AK43: 443669477 | AL43: 34487222 | AM43: 8954076 | AN43: 487110776 | AO43: 27402176 | AP43: 1353557 | AQ43: 6916919 | AR43: 6119202 | AS43: 41791854 | AT43: =+N43+O43 -> 2732005 | AU43: =+U43/V43 -> 0.56029721 | AV43: =+AJ43/Y43 -> 40.050517 | AW43: =+T43/D43 -> 299.25253 | AX43: =+V43/D43 -> 4744.1518 | AY43: =+G43/D43 -> 4234.1221 | AZ43: =SUM(G43:M43)/D43 -> 4592.6843 | BA43: =+L43/D43 -> 264.16747
A44: World A | B44: Totals | D44: =+Y44/1000 -> 507105.11 | E44: 16075 | F44: 23543 | G44: 1286879868 | H44: 580656 | I44: 2357666 | J44: 207200 | K44: 10859117 | L44: 58912098 | M44: 1419131 | N44: 48858039 | O44: 4662013 | P44: 91 | Q44: 73 | R44: 52084 | S44: 27240 | T44: 123647184 | U44: 2959769335 | V44: 2500816604 | W44: 3085361 | X44: 15645081 | Y44: 507105112 | Z44: 68036 | AA44: 117290 | AB44: 185326 | AC44: 5705330144 | AD44: 1603397293 | AE44: 35643 | AF44: 1599878 | AG44: 4958246 | AH44: 1712404 | AI44: 1643218802 | AJ44: 8960252410 | AK44: 8159776472 | AL44: 442833129 | AM44: 357642809 | AN44: 8960252410 | AO44: 698772372 | AP44: 34516568 | AQ44: 176385710 | AR44: 156043390 | AS44: 1065718040 | AT44: =+N44+O44 -> 53520052 | AU44: =+U44/V44 -> 1.1835211 | AV44: =+AJ44/Y44 -> 17.669418 | AW44: =+T44/D44 -> 243.8295 | AX44: =+V44/D44 -> 4931.5547 | AY44: =+G44/D44 -> 2537.6985 | AZ44: =SUM(G44:M44)/D44 -> 2684.2872 | BA44: =+L44/D44 -> 116.17335
A45: World B | B45: Totals | D45: =+Y45/1000 -> 166052.05 | E45: 3229 | F45: 4465 | G45: 28102579 | H45: 105749 | I45: 295 | J45: 353673 | K45: 16033 | L45: 254421 | M45: 1344 | N45: 1327700 | O45: 23108 | P45: 89 | Q45: 11 | R45: 9386 | S45: 64 | T45: 845160 | U45: 8257250 | V45: 42415084 | W45: 10007 | X45: 50743 | Y45: 166052055 | Z45: 594 | AA45: 5810 | AB45: 6404 | AC45: 36552133 | AD45: 0 | AE45: 0 | AF45: 451018 | AG45: 44691156 | AH45: 6488950 | AI45: 0 | AJ45: 88183257 | AK45: 80357901 | AL45: 4539690 | AM45: 3285666 | AN45: 88183257 | AO45: 7007941 | AP45: 346165 | AQ45: 1768960 | AR45: 1564949 | AS45: 10688015 | AT45: =+N45+O45 -> 1350808 | AU45: =+U45/V45 -> 0.1946772 | AV45: =+AJ45/Y45 -> 0.53105791 | AW45: =+T45/D45 -> 5.0897292 | AX45: =+V45/D45 -> 255.43245 | AY45: =+G45/D45 -> 169.23957 | AZ45: =SUM(G45:M45)/D45 -> 173.64491 | BA45: =+L45/D45 -> 1.5321762
A46: EU Accession Countries | B46: Totals | D46: =+Y46/1000 -> 74780.543 | E46: 22040 | F46: 19935 | G46: 303280501 | H46: 302294 | I46: 471859 | J46: 150374 | K46: 160119 | L46: 5692236 | M46: 130016 | N46: 9036997 | O46: 277836 | P46: 81 | Q46: 39 | R46: 7488 | S46: 4473 | T46: 13438170 | U46: 378302867 | V46: 125564863 | W46: 204654 | X46: 292610 | Y46: 74780543 | Z46: 26981 | AA46: 11774 | AB46: 38755 | AC46: 157305954 | AD46: 46509895 | AE46: 319834 | AF46: 2865532 | AG46: 10943911 | AH46: 2225612 | AI46: 91125512 | AJ46: 311296252 | AK46: 267639948 | AL46: 10591311 | AM46: 36240517 | AN46: 314471776 | AO46: 22806084 | AP46: 965604 | AQ46: 5099197 | AR46: 7517544 | AS46: 36388431 | AT46: =+N46+O46 -> 9314833 | AU46: =+U46/V46 -> 3.0128083 | AV46: =+AJ46/Y46 -> 4.1627974 | AW46: =+T46/D46 -> 179.70142 | AX46: =+V46/D46 -> 1679.1114 | AY46: =+G46/D46 -> 4055.6071 | AZ46: =SUM(G46:M46)/D46 -> 4147.9693 | BA46: =+L46/D46 -> 76.119212
A47: Europe (Excl. Malta & Cyprus) | B47: Totals | D47: =+Y47/1000 -> 494250.64 | E47: 51260 | F47: 70029 | G47: 1134201344 | H47: 1839103 | I47: 2464216 | J47: 3031672 | K47: 15432757 | L47: 63773589 | M47: 1319015 | N47: 60893533 | O47: 7178215 | P47: 84 | Q47: 65 | R47: 141788 | S47: 76038 | T47: 118791384 | U47: 2316851091 | V47: 2002235070 | W47: 2840082 | X47: 13232911 | Y47: 494250638 | Z47: 83076 | AA47: 94538 | AB47: 177613 | AC47: 4197575878 | AD47: 961271988 | AE47: 7857891 | AF47: 159187989 | AG47: 472254974 | AH47: 36029817 | AI47: 1324743202 | AJ47: 7158921742 | AK47: 6450133646 | AL47: 442538992 | AM47: 282003143 | AN47: 7174675782 | AO47: 531519868 | AP47: 31597031 | AQ47: 139703599 | AR47: 109920637 | AS47: 812741137 | AT47: =+N47+O47 -> 68071748 | AU47: =+U47/V47 -> 1.1571324 | AV47: =+AJ47/Y47 -> 14.484396 | AW47: =+T47/D47 -> 240.34645 | AX47: =+V47/D47 -> 4051.0521 | AY47: =+G47/D47 -> 2294.7898 | AZ47: =SUM(G47:M47)/D47 -> 2472.5546 | BA47: =+L47/D47 -> 129.03087
A48: Eastern Europe | B48: Totals | D48: =+Y48/1000 -> 96204.786 | E48: 27073 | F48: 23858 | G48: 357587662 | H48: 284161 | I48: 625342 | J48: 194482 | K48: 239708 | L48: 6351506 | M48: 156206 | N48: 8542864 | O48: 261753 | P48: 80 | Q48: 42 | R48: 6758 | S48: 4014 | T48: 14161218 | U48: 371629805 | V48: 123343919 | W48: 208506 | X48: 238684 | Y48: 96204786 | Z48: 28107 | AA48: 11090 | AB48: 39196 | AC48: 147646030 | AD48: 41091044 | AE48: 176792 | AF48: 2227361 | AG48: 10458147 | AH48: 2242821 | AI48: 83863545 | AJ48: 287705741 | AK48: 241720059 | AL48: 10322820 | AM48: 36065880 | AN48: 288108759 | AO48: 19921478 | AP48: 960460 | AQ48: 4972543 | AR48: 7364374 | AS48: 33218856 | AT48: =+N48+O48 -> 8804617 | AU48: =+U48/V48 -> 3.012956 | AV48: =+AJ48/Y48 -> 2.9905554 | AW48: =+T48/D48 -> 147.19869 | AX48: =+V48/D48 -> 1282.0975 | AY48: =+G48/D48 -> 3716.9425 | AZ48: =SUM(G48:M48)/D48 -> 3798.5539 | BA48: =+L48/D48 -> 66.020686
A49: Baltic States | B49: Totals | D49: =+Y49/1000 -> 7404.073 | E49: 1532 | F49: 3016 | G49: 45196417 | H49: 39040 | I49: 61706 | J49: 15606 | K49: 4132 | L49: 464852 | M49: 10811 | N49: 1750008 | O49: 24254 | P49: 83 | Q49: 32 | R49: 1256 | S49: 713 | T49: 1854723 | U49: 59798468 | V49: 22660536 | W49: 9376 | X49: 71675 | Y49: 7404073 | Z49: 6156 | AA49: 1804 | AB49: 7960 | AC49: 19983682 | AD49: 6579571 | AE49: 145149 | AF49: 661564 | AG49: 506659 | AH49: 0 | AI49: 9402440 | AJ49: 37279066 | AK49: 39033195 | AL49: 468867 | AM49: 549510 | AN49: 40051572 | AO49: 3986589 | AP49: 74342 | AQ49: 480416 | AR49: 425212 | AS49: 4966560 | AT49: =+N49+O49 -> 1774262 | AU49: =+U49/V49 -> 2.6388814 | AV49: =+AJ49/Y49 -> 5.0349404 | AW49: =+T49/D49 -> 250.50037 | AX49: =+V49/D49 -> 3060.5501 | AY49: =+G49/D49 -> 6104.2641 | AZ49: =SUM(G49:M49)/D49 -> 6184.7802 | BA49: =+L49/D49 -> 62.783282
A50: Central Europe | B50: Totals | D50: =+Y50/1000 -> 248360.84 | E50: 15311 | F50: 26187 | G50: 498805726 | H50: 863815 | I50: 816158 | J50: 833141 | K50: 12075556 | L50: 35841472 | M50: 733042 | N50: 37281171 | O50: 4661009 | P50: 89 | Q50: 74 | R50: 85395 | S50: 46517 | T50: 65054373 | U50: 1337784764 | V50: 1125060599 | W50: 852106 | X50: 815871 | Y50: 248360839 | Z50: 29775 | AA50: 50782 | AB50: 80557 | AC50: 2639784696 | AD50: 578223146 | AE50: 6333288 | AF50: 121857511 | AG50: 343428036 | AH50: 31304036 | AI50: 736460625 | AJ50: 4457391339 | AK50: 3965509527 | AL50: 323006215 | AM50: 181275082 | AN50: 4469790824 | AO50: 374630343 | AP50: 23512053 | AQ50: 98346185 | AR50: 70344439 | AS50: 566833020 | AT50: =+N50+O50 -> 41942180 | AU50: =+U50/V50 -> 1.189078 | AV50: =+AJ50/Y50 -> 17.947239 | AW50: =+T50/D50 -> 261.93491 | AX50: =+V50/D50 -> 4529.9436 | AY50: =+G50/D50 -> 2008.3912 | AZ50: =SUM(G50:M50)/D50 -> 2214.3946 | BA50: =+L50/D50 -> 144.31209
A51: Northern Europe | B51: Totals | D51: =+Y51/1000 -> 24238.94 | E51: 1534 | F51: 4649 | G51: 131282474 | H51: 134721 | I51: 433793 | J51: 100956 | K51: 596123 | L51: 11357075 | M51: 162718 | N51: 6136975 | O51: 1061419 | P51: 88 | Q51: 81 | R51: 12075 | S51: 7407 | T51: 8098760 | U51: 281164661 | V51: 167824177 | W51: 1176481 | X51: 11588235 | Y51: 24238940 | Z51: 7094 | AA51: 9201 | AB51: 16295 | AC51: 587567060 | AD51: 155220687 | AE51: 414356 | AF51: 14203741 | AG51: 48537755 | AH51: 2447753 | AI51: 258893666 | AJ51: 1067285018 | AK51: 1002733449 | AL51: 36121999 | AM51: 28608600 | AN51: 1067464049 | AO51: 38602867 | AP51: 2329523 | AQ51: 11904272 | AR51: 10531370 | AS51: 63368032 | AT51: =+N51+O51 -> 7198394 | AU51: =+U51/V51 -> 1.6753525 | AV51: =+AJ51/Y51 -> 44.031835 | AW51: =+T51/D51 -> 334.12187 | AX51: =+V51/D51 -> 6923.7424 | AY51: =+G51/D51 -> 5416.1805 | AZ51: =SUM(G51:M51)/D51 -> 5943.6535 | BA51: =+L51/D51 -> 468.54669
A52: Southern Europe | B52: Totals | D52: =+Y52/1000 -> 118042 | E52: 5810 | F52: 12319 | G52: 101329065 | H52: 517366 | I52: 527217 | J52: 1887487 | K52: 2517238 | L52: 9758684 | M52: 256238 | N52: 7182515 | O52: 1169780 | P52: 89 | Q52: 73 | R52: 36304 | S52: 17387 | T52: 29622310 | U52: 266473393 | V52: 563345839 | W52: 593613 | X52: 518446 | Y52: 118042000 | Z52: 11944 | AA52: 21661 | AB52: 33605 | AC52: 802594410 | AD52: 180157540 | AE52: 788306 | AF52: 20237812 | AG52: 69324377 | AH52: 35207 | AI52: 236122926 | AJ52: 1309260578 | AK52: 1201137416 | AL52: 72619091 | AM52: 35504071 | AN52: 1309260578 | AO52: 94378591 | AP52: 4720653 | AQ52: 24000183 | AR52: 21255242 | AS52: 144354669 | AT52: =+N52+O52 -> 8352295 | AU52: =+U52/V52 -> 0.47301919 | AV52: =+AJ52/Y52 -> 11.091481 | AW52: =+T52/D52 -> 250.94721 | AX52: =+V52/D52 -> 4772.4186 | AY52: =+G52/D52 -> 858.41535 | AZ52: =SUM(G52:M52)/D52 -> 989.42152 | BA52: =+L52/D52 -> 82.671286

Sheet 2000
A1: Name | B1: Type | C1: Code | D1: Population '000s | E1: Libraries - Total Administrative Units | F1: Libraries - Service Points | G1: Collections - Books & Bound Periodicals | H1: Collections - Current Periodicals - Titles | I1: Collections - Current Periodicals - Subscriptions | J1: Collections - Manuscripts | K1: Collections - Microforms | L1: Collections - Audio-visual Materials | M1: Collections - CD-ROMs | N1: Additions - Books & Bound Periodicals | O1: Additions - Audio-visual Materials | P1: Facilities & Services - Percentage Stock on Open Access | Q1: Facilities & Services - Percentage Catalogue Records Automated | R1: Facilities & Services - Number of Workstations for users | S1: Facilities & Services - Number connected to the internet | T1: Use & Users - Registered Users | U1: Use & Users - Loan Transactions | V1: Use & Users - Number of Visits | W1: Use & Users - Number of virtual referrals and transactions | X1: Use & Users - Number of virtual visits to networked library services | Y1: Use & Users - Potential Total Population Served | Z1: Library Staff FTE - Trained Librarians | AA1: Library Staff FTE - Other Library Staff | AB1: Library Staff FTE - Total Staff | AC1: Recurrent Expenditure (Euros) - Staff | AD1: Recurrent Expenditure (Euros) - Acquisition of Stock | AE1: Recurrent Expenditure (Euros) - Electronic Information | AF1: Recurrent Expenditure (Euros) - Automation | AG1: Recurrent Expenditure (Euros) - Premises and Related Costs | AH1: Recurrent Expenditure (Euros) - New Buildings / Refurbishment | AI1: Recurrent Expenditure (Euros) - Other Expenditure | AJ1: Recurrent Expenditure (Euros) - TOTAL EXPENDITURE | AK1: Income - Public Funding | AL1: Income - Fees & Charges | AM1: Income - Other Income | AN1: Income - TOTAL INCOME | AO1: Capital Expenditure - New Buildings / Refurbishment | AP1: Capital Expenditure - Acquisition of Stock | AQ1: Capital Expenditure - Automation | AR1: Capital Expenditure - Other Capital Expenditure | AS1: Capital Expenditure - TOTAL CAPITAL PAYMENTS | AT1: Additions | AU1: Loans per visit | AV1: Cost per pop | AW1: Users per 1000 pop | AX1: visits per 1000 pop | AY1: Bookstock per 1000 pop | AZ1: Total stock per 1000 pop | BA1: AV materials per 1000 pop
A2: Bulgaria | B2: CEE | C2: C1 | D2: =+Y2/1000 -> 8057 | E2: 3877 | F2: 3877 | G2: 49201077 | H2: 15242 | K2: 65323 | L2: 751137 | N2: 288783 | O2: 5065 | P2: 80 | T2: 899735 | U2: 18061316 | V2: 9443522 | W2: 11892 | X2: 13530 | Y2: 8057000 | Z2: 2979 | AA2: 415 | AB2: 3394 | AC2: 3949524 | AD2: 541955 | AE2: 0 | AF2: 0 | AG2: 0 | AH2: 0 | AI2: 828630 | AJ2: 5320109 | AK2: 4817791 | AL2: 367053 | AM2: 258747 | AN2: 5443591 | AT2: =+N2+O2 -> 293848 | AU2: =+U2/V2 -> 1.9125614 | AV2: =+AJ2/Y2 -> 0.66030892 | AW2: =+T2/D2 -> 111.67122 | AX2: =+V2/D2 -> 1172.0891 | AY2: =+G2/D2 -> 6106.6249 | AZ2: =SUM(G2:M2)/D2 -> 6209.8522 | BA2: =+L2/D2 -> 93.227876
A3: Czech Republic | B3: CEE | C3: C2 | D3: =+Y3/1000 -> 10242 | E3: 6018 | F3: 7140 | G3: 54351497 | H3: 78444 | I3: 89007 | J3: 3951 | K3: 91486 | L3: 592012 | M3: 16898 | N3: 1582143 | O3: 21063 | P3: 75 | Q3: 43 | R3: 1925 | S3: 1083 | T3: 1473800 | U3: 69804524 | V3: 16040601 | W3: 72277 | X3: 50671 | Y3: 10242000 | Z3: 3753 | AA3: 575 | AB3: 4328 | AC3: 17039993 | AD3: 4918543 | AE3: 10396 | AF3: 341645 | AG3: 1269677 | AH3: 362724 | AI3: 20340771 | AJ3: 44283749 | AK3: 42283749 | AL3: 1310907 | AM3: 1434618 | AN3: 45029274 | AO3: 2077990 | AP3: 0 | AQ3: 0 | AR3: 15637419 | AS3: 17715410 | AT3: =+N3+O3 -> 1603206 | AU3: =+U3/V3 -> 4.3517399 | AV3: =+AJ3/Y3 -> 4.3237404 | AW3: =+T3/D3 -> 143.89768 | AX3: =+V3/D3 -> 1566.1591 | AY3: =+G3/D3 -> 5306.7269 | AZ3: =SUM(G3:M3)/D3 -> 5391.8468 | BA3: =+L3/D3 -> 57.802382
A4: Estonia | B4: CEE | C4: C3 | D4: =+Y4/1000 -> 1439.197 | E4: 585 | F4: 711 | G4: 10851579 | H4: 10600 | I4: 18901 | J4: 85 | K4: 1600 | L4: 51600 | M4: 712 | N4: 542106 | O4: 4251 | P4: 72 | Q4: 0 | R4: 362 | S4: 310 | T4: 449495 | U4: 14011606 | V4: 6309760 | Y4: 1439197 | Z4: 1204 | AA4: 278 | AB4: 1482 | AC4: 4466601 | AD4: 3264051 | AE4: 0 | AF4: 440253 | AG4: 0 | AH4: 0 | AI4: 2002671 | AJ4: 10173576 | AK4: 11885650 | AL4: 0 | AM4: 191705 | AN4: 12077356 | AO4: 1529412 | AP4: 0 | AQ4: 263706 | AR4: 85209 | AS4: 1878327 | AT4: =+N4+O4 -> 546357 | AU4: =+U4/V4 -> 2.2206242 | AV4: =+AJ4/Y4 -> 7.0689252 | AW4: =+T4/D4 -> 312.32347 | AX4: =+V4/D4 -> 4384.2226 | AY4: =+G4/D4 -> 7540.0234 | AZ4: =SUM(G4:M4)/D4 -> 7598.0404 | BA4: =+L4/D4 -> 35.853327
A5: Hungary | B5: CEE | C5: C4 | D5: =+Y5/1000 -> 10047 | E5: 2573 | F5: 3132 | G5: 41380150 | H5: 42911 | L5: 1382491 | M5: 44468 | N5: 1069733 | O5: 57400 | T5: 1357449 | U5: 12554527 | V5: 16560559 | W5: 15908 | X5: 45462 | Y5: 10047000 | Z5: 3566 | AA5: 2166 | AB5: 5732 | AC5: 19708549 | AD5: 4628186 | AE5: 0 | AF5: 0 | AG5: 0 | AH5: 0 | AI5: 16659271 | AJ5: 40996006 | AK5: 28084798 | AL5: 0 | AM5: 12911208 | AN5: 40996006 | AT5: =+N5+O5 -> 1127133 | AU5: =+U5/V5 -> 0.75809802 | AV5: =+AJ5/Y5 -> 4.0804226 | AW5: =+T5/D5 -> 135.10988 | AX5: =+V5/D5 -> 1648.3088 | AY5: =+G5/D5 -> 4118.6573 | AZ5: =SUM(G5:M5)/D5 -> 4264.9567 | BA5: =+L5/D5 -> 137.60237
A6: Latvia | B6: CEE | C6: C5 | D6: =+Y6/1000 -> 2384 | E6: 932 | F6: 932 | G6: 12343319 | K6: 933 | L6: 167233 | N6: 293900 | O6: 18600 | T6: 531801 | U6: 20279759 | V6: 6167307 | W6: 0 | X6: 0 | Y6: 2384000 | Z6: 1872 | AA6: 620 | AB6: 2492 | AC6: 5340990 | AD6: 1277610 | AE6: 0 | AF6: 0 | AG6: 0 | AH6: 0 | AI6: 2811237 | AJ6: 9429837 | AK6: 8694303 | AL6: 23142 | AM6: 11946 | AN6: 8729391 | AO6: 0 | AP6: 0 | AQ6: 0 | AR6: 0 | AS6: 0 | AT6: =+N6+O6 -> 312500 | AU6: =+U6/V6 -> 3.2882681 | AV6: =+AJ6/Y6 -> 3.9554685 | AW6: =+T6/D6 -> 223.07089 | AX6: =+V6/D6 -> 2586.9576 | AY6: =+G6/D6 -> 5177.5667 | AZ6: =SUM(G6:M6)/D6 -> 5248.1061 | BA6: =+L6/D6 -> 70.14807
A7: Lithuania | B7: CEE | C7: C6 | D7: =+Y7/1000 -> 3661.14 | E7: 66 | F7: 1453 | G7: 22432006 | J7: 8557 | K7: 1102 | L7: 249805 | M7: 1113 | N7: 1011820 | O7: 3918 | P7: 96 | R7: 93 | S7: 36 | T7: 839499 | U7: 24637643 | V7: 9377600 | W7: 9341 | X7: 3433 | Y7: 3661140 | Z7: 3167 | AA7: 925 | AB7: 4092 | AC7: 9016424 | AD7: 1694692 | AE7: 52993 | AF7: 110946 | AG7: 394814 | AH7: 0 | AI7: 4252728 | AJ7: 15522597 | AK7: 14976990 | AL7: 421765 | AM7: 231840 | AN7: 15630594 | AT7: =+N7+O7 -> 1015738 | AU7: =+U7/V7 -> 2.6272866 | AV7: =+AJ7/Y7 -> 4.2398261 | AW7: =+T7/D7 -> 229.29989 | AX7: =+V7/D7 -> 2561.388 | AY7: =+G7/D7 -> 6127.055 | AZ7: =SUM(G7:M7)/D7 -> 6198.2287 | BA7: =+L7/D7 -> 68.23148
A8: Poland | B8: CEE | C8: C7 | D8: =+Y8/1000 -> 38654 | E8: 9227 | F8: 3564 | G8: 135829107 | K8: 10380 | L8: 2596307 | N8: 3793047 | O8: 121173 | T8: 7220254 | U8: 188976647 | W8: 105819 | X8: 120410 | Y8: 38654000 | Z8: 11134 | AA8: 6689 | AB8: 17823 | AT8: =+N8+O8 -> 3914220 | AU8: =+U8/V8 -> #DIV/0! | AV8: =+AJ8/Y8 -> 0 | AW8: =+T8/D8 -> 186.7919 | AX8: =+V8/D8 -> 0 | AY8: =+G8/D8 -> 3513.9729 | AZ8: =SUM(G8:M8)/D8 -> 3581.4093 | BA8: =+L8/D8 -> 67.167874
A9: Romania | B9: CEE | C9: C8 | D9: =+Y9/1000 -> 22334 | E9: 2849 | F9: 3174 | G9: 48364343 | H9: 8945 | I9: 10293 | J9: 68044 | K9: 9458 | L9: 300166 | M9: 2700 | N9: 977144 | O9: 7235 | P9: 68 | Q9: 8 | R9: 189 | S9: 59 | T9: 2057844 | U9: 35740786 | V9: 16421942 | W9: 3685 | X9: 4327 | Y9: 22334000 | Z9: 4346 | AA9: 774 | AB9: 5119 | AC9: 8146179 | AD9: 1161824 | AE9: 2524 | AF9: 39200 | AG9: 84927 | AH9: 14409 | AI9: 1733064 | AJ9: 11182127 | AK9: 10846663 | AL9: 111822 | AM9: 223642 | AN9: 11182127 | AO9: 785260 | AP9: 50193 | AQ9: 256491 | AR9: 226910 | AS9: 1318854 | AT9: =+N9+O9 -> 984379 | AU9: =+U9/V9 -> 2.1764043 | AV9: =+AJ9/Y9 -> 0.50067731 | AW9: =+T9/D9 -> 92.139518 | AX9: =+V9/D9 -> 735.28889 | AY9: =+G9/D9 -> 2165.503 | AZ9: =SUM(G9:M9)/D9 -> 2183.3952 | BA9: =+L9/D9 -> 13.439867
A10: Slovak Rep | B10: CEE | C10: C9 | D10: =+Y10/1000 -> 5396.15 | E10: 2657 | F10: 2916 | G10: 18695936 | H10: 9786 | I10: 11802 | J10: 631 | K10: 100 | L10: 252656 | M10: 1406 | N10: 345367 | O10: 2280 | P10: 93 | Q10: 26 | R10: 113 | S10: 100 | T10: 697006 | U10: 25017852 | V10: 7172297 | W10: 4273 | X10: 8571 | Y10: 5396150 | Z10: 1025 | AA10: 776 | AB10: 1801 | AC10: 3764903 | AD10: 799238 | AE10: 0 | AF10: 0 | AG10: 0 | AH10: 0 | AI10: 3191927 | AJ10: 7756068 | AK10: 6431570 | AL10: 623036 | AM10: 952076 | AN10: 8006682 | AO10: 349290 | AP10: 0 | AQ10: 151034 | AR10: 92687 | AS10: 593011 | AT10: =+N10+O10 -> 347647 | AU10: =+U10/V10 -> 3.4881227 | AV10: =+AJ10/Y10 -> 1.4373337 | AW10: =+T10/D10 -> 129.16728 | AX10: =+V10/D10 -> 1329.1508 | AY10: =+G10/D10 -> 3464.6806 | AZ10: =SUM(G10:M10)/D10 -> 3515.8987 | BA10: =+L10/D10 -> 46.82153
A11: Slovenia | B11: CEE | C11: C10 | D11: =+Y11/1000 -> 1990.094 | E11: 60 | F11: 283 | G11: 6983185 | H11: 11943 | I11: 19173 | J11: 13461 | K11: 609 | L11: 224973 | M11: 9478 | N11: 388991 | O11: 30369 | P11: 87 | Q11: 77 | R11: 528 | S11: 272 | T11: 491626 | U11: 19351425 | V11: 7423159 | W11: 0 | X11: 0 | Y11: 1990094 | Z11: 643 | AA11: 216 | AB11: 859 | AC11: 11998743 | AD11: 5749316 | AE11: 4843 | AF11: 159164 | AG11: 591511 | AH11: 13585 | AI11: 5214658 | AJ11: 23731821 | AK11: 21119629 | AL11: 2007707 | AM11: 1566564 | AN11: 24693900 | AO11: 2269544 | AP11: 145065 | AQ11: 741305 | AR11: 655812 | AS11: 3811726 | AT11: =+N11+O11 -> 419360 | AU11: =+U11/V11 -> 2.6068989 | AV11: =+AJ11/Y11 -> 11.924975 | AW11: =+T11/D11 -> 247.03657 | AX11: =+V11/D11 -> 3730.0545 | AY11: =+G11/D11 -> 3508.9724 | AZ11: =SUM(G11:M11)/D11 -> 3649.4869 | BA11: =+L11/D11 -> 113.04642
A12: Austria | B12: EU | C12: C11 | D12: =+Y12/1000 -> 8110.244 | E12: 991 | F12: 1873 | G12: 9351946 | P12: 100 | Q12: 61 | R12: 1452 | S12: 1452 | T12: 868648 | U12: 14638735 | V12: 6305411 | W12: 19946 | X12: 21906 | Y12: 8110244 | Z12: 728 | AA12: 580 | AB12: 1308 | AC12: 30251901 | AD12: 5107475 | AE12: 19952 | AF12: 703294 | AG12: 2640554 | AH12: 37381 | AI12: 7639096 | AJ12: 46399652 | AK12: 39527461 | AL12: 2776614 | AM12: 1433341 | AN12: 43737415 | AT12: =+N12+O12 -> 0 | AU12: =+U12/V12 -> 2.3216147 | AV12: =+AJ12/Y12 -> 5.7211167 | AW12: =+T12/D12 -> 107.10504 | AX12: =+V12/D12 -> 777.46255 | AY12: =+G12/D12 -> 1153.1029 | AZ12: =SUM(G12:M12)/D12 -> 1153.1029 | BA12: =+L12/D12 -> 0
A13: België Vlaamse Gemeenschap | B13: België Vlaamse Gemeenschap | C13: C12a | D13: =+Y13/1000 -> 6232.321 | E13: 320 | F13: 903 | G13: 21241805 | I13: 43443 | L13: 2051533 | M13: 94315 | N13: 1378323 | O13: 258468 | Q13: 98 | T13: 1658175 | U13: 52166885 | Y13: 6232321 | Z13: 1521 | AA13: 913 | AB13: 2434 | AC13: 88345956 | AD13: 16885140 | AE13: 3806378 | AF13: 0 | AG13: 0 | AH13: 27069661 | AI13: 20903469 | AJ13: 157010604 | AK13: 54557803 | AL13: 8627125 | AM13: 914522 | AN13: 64099451 | AV13: =+AJ13/Y13 -> 25.192958 | AW13: =+T13/D13 -> 266.06059 | AY13: =+G13/D13 -> 3408.3297 | AZ13: =SUM(G13:M13)/D13 -> 3759.6099
A14: Belgique-Communauté française | B14: Belgique-Communauté française | C14: C12b | D14: =+Y14/1000 -> 3987.679 | E14: 175 | F14: 572 | G14: 12243069 | I14: 96659 | L14: 91161 | M14: 8332 | T14: 756992 | Y14: 3987679 | AW14: =+T14/D14 -> 189.83273 | AY14: =+G14/D14 -> 3070.2243 | AZ14: =SUM(G14:M14)/D14 -> 3119.4138
A15: Belgium | B15: EU | C15: C12 | D15: =+Y15/1000 -> 10220 | E15: 495 | F15: 1475 | G15: 33484874 | I15: 140102 | L15: 2142694 | M15: 102647 | N15: 1602000 | O15: 211166 | Q15: 98 | T15: 2415167 | W15: 41168 | X15: 34834 | Y15: 10220000 | Z15: 2463 | AA15: 1297 | AB15: 3760 | AC15: 126001459 | AD15: 28159370 | AE15: 151105 | AF15: 3879229 | AG15: 13288071 | AH15: 6297 | AI15: 29699376 | AJ15: 201184906 | AK15: 194264948 | AL15: 8093499 | AM15: 5625211 | AN15: 207983658 | AT15: =+N15+O15 -> 1813166 | AU15: =+U15/V15 -> #DIV/0! | AV15: =+AJ15/Y15 -> 19.685412 | AW15: =+T15/D15 -> 236.31771 | AX15: =+V15/D15 -> 0 | AY15: =+G15/D15 -> 3276.4065 | AZ15: =SUM(G15:M15)/D15 -> 3509.8158 | BA15: =+L15/D15 -> 209.65695
A16: Denmark | B16: EU | C16: C13 | D16: =+Y16/1000 -> 5349.11 | E16: 245 | F16: 800 | G16: 27634549 | H16: 1688 | I16: 205550 | K16: 369 | L16: 2756369 | M16: 98401 | N16: 1660108 | O16: 297177 | R16: 3343 | S16: 2218 | T16: 1845698 | U16: 72464549 | V16: 30533524 | W16: 7280437 | X16: 11211602 | Y16: 5349110 | Z16: 2283 | AA16: 2787 | AB16: 5070 | AC16: 194778050 | AD16: 48800761 | AE16: 9585 | AF16: 535168 | AG16: 1236422 | AH16: 0 | AI16: 87186903 | AJ16: 332546890 | AK16: 293737414 | AL16: 26651389 | AM16: 12141194 | AN16: 332529998 | AO16: 0 | AP16: 0 | AQ16: 0 | AR16: 0 | AS16: 0 | AT16: =+N16+O16 -> 1957285 | AU16: =+U16/V16 -> 2.3732783 | AV16: =+AJ16/Y16 -> 62.168639 | AW16: =+T16/D16 -> 345.04768 | AX16: =+V16/D16 -> 5708.1503 | AY16: =+G16/D16 -> 5166.1957 | AZ16: =SUM(G16:M16)/D16 -> 5738.6978 | BA16: =+L16/D16 -> 515.29488
A17: Eire | B17: EU | C17: C15 | D17: =+Y17/1000 -> 3720 | E17: 32 | F17: 357 | G17: 11270238 | H17: 12426 | I17: 2204 | J17: 12481 | K17: 19840 | L17: 327891 | M17: 3202 | N17: 909438 | O17: 34111 | P17: 89 | Q17: 70 | R17: 1084 | S17: 668 | T17: 894606 | U17: 12268767 | V17: 20082704 | W17: 1820 | X17: 4606 | Y17: 3720000 | Z17: 291 | AA17: 1092 | AB17: 1383 | AC17: 32435319 | AD17: 9215175 | AE17: 0 | AF17: 1523093 | AG17: 7859332 | AH17: 0 | AI17: 6404022 | AJ17: 57436941 | AK17: 50565429 | AL17: 1480618 | AM17: 5797751 | AN17: 57843799 | AO17: 3120637 | AP17: 3652805 | AQ17: 1642007 | AR17: 1106164 | AS17: 9521614 | AT17: =+N17+O17 -> 943549 | AU17: =+U17/V17 -> 0.61091211 | AV17: =+AJ17/Y17 -> 15.440038 | AW17: =+T17/D17 -> 240.48548 | AX17: =+V17/D17 -> 5398.5763 | AY17: =+G17/D17 -> 3029.6339 | AZ17: =SUM(G17:M17)/D17 -> 3131.2586 | BA17: =+L17/D17 -> 88.142742
A18: Finland | B18: EU | C18: C16 | D18: =+Y18/1000 -> 5145.596 | E18: 436 | F18: 1138 | G18: 37013045 | I18: 97600 | L18: 3884200 | M18: 22219 | N18: 1606835 | O18: 309996 | P18: 99 | Q18: 99 | R18: 2500 | S18: 1256 | T18: 2417055 | U18: 102197190 | V18: 63990752 | W18: 184680 | X18: 192684 | Y18: 5145596 | Z18: 1500 | AA18: 2674 | AB18: 4174 | AC18: 130057045 | AD18: 40789913 | AE18: 0 | AF18: 0 | AG18: 0 | AH18: 0 | AI18: 60983022 | AJ18: 231829980 | AK18: 213163872 | AL18: 4399221 | AM18: 14266888 | AN18: 231829980 | AO18: 18378394 | AP18: 1174709 | AQ18: 6002968 | AR18: 5310654 | AS18: 30866725 | AT18: =+N18+O18 -> 1916831 | AU18: =+U18/V18 -> 1.5970619 | AV18: =+AJ18/Y18 -> 45.054058 | AW18: =+T18/D18 -> 469.73276 | AX18: =+V18/D18 -> 12436.023 | AY18: =+G18/D18 -> 7193.1502 | AZ18: =SUM(G18:M18)/D18 -> 7971.2951 | BA18: =+L18/D18 -> 754.85911
A19: France | B19: EU | C19: C17 | D19: =+Y19/1000 -> 59400 | E19: 3881 | F19: 3884 | G19: 144456108 | I19: 223647 | L19: 9670922 | M19: 216654 | N19: 6827452 | O19: 942839 | P19: 82 | T19: 12025650 | U19: 302627916 | W19: 18621 | X19: 21328 | Y19: 59400000 | Z19: 7031 | AA19: 14498 | AB19: 21529 | AC19: 646073217 | AD19: 117360248 | AE19: 613120 | AF19: 15740293 | AG19: 53917450 | AH19: 25549 | AI19: 161083516 | AJ19: 994813393 | AK19: 899963958 | AL19: 23852331 | AM19: 5493134 | AN19: 929309423 | AO19: 186846019 | AP19: 7611358 | AQ19: 38895372 | AR19: 34409621 | AS19: 267762370 | AT19: =+N19+O19 -> 7770291 | AU19: =+U19/V19 -> #DIV/0! | AV19: =+AJ19/Y19 -> 16.7477 | AW19: =+T19/D19 -> 202.45202 | AX19: =+V19/D19 -> 0 | AY19: =+G19/D19 -> 2431.921 | AZ19: =SUM(G19:M19)/D19 -> 2602.1436 | BA19: =+L19/D19 -> 162.81013
A20: Greece | B20: EU | C20: C18 | D20: =+Y20/1000 -> 10586 | E20: 718 | F20: 829 | G20: 9702367 | H20: 161033 | I20: 125025 | J20: 1509096 | K20: 317503 | L20: 102507 | M20: 12623 | N20: 296284 | O20: 12264 | P20: 89 | Q20: 70 | R20: 4032 | S20: 2025 | T20: 2875762 | U20: 1952957 | V20: 2440868 | W20: 8727 | X20: 12210 | Y20: 10586000 | Z20: 1029 | AA20: 805 | AB20: 1834 | AC20: 40693056 | AD20: 9094266 | AE20: 48800 | AF20: 1252824 | AG20: 4291476 | AH20: 2034 | AI20: 12821192 | AJ20: 68203648 | AT20: =+N20+O20 -> 308548 | AU20: =+U20/V20 -> 0.80010758 | AV20: =+AJ20/Y20 -> 6.4428158 | AW20: =+T20/D20 -> 271.65709 | AX20: =+V20/D20 -> 230.5751 | AY20: =+G20/D20 -> 916.52815 | AZ20: =SUM(G20:M20)/D20 -> 1126.9747 | BA20: =+L20/D20 -> 9.6832609
A21: Iceland | B21: EFTA | C21: C19 | D21: =+Y21/1000 -> 279 | E21: 137 | F21: 143 | G21: 2065660 | I21: 2087 | J21: 759 | K21: 3178 | L21: 67321 | M21: 743 | N21: 75879 | O21: 4640 | T21: 86073 | U21: 2224533 | V21: 859249 | W21: 867 | X21: 1852 | Y21: 279000 | Z21: 80 | AA21: 207 | AB21: 299 | AC21: 4582198 | AD21: 1589323 | AE21: 0 | AF21: 90603 | AG21: 645061 | AH21: 216354 | AI21: 1196842 | AJ21: 8320381 | AK21: 7589487 | AL21: 593092 | AM21: 152676 | AN21: 8335255 | AT21: =+N21+O21 -> 80519 | AU21: =+U21/V21 -> 2.5889271 | AV21: =+AJ21/Y21 -> 29.822154 | AW21: =+T21/D21 -> 308.50538 | AX21: =+V21/D21 -> 3079.7455 | AY21: =+G21/D21 -> 7403.7993 | AZ21: =SUM(G21:M21)/D21 -> 7669.3477 | BA21: =+L21/D21 -> 241.29391
A22: Italy | B22: EU | C22: C20 | D22: =+Y22/1000 -> 57535 | E22: 84 | F22: 6028 | G22: 42029422 | N22: 5558455 | W22: 450786 | X22: 495070 | Y22: 57535000 | Z22: 5984 | AA22: 17856 | AB22: 23840 | AT22: =+N22+O22 -> 5558455 | AU22: =+U22/V22 -> #DIV/0! | AV22: =+AJ22/Y22 -> 0 | AW22: =+T22/D22 -> 0 | AX22: =+V22/D22 -> 0 | AY22: =+G22/D22 -> 730.50182 | AZ22: =SUM(G22:M22)/D22 -> 730.50182 | BA22: =+L22/D22 -> 0
A23: Liechtenstein | B23: EFTA | C23: C21 | D23: =+Y23/1000 -> 32.528 | E23: 3 | F23: 3 | G23: 24441 | N23: 5865 | S23: 4 | U23: 78920 | W23: 1344 | X23: 994 | Y23: 32528 | Z23: 2 | AA23: 3 | AB23: 5 | AT23: =+N23+O23 -> 5865 | AU23: =+U23/V23 -> #DIV/0! | AV23: =+AJ23/Y23 -> 0 | AW23: =+T23/D23 -> 0 | AX23: =+V23/D23 -> 0 | AY23: =+G23/D23 -> 751.38342 | AZ23: =SUM(G23:M23)/D23 -> 751.38342 | BA23: =+L23/D23 -> 0
A24: Luxembourg | B24: EU | C24: C22 | D24: =+Y24/1000 -> 436 | E24: 9 | F24: 13 | G24: 253876 | H24: 244 | I24: 372 | J24: 0 | K24: 0 | L24: 1179 | M24: 296 | N24: 67838 | O24: 179 | P24: 90 | Q24: 43 | R24: 75 | S24: 16 | T24: 30356 | U24: 153385 | V24: 75204 | W24: 2089 | X24: 3687 | Y24: 436000 | Z24: 18 | AA24: 5 | AB24: 23 | AC24: 1073730 | AD24: 247339 | AE24: 401 | AF24: 20 | AG24: 37341 | AH24: 40152 | AI24: 31693 | AJ24: 1430676 | AO24: 8543 | AP24: 435 | AQ24: 2209 | AR24: 1715 | AS24: 12902 | AT24: =+N24+O24 -> 68017 | AU24: =+U24/V24 -> 2.0395857 | AV24: =+AJ24/Y24 -> 3.281367 | AW24: =+T24/D24 -> 69.623853 | AX24: =+V24/D24 -> 172.48624 | AY24: =+G24/D24 -> 582.2844 | AZ24: =SUM(G24:M24)/D24 -> 587.08028 | BA24: =+L24/D24 -> 2.7041284
A25: Netherlands | B25: EU | C25: C23 | D25: =+Y25/1000 -> 15840 | E25: 492 | F25: 1074 | G25: 42161911 | N25: 3515165 | U25: 149530000 | W25: 121053 | X25: 132945 | Y25: 15840000 | Z25: 2510 | AA25: 5898 | AB25: 8408 | AC25: 269200000 | AD25: 53532129 | AE25: 286909 | AF25: 35312000 | AG25: 69186000 | AH25: 12930 | AI25: 70686032 | AJ25: 498216000 | AK25: 331069000 | AL25: 61631000 | AM25: 105516000 | AN25: 498216000 | AT25: =+N25+O25 -> 3515165 | AU25: =+U25/V25 -> #DIV/0! | AV25: =+AJ25/Y25 -> 31.45303 | AW25: =+T25/D25 -> 0 | AX25: =+V25/D25 -> 0 | AY25: =+G25/D25 -> 2661.7368 | AZ25: =SUM(G25:M25)/D25 -> 2661.7368 | BA25: =+L25/D25 -> 0
A26: Norway | B26: EFTA | C26: C24 | D26: =+Y26/1000 -> 4503.436 | E26: 435 | F26: 1046 | G26: 20916571 | H26: 20978 | I26: 44805 | J26: 36735 | K26: 293423 | L26: 1244109 | M26: 12719 | N26: 946657 | O26: 132325 | P26: 82 | Q26: 76 | R26: 1477 | S26: 1072 | T26: 1314521 | U26: 23452990 | V26: 22084283 | W26: 113594 | X26: 142746 | Y26: 4503436 | Z26: 934 | AA26: 962 | AB26: 1896 | AC26: 71043116 | AD26: 16564858 | AE26: 0 | AF26: 3147538 | AG26: 9742878 | AH26: 0 | AI26: 11664659 | AJ26: 112163049 | AK26: 102127650 | AL26: 7980921 | AM26: 2054478 | AN26: 112163049 | AT26: =+N26+O26 -> 1078982 | AU26: =+U26/V26 -> 1.0619765 | AV26: =+AJ26/Y26 -> 24.906105 | AW26: =+T26/D26 -> 291.8929 | AX26: =+V26/D26 -> 4903.8741 | AY26: =+G26/D26 -> 4644.5805 | AZ26: =SUM(G26:M26)/D26 -> 5011.5823 | BA26: =+L26/D26 -> 276.25773
A27: Portugal | B27: EU | C27: C25 | D27: =+Y27/1000 -> 9901 | E27: 165 | F27: 278 | G27: 7182218 | K27: 2198 | L27: 184420 | N27: 513084 | O27: 31016 | R27: 643 | T27: 3150844 | U27: 1637369 | W27: 626 | X27: 2 | Y27: 9901000 | Z27: 844 | AA27: 565 | AB27: 1409 | AC27: 13020660 | AD27: 2730447 | AE27: 27 | AF27: 727 | AG27: 3419 | AH27: 2345 | AI27: 2561252 | AJ27: 18318877 | AK27: 25321556 | AL27: 342212 | AM27: 1887 | AN27: 25665652 | AO27: 4012345 | AP27: 0 | AQ27: 0 | AR27: 3057918 | AS27: 7070264 | AT27: =+N27+O27 -> 544100 | AU27: =+U27/V27 -> #DIV/0! | AV27: =+AJ27/Y27 -> 1.8502047 | AW27: =+T27/D27 -> 318.23493 | AX27: =+V27/D27 -> 0 | AY27: =+G27/D27 -> 725.40329 | AZ27: =SUM(G27:M27)/D27 -> 744.25169 | BA27: =+L27/D27 -> 18.626401
A28: Spain | B28: EU | C28: C26 | D28: =+Y28/1000 -> 39218 | E28: 4722 | F28: 5209 | G28: 41291671 | H28: 113759 | I28: 158516 | J28: 33445 | K28: 266645 | L28: 1432434 | M28: 121228 | N28: 2330100 | O28: 181377 | P28: 89 | Q28: 70 | R28: 3255 | S28: 803 | T28: 7172882 | U28: 26146158 | V28: 204131947 | W28: 125104 | X28: 5128 | Y28: 39218000 | Z28: 4139 | AA28: 2469 | AB28: 6608 | AC28: 121041037 | AD28: 27939755 | AE28: 0 | AF28: 0 | AG28: 0 | AH28: 0 | AI28: 24216136 | AJ28: 173196928 | AK28: 156522058 | AL28: 10994920 | AM28: 5675786 | AN28: 173192764 | AT28: =+N28+O28 -> 2511477 | AU28: =+U28/V28 -> 0.1280846 | AV28: =+AJ28/Y28 -> 4.4162611 | AW28: =+T28/D28 -> 182.8977 | AX28: =+V28/D28 -> 5205.0576 | AY28: =+G28/D28 -> 1052.8755 | AZ28: =SUM(G28:M28)/D28 -> 1107.086 | BA28: =+L28/D28 -> 36.524912
A29: Sweden | B29: EU | C29: C27 | D29: =+Y29/1000 -> 8894 | E29: 290 | F29: 1596 | G29: 44162401 | H29: 68255 | I29: 106262 | J29: 0 | K29: 0 | L29: 2574724 | M29: 0 | N29: 2005404 | O29: 182627 | P29: 87 | U29: 81156238 | V29: 47681646 | W29: 0 | X29: 0 | Y29: 8894000 | Z29: 2304 | AA29: 2587 | AB29: 4891 | AC29: 167033680 | AD29: 44282699 | AE29: 408289 | AF29: 10481772 | AG29: 35904696 | AH29: 17013 | AI29: 85079007 | AJ29: 343207156 | AK29: 310171679 | AL29: 21788065 | AM29: 11247412 | AN29: 343207156 | AO29: 8537937 | AP29: 545727 | AQ29: 2788762 | AR29: 2467138 | AS29: 14339565 | AT29: =+N29+O29 -> 2188031 | AU29: =+U29/V29 -> 1.7020435 | AV29: =+AJ29/Y29 -> 38.588617 | AW29: =+T29/D29 -> 0 | AX29: =+V29/D29 -> 5361.1025 | AY29: =+G29/D29 -> 4965.415 | AZ29: =SUM(G29:M29)/D29 -> 5274.5269 | BA29: =+L29/D29 -> 289.48999
A30: Switzerland | B30: EFTA | C30: C28 | D30: =+Y30/1000 -> 7206.1 | E30: 42 | F30: 2093 | G30: 28484968 | N30: 1354590 | U30: 6225230 | V30: 33229533 | W30: 301573 | X30: 223277 | Y30: 7206100 | Z30: 1841 | AA30: 3476 | AB30: 5317 | AT30: =+N30+O30 -> 1354590 | AU30: =+U30/V30 -> 0.18734028 | AV30: =+AJ30/Y30 -> 0 | AW30: =+T30/D30 -> 0 | AX30: =+V30/D30 -> 4611.3061 | AY30: =+G30/D30 -> 3952.8966 | AZ30: =SUM(G30:M30)/D30 -> 3952.8966 | BA30: =+L30/D30 -> 0
A31: UK | B31: EU | C31: C29 | D31: =+Y31/1000 -> 59974.2 | E31: 208 | F31: 4610 | G31: 118745000 | H31: 73000 | I31: 109000 | J31: 136000 | K31: 6752000 | L31: 7416000 | M31: 141000 | N31: 11042000 | O31: 1384000 | P31: 89 | R31: 16700 | S31: 8600 | T31: 34657000 | U31: 444548000 | V31: 323932000 | W31: 0 | X31: 0 | Y31: 59974200 | Z31: 6200 | AA31: 19400 | AB31: 25600 | AC31: 789825619 | AD31: 197912321 | AE31: 1597132 | AF31: 48678292 | AG31: 157878096 | AH31: 0 | AI31: 235752934 | AJ31: 1431644394 | AK31: 1293943937 | AL31: 84639831 | AM31: 36955671 | AN31: 1415539439 | AO31: 36000311 | AP31: 3008015 | AQ31: 15026181 | AR31: 4080482 | AS31: 58114989 | AT31: =+N31+O31 -> 12426000 | AU31: =+U31/V31 -> 1.3723498 | AV31: =+AJ31/Y31 -> 23.871004 | AW31: =+T31/D31 -> 577.86515 | AX31: =+V31/D31 -> 5401.1892 | AY31: =+G31/D31 -> 1979.9347 | AZ31: =SUM(G31:M31)/D31 -> 2223.8229 | BA31: =+L31/D31 -> 123.65317
A32: Germany | B32: EU | C32: C31 | D32: =+Y32/1000 -> 82163.475 | E32: 9417 | F32: 11332 | G32: 107772013 | I32: 139192 | L32: 9485250 | P32: 94 | T32: 8708712 | U32: 311619520 | V32: 332934647 | W32: 363080 | X32: 398746 | Y32: 82163475 | Z32: 8337 | AA32: 6661 | AB32: 14998 | AC32: 477535730 | AD32: 91699007 | AE32: 0 | AF32: 0 | AG32: 0 | AH32: 0 | AI32: 153311306 | AJ32: 722546043 | AK32: 639349381 | AL32: 57157968 | AM32: 26038642 | AN32: 722545992 | AO32: 25714289 | AP32: 1643604 | AQ32: 8399106 | AR32: 7430448 | AS32: 43187447 | AT32: =+N32+O32 -> 0 | AU32: =+U32/V32 -> 0.93597804 | AV32: =+AJ32/Y32 -> 8.7940054 | AW32: =+T32/D32 -> 105.9925 | AX32: =+V32/D32 -> 4052.1004 | AY32: =+G32/D32 -> 1311.6779 | AZ32: =SUM(G32:M32)/D32 -> 1428.8156 | BA32: =+L32/D32 -> 115.44363
A33: USA | B33: World - A | C33: C50 | D33: =+Y33/1000 -> 272861 | E33: 9143 | F33: 16391 | G33: 740318283 | I33: 1937947 | J33: 0 | L33: 45985974 | M33: 1148788 | N33: 16072993 | O33: 3647960 | P33: 100 | S33: 15521 | U33: 1737674662 | V33: 1111372500 | W33: 1403899 | X33: 7118811 | Y33: 272861000 | Z33: 41220 | AA33: 83834 | AB33: 125054 | AC33: 3856553363 | AD33: 925092240 | AE33: 12288 | AF33: 347255 | AG33: 1631775 | AH33: 1119074 | AI33: 1222336470 | AJ33: 6007092465 | AK33: 5946742797 | AL33: 318804276 | AM33: 269335122 | AN33: 6534882194 | AT33: =+N33+O33 -> 19720953 | AU33: =+U33/V33 -> 1.5635394 | AV33: =+AJ33/Y33 -> 22.015211 | AW33: =+T33/D33 -> 0 | AX33: =+V33/D33 -> 4073.0354 | AY33: =+G33/D33 -> 2713.17 | AZ33: =SUM(G33:M33)/D33 -> 2893.0151 | BA33: =+L33/D33 -> 168.5326
A34: Turkey | B34: World - B | C34: C42 | D34: =+Y34/1000 -> 66565 | E34: 1403 | F34: 1939 | G34: 12181330 | I34: 118 | J34: 158197 | K34: 6783 | L34: 110204 | M34: 540 | Q34: 11 | S34: 23 | T34: 386790 | U34: 3926314 | V34: 19903256 | W34: 8937 | X34: 45317 | Y34: 66565000 | Z34: 271 | AA34: 2652 | AB34: 2923 | AC34: 14548749 | AD34: 0 | AE34: 0 | AF34: 179517 | AG34: 17788303 | AH34: 2582780 | AI34: 0 | AJ34: 35099349 | AK34: 31638500 | AL34: 1766063 | AM34: 1278214 | AN34: 34682777 | AT34: =+N34+O34 -> 0 | AU34: =+U34/V34 -> 0.19726993 | AV34: =+AJ34/Y34 -> 0.52729436 | AW34: =+T34/D34 -> 5.8107113 | AX34: =+V34/D34 -> 299.00482 | AY34: =+G34/D34 -> 182.99902 | AZ34: =SUM(G34:M34)/D34 -> 187.14297 | BA34: =+L34/D34 -> 1.6555848
A35: Australia | B35: World - A | C35: C70 | D35: =+Y35/1000 -> 19111 | Y35: 19111000 | AT35: =+N35+O35 -> 0 | AU35: =+U35/V35 -> #DIV/0! | AV35: =+AJ35/Y35 -> 0 | AW35: =+T35/D35 -> 0 | AX35: =+V35/D35 -> 0 | AY35: =+G35/D35 -> 0 | AZ35: =SUM(G35:M35)/D35 -> 0 | BA35: =+L35/D35 -> 0
A36: Japan | B36: World - A | C36: C41 | D36: =+Y36/1000 -> 126920 | E36: 1687 | F36: 2635 | G36: 287111133 | N36: 19459470 | T36: 37275313 | U36: 527748609 | W36: 964048 | X36: 4888445 | Y36: 126920000 | Z36: 11559 | AA36: 15105 | AB36: 26664 | AC36: 762697794 | AD36: 346736256 | AE36: 14816 | AF36: 823375 | AG36: 2121263 | AH36: 302171 | AI36: 127906312 | AJ36: 1240601987 | AK36: 1118276748 | AL36: 62422265 | AM36: 45179053 | AN36: 1225878065 | AT36: =+N36+O36 -> 19459470 | AU36: =+U36/V36 -> #DIV/0! | AV36: =+AJ36/Y36 -> 9.7746769 | AW36: =+T36/D36 -> 293.6914 | AX36: =+V36/D36 -> 0 | AY36: =+G36/D36 -> 2262.1426 | AZ36: =SUM(G36:M36)/D36 -> 2262.1426 | BA36: =+L36/D36 -> 0
A37: Korea | B37: World - A | C37: C40 | D37: =+Y37/1000 -> 48800 | Y37: 48800000 | AT37: =+N37+O37 -> 0 | AU37: =+U37/V37 -> #DIV/0! | AV37: =+AJ37/Y37 -> 0 | AW37: =+T37/D37 -> 0 | AX37: =+V37/D37 -> 0 | AY37: =+G37/D37 -> 0 | AZ37: =SUM(G37:M37)/D37 -> 0 | BA37: =+L37/D37 -> 0
A38: Canada | B38: World - A | C38: C51 | D38: =+Y38/1000 -> 31281 | E38: 2739 | F38: 910 | G38: 75032608 | I38: 150814 | U38: 331565367 | Y38: 31281000 | Z38: 6733 | AA38: 6616 | AB38: 13349 | AC38: 229533941 | AD38: 49614746 | AE38: 0 | AF38: 0 | AG38: 0 | AH38: 0 | AI38: 74500417 | AJ38: 353649103 | AK38: 322607590 | AL38: 18007972 | AM38: 13033541 | AN38: 353649103 | AO38: 17655562 | AP38: 872114 | AQ38: 4456657 | AR38: 3942678 | AS38: 26927011 | AT38: =+N38+O38 -> 0 | AU38: =+U38/V38 -> #DIV/0! | AV38: =+AJ38/Y38 -> 11.305556 | AW38: =+T38/D38 -> 0 | AX38: =+V38/D38 -> 0 | AY38: =+G38/D38 -> 2398.664 | AZ38: =SUM(G38:M38)/D38 -> 2403.4852 | BA38: =+L38/D38 -> 0
A39: New Zealand | B39: World - A | C39: C71 | D39: =+Y39/1000 -> 3900 | Y39: 3900000 | AT39: =+N39+O39 -> 0 | AU39: =+U39/V39 -> #DIV/0! | AV39: =+AJ39/Y39 -> 0 | AW39: =+T39/D39 -> 0 | AX39: =+V39/D39 -> 0 | AY39: =+G39/D39 -> 0 | AZ39: =SUM(G39:M39)/D39 -> 0 | BA39: =+L39/D39 -> 0
A40: Mexico | B40: World - B | C40: C72 | D40: =+Y40/1000 -> 97400 | Y40: 97400000 | AT40: =+N40+O40 -> 0 | AU40: =+U40/V40 -> #DIV/0! | AV40: =+AJ40/Y40 -> 0 | AW40: =+T40/D40 -> 0 | AX40: =+V40/D40 -> 0 | AY40: =+G40/D40 -> 0 | AZ40: =SUM(G40:M40)/D40 -> 0 | BA40: =+L40/D40 -> 0
A41: CEE | B41: Totals | D41: =+Y41/1000 -> 104204.58 | E41: 28844 | F41: 27182 | G41: 400432199 | H41: 313034 | I41: 644829 | J41: 209198 | K41: 184475 | L41: 6568380 | M41: 135047 | N41: 10293034 | O41: 271354 | P41: 80 | Q41: 37 | R41: 5280 | S41: 2893 | T41: 16018509 | U41: 428436085 | V41: 145664894 | W41: 223195 | X41: 246404 | Y41: 104204581 | Z41: 33689 | AA41: 13434 | AB41: 47122 | AC41: 148785357 | AD41: 44686382 | AE41: 132191 | AF41: 2045504 | AG41: 4408381 | AH41: 741476 | AI41: 99224615 | AJ41: 300023909 | AK41: 258047600 | AL41: 9860288 | AM41: 33946842 | AN41: 301854730 | AO41: 21124575 | AP41: 892387 | AQ41: 4974992 | AR41: 19849638 | AS41: 46841595 | AT41: =+N41+O41 -> 10564388 | AU41: =+U41/V41 -> 2.9412446 | AV41: =+AJ41/Y41 -> 2.8791816 | AW41: =+T41/D41 -> 153.72174 | AX41: =+V41/D41 -> 1397.8742 | AY41: =+G41/D41 -> 3842.7504 | AZ41: =SUM(G41:M41)/D41 -> 3920.0499 | BA41: =+L41/D41 -> 63.033505
A42: EU | B42: Totals | D42: =+Y42/1000 -> 376492.62 | E42: 22185 | F42: 40496 | G42: 676511639 | H42: 1458315 | I42: 1669307 | J42: 2716491 | K42: 14766107 | L42: 50830993 | M42: 1060708 | N42: 49466500 | O42: 6166330 | P42: 88 | Q42: 73 | R42: 104295 | S42: 53353 | T42: 99574113 | U42: 1834338107 | V42: 1833750970 | W42: 2198103 | X42: 12534748 | Y42: 376492625 | Z42: 45661 | AA42: 79174 | AB42: 124835 | AC42: 3627935387 | AD42: 808484241 | AE42: 3841564 | AF42: 136237737 | AG42: 408349619 | AH42: 173130 | AI42: 1123005351 | AJ42: 6108027029 | AK42: 5409037561 | AL42: 361156650 | AM42: 258032655 | AN42: 6028226863 | AO42: 401570239 | AP42: 23758922 | AQ42: 103878198 | AR42: 82224921 | AS42: 611432284 | AT42: =+N42+O42 -> 55632830 | AU42: =+U42/V42 -> 1.0003202 | AV42: =+AJ42/Y42 -> 16.223497 | AW42: =+T42/D42 -> 264.47826 | AX42: =+V42/D42 -> 4870.6159 | AY42: =+G42/D42 -> 1796.8789 | AZ42: =SUM(G42:M42)/D42 -> 1989.4508 | BA42: =+L42/D42 -> 135.01192
A43: EFTA | B43: Totals | D43: =+Y43/1000 -> 12000.371 | E43: 612 | F43: 3279 | G43: 51516655 | H43: 62815 | I43: 124703 | J43: 104370 | K43: 828278 | L43: 3059685 | M43: 23751 | N43: 2396343 | O43: 333323 | P43: 82 | Q43: 80 | R43: 3609 | S43: 2159 | T43: 3594933 | U43: 31915693 | V43: 56277920 | W43: 417378 | X43: 368869 | Y43: 12000371 | Z43: 2857 | AA43: 4648 | AB43: 7517 | AC43: 259818323 | AD43: 82007075 | AE43: 0 | AF43: 6830564 | AG43: 36284013 | AH43: 9441251 | AI43: 61080726 | AJ43: 455461952 | AK43: 305491318 | AL43: 23857171 | AM43: 6137404 | AN43: 335485893 | AO43: 24245599 | AP43: 1197635 | AQ43: 6120130 | AR43: 5414303 | AS43: 36977668 | AT43: =+N43+O43 -> 2729666 | AU43: =+U43/V43 -> 0.56710861 | AV43: =+AJ43/Y43 -> 37.953989 | AW43: =+T43/D43 -> 299.56849 | AX43: =+V43/D43 -> 4689.6817 | AY43: =+G43/D43 -> 4292.9219 | AZ43: =SUM(G43:M43)/D43 -> 4643.2112 | BA43: =+L43/D43 -> 254.96587
A44: World A | B44: Totals | D44: =+Y44/1000 -> 502873 | E44: 15960 | F44: 23357 | G44: 1265230868 | H44: 576323 | I44: 2347670 | J44: 204297 | K44: 11094064 | L44: 57307261 | M44: 1363969 | N44: 47331647 | O44: 4615537 | P44: 91 | Q44: 70 | R44: 41960 | S44: 22548 | T44: 120956789 | U44: 2907850094 | V44: 2438329431 | W44: 3016882 | X44: 15297839 | Y44: 502873000 | Z44: 67174 | AA44: 115817 | AB44: 182991 | AC44: 5467270029 | AD44: 1532776482 | AE44: 33838 | AF44: 1516498 | AG44: 4706262 | AH44: 1631802 | AI44: 1577004895 | AJ44: 8584939805 | AK44: 8274239302 | AL44: 448725249 | AM44: 363367380 | AN44: 9086331929 | AO44: 618114664 | AP44: 30532399 | AQ44: 156025909 | AR44: 138031654 | AS44: 942704630 | AT44: =+N44+O44 -> 51947184 | AU44: =+U44/V44 -> 1.1925583 | AV44: =+AJ44/Y44 -> 17.071785 | AW44: =+T44/D44 -> 240.53148 | AX44: =+V44/D44 -> 4848.7977 | AY44: =+G44/D44 -> 2516.0048 | AZ44: =SUM(G44:M44)/D44 -> 2660.959 | BA44: =+L44/D44 -> 113.95971
A45: World B | B45: Totals | D45: =+Y45/1000 -> 163965 | E45: 3160 | F45: 4368 | G45: 27438144 | H45: 103472 | I45: 266 | J45: 356335 | K45: 15279 | L45: 248232 | M45: 1216 | N45: 1296309 | O45: 22545 | P45: 89 | Q45: 11 | R45: 7537 | S45: 52 | T45: 871235 | U45: 8843925 | V45: 44831591 | W45: 20130 | X45: 102075 | Y45: 163965000 | Z45: 610 | AA45: 5974 | AB45: 6584 | AC45: 32770697 | AD45: 0 | AE45: 0 | AF45: 404358 | AG45: 40067712 | AH45: 5817648 | AI45: 0 | AJ45: 79060415 | AK45: 71323484 | AL45: 4029377 | AM45: 2916321 | AN45: 78269181 | AO45: 5939340 | AP45: 293380 | AQ45: 1499221 | AR45: 1326319 | AS45: 9058260 | AT45: =+N45+O45 -> 1318854 | AU45: =+U45/V45 -> 0.19726993 | AV45: =+AJ45/Y45 -> 0.48217861 | AW45: =+T45/D45 -> 5.3135425 | AX45: =+V45/D45 -> 273.42171 | AY45: =+G45/D45 -> 167.34147 | AZ45: =SUM(G45:M45)/D45 -> 171.76192 | BA45: =+L45/D45 -> 1.5139329
A46: EU Accession Countries | B46: Totals | D46: =+Y46/1000 -> 74896.962 | E46: 22124 | F46: 20139 | G46: 304068766 | H46: 293928 | I46: 459186 | J46: 149500 | K46: 120334 | L46: 5548276 | M46: 108137 | N46: 9084074 | O46: 263131 | P46: 80 | Q46: 37 | R46: 4911 | S46: 2728 | T46: 13425665 | U46: 375815577 | V46: 124503588 | W46: 210058 | X46: 228862 | Y46: 74896962 | Z46: 26473 | AA46: 12315 | AB46: 38788 | AC46: 139860678 | AD46: 43704152 | AE46: 130553 | AF46: 2029050 | AG46: 4401387 | AH46: 727146 | AI46: 97381461 | AJ46: 288234429 | AK46: 246697628 | AL46: 9647454 | AM46: 33596686 | AN46: 289941768 | AO46: 20210407 | AP46: 833780 | AQ46: 4675377 | AR46: 19637589 | AS46: 45357155 | AT46: =+N46+O46 -> 9347205 | AU46: =+U46/V46 -> 3.018512 | AV46: =+AJ46/Y46 -> 3.8484128 | AW46: =+T46/D46 -> 179.25513 | AX46: =+V46/D46 -> 1662.3316 | AY46: =+G46/D46 -> 4059.8278 | AZ46: =SUM(G46:M46)/D46 -> 4149.0084 | BA46: =+L46/D46 -> 74.078786
A47: Europe (Excl. Malta & Cyprus) | B47: Totals | D47: =+Y47/1000 -> 492697.58 | E47: 51641 | F47: 70957 | G47: 1128460493 | H47: 1834164 | I47: 2438839 | J47: 3030059 | K47: 15778860 | L47: 60459058 | M47: 1219506 | N47: 62155877 | O47: 6771007 | P47: 83 | Q47: 63 | R47: 113184 | S47: 58405 | T47: 119187555 | U47: 2294689885 | V47: 2035693784 | W47: 2838676 | X47: 13150021 | Y47: 492697577 | Z47: 82207 | AA47: 97256 | AB47: 179474 | AC47: 4036539067 | AD47: 935177698 | AE47: 3973755 | AF47: 145113805 | AG47: 449042013 | AH47: 10355857 | AI47: 1283310692 | AJ47: 6863512890 | AK47: 5972576479 | AL47: 394874109 | AM47: 298116901 | AN47: 6665567486 | AO47: 446940413 | AP47: 25848944 | AQ47: 114973320 | AR47: 107488862 | AS47: 695251548 | AT47: =+N47+O47 -> 68926884 | AU47: =+U47/V47 -> 1.1272274 | AV47: =+AJ47/Y47 -> 13.930478 | AW47: =+T47/D47 -> 241.90814 | AX47: =+V47/D47 -> 4131.7309 | AY47: =+G47/D47 -> 2290.3715 | AZ47: =SUM(G47:M47)/D47 -> 2462.405 | BA47: =+L47/D47 -> 122.71028
A48: Eastern Europe | B48: Totals | D48: =+Y48/1000 -> 96720.244 | E48: 27261 | F48: 24086 | G48: 354805295 | H48: 279796 | I48: 582134 | J48: 194435 | K48: 180840 | L48: 6099742 | M48: 125992 | N48: 8445208 | O48: 244585 | P48: 79 | Q48: 40 | R48: 4763 | S48: 2523 | T48: 14197714 | U48: 369507077 | V48: 123810227 | W48: 213854 | X48: 242971 | Y48: 96720244 | Z48: 27446 | AA48: 11611 | AB48: 39056 | AC48: 129961342 | AD48: 38450029 | AE48: 79198 | AF48: 1494305 | AG48: 4013567 | AH48: 741476 | AI48: 90157979 | AJ48: 264897899 | AK48: 222490657 | AL48: 9415381 | AM48: 33511351 | AN48: 265417389 | AO48: 18462815 | AP48: 836454 | AQ48: 4425456 | AR48: 19511564 | AS48: 43236292 | AT48: =+N48+O48 -> 8689793 | AU48: =+U48/V48 -> 2.9844633 | AV48: =+AJ48/Y48 -> 2.7388051 | AW48: =+T48/D48 -> 146.79154 | AX48: =+V48/D48 -> 1280.086 | AY48: =+G48/D48 -> 3668.3664 | AZ48: =SUM(G48:M48)/D48 -> 3745.5265 | BA48: =+L48/D48 -> 63.065825
A49: Baltic States | B49: Totals | D49: =+Y49/1000 -> 7484.337 | E49: 1583 | F49: 3096 | G49: 45626904 | H49: 33238 | I49: 62695 | J49: 14763 | K49: 3635 | L49: 468638 | M49: 9055 | N49: 1847826 | O49: 26769 | P49: 81 | Q49: 29 | R49: 517 | S49: 370 | T49: 1820795 | U49: 58929008 | V49: 21854667 | W49: 9341 | X49: 3433 | Y49: 7484337 | Z49: 6243 | AA49: 1823 | AB49: 8066 | AC49: 18824015 | AD49: 6236353 | AE49: 52993 | AF49: 551199 | AG49: 394814 | AH49: 0 | AI49: 9066636 | AJ49: 35126010 | AK49: 35556943 | AL49: 444907 | AM49: 435491 | AN49: 36437341 | AO49: 2661760 | AP49: 55933 | AQ49: 549536 | AR49: 338074 | AS49: 3605304 | AT49: =+N49+O49 -> 1874595 | AU49: =+U49/V49 -> 2.6964038 | AV49: =+AJ49/Y49 -> 4.6932694 | AW49: =+T49/D49 -> 243.28073 | AX49: =+V49/D49 -> 2920.0538 | AY49: =+G49/D49 -> 6096.3188 | AZ49: =SUM(G49:M49)/D49 -> 6175.4205 | BA49: =+L49/D49 -> 62.615834
A50: Central Europe | B50: Totals | D50: =+Y50/1000 -> 247102.55 | E50: 15570 | F50: 26714 | G50: 496005375 | H50: 857283 | I50: 812585 | J50: 861470 | K50: 12468502 | L50: 33884245 | M50: 707463 | N50: 36856685 | O50: 4426972 | P50: 89 | Q50: 71 | R50: 67088 | S50: 34958 | T50: 66042161 | U50: 1313971201 | V50: 1159920996 | W50: 870694 | X50: 842323 | Y50: 247102547 | Z50: 29421 | AA50: 52910 | AB50: 82331 | AC50: 2555914514 | AD50: 566885627 | AE50: 2668619 | AF50: 109464881 | AG50: 330641608 | AH50: 8787310 | AI50: 712541633 | AJ50: 4286904190 | AK50: 3649675334 | AL50: 255213457 | AM50: 190962861 | AN50: 4095851653 | AO50: 305374837 | AP50: 18624282 | AQ50: 77748686 | AR50: 58163100 | AS50: 459910907 | AT50: =+N50+O50 -> 41283657 | AU50: =+U50/V50 -> 1.1328109 | AV50: =+AJ50/Y50 -> 17.348685 | AW50: =+T50/D50 -> 267.26621 | AX50: =+V50/D50 -> 4694.0876 | AY50: =+G50/D50 -> 2007.2856 | AZ50: =SUM(G50:M50)/D50 -> 2207.9777 | BA50: =+L50/D50 -> 137.12625
A51: Northern Europe | B51: Totals | D51: =+Y51/1000 -> 24150.449 | E51: 1538 | F51: 4717 | G51: 131817241 | H51: 134448 | I51: 456412 | J51: 102953 | K51: 603592 | L51: 10530351 | M51: 134395 | N51: 6308235 | O51: 928195 | P51: 88 | Q51: 79 | R51: 10667 | S51: 6243 | T51: 8069562 | U51: 281429520 | V51: 165106257 | W51: 1159544 | X51: 11548884 | Y51: 24150449 | Z51: 7101 | AA51: 9217 | AB51: 16330 | AC51: 568169559 | AD51: 152227885 | AE51: 417874 | AF51: 14218844 | AG51: 47590367 | AH51: 793263 | AI51: 246396000 | AJ51: 1029813793 | AK51: 928339966 | AL51: 61517891 | AM51: 39885732 | AN51: 1029743589 | AO51: 35414461 | AP51: 2140209 | AQ51: 10936848 | AR51: 9675516 | AS51: 58167036 | AT51: =+N51+O51 -> 7236430 | AU51: =+U51/V51 -> 1.7045358 | AV51: =+AJ51/Y51 -> 42.6416 | AW51: =+T51/D51 -> 334.13714 | AX51: =+V51/D51 -> 6836.5709 | AY51: =+G51/D51 -> 5458.1694 | AZ51: =SUM(G51:M51)/D51 -> 5953.4873 | BA51: =+L51/D51 -> 436.03127
A52: Southern Europe | B52: Totals | D52: =+Y52/1000 -> 117240 | E52: 5689 | F52: 12344 | G52: 100205678 | H52: 529399 | I52: 525013 | J52: 1856438 | K52: 2522291 | L52: 9476082 | M52: 242601 | N52: 8697923 | O52: 1144486 | P52: 89 | Q52: 70 | R52: 30149 | S52: 14311 | T52: 29057323 | U52: 270853079 | V52: 565001637 | W52: 585243 | X52: 512410 | Y52: 117240000 | Z52: 11996 | AA52: 21695 | AB52: 33691 | AC52: 763669637 | AD52: 171377804 | AE52: 755071 | AF52: 19384576 | AG52: 66401657 | AH52: 33808 | AI52: 225148444 | AJ52: 1246770998 | AK52: 1136513579 | AL52: 68282473 | AM52: 33321466 | AN52: 1238117514 | AO52: 85026540 | AP52: 4192066 | AQ52: 21312794 | AR52: 19800608 | AS52: 130332009 | AT52: =+N52+O52 -> 9842409 | AU52: =+U52/V52 -> 0.47938459 | AV52: =+AJ52/Y52 -> 10.634348 | AW52: =+T52/D52 -> 247.84479 | AX52: =+V52/D52 -> 4819.1883 | AY52: =+G52/D52 -> 854.70554 | AZ52: =SUM(G52:M52)/D52 -> 983.94321 | BA52: =+L52/D52 -> 80.826356

Sheet 1999
A1: Name | B1: Type | C1: Code | D1: Population '000s | E1: Libraries - Total Administrative Units | F1: Libraries - Service Points | G1: Collections - Books & Bound Periodicals | H1: Collections - Current Periodicals - Titles | I1: Collections - Current Periodicals - Subscriptions | J1: Collections - Manuscripts | K1: Collections - Microforms | L1: Collections - Audio-visual Materials | M1: Collections - CD-ROMs | N1: Additions - Books & Bound Periodicals | O1: Additions - Audio-visual Materials | P1: Facilities & Services - Percentage Stock on Open Access | Q1: Facilities & Services - Percentage Catalogue Records Automated | R1: Facilities & Services - Number of Workstations for users | S1: Facilities & Services - Number connected to the internet | T1: Use & Users - Registered Users | U1: Use & Users - Loan Transactions | V1: Use & Users - Number of Visits | W1: Use & Users - Number of virtual referrals and transactions | X1: Use & Users - Number of virtual visits to networked library services | Y1: Use & Users - Potential Total Population Served | Z1: Library Staff FTE - Trained Librarians | AA1: Library Staff FTE - Other Library Staff | AB1: Library Staff FTE - Total Staff | AC1: Recurrent Expenditure (Euros) - Staff | AD1: Recurrent Expenditure (Euros) - Acquisition of Stock | AE1: Recurrent Expenditure (Euros) - Electronic Information | AF1: Recurrent Expenditure (Euros) - Automation | AG1: Recurrent Expenditure (Euros) - Premises and Related Costs | AH1: Recurrent Expenditure (Euros) - New Buildings / Refurbishment | AI1: Recurrent Expenditure (Euros) - Other Expenditure | AJ1: Recurrent Expenditure (Euros) - TOTAL EXPENDITURE | AK1: Income - Public Funding | AL1: Income - Fees & Charges | AM1: Income - Other Income | AN1: Income - TOTAL INCOME | AO1: Capital Expenditure - New Buildings / Refurbishment | AP1: Capital Expenditure - Acquisition of Stock | AQ1: Capital Expenditure - Automation | AR1: Capital Expenditure - Other Capital Expenditure | AS1: Capital Expenditure - TOTAL CAPITAL PAYMENTS | AT1: Additions | AU1: Loans per visit | AV1: Cost per pop | AW1: Users per 1000 pop | AX1: visits per 1000 pop | AY1: Bookstock per 1000 pop | AZ1: Total stock per 1000 pop | BA1: AV materials per 1000 pop
A2: Bulgaria | B2: CEE | C2: C1 | D2: =+Y2/1000 -> 8413.05 | E2: 4017 | F2: 4017 | G2: 39348678 | H2: 7435 | K2: 4176 | L2: 462859 | N2: 198804 | O2: 3300 | P2: 80 | T2: 752297 | U2: 14955904 | V2: 8138239 | W2: 9943 | X2: 11313 | Y2: 8413050 | Z2: 2230 | AA2: 1287 | AB2: 3517 | AC2: 3188198 | AD2: 458455 | AE2: 0 | AF2: 0 | AG2: 0 | AH2: 0 | AI2: 384791 | AJ2: 4031444 | AK2: 3575301 | AL2: 270965 | AM2: 257463 | AN2: 4103729 | AT2: =+N2+O2 -> 202104 | AU2: =+U2/V2 -> 1.8377322 | AV2: =+AJ2/Y2 -> 0.47918935 | AW2: =+T2/D2 -> 89.420246 | AX2: =+V2/D2 -> 967.33515 | AY2: =+G2/D2 -> 4677.1002 | AZ2: =SUM(G2:M2)/D2 -> 4733.4971 | BA2: =+L2/D2 -> 55.016789
A3: Czech Republic | B3: CEE | C3: C2 | D3: =+Y3/1000 -> 10265.811 | E3: 6075 | F3: 7197 | G3: 53983820 | H3: 78627 | I3: 84491 | J3: 3950 | K3: 128064 | L3: 554760 | M3: 10275 | N3: 1702948 | O3: 21112 | P3: 76 | Q3: 43 | R3: 1313 | S3: 609 | T3: 1461693 | U3: 69508548 | V3: 16077888 | W3: 72445 | X3: 50789 | Y3: 10265811 | Z3: 3723 | AA3: 595 | AB3: 4318 | AC3: 13524960 | AD3: 4684327 | AE3: 9901 | AF3: 325376 | AG3: 1209216 | AH3: 345451 | AI3: 10660232 | AJ3: 30759463 | AK3: 34268975 | AL3: 2090184 | AM3: 2287435 | AN3: 38646593 | AO3: 6642746 | AP3: 0 | AQ3: 0 | AR3: 7364323 | AS3: 14007068 | AT3: =+N3+O3 -> 1724060 | AU3: =+U3/V3 -> 4.3232387 | AV3: =+AJ3/Y3 -> 2.9963013 | AW3: =+T3/D3 -> 142.38456 | AX3: =+V3/D3 -> 1566.1586 | AY3: =+G3/D3 -> 5258.6026 | AZ3: =SUM(G3:M3)/D3 -> 5342.392 | BA3: =+L3/D3 -> 54.039569
A4: Estonia | B4: CEE | C4: C3 | D4: =+Y4/1000 -> 1445.58 | E4: 597 | F4: 731 | G4: 10776779 | H4: 10500 | I4: 18085 | J4: 76 | N4: 538455 | O4: 5782 | P4: 72 | Q4: 0 | R4: 146 | S4: 120 | T4: 440797 | U4: 15760713 | V4: 5875066 | Y4: 1445580 | Z4: 1199 | AA4: 284 | AB4: 1483 | AC4: 4381678 | AD4: 3088764 | AE4: 0 | AF4: 586754 | AG4: 0 | AH4: 0 | AI4: 1746899 | AJ4: 9804096 | AK4: 11145450 | AL4: 0 | AM4: 282547 | AN4: 11427997 | AO4: 1307838 | AP4: 0 | AQ4: 0 | AR4: 313168 | AS4: 1621006 | AT4: =+N4+O4 -> 544237 | AU4: =+U4/V4 -> 2.6826444 | AV4: =+AJ4/Y4 -> 6.7821193 | AW4: =+T4/D4 -> 304.92743 | AX4: =+V4/D4 -> 4064.1583 | AY4: =+G4/D4 -> 7454.9862 | AZ4: =SUM(G4:M4)/D4 -> 7474.8129 | BA4: =+L4/D4 -> 0
A5: Hungary | B5: CEE | C5: C4 | D5: =+Y5/1000 -> 10043.244 | E5: 2685 | F5: 3808 | G5: 43206541 | H5: 50863 | L5: 1275491 | M5: 21522 | N5: 1099313 | O5: 24242 | T5: 1460013 | V5: 17248796 | W5: 17110 | X5: 48897 | Y5: 10043244 | Z5: 3549 | AA5: 2203 | AB5: 5752 | AC5: 18462337 | AD5: 5507843 | AE5: 0 | AF5: 0 | AG5: 0 | AH5: 0 | AI5: 11521748 | AJ5: 35491928 | AN5: 35491928 | AT5: =+N5+O5 -> 1123555 | AU5: =+U5/V5 -> 0 | AV5: =+AJ5/Y5 -> 3.5339108 | AW5: =+T5/D5 -> 145.37265 | AX5: =+V5/D5 -> 1717.4526 | AY5: =+G5/D5 -> 4302.0503 | AZ5: =SUM(G5:M5)/D5 -> 4436.2575 | BA5: =+L5/D5 -> 126.9999
A6: Latvia | B6: CEE | C6: C5 | D6: =+Y6/1000 -> 2470.7 | E6: 974 | F6: 974 | G6: 12877002 | L6: 157123 | N6: 284154 | O6: 11900 | T6: 524670 | U6: 19905930 | V6: 5982838 | W6: 0 | X6: 0 | Y6: 2470700 | Z6: 1850 | AA6: 613 | AB6: 2463 | AC6: 4328912 | AD6: 1072409 | AE6: 0 | AF6: 0 | AG6: 0 | AH6: 0 | AI6: 2482015 | AJ6: 7883335 | AK6: 7508172 | AL6: 11057 | AM6: 9039 | AN6: 7528268 | AS6: 206710 | AT6: =+N6+O6 -> 296054 | AU6: =+U6/V6 -> 3.3271718 | AV6: =+AJ6/Y6 -> 3.1907293 | AW6: =+T6/D6 -> 212.35682 | AX6: =+V6/D6 -> 2421.5154 | AY6: =+G6/D6 -> 5211.8841 | AZ6: =SUM(G6:M6)/D6 -> 5275.4786 | BA6: =+L6/D6 -> 63.594528
A7: Lithuania | B7: CEE | C7: C6 | D7: =+Y7/1000 -> 3650.188 | E7: 61 | F7: 1452 | G7: 22666196 | J7: 6969 | K7: 1094 | L7: 252007 | M7: 550 | N7: 907124 | O7: 5294 | P7: 96 | R7: 66 | S7: 0 | T7: 816629 | U7: 23519915 | V7: 8470596 | W7: 9087 | X7: 3339 | Y7: 3650188 | Z7: 3103 | AA7: 1010 | AB7: 4113 | AC7: 7580659 | AD7: 1292996 | AE7: 0 | AF7: 0 | AG7: 0 | AH7: 0 | AI7: 3707352 | AJ7: 12581006 | AK7: 12731006 | AL7: 291071 | AM7: 147078 | AN7: 13169156 | AT7: =+N7+O7 -> 912418 | AU7: =+U7/V7 -> 2.7766541 | AV7: =+AJ7/Y7 -> 3.4466734 | AW7: =+T7/D7 -> 223.72245 | AX7: =+V7/D7 -> 2320.5917 | AY7: =+G7/D7 -> 6209.5969 | AZ7: =SUM(G7:M7)/D7 -> 6280.9959 | BA7: =+L7/D7 -> 69.039458
A8: Poland | B8: CEE | C8: C7 | D8: =+Y8/1000 -> 38654 | Y8: 38654000 | AT8: =+N8+O8 -> 0 | AU8: =+U8/V8 -> #DIV/0! | AV8: =+AJ8/Y8 -> 0 | AW8: =+T8/D8 -> 0 | AX8: =+V8/D8 -> 0 | AY8: =+G8/D8 -> 0 | AZ8: =SUM(G8:M8)/D8 -> 0 | BA8: =+L8/D8 -> 0
A9: Romania | B9: CEE | C9: C8 | D9: =+Y9/1000 -> 22418.402 | E9: 2884 | F9: 3157 | P9: 63 | Q9: 8 | R9: 99 | T9: 2069011 | U9: 35157339 | V9: 15952999 | W9: 3699 | X9: 4343 | Y9: 22418402 | Z9: 4216 | AA9: 765 | AB9: 4981 | AC9: 6516943 | AD9: 929459 | AE9: 2019 | AF9: 31360 | AG9: 67941 | AH9: 11527 | AI9: 1386452 | AJ9: 8945701 | AK9: 8677330 | AL9: 89457 | AM9: 178914 | AN9: 8945701 | AS9: 1055083 | AT9: =+N9+O9 -> 0 | AU9: =+U9/V9 -> 2.2038075 | AV9: =+AJ9/Y9 -> 0.39903384 | AW9: =+T9/D9 -> 92.290744 | AX9: =+V9/D9 -> 711.60286 | AY9: =+G9/D9 -> 0 | AZ9: =SUM(G9:M9)/D9 -> 0 | BA9: =+L9/D9 -> 0
A10: Slovak Rep | B10: CEE | C10: C9 | D10: =+Y10/1000 -> 5230.85 | E10: 2696 | F10: 3212 | G10: 19223111 | H10: 9930 | I10: 13250 | L10: 260767 | M10: 596 | N10: 341641 | O10: 2341 | P10: 95 | Q10: 51 | T10: 725993 | U10: 25421924 | V10: 7385109 | W10: 4451 | X10: 8927 | Y10: 5230850 | Z10: 1067 | AA10: 833 | AB10: 1900 | AC10: 3513882 | AD10: 795843 | AE10: 0 | AF10: 0 | AG10: 0 | AH10: 0 | AI10: 2860324 | AJ10: 7170050 | AK10: 5977069 | AL10: 491617 | AM10: 752267 | AN10: 7220953 | AS10: 351142 | AT10: =+N10+O10 -> 343982 | AU10: =+U10/V10 -> 3.4423221 | AV10: =+AJ10/Y10 -> 1.3707237 | AW10: =+T10/D10 -> 138.79064 | AX10: =+V10/D10 -> 1411.8373 | AY10: =+G10/D10 -> 3674.9498 | AZ10: =SUM(G10:M10)/D10 -> 3729.3469 | BA10: =+L10/D10 -> 49.851745
A11: Slovenia | B11: CEE | C11: C10 | D11: =+Y11/1000 -> 1987.755 | E11: 60 | F11: 299 | G11: 6758312 | H11: 16061 | J11: 13557 | K11: 670 | L11: 207786 | M11: 5411 | N11: 403706 | O11: 26483 | P11: 88 | Q11: 74 | R11: 311 | S11: 0 | T11: 461287 | U11: 16713284 | V11: 7114981 | W11: 0 | X11: 0 | Y11: 1987755 | Z11: 643 | AA11: 201 | AB11: 844 | AC11: 11334147 | AD11: 6700863 | AE11: 5399 | AF11: 177420 | AG11: 659360 | AH11: 15143 | AI11: 5812798 | AJ11: 24705130 | AK11: 22636815 | AL11: 3149833 | AM11: 1 | AN11: 25786649 | AS11: 7301947 | AT11: =+N11+O11 -> 430189 | AU11: =+U11/V11 -> 2.3490272 | AV11: =+AJ11/Y11 -> 12.428659 | AW11: =+T11/D11 -> 232.06431 | AX11: =+V11/D11 -> 3579.4054 | AY11: =+G11/D11 -> 3399.9723 | AZ11: =SUM(G11:M11)/D11 -> 3522.4648 | BA11: =+L11/D11 -> 104.533
A12: Austria | B12: EU | C12: C11 | D12: =+Y12/1000 -> 8108.036 | E12: 1019 | F12: 1953 | G12: 9335001 | P12: 100 | Q12: 59 | R12: 332 | T12: 874552 | U12: 15619720 | V12: 9541362 | W12: 20082 | X12: 22055 | Y12: 8108036 | Z12: 727 | AA12: 953 | AB12: 1680 | AC12: 23643560 | AD12: 4970318 | AE12: 19952 | AF12: 655681 | AG12: 2436750 | AH12: 55964 | AI12: 21481960 | AJ12: 53264185 | AN12: 53264136 | AT12: =+N12+O12 -> 0 | AU12: =+U12/V12 -> 1.6370535 | AV12: =+AJ12/Y12 -> 6.5693079 | AW12: =+T12/D12 -> 107.86237 | AX12: =+V12/D12 -> 1176.7784 | AY12: =+G12/D12 -> 1151.327 | AZ12: =SUM(G12:M12)/D12 -> 1151.327 | BA12: =+L12/D12 -> 0
A13: België Vlaamse Gemeenschap | B13: België Vlaamse Gemeenschap | C13: C12a
A14: Belgique-Communauté française | B14: Belgique-Communauté française | C14: C12b
A15: Belgium | B15: EU | C15: C12 | D15: =+Y15/1000 -> 9950.95 | Y15: 9950950 | AT15: =+N15+O15 -> 0 | AU15: =+U15/V15 -> #DIV/0! | AV15: =+AJ15/Y15 -> 0 | AW15: =+T15/D15 -> 0 | AX15: =+V15/D15 -> 0 | AY15: =+G15/D15 -> 0 | AZ15: =SUM(G15:M15)/D15 -> 0 | BA15: =+L15/D15 -> 0
A16: Denmark | B16: EU | C16: C13 | D16: =+Y16/1000 -> 5329.921 | E16: 252 | F16: 833 | G16: 29044153 | I16: 165630 | L16: 2604772 | M16: 60171 | N16: 1809785 | O16: 284839 | R16: 2057 | S16: 1271 | U16: 72996911 | W16: 857317 | X16: 11171383 | Y16: 5329921 | Z16: 2367 | AA16: 2811 | AB16: 5178 | AC16: 190643299 | AD16: 46971071 | AE16: 9821 | AF16: 545796 | AG16: 1406136 | AH16: 0 | AI16: 84786094 | AJ16: 324362217 | AK16: 288098224 | AL16: 21024905 | AM16: 15239089 | AN16: 324362217 | AO16: 0 | AP16: 0 | AQ16: 0 | AR16: 0 | AS16: 0 | AT16: =+N16+O16 -> 2094624 | AU16: =+U16/V16 -> #DIV/0! | AV16: =+AJ16/Y16 -> 60.856853 | AW16: =+T16/D16 -> 0 | AX16: =+V16/D16 -> 0 | AY16: =+G16/D16 -> 5449.2652 | AZ16: =SUM(G16:M16)/D16 -> 5980.3374 | BA16: =+L16/D16 -> 488.70743
A17: Eire | B17: EU | C17: C15 | D17: =+Y17/1000 -> 3596.5 | E17: 32 | F17: 352 | G17: 11352868 | I17: 2690 | K17: 16945 | L17: 292247 | M17: 2854 | N17: 847203 | O17: 34623 | R17: 824 | T17: 848079 | U17: 12509804 | W17: 1760 | X17: 4453 | Y17: 3596500 | Z17: 259 | AA17: 1072 | AB17: 1331 | AC17: 29790269 | AD17: 7418274 | AE17: 0 | AF17: 1399241 | AG17: 6291566 | AH17: 0 | AI17: 6212494 | AJ17: 51111844 | AK17: 46893475 | AL17: 1401113 | AM17: 4977063 | AN17: 53271651 | AO17: 4916133 | AP17: 2950923 | AQ17: 1917270 | AR17: 179728 | AS17: 9964055 | AT17: =+N17+O17 -> 881826 | AU17: =+U17/V17 -> #DIV/0! | AV17: =+AJ17/Y17 -> 14.211551 | AW17: =+T17/D17 -> 235.80676 | AX17: =+V17/D17 -> 0 | AY17: =+G17/D17 -> 3156.6434 | AZ17: =SUM(G17:M17)/D17 -> 3244.1552 | BA17: =+L17/D17 -> 81.258724
A18: Finland | B18: EU | C18: C16 | D18: =+Y18/1000 -> 5134.021 | E18: 436 | F18: 1151 | G18: 36925298 | I18: 96815 | L18: 3701060 | N18: 1556934 | O18: 309806 | P18: 95 | Q18: 95 | R18: 2300 | T18: 2417196 | U18: 99053526 | V18: 63764831 | W18: 184691 | X18: 192695 | Y18: 5134021 | Z18: 1500 | AA18: 2656 | AB18: 4156 | AC18: 122133979 | AD18: 38304994 | AE18: 0 | AF18: 0 | AG18: 0 | AH18: 0 | AI18: 57267942 | AJ18: 217706914 | AK18: 200177944 | AL18: 4131221 | AM18: 13397750 | AN18: 217706914 | AS18: 28986326 | AT18: =+N18+O18 -> 1866740 | AU18: =+U18/V18 -> 1.5534194 | AV18: =+AJ18/Y18 -> 42.404757 | AW18: =+T18/D18 -> 470.81927 | AX18: =+V18/D18 -> 12420.057 | AY18: =+G18/D18 -> 7192.2764 | AZ18: =SUM(G18:M18)/D18 -> 7932.0231 | BA18: =+L18/D18 -> 720.88914
A19: France | B19: EU | C19: C17 | D19: =+Y19/1000 -> 59336.462 | E19: 3755 | F19: 3884 | G19: 137006200 | I19: 213997 | L19: 9137500 | M19: 108890 | N19: 6868900 | O19: 910360 | P19: 73 | T19: 12025650 | U19: 292235000 | W19: 18231 | X19: 20882 | Y19: 59336462 | Z19: 7031 | AA19: 14498 | AB19: 21529 | AC19: 606714482 | AD19: 110210671 | AE19: 438443 | AF19: 14221671 | AG19: 48622169 | AH19: 31105 | AI19: 158289670 | AJ19: 938528211 | AK19: 848654977 | AL19: 22375610 | AM19: 5153049 | AN19: 876183636 | AS19: 251450305 | AT19: =+N19+O19 -> 7779260 | AU19: =+U19/V19 -> #DIV/0! | AV19: =+AJ19/Y19 -> 15.817057 | AW19: =+T19/D19 -> 202.66881 | AX19: =+V19/D19 -> 0 | AY19: =+G19/D19 -> 2308.9715 | AZ19: =SUM(G19:M19)/D19 -> 2468.4078 | BA19: =+L19/D19 -> 153.99469
A20: Greece | B20: EU | C20: C18 | D20: =+Y20/1000 -> 10249.5 | Y20: 10249500 | AT20: =+N20+O20 -> 0 | AU20: =+U20/V20 -> #DIV/0! | AV20: =+AJ20/Y20 -> 0 | AW20: =+T20/D20 -> 0 | AX20: =+V20/D20 -> 0 | AY20: =+G20/D20 -> 0 | AZ20: =SUM(G20:M20)/D20 -> 0 | BA20: =+L20/D20 -> 0
A21: Iceland | B21: EFTA | C21: C19 | D21: =+Y21/1000 -> 255.312 | E21: 137 | F21: 143 | G21: 2065660 | I21: 2087 | J21: 759 | K21: 3178 | L21: 67321 | M21: 743 | N21: 75879 | O21: 4640 | R21: 31 | S21: 30 | T21: 85986 | U21: 2225001 | V21: 858380 | W21: 866 | X21: 1850 | Y21: 255312 | AC21: 4440264 | AD21: 1540094 | AE21: 0 | AF21: 87797 | AG21: 625080 | AH21: 209652 | AI21: 1159770 | AJ21: 8062657 | AK21: 7354402 | AL21: 574721 | AM21: 147973 | AN21: 8077096 | AT21: =+N21+O21 -> 80519 | AU21: =+U21/V21 -> 2.5920932 | AV21: =+AJ21/Y21 -> 31.579624 | AW21: =+T21/D21 -> 336.78793 | AX21: =+V21/D21 -> 3362.0825 | AY21: =+G21/D21 -> 8090.7282 | AZ21: =SUM(G21:M21)/D21 -> 8380.9143 | BA21: =+L21/D21 -> 263.6813
A22: Italy | B22: EU | C22: C20 | D22: =+Y22/1000 -> 57064.5 | Y22: 57064500 | AT22: =+N22+O22 -> 0 | AU22: =+U22/V22 -> #DIV/0! | AV22: =+AJ22/Y22 -> 0 | AW22: =+T22/D22 -> 0 | AX22: =+V22/D22 -> 0 | AY22: =+G22/D22 -> 0 | AZ22: =SUM(G22:M22)/D22 -> 0 | BA22: =+L22/D22 -> 0
A23: Liechtenstein | B23: EFTA | C23: C21 | D23: =+Y23/1000 -> 31.451 | Y23: 31451 | AT23: =+N23+O23 -> 0 | AU23: =+U23/V23 -> #DIV/0! | AV23: =+AJ23/Y23 -> 0 | AW23: =+T23/D23 -> 0 | AX23: =+V23/D23 -> 0 | AY23: =+G23/D23 -> 0 | AZ23: =SUM(G23:M23)/D23 -> 0 | BA23: =+L23/D23 -> 0
A24: Luxembourg | B24: EU | C24: C22 | D24: =+Y24/1000 -> 404 | G24: 259271 | W24: 1936 | X24: 3416 | Y24: 404000 | AT24: =+N24+O24 -> 0 | AU24: =+U24/V24 -> #DIV/0! | AV24: =+AJ24/Y24 -> 0 | AW24: =+T24/D24 -> 0 | AX24: =+V24/D24 -> 0 | AY24: =+G24/D24 -> 641.7599 | AZ24: =SUM(G24:M24)/D24 -> 641.7599 | BA24: =+L24/D24 -> 0
A25: Netherlands | B25: EU | C25: C23 | D25: =+Y25/1000 -> 15298.5 | Y25: 15298500 | AT25: =+N25+O25 -> 0 | AU25: =+U25/V25 -> #DIV/0! | AV25: =+AJ25/Y25 -> 0 | AW25: =+T25/D25 -> 0 | AX25: =+V25/D25 -> 0 | AY25: =+G25/D25 -> 0 | AZ25: =SUM(G25:M25)/D25 -> 0 | BA25: =+L25/D25 -> 0
A26: Norway | B26: EFTA | C26: C24 | D26: =+Y26/1000 -> 4479 | E26: 435 | F26: 1094 | G26: 20787772 | I26: 45232 | L26: 1167930 | M26: 9464 | N26: 938005 | O26: 126706 | Q26: 72 | R26: 1355 | S26: 841 | U26: 22999296 | V26: 21370009 | W26: 112978 | X26: 141971 | Y26: 4479000 | Z26: 947 | AA26: 969 | AB26: 1916 | AC26: 65298308 | AD26: 16077675 | AE26: 0 | AF26: 3158327 | AG26: 10036216 | AH26: 0 | AI26: 12586848 | AJ26: 107157374 | AK26: 97569837 | AL26: 7624744 | AM26: 1962793 | AN26: 107157374 | AT26: =+N26+O26 -> 1064711 | AU26: =+U26/V26 -> 1.0762418 | AV26: =+AJ26/Y26 -> 23.924397 | AW26: =+T26/D26 -> 0 | AX26: =+V26/D26 -> 4771.1563 | AY26: =+G26/D26 -> 4641.1637 | AZ26: =SUM(G26:M26)/D26 -> 4914.1322 | BA26: =+L26/D26 -> 260.75687
A27: Portugal | B27: EU | C27: C25 | D27: =+Y27/1000 -> 10031.5 | Y27: 10031500 | AT27: =+N27+O27 -> 0 | AU27: =+U27/V27 -> #DIV/0! | AV27: =+AJ27/Y27 -> 0 | AW27: =+T27/D27 -> 0 | AX27: =+V27/D27 -> 0 | AY27: =+G27/D27 -> 0 | AZ27: =SUM(G27:M27)/D27 -> 0 | BA27: =+L27/D27 -> 0
A28: Spain | B28: EU | C28: C26 | D28: =+Y28/1000 -> 38731.5 | Y28: 38731500 | AT28: =+N28+O28 -> 0 | AU28: =+U28/V28 -> #DIV/0! | AV28: =+AJ28/Y28 -> 0 | AW28: =+T28/D28 -> 0 | AX28: =+V28/D28 -> 0 | AY28: =+G28/D28 -> 0 | AZ28: =SUM(G28:M28)/D28 -> 0 | BA28: =+L28/D28 -> 0
A29: Sweden | B29: EU | C29: C27 | D29: =+Y29/1000 -> 8861.726 | E29: 289 | F29: 1590 | G29: 43996377 | H29: 67998 | I29: 105862 | J29: 0 | K29: 0 | L29: 2565045 | N29: 1997865 | P29: 87 | U29: 80861726 | V29: 47508612 | W29: 0 | X29: 0 | Y29: 8861726 | Z29: 2304 | AA29: 2587 | AB29: 4891 | AC29: 156858000 | AD29: 41585000 | AE29: 304422 | AF29: 9874446 | AG29: 33759535 | AH29: 21597 | AI29: 79896000 | AJ29: 322299000 | AN29: 322299000 | AS29: 13466000 | AT29: =+N29+O29 -> 1997865 | AU29: =+U29/V29 -> 1.7020435 | AV29: =+AJ29/Y29 -> 36.369777 | AW29: =+T29/D29 -> 0 | AX29: =+V29/D29 -> 5361.1014 | AY29: =+G29/D29 -> 4964.7639 | AZ29: =SUM(G29:M29)/D29 -> 5273.8351 | BA29: =+L29/D29 -> 289.45208
A30: Switzerland | B30: EFTA | C30: C28 | D30: =+Y30/1000 -> 7200 | Y30: 7200000 | AT30: =+N30+O30 -> 0 | AU30: =+U30/V30 -> #DIV/0! | AV30: =+AJ30/Y30 -> 0 | AW30: =+T30/D30 -> 0 | AX30: =+V30/D30 -> 0 | AY30: =+G30/D30 -> 0 | AZ30: =SUM(G30:M30)/D30 -> 0 | BA30: =+L30/D30 -> 0
A31: UK | B31: EU | C31: C29 | D31: =+Y31/1000 -> 59497.2 | E31: 208 | F31: 4630 | G31: 121362000 | H31: 74000 | I31: 110000 | J31: 93000 | K31: 7528000 | L31: 7435000 | M31: 76600 | N31: 10787000 | O31: 1453000 | P31: 89 | R31: 14500 | S31: 6000 | T31: 34508000 | U31: 467843000 | V31: 331299000 | W31: 0 | X31: 0 | Y31: 59497200 | Z31: 6335 | AA31: 19356 | AB31: 25691 | AC31: 693302534 | AD31: 176074516 | AE31: 1321908 | AF31: 42631893 | AG31: 145983607 | AH31: 0 | AI31: 204952308 | AJ31: 1264266766 | AK31: 1144323119 | AL31: 68038224 | AM31: 51801821 | AN31: 1264163164 | AO31: 38615499 | AP31: 3226528 | AQ31: 16117735 | AR31: 4376903 | AS31: 62336665 | AT31: =+N31+O31 -> 12240000 | AU31: =+U31/V31 -> 1.4121473 | AV31: =+AJ31/Y31 -> 21.249181 | AW31: =+T31/D31 -> 579.99368 | AX31: =+V31/D31 -> 5568.3125 | AY31: =+G31/D31 -> 2039.7935 | AZ31: =SUM(G31:M31)/D31 -> 2297.2274 | BA31: =+L31/D31 -> 124.96386
A32: Germany | B32: EU | C32: C31 | D32: =+Y32/1000 -> 82037.011 | E32: 9734 | F32: 11817 | G32: 112952789 | I32: 145879 | L32: 9673616 | P32: 94 | T32: 9169553 | U32: 319809368 | W32: 382293 | X32: 419847 | Y32: 82037011 | Z32: 8738 | AA32: 7227 | AB32: 15965 | AC32: 484765248 | AD32: 90151835 | AE32: 0 | AF32: 0 | AG32: 0 | AH32: 0 | AI32: 146972098 | AJ32: 721889181 | AK32: 647722683 | AL32: 42999775 | AM32: 31166723 | AN32: 721889181 | AS32: 43655271 | AT32: =+N32+O32 -> 0 | AU32: =+U32/V32 -> #DIV/0! | AV32: =+AJ32/Y32 -> 8.7995549 | AW32: =+T32/D32 -> 111.77337 | AX32: =+V32/D32 -> 0 | AY32: =+G32/D32 -> 1376.8516 | AZ32: =SUM(G32:M32)/D32 -> 1496.5475 | BA32: =+L32/D32 -> 117.9177
A33: USA | B33: World - A | C33: C50 | D33: =+Y33/1000 -> 269996 | E33: 9047 | F33: 16219 | J33: 0 | P33: 100 | W33: 1389158 | X33: 7044065 | Y33: 269996000 | AT33: =+N33+O33 -> 0 | AU33: =+U33/V33 -> #DIV/0! | AV33: =+AJ33/Y33 -> 0 | AW33: =+T33/D33 -> 0 | AX33: =+V33/D33 -> 0 | AY33: =+G33/D33 -> 0 | AZ33: =SUM(G33:M33)/D33 -> 0 | BA33: =+L33/D33 -> 0
A34: Turkey | B34: World - B | C34: C42 | D34: =+Y34/1000 -> 65913.096 | E34: 1373 | G34: 11930929 | I34: 100 | J34: 157823 | K34: 6057 | L34: 106859 | M34: 387 | Q34: 11 | T34: 398723 | U34: 4117786 | V34: 20732712 | W34: 9213 | X34: 46715 | Y34: 65913096 | Z34: 278 | AA34: 2789 | AB34: 3067 | AC34: 12277877 | AD34: 0 | AE34: 0 | AF34: 111902 | AG34: 14751424 | AH34: 3156109 | AI34: 0 | AJ34: 30297311 | AT34: =+N34+O34 -> 0 | AU34: =+U34/V34 -> 0.19861299 | AV34: =+AJ34/Y34 -> 0.45965541 | AW34: =+T34/D34 -> 6.0492228 | AX34: =+V34/D34 -> 314.54617 | AY34: =+G34/D34 -> 181.00999 | AZ34: =SUM(G34:M34)/D34 -> 185.1249 | BA34: =+L34/D34 -> 1.6212104
A35: Australia | B35: World - A | C35: C70 | D35: =+Y35/1000 -> 18923.836 | Y35: 18923836 | AT35: =+N35+O35 -> 0 | AU35: =+U35/V35 -> #DIV/0! | AV35: =+AJ35/Y35 -> 0 | AW35: =+T35/D35 -> 0 | AX35: =+V35/D35 -> 0 | AY35: =+G35/D35 -> 0 | AZ35: =SUM(G35:M35)/D35 -> 0 | BA35: =+L35/D35 -> 0
A36: Japan | B36: World - A | C36: C41 | D36: =+Y36/1000 -> 125860 | E36: 1673 | F36: 2613 | G36: 284714000 | N36: 19297000 | T36: 36964000 | U36: 523341000 | W36: 955997 | X36: 4847618 | Y36: 125860000 | Z36: 11462 | AA36: 14979 | AB36: 26441 | AC36: 716234298 | AD36: 325613108 | AE36: 13913 | AF36: 773215 | AG36: 1992036 | AH36: 283763 | AI36: 120114267 | AJ36: 1165024601 | AT36: =+N36+O36 -> 19297000 | AU36: =+U36/V36 -> #DIV/0! | AV36: =+AJ36/Y36 -> 9.256512 | AW36: =+T36/D36 -> 293.6914 | AX36: =+V36/D36 -> 0 | AY36: =+G36/D36 -> 2262.1484 | AZ36: =SUM(G36:M36)/D36 -> 2262.1484 | BA36: =+L36/D36 -> 0
A37: Korea | B37: World - A | C37: C40 | D37: =+Y37/1000 -> 48361 | Y37: 48361000 | AT37: =+N37+O37 -> 0 | AU37: =+U37/V37 -> #DIV/0! | AV37: =+AJ37/Y37 -> 0 | AW37: =+T37/D37 -> 0 | AX37: =+V37/D37 -> 0 | AY37: =+G37/D37 -> 0 | AZ37: =SUM(G37:M37)/D37 -> 0 | BA37: =+L37/D37 -> 0
A38: Canada | B38: World - A | C38: C51 | D38: =+Y38/1000 -> 31187 | E38: 2739 | F38: 910 | G38: 75032608 | I38: 150814 | U38: 331565367 | Y38: 31187000 | Z38: 6733 | AA38: 6616 | AB38: 13349 | AC38: 337981271 | AD38: 73056101 | AE38: 0 | AF38: 0 | AG38: 0 | AH38: 0 | AI38: 109699443 | AJ38: 520736815 | AN38: 520736815 | AS38: 25891357 | AT38: =+N38+O38 -> 0 | AU38: =+U38/V38 -> #DIV/0! | AV38: =+AJ38/Y38 -> 16.69724 | AW38: =+T38/D38 -> 0 | AX38: =+V38/D38 -> 0 | AY38: =+G38/D38 -> 2405.8937 | AZ38: =SUM(G38:M38)/D38 -> 2410.7295 | BA38: =+L38/D38 -> 0
A39: New Zealand | B39: World - A | C39: C71 | D39: =+Y39/1000 -> 3869 | Y39: 3869000 | AT39: =+N39+O39 -> 0 | AU39: =+U39/V39 -> #DIV/0! | AV39: =+AJ39/Y39 -> 0 | AW39: =+T39/D39 -> 0 | AX39: =+V39/D39 -> 0 | AY39: =+G39/D39 -> 0 | AZ39: =SUM(G39:M39)/D39 -> 0 | BA39: =+L39/D39 -> 0
A40: Mexico | B40: World - B | C40: C72 | D40: =+Y40/1000 -> 95812.38 | Y40: 95812380 | AT40: =+N40+O40 -> 0 | AU40: =+U40/V40 -> #DIV/0! | AV40: =+AJ40/Y40 -> 0 | AW40: =+T40/D40 -> 0 | AX40: =+V40/D40 -> 0 | AY40: =+G40/D40 -> 0 | AZ40: =SUM(G40:M40)/D40 -> 0 | BA40: =+L40/D40 -> 0
A41: CEE | B41: Totals | D41: =+Y41/1000 -> 104579.58 | E41: 29276 | F41: 28411 | G41: 392681546 | H41: 318424 | I41: 574500 | J41: 212678 | K41: 160785 | L41: 6109788 | M41: 84498 | N41: 10249975 | O41: 228834 | P41: 80 | Q41: 39 | R41: 3327 | S41: 1581 | T41: 15932644 | U41: 434559218 | V41: 142994659 | W41: 222554 | X41: 248018 | Y41: 104579580 | Z41: 32714 | AA41: 14480 | AB41: 47194 | AC41: 131749149 | AD41: 45499738 | AE41: 30912 | AF41: 2088922 | AG41: 3596655 | AH41: 692491 | AI41: 75368712 | AJ41: 259026579 | AK41: 228961262 | AL41: 11781581 | AM41: 27836192 | AN41: 268579034 | AO41: 25725383 | AP41: 941050 | AQ41: 4819915 | AR41: 12096802 | AS41: 43583152 | AT41: =+N41+O41 -> 10478809 | AU41: =+U41/V41 -> 3.0389892 | AV41: =+AJ41/Y41 -> 2.4768371 | AW41: =+T41/D41 -> 152.34947 | AX41: =+V41/D41 -> 1367.3287 | AY41: =+G41/D41 -> 3754.8587 | AZ41: =SUM(G41:M41)/D41 -> 3826.1984 | BA41: =+L41/D41 -> 58.42238
A42: EU | B42: Totals | D42: =+Y42/1000 -> 373631.33 | E42: 22260 | F42: 41162 | G42: 675392729 | H42: 1489264 | I42: 1619149 | J42: 2646675 | K42: 15637410 | L42: 49591430 | M42: 797877 | N42: 52594481 | O42: 6125556 | P42: 87 | Q42: 73 | R42: 71624 | S42: 37907 | T42: 98737344 | U42: 1859451688 | V42: 1848586339 | W42: 2203045 | X42: 12504957 | Y42: 373631327 | Z42: 46299 | AA42: 80084 | AB42: 126383 | AC42: 3377961863 | AD42: 748705456 | AE42: 2953587 | AF42: 122821498 | AG42: 373795899 | AH42: 209486 | AI42: 1080927712 | AJ42: 5707375496 | AK42: 5060302044 | AL42: 297921547 | AM42: 283414989 | AN42: 5641638573 | AO42: 385194271 | AP42: 22261582 | AQ42: 98791726 | AR42: 79042997 | AS42: 585290588 | AT42: =+N42+O42 -> 58720037 | AU42: =+U42/V42 -> 1.0058777 | AV42: =+AJ42/Y42 -> 15.27542 | AW42: =+T42/D42 -> 264.26409 | AX42: =+V42/D42 -> 4947.6214 | AY42: =+G42/D42 -> 1807.6448 | AZ42: =SUM(G42:M42)/D42 -> 1999.7642 | BA42: =+L42/D42 -> 132.72824
A43: EFTA | B43: Totals | D43: =+Y43/1000 -> 11965.763 | E43: 617 | F43: 3417 | G43: 51203036 | H43: 62680 | I43: 124943 | J43: 104048 | K43: 826395 | L43: 2978116 | M43: 20173 | N43: 2362741 | O43: 325957 | P43: 82 | Q43: 79 | R43: 2654 | S43: 1610 | T43: 3574799 | U43: 31416508 | V43: 55572941 | W43: 416461 | X43: 367870 | Y43: 11965763 | Z43: 2870 | AA43: 4656 | AB43: 7540 | AC43: 247596187 | AD43: 79307219 | AE43: 0 | AF43: 6762890 | AG43: 35699276 | AH43: 8607398 | AI43: 60201946 | AJ43: 438174916 | AK43: 293136752 | AL43: 22907620 | AM43: 5896999 | AN43: 321941371 | AO43: 23664110 | AP43: 1168190 | AQ43: 5867927 | AR43: 5423950 | AS43: 36124177 | AT43: =+N43+O43 -> 2688698 | AU43: =+U43/V43 -> 0.56532023 | AV43: =+AJ43/Y43 -> 36.619054 | AW43: =+T43/D43 -> 298.75228 | AX43: =+V43/D43 -> 4644.3291 | AY43: =+G43/D43 -> 4279.1284 | AZ43: =SUM(G43:M43)/D43 -> 4623.1395 | BA43: =+L43/D43 -> 248.88643
A44: World A | B44: Totals | D44: =+Y44/1000 -> 498196.84 | E44: 15828 | F44: 23132 | G44: 1253740983 | H44: 570853 | I44: 2325060 | J44: 202500 | K44: 10820599 | L44: 56755721 | M44: 1350785 | N44: 46908594 | O44: 4571175 | P44: 90 | Q44: 70 | R44: 25162 | S44: 19857 | T44: 119843055 | U44: 2882348318 | V44: 2415952320 | W44: 2989159 | X44: 15157264 | Y44: 498196836 | Z44: 66575 | AA44: 114718 | AB44: 181293 | AC44: 5256770472 | AD44: 1465857846 | AE44: 31772 | AF44: 1423948 | AG44: 4419194 | AH44: 1532413 | AI44: 1520741140 | AJ44: 8250776786 | AK44: 7942116033 | AL44: 423754513 | AM44: 355751232 | AN44: 8721621776 | AO44: 584914700 | AP44: 28874563 | AQ44: 145039753 | AR44: 134065813 | AS44: 892894841 | AT44: =+N44+O44 -> 51479769 | AU44: =+U44/V44 -> 1.1930485 | AV44: =+AJ44/Y44 -> 16.561279 | AW44: =+T44/D44 -> 240.55363 | AX44: =+V44/D44 -> 4849.3931 | AY44: =+G44/D44 -> 2516.5575 | AZ44: =SUM(G44:M44)/D44 -> 2661.1299 | BA44: =+L44/D44 -> 113.92228
A45: World B | B45: Totals | D45: =+Y45/1000 -> 161725.48 | E45: 3093 | F45: 4275 | G45: 26874122 | H45: 101285 | I45: 225 | J45: 355492 | K45: 13643 | L45: 240697 | M45: 872 | N45: 1269662 | O45: 21860 | P45: 88 | Q45: 11 | R45: 4467 | S45: 32 | T45: 898114 | U45: 9275211 | V45: 46699921 | W45: 20752 | X45: 105224 | Y45: 161725476 | Z45: 626 | AA45: 6282 | AB45: 6908 | AC45: 27655614 | AD45: 0 | AE45: 0 | AF45: 252056 | AG45: 33227217 | AH45: 7109057 | AI45: 0 | AJ45: 68243943 | AK45: 61555870 | AL45: 3287314 | AM45: 2717776 | AN45: 67560960 | AO45: 5167308 | AP45: 255087 | AQ45: 1281323 | AR45: 1184376 | AS45: 7888095 | AT45: =+N45+O45 -> 1291522 | AU45: =+U45/V45 -> 0.19861299 | AV45: =+AJ45/Y45 -> 0.42197398 | AW45: =+T45/D45 -> 5.5533242 | AX45: =+V45/D45 -> 288.76045 | AY45: =+G45/D45 -> 166.17123 | AZ45: =SUM(G45:M45)/D45 -> 170.57508 | BA45: =+L45/D45 -> 1.488306
A46: EU Accession Countries | B46: Totals | D46: =+Y46/1000 -> 74819.296 | E46: 22381 | F46: 21245 | G46: 306491537 | H46: 307449 | I46: 481210 | J46: 152576 | K46: 157948 | L46: 5379640 | M46: 64278 | N46: 9122854 | O46: 221649 | P46: 80 | Q46: 39 | R46: 3156 | S46: 1490 | T46: 13468833 | U46: 385598344 | V46: 123620323 | W46: 211320 | X46: 232669 | Y46: 74819296 | Z46: 26377 | AA46: 12498 | AB46: 38875 | AC46: 124851978 | AD46: 44770854 | AE46: 29525 | AF46: 2078053 | AG46: 3598786 | AH46: 681049 | AI46: 74225422 | AJ46: 250235667 | AK46: 220540572 | AL46: 11620753 | AM46: 27554513 | AN46: 259715837 | AO46: 25035698 | AP46: 895789 | AQ46: 4589040 | AR46: 11941287 | AS46: 42461816 | AT46: =+N46+O46 -> 9344503 | AU46: =+U46/V46 -> 3.1192148 | AV46: =+AJ46/Y46 -> 3.3445338 | AW46: =+T46/D46 -> 180.01817 | AX46: =+V46/D46 -> 1652.2519 | AY46: =+G46/D46 -> 4096.4237 | AZ46: =SUM(G46:M46)/D46 -> 4183.8757 | BA46: =+L46/D46 -> 71.901773
A47: Europe (Excl. Malta & Cyprus) | B47: Totals | D47: =+Y47/1000 -> 490176.67 | E47: 52153 | F47: 72990 | G47: 1119277311 | H47: 1870368 | I47: 2318592 | J47: 2963401 | K47: 16624590 | L47: 58679334 | M47: 902548 | N47: 65207197 | O47: 6680347 | P47: 83 | Q47: 63 | R47: 77605 | S47: 41098 | T47: 118244787 | U47: 2325427414 | V47: 2047153939 | W47: 2842060 | X47: 13120845 | Y47: 490176670 | Z47: 81883 | AA47: 99220 | AB47: 181117 | AC47: 3757307199 | AD47: 873512413 | AE47: 2984499 | AF47: 131673310 | AG47: 413091830 | AH47: 9509375 | AI47: 1216498370 | AJ47: 6404576991 | AK47: 5582400058 | AL47: 332610748 | AM47: 317148180 | AN47: 6232158978 | AO47: 434583764 | AP47: 24370822 | AQ47: 109479568 | AR47: 96563749 | AS47: 664997916 | AT47: =+N47+O47 -> 71887544 | AU47: =+U47/V47 -> 1.1359319 | AV47: =+AJ47/Y47 -> 13.065854 | AW47: =+T47/D47 -> 241.22892 | AX47: =+V47/D47 -> 4176.3594 | AY47: =+G47/D47 -> 2283.4161 | AZ47: =SUM(G47:M47)/D47 -> 2453.4749 | BA47: =+L47/D47 -> 119.71058
A48: Eastern Europe | B48: Totals | D48: =+Y48/1000 -> 97013.112 | E48: 27644 | F48: 25254 | G48: 346361569 | H48: 284419 | I48: 510199 | J48: 199238 | K48: 157116 | L48: 5652342 | M48: 77705 | N48: 8520242 | O48: 205858 | P48: 79 | Q48: 43 | R48: 3071 | S48: 1461 | T48: 14150548 | U48: 375372660 | V48: 122666159 | W48: 213467 | X48: 244679 | Y48: 97013112 | Z48: 26562 | AA48: 12573 | AB48: 39135 | AC48: 115457900 | AD48: 40045569 | AE48: 30912 | AF48: 1502168 | AG48: 3596655 | AH48: 692491 | AI48: 67432446 | AJ48: 228758142 | AK48: 197576634 | AL48: 11479453 | AM48: 27397528 | AN48: 236453613 | AO48: 23370199 | AP48: 887567 | AQ48: 4551266 | AR48: 11535312 | AS48: 40344347 | AT48: =+N48+O48 -> 8726100 | AU48: =+U48/V48 -> 3.0601159 | AV48: =+AJ48/Y48 -> 2.3580126 | AW48: =+T48/D48 -> 145.86222 | AX48: =+V48/D48 -> 1264.4287 | AY48: =+G48/D48 -> 3570.2552 | AZ48: =SUM(G48:M48)/D48 -> 3641.184 | BA48: =+L48/D48 -> 58.263691
A49: Baltic States | B49: Totals | D49: =+Y49/1000 -> 7566.468 | E49: 1632 | F49: 3157 | G49: 46319977 | H49: 34005 | I49: 64301 | J49: 13440 | K49: 3669 | L49: 457446 | M49: 6792 | N49: 1729733 | O49: 22976 | P49: 81 | Q49: 29 | R49: 256 | S49: 120 | T49: 1782096 | U49: 59186558 | V49: 20328500 | W49: 9087 | X49: 3339 | Y49: 7566468 | Z49: 6152 | AA49: 1907 | AB49: 8059 | AC49: 16291249 | AD49: 5454169 | AE49: 0 | AF49: 586754 | AG49: 0 | AH49: 0 | AI49: 7936266 | AJ49: 30268437 | AK49: 31384628 | AL49: 302128 | AM49: 438664 | AN49: 32125421 | AO49: 2355184 | AP49: 53483 | AQ49: 268649 | AR49: 561490 | AS49: 3238805 | AT49: =+N49+O49 -> 1752709 | AU49: =+U49/V49 -> 2.9115064 | AV49: =+AJ49/Y49 -> 4.000339 | AW49: =+T49/D49 -> 235.52548 | AX49: =+V49/D49 -> 2686.6564 | AY49: =+G49/D49 -> 6121.7436 | AZ49: =SUM(G49:M49)/D49 -> 6198.3517 | BA49: =+L49/D49 -> 60.457006
A50: Central Europe | B50: Totals | D50: =+Y50/1000 -> 245460.11 | E50: 15822 | F50: 27396 | G50: 496121446 | H50: 870418 | I50: 811225 | J50: 830644 | K50: 13341711 | L50: 33277257 | M50: 532439 | N50: 36386778 | O50: 4464834 | P50: 87 | Q50: 71 | R50: 45982 | S50: 23343 | T50: 66058246 | U50: 1339850129 | V50: 1176781671 | W50: 883918 | X50: 857019 | Y50: 245460110 | Z50: 29963 | AA50: 53806 | AB50: 83769 | AC50: 2383814103 | AD50: 525094701 | AE50: 2103961 | AF50: 98552073 | AG50: 304295258 | AH50: 8545452 | AI50: 690116720 | AJ50: 4012522267 | AK50: 3418087574 | AL50: 216173843 | AM50: 203893801 | AN50: 3838155218 | AO50: 296175330 | AP50: 17532561 | AQ50: 75060925 | AR50: 56248967 | AS50: 445017792 | AT50: =+N50+O50 -> 40851612 | AU50: =+U50/V50 -> 1.1385715 | AV50: =+AJ50/Y50 -> 16.346942 | AW50: =+T50/D50 -> 269.12009 | AX50: =+V50/D50 -> 4794.187 | AY50: =+G50/D50 -> 2021.1897 | AZ50: =SUM(G50:M50)/D50 -> 2223.5187 | BA50: =+L50/D50 -> 135.57094
A51: Northern Europe | B51: Totals | D51: =+Y51/1000 -> 24059.98 | E51: 1549 | F51: 4811 | G51: 132819260 | H51: 134555 | I51: 415626 | J51: 104250 | K51: 605766 | L51: 10106128 | M51: 92851 | N51: 6378468 | O51: 891248 | P51: 87 | Q51: 78 | R51: 7740 | S51: 4647 | T51: 7903078 | U51: 278136460 | V51: 164259671 | W51: 1155852 | X51: 11507899 | Y51: 24059980 | Z51: 7198 | AA51: 9231 | AB51: 16443 | AC51: 539373850 | AD51: 144478834 | AE51: 314243 | AF51: 13666366 | AG51: 45826967 | AH51: 231249 | AI51: 235696654 | AJ51: 979588162 | AK51: 884166071 | AL51: 50594992 | AM51: 44841540 | AN51: 979602601 | AO51: 33549502 | AP51: 2021747 | AQ51: 10155430 | AR51: 9387053 | AS51: 55113733 | AT51: =+N51+O51 -> 7269716 | AU51: =+U51/V51 -> 1.693273 | AV51: =+AJ51/Y51 -> 40.714421 | AW51: =+T51/D51 -> 328.47401 | AX51: =+V51/D51 -> 6827.0909 | AY51: =+G51/D51 -> 5520.3396 | AZ51: =SUM(G51:M51)/D51 -> 5996.615 | BA51: =+L51/D51 -> 420.03892
A52: Southern Europe | B52: Totals | D52: =+Y52/1000 -> 116077 | E52: 5506 | F52: 12372 | G52: 97655059 | H52: 546971 | I52: 517241 | J52: 1815829 | K52: 2516328 | L52: 9186161 | M52: 192760 | N52: 12191976 | O52: 1095431 | P52: 88 | Q52: 70 | R52: 20556 | S52: 11527 | T52: 28350819 | U52: 272881607 | V52: 563117938 | W52: 579736 | X52: 507909 | Y52: 116077000 | Z52: 12008 | AA52: 21703 | AB52: 33711 | AC52: 702370097 | AD52: 158439140 | AE52: 535383 | AF52: 17365949 | AG52: 59372950 | AH52: 40183 | AI52: 215316284 | AJ52: 1153439983 | AK52: 1051185151 | AL52: 54060332 | AM52: 40576647 | AN52: 1145822125 | AO52: 79133549 | AP52: 3875464 | AQ52: 19443298 | AR52: 18830927 | AS52: 121283239 | AT52: =+N52+O52 -> 13287407 | AU52: =+U52/V52 -> 0.48459051 | AV52: =+AJ52/Y52 -> 9.9368521 | AW52: =+T52/D52 -> 244.24149 | AX52: =+V52/D52 -> 4851.2448 | AY52: =+G52/D52 -> 841.29551 | AZ52: =SUM(G52:M52)/D52 -> 968.58421 | BA52: =+L52/D52 -> 79.138512

Sheet 1998
A1: Name | B1: Type | C1: Code | D1: Population '000s | E1: Libraries - Total Administrative Units | F1: Libraries - Service Points | G1: Collections - Books & Bound Periodicals | H1: Collections - Current Periodicals - Titles | I1: Collections - Current Periodicals - Subscriptions | J1: Collections - Manuscripts | K1: Collections - Microforms | L1: Collections - Audio-visual Materials | M1: Collections - CD-ROMs | N1: Additions - Books & Bound Periodicals | O1: Additions - Audio-visual Materials | P1: Facilities & Services - Percentage Stock on Open Access | Q1: Facilities & Services - Percentage Catalogue Records Automated | R1: Facilities & Services - Number of Workstations for users | S1: Facilities & Services - Number connected to the internet | T1: Use & Users - Registered Users | U1: Use & Users - Loan Transactions | V1: Use & Users - Number of Visits | W1: Use & Users - Number of virtual referrals and transactions | X1: Use & Users - Number of virtual visits to networked library services | Y1: Use & Users - Potential Total Population Served | Z1: Library Staff FTE - Trained Librarians | AA1: Library Staff FTE - Other Library Staff | AB1: Library Staff FTE - Total Staff | AC1: Recurrent Expenditure (Euros) - Staff | AD1: Recurrent Expenditure (Euros) - Acquisition of Stock | AE1: Recurrent Expenditure (Euros) - Electronic Information | AF1: Recurrent Expenditure (Euros) - Automation | AG1: Recurrent Expenditure (Euros) - Premises and Related Costs | AH1: Recurrent Expenditure (Euros) - New Buildings / Refurbishment | AI1: Recurrent Expenditure (Euros) - Other Expenditure | AJ1: Recurrent Expenditure (Euros) - TOTAL EXPENDITURE | AK1: Income - Public Funding | AL1: Income - Fees & Charges | AM1: Income - Other Income | AN1: Income - TOTAL INCOME | AO1: Capital Expenditure - New Buildings / Refurbishment | AP1: Capital Expenditure - Acquisition of Stock | AQ1: Capital Expenditure - Automation | AR1: Capital Expenditure - Other Capital Expenditure | AS1: Capital Expenditure - TOTAL CAPITAL PAYMENTS | AT1: Additions | AU1: Loans per visit | AV1: Cost per pop | AW1: Users per 1000 pop | AX1: visits per 1000 pop | AY1: Bookstock per 1000 pop | AZ1: Total stock per 1000 pop | BA1: AV materials per 1000 pop
A2: Bulgaria | B2: CEE | C2: C1 | D2: =+Y2/1000 -> 8769.1 | E2: 4128 | F2: 4128 | G2: 39950456 | H2: 7853 | K2: 6639 | L2: 455665 | N2: 251370 | O2: 3077 | P2: 80 | T2: 812472 | U2: 16197152 | V2: 8778919 | W2: 10738 | X2: 12218 | Y2: 8769100 | Z2: 2533 | AA2: 1081 | AB2: 3614 | AC2: 3867352 | AD2: 619874 | AE2: 0 | AF2: 0 | AG2: 0 | AH2: 0 | AI2: 307229 | AJ2: 4794456 | AK2: 4306495 | AL2: 252605 | AM2: 298285 | AN2: 4857384 | AT2: =+N2+O2 -> 254447 | AU2: =+U2/V2 -> 1.8450053 | AV2: =+AJ2/Y2 -> 0.54674436 | AW2: =+T2/D2 -> 92.651697 | AX2: =+V2/D2 -> 1001.1197 | AY2: =+G2/D2 -> 4555.8217 | AZ2: =SUM(G2:M2)/D2 -> 4609.4369 | BA2: =+L2/D2 -> 51.962573
A3: Czech Republic | B3: CEE | C3: C2 | D3: =+Y3/1000 -> 10289.621 | E3: 6140 | F3: 7318 | G3: 54279973 | H3: 78810 | I3: 87279 | J3: 3949 | K3: 116782 | L3: 454737 | M3: 3124 | N3: 1794569 | O3: 21161 | P3: 76 | Q3: 43 | R3: 131 | S3: 81 | T3: 1449562 | U3: 62002614 | V3: 16115175 | W3: 72613 | X3: 50907 | Y3: 10289621 | Z3: 3693 | AA3: 651 | AB3: 4344 | AC3: 12891333 | AD3: 4484546 | AE3: 4921 | AF3: 183971 | AG3: 752295 | AH3: 660928 | AI3: 11827075 | AJ3: 30805069 | AK3: 32717085 | AL3: 1891397 | AM3: 2491670 | AN3: 37100152 | AO3: 3869078 | AP3: 0 | AQ3: 0 | AR3: 5695009 | AS3: 9564088 | AT3: =+N3+O3 -> 1815730 | AU3: =+U3/V3 -> 3.8474676 | AV3: =+AJ3/Y3 -> 2.9938002 | AW3: =+T3/D3 -> 140.87613 | AX3: =+V3/D3 -> 1566.1583 | AY3: =+G3/D3 -> 5275.216 | AZ3: =SUM(G3:M3)/D3 -> 5347.588 | BA3: =+L3/D3 -> 44.193756
A4: Estonia | B4: CEE | C4: C3 | D4: =+Y4/1000 -> 1453.8 | E4: 599 | F4: 738 | G4: 10656673 | H4: 10000 | I4: 17646 | J4: 53 | K4: 1600 | L4: 42769 | M4: 598 | N4: 544016 | O4: 3915 | P4: 70 | Q4: 0 | R4: 0 | S4: 0 | T4: 428437 | U4: 15351751 | V4: 5461970 | Y4: 1453800 | Z4: 1171 | AA4: 296 | AB4: 1467 | AC4: 3943800 | AD4: 2859934 | AE4: 0 | AF4: 0 | AG4: 0 | AH4: 0 | AI4: 1952781 | AJ4: 8756515 | AK4: 10354432 | AL4: 0 | AM4: 296831 | AN4: 10651262 | AO4: 1575943 | AP4: 0 | AQ4: 0 | AR4: 271406 | AS4: 1847349 | AT4: =+N4+O4 -> 547931 | AU4: =+U4/V4 -> 2.8106619 | AV4: =+AJ4/Y4 -> 6.0231909 | AW4: =+T4/D4 -> 294.70147 | AX4: =+V4/D4 -> 3757.0299 | AY4: =+G4/D4 -> 7330.2194 | AZ4: =SUM(G4:M4)/D4 -> 7380.2029 | BA4: =+L4/D4 -> 29.418765
A5: Hungary | B5: CEE | C5: C4 | D5: =+Y5/1000 -> 10135.358 | E5: 2883 | F5: 3518 | G5: 43377000 | H5: 37441 | L5: 1234000 | M5: 5208 | N5: 1016521 | O5: 20985 | T5: 1343508 | U5: 36723500 | V5: 16501920 | W5: 15745 | X5: 44995 | Y5: 10135358 | Z5: 3100 | AA5: 781 | AB5: 3881 | AC5: 17185728 | AD5: 3630203 | AE5: 0 | AF5: 0 | AG5: 0 | AH5: 0 | AI5: 9098170 | AJ5: 29914100 | AK5: 20493007 | AL5: 0 | AM5: 9421093 | AN5: 29914100 | AT5: =+N5+O5 -> 1037506 | AU5: =+U5/V5 -> 2.2254077 | AV5: =+AJ5/Y5 -> 2.9514596 | AW5: =+T5/D5 -> 132.55654 | AX5: =+V5/D5 -> 1628.1536 | AY5: =+G5/D5 -> 4279.7699 | AZ5: =SUM(G5:M5)/D5 -> 4405.7298 | BA5: =+L5/D5 -> 121.75199
A6: Latvia | B6: CEE | C6: C5 | D6: =+Y6/1000 -> 2557.4 | E6: 1000 | F6: 1018 | G6: 15344000 | K6: 1001 | L6: 147624 | N6: 445000 | O6: 5366 | T6: 506000 | U6: 17902000 | V6: 5115000 | W6: 0 | X6: 0 | Y6: 2557400 | Z6: 1599 | AA6: 301 | AB6: 1900 | AC6: 3264898 | AD6: 848904 | AE6: 0 | AF6: 0 | AG6: 0 | AH6: 0 | AI6: 2414456 | AJ6: 6528258 | AK6: 5702120 | AL6: 444012 | AM6: 382126 | AN6: 6528258 | AO6: 0 | AP6: 0 | AQ6: 0 | AR6: 0 | AS6: 0 | AT6: =+N6+O6 -> 450366 | AU6: =+U6/V6 -> 3.4999022 | AV6: =+AJ6/Y6 -> 2.5526934 | AW6: =+T6/D6 -> 197.8572 | AX6: =+V6/D6 -> 2000.0782 | AY6: =+G6/D6 -> 5999.8436 | AZ6: =SUM(G6:M6)/D6 -> 6057.9593 | BA6: =+L6/D6 -> 57.724251
A7: Lithuania | B7: CEE | C7: C6 | D7: =+Y7/1000 -> 3702.6 | E7: 61 | F7: 1464 | G7: 24022858 | J7: 5551 | K7: 1094 | L7: 260515 | M7: 136 | N7: 968666 | O7: 4702 | P7: 96 | R7: 31 | S7: 0 | T7: 797540 | U7: 21990579 | V7: 7628828 | W7: 8875 | X7: 3261 | Y7: 3702600 | Z7: 3120 | AA7: 996 | AB7: 4116 | AC7: 7326062 | AD7: 1060107 | AE7: 0 | AF7: 0 | AG7: 0 | AH7: 0 | AI7: 4074271 | AJ7: 12460440 | AK7: 12624968 | AL7: 88798 | AM7: 111097 | AN7: 12824862 | AT7: =+N7+O7 -> 973368 | AU7: =+U7/V7 -> 2.8825632 | AV7: =+AJ7/Y7 -> 3.3653217 | AW7: =+T7/D7 -> 215.39999 | AX7: =+V7/D7 -> 2060.3976 | AY7: =+G7/D7 -> 6488.1051 | AZ7: =SUM(G7:M7)/D7 -> 6560.2965 | BA7: =+L7/D7 -> 70.360017
A8: Poland | B8: CEE | C8: C7 | D8: =+Y8/1000 -> 38666 | E8: 9230 | F8: 3565 | G8: 135867218 | K8: 10383 | L8: 2597035 | N8: 3794111 | O8: 121207 | T8: 7222496 | U8: 189035327 | W8: 105852 | X8: 120447 | Y8: 38666000 | Z8: 11137 | AA8: 6691 | AB8: 17828 | AT8: =+N8+O8 -> 3915318 | AU8: =+U8/V8 -> #DIV/0! | AV8: =+AJ8/Y8 -> 0 | AW8: =+T8/D8 -> 186.79191 | AX8: =+V8/D8 -> 0 | AY8: =+G8/D8 -> 3513.8679 | AZ8: =SUM(G8:M8)/D8 -> 3581.3023 | BA8: =+L8/D8 -> 67.165856
A9: Romania | B9: CEE | C9: C8 | D9: =+Y9/1000 -> 22502.803 | E9: 2953 | F9: 3246 | G9: 50493040 | H9: 9011 | I9: 10369 | J9: 81753 | K9: 9515 | L9: 295464 | M9: 839 | N9: 984422 | O9: 7190 | P9: 46 | Q9: 2 | R9: 45 | S9: 28 | T9: 1994240 | U9: 37892994 | V9: 15571569 | W9: 3713 | X9: 4359 | Y9: 22502803 | Z9: 4433 | AA9: 581 | AB9: 5014 | AC9: 2675285 | AD9: 792972 | AE9: 433 | AF9: 7673 | AG9: 29569 | AH9: 25464 | AI9: 1332758 | AJ9: 4864154 | AK9: 4718229 | AL9: 48642 | AM9: 97283 | AN9: 4864154 | AO9: 341583 | AP9: 21833 | AQ9: 111572 | AR9: 98705 | AS9: 573693 | AT9: =+N9+O9 -> 991612 | AU9: =+U9/V9 -> 2.4334731 | AV9: =+AJ9/Y9 -> 0.21615769 | AW9: =+T9/D9 -> 88.621849 | AX9: =+V9/D9 -> 691.98353 | AY9: =+G9/D9 -> 2243.8556 | AZ9: =SUM(G9:M9)/D9 -> 2261.94 | BA9: =+L9/D9 -> 13.130098
A10: Slovak Rep | B10: CEE | C10: C9 | D10: =+Y10/1000 -> 5352.9 | E10: 2706 | F10: 3195 | G10: 19160968 | H10: 10666 | I10: 14085 | J10: 0 | K10: 0 | L10: 160059 | M10: 487 | N10: 356131 | O10: 2723 | P10: 95 | Q10: 49 | R10: 58 | S10: 51 | T10: 751086 | U10: 25799524 | V10: 7793474 | W10: 4605 | X10: 9236 | Y10: 5352900 | Z10: 1085 | AA10: 842 | AB10: 1927 | AC10: 3904308 | AD10: 962152 | AE10: 6317 | AF10: 15177 | AG10: 15177 | AH10: 0 | AI10: 2753139 | AJ10: 7656270 | AK10: 6145551 | AL10: 500115 | AM10: 437690 | AN10: 7083356 | AO10: 220560 | AP10: 0 | AQ10: 95371 | AR10: 58527 | AS10: 374459 | AT10: =+N10+O10 -> 358854 | AU10: =+U10/V10 -> 3.310401 | AV10: =+AJ10/Y10 -> 1.4303032 | AW10: =+T10/D10 -> 140.31385 | AX10: =+V10/D10 -> 1455.9349 | AY10: =+G10/D10 -> 3579.549 | AZ10: =SUM(G10:M10)/D10 -> 3614.1652 | BA10: =+L10/D10 -> 29.901362
A11: Slovenia | B11: CEE | C11: C10 | D11: =+Y11/1000 -> 1983 | E11: 60 | F11: 299 | G11: 6495436 | H11: 14341 | I11: 23023 | J11: 14909 | K11: 2497 | L11: 177675 | M11: 184 | N11: 366453 | O11: 27335 | P11: 88 | Q11: 77 | R11: 272 | S11: 0 | T11: 463652 | U11: 15600266 | V11: 6250428 | W11: 0 | X11: 0 | Y11: 1983000 | Z11: 588 | AA11: 188 | AB11: 776 | AC11: 10927423 | AD11: 6116386 | AE11: 0 | AF11: 0 | AG11: 0 | AH11: 0 | AI11: 6449099 | AJ11: 23492908 | AK11: 20667857 | AL11: 2064308 | AM11: 429627 | AN11: 23161792 | AO11: 1310917 | AP11: 86946 | AQ11: 399947 | AR11: 482152 | AS11: 2279961 | AT11: =+N11+O11 -> 393788 | AU11: =+U11/V11 -> 2.4958716 | AV11: =+AJ11/Y11 -> 11.847155 | AW11: =+T11/D11 -> 233.81341 | AX11: =+V11/D11 -> 3152.0061 | AY11: =+G11/D11 -> 3275.5603 | AZ11: =SUM(G11:M11)/D11 -> 3392.8719 | BA11: =+L11/D11 -> 89.599092
A12: Austria | B12: EU | C12: C11 | D12: =+Y12/1000 -> 8094.097 | E12: 973 | F12: 1966 | G12: 9341615 | P12: 100 | Q12: 42 | R12: 309 | S12: 309 | T12: 908034 | U12: 16065599 | V12: 9970213 | W12: 20851 | X12: 22899 | Y12: 8094097 | Z12: 722 | AA12: 866 | AB12: 1588 | AC12: 19242933 | AD12: 5038336 | AE12: 3725 | AF12: 139251 | AG12: 569425 | AH12: 8765 | AI12: 8952123 | AJ12: 33954558 | AK12: 29657650 | AL12: 2309378 | AM12: 1987499 | AN12: 33954527 | AT12: =+N12+O12 -> 0 | AU12: =+U12/V12 -> 1.6113597 | AV12: =+AJ12/Y12 -> 4.1949779 | AW12: =+T12/D12 -> 112.18472 | AX12: =+V12/D12 -> 1231.7882 | AY12: =+G12/D12 -> 1154.1269 | AZ12: =SUM(G12:M12)/D12 -> 1154.1269 | BA12: =+L12/D12 -> 0
A13: België Vlaamse Gemeenschap | B13: België Vlaamse Gemeenschap | C13: C12a
A14: Belgique-Communauté française | B14: Belgique-Communauté française | C14: C12b
A15: Belgium | B15: EU | C15: C12 | D15: =+Y15/1000 -> 9681.9 | E15: 495 | F15: 1485 | G15: 31391605 | I15: 140102 | L15: 1735583 | M15: 83144 | N15: 1602000 | O15: 171044 | Q15: 70 | T15: 2310000 | W15: 39000 | X15: 33000 | Y15: 9681900 | Z15: 2541 | AA15: 1339 | AB15: 3880 | AC15: 111555734 | AD15: 25611400 | AE15: 93565 | AF15: 3474356 | AG15: 13044524 | AH15: 4440 | AI15: 38414616 | AJ15: 192198634 | AK15: 172147770 | AL15: 7958908 | AM15: 9139875 | AN15: 189246553 | AT15: =+N15+O15 -> 1773044 | AU15: =+U15/V15 -> #DIV/0! | AV15: =+AJ15/Y15 -> 19.851334 | AW15: =+T15/D15 -> 238.58953 | AX15: =+V15/D15 -> 0 | AY15: =+G15/D15 -> 3242.298 | AZ15: =SUM(G15:M15)/D15 -> 3444.6167 | BA15: =+L15/D15 -> 179.26058
A16: Denmark | B16: EU | C16: C13 | D16: =+Y16/1000 -> 5313.577 | E16: 251 | F16: 849 | G16: 31255310 | I16: 89235 | K16: 391 | L16: 2502755 | M16: 57171 | N16: 2242381 | O16: 245636 | R16: 749 | S16: 463 | T16: 1833438 | U16: 75514011 | V16: 31818439 | W16: 854688 | X16: 11137129 | Y16: 5313577 | Z16: 2357 | AA16: 2842 | AB16: 5199 | AC16: 183781020 | AD16: 46575947 | AE16: 746 | AF16: 21072 | AG16: 99019 | AH16: 0 | AI16: 74173830 | AJ16: 304651634 | AK16: 270540850 | AL16: 18489943 | AM16: 15620841 | AN16: 304651634 | AO16: 0 | AP16: 0 | AQ16: 0 | AR16: 0 | AS16: 0 | AT16: =+N16+O16 -> 2488017 | AU16: =+U16/V16 -> 2.3732783 | AV16: =+AJ16/Y16 -> 57.334567 | AW16: =+T16/D16 -> 345.04779 | AX16: =+V16/D16 -> 5988.1393 | AY16: =+G16/D16 -> 5882.16 | AZ16: =SUM(G16:M16)/D16 -> 6380.7981 | BA16: =+L16/D16 -> 471.01134
A17: Eire | B17: EU | C17: C15 | D17: =+Y17/1000 -> 3473 | E17: 32 | F17: 348 | G17: 10831591 | H17: 11688 | I17: 2320 | J17: 11739 | K17: 14704 | L17: 262037 | M17: 2559 | N17: 623469 | O17: 22877 | P17: 88 | Q17: 69 | R17: 518 | S17: 319 | T17: 824985 | U17: 13027550 | V17: 18749238 | W17: 1700 | X17: 4300 | Y17: 3473000 | Z17: 267 | AA17: 1066 | AB17: 1333 | AC17: 29523085 | AD17: 6616416 | AE17: 0 | AF17: 0 | AG17: 5818092 | AH17: 0 | AI17: 6511440 | AJ17: 48469033 | AK17: 43745217 | AL17: 1422904 | AM17: 3587724 | AN17: 48755845 | AO17: 2992392 | AP17: 61619 | AQ17: 26721 | AR17: 217690 | AS17: 3298422 | AT17: =+N17+O17 -> 646346 | AU17: =+U17/V17 -> 0.6948309 | AV17: =+AJ17/Y17 -> 13.955955 | AW17: =+T17/D17 -> 237.54247 | AX17: =+V17/D17 -> 5398.5713 | AY17: =+G17/D17 -> 3118.7996 | AZ17: =SUM(G17:M17)/D17 -> 3206.6335 | BA17: =+L17/D17 -> 75.449755
A18: Finland | B18: EU | C18: C16 | D18: =+Y18/1000 -> 5120.859 | E18: 436 | F18: 1178 | G18: 36875194 | I18: 96763 | L18: 3414000 | M18: 23000 | N18: 1569383 | O18: 198000 | P18: 95 | Q18: 95 | R18: 2400 | S18: 1477 | T18: 2465543 | U18: 100332465 | V18: 64167689 | W18: 188385 | X18: 196549 | Y18: 5120859 | Z18: 1480 | AA18: 2710 | AB18: 4190 | AC18: 119833481 | AD18: 37556310 | AE18: 0 | AF18: 0 | AG18: 0 | AH18: 0 | AI18: 52843539 | AJ18: 210233330 | AK18: 193327383 | AL18: 3929956 | AM18: 12975992 | AN18: 210233330 | AO18: 18080319 | AP18: 1199168 | AQ18: 5516111 | AR18: 6649898 | AS18: 31445497 | AT18: =+N18+O18 -> 1767383 | AU18: =+U18/V18 -> 1.5635979 | AV18: =+AJ18/Y18 -> 41.054309 | AW18: =+T18/D18 -> 481.47059 | AX18: =+V18/D18 -> 12530.649 | AY18: =+G18/D18 -> 7200.9782 | AZ18: =SUM(G18:M18)/D18 -> 7891.0505 | BA18: =+L18/D18 -> 666.68502
A19: France | B19: EU | C19: C17 | D19: =+Y19/1000 -> 59272.923 | E19: 3633 | F19: 3764 | G19: 129940500 | I19: 204763 | L19: 8633500 | M19: 54728 | N19: 6910600 | O19: 879000 | P19: 72 | T19: 11625521 | U19: 282199000 | W19: 17667 | X19: 20237 | Y19: 59272923 | Z19: 6974 | AA19: 13531 | AB19: 20505 | AC19: 564623164 | AD19: 103304749 | AE19: 376754 | AF19: 13989953 | AG19: 52525504 | AH19: 17878 | AI19: 154681540 | AJ19: 889519542 | AK19: 797422757 | AL19: 21454962 | AM19: 7055765 | AN19: 825933484 | AO19: 123049134 | AP19: 4781192 | AQ19: 21993243 | AR19: 26513753 | AS19: 176337328 | AT19: =+N19+O19 -> 7789600 | AU19: =+U19/V19 -> #DIV/0! | AV19: =+AJ19/Y19 -> 15.007182 | AW19: =+T19/D19 -> 196.13544 | AX19: =+V19/D19 -> 0 | AY19: =+G19/D19 -> 2192.2405 | AZ19: =SUM(G19:M19)/D19 -> 2342.2751 | BA19: =+L19/D19 -> 145.65673
A20: Greece | B20: EU | C20: C18 | D20: =+Y20/1000 -> 9913 | E20: 672 | F20: 829 | G20: 9088431 | H20: 150843 | I20: 117113 | J20: 1413606 | K20: 297413 | L20: 96021 | M20: 11825 | N20: 277536 | O20: 11488 | P20: 88 | Q20: 69 | R20: 1439 | S20: 886 | T20: 2692936 | U20: 1828799 | V20: 2285690 | W20: 8173 | X20: 11434 | Y20: 9913000 | Z20: 1029 | AA20: 805 | AB20: 1834 | AC20: 36492231 | AD20: 8378028 | AE20: 30607 | AF20: 1136535 | AG20: 4267139 | AH20: 1452 | AI20: 12566230 | AJ20: 62872222 | AT20: =+N20+O20 -> 289024 | AU20: =+U20/V20 -> 0.80010806 | AV20: =+AJ20/Y20 -> 6.3424011 | AW20: =+T20/D20 -> 271.65702 | AX20: =+V20/D20 -> 230.575 | AY20: =+G20/D20 -> 916.81943 | AZ20: =SUM(G20:M20)/D20 -> 1127.333 | BA20: =+L20/D20 -> 9.6863714
A21: Iceland | B21: EFTA | C21: C19 | D21: =+Y21/1000 -> 275.264 | E21: 149 | F21: 155 | G21: 2081101 | I21: 1854 | J21: 844 | K21: 3178 | L21: 64866 | M21: 509 | N21: 71029 | O21: 11015 | T21: 79421 | U21: 2207075 | V21: 770863 | W21: 1676 | X21: 2088 | Y21: 275264 | Z21: 87 | AA21: 210 | AB21: 300 | AC21: 4067659 | AD21: 1490983 | AE21: 0 | AF21: 84482 | AG21: 650254 | AH21: 693098 | AI21: 826439 | AJ21: 7812916 | AK21: 7102374 | AL21: 474437 | AM21: 206197 | AN21: 7783008 | AT21: =+N21+O21 -> 82044 | AU21: =+U21/V21 -> 2.8631222 | AV21: =+AJ21/Y21 -> 28.383356 | AW21: =+T21/D21 -> 288.52665 | AX21: =+V21/D21 -> 2800.4498 | AY21: =+G21/D21 -> 7560.382 | AZ21: =SUM(G21:M21)/D21 -> 7819.2281 | BA21: =+L21/D21 -> 235.65014
A22: Italy | B22: EU | C22: C20 | D22: =+Y22/1000 -> 56594 | E22: 84 | F22: 6076 | G22: 41459636 | N22: 10292911 | W22: 443414 | X22: 486972 | Y22: 56594000 | Z22: 5984 | AA22: 17856 | AB22: 23840 | AT22: =+N22+O22 -> 10292911 | AU22: =+U22/V22 -> #DIV/0! | AV22: =+AJ22/Y22 -> 0 | AW22: =+T22/D22 -> 0 | AX22: =+V22/D22 -> 0 | AY22: =+G22/D22 -> 732.58006 | AZ22: =SUM(G22:M22)/D22 -> 732.58006 | BA22: =+L22/D22 -> 0
A23: Liechtenstein | B23: EFTA | C23: C21 | D23: =+Y23/1000 -> 30.374 | E23: 3 | F23: 3 | G23: 24174 | N23: 5778 | S23: 2 | U23: 77206 | W23: 1254 | X23: 928 | Y23: 30374 | Z23: 2 | AA23: 3 | AB23: 5 | AT23: =+N23+O23 -> 5778 | AU23: =+U23/V23 -> #DIV/0! | AV23: =+AJ23/Y23 -> 0 | AW23: =+T23/D23 -> 0 | AX23: =+V23/D23 -> 0 | AY23: =+G23/D23 -> 795.87805 | AZ23: =SUM(G23:M23)/D23 -> 795.87805 | BA23: =+L23/D23 -> 0
A24: Luxembourg | B24: EU | C24: C22 | D24: =+Y24/1000 -> 372 | E24: 13 | F24: 13 | G24: 264666 | H24: 356 | I24: 328 | J24: 0 | K24: 0 | L24: 1040 | M24: 261 | N24: 83750 | O24: 287 | P24: 88 | Q24: 41 | R24: 25 | S24: 8 | T24: 25900 | U24: 199385 | V24: 64165 | W24: 1783 | X24: 3145 | Y24: 372000 | Z24: 18 | AA24: 5 | AB24: 23 | AC24: 987497 | AD24: 227475 | AE24: 369 | AF24: 19 | AG24: 34342 | AH24: 36927 | AI24: 29148 | AJ24: 1315777 | AO24: 7670 | AP24: 397 | AQ24: 1822 | AR24: 1977 | AS24: 11866 | AT24: =+N24+O24 -> 84037 | AU24: =+U24/V24 -> 3.1073794 | AV24: =+AJ24/Y24 -> 3.5370349 | AW24: =+T24/D24 -> 69.623656 | AX24: =+V24/D24 -> 172.48656 | AY24: =+G24/D24 -> 711.46774 | AZ24: =SUM(G24:M24)/D24 -> 716.80376 | BA24: =+L24/D24 -> 2.7956989
A25: Netherlands | B25: EU | C25: C23 | D25: =+Y25/1000 -> 14757 | E25: 551 | F25: 1111 | G25: 41479883 | N25: 2675657 | U25: 156671699 | W25: 112777 | X25: 123855 | Y25: 14757000 | Z25: 2510 | AA25: 5898 | AB25: 8408 | AC25: 237769481 | AD25: 48216205 | AE25: 192941 | AF25: 31189138 | AG25: 61108170 | AH25: 9154 | AI25: 61561566 | AJ25: 440046655 | AK25: 292414948 | AL25: 54435256 | AM25: 93196451 | AN25: 440046655 | AT25: =+N25+O25 -> 2675657 | AU25: =+U25/V25 -> #DIV/0! | AV25: =+AJ25/Y25 -> 29.81952 | AW25: =+T25/D25 -> 0 | AX25: =+V25/D25 -> 0 | AY25: =+G25/D25 -> 2810.8615 | AZ25: =SUM(G25:M25)/D25 -> 2810.8615 | BA25: =+L25/D25 -> 0
A26: Norway | B26: EFTA | C26: C24 | D26: =+Y26/1000 -> 4445 | E26: 435 | F26: 1126 | G26: 20650302 | H26: 20747 | I26: 47159 | J26: 36330 | K26: 290190 | L26: 1099689 | M26: 5918 | N26: 936392 | O26: 117437 | P26: 82 | Q26: 70 | R26: 475 | S26: 292 | T26: 1297464 | U26: 22912736 | V26: 20727675 | W26: 112120 | X26: 140893 | Y26: 4445000 | Z26: 923 | AA26: 978 | AB26: 1901 | AC26: 61385540 | AD26: 15504727 | AE26: 0 | AF26: 2203908 | AG26: 8311018 | AH26: 0 | AI26: 12547913 | AJ26: 99953106 | AK26: 91212079 | AL26: 6092947 | AM26: 2648080 | AN26: 99953106 | AT26: =+N26+O26 -> 1053829 | AU26: =+U26/V26 -> 1.1054176 | AV26: =+AJ26/Y26 -> 22.486638 | AW26: =+T26/D26 -> 291.89291 | AX26: =+V26/D26 -> 4663.144 | AY26: =+G26/D26 -> 4645.7372 | AZ26: =SUM(G26:M26)/D26 -> 4983.2025 | BA26: =+L26/D26 -> 247.3991
A27: Portugal | B27: EU | C27: C25 | D27: =+Y27/1000 -> 10162 | E27: 167 | F27: 286 | G27: 7388900 | K27: 2262 | L27: 189728 | N27: 527848 | O27: 31908 | R27: 252 | T27: 3233904 | U27: 1680532 | W27: 642 | X27: 2 | Y27: 10162000 | Z27: 868 | AA27: 581 | AB27: 1449 | AC27: 11974962 | AD27: 2511163 | AE27: 24 | AF27: 669 | AG27: 3145 | AH27: 2157 | AI27: 2355557 | AJ27: 16847676 | AK27: 23287965 | AL27: 314728 | AM27: 1735 | AN27: 23604427 | AO27: 3690111 | AP27: 0 | AQ27: 0 | AR27: 2812335 | AS27: 6502447 | AT27: =+N27+O27 -> 559756 | AU27: =+U27/V27 -> #DIV/0! | AV27: =+AJ27/Y27 -> 1.6579095 | AW27: =+T27/D27 -> 318.23499 | AX27: =+V27/D27 -> 0 | AY27: =+G27/D27 -> 727.1108 | AZ27: =SUM(G27:M27)/D27 -> 746.00374 | BA27: =+L27/D27 -> 18.67034
A28: Spain | B28: EU | C28: C26 | D28: =+Y28/1000 -> 38245 | E28: 4400 | F28: 5209 | G28: 36714000 | H28: 162968 | I28: 154560 | J28: 49573 | K28: 306000 | L28: 979000 | M28: 24000 | N28: 1836000 | O28: 98000 | P28: 88 | Q28: 69 | R28: 5653 | S28: 3479 | T28: 6119000 | U28: 21417000 | V28: 204131947 | W28: 122000 | X28: 5000 | Y28: 38245000 | Z28: 4139 | AA28: 2469 | AB28: 6608 | AC28: 87790002 | AD28: 22574572 | AE28: 0 | AF28: 0 | AG28: 0 | AH28: 0 | AI28: 15049715 | AJ28: 125414288 | AK28: 109543361 | AL28: 8529908 | AM28: 7341019 | AN28: 125414288 | AT28: =+N28+O28 -> 1934000 | AU28: =+U28/V28 -> 0.10491743 | AV28: =+AJ28/Y28 -> 3.2792336 | AW28: =+T28/D28 -> 159.99477 | AX28: =+V28/D28 -> 5337.4806 | AY28: =+G28/D28 -> 959.96862 | AZ28: =SUM(G28:M28)/D28 -> 1003.794 | BA28: =+L28/D28 -> 25.598117
A29: Sweden | B29: EU | C29: C27 | D29: =+Y29/1000 -> 8847.629 | E29: 288 | F29: 1609 | G29: 43659000 | H29: 69138 | I29: 105638 | J29: 0 | K29: 0 | L29: 2439000 | M29: 0 | N29: 1858000 | O29: 173000 | P29: 87 | U29: 80479000 | V29: 48000000 | W29: 0 | X29: 0 | Y29: 8847629 | Z29: 2360 | AA29: 2868 | AB29: 5228 | AC29: 157033557 | AD29: 40985208 | AE29: 457769 | AF29: 16998290 | AG29: 63820355 | AH29: 21722 | AI29: 48589960 | AJ29: 327906861 | AK29: 286410905 | AL29: 22302206 | AM29: 19193750 | AN29: 327906861 | AO29: 5289304 | AP29: 350810 | AQ29: 1613710 | AR29: 1945393 | AS29: 9199218 | AT29: =+N29+O29 -> 2031000 | AU29: =+U29/V29 -> 1.6766458 | AV29: =+AJ29/Y29 -> 37.061552 | AW29: =+T29/D29 -> 0 | AX29: =+V29/D29 -> 5425.1823 | AY29: =+G29/D29 -> 4934.5424 | AZ29: =SUM(G29:M29)/D29 -> 5229.9634 | BA29: =+L29/D29 -> 275.66707
A30: Switzerland | B30: EFTA | C30: C28 | D30: =+Y30/1000 -> 6861 | E30: 43 | F30: 2254 | G30: 28173790 | N30: 1334496 | U30: 6090019 | V30: 31638171 | W30: 287131 | X30: 212584 | Y30: 6861000 | Z30: 1841 | AA30: 3476 | AB30: 5317 | AT30: =+N30+O30 -> 1334496 | AU30: =+U30/V30 -> 0.1924896 | AV30: =+AJ30/Y30 -> 0 | AW30: =+T30/D30 -> 0 | AX30: =+V30/D30 -> 4611.3061 | AY30: =+G30/D30 -> 4106.3679 | AZ30: =SUM(G30:M30)/D30 -> 4106.3679 | BA30: =+L30/D30 -> 0
A31: UK | B31: EU | C31: C29 | D31: =+Y31/1000 -> 59234.7 | E31: 208 | F31: 4630 | G31: 122677000 | H31: 79000 | I31: 121000 | J31: 76000 | K31: 7522000 | L31: 7444000 | M31: 124000 | N31: 10984000 | O31: 1381000 | P31: 87 | R31: 10700 | S31: 2800 | T31: 34356000 | U31: 497874000 | V31: 344519000 | W31: 0 | X31: 0 | Y31: 59234700 | Z31: 6342 | AA31: 19487 | AB31: 25829 | AC31: 662509572 | AD31: 181844792 | AE31: 1003793 | AF31: 37282277 | AG31: 139877653 | AH31: 0 | AI31: 191181993 | AJ31: 1213700080 | AK31: 1099886973 | AL31: 65305214 | AM31: 48507844 | AN31: 1213700031 | AO31: 29673257 | AP31: 2588575 | AQ31: 11811943 | AR31: 5517477 | AS31: 49591252 | AT31: =+N31+O31 -> 12365000 | AU31: =+U31/V31 -> 1.4451278 | AV31: =+AJ31/Y31 -> 20.489681 | AW31: =+T31/D31 -> 579.99787 | AX31: =+V31/D31 -> 5816.1686 | AY31: =+G31/D31 -> 2071.0327 | AZ31: =SUM(G31:M31)/D31 -> 2330.4414 | BA31: =+L31/D31 -> 125.66958
A32: Germany | B32: EU | C32: C31 | D32: =+Y32/1000 -> 82057.379 | E32: 10261 | F32: 12134 | G32: 113256537 | I32: 150856 | L32: 9369872 | P32: 88 | T32: 11100286 | U32: 324555454 | V32: 424364683 | W32: 462788 | X32: 508250 | Y32: 82057379 | Z32: 8928 | AA32: 7129 | AB32: 16057 | AC32: 477249801 | AD32: 86405938 | AE32: 0 | AF32: 0 | AG32: 0 | AH32: 0 | AI32: 223819150 | AJ32: 787474888 | AK32: 631231714 | AL32: 84692494 | AM32: 71550681 | AN32: 787474888 | AO32: 26233730 | AP32: 1739939 | AQ32: 8003630 | AR32: 9648703 | AS32: 45626003 | AT32: =+N32+O32 -> 0 | AU32: =+U32/V32 -> 0.76480317 | AV32: =+AJ32/Y32 -> 9.5966371 | AW32: =+T32/D32 -> 135.27468 | AX32: =+V32/D32 -> 5171.5603 | AY32: =+G32/D32 -> 1380.2115 | AZ32: =SUM(G32:M32)/D32 -> 1496.2367 | BA32: =+L32/D32 -> 114.18683
A33: USA | B33: World - A | C33: C50 | D33: =+Y33/1000 -> 267131 | E33: 8964 | F33: 16180 | G33: 730461817 | I33: 1913000 | J33: 0 | L33: 45394000 | M33: 1134000 | N33: 15859000 | O33: 3601000 | P33: 100 | S33: 13526 | U33: 1701184000 | V33: 1088034000 | W33: 1374417 | X33: 6969319 | Y33: 267131000 | Z33: 40689 | AA33: 82755 | AB33: 123444 | AC33: 3546831102 | AD33: 850797492 | AE33: 11301 | AF33: 319366 | AG33: 1500726 | AH33: 1029200 | AI33: 1124169850 | AJ33: 5524659037 | AK33: 5469156089 | AL33: 293200901 | AM33: 247704646 | AN33: 6010061636 | AT33: =+N33+O33 -> 19460000 | AU33: =+U33/V33 -> 1.5635394 | AV33: =+AJ33/Y33 -> 20.68146 | AW33: =+T33/D33 -> 0 | AX33: =+V33/D33 -> 4073.0353 | AY33: =+G33/D33 -> 2734.4704 | AZ33: =SUM(G33:M33)/D33 -> 2915.8084 | BA33: =+L33/D33 -> 169.93161
A34: Turkey | B34: World - B | C34: C42 | D34: =+Y34/1000 -> 65292.66 | E34: 1343 | F34: 1857 | G34: 11598444 | I34: 114 | J34: 162214 | K34: 5926 | L34: 104551 | M34: 379 | Q34: 17 | S34: 9 | T34: 498180 | U34: 4130219 | V34: 20515171 | W34: 11511 | X34: 58368 | Y34: 65292660 | Z34: 274 | AA34: 2938 | AB34: 3212 | AC34: 10272802 | AD34: 0 | AE34: 0 | AF34: 386218 | AG34: 13866459 | AH34: 1647295 | AI34: 0 | AJ34: 26172774 | AK34: 23358025 | AL34: 1355539 | AM34: 1148582 | AN34: 25862146 | AT34: =+N34+O34 -> 0 | AU34: =+U34/V34 -> 0.20132511 | AV34: =+AJ34/Y34 -> 0.40085324 | AW34: =+T34/D34 -> 7.6299541 | AX34: =+V34/D34 -> 314.20333 | AY34: =+G34/D34 -> 177.63779 | AZ34: =SUM(G34:M34)/D34 -> 181.82179 | BA34: =+L34/D34 -> 1.6012673
A35: Australia | B35: World - A | C35: C70 | D35: =+Y35/1000 -> 18745.707 | Y35: 18745707 | AT35: =+N35+O35 -> 0 | AU35: =+U35/V35 -> #DIV/0! | AV35: =+AJ35/Y35 -> 0 | AW35: =+T35/D35 -> 0 | AX35: =+V35/D35 -> 0 | AY35: =+G35/D35 -> 0 | AZ35: =SUM(G35:M35)/D35 -> 0 | BA35: =+L35/D35 -> 0
A36: Japan | B36: World - A | C36: C41 | D36: =+Y36/1000 -> 125568 | E36: 1637 | F36: 2560 | G36: 274337000 | N36: 19723000 | T36: 35723000 | U36: 495215000 | W36: 923901 | X36: 4684868 | Y36: 125568000 | Z36: 11175 | AA36: 14438 | AB36: 25613 | AC36: 552106569 | AD36: 261053182 | AE36: 1078 | AF36: 29739 | AG36: 142160 | AH36: 98434 | AI36: 104682973 | AJ36: 918114136 | AK36: 819375616 | AL36: 47550913 | AM36: 40291089 | AN36: 907217618 | AT36: =+N36+O36 -> 19723000 | AU36: =+U36/V36 -> #DIV/0! | AV36: =+AJ36/Y36 -> 7.3116888 | AW36: =+T36/D36 -> 284.49127 | AX36: =+V36/D36 -> 0 | AY36: =+G36/D36 -> 2184.7684 | AZ36: =SUM(G36:M36)/D36 -> 2184.7684 | BA36: =+L36/D36 -> 0
A37: Korea | B37: World - A | C37: C40 | D37: =+Y37/1000 -> 47926 | Y37: 47926000 | AT37: =+N37+O37 -> 0 | AU37: =+U37/V37 -> #DIV/0! | AV37: =+AJ37/Y37 -> 0 | AW37: =+T37/D37 -> 0 | AX37: =+V37/D37 -> 0 | AY37: =+G37/D37 -> 0 | AZ37: =SUM(G37:M37)/D37 -> 0 | BA37: =+L37/D37 -> 0
A38: Canada | B38: World - A | C38: C51 | D38: =+Y38/1000 -> 31093 | E38: 2739 | F38: 910 | G38: 75032608 | I38: 150814 | U38: 331565367 | Y38: 31093000 | Z38: 6733 | AA38: 6616 | AB38: 13349 | AC38: 293843525 | AD38: 63515538 | AE38: 0 | AF38: 0 | AG38: 0 | AH38: 0 | AI38: 95373542 | AJ38: 452732605 | AK38: 408896443 | AL38: 23729531 | AM38: 20106631 | AN38: 452732605 | AO38: 15934721 | AP38: 803994 | AQ38: 3698331 | AR38: 4458490 | AS38: 24895536 | AT38: =+N38+O38 -> 0 | AU38: =+U38/V38 -> #DIV/0! | AV38: =+AJ38/Y38 -> 14.560596 | AW38: =+T38/D38 -> 0 | AX38: =+V38/D38 -> 0 | AY38: =+G38/D38 -> 2413.1672 | AZ38: =SUM(G38:M38)/D38 -> 2418.0176 | BA38: =+L38/D38 -> 0
A39: New Zealand | B39: World - A | C39: C71 | D39: =+Y39/1000 -> 3838 | Y39: 3838000 | AT39: =+N39+O39 -> 0 | AU39: =+U39/V39 -> #DIV/0! | AV39: =+AJ39/Y39 -> 0 | AW39: =+T39/D39 -> 0 | AX39: =+V39/D39 -> 0 | AY39: =+G39/D39 -> 0 | AZ39: =SUM(G39:M39)/D39 -> 0 | BA39: =+L39/D39 -> 0
A40: Mexico | B40: World - B | C40: C72 | D40: =+Y40/1000 -> 94250.638 | Y40: 94250638 | AT40: =+N40+O40 -> 0 | AU40: =+U40/V40 -> #DIV/0! | AV40: =+AJ40/Y40 -> 0 | AW40: =+T40/D40 -> 0 | AX40: =+V40/D40 -> 0 | AY40: =+G40/D40 -> 0 | AZ40: =SUM(G40:M40)/D40 -> 0 | BA40: =+L40/D40 -> 0
A41: CEE | B41: Totals | D41: =+Y41/1000 -> 105412.58 | E41: 29760 | F41: 28489 | G41: 399647622 | H41: 305043 | I41: 552769 | J41: 225317 | K41: 153424 | L41: 5825543 | M41: 19443 | N41: 10521259 | O41: 217661 | P41: 78 | Q41: 39 | R41: 1345 | S41: 645 | T41: 15768993 | U41: 438495707 | V41: 139981188 | W41: 222141 | X41: 245423 | Y41: 105412582 | Z41: 32459 | AA41: 12408 | AB41: 44867 | AC41: 121315536 | AD41: 39362414 | AE41: 21492 | AF41: 380863 | AG41: 1467758 | AH41: 1263997 | AI41: 74184103 | AJ41: 237996164 | AK41: 209624452 | AL41: 9551759 | AM41: 25242733 | AN41: 244418938 | AO41: 16106793 | AP41: 552218 | AQ41: 2646686 | AR41: 9064856 | AS41: 28370554 | AT41: =+N41+O41 -> 10738920 | AU41: =+U41/V41 -> 3.1325331 | AV41: =+AJ41/Y41 -> 2.2577586 | AW41: =+T41/D41 -> 149.59308 | AX41: =+V41/D41 -> 1327.9362 | AY41: =+G41/D41 -> 3791.2706 | AZ41: =SUM(G41:M41)/D41 -> 3858.4498 | BA41: =+L41/D41 -> 55.264209
A42: EU | B42: Totals | D42: =+Y42/1000 -> 371139.06 | E42: 22464 | F42: 41477 | G42: 667717137 | H42: 1517906 | I42: 1539245 | J42: 2594960 | K42: 15668842 | L42: 47699204 | M42: 733456 | N42: 53546473 | O42: 5787568 | P42: 87 | Q42: 71 | R42: 49997 | S42: 26293 | T42: 99316577 | U42: 1893808593 | V42: 1921924063 | W42: 2273868 | X42: 12552772 | Y42: 371139064 | Z42: 46519 | AA42: 79452 | AB42: 125971 | AC42: 3221806170 | AD42: 735560684 | AE42: 2597641 | AF42: 120471574 | AG42: 402140764 | AH42: 123248 | AI42: 1070290014 | AJ42: 5552990092 | AK42: 4800831339 | AL42: 347045529 | AM42: 335352838 | AN42: 5483229702 | AO42: 291406666 | AP42: 15029873 | AQ42: 68747852 | AR42: 74878829 | AS42: 450063236 | AT42: =+N42+O42 -> 59334041 | AU42: =+U42/V42 -> 0.98537119 | AV42: =+AJ42/Y42 -> 14.96202 | AW42: =+T42/D42 -> 267.59936 | AX42: =+V42/D42 -> 5178.4472 | AY42: =+G42/D42 -> 1799.1023 | AZ42: =SUM(G42:M42)/D42 -> 1987.047 | BA42: =+L42/D42 -> 128.52111
A43: EFTA | B43: Totals | D43: =+Y43/1000 -> 11611.638 | E43: 630 | F43: 3538 | G43: 50929367 | H43: 61031 | I43: 123026 | J43: 100794 | K43: 799720 | L43: 2826365 | M43: 15929 | N43: 2347695 | O43: 313890 | P43: 82 | Q43: 78 | R43: 1259 | S43: 782 | T43: 3455721 | U43: 31290800 | V43: 53274947 | W43: 402181 | X43: 356493 | Y43: 11611638 | Z43: 2853 | AA43: 4667 | AB43: 7523 | AC43: 222615218 | AD43: 74620670 | AE43: 0 | AF43: 5553533 | AG43: 34092921 | AH43: 8855970 | AI43: 63927864 | AJ43: 409666176 | AK43: 274690832 | AL43: 18349287 | AM43: 7974857 | AN43: 301014976 | AO43: 17194311 | AP43: 867547 | AQ43: 3990673 | AR43: 4810919 | AS43: 26863453 | AT43: =+N43+O43 -> 2661585 | AU43: =+U43/V43 -> 0.58734549 | AV43: =+AJ43/Y43 -> 35.280653 | AW43: =+T43/D43 -> 297.6084 | AX43: =+V43/D43 -> 4588.0648 | AY43: =+G43/D43 -> 4386.0622 | AZ43: =SUM(G43:M43)/D43 -> 4724.2458 | BA43: =+L43/D43 -> 243.40795
A44: World A | B44: Totals | D44: =+Y44/1000 -> 494301.71 | E44: 15676 | F44: 22992 | G44: 1235974535 | H44: 567770 | I44: 2316129 | J44: 199091 | K44: 11309795 | L44: 56572982 | M44: 1347349 | N44: 47385756 | O44: 4555517 | P44: 90 | Q44: 69 | R44: 15751 | S44: 17486 | T44: 117361800 | U44: 2822915652 | V44: 2364354300 | W44: 2926066 | X44: 14837330 | Y44: 494301707 | Z44: 66023 | AA44: 113693 | AB44: 179716 | AC44: 4903360845 | AD44: 1346931199 | AE44: 13745 | AF44: 387455 | AG44: 1824019 | AH44: 1252214 | AI44: 1459220323 | AJ44: 7712989803 | AK44: 7426995912 | AL44: 406820430 | AM44: 343977341 | AN44: 8177793682 | AO44: 425243137 | AP44: 21455844 | AQ44: 98695797 | AR44: 118981818 | AS44: 664376618 | AT44: =+N44+O44 -> 51941273 | AU44: =+U44/V44 -> 1.1939478 | AV44: =+AJ44/Y44 -> 15.60381 | AW44: =+T44/D44 -> 237.42949 | AX44: =+V44/D44 -> 4783.221 | AY44: =+G44/D44 -> 2500.4456 | AZ44: =SUM(G44:M44)/D44 -> 2646.7391 | BA44: =+L44/D44 -> 114.45031
A45: World B | B45: Totals | D45: =+Y45/1000 -> 159543.3 | E45: 3025 | F45: 4183 | G45: 26125208 | H45: 99098 | I45: 257 | J45: 365383 | K45: 13348 | L45: 235499 | M45: 854 | N45: 1234280 | O45: 21387 | P45: 88 | Q45: 17 | R45: 2750 | S45: 20 | T45: 1122138 | U45: 9303216 | V45: 46209915 | W45: 25928 | X45: 131472 | Y45: 159543298 | Z45: 617 | AA45: 6618 | AB45: 7235 | AC45: 23139232 | AD45: 0 | AE45: 0 | AF45: 869946 | AG45: 31233856 | AH45: 3710491 | AI45: 0 | AJ45: 58953526 | AK45: 52643251 | AL45: 3096515 | AM45: 2623755 | AN45: 58363520 | AO45: 3433720 | AP45: 173251 | AQ45: 796941 | AR45: 960744 | AS45: 5364655 | AT45: =+N45+O45 -> 1255667 | AU45: =+U45/V45 -> 0.20132511 | AV45: =+AJ45/Y45 -> 0.36951427 | AW45: =+T45/D45 -> 7.0334387 | AX45: =+V45/D45 -> 289.63871 | AY45: =+G45/D45 -> 163.74996 | AZ45: =SUM(G45:M45)/D45 -> 168.22798 | BA45: =+L45/D45 -> 1.4760821
A46: EU Accession Countries | B46: Totals | D46: =+Y46/1000 -> 75199.795 | E46: 22685 | F46: 21123 | G46: 310343756 | H46: 293976 | I46: 454385 | J46: 149174 | K46: 148269 | L46: 5097382 | M46: 19296 | N46: 9333436 | O46: 209962 | P46: 78 | Q46: 39 | R46: 1302 | S46: 619 | T46: 13312604 | U46: 385528930 | V46: 120361109 | W46: 210066 | X46: 229144 | Y46: 75199795 | Z46: 25603 | AA46: 10816 | AB46: 36419 | AC46: 117247387 | AD46: 38557284 | AE46: 21615 | AF46: 393842 | AG46: 1515739 | AH46: 1238598 | AI46: 73088413 | AJ46: 232062878 | AK46: 203923084 | AL46: 9470905 | AM46: 25028740 | AN46: 238422724 | AO46: 15681790 | AP46: 523768 | AQ46: 2504648 | AR46: 8978668 | AS46: 27688874 | AT46: =+N46+O46 -> 9543398 | AU46: =+U46/V46 -> 3.2031022 | AV46: =+AJ46/Y46 -> 3.0859509 | AW46: =+T46/D46 -> 177.02979 | AX46: =+V46/D46 -> 1600.551 | AY46: =+G46/D46 -> 4126.9229 | AZ46: =SUM(G46:M46)/D46 -> 4208.871 | BA46: =+L46/D46 -> 67.78452
A47: Europe (Excl. Malta & Cyprus) | B47: Totals | D47: =+Y47/1000 -> 488163.28 | E47: 52854 | F47: 73504 | G47: 1118294126 | H47: 1883980 | I47: 2215040 | J47: 2921071 | K47: 16621986 | L47: 56351112 | M47: 768828 | N47: 66415427 | O47: 6319119 | P47: 82 | Q47: 62 | R47: 52601 | S47: 27720 | T47: 118541291 | U47: 2363595100 | V47: 2115180198 | W47: 2898190 | X47: 13154688 | Y47: 488163284 | Z47: 81831 | AA47: 96527 | AB47: 178361 | AC47: 3565736924 | AD47: 849543768 | AE47: 2619133 | AF47: 126405970 | AG47: 437701443 | AH47: 10243215 | AI47: 1208401981 | AJ47: 6200652432 | AK47: 5285146623 | AL47: 374946575 | AM47: 368570428 | AN47: 6028663616 | AO47: 324707770 | AP47: 16449638 | AQ47: 75385211 | AR47: 88754604 | AS47: 505297242 | AT47: =+N47+O47 -> 72734546 | AU47: =+U47/V47 -> 1.1174438 | AV47: =+AJ47/Y47 -> 12.702005 | AW47: =+T47/D47 -> 242.83123 | AX47: =+V47/D47 -> 4332.9359 | AY47: =+G47/D47 -> 2290.8198 | AZ47: =SUM(G47:M47)/D47 -> 2456.2604 | BA47: =+L47/D47 -> 115.43497
A48: Eastern Europe | B48: Totals | D48: =+Y48/1000 -> 97698.782 | E48: 28100 | F48: 25269 | G48: 349624091 | H48: 270679 | I48: 487442 | J48: 213149 | K48: 149729 | L48: 5374635 | M48: 16566 | N48: 8563577 | O48: 203678 | P48: 77 | Q48: 43 | R48: 1293 | S48: 645 | T48: 14037016 | U48: 383251377 | V48: 121775390 | W48: 213266 | X48: 242162 | Y48: 97698782 | Z48: 26569 | AA48: 10815 | AB48: 37384 | AC48: 106780776 | AD48: 34593469 | AE48: 21492 | AF48: 380863 | AG48: 1467758 | AH48: 1263997 | AI48: 65742595 | AJ48: 210250951 | AK48: 180942932 | AL48: 9018949 | AM48: 24452679 | AN48: 214414556 | AO48: 13828373 | AP48: 516774 | AQ48: 2483646 | AR48: 8596899 | AS48: 25425693 | AT48: =+N48+O48 -> 8767255 | AU48: =+U48/V48 -> 3.1471989 | AV48: =+AJ48/Y48 -> 2.1520325 | AW48: =+T48/D48 -> 143.67647 | AX48: =+V48/D48 -> 1246.4371 | AY48: =+G48/D48 -> 3578.5921 | AZ48: =SUM(G48:M48)/D48 -> 3645.248 | BA48: =+L48/D48 -> 55.012303
A49: Baltic States | B49: Totals | D49: =+Y49/1000 -> 7713.8 | E49: 1660 | F49: 3220 | G49: 50023531 | H49: 34364 | I49: 65327 | J49: 12168 | K49: 3695 | L49: 450908 | M49: 2877 | N49: 1957682 | O49: 13983 | P49: 81 | Q49: 29 | R49: 52 | S49: 0 | T49: 1731977 | U49: 55244330 | V49: 18205798 | W49: 8875 | X49: 3261 | Y49: 7713800 | Z49: 5890 | AA49: 1593 | AB49: 7483 | AC49: 14534760 | AD49: 4768945 | AE49: 0 | AF49: 0 | AG49: 0 | AH49: 0 | AI49: 8441508 | AJ49: 27745213 | AK49: 28681520 | AL49: 532810 | AM49: 790054 | AN49: 30004382 | AO49: 2278420 | AP49: 35444 | AQ49: 163040 | AR49: 467957 | AS49: 2944860 | AT49: =+N49+O49 -> 1971665 | AU49: =+U49/V49 -> 3.0344361 | AV49: =+AJ49/Y49 -> 3.5968282 | AW49: =+T49/D49 -> 224.52967 | AX49: =+V49/D49 -> 2360.1595 | AY49: =+G49/D49 -> 6484.9401 | AZ49: =SUM(G49:M49)/D49 -> 6558.748 | BA49: =+L49/D49 -> 58.454718
A50: Central Europe | B50: Totals | D50: =+Y50/1000 -> 243834.37 | E50: 16212 | F50: 27698 | G50: 489474630 | H50: 877604 | I50: 812153 | J50: 814984 | K50: 13347036 | L50: 32109019 | M50: 519868 | N50: 36282688 | O50: 4272464 | P50: 86 | Q50: 69 | R50: 30664 | S50: 14393 | T50: 67196844 | U50: 1365234912 | V50: 1248480105 | W50: 944951 | X50: 929198 | Y50: 243834373 | Z50: 30145 | AA50: 52800 | AB50: 82945 | AC50: 2260672106 | AD50: 514890271 | AE50: 1671147 | AF50: 89340137 | AG50: 298109359 | AH50: 8240036 | AI50: 735717247 | AJ50: 3908640301 | AK50: 3248080666 | AL50: 249702326 | AM50: 240422358 | AN50: 3738205349 | AO50: 218664088 | AP50: 11056876 | AQ50: 50497088 | AR50: 51602558 | AS50: 331820622 | AT50: =+N50+O50 -> 40555152 | AU50: =+U50/V50 -> 1.0935176 | AV50: =+AJ50/Y50 -> 16.029899 | AW50: =+T50/D50 -> 275.58397 | AX50: =+V50/D50 -> 5120.1973 | AY50: =+G50/D50 -> 2007.4062 | AZ50: =SUM(G50:M50)/D50 -> 2206.2324 | BA50: =+L50/D50 -> 131.68373
A51: Northern Europe | B51: Totals | D51: =+Y51/1000 -> 24002.329 | E51: 1559 | F51: 4917 | G51: 134520907 | H51: 136791 | I51: 340649 | J51: 105550 | K51: 611162 | L51: 9520310 | M51: 86598 | N51: 6677185 | O51: 782619 | P51: 87 | Q51: 77 | R51: 4919 | S51: 3036 | T51: 7931139 | U51: 281449051 | V51: 165484666 | W51: 1156869 | X51: 11476659 | Y51: 24002329 | Z51: 7207 | AA51: 9608 | AB51: 16818 | AC51: 526052437 | AD51: 142113175 | AE51: 458515 | AF51: 19307752 | AG51: 72880646 | AH51: 714820 | AI51: 188969522 | AJ51: 950496867 | AK51: 848593591 | AL51: 51289489 | AM51: 50644860 | AN51: 950527939 | AO51: 29536659 | AP51: 1861139 | AQ51: 8561145 | AR51: 10320810 | AS51: 50279755 | AT51: =+N51+O51 -> 7459804 | AU51: =+U51/V51 -> 1.7007561 | AV51: =+AJ51/Y51 -> 39.600193 | AW51: =+T51/D51 -> 330.43206 | AX51: =+V51/D51 -> 6894.5254 | AY51: =+G51/D51 -> 5604.4939 | AZ51: =SUM(G51:M51)/D51 -> 6054.4944 | BA51: =+L51/D51 -> 396.64109
A52: Southern Europe | B52: Totals | D52: =+Y52/1000 -> 114914 | E52: 5323 | F52: 12400 | G52: 94650967 | H52: 564542 | I52: 509469 | J52: 1775220 | K52: 2510364 | L52: 8896240 | M52: 142919 | N52: 12934295 | O52: 1046375 | P52: 88 | Q52: 69 | R52: 15673 | S52: 9646 | T52: 27644315 | U52: 278415430 | V52: 561234239 | W52: 574229 | X52: 503408 | Y52: 114914000 | Z52: 12020 | AA52: 21711 | AB52: 33731 | AC52: 657696845 | AD52: 153177908 | AE52: 467979 | AF52: 17377218 | AG52: 65243680 | AH52: 24362 | AI52: 209531109 | AJ52: 1103519100 | AK52: 978847914 | AL52: 64403001 | AM52: 52260477 | AN52: 1095511390 | AO52: 60400230 | AP52: 2979405 | AQ52: 13680292 | AR52: 17766380 | AS52: 94826311 | AT52: =+N52+O52 -> 13980670 | AU52: =+U52/V52 -> 0.49607706 | AV52: =+AJ52/Y52 -> 9.6029996 | AW52: =+T52/D52 -> 240.56525 | AX52: =+V52/D52 -> 4883.9501 | AY52: =+G52/D52 -> 823.66785 | AZ52: =SUM(G52:M52)/D52 -> 948.96811 | BA52: =+L52/D52 -> 77.416503

Sheet 1997
A1: Name | B1: Type | C1: Code | D1: Population '000s | E1: Libraries - Total Administrative Units | F1: Libraries - Service Points | G1: Collections - Books & Bound Periodicals | H1: Collections - Current Periodicals - Titles | I1: Collections - Current Periodicals - Subscriptions | J1: Collections - Manuscripts | K1: Collections - Microforms | L1: Collections - Audio-visual Materials | M1: Collections - CD-ROMs | N1: Additions - Books & Bound Periodicals | O1: Additions - Audio-visual Materials | P1: Facilities & Services - Percentage Stock on Open Access | Q1: Facilities & Services - Percentage Catalogue Records Automated | R1: Facilities & Services - Number of Workstations for users | S1: Facilities & Services - Number connected to the internet | T1: Use & Users - Registered Users | U1: Use & Users - Loan Transactions | V1: Use & Users - Number of Visits | W1: Use & Users - Number of virtual referrals and transactions | X1: Use & Users - Number of virtual visits to networked library services | Y1: Use & Users - Potential Total Population Served | Z1: Library Staff FTE - Trained Librarians | AA1: Library Staff FTE - Other Library Staff | AB1: Library Staff FTE - Total Staff | AC1: Recurrent Expenditure (Euros) - Staff | AD1: Recurrent Expenditure (Euros) - Acquisition of Stock | AE1: Recurrent Expenditure (Euros) - Electronic Information | AF1: Recurrent Expenditure (Euros) - Automation | AG1: Recurrent Expenditure (Euros) - Premises and Related Costs | AH1: Recurrent Expenditure (Euros) - New Buildings / Refurbishment | AI1: Recurrent Expenditure (Euros) - Other Expenditure | AJ1: Recurrent Expenditure (Euros) - TOTAL EXPENDITURE | AK1: Income - Public Funding | AL1: Income - Fees & Charges | AM1: Income - Other Income | AN1: Income - TOTAL INCOME | AO1: Capital Expenditure - New Buildings / Refurbishment | AP1: Capital Expenditure - Acquisition of Stock | AQ1: Capital Expenditure - Automation | AR1: Capital Expenditure - Other Capital Expenditure | AS1: Capital Expenditure - TOTAL CAPITAL PAYMENTS | AT1: Additions | AU1: Loans per visit | AV1: Cost per pop | AW1: Users per 1000 pop | AX1: visits per 1000 pop | AY1: Bookstock per 1000 pop | AZ1: Total stock per 1000 pop | BA1: AV materials per 1000 pop
A2: Bulgaria | B2: CEE | C2: C1 | D2: =+Y2/1000 -> 8769.1 | E2: 4237 | F2: 4237 | G2: 40790778 | H2: 10446 | K2: 6762 | L2: 448471 | N2: 313707 | O2: 4198 | P2: 80 | T2: 894405 | U2: 18246233 | V2: 13017899 | W2: 11504 | X2: 12859 | Y2: 8769100 | Z2: 2474 | AA2: 1138 | AB2: 3612 | AC2: 3877672 | AD2: 1251617 | AE2: 0 | AF2: 0 | AG2: 0 | AH2: 0 | AI2: 147288 | AJ2: 5276577 | AK2: 2645244 | AL2: 60713 | AM2: 2603508 | AN2: 5309466 | AT2: =+N2+O2 -> 317905 | AU2: =+U2/V2 -> 1.4016266 | AV2: =+AJ2/Y2 -> 0.60172389 | AW2: =+T2/D2 -> 101.99507 | AX2: =+V2/D2 -> 1484.5194 | AY2: =+G2/D2 -> 4651.6493 | AZ2: =SUM(G2:M2)/D2 -> 4704.7539 | BA2: =+L2/D2 -> 51.142192
A3: Czech Republic | B3: CEE | C3: C2 | D3: =+Y3/1000 -> 10296.5 | E3: 6245 | F3: 7435 | G3: 53693232 | H3: 77840 | I3: 87591 | J3: 3948 | K3: 112111 | L3: 446335 | M3: 475 | N3: 2132727 | O3: 19689 | P3: 73 | Q3: 33 | R3: 104 | S3: 45 | T3: 1403068 | U3: 59634440 | V3: 14705715 | W3: 83000 | X3: 58000 | Y3: 10296500 | Z3: 3739 | AA3: 634 | AB3: 4374 | AC3: 11925966 | AD3: 4303356 | AE3: 6040 | AF3: 155246 | AG3: 125019 | AH3: 975116 | AI3: 12135950 | AJ3: 29626692 | AK3: 29766841 | AL3: 1605064 | AM3: 2609233 | AN3: 33981139 | AO3: 770780 | AP3: 255859 | AQ3: 1767564 | AR3: 1672831 | AS3: 4467034 | AT3: =+N3+O3 -> 2152416 | AU3: =+U3/V3 -> 4.0551881 | AV3: =+AJ3/Y3 -> 2.8773556 | AW3: =+T3/D3 -> 136.2665 | AX3: =+V3/D3 -> 1428.2246 | AY3: =+G3/D3 -> 5214.7071 | AZ3: =SUM(G3:M3)/D3 -> 5285.4399 | BA3: =+L3/D3 -> 43.348225
A4: Estonia | B4: CEE | C4: C3 | D4: =+Y4/1000 -> 1462.13 | E4: 602 | F4: 743 | G4: 10561242 | H4: 9762 | I4: 17163 | J4: 37 | K4: 1570 | L4: 39450 | M4: 552 | N4: 522603 | O4: 3663 | P4: 69 | Q4: 0 | R4: 0 | S4: 0 | T4: 407149 | U4: 14549200 | V4: 5022559 | Y4: 1462130 | Z4: 1166 | AA4: 302 | AB4: 1468 | AC4: 3514320 | AD4: 2663409 | AE4: 0 | AF4: 0 | AG4: 0 | AH4: 0 | AI4: 1352165 | AJ4: 7529894 | AK4: 8455439 | AL4: 0 | AM4: 276286 | AN4: 8731725 | AO4: 901092 | AP4: 0 | AQ4: 0 | AR4: 292450 | AS4: 1193542 | AT4: =+N4+O4 -> 526266 | AU4: =+U4/V4 -> 2.8967704 | AV4: =+AJ4/Y4 -> 5.1499484 | AW4: =+T4/D4 -> 278.46293 | AX4: =+V4/D4 -> 3435.0974 | AY4: =+G4/D4 -> 7223.1895 | AZ4: =SUM(G4:M4)/D4 -> 7270.0622 | BA4: =+L4/D4 -> 26.981185
A5: Hungary | B5: CEE | C5: C4 | D5: =+Y5/1000 -> 10135.358 | E5: 2883 | F5: 3518 | G5: 43377000 | H5: 36980 | L5: 1200000 | M5: 630 | N5: 1040701 | O5: 19526 | T5: 1343508 | U5: 36723500 | V5: 16501920 | W5: 15745 | X5: 44995 | Y5: 10135358 | Z5: 3100 | AA5: 781 | AB5: 3881 | AC5: 17185728 | AD5: 3630203 | AE5: 0 | AF5: 0 | AG5: 0 | AH5: 0 | AI5: 9098170 | AJ5: 29914100 | AK5: 20493007 | AL5: 0 | AM5: 9421093 | AN5: 29914100 | AT5: =+N5+O5 -> 1060227 | AU5: =+U5/V5 -> 2.2254077 | AV5: =+AJ5/Y5 -> 2.9514596 | AW5: =+T5/D5 -> 132.55654 | AX5: =+V5/D5 -> 1628.1536 | AY5: =+G5/D5 -> 4279.7699 | AZ5: =SUM(G5:M5)/D5 -> 4401.8781 | BA5: =+L5/D5 -> 118.3974
A6: Latvia | B6: CEE | C6: C5 | D6: =+Y6/1000 -> 2557.4 | E6: 998 | F6: 1064 | G6: 14947580 | K6: 931 | L6: 138699 | N6: 433000 | O6: 4993 | T6: 507635 | U6: 17805663 | V6: 5318008 | W6: 0 | X6: 0 | Y6: 2557400 | Z6: 1585 | AA6: 301 | AB6: 1886 | AC6: 3246752 | AD6: 809069 | AE6: 0 | AF6: 0 | AG6: 0 | AH6: 0 | AI6: 2292976 | AJ6: 6348797 | AK6: 5625081 | AL6: 336040 | AM6: 387675 | AN6: 6348796 | AO6: 0 | AP6: 0 | AQ6: 0 | AR6: 0 | AS6: 0 | AT6: =+N6+O6 -> 437993 | AU6: =+U6/V6 -> 3.3481828 | AV6: =+AJ6/Y6 -> 2.4825201 | AW6: =+T6/D6 -> 198.49652 | AX6: =+V6/D6 -> 2079.4588 | AY6: =+G6/D6 -> 5844.8346 | AZ6: =SUM(G6:M6)/D6 -> 5899.433 | BA6: =+L6/D6 -> 54.234379
A7: Lithuania | B7: CEE | C7: C6 | D7: =+Y7/1000 -> 3705.6 | E7: 61 | F7: 1478 | G7: 23167801 | J7: 4434 | K7: 1094 | L7: 260370 | M7: 0 | N7: 829737 | O7: 5067 | P7: 96 | R7: 15 | S7: 0 | T7: 778604 | U7: 20942390 | V7: 6882350 | W7: 9235 | X7: 2885 | Y7: 3705600 | Z7: 3105 | AA7: 984 | AB7: 4089 | AC7: 4926458 | AD7: 784364 | AE7: 0 | AF7: 0 | AG7: 0 | AH7: 0 | AI7: 2806515 | AJ7: 8517336 | AK7: 8611204 | AL7: 56722 | AM7: 42062 | AN7: 8709988 | AT7: =+N7+O7 -> 834804 | AU7: =+U7/V7 -> 3.0429127 | AV7: =+AJ7/Y7 -> 2.2985039 | AW7: =+T7/D7 -> 210.1155 | AX7: =+V7/D7 -> 1857.2836 | AY7: =+G7/D7 -> 6252.1052 | AZ7: =SUM(G7:M7)/D7 -> 6323.8609 | BA7: =+L7/D7 -> 70.263925
A8: Poland | B8: CEE | C8: C7 | D8: =+Y8/1000 -> 38660 | E8: 9230 | F8: 3565 | G8: 135867218 | K8: 10383 | L8: 2597035 | N8: 3794111 | O8: 121207 | T8: 7222496 | U8: 189035327 | W8: 113401 | X8: 126762 | Y8: 38660000 | Z8: 11137 | AA8: 6691 | AB8: 17828 | AT8: =+N8+O8 -> 3915318 | AU8: =+U8/V8 -> #DIV/0! | AV8: =+AJ8/Y8 -> 0 | AW8: =+T8/D8 -> 186.8209 | AX8: =+V8/D8 -> 0 | AY8: =+G8/D8 -> 3514.4133 | AZ8: =SUM(G8:M8)/D8 -> 3581.8581 | BA8: =+L8/D8 -> 67.17628
A9: Romania | B9: CEE | C9: C8 | D9: =+Y9/1000 -> 22545.925 | E9: 2953 | F9: 3246 | G9: 50493040 | H9: 9011 | I9: 10369 | J9: 81753 | K9: 9515 | L9: 295464 | M9: 839 | N9: 984422 | O9: 7190 | P9: 46 | Q9: 2 | R9: 45 | S9: 20 | T9: 1994240 | U9: 37892994 | V9: 15571569 | W9: 3713 | X9: 4359 | Y9: 22545925 | Z9: 4433 | AA9: 581 | AB9: 5014 | AC9: 2524808 | AD9: 828736 | AE9: 250 | AF9: 6417 | AG9: 5168 | AH9: 40308 | AI9: 947431 | AJ9: 4353118 | AK9: 4222524 | AL9: 43532 | AM9: 87062 | AN9: 4353118 | AO9: 305696 | AP9: 19539 | AQ9: 99850 | AR9: 88335 | AS9: 513420 | AT9: =+N9+O9 -> 991612 | AU9: =+U9/V9 -> 2.4334731 | AV9: =+AJ9/Y9 -> 0.19307782 | AW9: =+T9/D9 -> 88.452348 | AX9: =+V9/D9 -> 690.66002 | AY9: =+G9/D9 -> 2239.5639 | AZ9: =SUM(G9:M9)/D9 -> 2257.6138 | BA9: =+L9/D9 -> 13.104985
A10: Slovak Rep | B10: CEE | C10: C9 | D10: =+Y10/1000 -> 5387.65 | E10: 2713 | F10: 3200 | G10: 19353703 | H10: 10567 | I10: 13051 | J10: 0 | K10: 0 | L10: 160000 | M10: 200 | N10: 391219 | O10: 3000 | P10: 95 | Q10: 48 | R10: 30 | S10: 27 | T10: 758232 | U10: 25780373 | V10: 7526692 | W10: 2537 | X10: 8860 | Y10: 5387650 | Z10: 1110 | AA10: 877 | AB10: 1987 | AC10: 3761020 | AD10: 1107605 | AE10: 0 | AF10: 0 | AG10: 0 | AH10: 0 | AI10: 2937296 | AJ10: 7805921 | AK10: 5942057 | AL10: 420425 | AM10: 371370 | AN10: 6733852 | AO10: 224871 | AP10: 0 | AQ10: 97235 | AR10: 59671 | AS10: 381778 | AT10: =+N10+O10 -> 394219 | AU10: =+U10/V10 -> 3.425193 | AV10: =+AJ10/Y10 -> 1.4488545 | AW10: =+T10/D10 -> 140.7352 | AX10: =+V10/D10 -> 1397.0269 | AY10: =+G10/D10 -> 3592.2346 | AZ10: =SUM(G10:M10)/D10 -> 3626.353 | BA10: =+L10/D10 -> 29.697549
A11: Slovenia | B11: CEE | C11: C10 | D11: =+Y11/1000 -> 1995.333 | E11: 60 | F11: 299 | G11: 6159079 | H11: 9977 | I11: 16017 | J11: 14077 | K11: 197 | L11: 162201 | M11: 75 | N11: 330895 | O11: 13990 | P11: 75 | Q11: 50 | R11: 221 | S11: 0 | T11: 441968 | U11: 14379834 | V11: 6153186 | W11: 0 | X11: 0 | Y11: 1995333 | Z11: 613 | AA11: 172 | AB11: 785 | AC11: 9537356 | AD11: 5498740 | AE11: 0 | AF11: 0 | AG11: 0 | AH11: 0 | AI11: 6118976 | AJ11: 21155072 | AK11: 19875184 | AL11: 2115946 | AM11: 0 | AN11: 21991130 | AO11: 1645934 | AP11: 64090 | AQ11: 446477 | AR11: 421310 | AS11: 2577811 | AT11: =+N11+O11 -> 344885 | AU11: =+U11/V11 -> 2.3369737 | AV11: =+AJ11/Y11 -> 10.602276 | AW11: =+T11/D11 -> 221.50087 | AX11: =+V11/D11 -> 3083.789 | AY11: =+G11/D11 -> 3086.7424 | AZ11: =SUM(G11:M11)/D11 -> 3188.2513 | BA11: =+L11/D11 -> 81.290191
A12: Austria | B12: EU | C12: C11 | D12: =+Y12/1000 -> 8072.178 | E12: 984 | F12: 2016 | G12: 9110058 | P12: 100 | Q12: 29 | R12: 253 | S12: 253 | T12: 928834 | U12: 15727531 | V12: 9474312 | W12: 20180 | X12: 22471 | Y12: 8072178 | Z12: 776 | AA12: 859 | AB12: 1635 | AC12: 17859007 | AD12: 4834763 | AE12: 4468 | AF12: 114839 | AG12: 92480 | AH12: 13129 | AI12: 8977253 | AJ12: 31895939 | AK12: 28260013 | AL12: 1688240 | AM12: 1947653 | AN12: 31895906 | AT12: =+N12+O12 -> 0 | AU12: =+U12/V12 -> 1.6600183 | AV12: =+AJ12/Y12 -> 3.9513424 | AW12: =+T12/D12 -> 115.06609 | AX12: =+V12/D12 -> 1173.6996 | AY12: =+G12/D12 -> 1128.575 | AZ12: =SUM(G12:M12)/D12 -> 1128.575 | BA12: =+L12/D12 -> 0
A13: België Vlaamse Gemeenschap | B13: België Vlaamse Gemeenschap | C13: C12a
A14: Belgique-Communauté française | B14: Belgique-Communauté française | C14: C12b
A15: Belgium | B15: EU | C15: C12 | D15: =+Y15/1000 -> 9681.9 | E15: 495 | F15: 1490 | G15: 30531000 | I15: 140102 | L15: 1562025 | M15: 74830 | N15: 1602000 | O15: 153940 | Q15: 69 | T15: 2310000 | W15: 39000 | X15: 33000 | Y15: 9681900 | Z15: 2580 | AA15: 1360 | AB15: 3940 | AC15: 111271167 | AD15: 25546068 | AE15: 93326 | AF15: 3465493 | AG15: 13011249 | AH15: 4429 | AI15: 38316623 | AJ15: 191708355 | AK15: 172147770 | AL15: 7958908 | AM15: 9453971 | AN15: 189560649 | AT15: =+N15+O15 -> 1755940 | AU15: =+U15/V15 -> #DIV/0! | AV15: =+AJ15/Y15 -> 19.800696 | AW15: =+T15/D15 -> 238.58953 | AX15: =+V15/D15 -> 0 | AY15: =+G15/D15 -> 3153.41 | AZ15: =SUM(G15:M15)/D15 -> 3336.9439 | BA15: =+L15/D15 -> 161.33455
A16: Denmark | B16: EU | C16: C13 | D16: =+Y16/1000 -> 5294.762 | E16: 250 | F16: 892 | G16: 31432846 | I16: 93647 | K16: 411 | L16: 2596389 | M16: 29000 | N16: 2360148 | O16: 261494 | R16: 556 | S16: 344 | T16: 1826946 | U16: 85880017 | V16: 36186239 | W16: 814343 | X16: 11097694 | Y16: 5294762 | Z16: 2292 | AA16: 2650 | AB16: 4942 | AC16: 177068420 | AD16: 46536097 | AE16: 551 | AF16: 15755 | AG16: 46123 | AH16: 0 | AI16: 72546913 | AJ16: 296213859 | AK16: 263991710 | AL16: 14254117 | AM16: 17968033 | AN16: 296213859 | AO16: 5282210 | AP16: 0 | AQ16: 0 | AR16: 0 | AS16: 5282210 | AT16: =+N16+O16 -> 2621642 | AU16: =+U16/V16 -> 2.3732783 | AV16: =+AJ16/Y16 -> 55.944698 | AW16: =+T16/D16 -> 345.0478 | AX16: =+V16/D16 -> 6834.3467 | AY16: =+G16/D16 -> 5936.5928 | AZ16: =SUM(G16:M16)/D16 -> 6450.2036 | BA16: =+L16/D16 -> 490.36935
A17: Eire | B17: EU | C17: C15 | D17: =+Y17/1000 -> 3473 | E17: 32 | F17: 348 | G17: 10496739 | H17: 11715 | I17: 3685 | J17: 11739 | K17: 15440 | L17: 255990 | M17: 2500 | N17: 624573 | O17: 22973 | P17: 88 | Q17: 62 | R17: 385 | S17: 167 | T17: 862233 | U17: 12935846 | V17: 19210802 | W17: 1700 | X17: 4300 | Y17: 3473000 | Z17: 256 | AA17: 1076 | AB17: 1332 | AC17: 27170103 | AD17: 7361222 | AE17: 0 | AF17: 0 | AG17: 5685395 | AH17: 0 | AI17: 6685108 | AJ17: 46901828 | AK17: 41180048 | AL17: 1514386 | AM17: 4539866 | AN17: 47234300 | AO17: 1453448 | AP17: 313304 | AQ17: 256868 | AR17: 527095 | AS17: 2550716 | AT17: =+N17+O17 -> 647546 | AU17: =+U17/V17 -> 0.67336314 | AV17: =+AJ17/Y17 -> 13.504701 | AW17: =+T17/D17 -> 248.26749 | AX17: =+V17/D17 -> 5531.4719 | AY17: =+G17/D17 -> 3022.3838 | AZ17: =SUM(G17:M17)/D17 -> 3109.0723 | BA17: =+L17/D17 -> 73.708609
A18: Finland | B18: EU | C18: C16 | D18: =+Y18/1000 -> 5107.063 | E18: 436 | F18: 1202 | G18: 36831532 | I18: 96483 | L18: 2475817 | M18: 16617 | N18: 1635846 | O18: 206843 | P18: 95 | Q18: 95 | R18: 2100 | S18: 913 | T18: 2516020 | U18: 102138814 | V18: 64196325 | W18: 180024 | X18: 188335 | Y18: 5107063 | Z18: 1490 | AA18: 2740 | AB18: 4230 | AC18: 121421648 | AD18: 36064442 | AE18: 0 | AF18: 0 | AG18: 0 | AH18: 0 | AI18: 54389828 | AJ18: 211875918 | AK18: 194054899 | AL18: 0 | AM18: 17821019 | AN18: 211875918 | AO18: 15941564 | AP18: 620737 | AQ18: 4324319 | AR18: 4080560 | AS18: 24967180 | AT18: =+N18+O18 -> 1842689 | AU18: =+U18/V18 -> 1.5910383 | AV18: =+AJ18/Y18 -> 41.486842 | AW18: =+T18/D18 -> 492.65498 | AX18: =+V18/D18 -> 12570.106 | AY18: =+G18/D18 -> 7211.8813 | AZ18: =SUM(G18:M18)/D18 -> 7718.81 | BA18: =+L18/D18 -> 484.78294
A19: France | B19: EU | C19: C17 | D19: =+Y19/1000 -> 59209.385 | E19: 3556 | F19: 3758 | G19: 121346740 | I19: 202449 | L19: 7988500 | M19: 27956 | N19: 6183471 | O19: 735816 | P19: 72 | T19: 11761115 | U19: 279984807 | W19: 17667 | X19: 20237 | Y19: 59209385 | Z19: 6964 | AA19: 13248 | AB19: 20212 | AC19: 517990654 | AD19: 98442519 | AE19: 343334 | AF19: 12748956 | AG19: 47866161 | AH19: 16292 | AI19: 133205638 | AJ19: 810613554 | AK19: 734158053 | AL19: 20049602 | AM19: 5545020 | AN19: 759752675 | AO19: 92269844 | AP19: 2748167 | AQ19: 19144898 | AR19: 18065714 | AS19: 132228624 | AT19: =+N19+O19 -> 6919287 | AU19: =+U19/V19 -> #DIV/0! | AV19: =+AJ19/Y19 -> 13.690626 | AW19: =+T19/D19 -> 198.63599 | AX19: =+V19/D19 -> 0 | AY19: =+G19/D19 -> 2049.4511 | AZ19: =SUM(G19:M19)/D19 -> 2188.262 | BA19: =+L19/D19 -> 134.91949
A20: Greece | B20: EU | C20: C18 | D20: =+Y20/1000 -> 9872 | E20: 672 | F20: 829 | G20: 9088431 | H20: 150843 | I20: 119166 | J20: 1413606 | K20: 297413 | L20: 96021 | M20: 9163 | N20: 277536 | O20: 11488 | P20: 88 | Q20: 62 | R20: 1069 | S20: 465 | T20: 2649105 | U20: 1828799 | V20: 2285690 | W20: 8173 | X20: 11434 | Y20: 9872000 | Z20: 1029 | AA20: 805 | AB20: 1834 | AC20: 35270796 | AD20: 8097606 | AE20: 29583 | AF20: 1098494 | AG20: 4124313 | AH20: 1403 | AI20: 12145624 | AJ20: 60767819 | AT20: =+N20+O20 -> 289024 | AU20: =+U20/V20 -> 0.80010806 | AV20: =+AJ20/Y20 -> 6.1555732 | AW20: =+T20/D20 -> 268.34532 | AX20: =+V20/D20 -> 231.53262 | AY20: =+G20/D20 -> 920.62713 | AZ20: =SUM(G20:M20)/D20 -> 1131.9533 | BA20: =+L20/D20 -> 9.7266005
A21: Iceland | B21: EFTA | C21: C19 | D21: =+Y21/1000 -> 272.069 | E21: 167 | F21: 173 | G21: 2059646 | I21: 8067 | J21: 1236 | K21: 3178 | L21: 57129 | M21: 333 | N21: 53295 | O21: 3674 | T21: 72205 | U21: 2198507 | V21: 909227 | W21: 1978 | X21: 832 | Y21: 272069 | Z21: 88 | AA21: 207 | AB21: 295 | AC21: 3518151 | AD21: 1397688 | AE21: 0 | AF21: 30234 | AG21: 661670 | AH21: 806563 | AI21: 714134 | AJ21: 7128441 | AK21: 6685440 | AL21: 424443 | AM21: 126474 | AN21: 7236357 | AT21: =+N21+O21 -> 56969 | AU21: =+U21/V21 -> 2.4179957 | AV21: =+AJ21/Y21 -> 26.200857 | AW21: =+T21/D21 -> 265.39224 | AX21: =+V21/D21 -> 3341.8986 | AY21: =+G21/D21 -> 7570.3075 | AZ21: =SUM(G21:M21)/D21 -> 7827.3857 | BA21: =+L21/D21 -> 209.97982
A22: Italy | B22: EU | C22: C20 | D22: =+Y22/1000 -> 56609 | E22: 84 | F22: 6100 | G22: 41474000 | N22: 10254000 | W22: 429148 | X22: 477866 | Y22: 56609000 | Z22: 5984 | AA22: 17856 | AB22: 23840 | AT22: =+N22+O22 -> 10254000 | AU22: =+U22/V22 -> #DIV/0! | AV22: =+AJ22/Y22 -> 0 | AW22: =+T22/D22 -> 0 | AX22: =+V22/D22 -> 0 | AY22: =+G22/D22 -> 732.63969 | AZ22: =SUM(G22:M22)/D22 -> 732.63969 | BA22: =+L22/D22 -> 0
A23: Liechtenstein | B23: EFTA | C23: C21 | D23: =+Y23/1000 -> 30.147 | E23: 3 | F23: 3 | G23: 24000 | N23: 5200 | S23: 1 | U23: 75000 | W23: 1257 | X23: 949 | Y23: 30147 | Z23: 2 | AA23: 3 | AB23: 5 | AT23: =+N23+O23 -> 5200 | AU23: =+U23/V23 -> #DIV/0! | AV23: =+AJ23/Y23 -> 0 | AW23: =+T23/D23 -> 0 | AX23: =+V23/D23 -> 0 | AY23: =+G23/D23 -> 796.09911 | AZ23: =SUM(G23:M23)/D23 -> 796.09911 | BA23: =+L23/D23 -> 0
A24: Luxembourg | B24: EU | C24: C22 | D24: =+Y24/1000 -> 372 | E24: 13 | F24: 13 | G24: 268401 | H24: 357 | I24: 334 | J24: 0 | K24: 0 | L24: 999 | M24: 202 | N24: 83855 | O24: 288 | P24: 88 | Q24: 40 | R24: 19 | S24: 3 | T24: 25478 | U24: 202643 | V24: 65745 | W24: 1726 | X24: 3086 | Y24: 372000 | Z24: 19 | AA24: 5 | AB24: 23 | AC24: 941138 | AD24: 216796 | AE24: 352 | AF24: 18 | AG24: 32730 | AH24: 35193 | AI24: 27780 | AJ24: 1254006 | AO24: 7626 | AP24: 254 | AQ24: 1769 | AR24: 1659 | AS24: 11309 | AT24: =+N24+O24 -> 84143 | AU24: =+U24/V24 -> 3.0822572 | AV24: =+AJ24/Y24 -> 3.3709839 | AW24: =+T24/D24 -> 68.489247 | AX24: =+V24/D24 -> 176.73387 | AY24: =+G24/D24 -> 721.50806 | AZ24: =SUM(G24:M24)/D24 -> 726.59409 | BA24: =+L24/D24 -> 2.6854839
A25: Netherlands | B25: EU | C25: C23 | D25: =+Y25/1000 -> 14608 | E25: 579 | F25: 1130 | G25: 41489000 | N25: 2608000 | U25: 158887000 | W25: 109148 | X25: 121539 | Y25: 14608000 | Z25: 2510 | AA25: 5898 | AB25: 8408 | AC25: 226978442 | AD25: 59552732 | AE25: 265160 | AF25: 29773636 | AG25: 58334809 | AH25: 11856 | AI25: 45158741 | AJ25: 420075376 | AK25: 279143854 | AL25: 51964741 | AM25: 88966781 | AN25: 420075376 | AT25: =+N25+O25 -> 2608000 | AU25: =+U25/V25 -> #DIV/0! | AV25: =+AJ25/Y25 -> 28.756529 | AW25: =+T25/D25 -> 0 | AX25: =+V25/D25 -> 0 | AY25: =+G25/D25 -> 2840.1561 | AZ25: =SUM(G25:M25)/D25 -> 2840.1561 | BA25: =+L25/D25 -> 0
A26: Norway | B26: EFTA | C26: C24 | D26: =+Y26/1000 -> 4360 | E26: 435 | F26: 1159 | G26: 20508094 | H26: 20904 | I26: 46822 | J26: 37376 | K26: 298543 | L26: 1010676 | M26: 3158 | N26: 853271 | O26: 104732 | P26: 81 | Q26: 64 | R26: 354 | S26: 154 | T26: 1300760 | U26: 22203517 | V26: 19857745 | W26: 112387 | X26: 143970 | Y26: 4360000 | Z26: 909 | AA26: 962 | AB26: 1871 | AC26: 60711395 | AD26: 15803362 | AE26: 0 | AF26: 2342177 | AG26: 8676566 | AH26: 0 | AI26: 12603057 | AJ26: 100136557 | AK26: 92512979 | AL26: 5873433 | AM26: 1750145 | AN26: 100136557 | AT26: =+N26+O26 -> 958003 | AU26: =+U26/V26 -> 1.1181288 | AV26: =+AJ26/Y26 -> 22.9671 | AW26: =+T26/D26 -> 298.33945 | AX26: =+V26/D26 -> 4554.5287 | AY26: =+G26/D26 -> 4703.6913 | AZ26: =SUM(G26:M26)/D26 -> 5028.8011 | BA26: =+L26/D26 -> 231.80642
A27: Portugal | B27: EU | C27: C25 | D27: =+Y27/1000 -> 10108 | E27: 168 | F27: 226 | G27: 9559086 | K27: 1328 | L27: 221269 | N27: 876610 | O27: 50308 | R27: 233 | T27: 3249669 | U27: 2090341 | W27: 816 | X27: 5 | Y27: 10108000 | Z27: 882 | AA27: 784 | AB27: 1666 | AC27: 11879052 | AD27: 2877083 | AE27: 24 | AF27: 699 | AG27: 2047 | AH27: 4179 | AI27: 3219448 | AJ27: 17982532 | AK27: 28954746 | AL27: 279114 | AM27: 581115 | AN27: 29814975 | AO27: 11287569 | AP27: 0 | AQ27: 0 | AR27: 337859 | AS27: 11625427 | AT27: =+N27+O27 -> 926918 | AU27: =+U27/V27 -> #DIV/0! | AV27: =+AJ27/Y27 -> 1.7790396 | AW27: =+T27/D27 -> 321.49476 | AX27: =+V27/D27 -> 0 | AY27: =+G27/D27 -> 945.69509 | AZ27: =SUM(G27:M27)/D27 -> 967.71696 | BA27: =+L27/D27 -> 21.890483
A28: Spain | B28: EU | C28: C26 | D28: =+Y28/1000 -> 38245 | E28: 4400 | F28: 5209 | G28: 36714000 | H28: 163345 | I28: 157270 | J28: 49573 | K28: 306000 | L28: 979000 | M28: 24000 | N28: 1836000 | O28: 98000 | P28: 88 | Q28: 62 | R28: 4198 | S28: 1826 | T28: 6119000 | U28: 22110997 | V28: 209157219 | W28: 122000 | X28: 5000 | Y28: 38245000 | Z28: 4139 | AA28: 2469 | AB28: 6608 | AC28: 87790002 | AD28: 22574572 | AE28: 0 | AF28: 0 | AG28: 0 | AH28: 0 | AI28: 15049715 | AJ28: 125414288 | AK28: 111110833 | AL28: 6640938 | AM28: 7662517 | AN28: 125414288 | AT28: =+N28+O28 -> 1934000 | AU28: =+U28/V28 -> 0.10571472 | AV28: =+AJ28/Y28 -> 3.2792336 | AW28: =+T28/D28 -> 159.99477 | AX28: =+V28/D28 -> 5468.8775 | AY28: =+G28/D28 -> 959.96862 | AZ28: =SUM(G28:M28)/D28 -> 1003.8747 | BA28: =+L28/D28 -> 25.598117
A29: Sweden | B29: EU | C29: C27 | D29: =+Y29/1000 -> 8847.629 | E29: 288 | F29: 1609 | G29: 43659000 | H29: 69138 | I29: 105638 | J29: 0 | K29: 0 | L29: 2439000 | M29: 0 | N29: 1858000 | O29: 173000 | P29: 87 | U29: 80479000 | V29: 48000000 | W29: 0 | X29: 0 | Y29: 8847629 | Z29: 2360 | AA29: 2868 | AB29: 5228 | AC29: 157033557 | AD29: 40985208 | AE29: 457769 | AF29: 16998290 | AG29: 63820355 | AH29: 21722 | AI29: 48589960 | AJ29: 327906861 | AK29: 290527951 | AL29: 17356005 | AM29: 20022905 | AN29: 327906861 | AO29: 5873708 | AP29: 228712 | AQ29: 1593306 | AR29: 1503492 | AS29: 9199218 | AT29: =+N29+O29 -> 2031000 | AU29: =+U29/V29 -> 1.6766458 | AV29: =+AJ29/Y29 -> 37.061552 | AW29: =+T29/D29 -> 0 | AX29: =+V29/D29 -> 5425.1823 | AY29: =+G29/D29 -> 4934.5424 | AZ29: =SUM(G29:M29)/D29 -> 5229.9634 | BA29: =+L29/D29 -> 275.66707
A30: Switzerland | B30: EFTA | C30: C28 | D30: =+Y30/1000 -> 6862 | E30: 44 | F30: 2344 | G30: 27971000 | N30: 1201000 | U30: 5916000 | V30: 30404750 | W30: 287880 | X30: 217352 | Y30: 6862000 | Z30: 1841 | AA30: 3476 | AB30: 5317 | AT30: =+N30+O30 -> 1201000 | AU30: =+U30/V30 -> 0.19457486 | AV30: =+AJ30/Y30 -> 0 | AW30: =+T30/D30 -> 0 | AX30: =+V30/D30 -> 4430.8875 | AY30: =+G30/D30 -> 4076.2168 | AZ30: =SUM(G30:M30)/D30 -> 4076.2168 | BA30: =+L30/D30 -> 0
A31: UK | B31: EU | C31: C29 | D31: =+Y31/1000 -> 59006.9 | E31: 190 | F31: 4657 | G31: 128040000 | H31: 76000 | I31: 123000 | J31: 100000 | K31: 8588000 | L31: 7333000 | M31: 95700 | N31: 10466000 | O31: 1344000 | P31: 87 | R31: 8800 | S31: 1000 | T31: 34224000 | U31: 517832000 | V31: 355974000 | W31: 0 | X31: 0 | Y31: 59006900 | Z31: 6388 | AA31: 19548 | AB31: 25936 | AC31: 637750179 | AD31: 175687270 | AE31: 1250896 | AF31: 31798170 | AG31: 138018847 | AH31: 0 | AI31: 166981557 | AJ31: 1151486919 | AK31: 1045652179 | AL31: 60892086 | AM31: 44942153 | AN31: 1151486418 | AO31: 24532575 | AP31: 1418452 | AQ31: 9799163 | AR31: 8643662 | AS31: 44393853 | AT31: =+N31+O31 -> 11810000 | AU31: =+U31/V31 -> 1.4546905 | AV31: =+AJ31/Y31 -> 19.514445 | AW31: =+T31/D31 -> 579.99997 | AX31: =+V31/D31 -> 6032.7521 | AY31: =+G31/D31 -> 2169.9157 | AZ31: =SUM(G31:M31)/D31 -> 2446.4207 | BA31: =+L31/D31 -> 124.2736
A32: Germany | B32: EU | C32: C31 | D32: =+Y32/1000 -> 82012.162 | E32: 10483 | F32: 12532 | G32: 114887722 | I32: 147845 | L32: 9268822 | P32: 88 | T32: 9955638 | U32: 316578515 | V32: 434811593 | W32: 447899 | X32: 498745 | Y32: 82012162 | Z32: 9824 | AA32: 6157 | AB32: 15981 | AC32: 471353495 | AD32: 90354137 | AE32: 0 | AF32: 0 | AG32: 0 | AH32: 0 | AI32: 184754346 | AJ32: 746461978 | AK32: 625391425 | AL32: 53557997 | AM32: 67512556 | AN32: 746461978 | AO32: 29132150 | AP32: 1134356 | AQ32: 7902405 | AR32: 7456952 | AS32: 45625864 | AT32: =+N32+O32 -> 0 | AU32: =+U32/V32 -> 0.72808205 | AV32: =+AJ32/Y32 -> 9.1018449 | AW32: =+T32/D32 -> 121.39221 | AX32: =+V32/D32 -> 5301.7941 | AY32: =+G32/D32 -> 1400.862 | AZ32: =SUM(G32:M32)/D32 -> 1515.6824 | BA32: =+L32/D32 -> 113.01765
A33: USA | B33: World - A | C33: C50 | D33: =+Y33/1000 -> 263959 | E33: 8967 | F33: 16090 | G33: 714148203 | I33: 1919000 | J33: 0 | L33: 41793000 | M33: 1001000 | N33: 12296000 | O33: 3535000 | P33: 100 | S33: 6483 | U33: 1690203000 | V33: 1057775000 | W33: 1358097 | X33: 6886563 | Y33: 263959000 | Z33: 40161 | AA33: 80589 | AB33: 120750 | AC33: 3321324862 | AD33: 785134337 | AE33: 8029 | AF33: 229469 | AG33: 671758 | AH33: 1371384 | AI33: 1056617643 | AJ33: 5165357483 | AK33: 5012515457 | AL33: 227361639 | AM33: 286600806 | AN33: 5526477902 | AT33: =+N33+O33 -> 15831000 | AU33: =+U33/V33 -> 1.5978852 | AV33: =+AJ33/Y33 -> 19.568787 | AW33: =+T33/D33 -> 0 | AX33: =+V33/D33 -> 4007.3458 | AY33: =+G33/D33 -> 2705.527 | AZ33: =SUM(G33:M33)/D33 -> 2874.9207 | BA33: =+L33/D33 -> 158.33141
A34: Turkey | B34: World - B | C34: C42 | D34: =+Y34/1000 -> 64989.482 | E34: 1310 | F34: 1811 | G34: 11296391 | I34: 79 | J34: 161743 | K34: 5779 | L34: 101961 | M34: 370 | Q34: 12 | S34: 7 | T34: 970316 | U34: 4707687 | V34: 23121725 | W34: 22420 | X34: 113684 | Y34: 64989482 | Z34: 267 | AA34: 2895 | AB34: 3162 | AC34: 9303900 | AD34: 0 | AE34: 0 | AF34: 320187 | AG34: 11431055 | AH34: 1893785 | AI34: 0 | AJ34: 22948927 | AK34: 20511930 | AL34: 985905 | AM34: 1178726 | AN34: 22676561 | AT34: =+N34+O34 -> 0 | AU34: =+U34/V34 -> 0.20360449 | AV34: =+AJ34/Y34 -> 0.35311756 | AW34: =+T34/D34 -> 14.930354 | AX34: =+V34/D34 -> 355.77642 | AY34: =+G34/D34 -> 173.81876 | AZ34: =SUM(G34:M34)/D34 -> 177.97223 | BA34: =+L34/D34 -> 1.5688846
A35: Australia | B35: World - A | C35: C70 | D35: =+Y35/1000 -> 18658.664 | Y35: 18658664 | AT35: =+N35+O35 -> 0 | AU35: =+U35/V35 -> #DIV/0! | AV35: =+AJ35/Y35 -> 0 | AW35: =+T35/D35 -> 0 | AX35: =+V35/D35 -> 0 | AY35: =+G35/D35 -> 0 | AZ35: =SUM(G35:M35)/D35 -> 0 | BA35: =+L35/D35 -> 0
A36: Japan | B36: World - A | C36: C41 | D36: =+Y36/1000 -> 125257 | E36: 1600 | F36: 2499 | G36: 260995000 | N36: 19284000 | T36: 33062000 | U36: 453122000 | W36: 855080 | X36: 4335893 | Y36: 125257000 | Z36: 10836 | AA36: 14103 | AB36: 24939 | AC36: 570236373 | AD36: 290753453 | AE36: 1278 | AF36: 36516 | AG36: 106898 | AH36: 218231 | AI36: 168141410 | AJ36: 1029494159 | AK36: 920169909 | AL36: 44227913 | AM36: 52877920 | AN36: 1017275742 | AT36: =+N36+O36 -> 19284000 | AU36: =+U36/V36 -> #DIV/0! | AV36: =+AJ36/Y36 -> 8.2190549 | AW36: =+T36/D36 -> 263.95331 | AX36: =+V36/D36 -> 0 | AY36: =+G36/D36 -> 2083.676 | AZ36: =SUM(G36:M36)/D36 -> 2083.676 | BA36: =+L36/D36 -> 0
A37: Korea | B37: World - A | C37: C40 | D37: =+Y37/1000 -> 47495 | Y37: 47495000 | AT37: =+N37+O37 -> 0 | AU37: =+U37/V37 -> #DIV/0! | AV37: =+AJ37/Y37 -> 0 | AW37: =+T37/D37 -> 0 | AX37: =+V37/D37 -> 0 | AY37: =+G37/D37 -> 0 | AZ37: =SUM(G37:M37)/D37 -> 0 | BA37: =+L37/D37 -> 0
A38: Canada | B38: World - A | C38: C51 | D38: =+Y38/1000 -> 31000 | E38: 2739 | F38: 910 | G38: 75032608 | I38: 150814 | U38: 331565367 | Y38: 31000000 | Z38: 6733 | AA38: 6616 | AB38: 13349 | AC38: 313061342 | AD38: 67669552 | AE38: 0 | AF38: 0 | AG38: 0 | AH38: 0 | AI38: 101611118 | AJ38: 482342012 | AK38: 436299213 | AL38: 20970696 | AM38: 25072103 | AN38: 482342012 | AO38: 15950238 | AP38: 549360 | AQ38: 3827073 | AR38: 3611344 | AS38: 23938015 | AT38: =+N38+O38 -> 0 | AU38: =+U38/V38 -> #DIV/0! | AV38: =+AJ38/Y38 -> 15.55942 | AW38: =+T38/D38 -> 0 | AX38: =+V38/D38 -> 0 | AY38: =+G38/D38 -> 2420.4067 | AZ38: =SUM(G38:M38)/D38 -> 2425.2717 | BA38: =+L38/D38 -> 0
A39: New Zealand | B39: World - A | C39: C71 | D39: =+Y39/1000 -> 3807 | Y39: 3807000 | AT39: =+N39+O39 -> 0 | AU39: =+U39/V39 -> #DIV/0! | AV39: =+AJ39/Y39 -> 0 | AW39: =+T39/D39 -> 0 | AX39: =+V39/D39 -> 0 | AY39: =+G39/D39 -> 0 | AZ39: =SUM(G39:M39)/D39 -> 0 | BA39: =+L39/D39 -> 0
A40: Mexico | B40: World - B | C40: C72 | D40: =+Y40/1000 -> 92714.353 | Y40: 92714353 | AT40: =+N40+O40 -> 0 | AU40: =+U40/V40 -> #DIV/0! | AV40: =+AJ40/Y40 -> 0 | AW40: =+T40/D40 -> 0 | AX40: =+V40/D40 -> 0 | AY40: =+G40/D40 -> 0 | AZ40: =SUM(G40:M40)/D40 -> 0 | BA40: =+L40/D40 -> 0
A41: CEE | B41: Totals | D41: =+Y41/1000 -> 105515 | E41: 29982 | F41: 28785 | G41: 398410673 | H41: 301220 | I41: 538368 | J41: 222774 | K41: 146204 | L41: 5748025 | M41: 4433 | N41: 10773122 | O41: 202523 | P41: 75 | Q41: 30 | R41: 1047 | S41: 362 | T41: 15751305 | U41: 434989954 | V41: 142307399 | W41: 239135 | X41: 258720 | Y41: 105514996 | Z41: 32462 | AA41: 12461 | AB41: 44924 | AC41: 111083944 | AD41: 38369448 | AE41: 11560 | AF41: 297116 | AG41: 239267 | AH41: 1866220 | AI41: 70022992 | AJ41: 221890541 | AK41: 189087268 | AL41: 8419460 | AM41: 28726602 | AN41: 226233334 | AO41: 11416024 | AP41: 600134 | AQ41: 4226896 | AR41: 4248013 | AS41: 20491069 | AT41: =+N41+O41 -> 10975645 | AU41: =+U41/V41 -> 3.0566925 | AV41: =+AJ41/Y41 -> 2.102929 | AW41: =+T41/D41 -> 149.28025 | AX41: =+V41/D41 -> 1348.6936 | AY41: =+G41/D41 -> 3775.8678 | AZ41: =SUM(G41:M41)/D41 -> 3841.8397 | BA41: =+L41/D41 -> 54.475906
A42: EU | B42: Totals | D42: =+Y42/1000 -> 370518.98 | E42: 22630 | F42: 41996 | G42: 667882429 | H42: 1517711 | I42: 1552438 | J42: 2625114 | K42: 16895521 | L42: 45432211 | M42: 553309 | N42: 52744051 | O42: 5606677 | P42: 87 | Q42: 65 | R42: 38366 | S42: 13908 | T42: 97898313 | U42: 1923113310 | V42: 1972265456 | W42: 2191824 | X42: 12483712 | Y42: 370518979 | Z42: 47493 | AA42: 78323 | AB42: 125815 | AC42: 3098115761 | AD42: 733081749 | AE42: 2861758 | AF42: 111472587 | AG42: 389072711 | AH42: 127957 | AI42: 960964332 | AJ42: 5295696853 | AK42: 4637505163 | AL42: 279231939 | AM42: 332157159 | AN42: 5248894259 | AO42: 260503246 | AP42: 8977228 | AQ42: 60499261 | AR42: 57005983 | AS42: 386985723 | AT42: =+N42+O42 -> 58350728 | AU42: =+U42/V42 -> 0.97507833 | AV42: =+AJ42/Y42 -> 14.292647 | AW42: =+T42/D42 -> 264.21943 | AX42: =+V42/D42 -> 5322.9809 | AY42: =+G42/D42 -> 1802.5593 | AZ42: =SUM(G42:M42)/D42 -> 1987.6411 | BA42: =+L42/D42 -> 122.61777
A43: EFTA | B43: Totals | D43: =+Y43/1000 -> 11524.216 | E43: 649 | F43: 3679 | G43: 50562740 | H43: 61493 | I43: 137737 | J43: 103885 | K43: 821277 | L43: 2595505 | M43: 8846 | N43: 2112766 | O43: 212612 | P43: 81 | Q43: 74 | R43: 941 | S43: 409 | T43: 3457083 | U43: 30393024 | V43: 51304571 | W43: 403502 | X43: 363103 | Y43: 11524216 | Z43: 2840 | AA43: 4648 | AB43: 7488 | AC43: 209372023 | AD43: 70402404 | AE43: 0 | AF43: 5386904 | AG43: 32540642 | AH43: 8723238 | AI43: 59620735 | AJ43: 386045947 | AK43: 264050656 | AL43: 16763960 | AM43: 4995265 | AN43: 285809881 | AO43: 15015461 | AP43: 517164 | AQ43: 3602785 | AR43: 3399698 | AS43: 22535109 | AT43: =+N43+O43 -> 2325378 | AU43: =+U43/V43 -> 0.59240382 | AV43: =+AJ43/Y43 -> 33.498673 | AW43: =+T43/D43 -> 299.98422 | AX43: =+V43/D43 -> 4451.8925 | AY43: =+G43/D43 -> 4387.521 | AZ43: =SUM(G43:M43)/D43 -> 4711.0782 | BA43: =+L43/D43 -> 225.22183
A44: World A | B44: Totals | D44: =+Y44/1000 -> 490176.66 | E44: 15614 | F44: 22798 | G44: 1200283871 | H44: 563324 | I44: 2317686 | J44: 195586 | K44: 11798905 | L44: 52492751 | M44: 1198483 | N44: 42752472 | O44: 4476106 | P44: 90 | Q44: 62 | R44: 11587 | S44: 8473 | T44: 112885602 | U44: 2752092370 | V44: 2250867911 | W44: 2811445 | X44: 14256116 | Y44: 490176664 | Z44: 64983 | AA44: 111004 | AB44: 175985 | AC44: 4703084797 | AD44: 1321507726 | AE44: 10691 | AF44: 305244 | AG44: 938610 | AH44: 1754262 | AI44: 1479582133 | AJ44: 7507183463 | AK44: 7110835944 | AL44: 328217290 | AM44: 407181605 | AN44: 7846234840 | AO44: 382402103 | AP44: 13170734 | AQ44: 91752923 | AR44: 86580877 | AS44: 573906643 | AT44: =+N44+O44 -> 47228578 | AU44: =+U44/V44 -> 1.2226805 | AV44: =+AJ44/Y44 -> 15.315261 | AW44: =+T44/D44 -> 230.29575 | AX44: =+V44/D44 -> 4591.9524 | AY44: =+G44/D44 -> 2448.6761 | AZ44: =SUM(G44:M44)/D44 -> 2588.5578 | BA44: =+L44/D44 -> 107.08945
A45: World B | B45: Totals | D45: =+Y45/1000 -> 157703.83 | E45: 2954 | F45: 4079 | G45: 25444841 | H45: 96642 | I45: 178 | J45: 364322 | K45: 13017 | L45: 229665 | M45: 833 | N45: 1202137 | O45: 20858 | P45: 88 | Q45: 12 | R45: 1989 | S45: 16 | T45: 2185613 | U45: 10603948 | V45: 52081113 | W45: 50500 | X45: 256070 | Y45: 157703835 | Z45: 601 | AA45: 6521 | AB45: 7122 | AC45: 20956804 | AD45: 0 | AE45: 0 | AF45: 721213 | AG45: 25748168 | AH45: 4265704 | AI45: 0 | AJ45: 51691890 | AK45: 46233745 | AL45: 2250348 | AM45: 2690466 | AN45: 51174560 | AO45: 2777859 | AP45: 95676 | AQ45: 666515 | AR45: 628944 | AS45: 4168994 | AT45: =+N45+O45 -> 1222995 | AU45: =+U45/V45 -> 0.20360448 | AV45: =+AJ45/Y45 -> 0.32777827 | AW45: =+T45/D45 -> 13.858972 | AX45: =+V45/D45 -> 330.24633 | AY45: =+G45/D45 -> 161.34573 | AZ45: =SUM(G45:M45)/D45 -> 165.81396 | BA45: =+L45/D45 -> 1.4563057
A46: EU Accession Countries | B46: Totals | D46: =+Y46/1000 -> 75162.224 | E46: 22798 | F46: 21310 | G46: 308202479 | H46: 287044 | I46: 440954 | J46: 144101 | K46: 139921 | L46: 5025513 | M46: 4172 | N46: 9524410 | O46: 193776 | P46: 75 | Q46: 30 | R46: 989 | S46: 336 | T46: 13193274 | U46: 379944973 | V46: 118127770 | W46: 226083 | X46: 241774 | Y46: 75162224 | Z46: 25655 | AA46: 10809 | AB46: 36465 | AC46: 106911542 | AD46: 36843545 | AE46: 11799 | AF46: 308865 | AG46: 302293 | AH46: 1826004 | AI46: 69430922 | AJ46: 215634964 | AK46: 185264782 | AL46: 8468169 | AM46: 26211914 | AN46: 219944868 | AO46: 11133150 | AP46: 575166 | AQ46: 4089194 | AR46: 4129467 | AS46: 19926978 | AT46: =+N46+O46 -> 9718186 | AU46: =+U46/V46 -> 3.21639 | AV46: =+AJ46/Y46 -> 2.8689274 | AW46: =+T46/D46 -> 175.53065 | AX46: =+V46/D46 -> 1571.6375 | AY46: =+G46/D46 -> 4100.4971 | AZ46: =SUM(G46:M46)/D46 -> 4180.8793 | BA46: =+L46/D46 -> 66.862218
A47: Europe (Excl. Malta & Cyprus) | B47: Totals | D47: =+Y47/1000 -> 487558.19 | E47: 53261 | F47: 74460 | G47: 1116855842 | H47: 1880424 | I47: 2228543 | J47: 2951773 | K47: 17863002 | L47: 53775741 | M47: 566588 | N47: 65629939 | O47: 6021812 | P47: 81 | Q47: 56 | R47: 40354 | S47: 14679 | T47: 117106701 | U47: 2388496288 | V47: 2165877426 | W47: 2834461 | X47: 13105535 | Y47: 487558191 | Z47: 82795 | AA47: 95432 | AB47: 178227 | AC47: 3418571728 | AD47: 841853601 | AE47: 2873318 | AF47: 117156607 | AG47: 421852620 | AH47: 10717415 | AI47: 1090608059 | AJ47: 5903633341 | AK47: 5090643087 | AL47: 304415359 | AM47: 365879026 | AN47: 5760937474 | AO47: 286934731 | AP47: 10094526 | AQ47: 68328942 | AR47: 64653694 | AS47: 430011901 | AT47: =+N47+O47 -> 71651751 | AU47: =+U47/V47 -> 1.1027846 | AV47: =+AJ47/Y47 -> 12.108572 | AW47: =+T47/D47 -> 240.1902 | AX47: =+V47/D47 -> 4442.2952 | AY47: =+G47/D47 -> 2290.7129 | AZ47: =SUM(G47:M47)/D47 -> 2453.2906 | BA47: =+L47/D47 -> 110.29605
A48: Eastern Europe | B48: Totals | D48: =+Y48/1000 -> 97789.866 | E48: 28321 | F48: 25500 | G48: 349734050 | H48: 267378 | I48: 474628 | J48: 211809 | K48: 142609 | L48: 5309506 | M48: 3468 | N48: 8987782 | O48: 188800 | P48: 74 | Q48: 33 | R48: 1022 | S48: 362 | T48: 14057917 | U48: 381692701 | V48: 125084482 | W48: 229900 | X48: 255835 | Y48: 97789866 | Z48: 26606 | AA48: 10874 | AB48: 37481 | AC48: 99396414 | AD48: 34112606 | AE48: 11560 | AF48: 297116 | AG48: 239267 | AH48: 1866220 | AI48: 63571336 | AJ48: 199494514 | AK48: 166395544 | AL48: 8026698 | AM48: 28020579 | AN48: 202442825 | AO48: 10070624 | AP48: 584831 | AQ48: 4120289 | AR48: 3854966 | AS48: 18630712 | AT48: =+N48+O48 -> 9176582 | AU48: =+U48/V48 -> 3.0514792 | AV48: =+AJ48/Y48 -> 2.0400326 | AW48: =+T48/D48 -> 143.75638 | AX48: =+V48/D48 -> 1279.115 | AY48: =+G48/D48 -> 3576.3834 | AZ48: =SUM(G48:M48)/D48 -> 3641.9259 | BA48: =+L48/D48 -> 54.295053
A49: Baltic States | B49: Totals | D49: =+Y49/1000 -> 7725.13 | E49: 1661 | F49: 3285 | G49: 48676623 | H49: 33842 | I49: 63740 | J49: 10965 | K49: 3595 | L49: 438519 | M49: 965 | N49: 1785340 | O49: 13723 | P49: 79 | Q49: 22 | R49: 25 | S49: 0 | T49: 1693388 | U49: 53297253 | V49: 17222917 | W49: 9235 | X49: 2885 | Y49: 7725130 | Z49: 5856 | AA49: 1587 | AB49: 7443 | AC49: 11687530 | AD49: 4256842 | AE49: 0 | AF49: 0 | AG49: 0 | AH49: 0 | AI49: 6451656 | AJ49: 22396027 | AK49: 22691724 | AL49: 392762 | AM49: 706023 | AN49: 23790509 | AO49: 1345400 | AP49: 15303 | AQ49: 106607 | AR49: 393047 | AS49: 1860357 | AT49: =+N49+O49 -> 1799063 | AU49: =+U49/V49 -> 3.0945544 | AV49: =+AJ49/Y49 -> 2.8991133 | AW49: =+T49/D49 -> 219.20511 | AX49: =+V49/D49 -> 2229.4663 | AY49: =+G49/D49 -> 6301.0749 | AZ49: =SUM(G49:M49)/D49 -> 6372.4816 | BA49: =+L49/D49 -> 56.765258
A50: Central Europe | B50: Totals | D50: =+Y50/1000 -> 243327.67 | E50: 16379 | F50: 28276 | G50: 487118534 | H50: 876634 | I50: 821117 | J50: 856459 | K50: 14553344 | L50: 30820429 | M50: 396903 | N50: 34852111 | O50: 4000944 | P50: 86 | Q50: 63 | R50: 23645 | S50: 7404 | T50: 66054125 | U50: 1376614342 | V50: 1279426188 | W50: 926457 | X50: 921679 | Y50: 243327672 | Z50: 31160 | AA50: 51630 | AB50: 82789 | AC50: 2156456662 | AD50: 515196861 | AE50: 1957536 | AF50: 80915605 | AG50: 286244077 | AH50: 7997574 | AI50: 630410590 | AJ50: 3679178904 | AK50: 3095803805 | AL50: 208354720 | AM50: 226302236 | AN50: 3530460760 | AO50: 180056157 | AP50: 6714473 | AQ50: 44757365 | AR50: 41882544 | AS50: 273410546 | AT50: =+N50+O50 -> 38853055 | AU50: =+U50/V50 -> 1.0759623 | AV50: =+AJ50/Y50 -> 15.120265 | AW50: =+T50/D50 -> 271.46162 | AX50: =+V50/D50 -> 5258.0382 | AY50: =+G50/D50 -> 2001.9036 | AZ50: =SUM(G50:M50)/D50 -> 2200.5036 | BA50: =+L50/D50 -> 126.66224
A51: Northern Europe | B51: Totals | D51: =+Y51/1000 -> 23881.523 | E51: 1576 | F51: 5035 | G51: 134491118 | H51: 137071 | I51: 350657 | J51: 109249 | K51: 626002 | L51: 8579011 | M51: 49108 | N51: 6760560 | O51: 749743 | P51: 86 | Q51: 72 | R51: 3976 | S51: 1831 | T51: 7938910 | U51: 292899855 | V51: 169149536 | W51: 1108732 | X51: 11430831 | Y51: 23881523 | Z51: 7139 | AA51: 9427 | AB51: 16566 | AC51: 519753171 | AD51: 140786797 | AE51: 458320 | AF51: 19386456 | AG51: 73204714 | AH51: 828285 | AI51: 188843892 | AJ51: 943261636 | AK51: 847772979 | AL51: 37907998 | AM51: 57688576 | AN51: 943369552 | AO51: 32692953 | AP51: 1042169 | AQ51: 7260194 | AR51: 6850940 | AS51: 47846256 | AT51: =+N51+O51 -> 7510303 | AU51: =+U51/V51 -> 1.7316031 | AV51: =+AJ51/Y51 -> 39.497549 | AW51: =+T51/D51 -> 332.42897 | AX51: =+V51/D51 -> 7082.8622 | AY51: =+G51/D51 -> 5631.5972 | AZ51: =SUM(G51:M51)/D51 -> 6044.0959 | BA51: =+L51/D51 -> 359.23216
A52: Southern Europe | B52: Totals | D52: =+Y52/1000 -> 114834 | E52: 5324 | F52: 12364 | G52: 96835517 | H52: 565499 | I52: 518401 | J52: 1763291 | K52: 2537452 | L52: 8628276 | M52: 116144 | N52: 13244146 | O52: 1068602 | P52: 88 | Q52: 62 | R52: 11686 | S52: 5082 | T52: 27362361 | U52: 283992137 | V52: 574994303 | W52: 560137 | X52: 494305 | Y52: 114834000 | Z52: 12034 | AA52: 21914 | AB52: 33948 | AC52: 631277951 | AD52: 147500495 | AE52: 445902 | AF52: 16557430 | AG52: 62164562 | AH52: 25336 | AI52: 201330585 | AJ52: 1059302260 | AK52: 957979035 | AL52: 49733181 | AM52: 53161612 | AN52: 1060873828 | AO52: 62769597 | AP52: 1737750 | AQ52: 12084487 | AR52: 11672197 | AS52: 88264030 | AT52: =+N52+O52 -> 14312748 | AU52: =+U52/V52 -> 0.49390426 | AV52: =+AJ52/Y52 -> 9.2246396 | AW52: =+T52/D52 -> 238.27752 | AX52: =+V52/D52 -> 5007.1782 | AY52: =+G52/D52 -> 843.26521 | AZ52: =SUM(G52:M52)/D52 -> 966.30423 | BA52: =+L52/D52 -> 75.136946

Sheet 2001 Grossed
A1: Name | B1: Type | C1: Code | D1: Population '000s | E1: Libraries - Total Administrative Units | F1: Libraries - Service Points | G1: Collections - Books & Bound Periodicals | H1: Collections - Current Periodicals - Titles | I1: Collections - Current Periodicals - Subscriptions | J1: Collections - Manuscripts | K1: Collections - Microforms | L1: Collections - Audio-visual Materials | M1: Collections - CD-ROMs | N1: Additions - Books & Bound Periodicals | O1: Additions - Audio-visual Materials | P1: Facilities & Services - Percentage Stock on Open Access | Q1: Facilities & Services - Percentage Catalogue Records Automated | R1: Facilities & Services - Number of Workstations for users | S1: Facilities & Services - Number connected to the internet | T1: Use & Users - Registered Users | U1: Use & Users - Loan Transactions | V1: Use & Users - Number of Visits | W1: Use & Users - Number of virtual referrals and transactions | X1: Use & Users - Number of virtual visits to networked library services | Y1: Use & Users - Potential Total Population Served | Z1: Library Staff FTE - Trained Librarians | AA1: Library Staff FTE - Other Library Staff | AB1: Library Staff FTE - Total Staff | AC1: Recurrent Expenditure (Euros) - Staff | AD1: Recurrent Expenditure (Euros) - Acquisition of Stock | AE1: Recurrent Expenditure (Euros) - Electronic Information | AF1: Recurrent Expenditure (Euros) - Automation | AG1: Recurrent Expenditure (Euros) - Premises and Related Costs | AH1: Recurrent Expenditure (Euros) - New Buildings / Refurbishment | AI1: Recurrent Expenditure (Euros) - Other Expenditure | AJ1: Recurrent Expenditure (Euros) - TOTAL EXPENDITURE | AK1: Income - Public Funding | AL1: Income - Fees & Charges | AM1: Income - Other Income | AN1: Income - TOTAL INCOME | AO1: Capital Expenditure - New Buildings / Refurbishment | AP1: Capital Expenditure - Acquisition of Stock | AQ1: Capital Expenditure - Automation | AR1: Capital Expenditure - Other Capital Expenditure | AS1: Capital Expenditure - TOTAL CAPITAL PAYMENTS | AT1: Additions | AU1: Loans per visit | AV1: Cost per pop | AW1: Users per 1000 pop | AX1: visits per 1000 pop | AY1: Bookstock per 1000 pop | AZ1: Total stock per 1000 pop | BA1: AV materials per 1000 pop
A2: Bulgaria | B2: CEE | C2: C1 | D2: =+Y2/1000 -> 7819.633 | E2: 3757 | F2: 3757 | G2: 52004510 | H2: 16841 | I2: 210214 | J2: 20569 | K2: 84843 | L2: 852026 | M2: 35573 | N2: 280475 | O2: 5354 | P2: 80 | Q2: 44 | R2: 397 | S2: 202 | T2: 901512 | U2: 17999677 | V2: 8252063 | W2: 12021 | X2: 13754 | Y2: 7819633 | Z2: 2915 | AA2: 406 | AB2: 3321 | AC2: 3960297 | AD2: 543433 | AE2: 0 | AF2: 0 | AG2: 0 | AH2: 0 | AI2: 830890 | AJ2: 5334620 | AK2: 4721347 | AL2: 359705 | AM2: 253568 | AN2: 5334620 | AO2: 427170 | AP2: 21100 | AQ2: 107827 | AR2: 95393 | AS2: 651490 | AT2: =+N2+O2 -> 285829 | AU2: =+U2/V2 -> 2.1812336 | AV2: =+AJ2/Y2 -> 0.68220849 | AW2: =+T2/D2 -> 115.28828 | AX2: =+V2/D2 -> 1055.3005 | AY2: =+G2/D2 -> 6650.5052 | AZ2: =SUM(G2:M2)/D2 -> 6806.5312 | BA2: =+L2/D2 -> 108.95985
A3: Czech Republic | B3: CEE | C3: C2 | D3: =+Y3/1000 -> 10223.833 | E3: 6090 | F3: 7179 | G3: 54293396 | H3: 78645 | I3: 87177 | J3: 3951 | K3: 130796 | L3: 676032 | M3: 25018 | N3: 1667841 | O3: 22204 | P3: 76 | Q3: 46 | R3: 3166 | S3: 2116 | T3: 1466682 | U3: 69208089 | V3: 16485563 | W3: 68703 | X3: 48228 | Y3: 10223833 | Z3: 3807 | AA3: 594 | AB3: 4401 | AC3: 22656487 | AD3: 5164471 | AE3: 10916 | AF3: 358727 | AG3: 1333161 | AH3: 380860 | AI3: 14089619 | AJ3: 43994240 | AK3: 45846096 | AL3: 157236 | AM3: 172074 | AN3: 46175406 | AO3: 1044702 | AP3: 0 | AQ3: 0 | AR3: 2938566 | AS3: 3983268 | AT3: =+N3+O3 -> 1690045 | AU3: =+U3/V3 -> 4.1981028 | AV3: =+AJ3/Y3 -> 4.3031063 | AW3: =+T3/D3 -> 143.45716 | AX3: =+V3/D3 -> 1612.464 | AY3: =+G3/D3 -> 5310.4737 | AZ3: =SUM(G3:M3)/D3 -> 5408.4427 | BA3: =+L3/D3 -> 66.123146
A4: Estonia | B4: CEE | C4: C3 | D4: =+Y4/1000 -> 1431.553 | E4: 546 | F4: 664 | G4: 10986247 | H4: 16010 | I4: 17865 | J4: 87 | K4: 1600 | L4: 54302 | M4: 900 | N4: 535439 | O4: 4708 | P4: 75 | Q4: 5 | R4: 631 | S4: 603 | T4: 447834 | U4: 13503545 | V4: 6426415 | W4: 0 | X4: 0 | Y4: 1431553 | Z4: 1224 | AA4: 257 | AB4: 1481 | AC4: 5053889 | AD4: 3335506 | AE4: 0 | AF4: 446677 | AG4: 0 | AH4: 0 | AI4: 1928745 | AJ4: 10764818 | AK4: 13209526 | AL4: 0 | AM4: 269121 | AN4: 13478647 | AO4: 2513456 | AP4: 0 | AQ4: 101119 | AR4: 88273 | AS4: 2702849 | AT4: =+N4+O4 -> 540147 | AU4: =+U4/V4 -> 2.1012563 | AV4: =+AJ4/Y4 -> 7.5196783 | AW4: =+T4/D4 -> 312.83089 | AX4: =+V4/D4 -> 4489.1213 | AY4: =+G4/D4 -> 7674.3558 | AZ4: =SUM(G4:M4)/D4 -> 7737.7582 | BA4: =+L4/D4 -> 37.932232
A5: Hungary | B5: CEE | C5: C4 | D5: =+Y5/1000 -> 10017.547 | E5: 2470 | F5: 3003 | G5: 40714533 | H5: 44888 | I5: 95904 | J5: 22004 | K5: 3432 | L5: 1443321 | M5: 48915 | N5: 1079410 | O5: 70025 | P5: 77 | Q5: 46 | R5: 373 | S5: 190 | T5: 1362096 | U5: 12554527 | V5: 16580105 | W5: 15962 | X5: 45618 | Y5: 10017547 | Z5: 3566 | AA5: 2166 | AB5: 5732 | AC5: 21484399 | AD5: 5045211 | AE5: 0 | AF5: 0 | AG5: 0 | AH5: 0 | AI5: 18160365 | AJ5: 44689975 | AK5: 30615395 | AL5: 0 | AM5: 14074580 | AN5: 44689975 | AO5: 3475597 | AP5: 171680 | AQ5: 877318 | AR5: 776139 | AS5: 5300734 | AT5: =+N5+O5 -> 1149435 | AU5: =+U5/V5 -> 0.75720431 | AV5: =+AJ5/Y5 -> 4.4611695 | AW5: =+T5/D5 -> 135.97101 | AX5: =+V5/D5 -> 1655.1063 | AY5: =+G5/D5 -> 4064.3216 | AZ5: =SUM(G5:M5)/D5 -> 4229.8775 | BA5: =+L5/D5 -> 144.07928
A6: Latvia | B6: CEE | C6: C5 | D6: =+Y6/1000 -> 2326.2 | E6: 920 | F6: 920 | G6: 11738720 | H6: 11596 | I6: 24782 | J6: 5997 | K6: 1358 | L6: 164674 | M6: 7953 | N6: 298116 | O6: 14554 | P6: 77 | Q6: 46 | R6: 250 | S6: 44 | T6: 575148 | U6: 21104458 | V6: 6440086 | W6: 0 | X6: 0 | Y6: 2326200 | Z6: 1828 | AA6: 655 | AB6: 2483 | AC6: 5638690 | AD6: 1456082 | AE6: 0 | AF6: 0 | AG6: 0 | AH6: 0 | AI6: 3072809 | AJ6: 10167581 | AK6: 10126712 | AL6: 26955 | AM6: 13914 | AN6: 10167581 | AO6: 109075 | AP6: 6964 | AQ6: 34978 | AR6: 32330 | AS6: 183347 | AT6: =+N6+O6 -> 312670 | AU6: =+U6/V6 -> 3.277046 | AV6: =+AJ6/Y6 -> 4.3708972 | AW6: =+T6/D6 -> 247.24787 | AX6: =+V6/D6 -> 2768.5006 | AY6: =+G6/D6 -> 5046.3073 | AZ6: =SUM(G6:M6)/D6 -> 5139.3173 | BA6: =+L6/D6 -> 70.79099
A7: Lithuania | B7: CEE | C7: C6 | D7: =+Y7/1000 -> 3646.32 | E7: 66 | F7: 1432 | G7: 22471450 | H7: 11434 | I7: 19059 | J7: 9522 | K7: 1174 | L7: 245876 | M7: 1958 | N7: 916453 | O7: 4992 | P7: 96 | Q7: 46 | R7: 375 | S7: 66 | T7: 831741 | U7: 25190465 | V7: 9794035 | W7: 9376 | X7: 71675 | Y7: 3646320 | Z7: 3104 | AA7: 892 | AB7: 3996 | AC7: 9291103 | AD7: 1787983 | AE7: 145149 | AF7: 214887 | AG7: 506659 | AH7: 0 | AI7: 4400886 | AJ7: 16346667 | AK7: 15696957 | AL7: 441912 | AM7: 266475 | AN7: 16405344 | AO7: 1364058 | AP7: 67378 | AQ7: 344319 | AR7: 304609 | AS7: 2080364 | AT7: =+N7+O7 -> 921445 | AU7: =+U7/V7 -> 2.5720211 | AV7: =+AJ7/Y7 -> 4.4830588 | AW7: =+T7/D7 -> 228.10423 | AX7: =+V7/D7 -> 2686.0053 | AY7: =+G7/D7 -> 6162.7751 | AZ7: =SUM(G7:M7)/D7 -> 6242.0394 | BA7: =+L7/D7 -> 67.431273
A8: Poland | B8: CEE | C8: C7 | D8: =+Y8/1000 -> 38652 | E8: 9226 | F8: 3564 | G8: 135816403 | H8: 112514 | I8: 180494 | J8: 64548 | K8: 10379 | L8: 2596064 | M8: 26799 | N8: 3792692 | O8: 121162 | P8: 77 | Q8: 46 | R8: 1699 | S8: 863 | T8: 7219507 | U8: 188957087 | V8: 50461696 | W8: 103292 | X8: 118293 | Y8: 38652000 | Z8: 11133 | AA8: 6688 | AB8: 17821 | AC8: 70362317 | AD8: 22233713 | AE8: 66144 | AF8: 1027436 | AG8: 2225907 | AH8: 377641 | AI8: 45423189 | AJ8: 141716347 | AK8: 118661663 | AL8: 5442266 | AM8: 17612418 | AN8: 141716347 | AO8: 11068314 | AP8: 546731 | AQ8: 2793889 | AR8: 2471673 | AS8: 16880607 | AT8: =+N8+O8 -> 3913854 | AU8: =+U8/V8 -> 3.7445647 | AV8: =+AJ8/Y8 -> 3.6664687 | AW8: =+T8/D8 -> 186.78224 | AX8: =+V8/D8 -> 1305.5391 | AY8: =+G8/D8 -> 3513.826 | AZ8: =SUM(G8:M8)/D8 -> 3591.2036 | BA8: =+L8/D8 -> 67.165063
