Workbook

Sheet IS
A1: Petroleum Geo-Services ASA
A2: Consolidated Statements of Operations (1)
C4: Quarter ended | G4: Nine months ended | K4: Year ended
C5: September 30, | G5: September 30, | K5: December 31,
C6: 2002 | E6: 2001 | G6: 2002 | I6: 2001 | K6: 2001
A7: (In thousands of dollars, except for share data) | E7: (restated) | I7: (restated)
A9: Revenue | C9: =317745-7942-53102 -> 256701 | E9: =290705-141-47529 -> 243035 | G9: =893867-20595-141271-1 -> 732000 | I9: =462699+E9-39810-35325 -> 630599 | K9: 885063
A11: Cost of sales | C11: =1115677-2+486+6744-1063-425214-268403-56169-2625-140101+437-6526-48834-39056 -> 135351 | E11: =152966-114-17295+18601-46674+232+633 -> 108349 | G11: =(1510767-25042)+1520-3521+6744-1063-425214-268403-56169-2625-140101+437-9178-130517-104314-1 -> 353320 | I11: =228084+E11-39520+1236+342-57756+23279+376-676 -> 263714 | K11: 381019
A12: Depreciation and amortization (2) | C12: =48859+39056+749 -> 88664 | E12: =75144-19-364 -> 74761 | G12: =142031+104314+2220 -> 248565 | I12: =136079+E12-342-376 -> 210122 | K12: 333027
A13: Research and technology costs | C13: =576 -> 576 | E13: =627 -> 627 | G13: =2048+1 -> 2049 | I13: =2191+E13 -> 2818 | K13: =3752 -> 3752
A14: Selling, general and administrative costs | C14: =25439-3619-4000-50-749-2551+2019-122 -> 16367 | E14: =19782-1833-3+19-691-832+132 -> 16574 | G14: =64017-3619-4000-50-1620-8094-364-2220+1 -> 44051 | I14: =35840+E14-736-677-697-1713+456 -> 49047 | K14: 66505
A15: Unusual items, net (3) | C15: =-6744+3619+4000+53-437+6695+425214+268403+56169+3549+4500+2625 -> 767646 | E15: =446-25805-633 -> -25992 | G15: =3521-30938-23211-6744+3619+4000+53-437+6695+425214+268403+56169+3549+4500+2625 -> 717018 | I15: =-87056+E15 -> -113048 | K15: =13155-122349+1345-900+2230+607+17995-633 -> -88550
B16: Total operating expenses | C16: =SUM(C11:C15) -> 1008604 | E16: =SUM(E11:E15) -> 174319 | G16: =SUM(G11:G15) -> 1365003 | I16: =SUM(I11:I15) -> 412653 | K16: =SUM(K11:K15) -> 695753
A17: Operating profit (loss) | C17: =+C9-C16 -> -751903 | E17: =+E9-E16 -> 68716 | G17: =+G9-G16 -> -633003 | I17: =+I9-I16 -> 217946 | K17: =+K9-K16 -> 189310
A18: Financial expense, net (4) | C18: =1143-38194+4439-4444+3+2194+38-2844 -> -37665 | E18: =-34616+1587+604-1360+627-650 -> -33808 | G18: =3401-106897+13115-14164+3+6119+41-8223 -> -106605 | I18: =-68825+E18-55+641-635+210-42+1+619-6-607+174-396 -> -102729 | K18: -140808
A19: Other loss, net (5) | C19: =-14744-4039-579+6695+4500+3549+70-14 -> -4562 | E19: =25281-18+2-25805-1221-4-7 -> -1772 | G19: =-16437-12204+51815+6695-30938-23211+3549+4500+20-12+1 -> -16222 | I19: =359+E19-825+4-60-5 -> -2299 | K19: -4853
A20: Income (loss) before income taxes | C20: =SUM(C17:C19) -> -794130 | E20: =SUM(E17:E19) -> 33136 | G20: =SUM(G17:G19) -> -755830 | I20: =SUM(I17:I19) -> 112918 | K20: =SUM(K17:K19) -> 43649
A21: Provision (benefit) for income taxes (6) | C21: =130996-1741+(1063*0.28) -> 129552.64 | E21: =18685-176+369 -> 18878 | G21: =200806-3952+(1063*0.28) -> 197151.64 | I21: =-26037+E21+206 -> -6953 | K21: =35803-6373-44 -> 29386
A22: (Loss) on tax equalization swap contracts, net of tax (7) | C22: 0 | E22: 0 | G22: 0 | I22: 0 | K22: 0
A23: (Loss) from operations held for sale, net of tax (7) | C23: =2952+1571-1063+1063-140101-1741+(1063*0.28) -> -137021.36 | E23: =-1318+369+587-176 -> -538 | G23: =1063-1063-140101+10850+2235-3952+(1063*0.28) -> -130670.36 | I23: =-9479+E23+772-1635+206+176 -> -10498 | K23: =-4020-6373+628-44-1 -> -9810
A24: Income (loss) before cumulative effect of accounting change | C24: =C20-C21+C23+C22 -> -1060704 | E24: =E20-E21+E23+E22 -> 13720 | G24: =G20-G21+G23+G22 -> -1083652 | I24: =I20-I21+I23+I22 -> 109373 | K24: =K20-K21+K23+K22 -> 4453
A25: Cumulative effect of accounting change, net of tax (8) | C25: 0 | E25: 0 | G25: =-185933 -> -185933 | I25: 0 | K25: 0
B26: Net income (loss) | C26: =SUM(C24:C25) -> -1060704 | E26: =SUM(E24:E25) -> 13720 | G26: =SUM(G24:G25) -> -1269585 | I26: =SUM(I24:I25) -> 109373 | K26: =SUM(K24:K25) -> 4453
A28: Basic earnings (loss) per share before cumulative effect of accounting change | C28: =C24/(C36/1000) -> -10.263621 | E28: =E24/(E36/1000) -> 0.13319614 | G28: =G24/(G36/1000) -> -10.485671 | I28: =I24/(I36/1000) -> 1.0662966 | K28: =K24/(K36/1000) -> 0.043330489
A29: Cumulative effect of accounting change, net of tax (8) | C29: =C25/(C36/1000) -> 0 | E29: =E25/(E36/1000) -> 0 | G29: =G25/(G36/1000) -> -1.7991313 | I29: =I25/(I36/1000) -> 0 | K29: =K25/(K36/1000) -> 0
A30: Basic earnings (loss) per share | C30: =C26/(C36/1000) -> -10.263621 | E30: =E26/(E36/1000) -> 0.13319614 | G30: =G26/(G36/1000) -> -12.284802 | I30: =I26/(I36/1000) -> 1.0662966 | K30: =K26/(K36/1000) -> 0.043330489
A32: Diluted earnings (loss) per share before cumulative effect of accounting change | C32: =C24/(C37/1000) -> -10.263621 | E32: =E24/(E37/1000) -> 0.13319108 | G32: =G24/(G37/1000) -> -10.485671 | I32: =I24/(I37/1000) -> 1.066025 | K32: =K24/(K37/1000) -> 0.043322155
A33: Cumulative effect of accounting change, net of tax (8) | C33: =C25/(C37/1000) -> 0 | E33: =E25/(E37/1000) -> 0 | G33: =G25/(G37/1000) -> -1.7991313 | I33: =I25/(I37/1000) -> 0 | K33: =K25/(K37/1000) -> 0
A34: Diluted earnings (loss) per share | C34: =C26/(C37/1000) -> -10.263621 | E34: =E26/(E37/1000) -> 0.13319108 | G34: =G26/(G37/1000) -> -12.284802 | I34: =I26/(I37/1000) -> 1.066025 | K34: =K26/(K37/1000) -> 0.043322155
A36: Basic shares outstanding | C36: 103345987 | E36: 103005987 | G36: 103345987 | I36: 102572775 | K36: 102768283
A37: Diluted shares outstanding | C37: 103345987 | E37: 103009900 | G37: 103345987 | I37: 102598903 | K37: 102788055
A40: The accompanying notes are an integral part of these consolidated financial statements.

Sheet BS
A1: Petroleum Geo-Services ASA
A2: Consolidated Balance Sheets (1), (10)
F4: September 30, | G4: December 31,
A5: (In thousands of dollars, except for share data) | F5: 2002 | G5: 2001
A7: Assets
A8: Cash and cash equivalents | F8: =93507-4231-2427 -> 86849 | G8: =110909-3613-5166 -> 102130
A9: Accounts receivable, net | F9: =258760-33979-8270 -> 216511 | G9: =254177-3-19287 -> 234887
A10: Other current assets | F10: =44430+38960-914-34-2766-940 -> 78736 | G10: =51488+48468+3-175-306-1331-226 -> 97921
A11: Oil and gas assets | F11: =14795 -> 14795 | G11: 0
A12: Assets held for sale (7) | F12: =4231+33979+914+34+605+336+35113+100000+2427+8270+2766+940+78+317 -> 190010 | G12: =3613+3+175+306+237+171041+9024+5166+19287+1331+226+660+670+29358 -> 241097
B13: Total current assets | F13: =SUM(F8:F12) -> 586901 | G13: =SUM(G8:G12) -> 676035
A14: Multi-client library, net (9) | F14: =583688+106326 -> 690014 | G14: =841350+76722 -> 918072
A15: Property and equipment, net | F15: =6+399574+207456+1151759+21146-336-317 -> 1779288 | G15: =5300+418472+202767+1624670+22544+8488-237-670 -> 2281334
A16: Goodwill (8) | F16: 0 | G16: =215291-29358 -> 185933
A17: Other long-term assets, net | F17: =4792+13492+9344+12488+26+6926+6+19148-605-78-1 -> 65538 | G17: =4114+21373+13894+183592+43+8443+7+19650-9024-660 -> 241432
B18: Total assets | F18: =SUM(F13:F17) -> 3121741 | G18: =SUM(G13:G17) -> 4302806
A20: Liabilities and Shareholders' Equity
A21: Short-term debt and current portion of long-term debt and capital lease obligations | F21: =250000+430000+13395-2522+18777 -> 709650 | G21: =585484-340000+12240+9933-20500-726-2 -> 246429
A22: Debt and other liabilities held for sale (7) | F22: =15800+2522+5441+11+16653+2522+12+4149+9605 -> 56715 | G22: =20500+3678+5543+23+5072+726+2+5607+473+12914+1194 -> 55732
A23: Accounts payable and accrued expenses | F23: =73068+187260-5441-16653-4149-9605 -> 224480 | G23: =76859+226127-3678-5543-5607-12914 -> 275244
A24: Income taxes payable | F24: =13918-11 -> 13907 | G24: =16944-23-473 -> 16448
B25: Total current liabilities | F25: =SUM(F21:F24) -> 1004752 | G25: =SUM(G21:G24) -> 593853
A26: Long-term debt and capital lease obligations | F26: =1709821-143750+1760+90221-2522 -> 1655530 | G26: =1704571-141000+41683+340000 -> 1945254
A27: Other long-term liabilities | F27: =1+55635-12 -> 55624 | G27: =25355-1194 -> 24161
A28: Deferred income taxes | F28: =78575 -> 78575 | G28: =78575-5072 -> 73503
B29: Total liabilities | F29: =SUM(F25:F28) -> 2794481 | G29: =SUM(G25:G28) -> 2636771
A30: Commitments and contingencies
A31: Guaranteed preferred beneficial interest in PGS junior
B32: subordinated debt securities (4) | F32: =143750-1760 -> 141990 | G32: =141000 -> 141000
A33: Mandatorily redeemable cumulative preferred stock related to multi-client securitization | F33: =85818 -> 85818 | G33: =163588 -> 163588
A34: Shareholders' equity:
B35: Common stock, par value NOK 5; issued & outstanding
C36: 103,345,987 shares at September 30, 2002 and December 31, 2001 | F36: 71089 | G36: 71089
B37: Additional paid-in capital | F37: 1225115 | G37: 1225115
B38: Retained earnings | F38: =-1170722 -> -1170722 | G38: =106130-7268+1 -> 98863
B39: Accumulated other comprehensive loss | F39: -26030 | G39: =-1-33619 -> -33620
B40: Total shareholders' equity | F40: =SUM(F35:F39) -> 99452 | G40: =SUM(G35:G39) -> 1361447
B41: Total liabilities and shareholders' equity | F41: =+F29+F40+F32+F33 -> 3121741 | G41: =+G29+G40+G32+G33 -> 4302806
A44: The accompanying notes are an integral part of these consolidated financial statements.

Sheet CF
A1: Petroleum Geo-Services ASA
A2: Consolidated Statements of Cash Flows (1)
D4: Quarter ended | G4: Nine months ended | J4: Year ended
D5: September 30, | G5: September 30, | J5: December 31,
D6: 2002 | E6: 2001 | G6: 2002 | H6: 2001 | J6: 2001
A7: (In thousands of dollars) | E7: (restated) | H7: (restated)
A9: Cash flows from operating activities:
B10: Net income (loss) | D10: =IS!C26 -> -1060704 | E10: =IS!E26 -> 13720 | G10: =IS!G26 -> -1269585 | H10: =IS!I26 -> 109373 | J10: =IS!K26 -> 4453
B11: Adjustments to reconcile net income (loss) to
B12: net cash provided by operating activities:
C13: Depreciation and amortization charged to expense | D13: =IS!C12 -> 88664 | E13: =IS!E12 -> 74761 | G13: =IS!G12 -> 248565 | H13: =IS!I12 -> 210122 | J13: =IS!K12 -> 333027
C14: Non-cash unusual items and gain on sale of subsidiary, net | D14: =914491 -> 914491 | E14: 9332 | G14: =1101790-1366 -> 1100424 | H14: =15251-128270 -> -113019 | J14: =31243-128270 -> -97027
C15: Cash effects related to assets and liabilities held for sale (7) | D15: 64 | E15: =-2416 -> -2416 | G15: 2121 | H15: -5360 | J15: =-3613-5166 -> -8779
C16: Provision (benefit) for deferred income taxes | D16: 127496 | E16: =16989 -> 16989 | G16: 193375 | H16: =-3192 -> -3192 | J16: 22114
C17: Working capital changes and other items | D17: =724+1061+1034+2700-2278 -> 3241 | E17: =132-1720-27501+2851-26668-27688 -> -80594 | G17: =1274+1694+1061+2404+4537-966-46741 -> -36737 | H17: =256-2587+7301+12245-93416-31230-1 -> -107432 | J17: =294+492+8548+14522-39090-35631 -> -50865
B18: Net cash provided by operating activities | D18: =SUM(D10:D17) -> 73252 | E18: =SUM(E10:E17) -> 31792 | G18: =SUM(G10:G17) -> 238163 | H18: =SUM(H10:H17) -> 90492 | J18: =SUM(J10:J17) -> 202923
A19: Cash flows from investing activities:
B20: Investment in multi-client library | D20: =-35847 -> -35847 | E20: -46004 | G20: =-155945 -> -155945 | H20: =-170817 -> -170817 | J20: -230166
B21: Capital expenditures | D21: =-13447 -> -13447 | E21: =-29234+16+91 -> -29127 | G21: =-53654 -> -53654 | H21: =-83866-41219-29234+3+80+14+16+91-275 -> -154390 | J21: =54262-239623+80+14+16+3+91+22+116 -> -185019
B22: Sale of investment in affiliated company | D22: 0 | E22: 0 | G22: 0 | H22: 0 | J22: 0
B23: Development of assets held for sale (7) | D23: =-23512 -> -23512 | E23: =-5357-16-91 -> -5464 | G23: =-62958 -> -62958 | H23: =-11205-16243-5357-3-91-14-80-16+275 -> -32734 | J23: =-54262-80-14-16-3-91-22-116 -> -54604
B24: Sale of subsidiary | D24: 0 | E24: 0 | G24: 0 | H24: 175000 | J24: 175000
B25: Other items, net | D25: =-5563 -> -5563 | E25: =-14768 -> -14768 | G25: =89-9683 -> -9594 | H25: =-18828 -> -18828 | J25: =-19485 -> -19485
B26: Net cash (used in) investing activities | D26: =SUM(D20:D25) -> -78369 | E26: =SUM(E20:E25) -> -95363 | G26: =SUM(G20:G25) -> -282151 | H26: =SUM(H20:H25) -> -201769 | J26: =SUM(J20:J25) -> -314274
A27: Cash flows from financing activities:
B28: Net increase (decrease) in short-term debt
B29: Net proceeds from issuance of subsidiary preferred stock | D29: 0 | E29: 0 | G29: 0 | H29: 234285 | J29: 234285
B30: Redemption of preferred stock | D30: -22543 | E30: -27566 | G30: -77200 | H30: =-54926 -> -54926 | J30: -77280
B31: Repayment of long-term debt | D31: -2106 | E31: -6801 | G31: -236866 | H31: -12184 | J31: -11414
B32: Principal payments under capital lease obligations | D32: -5005 | E32: -1205 | G32: -10596 | H32: -4857 | J32: -7806
B33: Net increase (decrease) in bank facility and short-term debt | D33: 60458 | E33: =62029 -> 62029 | G33: 335301 | H33: -76697 | J33: -5667
B34: Net receipts (payments) under tax equalization swap contracts | D34: =0 -> 0 | E34: =0 -> 0 | G34: 9566 | H34: -48160 | J34: -64575
B35: Other items, net | D35: =0 -> 0 | E35: 547 | G35: =8098 -> 8098 | H35: =816+4986 -> 5802 | J35: =816 -> 816
B36: Net cash provided by financing activities | D36: =SUM(D28:D35) -> 30804 | E36: =SUM(E28:E35) -> 27004 | G36: =SUM(G28:G35) -> 28303 | H36: =SUM(H28:H35) -> 43263 | J36: =SUM(J28:J35) -> 68359
B37: Effect of exchange rate changes in cash and cash equivalents | D37: 174 | E37: 107 | G37: 404 | H37: -65 | J37: -93
B38: Net increase (decrease) in cash and cash equivalents | D38: =+D18+D26+D36+D37 -> 25861 | E38: =+E18+E26+E36+E37 -> -36460 | G38: =+G18+G26+G36+G37 -> -15281 | H38: =+H18+H26+H36+H37 -> -68079 | J38: =+J18+J26+J36+J37 -> -43085
B39: Cash and cash equivalents at beginning of period | D39: 60988 | E39: =113596 -> 113596 | G39: 102130 | H39: 145215 | J39: 145215
A40: Cash and cash equivalents at end of period | D40: =+D38+D39 -> 86849 | E40: =+E38+E39 -> 77136 | G40: =+G38+G39 -> 86849 | H40: =+H38+H39 -> 77136 | J40: =+J38+J39 -> 102130
A44: The accompanying notes are an integral part of these consolidated financial statements.
