Workbook

Sheet Sheet1
A1: FINPACK Balance Sheet | F1: *=input
D2: Debt Level
C3: Low | D3: Medium | E3: High
A4: Current Farm Assets | C4: 431000 | D4: 431000 | E4: 431000 | F4: *
A5: Intermed. Farm Assets | B5: + | C5: 616000 | D5: 616000 | E5: 616000 | F5: *
A6: Long Term Farm Assets | B6: + | C6: 974000 | D6: 974000 | E6: 974000 | F6: *
A7: Total Farm Assets | B7: = | C7: =SUM(C4:C6) -> 2021000 | D7: =SUM(D4:D6) -> 2021000 | E7: =SUM(E4:E6) -> 2021000
A9: Current Farm Liabilities | C9: 50782 | D9: 311689 | E9: 376586 | F9: *
A10: Intermed. Farm Liabilities | B10: + | C10: 82014 | D10: 253300 | E10: 412502 | F10: *
A11: Long Term Farm Liabilites | B11: + | C11: 271458 | D11: 344461 | E11: 524562 | F11: *
A12: Total Liablilities | B12: = | C12: =C9+C10+C11 -> 404254 | D12: =D9+D10+D11 -> 909450 | E12: =E9+E10+E11 -> 1313650
A14: Equity | C14: =C7-C12 -> 1616746 | D14: =D7-D12 -> 1111550 | E14: =E7-E12 -> 707350
A15: Debt to Asset Ratio | C15: =C12/C7*100 -> 20.002672 | D15: =D12/D7*100 -> 45 | E15: =E12/E7*100 -> 65
A16: Equity to Asset Ratio | C16: =C14/C7*100 -> 79.997328 | D16: =D14/D7*100 -> 55 | E16: =E14/E7*100 -> 35
A20: Total Cash Farm Exp. | B20: - | C20: 417521 | D20: 456755 | E20: 496216 | F20: *
A21: Income Statement
D22: Debt Level
C23: Low | D23: Medium | E23: High
A24: Gross Farm Income | B24: + | C24: 550434 | D24: 550434 | E24: 550434 | F24: *
A25: Non Interest Cash Exp. | B25: - | C25: =C20-C26 -> 386945 | D25: =D20-D26 -> 386945 | E25: =E20-E26 -> 386945
A26: Interest Expense | B26: - | C26: 30576 | D26: 69810 | E26: 109271 | F26: *
A27: Net Cash Farm Income | B27: = | C27: =C24-C25-C26 -> 132913 | D27: =D24-D25-D26 -> 93679 | E27: =E24-E25-E26 -> 54218
A28: Inventory/Accrual Adj. | B28: + | C28: 0 | D28: 0 | E28: 0
A29: Net Operating Profit | B29: = | C29: =C27-C28 -> 132913 | D29: =D27-D28 -> 93679 | E29: =E27-E28 -> 54218
A30: Depreciation | B30: - | C30: 60000 | D30: 60000 | E30: 60000
A31: Net Farm Income | B31: = | C31: =C29-C30 -> 72913 | D31: =D29-D30 -> 33679 | E31: =E29-E30 -> -5782 | F31: *
A35: Cash Flow Statement
D36: Debt Level
C37: Low | D37: Medium | E37: High
A38: Net Cash Farm Income | B38: + | C38: =C27 -> 132913 | D38: =D27 -> 93679 | E38: =E27 -> 54218
A39: Nonfarm Income | B39: + | C39: 0 | D39: 0 | E39: 0
A40: Net Cash Available | B40: = | C40: =C38-C39 -> 132913 | D40: =D38-D39 -> 93679 | E40: =E38-E39 -> 54218
A41: Family Living | B41: - | C41: 30000 | D41: 30000 | E41: 30000 | F41: *
A42: Income Taxes & Social Security | B42: - | C42: 23550 | D42: 8945 | E42: 0 | F42: *
A43: Cash Avail. for Princ. Payments | B43: = | C43: =C40-C41-C42 -> 79363 | D43: =D40-D41-D42 -> 54734 | E43: =E40-E41-E42 -> 24218
A44: Farm Interest Paid | B44: + | C44: =C26 -> 30576 | D44: =D26 -> 69810 | E44: =E26 -> 109271
A45: Cash Avail. for P& I Payments | B45: = | C45: =C43+C44 -> 109939 | D45: =D43+D44 -> 124544 | E45: =E43+E44 -> 133489
A46: Total Sched. Principal & Interest | B46: - | C46: 58655 | D46: 178601 | E46: 176312 | F46: *
A47: Cash Avail. after Loan Payments | B47: = | C47: =C45-C46 -> 51284 | D47: =D45-D46 -> -54057 | E47: =E45-E46 -> -42823
A48: Cash Required for Replacement | B48: - | C48: 40978 | D48: 0 | E48: 13521 | F48: *
A49: Cash Surplus or Deficit | B49: = | C49: =C47-C48 -> 10306 | D49: =D47-D48 -> -54057 | E49: =E47-E48 -> -56344
A51: Change in Net Worth
D53: Debt Level
C54: Low | D54: Medium | E54: High
A55: Net Farm Income | C55: =C31 -> 72913 | D55: =D31 -> 33679 | E55: =E31 -> -5782
A56: Net non Farm Income | B56: + | C56: =C39 -> 0 | D56: =D39 -> 0 | E56: =E39 -> 0
A57: Family Living | B57: - | C57: =C41 -> 30000 | D57: =D41 -> 30000 | E57: =E41 -> 30000
A58: Income Taxes | B58: - | C58: =C42 -> 23550 | D58: =D42 -> 8945 | E58: =E42 -> 0
A59: Change in Net Worth | B59: = | C59: =C55+C56-C57-C58 -> 19363 | D59: =D55+D56-D57-D58 -> -5266 | E59: =E55+E56-E57-E58 -> -35782
A61: Percent Change in Equity | C61: =C59/C14 -> 0.011976526 | D61: =D59/D14 -> -0.0047375287 | E61: =E59/E14 -> -0.05058599
A63: Sensitivity Analysis
D64: Debt Level
C65: Low | D65: Medium | E65: High
A66: 2% Decrease
A67: Net Farm Income | C67: 63215 | D67: 23981 | E67: -15480 | F67: *
A68: Cash Surplus or Deficit | C68: 4051 | D68: -60370 | E68: -66042 | F68: *
A69: Net Worth Change per Year | C69: 13108 | D69: -11580 | E69: -45480 | F69: *
A71: 10 % Decrease
A72: Net Farm Income | C72: 24423 | D72: -14811 | E72: -54272 | F72: *
A73: Cash Surplus or Deficit | C73: -20384 | D73: -93602 | E73: -104834 | F73: *
A74: Net Worth Change per Year | C74: -11292 | D74: -44811 | E74: -84272 | F74: *
A76: Term Debt & Capital Lease Coverage Ratio
D77: Debt Level
C78: Low | D78: Medium | E78: High
A79: Net Farm Income | B79: + | C79: =C31 -> 72913 | D79: =D31 -> 33679 | E79: =E31 -> -5782
A80: Family Living Draw | B80: - | C80: =C41 -> 30000 | D80: =D41 -> 30000 | E80: =E41 -> 30000
A81: Outside Sources and Uses | B81: +/- | C81: 0 | D81: 0 | E81: 0
A82: Taxes | B82: - | C82: =C42 -> 23550 | D82: =D42 -> 8945 | E82: =E42 -> 0
A83: Depreciation | B83: + | C83: =+C30 -> 60000 | D83: =+D30 -> 60000 | E83: =+E30 -> 60000
A84: Int. on Term Debt & Cap. Lease | B84: + | C84: 30576 | D84: =69810-15000 -> 54810 | E84: =109271-25000 -> 84271 | F84: *
A85: Cash Available for P & I | B85: = | C85: =C79-C80-C82+C83+C84 -> 109939 | D85: =D79-D80-D82+D83+D84 -> 109544 | E85: =E79-E80-E82+E83+E84 -> 108489
A86: T. Debt & Cap. Lease P & I Due | B86: / | C86: 58655 | D86: =178601-15000 -> 163601 | E86: =176312-25000 -> 151312 | F86: *
A87: Term Debt Serv. Coverage Ratio | B87: = | C87: =C85/C86 -> 1.874333 | D87: =D85/D86 -> 0.66958026 | E87: =E85/E86 -> 0.71698874
A90: Capital Replacement & Term Debt Repayment Margin
D91: Debt Level
C92: Low | D92: Medium | E92: High
A93: Net Farm Income | B93: + | C93: =C79 -> 72913 | D93: =D79 -> 33679 | E93: =E79 -> -5782
A94: Family Living Draw | B94: - | C94: =C80 -> 30000 | D94: =D80 -> 30000 | E94: =E80 -> 30000
A95: Outside Sources and Uses | B95: +/- | C95: =C81 -> 0 | D95: =D81 -> 0 | E95: =E81 -> 0
A96: Income Taxes | B96: - | C96: =C82 -> 23550 | D96: =D82 -> 8945 | E96: =E82 -> 0
A97: Depreciation | B97: + | C97: =C83 -> 60000 | D97: =D83 -> 60000 | E97: =E83 -> 60000
A98: Cap. Rep. & T. Debt Repay. Capacity | B98: = | C98: =C93-C94-C96+C97 -> 79363 | D98: =D93-D94-D96+D97-15000 -> 39734 | E98: =E93-E94-E96+E97-25000 -> -782 | F98: *
A99: Princ. on Prior years Oper. Debts | B99: - | C99: 0 | D99: 0 | E99: 0 | F99: *
A100: Princ. on Cur. Portions of T. Debts | B100: - | C100: =C86-C44 -> 28079 | D100: =D86-D44 -> 93791 | E100: =E86-E44 -> 42041
A101: Princ. on Cur. Portions of Cap. Lease | B101: - | C101: 0 | D101: 0 | E101: 0 | F101: *
A102: Princ. on Per. Liab. not incl. in draw | B102: - | C102: 0 | D102: 0 | E102: 0 | F102: *
A103: Cap. Rep. & T. Debt Repay. Margin | B103: = | C103: =C98-C99-C100-C101-C102 -> 51284 | D103: =D98-D99-D100-D101-D102 -> -54057 | E103: =E98-E99-E100-E101-E102 -> -42823
A105: Cash Flow Requirements
D106: Debt Level
A107: Cash Expenditure: | C107: Low | D107: Medium | E107: High
A108: Total Cash Farm Expense | C108: =C20 -> 417521 | D108: =D20 -> 456755 | E108: =E20 -> 496216
A109: Principal on Term Debts | B109: + | C109: =C100 -> 28079 | D109: =D100 -> 93791 | E109: =E100 -> 42041
A110: Cash Req. for Replacement | B110: + | C110: =C48 -> 40978 | D110: =D48 -> 0 | E110: =E48 -> 13521
A111: Family Living Expenses | B111: + | C111: =C94 -> 30000 | D111: =D94 -> 30000 | E111: =E94 -> 30000
A112: Income Tax and Soc. Sec. | B112: + | C112: =C96 -> 23550 | D112: =D96 -> 8945 | E112: =E96 -> 0
A113: Total Cash Flow | B113: = | C113: =SUM(C108:C112) -> 540128 | D113: =SUM(D108:D112) -> 589491 | E113: =SUM(E108:E112) -> 581778
A114: $/acre 2,000 acres | C114: =C113/2000 -> 270.064 | D114: =D113/2000 -> 294.7455 | E114: =E113/2000 -> 290.889
A115: 128.5 bu Corn per acre | C115: =C114/128.5 -> 2.1016654 | D115: =D114/128.5 -> 2.2937393 | E115: =E114/128.5 -> 2.2637276
A116: 43.0 bu Soys per acre | C116: =C114/43 -> 6.2805581 | D116: =D114/43 -> 6.8545465 | E116: =E114/43 -> 6.7648605
A117: need to account for GPROG
...

Sheet Sheet2 (3)
A1: COST OF PRODUCTION WORKSHEET - Page 2
A2: Low Debt Farm
B3: CORN | C3: SOYS | D3: WHEAT | E3: OTHER1 | F3: OTHER2 | G3: OTHER3 | H3: OTHER4
A4: 1. Paid on Yield per Acre in Bushels | B4: 128.5 | C4: 43 | D4: Bu______ | E4: Bu______ | F4: Bu______ | G4: Bu______ | H4: Bu______
A5: 2. TIMES Selling Price per Bu x | B5: =Sheet1!C223 -> 2 | C5: =Sheet1!D223 -> 5.3 | D5: $________ | E5: $________ | F5: $________ | G5: $________ | H5: $________
A6: 3. EQUALS Gross Income per Acre = | B6: =B4*B5 -> 257 | C6: =C4*C5 -> 227.9 | D6: =D4*D5 -> #VALUE! | E6: =E4*E5 -> #VALUE! | F6: =F4*F5 -> #VALUE! | G6: =G4*G5 -> #VALUE! | H6: =H4*H5 -> #VALUE!
A8: DIRECT COST/AC
A9: 4. Seed | B9: 25 | C9: 26.4 | D9: $________ | E9: $________ | F9: $________ | G9: $________ | H9: $________
A10: 5. Fertilizer | B10: 54.8 | C10: 13 | D10: $________ | E10: $________ | F10: $________ | G10: $________ | H10: $________
A11: 6. Herbicides | B11: 20.35 | C11: 18.75 | D11: $________ | E11: $________ | F11: $________ | G11: $________ | H11: $________
A12: 7. Insecticides | B12: $__________ | C12: $__________ | D12: $________ | E12: $________ | F12: $________ | G12: $________ | H12: $________
A13: 8. Drying Fuel | B13: 7 | C13: $__________ | D13: $________ | E13: $________ | F13: $________ | G13: $________ | H13: $________
A14: 9. Crop Fuel & Oil | B14: 9.35 | C14: 7.5 | D14: $________ | E14: $________ | F14: $________ | G14: $________ | H14: $________
A15: 10. Crop Repairs | B15: 23.6 | C15: 20.2 | D15: $________ | E15: $________ | F15: $________ | G15: $________ | H15: $________
A16: 12. Crop Utilities | B16: 2.4 | C16: 1.5 | D16: $________ | E16: $________ | F16: $________ | G16: $________ | H16: $________
A17: 13. Crop Haul & Truck | B17: 15.42 | C17: 5.16 | D17: $________ | E17: $________ | F17: $________ | G17: $________ | H17: $________
A18: 14. Crop Marketing | B18: $__________ | C18: 1.72 | D18: $________ | E18: $________ | F18: $________ | G18: $________ | H18: $________
A19: 15. Crop Insurance | B19: $__________ | C19: $__________ | D19: $________ | E19: $________ | F19: $________ | G19: $________ | H19: $________
A20: 16. Other | B20: $__________ | C20: $__________ | D20: $________ | E20: $________ | F20: $________ | G20: $________ | H20: $________
A21: 17. TOTAL DIRECT COST/Ac | B21: =SUM(B9:B20) -> 157.92 | C21: =SUM(C9:C20) -> 94.23 | D21: =SUM(D9:D20) -> 0 | E21: =SUM(E9:E20) -> 0 | F21: =SUM(F9:F20) -> 0 | G21: =SUM(G9:G20) -> 0 | H21: =SUM(H9:H20) -> 0
A23: 18. GROSS MARGIN=G.I.-D.C./Ac | B23: =IF(B21>0,(B6-B21),0) -> 99.08 | C23: =IF(C21>0,(C6-C21),0) -> 133.67 | D23: =IF(D21>0,(D6-D21),0) -> 0 | E23: =IF(E21>0,(E6-E21),0) -> 0 | F23: =IF(F21>0,(F6-F21),0) -> 0 | G23: =IF(G21>0,(G6-G21),0) -> 0 | H23: =IF(H21>0,(H6-H21),0) -> 0
A24: For each crop (line 3) MINUS (line 17)
A25: OVERHEAD COSTS for Farm | B25: Column 1 | C25: 1.Gross Margin can be used in determining which crops will contribute
A26: 19. Acres Cropped | B26: =SUM(B53:H53) -> 2000 | C26: more toward Overhead Cost.
A27: 20. Interest | B27: 25498 | C27: 2. Accounting Costs of Production is the summation of direct
A28: 21. Hired Labor | B28: 25000 | C28: variable (or allocable) and of overhead (or non-allocable) cost.
A29: 22. Land Rents | B29: 82500 | C29: 3. Economic Costs is the summation of total accounting costs plus
A30: 23. Machinery Leases | B30: 0 | C30: the opportunity costs of resources used in the business; e.g. for
A31: 24. Real Estate Taxes | B31: 14100 | C31: equity capital and for unpaid family labor. Being able to price a
A32: 25. Farm Insurance | B32: 12000 | C32: commodity at your economic cost would provide the returns to unpaid
A33: 26. Farm Utilities | B33: 1200 | C33: resources (lines 30 and 31). Selling at less than the economic cost
A34: 27. Other Expenses | B34: 0 | C34: indicates that the price received is not adequate to earn the desired
A35: 28. Depreciation | B35: 60000 | C35: rates of return on unpaid resources.
A36: 29. Total Accounting Overhead Cost | B36: =SUM(B27:B35) -> 220298 | C36: ADD (lines 20 through lines 28)
A38: 30. Value of Unpaid Labor | B38: 45786 | C38: 4.Economic Cost includes a value for any unpaid labor.
A39: 31. Value of Unpaid Equity Capital | B39: =0.06*Sheet1!C14 -> 97004.76 | C39: 5.Economic Cost includes opportunity cost of Equity. (6%? of Net Worth)
A40: 32. Total Economic Overhead Cost | B40: =SUM(B36:B39) -> 363088.76 | C40: ADD(lines 29, 30 and 31)
A42: 33. Total Economic Overhead Cost/Ac | B42: =B40/B26 -> 181.54438 | C42: (line 32) DIVIDED BY (line 19)
B44: =B3 -> CORN | C44: =C3 -> SOYS | D44: =D3 -> WHEAT | E44: =E3 -> OTHER1 | F44: =F3 -> OTHER2 | G44: =G3 -> OTHER3 | H44: =H3 -> OTHER4
A45: 34. Total Economic Costs/Ac | B45: =IF(B21>0,(B21+$B42),0) -> 339.46438 | C45: =IF(C21>0,(C21+$B42),0) -> 275.77438 | D45: =IF(D21>0,(D21+$B42),0) -> 0 | E45: =IF(E21>0,(E21+$B42),0) -> 0 | F45: =IF(F21>0,(F21+$B42),0) -> 0 | G45: =IF(G21>0,(G21+$B42),0) -> 0 | H45: =IF(H21>0,(H21+$B42),0) -> 0
A46: (line 17 for each crop) PLUS (line33)
A48: 35. Total Economic Cost / Bu | B48: =IF(B45>0,(B45/B4),0) -> 2.6417461 | C48: =IF(C45>0,(C45/C4),0) -> 6.4133577 | D48: =IF(D45>0,(D45/D4),0) -> 0 | E48: =IF(E45>0,(E45/E4),0) -> 0 | F48: =IF(F45>0,(F45/F4),0) -> 0 | G48: =IF(G45>0,(G45/G4),0) -> 0 | H48: =IF(H45>0,(H45/H4),0) -> 0
A49: For each crop (line 34) DIVIDED BY (line 1)
A50: COST OF PRODUCTION WORKSHEET - Page 3
A51: =A2 -> Low Debt Farm
B52: =B44 -> CORN | C52: =C44 -> SOYS | D52: =D44 -> WHEAT | E52: =E44 -> OTHER1 | F52: =F44 -> OTHER2 | G52: =G44 -> OTHER3 | H52: =H44 -> OTHER4
A53: 36. Acres planted each crop | B53: 1000 | C53: 1000 | D53: 0 | E53: 0 | F53: 0 | G53: 0 | H53: 0
A55: 37. Total Direct Cost/Ac (line 17) | B55: =B21 -> 157.92 | C55: =C21 -> 94.23 | D55: =D21 -> 0 | E55: =E21 -> 0 | F55: =F21 -> 0 | G55: =G21 -> 0 | H55: =H21 -> 0
A57: 38. Direct Cost per Bushel | B57: =IF(B53>0,(B21/B4),0) -> 1.2289494 | C57: =IF(C53>0,(C21/C4),0) -> 2.1913953 | D57: =IF(D53>0,(D21/D4),0) -> 0 | E57: =IF(E53>0,(E21/E4),0) -> 0 | F57: =IF(F53>0,(F21/F4),0) -> 0 | G57: =IF(G53>0,(G21/G4),0) -> 0 | H57: =IF(H53>0,(H21/H4),0) -> 0
A58: For each crop (line 37)DIVIDED BY (line 1)
A59: 39. Total Direct Cost for Crop | B59: =IF(B55>0,(B53*B55),0) -> 157920 | C59: =IF(C55>0,(C53*C55),0) -> 94230 | D59: =IF(D55>0,(D53*D55),0) -> 0 | E59: =IF(E55>0,(E53*E55),0) -> 0 | F59: =IF(F55>0,(F53*F55),0) -> 0 | G59: =IF(G55>0,(G53*G55),0) -> 0 | H59: =IF(H55>0,(H53*H55),0) -> 0
A60: For each crop (line 36) TIMES (line 37)
A62: 40. Total Direct Cost for all crops combined | C62: =SUM(B59:H59) -> 252150 | D62: (SUM of each column in line 39)
A64: Crop Prices and Crop Revenues Needed to Maintain Net Worth
A65: 41. Total Economic Overhead Cost (line 32) | C65: =B40 -> 363088.76 | D65: This calculation is used to determine the crop price
A66: 42. Minus Gov. Program & Other Net Incomes | B66: - | C66: =Sheet1!C276 -> 65534 | D66: required after receipt of other farm income;e.g. fixed
A67: 43. Minus Value of Unpaid Equity (line 31) | B67: - | C67: =B39 -> 97004.76 | D67: government payments, custom work. It covers direct
A68: 44. Plus Income Taxes | B68: + | C68: =Sheet1!C125 -> 23550 | D68: costs associated with the crop, its share of the farm
A69: 45. Minus Value Unpaid Family Labor (line 30) | B69: - | C69: =B38 -> 45786 | D69: overhead, plus expenditures required for family living
A70: 46. Plus Actual Family Living & Other Draws | B70: =B68 -> + | C70: =Sheet1!C41 -> 30000 | D70: and income taxes.
A71: 47. “Maintain Net Worth Overhead Cost” | B71: = | C71: =C65-C66-C67+C68-C69+C70 -> 208314
A72: 48. “Maintain Net Worth Overhead Cost” per Acre | C72: =C71/B26 -> 104.157 | D72: (line 47) DIVIDED BY (line 19
A73: 49. Total Crop Revenues Needed to Maintain Net Worth | D73: =C62+C71 -> 460464 | E73: (line 40) PLUS (line 47)
B75: =B52 -> CORN | C75: =C52 -> SOYS | D75: WHEAT | E75: OTHER1 | F75: OTHER2 | G75: OTHER3 | H75: OTHER4
A76: 50. Total Revenues Needed / Acre | B76: =IF(B59>0,($C72+B55),0) -> 262.077 | C76: =IF(C59>0,($C72+C55),0) -> 198.387 | D76: =IF(D59>0,($C72+D55),0) -> 0 | E76: =IF(E59>0,($C72+E55),0) -> 0 | F76: =IF(F59>0,($C72+F55),0) -> 0 | G76: =IF(G59>0,($C72+G55),0) -> 0 | H76: =IF(H59>0,($C72+H55),0) -> 0
A77: (line 37 for each crop) PLUS (line 48)
A78: 51. Maintain Net Worth per Bu | B78: =IF(B76>0,(B76/B4),0) -> 2.0395097 | C78: =IF(C76>0,(C76/C4),0) -> 4.6136512 | D78: =IF(D76>0,(D76/D4),0) -> 0 | E78: =IF(E76>0,(E76/E4),0) -> 0 | F78: =IF(F76>0,(F76/F4),0) -> 0 | G78: =IF(G76>0,(G76/G4),0) -> 0 | H78: =IF(H76>0,(H76/H4),0) -> 0
A79: For each crop (line 50) DIVIDED BY (line 1)
A81: Crop Prices and Crop Revenues Required to Meet Cash Flow Demands This calculation is to determine the crop price
A82: 52. “Maintain Net Worth Overhead Cost” (line 47) | C82: =C71 -> 208314 | D82: required after receipt of other farm income; e.g.
A83: 53. Minus Depreciation (line 28) | B83: - | C83: =B35 -> 60000 | D83: government payments and custom work, that covers
A84: 54. Minus Interest Expense (line 20) | B84: - | C84: =B27 -> 25498 | D84: all cash flow expenditures for the farm business to
A85: 55. Plus Scheduled Principal and Interest | B85: + | C85: =Sheet1!C46 -> 58655 | D85: continue which includes annual principal payments to
A86: 56. Plus Cash required for Capital Replacement | B86: + | C86: =Sheet1!C48 -> 40978 | D86: service debt and an annual planned expenditure for
A87: 57. “Meet Cash Flow Demands Overhead Cost” | B87: = | C87: =C82-C83-C84+C85+C86 -> 222449 | D87: replacement and growth of the farm infrastructure
D88: e.g. machinery, equipment, tile, and buildings.
A89: 58. “Meet Cash Flow Overhead Cost” per Acre | C89: =C87/B26 -> 111.2245 | D89: (line 57) DIVIDED BY (line 19)
A91: 59. Total Crop Revenues Needed to Meet Cash Flow Demands | D91: =C62+C87 -> 474599 | E91: (line 40) PLUS (line 57)
B93: =B75 -> CORN | C93: =C75 -> SOYS | D93: =D75 -> WHEAT | E93: =E75 -> OTHER1 | F93: =F75 -> OTHER2 | G93: =G75 -> OTHER3 | H93: =H75 -> OTHER4
A94: 60.Total Crop Revenue Needed per Acre | B94: =IF(B78>0,(B55+$C89),0) -> 269.1445 | C94: =IF(C78>0,(C55+$C89),0) -> 205.4545 | D94: =IF(D78>0,(D55+$C89),0) -> 0 | E94: =IF(E78>0,(E55+$C89),0) -> 0 | F94: =IF(F78>0,(F55+$C89),0) -> 0 | G94: =IF(G78>0,(G55+$C89),0) -> 0 | H94: =IF(H78>0,(H55+$C89),0) -> 0
A95: (line 37 for each crop) PLUS (line 58)
A96: 61. Meet Cash Flow Demands per Bu | B96: =IF(B94>0,(B94/B4),0) -> 2.0945097 | C96: =IF(C94>0,(C94/C4),0) -> 4.7780116 | D96: =IF(D94>0,(D94/D4),0) -> 0 | E96: =IF(E94>0,(E94/E4),0) -> 0 | F96: =IF(F94>0,(F94/F4),0) -> 0 | G96: =IF(G94>0,(G94/G4),0) -> 0 | H96: =IF(H94>0,(H94/H4),0) -> 0
A97: For each crop (line 60) DIVIDED BY (line 1)
A98: =A2 -> Low Debt Farm | B98: =B52 -> CORN | C98: =C52 -> SOYS
A99: =A48 -> 35. Total Economic Cost / Bu | B99: =B48 -> 2.6417461 | C99: =C48 -> 6.4133577
A100: =A78 -> 51. Maintain Net Worth per Bu | B100: =B78 -> 2.0395097 | C100: =C78 -> 4.6136512
A101: =A96 -> 61. Meet Cash Flow Demands per Bu | B101: =B96 -> 2.0945097 | C101: =C96 -> 4.7780116

Sheet Sheet2 (4)
A1: COST OF PRODUCTION WORKSHEET - Page 2
A2: Medium Debt Farm
A3: Medium Debt Farm | B3: CORN | C3: SOYS | D3: WHEAT | E3: OTHER1 | F3: OTHER2 | G3: OTHER3 | H3: OTHER4
A4: 1. Paid on Yield per Acre in Bushels | B4: 128.5 | C4: 43 | D4: Bu______ | E4: Bu______ | F4: Bu______ | G4: Bu______ | H4: Bu______
A5: 2. TIMES Selling Price per Bu x | B5: =Sheet1!C223 -> 2 | C5: =Sheet1!D223 -> 5.3 | D5: $________ | E5: $________ | F5: $________ | G5: $________ | H5: $________
A6: 3. EQUALS Gross Income per Acre = | B6: =B4*B5 -> 257 | C6: =C4*C5 -> 227.9 | D6: =D4*D5 -> #VALUE! | E6: =E4*E5 -> #VALUE! | F6: =F4*F5 -> #VALUE! | G6: =G4*G5 -> #VALUE! | H6: =H4*H5 -> #VALUE!
A8: DIRECT COST/AC
A9: 4. Seed | B9: 25 | C9: 26.4 | D9: $________ | E9: $________ | F9: $________ | G9: $________ | H9: $________
A10: 5. Fertilizer | B10: 54.8 | C10: 13 | D10: $________ | E10: $________ | F10: $________ | G10: $________ | H10: $________
A11: 6. Herbicides | B11: 20.35 | C11: 18.75 | D11: $________ | E11: $________ | F11: $________ | G11: $________ | H11: $________
A12: 7. Insecticides | B12: $__________ | C12: $__________ | D12: $________ | E12: $________ | F12: $________ | G12: $________ | H12: $________
A13: 8. Drying Fuel | B13: 7 | C13: $__________ | D13: $________ | E13: $________ | F13: $________ | G13: $________ | H13: $________
A14: 9. Crop Fuel & Oil | B14: 9.35 | C14: 7.5 | D14: $________ | E14: $________ | F14: $________ | G14: $________ | H14: $________
A15: 10. Crop Repairs | B15: 23.6 | C15: 20.2 | D15: $________ | E15: $________ | F15: $________ | G15: $________ | H15: $________
A16: 12. Crop Utilities | B16: 2.4 | C16: 1.5 | D16: $________ | E16: $________ | F16: $________ | G16: $________ | H16: $________
A17: 13. Crop Haul & Truck | B17: 15.42 | C17: 5.16 | D17: $________ | E17: $________ | F17: $________ | G17: $________ | H17: $________
A18: 14. Crop Marketing | B18: $__________ | C18: 1.72 | D18: $________ | E18: $________ | F18: $________ | G18: $________ | H18: $________
A19: 15. Crop Insurance | B19: $__________ | C19: $__________ | D19: $________ | E19: $________ | F19: $________ | G19: $________ | H19: $________
A20: 16. Other | B20: $__________ | C20: $__________ | D20: $________ | E20: $________ | F20: $________ | G20: $________ | H20: $________
A21: 17. TOTAL DIRECT COST/Ac | B21: =SUM(B9:B20) -> 157.92 | C21: =SUM(C9:C20) -> 94.23 | D21: =SUM(D9:D20) -> 0 | E21: =SUM(E9:E20) -> 0 | F21: =SUM(F9:F20) -> 0 | G21: =SUM(G9:G20) -> 0 | H21: =SUM(H9:H20) -> 0
A23: 18. GROSS MARGIN=G.I.-D.C./Ac | B23: =IF(B21>0,(B6-B21),0) -> 99.08 | C23: =IF(C21>0,(C6-C21),0) -> 133.67 | D23: =IF(D21>0,(D6-D21),0) -> 0 | E23: =IF(E21>0,(E6-E21),0) -> 0 | F23: =IF(F21>0,(F6-F21),0) -> 0 | G23: =IF(G21>0,(G6-G21),0) -> 0 | H23: =IF(H21>0,(H6-H21),0) -> 0
A24: For each crop (line 3) MINUS (line 17)
A25: OVERHEAD COSTS for Farm | B25: Column 1 | C25: 1.Gross Margin can be used in determining which crops will contribute
A26: 19. Acres Cropped | B26: =SUM(B52:H52) -> 2000 | C26: more toward Overhead Cost.
A27: 20. Interest | B27: =Sheet1!D190 -> 69810 | C27: 2. Accounting Costs of Production is the summation of direct
A28: 21. Hired Labor | B28: 25000 | C28: variable (or allocable) and of overhead (or non-allocable) cost.
A29: 22. Land Rents | B29: 82500 | C29: 3. Economic Costs is the summation of total accounting costs plus
A30: 23. Machinery Leases | B30: 0 | C30: the opportunity costs of resources used in the business; e.g. for
A31: 24. Real Estate Taxes | B31: 14100 | C31: equity capital and for unpaid family labor. Being able to price a
A32: 25. Farm Insurance | B32: 12000 | C32: commodity at your economic cost would provide the returns to unpaid
A33: 26. Farm Utilities | B33: 1200 | C33: resources (lines 30 and 31). Selling at less than the economic cost
A34: 27. Other Expenses | B34: 0 | C34: indicates that the price received is not adequate to earn the desired
A35: 28. Depreciation | B35: 60000 | C35: rates of return on unpaid resources.
A36: 29. Total Accounting Overhead Cost | B36: =SUM(B27:B35) -> 264610 | C36: ADD (lines 20 through lines 28)
A38: 30. Value of Unpaid Labor | B38: =Sheet1!D182 -> 45022 | C38: 4.Economic Cost includes a value for any unpaid labor.
A39: 31. Value of Unpaid Equity Capital | B39: =(0.06*Sheet1!D14) -> 66693 | C39: 5.Economic Cost includes opportunity cost of Equity. (6%? of Net Worth)
A40: 32. Total Economic Overhead Cost | B40: =SUM(B36:B39) -> 376325 | C40: ADD(lines 29, 30 and 31)
A42: 33. Total Economic Overhead Cost/Ac | B42: =B40/B26 -> 188.1625 | C42: (line 32) DIVIDED BY (line 19)
B44: =B3 -> CORN | C44: =C3 -> SOYS | D44: =D3 -> WHEAT | E44: =E3 -> OTHER1 | F44: =F3 -> OTHER2 | G44: =G3 -> OTHER3 | H44: =H3 -> OTHER4
A45: 34. Total Economic Costs/Ac | B45: =IF(B21>0,(B21+$B42),0) -> 346.0825 | C45: =IF(C21>0,(C21+$B42),0) -> 282.3925 | D45: =IF(D21>0,(D21+$B42),0) -> 0 | E45: =IF(E21>0,(E21+$B42),0) -> 0 | F45: =IF(F21>0,(F21+$B42),0) -> 0 | G45: =IF(G21>0,(G21+$B42),0) -> 0 | H45: =IF(H21>0,(H21+$B42),0) -> 0
A46: (line 17 for each crop) PLUS (line33)
A47: 35. Total Economic Cost / Bu | B47: =IF(B45>0,(B45/B4),0) -> 2.693249 | C47: =IF(C45>0,(C45/C4),0) -> 6.5672674 | D47: =IF(D45>0,(D45/D4),0) -> 0 | E47: =IF(E45>0,(E45/E4),0) -> 0 | F47: =IF(F45>0,(F45/F4),0) -> 0 | G47: =IF(G45>0,(G45/G4),0) -> 0 | H47: =IF(H45>0,(H45/H4),0) -> 0
A48: For each crop (line 34) DIVIDED BY (line 1)
A49: COST OF PRODUCTION WORKSHEET - Page 3
A50: =A2 -> Medium Debt Farm
B51: =B44 -> CORN | C51: =C44 -> SOYS | D51: =D44 -> WHEAT | E51: =E44 -> OTHER1 | F51: =F44 -> OTHER2 | G51: =G44 -> OTHER3 | H51: =H44 -> OTHER4
A52: 36. Acres planted each crop | B52: 1000 | C52: 1000 | D52: 0 | E52: 0 | F52: 0 | G52: 0 | H52: 0
A54: 37. Total Direct Cost/Ac (line 17) | B54: =B21 -> 157.92 | C54: =C21 -> 94.23 | D54: =D21 -> 0 | E54: =E21 -> 0 | F54: =F21 -> 0 | G54: =G21 -> 0 | H54: =H21 -> 0
A56: 38. Direct Cost per Bushel | B56: =IF(B52>0,(B21/B4),0) -> 1.2289494 | C56: =IF(C52>0,(C21/C4),0) -> 2.1913953 | D56: =IF(D52>0,(D21/D4),0) -> 0 | E56: =IF(E52>0,(E21/E4),0) -> 0 | F56: =IF(F52>0,(F21/F4),0) -> 0 | G56: =IF(G52>0,(G21/G4),0) -> 0 | H56: =IF(H52>0,(H21/H4),0) -> 0
A57: For each crop (line 37)DIVIDED BY (line 1)
A58: 39. Total Direct Cost for Crop | B58: =IF(B54>0,(B52*B54),0) -> 157920 | C58: =IF(C54>0,(C52*C54),0) -> 94230 | D58: =IF(D54>0,(D52*D54),0) -> 0 | E58: =IF(E54>0,(E52*E54),0) -> 0 | F58: =IF(F54>0,(F52*F54),0) -> 0 | G58: =IF(G54>0,(G52*G54),0) -> 0 | H58: =IF(H54>0,(H52*H54),0) -> 0
A59: For each crop (line 36) TIMES (line 37)
A61: 40. Total Direct Cost for all crops combined | C61: =SUM(B58:H58) -> 252150 | D61: (SUM of each column in line 39)
A63: Crop Prices and Crop Revenues Needed to Maintain Net Worth
A64: 41. Total Economic Overhead Cost (line 32) | C64: =B40 -> 376325 | D64: This calculation is used to determine the crop price
A65: 42. Minus Gov. Program & Other Net Incomes | B65: - | C65: =Sheet1!D276 -> 65534 | D65: required after receipt of other farm income;e.g. fixed
A66: 43. Minus Value of Unpaid Equity (line 31) | B66: - | C66: =B39 -> 66693 | D66: government payments, custom work. It covers direct
A67: 44. Plus Income Taxes | B67: + | C67: =Sheet1!D42 -> 8945 | D67: costs associated with the crop, its share of the farm
A68: 45. Minus Value Unpaid Family Labor (line 30) | B68: - | C68: =B38 -> 45022 | D68: overhead, plus expenditures required for family living
A69: 46. Plus Actual Family Living & Other Draws | B69: =B67 -> + | C69: =Sheet1!D41 -> 30000 | D69: and income taxes.
A70: 47. “Maintain Net Worth Overhead Cost” | B70: = | C70: =C64-C65-C66+C67-C68+C69 -> 238021
A71: 48. “Maintain Net Worth Overhead Cost” per Acre | C71: =C70/B26 -> 119.0105 | D71: (line 47) DIVIDED BY (line 19
A72: 49. Total Crop Revenues Needed to Maintain Net Worth | C72: =C61+C70 -> 490171 | E72: (line 40) PLUS (line 47)
B74: =B51 -> CORN | C74: =C51 -> SOYS | D74: WHEAT | E74: OTHER1 | F74: OTHER2 | G74: OTHER3 | H74: OTHER4
A75: 50. Total Revenues Needed / Acre | B75: =IF(B58>0,($C71+B54),0) -> 276.9305 | C75: =IF(C58>0,($C71+C54),0) -> 213.2405 | D75: =IF(D58>0,($C71+D54),0) -> 0 | E75: =IF(E58>0,($C71+E54),0) -> 0 | F75: =IF(F58>0,($C71+F54),0) -> 0 | G75: =IF(G58>0,($C71+G54),0) -> 0 | H75: =IF(H58>0,($C71+H54),0) -> 0
A76: (line 37 for each crop) PLUS (line 48)
A77: 51. Maintain Net Worth per Bu | B77: =IF(B75>0,(B75/B4),0) -> 2.1551012 | C77: =IF(C75>0,(C75/C4),0) -> 4.9590814 | D77: =IF(D75>0,(D75/D4),0) -> 0 | E77: =IF(E75>0,(E75/E4),0) -> 0 | F77: =IF(F75>0,(F75/F4),0) -> 0 | G77: =IF(G75>0,(G75/G4),0) -> 0 | H77: =IF(H75>0,(H75/H4),0) -> 0
A78: For each crop (line 50) DIVIDED BY (line 1)
A80: Crop Prices and Crop Revenues Required to Meet Cash Flow Demands This calculation is to determine the crop price
A81: 52. “Maintain Net Worth Overhead Cost” (line 47) | C81: =C70 -> 238021 | D81: required after receipt of other farm income; e.g.
A82: 53. Minus Depreciation (line 28) | B82: - | C82: =B35 -> 60000 | D82: government payments and custom work, that covers
A83: 54. Minus Interest Expense (line 20) | B83: - | C83: =B27 -> 69810 | D83: all cash flow expenditures for the farm business to
A84: 55. Plus Scheduled Principal and Interest | B84: + | C84: =Sheet1!D46 -> 178601 | D84: continue which includes annual principal payments to
A85: 56. Plus Cash required for Capital Replacement | B85: + | C85: =Sheet1!D48 -> 0 | D85: service debt and an annual planned expenditure for
A86: 57. “Meet Cash Flow Demands Overhead Cost” | B86: = | C86: =C81-C82-C83+C84+C85 -> 286812 | D86: replacement and growth of the farm infrastructure
D87: e.g. machinery, equipment, tile, and buildings.
A88: 58. “Meet Cash Flow Overhead Cost” per Acre | C88: =C86/B26 -> 143.406 | D88: (line 57) DIVIDED BY (line 19)
A90: 59. Total Crop Revenues Needed to Meet Cash Flow Demands | C90: =C61+C86 -> 538962 | E90: (line 40) PLUS (line 57)
B92: =B74 -> CORN | C92: =C74 -> SOYS | D92: =D74 -> WHEAT | E92: =E74 -> OTHER1 | F92: =F74 -> OTHER2 | G92: =G74 -> OTHER3 | H92: =H74 -> OTHER4
A93: 60.Total Crop Revenue Needed per Acre | B93: =IF(B77>0,(B54+$C88),0) -> 301.326 | C93: =IF(C77>0,(C54+$C88),0) -> 237.636 | D93: =IF(D77>0,(D54+$C88),0) -> 0 | E93: =IF(E77>0,(E54+$C88),0) -> 0 | F93: =IF(F77>0,(F54+$C88),0) -> 0 | G93: =IF(G77>0,(G54+$C88),0) -> 0 | H93: =IF(H77>0,(H54+$C88),0) -> 0
A94: (line 37 for each crop) PLUS (line 58)
A95: 61. Meet Cash Flow Demands per Bu | B95: =IF(B93>0,(B93/B4),0) -> 2.3449494 | C95: =IF(C93>0,(C93/C4),0) -> 5.5264186 | D95: =IF(D93>0,(D93/D4),0) -> 0 | E95: =IF(E93>0,(E93/E4),0) -> 0 | F95: =IF(F93>0,(F93/F4),0) -> 0 | G95: =IF(G93>0,(G93/G4),0) -> 0 | H95: =IF(H93>0,(H93/H4),0) -> 0
A96: For each crop (line 60) DIVIDED BY (line 1)
A97: =A2 -> Medium Debt Farm | B97: =B51 -> CORN | C97: =C51 -> SOYS
A98: =A47 -> 35. Total Economic Cost / Bu | B98: =B47 -> 2.693249 | C98: =C47 -> 6.5672674
A99: =A77 -> 51. Maintain Net Worth per Bu | B99: =B77 -> 2.1551012 | C99: =C77 -> 4.9590814
A100: =A95 -> 61. Meet Cash Flow Demands per Bu | B100: =B95 -> 2.3449494 | C100: =C95 -> 5.5264186

Sheet Sheet2 (5)
A1: COST OF PRODUCTION WORKSHEET - Page 2
A2: High Debt Farm
B3: CORN | C3: SOYS | D3: WHEAT | E3: OTHER1 | F3: OTHER2 | G3: OTHER3 | H3: OTHER4
A4: 1. Paid on Yield per Acre in Bushels | B4: 128.5 | C4: 43 | D4: Bu______ | E4: Bu______ | F4: Bu______ | G4: Bu______ | H4: Bu______
A5: 2. TIMES Selling Price per Bu x | B5: 2 | C5: =Sheet1!D223 -> 5.3 | D5: $________ | E5: $________ | F5: $________ | G5: $________ | H5: $________
A6: 3. EQUALS Gross Income per Acre = | B6: =B4*B5 -> 257 | C6: =C4*C5 -> 227.9 | D6: =D4*D5 -> #VALUE! | E6: =E4*E5 -> #VALUE! | F6: =F4*F5 -> #VALUE! | G6: =G4*G5 -> #VALUE! | H6: =H4*H5 -> #VALUE!
A8: DIRECT COST/AC
A9: 4. Seed | B9: 25 | C9: 26.4 | D9: $________ | E9: $________ | F9: $________ | G9: $________ | H9: $________
A10: 5. Fertilizer | B10: 54.8 | C10: 13 | D10: $________ | E10: $________ | F10: $________ | G10: $________ | H10: $________
A11: 6. Herbicides | B11: 20.35 | C11: 18.75 | D11: $________ | E11: $________ | F11: $________ | G11: $________ | H11: $________
A12: 7. Insecticides | B12: $__________ | C12: $__________ | D12: $________ | E12: $________ | F12: $________ | G12: $________ | H12: $________
A13: 8. Drying Fuel | B13: 7 | C13: $__________ | D13: $________ | E13: $________ | F13: $________ | G13: $________ | H13: $________
A14: 9. Crop Fuel & Oil | B14: 9.35 | C14: 7.5 | D14: $________ | E14: $________ | F14: $________ | G14: $________ | H14: $________
A15: 10. Crop Repairs | B15: 23.6 | C15: 20.2 | D15: $________ | E15: $________ | F15: $________ | G15: $________ | H15: $________
A16: 12. Crop Utilities | B16: 2.4 | C16: 1.5 | D16: $________ | E16: $________ | F16: $________ | G16: $________ | H16: $________
A17: 13. Crop Haul & Truck | B17: 15.42 | C17: 5.16 | D17: $________ | E17: $________ | F17: $________ | G17: $________ | H17: $________
A18: 14. Crop Marketing | B18: $__________ | C18: 1.72 | D18: $________ | E18: $________ | F18: $________ | G18: $________ | H18: $________
A19: 15. Crop Insurance | B19: $__________ | C19: $__________ | D19: $________ | E19: $________ | F19: $________ | G19: $________ | H19: $________
A20: 16. Other | B20: $__________ | C20: $__________ | D20: $________ | E20: $________ | F20: $________ | G20: $________ | H20: $________
A21: 17. TOTAL DIRECT COST/Ac | B21: =SUM(B9:B20) -> 157.92 | C21: =SUM(C9:C20) -> 94.23 | D21: =SUM(D9:D20) -> 0 | E21: =SUM(E9:E20) -> 0 | F21: =SUM(F9:F20) -> 0 | G21: =SUM(G9:G20) -> 0 | H21: =SUM(H9:H20) -> 0
A23: 18. GROSS MARGIN=G.I.-D.C./Ac | B23: =IF(B21>0,(B6-B21),0) -> 99.08 | C23: =IF(C21>0,(C6-C21),0) -> 133.67 | D23: =IF(D21>0,(D6-D21),0) -> 0 | E23: =IF(E21>0,(E6-E21),0) -> 0 | F23: =IF(F21>0,(F6-F21),0) -> 0 | G23: =IF(G21>0,(G6-G21),0) -> 0 | H23: =IF(H21>0,(H6-H21),0) -> 0
A24: For each crop (line 3) MINUS (line 17)
A25: OVERHEAD COSTS for Farm | B25: Column 1 | C25: 1.Gross Margin can be used in determining which crops will contribute
A26: 19. Acres Cropped | B26: =SUM(B54:H54) -> 2000 | C26: more toward Overhead Cost.
A27: 20. Interest | B27: =Sheet1!E44 -> 109271 | C27: 2. Accounting Costs of Production is the summation of direct
A28: 21. Hired Labor | B28: 25000 | C28: variable (or allocable) and of overhead (or non-allocable) cost.
A29: 22. Land Rents | B29: 82500 | C29: 3. Economic Costs is the summation of total accounting costs plus
A30: 23. Machinery Leases | B30: 0 | C30: the opportunity costs of resources used in the business; e.g. for
A31: 24. Real Estate Taxes | B31: 14100 | C31: equity capital and for unpaid family labor. Being able to price a
A32: 25. Farm Insurance | B32: 12000 | C32: commodity at your economic cost would provide the returns to unpaid
A33: 26. Farm Utilities | B33: 1200 | C33: resources (lines 30 and 31). Selling at less than the economic cost
A34: 27. Other Expenses | B34: 0 | C34: indicates that the price received is not adequate to earn the desired
A35: 28. Depreciation | B35: 60000 | C35: rates of return on unpaid resources.
A36: 29. Total Accounting Overhead Cost | B36: =SUM(B27:B35) -> 304071 | C36: ADD (lines 20 through lines 28)
A38: 30. Value of Unpaid Labor | B38: =Sheet1!E182 -> 45022 | C38: 4.Economic Cost includes a value for any unpaid labor.
A39: 31. Value of Unpaid Equity Capital | B39: =0.06*Sheet1!E14 -> 42441 | C39: 5.Economic Cost includes opportunity cost of Equity. (6%? of Net Worth)
A40: 32. Total Economic Overhead Cost | B40: =SUM(B36:B39) -> 391534 | C40: ADD(lines 29, 30 and 31)
A42: 33. Total Economic Overhead Cost/Ac | B42: =B40/B26 -> 195.767 | C42: (line 32) DIVIDED BY (line 19)
B45: =B3 -> CORN | C45: =C3 -> SOYS | D45: =D3 -> WHEAT | E45: =E3 -> OTHER1 | F45: =F3 -> OTHER2 | G45: =G3 -> OTHER3 | H45: =H3 -> OTHER4
A46: 34. Total Economic Costs/Ac | B46: =IF(B21>0,(B21+$B42),0) -> 353.687 | C46: =IF(C21>0,(C21+$B42),0) -> 289.997 | D46: =IF(D21>0,(D21+$B42),0) -> 0 | E46: =IF(E21>0,(E21+$B42),0) -> 0 | F46: =IF(F21>0,(F21+$B42),0) -> 0 | G46: =IF(G21>0,(G21+$B42),0) -> 0 | H46: =IF(H21>0,(H21+$B42),0) -> 0
A47: (line 17 for each crop) PLUS (line33)
A49: 35. Total Economic Cost / Bu | B49: =IF(B46>0,(B46/B4),0) -> 2.752428 | C49: =IF(C46>0,(C46/C4),0) -> 6.7441163 | D49: =IF(D46>0,(D46/D4),0) -> 0 | E49: =IF(E46>0,(E46/E4),0) -> 0 | F49: =IF(F46>0,(F46/F4),0) -> 0 | G49: =IF(G46>0,(G46/G4),0) -> 0 | H49: =IF(H46>0,(H46/H4),0) -> 0
A50: For each crop (line 34) DIVIDED BY (line 1)
A51: COST OF PRODUCTION WORKSHEET - Page 3
A52: =A2 -> High Debt Farm
B53: =B45 -> CORN | C53: =C45 -> SOYS | D53: =D45 -> WHEAT | E53: =E45 -> OTHER1 | F53: =F45 -> OTHER2 | G53: =G45 -> OTHER3 | H53: =H45 -> OTHER4
A54: 36. Acres planted each crop | B54: 1000 | C54: 1000 | D54: 0 | E54: 0 | F54: 0 | G54: 0 | H54: 0
A56: 37. Total Direct Cost/Ac (line 17) | B56: =B21 -> 157.92 | C56: =C21 -> 94.23 | D56: =D21 -> 0 | E56: =E21 -> 0 | F56: =F21 -> 0 | G56: =G21 -> 0 | H56: =H21 -> 0
A58: 38. Direct Cost per Bushel | B58: =IF(B54>0,(B21/B4),0) -> 1.2289494 | C58: =IF(C54>0,(C21/C4),0) -> 2.1913953 | D58: =IF(D54>0,(D21/D4),0) -> 0 | E58: =IF(E54>0,(E21/E4),0) -> 0 | F58: =IF(F54>0,(F21/F4),0) -> 0 | G58: =IF(G54>0,(G21/G4),0) -> 0 | H58: =IF(H54>0,(H21/H4),0) -> 0
A59: For each crop (line 37)DIVIDED BY (line 1)
A60: 39. Total Direct Cost for Crop | B60: =IF(B56>0,(B54*B56),0) -> 157920 | C60: =IF(C56>0,(C54*C56),0) -> 94230 | D60: =IF(D56>0,(D54*D56),0) -> 0 | E60: =IF(E56>0,(E54*E56),0) -> 0 | F60: =IF(F56>0,(F54*F56),0) -> 0 | G60: =IF(G56>0,(G54*G56),0) -> 0 | H60: =IF(H56>0,(H54*H56),0) -> 0
A61: For each crop (line 36) TIMES (line 37)
A63: 40. Total Direct Cost for all crops combined | C63: =SUM(B60:H60) -> 252150 | D63: (SUM of each column in line 39)
A65: Crop Prices and Crop Revenues Needed to Maintain Net Worth
A66: 41. Total Economic Overhead Cost (line 32) | C66: =B40 -> 391534 | D66: This calculation is used to determine the crop price
A67: 42. Minus Gov. Program & Other Net Incomes | B67: - | C67: =Sheet1!E276 -> 65534 | D67: required after receipt of other farm income;e.g. fixed
A68: 43. Minus Value of Unpaid Equity (line 31) | B68: - | C68: =B39 -> 42441 | D68: government payments, custom work. It covers direct
A69: 44. Plus Income Taxes | B69: + | C69: =Sheet1!E125 -> 0 | D69: costs associated with the crop, its share of the farm
A70: 45. Minus Value Unpaid Family Labor (line 30) | B70: - | C70: =B38 -> 45022 | D70: overhead, plus expenditures required for family living
A71: 46. Plus Actual Family Living & Other Draws | B71: =B69 -> + | C71: =Sheet1!E111 -> 30000 | D71: and income taxes.
A72: 47. “Maintain Net Worth Overhead Cost” | B72: = | C72: =C66-C67-C68+C69-C70+C71 -> 268537
A73: 48. “Maintain Net Worth Overhead Cost” per Acre | C73: =C72/B26 -> 134.2685 | D73: (line 47) DIVIDED BY (line 19
A74: 49. Total Crop Revenues Needed to Maintain Net Worth | D74: =C63+C72 -> 520687 | E74: (line 40) PLUS (line 47)
B76: =B53 -> CORN | C76: =C53 -> SOYS | D76: WHEAT | E76: OTHER1 | F76: OTHER2 | G76: OTHER3 | H76: OTHER4
A77: 50. Total Revenues Needed / Acre | B77: =IF(B60>0,($C73+B56),0) -> 292.1885 | C77: =IF(C60>0,($C73+C56),0) -> 228.4985 | D77: =IF(D60>0,($C73+D56),0) -> 0 | E77: =IF(E60>0,($C73+E56),0) -> 0 | F77: =IF(F60>0,($C73+F56),0) -> 0 | G77: =IF(G60>0,($C73+G56),0) -> 0 | H77: =IF(H60>0,($C73+H56),0) -> 0
A78: (line 37 for each crop) PLUS (line 48)
A79: 51. Maintain Net Worth per Bu | B79: =IF(B77>0,(B77/B4),0) -> 2.2738405 | C79: =IF(C77>0,(C77/C4),0) -> 5.3139186 | D79: =IF(D77>0,(D77/D4),0) -> 0 | E79: =IF(E77>0,(E77/E4),0) -> 0 | F79: =IF(F77>0,(F77/F4),0) -> 0 | G79: =IF(G77>0,(G77/G4),0) -> 0 | H79: =IF(H77>0,(H77/H4),0) -> 0
A80: For each crop (line 50) DIVIDED BY (line 1)
A82: Crop Prices and Crop Revenues Required to Meet Cash Flow Demands This calculation is to determine the crop price
A83: 52. “Maintain Net Worth Overhead Cost” (line 47) | C83: =C72 -> 268537 | D83: required after receipt of other farm income; e.g.
A84: 53. Minus Depreciation (line 28) | B84: - | C84: =B35 -> 60000 | D84: government payments and custom work, that covers
A85: 54. Minus Interest Expense (line 20) | B85: - | C85: =B27 -> 109271 | D85: all cash flow expenditures for the farm business to
A86: 55. Plus Scheduled Principal and Interest | B86: + | C86: =Sheet1!E46 -> 176312 | D86: continue which includes annual principal payments to
A87: 56. Plus Cash required for Capital Replacement | B87: + | C87: =Sheet1!E48 -> 13521 | D87: service debt and an annual planned expenditure for
A88: 57. “Meet Cash Flow Demands Overhead Cost” | B88: = | C88: =C83-C84-C85+C86+C87 -> 289099 | D88: replacement and growth of the farm infrastructure
D89: e.g. machinery, equipment, tile, and buildings.
A90: 58. “Meet Cash Flow Overhead Cost” per Acre | C90: =C88/B26 -> 144.5495 | D90: (line 57) DIVIDED BY (line 19)
A92: 59. Total Crop Revenues Needed to Meet Cash Flow Demands | D92: =C63+C88 -> 541249 | E92: (line 40) PLUS (line 57)
B93: =B76 -> CORN | C93: =C76 -> SOYS | D93: =D76 -> WHEAT | E93: =E76 -> OTHER1 | F93: =F76 -> OTHER2 | G93: =G76 -> OTHER3 | H93: =H76 -> OTHER4
A95: 60.Total Crop Revenue Needed per Acre | B95: =IF(B79>0,(B56+$C90),0) -> 302.4695 | C95: =IF(C79>0,(C56+$C90),0) -> 238.7795 | D95: =IF(D79>0,(D56+$C90),0) -> 0 | E95: =IF(E79>0,(E56+$C90),0) -> 0 | F95: =IF(F79>0,(F56+$C90),0) -> 0 | G95: =IF(G79>0,(G56+$C90),0) -> 0 | H95: =IF(H79>0,(H56+$C90),0) -> 0
A96: (line 37 for each crop) PLUS (line 58)
A97: 61. Meet Cash Flow Demands per Bu | B97: =IF(B95>0,(B95/B4),0) -> 2.3538482 | C97: =IF(C95>0,(C95/C4),0) -> 5.5530116 | D97: =IF(D95>0,(D95/D4),0) -> 0 | E97: =IF(E95>0,(E95/E4),0) -> 0 | F97: =IF(F95>0,(F95/F4),0) -> 0 | G97: =IF(G95>0,(G95/G4),0) -> 0 | H97: =IF(H95>0,(H95/H4),0) -> 0
A98: For each crop (line 60) DIVIDED BY (line 1)
A99: =A2 -> High Debt Farm | B99: =B53 -> CORN | C99: =C53 -> SOYS
A100: =A49 -> 35. Total Economic Cost / Bu | B100: =B49 -> 2.752428 | C100: =C49 -> 6.7441163
A101: =A79 -> 51. Maintain Net Worth per Bu | B101: =B79 -> 2.2738405 | C101: =C79 -> 5.3139186
A102: =A97 -> 61. Meet Cash Flow Demands per Bu | B102: =B97 -> 2.3538482 | C102: =C97 -> 5.5530116
