Workbook

Sheet Final Report
A1: Digital Reference Statistics
A2: Fall Quarter 2003 (9/29 - 12/12)
A3: Hours: M-Th 11-9, F 11-5
B6: Calls serviced | C6: Total time open (hours) | D6: Average calls per hour
B7: ='Weekly Chart'!H19 -> 584 | C7: 506 | D7: =B7/C7 -> 1.1541502
B9: Mean call length (min) | C9: Median call length (min) | D9: Mode: most often occuring length (min)
B10: 16.09 | C10: 11 | D10: 7
C35: Spring 2001 | D35: 14
B36: Last updated: | C36: Summer 2001 | D36: 45
B37: 37971 | C37: Fall 2001 | D37: 93
C38: Winter 2002 | D38: 114
C39: Spring 2002 | D39: 200
C40: Summer 2002 | D40: 155
C41: Fall 2002 | D41: 316
C42: Winter 2003 | D42: 358
C43: Spring 2003 | D43: 377
C44: Summer 2003 | D44: 294
C45: Fall 2003 | D45: 584

Sheet Weekly Chart
A1: ='Final Report'!A1 -> Digital Reference Statistics
A2: ='Final Report'!A2 -> Fall Quarter 2003 (9/29 - 12/12)
A3: ='Final Report'!A3 -> Hours: M-Th 11-9, F 11-5
A6: Week | C6: Mon | D6: Tues | E6: Wed | F6: Thurs | G6: Fri | H6: Total | I6: Notes
A7: 1 | B7: 9/29-10/3 | C7: 12 | D7: 10 | E7: 8 | F7: 6 | G7: 5 | H7: =SUM(C7:G7) -> 41
A8: 2 | B8: 10/6-10/10 | C8: 6 | D8: 12 | E8: 13 | F8: 12 | G8: 4 | H8: =SUM(C8:G8) -> 47
A9: 3 | B9: 10/13-10/17 | C9: 12 | D9: 11 | E9: 14 | F9: 13 | G9: 6 | H9: =SUM(C9:G9) -> 56
A10: 4 | B10: 10/20-10/24 | C10: 12 | D10: 17 | E10: 6 | F10: 8 | G10: 7 | H10: =SUM(C10:G10) -> 50
A11: 5 | B11: 10/27-10/31 | C11: 16 | D11: 12 | E11: 12 | F11: 12 | G11: 4 | H11: =SUM(C11:G11) -> 56
A12: 6 | B12: 11/3-11/7 | C12: 14 | D12: 14 | E12: 14 | F12: 11 | G12: 4 | H12: =SUM(C12:G12) -> 57
A13: 7 | B13: 11/10-11/14 | C13: 13 | E13: 15 | F13: 10 | G13: 13 | H13: =SUM(C13:G13) -> 51 | I13: Holiday: 11/11 (Veteran's Day)
A14: 8 | B14: 11/17-11/21 | C14: 22 | D14: 14 | E14: 19 | F14: 20 | G14: 8 | H14: =SUM(C14:G14) -> 83 | I14: This week: table tents in dorms
A15: 9 | B15: 11/24-11/28 | C15: 20 | D15: 19 | E15: 10 | H15: =SUM(C15:G15) -> 49 | I15: Holiday: 11/27-28 (Thanksgiving)
A16: 10 | B16: 12/1-12/5 | C16: 10 | D16: 15 | E16: 10 | F16: 7 | G16: 11 | H16: =SUM(C16:G16) -> 53
A17: 11 | B17: 12/8-12/12 | C17: 16 | D17: 11 | E17: 2 | F17: 9 | G17: 3 | H17: =SUM(C17:G17) -> 41
A19: Total | B19: 9/29-12/12 | C19: =SUM(C7:C17) -> 153 | D19: =SUM(D7:D17) -> 135 | E19: =SUM(E7:E17) -> 123 | F19: =SUM(F7:F17) -> 108 | G19: =SUM(G7:G17) -> 65 | H19: =SUM(H7:H17) -> 584
A20: Average | C20: =AVERAGE(C7:C17) -> 13.909091 | D20: =AVERAGE(D7:D17) -> 13.5 | E20: =AVERAGE(E7:E17) -> 11.181818 | F20: =AVERAGE(F7:F17) -> 10.8 | G20: =AVERAGE(G7:G17) -> 6.5 | H20: =AVERAGE(H7:H17) -> 53.090909
A23: ='Final Report'!B36 -> Last updated:
A24: ='Final Report'!B37 -> 37971

Sheet Calls by Day & Week
A1: ='Final Report'!A1 -> Digital Reference Statistics
A2: ='Final Report'!A2 -> Fall Quarter 2003 (9/29 - 12/12)
A3: ='Final Report'!A3 -> Hours: M-Th 11-9, F 11-5
C6: Mon | D6: Tues | E6: Wed | F6: Thurs | G6: Fri
C7: ='Weekly Chart'!C19 -> 153 | D7: ='Weekly Chart'!D19 -> 135 | E7: ='Weekly Chart'!E19 -> 123 | F7: ='Weekly Chart'!F19 -> 108 | G7: ='Weekly Chart'!G19 -> 65
A50: ='Final Report'!B36 -> Last updated:
A51: ='Final Report'!B37 -> 37971

Sheet Calls by Time
A1: ='Final Report'!A1 -> Digital Reference Statistics
A2: ='Final Report'!A2 -> Fall Quarter 2003 (9/29 - 12/12)
A3: ='Final Report'!A3 -> Hours: M-Th 11-9, F 11-5
A6: 11a-12p | B6: 12p-1p | C6: 1p-2p | D6: 2p-3p | E6: 3p-4p | F6: 4p-5p | G6: 5p-6p | H6: 6p-7p | I6: 7p-8p | J6: 8p-9p
A7: 83 | B7: 66 | C7: 50 | D7: 74 | E7: 68 | F7: 81 | G7: 54 | H7: 36 | I7: 42 | J7: 30
A31: ='Final Report'!B36 -> Last updated:
A32: ='Final Report'!B37 -> 37971

Sheet Calls by Library
A1: ='Final Report'!A1 -> Digital Reference Statistics
A2: ='Final Report'!A2 -> Fall Quarter 2003 (9/29 - 12/12)
A3: ='Final Report'!A3 -> Hours: M-Th 11-9, F 11-5
B6: Main | C6: Biomed | D6: College | E6: SEL | F6: YRL | G6: Music | H6: CDL | I6: Orion2 | J6: Total
A7: Calls | B7: 341 | C7: 23 | D7: 16 | E7: 2 | F7: 9 | G7: 2 | H7: 113 | I7: 78 | J7: =SUM(B7:I7) -> 584
A8: Percentage | B8: =B7/$J7*100 -> 58.390411 | C8: =C7/$J7*100 -> 3.9383562 | D8: =D7/$J7*100 -> 2.739726 | E8: =E7/$J7*100 -> 0.34246575 | F8: =F7/$J7*100 -> 1.5410959 | G8: =G7/$J7*100 -> 0.34246575 | H8: =H7/$J7*100 -> 19.349315 | I8: =I7/$J7*100 -> 13.356164 | J8: =SUM(B8:I8) -> 100
A32: ='Final Report'!B36 -> Last updated:
A33: ='Final Report'!B37 -> 37971

Sheet Calls by User Status
A1: ='Final Report'!A1 -> Digital Reference Statistics
A2: ='Final Report'!A2 -> Fall Quarter 2003 (9/29 - 12/12)
A3: ='Final Report'!A3 -> Hours: M-Th 11-9, F 11-5
B6: Undergrad | C6: Graduate | D6: Faculty | E6: Staff | F6: Other UC | G6: Non-UC | H6: Unknown | I6: Total
A7: Calls | B7: 294 | C7: 102 | D7: 12 | E7: 39 | F7: 19 | G7: 59 | H7: 59 | I7: =SUM(B7:H7) -> 584
A8: Percentage | B8: =B7/$I7*100 -> 50.342466 | C8: =C7/$I7*100 -> 17.465753 | D8: =D7/$I7*100 -> 2.0547945 | E8: =E7/$I7*100 -> 6.6780822 | F8: =F7/$I7*100 -> 3.2534247 | G8: =G7/$I7*100 -> 10.10274 | H8: =H7/$I7*100 -> 10.10274 | I8: =SUM(B8:H8) -> 100
A32: ='Final Report'!B36 -> Last updated:
A33: ='Final Report'!B37 -> 37971

Sheet Calls by Subject
A1: ='Final Report'!A1 -> Digital Reference Statistics
A2: ='Final Report'!A2 -> Fall Quarter 2003 (9/29 - 12/12)
A3: ='Final Report'!A3 -> Hours: M-Th 11-9, F 11-5
B6: Arts / Music | C6: Business | D6: Biomed / Science | E6: Humanities / Social Science | F6: Library / Technical | G6: Unknown | H6: Total
A7: Calls | B7: 23 | C7: 10 | D7: 88 | E7: 113 | F7: 342 | G7: 8 | H7: =SUM(B7:G7) -> 584
A8: Percentage | B8: =B7/$H7*100 -> 3.9383562 | C8: =C7/$H7*100 -> 1.7123288 | D8: =D7/$H7*100 -> 15.068493 | E8: =E7/$H7*100 -> 19.349315 | F8: =F7/$H7*100 -> 58.561644 | G8: =G7/$H7*100 -> 1.369863 | H8: =SUM(B8:G8) -> 100
A32: ='Final Report'!B36 -> Last updated:
A33: ='Final Report'!B37 -> 37971

Sheet Calls by Resolution
A1: ='Final Report'!A1 -> Digital Reference Statistics
A2: ='Final Report'!A2 -> Fall Quarter 2003 (9/29 - 12/12)
A3: ='Final Report'!A3 -> Hours: M-Th 11-9, F 11-5
B5: * Note: this page tracks individual calls (a single transaction can span several calls)
B6: Completed | C6: Referred / In Process | D6: Disconnected, continued later | E6: Disconnected, not continued | F6: No librarian logged on | G6: Total
A7: Calls | B7: 385 | C7: 60 | D7: 56 | E7: 136 | F7: 13 | G7: =SUM(B7:F7) -> 650
A8: Percentage | B8: =B7/$G7*100 -> 59.230769 | C8: =C7/$G7*100 -> 9.2307692 | D8: =D7/$G7*100 -> 8.6153846 | E8: =E7/$G7*100 -> 20.923077 | F8: =F7/$G7*100 -> 2 | G8: =SUM(B8:F8) -> 100
A32: ='Final Report'!B36 -> Last updated:
A33: ='Final Report'!B37 -> 37971

Sheet Summary with Questions
A1: ='Final Report'!A1 -> Digital Reference Statistics
A2: ='Final Report'!A2 -> Fall Quarter 2003 (9/29 - 12/12)
A3: ='Final Report'!A3 -> Hours: M-Th 11-9, F 11-5
A6: Transcript | B6: Time of call | C6: Weekday | D6: Length | E6: Subject | F6: Question
A7: 68156 | B7: 9/29/2003 11:14:54 AM | C7: Mon | D7: 9 | E7: Arts/Music | F7: I'm trying to listen to music that was put on reserve for Music History 132: Mozart, but the course is not listed. I'm at the music library, where my professor said was the only place that one could access these files, but I still can't find them.
A8: 68787 | B8: 9/29/2003 5:10:43 PM | C8: Mon | D8: 7 | E8: Arts/Music | F8: I am in music history 132 moxart. Our professor Elisabeth Le Guin told us to go to www.library.ucla.edu and then click on reserves to find our listening homework. i searched both under her name and the class title, but i can not find the recordings. They
A9: 72936 | B9: 10/6/2003 11:26:32 AM | C9: Mon | D9: 12 | E9: Arts/Music | F9: Please could you tell me if it is possible to access the 20th Century Fox production files via the Internet. I am 29 weeks pregnant and based in the UK, so unfortunately I am unable to travel. I am currently writing a full-scale Marilyn Monroe biography
A10: 74116 | B10: 10/7/2003 5:32:47 PM | C10: Tue | D10: 16 | E10: Arts/Music | F10: My photo professor listed a reading for a class as "Picturing Vision" but did not say whether this was a book or chapter in a book. I have not had any success finding it. I assume it is art-related.
A11: 78791 | B11: 10/14/2003 4:07:42 PM | C11: Tue | D11: 4 | E11: Arts/Music | F11: Where are the books that pertain to film, specifically the silent film era?
A12: 79597 | B12: 10/15/2003 2:38:12 PM | C12: Wed | D12: 6 | E12: Arts/Music | F12: I'm looking for a copy of the SCORE for the Khatchaturian flute concerto. I was told that UCLA doesn't own it, but that CSU Fresno and CSU Hayward do. But I can't find it through WorldCat or any other search engine. Can you help me to find the reference,
A13: 80382 | B13: 10/16/2003 12:12:14 PM | C13: Thu | D13: 19 | E13: Arts/Music | F13: Do you have books on animal photography?
A14: 80475 | B14: 10/16/2003 2:25:19 PM | C14: Thu | D14: 8 | E14: Arts/Music | F14: I am looking for instructional videos that teach European folk dance. How can I find it?
A15: 80781 | B15: 10/16/2003 6:02:44 PM | C15: Thu | D15: 13 | E15: Arts/Music | F15: Hi - I'm trying to get some information about a videotape that UCLA has in its library. It's a taping of a 1971 television show called "Serendipity." I was actually on one episode of the show and I am trying to find out any and all information about it.
A16: 81190 | B16: 10/17/2003 12:02:52 PM | C16: Fri | D16: 19 | E16: Arts/Music | F16: I am looking for any kind of information for architect Schindler, Rudolph Michael.
A17: 89199 | B17: 10/28/2003 11:49:13 AM | C17: Tue | D17: 8 | E17: Arts/Music | F17: I am in search of aerial photographs for the City of Bakersfield, Kern County. Does the Research Library have coverage of this area and if so, can I review them today? If not, do you know of another Department/Library which I can review historical aerial
A18: 91833 | B18: 10/30/2003 7:24:03 PM | C18: Thu | D18: 50 | E18: Arts/Music | F18: I,am doing a peper in Art histor. I need the imformation. About my suject which is epigonos dying gaul
... A582: 124000 | B582: 12/12/2003 5:02:41 PM | C582: Fri | D582: 3 | E582: Library/Technical | F582: How do I look up journals for my topic at the ucla library site?
