Workbook

Sheet INSTRUCTIONS

Sheet Inv CC
A1: ESTIMATED INVENTORY CARRYING COST (PRE-TAX)
C2: $ (000) | D2: %
B3: Estimated Average Inventory Balance (from Balance Sheet, otherwise hardinput) | C3: =Financials!B14 -> 485
A5: Cost of Capital of Inventory
A6: Method 1- | B6: 1 Corporate after-tax Opportunity Cost of Capital/Hurdle Rate | D6: 0.15
A7: OR
A8: Method 2- | B8: 2. Estimate after-tax Opportunity Cost of Capital via CAPM & WACC
B9: Debt % of Total Capital | D9: =Financials!C41 -> 0.52380952
B10: Equity % of Total Capital | D10: =Financials!C46 -> 0.47619048
B11: Beta of Equity (or proxy) | C11: 1.2
B12: Risk Free Rate (short-term) | C12: 0.06
B13: Historical Market Premium (short-term) | C13: 0.08
B14: Cost of Equity (per CAPM) | D14: =C12+(C11*C13) -> 0.156
B15: Cost of Debt (short-term) | D15: 0.07
B16: Weighted Average Cost of Capital (after-tax) | D16: =(D9*D15*(1-D18))+(D10*D14) -> 0.096285714
B18: Overall Corporate Income Tax Rate | D18: 0.4
B19: Cost of Capital (pre-tax) | E19: =IF(D6>0,D6/(1-D18),D16/(1-D18)) -> 0.25
A21: Service Costs of Inventory (variable costs)
B22: Personal Property Taxes (ad-valorum) | C22: 4.85 | D22: =C22/$C$3 -> 0.01
B23: Insurance (fire and theft) | C23: 8.1 | D23: =C23/$C$3 -> 0.016701031 | E23: =D23+D22 -> 0.026701031
A25: Storage Costs of Inventory (variable costs)
B26: Plant Warehouse | C26: 0 | D26: =C26/$C$3 -> 0
B27: Public Warehouse | C27: 2.425 | D27: =C27/$C$3 -> 0.005
B28: Rented/Leased Warehouse | C28: 0 | D28: =C28/$C$3 -> 0
B29: Company-Owned Warehouse | C29: 0 | D29: =C29/$C$3 -> 0 | E29: =SUM(D26:D29) -> 0.005
A31: Risk Costs of Inventory (variable costs)
B32: Obsolescence/Write-Down | C32: 3.5 | D32: =C32/$C$3 -> 0.0072164948
B33: Damage | C33: 2 | D33: =C33/$C$3 -> 0.0041237113
B34: Shrinkage | C34: 2 | D34: =C34/$C$3 -> 0.0041237113
B35: Relocation/Transfer (to other facility) | C35: 0 | D35: =C35/$C$3 -> 0 | E35: =SUM(D32:D35) -> 0.015463918
A37: ESTIMATED TOTAL PRE-TAX INVENTORY CARRYING COST | E37: =E19+E23+E29+E35 -> 0.29716495

Sheet Financials
A1: WHOLESALER STRATEGIC PROFIT MODEL
A2: BASELINE INPUTS:
A3: Total Assets | B3: 1000
A4: Asset Turnover (Sales/T. Assets) | B4: 2.7
A5: Debt to Equity Ratio | B5: 1.1
A6: Gross Margin | B6: 0.248
A7: Operating Margin | B7: 0.026
A8: PreTax Margin | B8: 0.025
B9: BASELINE | E9: SCENARIO 1: INVENTORY DOWN 20% | H9: SCENARIO 2: WAREHOUSING EXPENSES DOWN 20% | K9: SCENARIO 3: TRANSPORTATION EXPENSES DOWN 20% | N9: SCENARIO 4: SCENARIOS 1-3 COMBINED
B10: 'AS-IS' ($000) | C10: Common Size | E10: 'TO-BE' ($000) | F10: Common Size | H10: 'TO-BE' ($000) | I10: Common Size | K10: 'TO-BE' ($000) | L10: Common Size | N10: 'TO-BE' ($000) | O10: Common Size
A11: BALANCE SHEET
A12: Cash & Equivlnts, ST Investments | B12: =C12*$B$28 -> 25 | C12: 0.025 | E12: =B12 -> 25 | F12: =E12/E$28 -> 0.027685493 | H12: =B12 -> 25 | I12: =H12/H$28 -> 0.025 | K12: =B12 -> 25 | L12: =K12/K$28 -> 0.025 | N12: =B12 -> 25 | O12: =N12/N$28 -> 0.027685493
A13: Accounts Receivable | B13: =C13*$B$28 -> 354 | C13: 0.354 | E13: =B13 -> 354 | F13: =E13/E$28 -> 0.39202658 | H13: =B13 -> 354 | I13: =H13/H$28 -> 0.354 | K13: =B13 -> 354 | L13: =K13/K$28 -> 0.354 | N13: =B13 -> 354 | O13: =N13/N$28 -> 0.39202658
A14: Inventory | B14: =C14*$B$28 -> 485 | C14: 0.485 | E14: =B14*0.8 -> 388 | F14: =E14/E$28 -> 0.42967885 | H14: =B14 -> 485 | I14: =H14/H$28 -> 0.485 | K14: =B14 -> 485 | L14: =K14/K$28 -> 0.485 | N14: =E14 -> 388 | O14: =N14/N$28 -> 0.42967885
A15: Other Current Assets | B15: =C15*$B$28 -> 22 | C15: 0.022 | E15: =B15 -> 22 | F15: =E15/E$28 -> 0.024363234 | H15: =B15 -> 22 | I15: =H15/H$28 -> 0.022 | K15: =B15 -> 22 | L15: =K15/K$28 -> 0.022 | N15: =B15 -> 22 | O15: =N15/N$28 -> 0.024363234
A16: TOTAL CURRENT ASSETS | B16: =SUM(B12:B15) -> 886 | C16: =B16/$B$28 -> 0.886 | E16: =SUM(E12:E15) -> 789 | F16: =E16/E$28 -> 0.87375415 | H16: =SUM(H12:H15) -> 886 | I16: =H16/H$28 -> 0.886 | K16: =SUM(K12:K15) -> 886 | L16: =K16/K$28 -> 0.886 | N16: =SUM(N12:N15) -> 789 | O16: =N16/N$28 -> 0.87375415
A18: Property, Plant & Equipment (PP&E)
A19: Warehouse/Distribution Gross | B19: =C19*$B$28 -> 128.25 | C19: =2*C21 -> 0.12825 | E19: =B19 -> 128.25 | F19: =E19/E$28 -> 0.14202658 | H19: =B19 -> 128.25 | I19: =H19/H$28 -> 0.12825 | K19: =B19 -> 128.25 | L19: =K19/K$28 -> 0.12825 | N19: =B19 -> 128.25 | O19: =N19/N$28 -> 0.14202658
A20: Warehouse/Distribution Accum Depreciation | B20: =C20*$B$28 -> -64.125 | C20: =-C21 -> -0.064125 | E20: =B20 -> -64.125 | F20: =E20/E$28 -> -0.071013289 | H20: =B20 -> -64.125 | I20: =H20/H$28 -> -0.064125 | K20: =B20 -> -64.125 | L20: =K20/K$28 -> -0.064125 | N20: =B20 -> -64.125 | O20: =N20/N$28 -> -0.071013289
A21: Net Warehouse/Distribution PP&E | B21: =C21*$B$28 -> 64.125 | C21: =0.75*$C$25 -> 0.064125 | E21: =SUM(E19:E20) -> 64.125 | F21: =E21/E$28 -> 0.071013289 | H21: =SUM(H19:H20) -> 64.125 | I21: =H21/H$28 -> 0.064125 | K21: =SUM(K19:K20) -> 64.125 | L21: =K21/K$28 -> 0.064125 | N21: =SUM(N19:N20) -> 64.125 | O21: =N21/N$28 -> 0.071013289
A22: Other PP&E Gross | B22: =C22*$B$28 -> 42.75 | C22: =2*C24 -> 0.04275 | E22: =B22 -> 42.75 | F22: =E22/E$28 -> 0.047342193 | H22: =B22 -> 42.75 | I22: =H22/H$28 -> 0.04275 | K22: =B22 -> 42.75 | L22: =K22/K$28 -> 0.04275 | N22: =B22 -> 42.75 | O22: =N22/N$28 -> 0.047342193
A23: Other PP&E Accum Depreciation | B23: =C23*$B$28 -> -21.375 | C23: =-C24 -> -0.021375 | E23: =B23 -> -21.375 | F23: =E23/E$28 -> -0.023671096 | H23: =B23 -> -21.375 | I23: =H23/H$28 -> -0.021375 | K23: =B23 -> -21.375 | L23: =K23/K$28 -> -0.021375 | N23: =B23 -> -21.375 | O23: =N23/N$28 -> -0.023671096
A24: Net Other PP&E | B24: =C24*$B$28 -> 21.375 | C24: =0.25*$C$25 -> 0.021375 | E24: =SUM(E22:E23) -> 21.375 | F24: =E24/E$28 -> 0.023671096 | H24: =SUM(H22:H23) -> 21.375 | I24: =H24/H$28 -> 0.021375 | K24: =SUM(K22:K23) -> 21.375 | L24: =K24/K$28 -> 0.021375 | N24: =SUM(N22:N23) -> 21.375 | O24: =N24/N$28 -> 0.023671096
A25: Net Total PP&E | B25: =C25*$B$28 -> 85.5 | C25: =0.75*$C$27 -> 0.0855 | E25: =E24+E21 -> 85.5 | F25: =E25/E$28 -> 0.094684385 | H25: =H24+H21 -> 85.5 | I25: =H25/H$28 -> 0.0855 | K25: =K24+K21 -> 85.5 | L25: =K25/K$28 -> 0.0855 | N25: =N24+N21 -> 85.5 | O25: =N25/N$28 -> 0.094684385
A26: Other NonCurrent Assets | B26: =C26*$B$28 -> 28.5 | C26: =0.25*$C$27 -> 0.0285 | E26: =B26 -> 28.5 | F26: =E26/E$28 -> 0.031561462 | H26: =B26 -> 28.5 | I26: =H26/H$28 -> 0.0285 | K26: =B26 -> 28.5 | L26: =K26/K$28 -> 0.0285 | N26: =B26 -> 28.5 | O26: =N26/N$28 -> 0.031561462
A27: TOTAL NONCURRENT ASSETS | B27: =C27*$B$28 -> 114 | C27: 0.114 | E27: =E26+E21+E24 -> 114 | F27: =E27/E$28 -> 0.12624585 | H27: =H26+H21+H24 -> 114 | I27: =H27/H$28 -> 0.114 | K27: =K26+K21+K24 -> 114 | L27: =K27/K$28 -> 0.114 | N27: =N26+N21+N24 -> 114 | O27: =N27/N$28 -> 0.12624585
A28: TOTAL ASSETS | B28: =B3 -> 1000 | C28: =B28/$B$28 -> 1 | E28: =E27+E16 -> 903 | F28: =E28/E$28 -> 1 | H28: =H27+H16 -> 1000 | I28: =H28/H$28 -> 1 | K28: =K27+K16 -> 1000 | L28: =K28/K$28 -> 1 | N28: =N27+N16 -> 903 | O28: =N28/N$28 -> 1
A30: Accounts Payable
A31: Inventory/COGS Payables | B31: =C31*$B$48 -> 194.25 | C31: =0.75*0.259 -> 0.19425 | E31: =(B31-(B14-E14)) -> 97.25 | F31: =E31/E$28 -> 0.10769657 | H31: =B31 -> 194.25 | I31: =H31/H$28 -> 0.19425 | K31: =B31 -> 194.25 | L31: =K31/K$28 -> 0.19425 | N31: =E31 -> 97.25 | O31: =N31/N$28 -> 0.10769657
A32: Other Payables | B32: =C32*$B$48 -> 64.75 | C32: =0.25*0.259 -> 0.06475 | E32: =B32 -> 64.75 | F32: =E32/E$28 -> 0.071705426 | H32: =B32 -> 64.75 | I32: =H32/H$28 -> 0.06475 | K32: =B32 -> 64.75 | L32: =K32/K$28 -> 0.06475 | N32: =B32 -> 64.75 | O32: =N32/N$28 -> 0.071705426
A33: Current Debt | B33: =C33*$B$48 -> 107 | C33: 0.107 | E33: =B33 -> 107 | F33: =E33/E$28 -> 0.11849391 | H33: =B33 -> 107 | I33: =H33/H$28 -> 0.107 | K33: =B33 -> 107 | L33: =K33/K$28 -> 0.107 | N33: =B33 -> 107 | O33: =N33/N$28 -> 0.11849391
A34: Accrued Expenses | B34: =C34*$B$48 -> 20.25 | C34: =0.25*0.081 -> 0.02025 | E34: =B34 -> 20.25 | F34: =E34/E$28 -> 0.022425249 | H34: =B34 -> 20.25 | I34: =H34/H$28 -> 0.02025 | K34: =B34 -> 20.25 | L34: =K34/K$28 -> 0.02025 | N34: =B34 -> 20.25 | O34: =N34/N$28 -> 0.022425249
A35: Other Current Liabilities | B35: =C35*$B$48 -> 60.75 | C35: =0.75*0.081 -> 0.06075 | E35: =B35 -> 60.75 | F35: =E35/E$28 -> 0.067275748 | H35: =B35 -> 60.75 | I35: =H35/H$28 -> 0.06075 | K35: =B35 -> 60.75 | L35: =K35/K$28 -> 0.06075 | N35: =B35 -> 60.75 | O35: =N35/N$28 -> 0.067275748
A36: TOTAL CURRENT LIABILITIES | B36: =SUM(B31:B35) -> 447 | C36: =SUM(C31:C35) -> 0.447 | E36: =SUM(E31:E35) -> 350 | F36: =E36/E$28 -> 0.3875969 | H36: =SUM(H31:H35) -> 447 | I36: =H36/H$28 -> 0.447 | K36: =SUM(K31:K35) -> 447 | L36: =K36/K$28 -> 0.447 | N36: =SUM(N31:N35) -> 350 | O36: =N36/N$28 -> 0.3875969
A38: NonCurrent Debt | B38: =C38*$B$48 -> 57.607143 | C38: =0.75*$C$40 -> 0.057607143 | E38: =B38 -> 57.607143 | F38: =E38/E$28 -> 0.063795286 | H38: =B38 -> 57.607143 | I38: =H38/H$28 -> 0.057607143 | K38: =B38 -> 57.607143 | L38: =K38/K$28 -> 0.057607143 | N38: =B38 -> 57.607143 | O38: =N38/N$28 -> 0.063795286
A39: Other NonCurrent Liabilities | B39: =C39*$B$48 -> 19.202381 | C39: =0.25*$C$40 -> 0.019202381 | E39: =B39 -> 19.202381 | F39: =E39/E$28 -> 0.021265095 | H39: =B39 -> 19.202381 | I39: =H39/H$28 -> 0.019202381 | K39: =B39 -> 19.202381 | L39: =K39/K$28 -> 0.019202381 | N39: =B39 -> 19.202381 | O39: =N39/N$28 -> 0.021265095
A40: TOTAL NONCURRENT LIABILITIES | B40: =SUM(B38:B39) -> 76.809524 | C40: =(C41-C36) -> 0.076809524 | E40: =SUM(E38:E39) -> 76.809524 | F40: =E40/E$28 -> 0.085060381 | H40: =SUM(H38:H39) -> 76.809524 | I40: =H40/H$28 -> 0.076809524 | K40: =SUM(K38:K39) -> 76.809524 | L40: =K40/K$28 -> 0.076809524 | N40: =SUM(N38:N39) -> 76.809524 | O40: =N40/N$28 -> 0.085060381
A41: TOTAL LIABILITIES | B41: =C41*$B$48 -> 523.80952 | C41: =(B5/(1+B5)) -> 0.52380952 | E41: =E40+E36 -> 426.80952 | F41: =E41/E$28 -> 0.47265728 | H41: =H40+H36 -> 523.80952 | I41: =H41/H$28 -> 0.52380952 | K41: =K40+K36 -> 523.80952 | L41: =K41/K$28 -> 0.52380952 | N41: =N40+N36 -> 426.80952 | O41: =N41/N$28 -> 0.47265728
A43: Stock - Par | B43: =C43*$B$48 -> 4.7619048 | C43: =0.01*$C$46 -> 0.0047619048 | E43: =B43 -> 4.7619048 | F43: =E43/E$28 -> 0.0052734272 | H43: =B43 -> 4.7619048 | I43: =H43/H$28 -> 0.0047619048 | K43: =B43 -> 4.7619048 | L43: =K43/K$28 -> 0.0047619048 | N43: =B43 -> 4.7619048 | O43: =N43/N$28 -> 0.0052734272
A44: Stock - Surplus | B44: =C44*$B$48 -> 95.238095 | C44: =0.2*$C$46 -> 0.095238095 | E44: =B44 -> 95.238095 | F44: =E44/E$28 -> 0.10546854 | H44: =B44 -> 95.238095 | I44: =H44/H$28 -> 0.095238095 | K44: =B44 -> 95.238095 | L44: =K44/K$28 -> 0.095238095 | N44: =B44 -> 95.238095 | O44: =N44/N$28 -> 0.10546854
A45: Retained Earnings | B45: =C45*$B$48 -> 376.19048 | C45: =0.79*$C$46 -> 0.37619048 | E45: =B45 -> 376.19048 | F45: =E45/E$28 -> 0.41660075 | H45: =B45 -> 376.19048 | I45: =H45/H$28 -> 0.37619048 | K45: =B45 -> 376.19048 | L45: =K45/K$28 -> 0.37619048 | N45: =B45 -> 376.19048 | O45: =N45/N$28 -> 0.41660075
A46: TOTAL EQUITY | B46: =C46*$B$48 -> 476.19048 | C46: =C48-C41 -> 0.47619048 | E46: =SUM(E43:E45) -> 476.19048 | F46: =E46/E$28 -> 0.52734272 | H46: =SUM(H43:H45) -> 476.19048 | I46: =H46/H$28 -> 0.47619048 | K46: =SUM(K43:K45) -> 476.19048 | L46: =K46/K$28 -> 0.47619048 | N46: =SUM(N43:N45) -> 476.19048 | O46: =N46/N$28 -> 0.52734272
A48: TOTAL LIABILITIES & EQUITY | B48: =B28 -> 1000 | C48: =B48/$B$28 -> 1 | E48: =E28 -> 903 | F48: =E48/E$28 -> 1 | H48: =H28 -> 1000 | I48: =H48/H$28 -> 1 | K48: =K28 -> 1000 | L48: =K48/K$28 -> 1 | N48: =N28 -> 903 | O48: =N48/N$28 -> 1
B49: =IF(B46+B41<>B28,"ERROR","") | E49: =IF(E46+E41<>E28,"ERROR","") | H49: =IF(H46+H41<>H28,"ERROR","") | K49: =IF(K46+K41<>K28,"ERROR","") | N49: =IF(N46+N41<>N28,"ERROR","")
A50: INCOME STATEMENT
A51: Gross Sales | B51: =B53+B52 -> 2781 | C51: =B51/B53 -> 1.03 | E51: =B51 -> 2781 | F51: =E51/$E$53 -> 1.03 | H51: =B51 -> 2781 | I51: =H51/H$53 -> 1.03 | K51: =B51 -> 2781 | L51: =K51/K$53 -> 1.03 | N51: =B51 -> 2781 | O51: =N51/N$53 -> 1.03
A52: Returns, Allowances & Discounts | B52: =C52*B53 -> 81 | C52: 0.03 | E52: =B52 -> 81 | F52: =E52/$E$53 -> 0.03 | H52: =B52 -> 81 | I52: =H52/H$53 -> 0.03 | K52: =B52 -> 81 | L52: =K52/K$53 -> 0.03 | N52: =B52 -> 81 | O52: =N52/N$53 -> 0.03
A53: Net Sales | B53: =B28*B4 -> 2700 | C53: =B53/$B$53 -> 1 | E53: =E51-E52 -> 2700 | F53: =E53/$E$53 -> 1 | H53: =H51-H52 -> 2700 | I53: =H53/H$53 -> 1 | K53: =K51-K52 -> 2700 | L53: =K53/K$53 -> 1 | N53: =N51-N52 -> 2700 | O53: =N53/N$53 -> 1
A54: Cost of Goods Sold
A55: Direct Product Cost | B55: =C55*$B$53 -> 1989.792 | C55: =(0.98*($C$53-$C$57)) -> 0.73696 | E55: =B55 -> 1989.792 | F55: =E55/$E$53 -> 0.73696 | H55: =B55 -> 1989.792 | I55: =H55/H$53 -> 0.73696 | K55: =B55 -> 1989.792 | L55: =K55/K$53 -> 0.73696 | N55: =B55 -> 1989.792 | O55: =N55/N$53 -> 0.73696
A56: In-bound Freight | B56: =C56*$B$53 -> 40.608 | C56: =(0.02*($C$53-$C$57)) -> 0.01504 | E56: =B56 -> 40.608 | F56: =E56/$E$53 -> 0.01504 | H56: =B56 -> 40.608 | I56: =H56/H$53 -> 0.01504 | K56: =B56*0.8 -> 32.4864 | L56: =K56/K$53 -> 0.012032 | N56: =K56 -> 32.4864 | O56: =N56/N$53 -> 0.012032
A57: GROSS MARGIN | B57: =B53-SUM(B55:B56) -> 669.6 | C57: =B6 -> 0.248 | E57: =E53-SUM(E55:E56) -> 669.6 | F57: =E57/$E$53 -> 0.248 | H57: =H53-SUM(H55:H56) -> 669.6 | I57: =H57/H$53 -> 0.248 | K57: =K53-SUM(K55:K56) -> 677.7216 | L57: =K57/K$53 -> 0.251008 | N57: =N53-SUM(N55:N56) -> 677.7216 | O57: =N57/N$53 -> 0.251008
B58: =IF(B57/B53<>C57,"ERROR","")
A59: Warehouse/Distribution Expenses
A60: General Warehousing Expense (cost of operations) | B60: =C60*$B$53 -> 276.023 | C60: =C57-C76-SUM(C61:C75) -> 0.10223074 | E60: =B60 -> 276.023 | F60: =E60/$E$53 -> 0.10223074 | H60: =B60*0.8 -> 220.8184 | I60: =H60/H$53 -> 0.081784593 | K60: =B60 -> 276.023 | L60: =K60/K$53 -> 0.10223074 | N60: =H60 -> 220.8184 | O60: =N60/N$53 -> 0.081784593
A61: Public/Leased Facilities (storage-related inventory CC) | B61: =SUM('Inv CC'!C26:C29) -> 2.425 | C61: =B61/$B$53 -> 0.00089814815 | E61: =E14*SUM('Inv CC'!D26:D29) -> 1.94 | F61: =E61/$E$53 -> 0.00071851852 | H61: =B61 -> 2.425 | I61: =H61/H$53 -> 0.00089814815 | K61: =B61 -> 2.425 | L61: =K61/K$53 -> 0.00089814815 | N61: =E61 -> 1.94 | O61: =N61/N$53 -> 0.00071851852
A62: Insurance
A63: Warehousing/Distribution Facilities | B63: =C63*$B$53 -> 8.1 | C63: 0.003 | E63: =B63-(0.1*(E61/B61)) -> 8.02 | F63: =E63/$E$53 -> 0.0029703704 | H63: =B63 -> 8.1 | I63: =H63/H$53 -> 0.003 | K63: =B63 -> 8.1 | L63: =K63/K$53 -> 0.003 | N63: =E63 -> 8.02 | O63: =N63/N$53 -> 0.0029703704
A64: Inventory (service-related inventory CC) | B64: ='Inv CC'!C23 -> 8.1 | C64: =B64/$B$53 -> 0.003 | E64: =$E$14*'Inv CC'!D23 -> 6.48 | F64: =E64/$E$53 -> 0.0024 | H64: =B64 -> 8.1 | I64: =H64/H$53 -> 0.003 | K64: =B64 -> 8.1 | L64: =K64/K$53 -> 0.003 | N64: =E64 -> 6.48 | O64: =N64/N$53 -> 0.0024
A65: Inventory Obsolescence (risk-related inventory CC) | B65: ='Inv CC'!C32 -> 3.5 | C65: =B65/$B$53 -> 0.0012962963 | E65: =$E$14*'Inv CC'!D32 -> 2.8 | F65: =E65/$E$53 -> 0.001037037 | H65: =B65 -> 3.5 | I65: =H65/H$53 -> 0.0012962963 | K65: =B65 -> 3.5 | L65: =K65/K$53 -> 0.0012962963 | N65: =E65 -> 2.8 | O65: =N65/N$53 -> 0.001037037
A66: Inventory Damage (risk-related inventory CC) | B66: ='Inv CC'!C33 -> 2 | C66: =B66/$B$53 -> 0.00074074074 | E66: =$E$14*'Inv CC'!D33 -> 1.6 | F66: =E66/$E$53 -> 0.00059259259 | H66: =B66 -> 2 | I66: =H66/H$53 -> 0.00074074074 | K66: =B66 -> 2 | L66: =K66/K$53 -> 0.00074074074 | N66: =E66 -> 1.6 | O66: =N66/N$53 -> 0.00059259259
A67: Inventory Shrinkage (risk-related inventory CC) | B67: ='Inv CC'!C34 -> 2 | C67: =B67/$B$53 -> 0.00074074074 | E67: =$E$14*'Inv CC'!D34 -> 1.6 | F67: =E67/$E$53 -> 0.00059259259 | H67: =B67 -> 2 | I67: =H67/H$53 -> 0.00074074074 | K67: =B67 -> 2 | L67: =K67/K$53 -> 0.00074074074 | N67: =E67 -> 1.6 | O67: =N67/N$53 -> 0.00059259259
A68: Inventory Relocation (risk-related inventory CC) | B68: ='Inv CC'!C35 -> 0 | C68: =B68/$B$53 -> 0 | E68: =$E$14*'Inv CC'!D35 -> 0 | F68: =E68/$E$53 -> 0 | H68: =B68 -> 0 | I68: =H68/H$53 -> 0 | K68: =B68 -> 0 | L68: =K68/K$53 -> 0 | N68: =E68 -> 0 | O68: =N68/N$53 -> 0
A69: Sales, General & Administrative Expenses
A70: General SG&A (salaries, corporate overhead) | B70: =C70*$B$53 -> 178.2 | C70: 0.066 | E70: =B70 -> 178.2 | F70: =E70/$E$53 -> 0.066 | H70: =B70 -> 178.2 | I70: =H70/H$53 -> 0.066 | K70: =B70 -> 178.2 | L70: =K70/K$53 -> 0.066 | N70: =B70 -> 178.2 | O70: =N70/N$53 -> 0.066
A71: Out-bound Freight | B71: =(B56/0.3)*0.7 -> 94.752 | C71: =B71/$B$53 -> 0.035093333 | E71: =B71 -> 94.752 | F71: =E71/$E$53 -> 0.035093333 | H71: =B71 -> 94.752 | I71: =H71/H$53 -> 0.035093333 | K71: =B71*0.8 -> 75.8016 | L71: =K71/K$53 -> 0.028074667 | N71: =K71 -> 75.8016 | O71: =N71/N$53 -> 0.028074667
A72: Customer Service Expense | B72: =C72*$B$53 -> 13.5 | C72: 0.005 | E72: =B72 -> 13.5 | F72: =E72/$E$53 -> 0.005 | H72: =B72*0.8 -> 10.8 | I72: =H72/H$53 -> 0.004 | K72: =B72 -> 13.5 | L72: =K72/K$53 -> 0.005 | N72: =H72 -> 10.8 | O72: =N72/N$53 -> 0.004
A73: Depreciation & Amortization
A74: General Corporate Depreciation | B74: =C74*$B$53 -> 5.4 | C74: 0.002 | E74: =B74 -> 5.4 | F74: =E74/$E$53 -> 0.002 | H74: =B74 -> 5.4 | I74: =H74/H$53 -> 0.002 | K74: =B74 -> 5.4 | L74: =K74/K$53 -> 0.002 | N74: =B74 -> 5.4 | O74: =N74/N$53 -> 0.002
A75: Warehouse/Distribution Depreciation | B75: =C75*$B$53 -> 5.4 | C75: 0.002 | E75: =B75 -> 5.4 | F75: =E75/$E$53 -> 0.002 | H75: =B75 -> 5.4 | I75: =H75/H$53 -> 0.002 | K75: =B75 -> 5.4 | L75: =K75/K$53 -> 0.002 | N75: =B75 -> 5.4 | O75: =N75/N$53 -> 0.002
A76: OPERATING INCOME | B76: =C76*$B$53 -> 70.2 | C76: =B7 -> 0.026 | E76: =E57-SUM(E60:E75) -> 73.885 | F76: =C76 -> 0.026 | H76: =H57-SUM(H60:H75) -> 128.1046 | I76: =H76/H$53 -> 0.047446148 | K76: =K57-SUM(K60:K75) -> 97.272 | L76: =K76/K$53 -> 0.036026667 | N76: =N57-SUM(N60:N75) -> 158.8616 | O76: =N76/N$53 -> 0.05883763
A77: Interest Expense/Income | B77: =IF(ABS(B76-(B57-SUM(B60:B75)))>0.0001,"ERROR","") | E77: =IF(ABS(E76-(E57-SUM(E60:E75)))>0.0001,"ERROR","") | H77: =IF(ABS(H76-(H57-SUM(H60:H75)))>0.0001,"ERROR","") | K77: =IF(ABS(K76-(K57-SUM(K60:K75)))>0.0001,"ERROR","") | N77: =IF(ABS(N76-(N57-SUM(N60:N75)))>0.0001,"ERROR","")
A78: General Corporate Debt Interest | B78: =C78*$B$53 -> 5.4 | C78: 0.002 | E78: =B78 -> 5.4 | F78: =E78/$E$53 -> 0.002 | H78: =B78 -> 5.4 | I78: =H78/H$53 -> 0.002 | K78: =B78 -> 5.4 | L78: =K78/K$53 -> 0.002 | N78: =B78 -> 5.4 | O78: =N78/N$53 -> 0.002
A79: Warehousing/Distribution Facilities Interest | B79: =C79*$B$53 -> 8.1 | C79: 0.003 | E79: =B79 -> 8.1 | F79: =E79/$E$53 -> 0.003 | H79: =B79 -> 8.1 | I79: =H79/H$53 -> 0.003 | K79: =B79 -> 8.1 | L79: =K79/K$53 -> 0.003 | N79: =B79 -> 8.1 | O79: =N79/N$53 -> 0.003
A80: Excess Inventory Interest (carrying cost) | B80: =C80*$B$53 -> 5.4 | C80: 0.002 | E80: =B80*0.8 -> 4.32 | F80: =E80/$E$53 -> 0.0016 | H80: =B80 -> 5.4 | I80: =H80/H$53 -> 0.002 | K80: =B80 -> 5.4 | L80: =K80/K$53 -> 0.002 | N80: =E80 -> 4.32 | O80: =N80/N$53 -> 0.0016
A81: Other NonOperating Expense/(Income) | B81: =C81*$B$53 -> -16.2 | C81: -0.006 | E81: =B81 -> -16.2 | F81: =E81/$E$53 -> -0.006 | H81: =B81 -> -16.2 | I81: =H81/H$53 -> -0.006 | K81: =B81 -> -16.2 | L81: =K81/K$53 -> -0.006 | N81: =B81 -> -16.2 | O81: =N81/N$53 -> -0.006
A82: PRETAX INCOME | B82: =C82*B53 -> 67.5 | C82: =B8 -> 0.025 | E82: =E76-SUM(E78:E81) -> 72.265 | F82: =E82/$E$53 -> 0.026764815 | H82: =H76-SUM(H78:H81) -> 125.4046 | I82: =H82/H$53 -> 0.046446148 | K82: =K76-SUM(K78:K81) -> 94.572 | L82: =K82/K$53 -> 0.035026667 | N82: =N76-SUM(N78:N81) -> 157.2416 | O82: =N82/N$53 -> 0.05823763
B83: =IF(B76-SUM(B78:B81)<>B82,"ERROR","") | E83: =IF(E76-SUM(E78:E81)<>E82,"ERROR","") | H83: =IF(H76-SUM(H78:H81)<>H82,"ERROR","") | K83: =IF(K76-SUM(K78:K81)<>K82,"ERROR","") | N83: =IF(N76-SUM(N78:N81)<>N82,"ERROR","")
A84: Overall Corporate Income Taxes (40%) | B84: =B82*'Inv CC'!$D$18 -> 27 | C84: =B84/$B$53 -> 0.01 | E84: =E82*'Inv CC'!$D$18 -> 28.906 | F84: =E84/$E$53 -> 0.010705926 | H84: =H82*'Inv CC'!$D$18 -> 50.16184 | I84: =H84/H$53 -> 0.018578459 | K84: =K82*'Inv CC'!$D$18 -> 37.8288 | L84: =K84/K$53 -> 0.014010667 | N84: =N82*'Inv CC'!$D$18 -> 62.89664 | O84: =N84/N$53 -> 0.023295052
A85: Personal Property Taxes (service-related inventory CC) | B85: =(B14*'Inv CC'!$D$22) -> 4.85 | C85: =B85/$B$53 -> 0.0017962963 | E85: =(E14*'Inv CC'!$D$22) -> 3.88 | F85: =E85/$E$53 -> 0.001437037 | H85: =(H14*'Inv CC'!$D$22) -> 4.85 | I85: =H85/H$53 -> 0.0017962963 | K85: =(K14*'Inv CC'!$D$22) -> 4.85 | L85: =K85/K$53 -> 0.0017962963 | N85: =(N14*'Inv CC'!$D$22) -> 3.88 | O85: =N85/N$53 -> 0.001437037
A86: Discontinued Ops, Extraordinary Items (net of tax) | B86: 0 | C86: =B86/$B$53 -> 0 | E86: =B86 -> 0 | F86: =E86/$E$53 -> 0 | H86: =B86 -> 0 | I86: =H86/H$53 -> 0 | K86: =B86 -> 0 | L86: =K86/K$53 -> 0 | N86: =B86 -> 0 | O86: =N86/N$53 -> 0
A87: NET INCOME | B87: =B82-SUM(B84:B86) -> 35.65 | C87: =B87/$B$53 -> 0.013203704 | E87: =E82-SUM(E84:E86) -> 39.479 | F87: =E87/$E$53 -> 0.014621852 | H87: =H82-SUM(H84:H86) -> 70.39276 | I87: =H87/H$53 -> 0.026071393 | K87: =K82-SUM(K84:K86) -> 51.8932 | L87: =K87/K$53 -> 0.019219704 | N87: =N82-SUM(N84:N86) -> 90.46496 | O87: =N87/N$53 -> 0.033505541
B88: =IF(B82-SUM(B84:B86)<>B87,"ERROR","") | E88: =IF(E82-SUM(E84:E86)<>E87,"ERROR","") | H88: =IF(H82-SUM(H84:H86)<>H87,"ERROR","") | K88: =IF(K82-SUM(K84:K86)<>K87,"ERROR","") | N88: =IF(N82-SUM(N84:N86)<>N87,"ERROR","")
A89: KEY PERFORMANCE METRICS
A90: Inventory Turns (on COGS) | B90: =(B55+B56)/B14 -> 4.1863918 | E90: =(E55+E56)/E14 -> 5.2329897 | H90: =(H55+H56)/H14 -> 4.1863918 | K90: =(K55+K56)/K14 -> 4.1696462 | N90: =(N55+N56)/N14 -> 5.2120577
A91: Inventory Days | B91: =B98 -> 87.187254 | E91: =E98 -> 69.749803 | H91: =H98 -> 87.187254 | K91: =K98 -> 87.537403 | N91: =N98 -> 70.029923
A92: Return on Assets (After-Tax) | B92: =B87/B28 -> 0.03565 | E92: =E87/E28 -> 0.043719823 | H92: =H87/H28 -> 0.07039276 | K92: =K87/K28 -> 0.0518932 | N92: =N87/N28 -> 0.10018268
A93: Return on Equity (After-Tax) | B93: =B87/B46 -> 0.074865 | E93: =E87/E46 -> 0.0829059 | H93: =H87/H46 -> 0.1478248 | K93: =K87/K46 -> 0.10897572 | N93: =N87/N46 -> 0.18997642
A95: Accounts Receivable Turns (on Sales) | B95: =B53/B13 -> 7.6271186 | E95: =E53/E13 -> 7.6271186 | H95: =H53/H13 -> 7.6271186 | K95: =K53/K13 -> 7.6271186 | N95: =N53/N13 -> 7.6271186
A96: Cash-to-Cash Cycle (Days) | B96: =SUM(B97:B99) -> 100.12297 | E96: =SUM(E97:E99) -> 100.12297 | H96: =SUM(H97:H99) -> 100.12297 | K96: =SUM(K97:K99) -> 100.33288 | N96: =SUM(N97:N99) -> 100.33288
A97: Accounts Payble Days | B97: =-365/(SUM(B55:B56)/B31) -> -34.919843 | E97: =-365/(SUM(E55:E56)/E31) -> -17.482393 | H97: =-365/(SUM(H55:H56)/H31) -> -34.919843 | K97: =-365/(SUM(K55:K56)/K31) -> -35.060084 | N97: =-365/(SUM(N55:N56)/N31) -> -17.552603
A98: Inventory Days | B98: =365/B90 -> 87.187254 | E98: =365/E90 -> 69.749803 | H98: =365/H90 -> 87.187254 | K98: =365/K90 -> 87.537403 | N98: =365/N90 -> 70.029923
A99: Accounts Receivable Days | B99: =365/B95 -> 47.855556 | E99: =365/E95 -> 47.855556 | H99: =365/H95 -> 47.855556 | K99: =365/K95 -> 47.855556 | N99: =365/N95 -> 47.855556
A100: Return on Equity (Before-Tax) | B100: =(B82/B53)*(B53/B28)*(B28/B46) -> 0.14175 | E100: =(E82/E53)*(E53/E28)*(E28/E46) -> 0.1517565 | H100: =(H82/H53)*(H53/H28)*(H28/H46) -> 0.26334966 | K100: =(K82/K53)*(K53/K28)*(K28/K46) -> 0.1986012 | N100: =(N82/N53)*(N53/N28)*(N28/N46) -> 0.33020736
A102: SIMPLIFIED CHANGE IN CASH FLOWS (changes versus baseline)
A103: Operating Net Cash Flow
A104: Net Income | E104: =E87-$B87 -> 3.829 | H104: =H87-$B87 -> 34.74276 | K104: =K87-$B87 -> 16.2432 | N104: =N87-$B87 -> 54.81496
A105: Change in Accounts Receivable/One-Time Drop in Inventory | E105: =(SUM($B31:$B32)-SUM(E31:E32)) -> 97 | H105: =(SUM($B31:$B32)-SUM(H31:H32)) -> 0 | K105: =(SUM($B31:$B32)-SUM(K31:K32)) -> 0 | N105: =(SUM($B31:$B32)-SUM(N31:N32)) -> 97
A106: Net Change | E106: =SUM(E104:E105) -> 100.829 | H106: =SUM(H104:H105) -> 34.74276 | K106: =SUM(K104:K105) -> 16.2432 | N106: =SUM(N104:N105) -> 151.81496

Sheet Baseline SPM
A1: STRATEGIC PROFIT MODEL FOR HYPOTHETICAL WHOLESALER - Baseline/'As-Is'
F2: ROE (Pre-Tax) | G2: =E14*H8*K9 -> 0.14175
F3: ROE (Post-Tax) | G3: =G6*K9 -> 0.074865 | H3: =IF(G3<>Financials!B87/Financials!B46,"ERROR","") | I3: =IF(G3<>(Financials!B87/Financials!B46),"ERROR","")
F6: ROA | G6: =E9*H8 -> 0.03565 | H6: =IF(G6<>(Financials!B87/Financials!B28),"ERROR","")
G8: Asset T/O | H8: =E43/H13 -> 2.7
D9: Net Margin | E9: =Financials!C87 -> 0.013203704 | I9: =IF((E43/H13)<>H8,"ERROR","") | J9: Leverage | K9: =H13/K11 -> 2.1
E10: =IF(E14-E11<>E9,"ERROR","")
D11: Taxes & Discnt'd/Extrord | E11: =SUM(Financials!C84:C86) -> 0.011796296 | J11: Total Equity | K11: =Financials!B46 -> 476.19048
E13: =IF(ABS(E44-E37-E32-E27-E23-E18-E16-E14)>0.0001,"ERROR","") | G13: Total Assets $ | H13: =Financials!B28 -> 1000
D14: Pretax Margin | E14: =Financials!C82 -> 0.025 | H14: =Financials!C28 -> 1
H15: =IF(H14<>(H17+K17),"ERROR","")
D16: Non-Operating Expense | E16: =Financials!C81 -> -0.006
G17: Total NonCurrent Assets | H17: =Financials!C27 -> 0.114 | J17: Total Current Assets | K17: =Financials!C16 -> 0.886
D18: Interest Expense | E18: =SUM(C19:C21) -> 0.007 | K18: =IF(K17<>(K19+K21+K23+K25),"ERROR","")
B19: General Corporate Interest | C19: =Financials!C78 -> 0.002 | G19: Other NonCurrent Assets | H19: =Financials!C26 -> 0.0285 | J19: Inventory | K19: =Financials!C14 -> 0.485
B20: Warehsng/Distrib Interest | C20: =Financials!C79 -> 0.003
B21: Excess Inventory Interest | C21: =Financials!C80 -> 0.002 | G21: Net Total PP&E | H21: =Financials!C25 -> 0.0855 | J21: Accounts Receivable | K21: =Financials!C13 -> 0.354
H22: =IF(H21<>(H25+H26+H28+H29),"ERROR","")
D23: Depreciation Expense | E23: =SUM(C24:C25) -> 0.004 | J23: Other Current Assets | K23: =Financials!C15 -> 0.022
B24: Genrl Corporate Depreciation | C24: =Financials!C74 -> 0.002
B25: Warehsng/Dist Depreciation | C25: =Financials!C75 -> 0.002 | G25: Warehsng/Dist Gross PP&E | H25: =Financials!C19 -> 0.12825 | J25: Cash, Equiv & ST Inv | K25: =Financials!C12 -> 0.025
G26: Warehsng/Dist Accum Dep | H26: =Financials!C20 -> -0.064125
D27: Selling, Genrl & Admin Expense | E27: =SUM(C28:C30) -> 0.10609333
B28: General SG&A | C28: =Financials!C70 -> 0.066 | E28: =IF((E44-E37)<>E35,"ERROR","") | G28: Other Gross PP&E | H28: =Financials!C22 -> 0.04275
B29: Out-bound Freight | C29: =Financials!C71 -> 0.035093333 | G29: Other Accum Dep | H29: =Financials!C23 -> -0.021375
B30: Customer Service Expense | C30: =Financials!C72 -> 0.005
D32: Warehousing/Distribtn Expense | E32: =SUM(C33:C37) -> 0.11190667
B33: General Warehsng/Dist Exp | C33: =Financials!C60 -> 0.10223074
B34: Public/Leased Facilities Exp | C34: =Financials!C61 -> 0.00089814815
B35: Warehsng/Dist Insurance | C35: =Financials!C63 -> 0.003 | D35: Gross Margin | E35: =E44-E37 -> 0.248
B36: Inventory Insurance | C36: =Financials!C64 -> 0.003
B37: Risk-related inventory CC | C37: =SUM(Financials!C65:C68) -> 0.0027777778 | D37: Cost of Goods Sold | E37: =SUM(C39:C40) -> 0.752
B39: Product Costs | C39: =Financials!C55 -> 0.73696
B40: In-Bound Freight | C40: =Financials!C56 -> 0.01504
D41: Gross Sales | E41: =Financials!C51 -> 1.03
D42: Returns, Allowances, Discounts | E42: =Financials!C52 -> 0.03
D43: Net Sales $ | E43: =Financials!B53 -> 2700
E44: =Financials!C53 -> 1
B47: INCOME STATEMENT | G47: BALANCE SHEET

Sheet SC1 SPM 
A1: STRATEGIC PROFIT MODEL TREE - 'Scenario 1' - 20% Decrease in Inventory
F2: ROE (Pre-Tax) | G2: =E14*H8*K9 -> 0.1517565
F3: ROE (Post-Tax) | G3: =G6*K9 -> 0.0829059 | H3: =IF(G3<>Financials!E87/Financials!E46,"ERROR","")
F6: ROA | G6: =E9*H8 -> 0.043719823 | H6: =IF(G6<>(Financials!E87/Financials!E28),"ERROR","")
G8: Asset T/O | H8: =E43/H13 -> 2.9900332
D9: Net Margin | E9: =Financials!F87 -> 0.014621852 | I9: =IF((E43/H13)<>H8,"ERROR","") | J9: Leverage | K9: =H13/K11 -> 1.8963
E10: =IF(E14-E11<>E9,"ERROR","")
D11: Taxes & Discnt'd/Extrord | E11: =SUM(Financials!F84:F86) -> 0.012142963 | J11: Total Equity | K11: =Financials!E46 -> 476.19048
E13: =IF(ABS(E44-E37-E32-E27-E23-E18-E16-E14)>0.0001,"ERROR","") | G13: Total Assets $ | H13: =Financials!E28 -> 903
D14: Pretax Margin | E14: =Financials!F82 -> 0.026764815 | H14: =Financials!F28 -> 1
H15: =IF(H14<>(H17+K17),"ERROR","")
D16: Non-Operating Expense | E16: =Financials!F81 -> -0.006
G17: Total NonCurrent Assets | H17: =Financials!F27 -> 0.12624585 | J17: Total Current Assets | K17: =Financials!F16 -> 0.87375415
D18: Interest Expense | E18: =SUM(C19:C21) -> 0.0066 | K18: =IF(K17<>(K19+K21+K23+K25),"ERROR","")
B19: General Corporate Interest | C19: =Financials!F78 -> 0.002 | G19: Other NonCurrent Assets | H19: =Financials!F26 -> 0.031561462 | J19: Inventory | K19: =Financials!F14 -> 0.42967885
B20: Warehsng/Distrib Interest | C20: =Financials!F79 -> 0.003
B21: Excess Inventory Interest | C21: =Financials!F80 -> 0.0016 | G21: Net Total PP&E | H21: =Financials!F25 -> 0.094684385 | J21: Accounts Receivable | K21: =Financials!F13 -> 0.39202658
H22: =IF(H21<>(H25+H26+H28+H29),"ERROR","")
D23: Depreciation Expense | E23: =SUM(C24:C25) -> 0.004 | J23: Other Current Assets | K23: =Financials!F15 -> 0.024363234
B24: Genrl Corporate Depreciation | C24: =Financials!F74 -> 0.002
B25: Warehsng/Dist Depreciation | C25: =Financials!F75 -> 0.002 | G25: Warehsng/Dist Gross PP&E | H25: =Financials!F19 -> 0.14202658 | J25: Cash, Equiv & ST Inv | K25: =Financials!F12 -> 0.027685493
G26: Warehsng/Dist Accum Dep | H26: =Financials!F20 -> -0.071013289
D27: Selling, Genrl & Admin Expense | E27: =SUM(C28:C30) -> 0.10609333
B28: General SG&A | C28: =Financials!F70 -> 0.066 | E28: =IF((E44-E37)<>E35,"ERROR","") | G28: Other Gross PP&E | H28: =Financials!F22 -> 0.047342193
B29: Out-bound Freight | C29: =Financials!F71 -> 0.035093333 | G29: Other Accum Dep | H29: =Financials!F23 -> -0.023671096
B30: Customer Service Expense | C30: =Financials!F72 -> 0.005
D32: Warehousing/Distribtn Expense | E32: =SUM(C33:C37) -> 0.11054185
B33: General Warehsng/Dist Exp | C33: =Financials!F60 -> 0.10223074
B34: Public/Leased Facilities Exp | C34: =Financials!F61 -> 0.00071851852
B35: Warehsng/Dist Insurance | C35: =Financials!F63 -> 0.0029703704 | D35: Gross Margin | E35: =E44-E37 -> 0.248
B36: Inventory Insurance | C36: =Financials!F64 -> 0.0024
B37: Risk-related inventory CC | C37: =SUM(Financials!F65:F68) -> 0.0022222222 | D37: Cost of Goods Sold | E37: =SUM(C39:C40) -> 0.752
B39: Product Costs | C39: =Financials!F55 -> 0.73696
B40: In-Bound Freight | C40: =Financials!F56 -> 0.01504
D41: Gross Sales | E41: =Financials!F51 -> 1.03
D42: Returns, Allowances, Discounts | E42: =Financials!F52 -> 0.03
D43: Net Sales $ | E43: =Financials!E53 -> 2700
E44: =Financials!F53 -> 1
B47: INCOME STATEMENT | G47: BALANCE SHEET

Sheet SC2 SPM
A1: STRATEGIC PROFIT MODEL TREE - 'Scenario 2' - 20% Decrease in Warehousing Expense
F2: ROE (Pre-Tax) | G2: =E14*H8*K9 -> 0.26334966
F3: ROE (Post-Tax) | G3: =G6*K9 -> 0.1478248 | H3: =IF(G3<>Financials!H87/Financials!H46,"ERROR","")
F6: ROA | G6: =E9*H8 -> 0.07039276 | H6: =IF(G6<>(Financials!H87/Financials!H28),"ERROR","")
G8: Asset T/O | H8: =E43/H13 -> 2.7
D9: Net Margin | E9: =Financials!I87 -> 0.026071393 | I9: =IF((E43/H13)<>H8,"ERROR","") | J9: Leverage | K9: =H13/K11 -> 2.1
E10: =IF(E14-E11<>E9,"ERROR","")
D11: Taxes & Discnt'd/Extrord | E11: =SUM(Financials!I84:I86) -> 0.020374756 | J11: Total Equity | K11: =Financials!H46 -> 476.19048
E13: =IF(ABS(E44-E37-E32-E27-E23-E18-E16-E14)>0.0001,"ERROR","") | G13: Total Assets $ | H13: =Financials!H28 -> 1000
D14: Pretax Margin | E14: =Financials!I82 -> 0.046446148 | H14: =Financials!I28 -> 1
H15: =IF(H14<>(H17+K17),"ERROR","")
D16: Non-Operating Expense | E16: =Financials!I81 -> -0.006
G17: Total NonCurrent Assets | H17: =Financials!I27 -> 0.114 | J17: Total Current Assets | K17: =Financials!I16 -> 0.886
D18: Interest Expense | E18: =SUM(C19:C21) -> 0.007 | K18: =IF(K17<>(K19+K21+K23+K25),"ERROR","")
B19: General Corporate Interest | C19: =Financials!I78 -> 0.002 | G19: Other NonCurrent Assets | H19: =Financials!I26 -> 0.0285 | J19: Inventory | K19: =Financials!I14 -> 0.485
B20: Warehsng/Distrib Interest | C20: =Financials!I79 -> 0.003
B21: Excess Inventory Interest | C21: =Financials!I80 -> 0.002 | G21: Net Total PP&E | H21: =Financials!I25 -> 0.0855 | J21: Accounts Receivable | K21: =Financials!I13 -> 0.354
H22: =IF(H21<>(H25+H26+H28+H29),"ERROR","")
D23: Depreciation Expense | E23: =SUM(C24:C25) -> 0.004 | J23: Other Current Assets | K23: =Financials!I15 -> 0.022
B24: Genrl Corporate Depreciation | C24: =Financials!I74 -> 0.002
B25: Warehsng/Dist Depreciation | C25: =Financials!I75 -> 0.002 | G25: Warehsng/Dist Gross PP&E | H25: =Financials!I19 -> 0.12825 | J25: Cash, Equiv & ST Inv | K25: =Financials!I12 -> 0.025
G26: Warehsng/Dist Accum Dep | H26: =Financials!I20 -> -0.064125
D27: Selling, Genrl & Admin Expense | E27: =SUM(C28:C30) -> 0.10509333
B28: General SG&A | C28: =Financials!I70 -> 0.066 | E28: =IF((E44-E37)<>E35,"ERROR","") | G28: Other Gross PP&E | H28: =Financials!I22 -> 0.04275
B29: Out-bound Freight | C29: =Financials!I71 -> 0.035093333 | G29: Other Accum Dep | H29: =Financials!I23 -> -0.021375
B30: Customer Service Expense | C30: =Financials!I72 -> 0.004
D32: Warehousing/Distribtn Expense | E32: =SUM(C33:C37) -> 0.091460519
B33: General Warehsng/Dist Exp | C33: =Financials!I60 -> 0.081784593
B34: Public/Leased Facilities Exp | C34: =Financials!I61 -> 0.00089814815
B35: Warehsng/Dist Insurance | C35: =Financials!I63 -> 0.003 | D35: Gross Margin | E35: =E44-E37 -> 0.248
B36: Inventory Insurance | C36: =Financials!I64 -> 0.003
B37: Risk-related inventory CC | C37: =SUM(Financials!I65:I68) -> 0.0027777778 | D37: Cost of Goods Sold | E37: =SUM(C39:C40) -> 0.752
B39: Product Costs | C39: =Financials!I55 -> 0.73696
B40: In-Bound Freight | C40: =Financials!I56 -> 0.01504
D41: Gross Sales | E41: =Financials!I51 -> 1.03
D42: Returns, Allowances, Discounts | E42: =Financials!I52 -> 0.03
D43: Net Sales $ | E43: =Financials!H53 -> 2700
E44: =Financials!I53 -> 1
B47: INCOME STATEMENT | G47: BALANCE SHEET

Sheet SC3 SPM
A1: STRATEGIC PROFIT MODEL TREE - 'Scenario 3' - 20% Decrease in Transportation Expense
F2: ROE (Pre-Tax) | G2: =E14*H8*K9 -> 0.1986012
F3: ROE (Post-Tax) | G3: =G6*K9 -> 0.10897572 | H3: =IF(G3<>Financials!K87/Financials!K46,"ERROR","")
F6: ROA | G6: =E9*H8 -> 0.0518932 | H6: =IF(G6<>(Financials!K87/Financials!K28),"ERROR","")
G8: Asset T/O | H8: =E43/H13 -> 2.7
D9: Net Margin | E9: =Financials!L87 -> 0.019219704 | I9: =IF((E43/H13)<>H8,"ERROR","") | J9: Leverage | K9: =H13/K11 -> 2.1
E10: =IF(E14-E11<>E9,"ERROR","")
D11: Taxes & Discnt'd/Extrord | E11: =SUM(Financials!L84:L86) -> 0.015806963 | J11: Total Equity | K11: =Financials!K46 -> 476.19048
E13: =IF(ABS(E44-E37-E32-E27-E23-E18-E16-E14)>0.0001,"ERROR","") | G13: Total Assets $ | H13: =Financials!K28 -> 1000
D14: Pretax Margin | E14: =Financials!L82 -> 0.035026667 | H14: =Financials!L28 -> 1
H15: =IF(H14<>(H17+K17),"ERROR","")
D16: Non-Operating Expense | E16: =Financials!L81 -> -0.006
G17: Total NonCurrent Assets | H17: =Financials!L27 -> 0.114 | J17: Total Current Assets | K17: =Financials!L16 -> 0.886
D18: Interest Expense | E18: =SUM(C19:C21) -> 0.007 | K18: =IF(K17<>(K19+K21+K23+K25),"ERROR","")
B19: General Corporate Interest | C19: =Financials!L78 -> 0.002 | G19: Other NonCurrent Assets | H19: =Financials!L26 -> 0.0285 | J19: Inventory | K19: =Financials!L14 -> 0.485
B20: Warehsng/Distrib Interest | C20: =Financials!L79 -> 0.003
B21: Excess Inventory Interest | C21: =Financials!L80 -> 0.002 | G21: Net Total PP&E | H21: =Financials!L25 -> 0.0855 | J21: Accounts Receivable | K21: =Financials!L13 -> 0.354
H22: =IF(H21<>(H25+H26+H28+H29),"ERROR","")
D23: Depreciation Expense | E23: =SUM(C24:C25) -> 0.004 | J23: Other Current Assets | K23: =Financials!L15 -> 0.022
B24: Genrl Corporate Depreciation | C24: =Financials!L74 -> 0.002
B25: Warehsng/Dist Depreciation | C25: =Financials!L75 -> 0.002 | G25: Warehsng/Dist Gross PP&E | H25: =Financials!L19 -> 0.12825 | J25: Cash, Equiv & ST Inv | K25: =Financials!L12 -> 0.025
G26: Warehsng/Dist Accum Dep | H26: =Financials!L20 -> -0.064125
D27: Selling, Genrl & Admin Expense | E27: =SUM(C28:C30) -> 0.099074667
B28: General SG&A | C28: =Financials!L70 -> 0.066 | E28: =IF((E44-E37)<>E35,"ERROR","") | G28: Other Gross PP&E | H28: =Financials!L22 -> 0.04275
B29: Out-bound Freight | C29: =Financials!L71 -> 0.028074667 | G29: Other Accum Dep | H29: =Financials!L23 -> -0.021375
B30: Customer Service Expense | C30: =Financials!L72 -> 0.005
D32: Warehousing/Distribtn Expense | E32: =SUM(C33:C37) -> 0.11190667
B33: General Warehsng/Dist Exp | C33: =Financials!L60 -> 0.10223074
B34: Public/Leased Facilities Exp | C34: =Financials!L61 -> 0.00089814815
B35: Warehsng/Dist Insurance | C35: =Financials!L63 -> 0.003 | D35: Gross Margin | E35: =E44-E37 -> 0.251008
B36: Inventory Insurance | C36: =Financials!L64 -> 0.003
B37: Risk-related inventory CC | C37: =SUM(Financials!L65:L68) -> 0.0027777778 | D37: Cost of Goods Sold | E37: =SUM(C39:C40) -> 0.748992
B39: Product Costs | C39: =Financials!L55 -> 0.73696
B40: In-Bound Freight | C40: =Financials!L56 -> 0.012032
D41: Gross Sales | E41: =Financials!L51 -> 1.03
D42: Returns, Allowances, Discounts | E42: =Financials!L52 -> 0.03
D43: Net Sales $ | E43: =Financials!K53 -> 2700
E44: =Financials!L53 -> 1
B47: INCOME STATEMENT | G47: BALANCE SHEET

Sheet SC4 SPM
A1: STRATEGIC PROFIT MODEL TREE - 'Scenario 4' - Combination of Scenarios 1 - 3
F2: ROE (Pre-Tax) | G2: =E14*H8*K9 -> 0.33020736
F3: ROE (Post-Tax) | G3: =G6*K9 -> 0.18997642 | H3: =IF(G3<>Financials!N87/Financials!N46,"ERROR","")
F6: ROA | G6: =E9*H8 -> 0.10018268 | H6: =IF(G6<>(Financials!N87/Financials!N28),"ERROR","")
G8: Asset T/O | H8: =E43/H13 -> 2.9900332
D9: Net Margin | E9: =Financials!O87 -> 0.033505541 | I9: =IF((E43/H13)<>H8,"ERROR","") | J9: Leverage | K9: =H13/K11 -> 1.8963
E10: =IF(E14-E11<>E9,"ERROR","")
D11: Taxes & Discnt'd/Extrord | E11: =SUM(Financials!O84:O86) -> 0.024732089 | J11: Total Equity | K11: =Financials!N46 -> 476.19048
E13: =IF(ABS(E44-E37-E32-E27-E23-E18-E16-E14)>0.0001,"ERROR","") | G13: Total Assets $ | H13: =Financials!N28 -> 903
D14: Pretax Margin | E14: =Financials!O82 -> 0.05823763 | H14: =Financials!O28 -> 1
H15: =IF(H14<>(H17+K17),"ERROR","")
D16: Non-Operating Expense | E16: =Financials!O81 -> -0.006
G17: Total NonCurrent Assets | H17: =Financials!O27 -> 0.12624585 | J17: Total Current Assets | K17: =Financials!O16 -> 0.87375415
D18: Interest Expense | E18: =SUM(C19:C21) -> 0.0066 | K18: =IF(K17<>(K19+K21+K23+K25),"ERROR","")
B19: General Corporate Interest | C19: =Financials!O78 -> 0.002 | G19: Other NonCurrent Assets | H19: =Financials!O26 -> 0.031561462 | J19: Inventory | K19: =Financials!O14 -> 0.42967885
B20: Warehsng/Distrib Interest | C20: =Financials!O79 -> 0.003
B21: Excess Inventory Interest | C21: =Financials!O80 -> 0.0016 | G21: Net Total PP&E | H21: =Financials!O25 -> 0.094684385 | J21: Accounts Receivable | K21: =Financials!O13 -> 0.39202658
H22: =IF(H21<>(H25+H26+H28+H29),"ERROR","")
D23: Depreciation Expense | E23: =SUM(C24:C25) -> 0.004 | J23: Other Current Assets | K23: =Financials!O15 -> 0.024363234
B24: Genrl Corporate Depreciation | C24: =Financials!O74 -> 0.002
B25: Warehsng/Dist Depreciation | C25: =Financials!O75 -> 0.002 | G25: Warehsng/Dist Gross PP&E | H25: =Financials!O19 -> 0.14202658 | J25: Cash, Equiv & ST Inv | K25: =Financials!O12 -> 0.027685493
G26: Warehsng/Dist Accum Dep | H26: =Financials!O20 -> -0.071013289
D27: Selling, Genrl & Admin Expense | E27: =SUM(C28:C30) -> 0.098074667
B28: General SG&A | C28: =Financials!O70 -> 0.066 | E28: =IF((E44-E37)<>E35,"ERROR","") | G28: Other Gross PP&E | H28: =Financials!O22 -> 0.047342193
B29: Out-bound Freight | C29: =Financials!O71 -> 0.028074667 | G29: Other Accum Dep | H29: =Financials!O23 -> -0.023671096
B30: Customer Service Expense | C30: =Financials!O72 -> 0.004
D32: Warehousing/Distribtn Expense | E32: =SUM(C33:C37) -> 0.090095704
B33: General Warehsng/Dist Exp | C33: =Financials!O60 -> 0.081784593
B34: Public/Leased Facilities Exp | C34: =Financials!O61 -> 0.00071851852
B35: Warehsng/Dist Insurance | C35: =Financials!O63 -> 0.0029703704 | D35: Gross Margin | E35: =E44-E37 -> 0.251008
B36: Inventory Insurance | C36: =Financials!O64 -> 0.0024
B37: Risk-related inventory CC | C37: =SUM(Financials!O65:O68) -> 0.0022222222 | D37: Cost of Goods Sold | E37: =SUM(C39:C40) -> 0.748992
B39: Product Costs | C39: =Financials!O55 -> 0.73696
B40: In-Bound Freight | C40: =Financials!O56 -> 0.012032
D41: Gross Sales | E41: =Financials!O51 -> 1.03
D42: Returns, Allowances, Discounts | E42: =Financials!O52 -> 0.03
D43: Net Sales $ | E43: =Financials!N53 -> 2700
E44: =Financials!O53 -> 1
B47: INCOME STATEMENT | G47: BALANCE SHEET

Sheet Composition Graphs
B1: TYPICAL WHOLESALER
A2: BALANCE SHEET | B2: % | C2: $
A3: Cash & Equivalents | B3: =Financials!C12 -> 0.025
A4: Accounts Receivables | B4: =Financials!C13 -> 0.354
A5: Inventory | B5: =Financials!C14 -> 0.485
A6: Other Current | B6: =Financials!C15 -> 0.022
A7: NonCurrent-Fixed Assets & Other | B7: =SUM(Financials!C25:C26) -> 0.114
A8: TOTAL ASSETS | B8: =SUM(B3:B7) -> 1
A10: INCOME STATEMENT - % of Gross Sales
A11: Gross Sales | C11: =Financials!B51 -> 2781
A12: Cost of Goods Sold | C12: =SUM(Financials!B55:B56) -> 2030.4
A13: Gross Sales (net of COGS) | C13: =C11-C12 -> 750.6
A14: Returns and Allowances | B14: =C14/$C$13 -> 0.10791367 | C14: =Financials!B52 -> 81
A15: Warehousing Expense | B15: =C15/$C$13 -> 0.36773648 | C15: =Financials!B60 -> 276.023
A16: Insurance & Obsolescence | B16: =C16/$C$13 -> 0.02624567 | C16: =SUM(Financials!B63:B65) -> 19.7
A17: Sales, General & Admin | B17: =C17/$C$13 -> 0.3816307 | C17: =SUM(Financials!B70:B72) -> 286.452
A18: Depreciation | B18: =C18/$C$13 -> 0.014388489 | C18: =SUM(Financials!B74:B75) -> 10.8
A19: Interest & Non-Operating | B19: =C19/$C$13 -> 0.0035971223 | C19: =SUM(Financials!B78:B81) -> 2.7
A20: Pretax Income | B20: =C20/$C$13 -> 0.089928058 | C20: =Financials!B82 -> 67.5
A23: Gross Sales | B23: =Financials!C51 -> 1.03
A24: Returns and Allowances | B24: =Financials!C52 -> 0.03
A25: Net Sales | B25: =B23-B24 -> 1
A26: Cost of Goods Sold | B26: =SUM(Financials!C55:C56) -> 0.752
A27: Gross Profit | B27: =B25-B26 -> 0.248
A28: Warehousing Expense | B28: =SUM(Financials!C60:C61) -> 0.10312889
A29: Insurance & Inv Carrying Costs | B29: =SUM(Financials!C63:C68) -> 0.0087777778
A30: Sales, General & Admin | B30: =SUM(Financials!C70:C72) -> 0.10609333
A31: Depreciation | B31: =SUM(Financials!C74:C75) -> 0.004
A32: Interest & Non-Operating | B32: =SUM(Financials!C78:C81) -> 0.001
A33: Pretax Income | B33: =Financials!C82 -> 0.025

Sheet Sheet3
