Workbook

Sheet Input Information
A1: Worksheet 1. Input Information
A3: Schedule F Data Taxable Year:
B4: Cost of livestock sold (Schedule F, line 21) | C4: A
B5: Gross income (Schedule F, line 112) | C5: B
B6: Depreciation (Schedule F, line 16) | C6: C
B7: Mortgage interest (Schedule F, line 23a) | C7: D
B8: Other interest paid (Schedule F, line 23b) | C8: E
B9: Total expenses (Schedule F, line 35) | C9: F
A11: Balance Sheet | D11: Beginning | F11: Ending
B12: Balance sheet date
B14: Cash | C14: G | E14: L
B15: Total current farm assets | C15: H | E15: M
B16: Total current farm liabilities | C16: I | E16: N
B17: Accrued Interest | C17: J | E17: O
B18: Farm accounts payable and accrued exp. | C18: K | E18: P
B19: Total farm assets | E19: Q
B20: Total farm liabilities | E20: R
B21: Owner's equity | E21: S
A23: Miscellaneous Data
B24: Breeding stock sales (Form 4797) | C24: T
B25: Number of operators and employees (annual full-time equiv.) | C25: U
B26: Family living expenses (all families supported by the farm)3 | C26: V
A28: Net Farm Income
B29: Gross revenues [A+B+T+(M-L)-(H-G)] | C29: W | D29: =D4+D5+D24+(F15-F14)-(D15-D14) -> 0
B30: Interest expense [D+E+(O-J)] | C30: X | D30: =D7+D8+(F17-D17) -> 0
B31: Other expenses [A+F-(D+E)+(P-K)] | C31: Y | D31: =D4+D9-(D7+D8)+(F18-D18) -> 0
B32: Net farm income [W-X-Y] | C32: Z | D32: =D29-D30-D31 -> 0
A35: 1 If included in total cash operating expenses set to zero.
A37: 2 Remove from this number the revenue received from the sale of items that are not part of the the ordinary business
A38: operations. These might include the sale of machinery, land, or other capital assets.
A40: 3 This number is used to approximate the value of unpaid family and operator labor. University of Illinois research indicates
A41: that 2000 total living expenses for the average three person farm family were $47,526. Do not include a value here
A42: if the operator and family members are paid a reasonable wage by the business and those wages are already
A43: included in the value on line F.

Sheet Performance Measures
A1: Worksheet 2. Financial Performance Measures
A3: Profitability | D3: Your Farm | F3: Benchmark | H3: Strong/Weak
B4: Return on Assets [(Z+X-V)/Q]*100 | D4: =IF('Input Information'!F19=0,"Must input data",(('Input Information'!D32+'Input Information'!D30-'Input Information'!D26)/'Input Information'!F19)) -> Must input data | H4: =IF(F4<=0,"Input Benchmark",IF(D4>F4, "strong","weak")) -> Input Benchmark
B5: Return on Equity [(Z-V)/S]*100 | D5: =IF('Input Information'!F21=0,"Must input data",(('Input Information'!D32-'Input Information'!D26)/'Input Information'!F21)) -> Must input data | H5: =IF(F5<=0,"Input Benchmark",IF(D5>F5, "strong","weak")) -> Input Benchmark
B6: Operating Profit Margin [(Z+X-V)/W]*100 | D6: =IF('Input Information'!D29=0,"Must input data",(('Input Information'!D32+'Input Information'!D30-'Input Information'!D26)/'Input Information'!D29)) -> Must input data | H6: =IF(F6<=0,"Input Benchmark",IF(D6>F6, "strong","weak")) -> Input Benchmark
A8: Liquidity
B9: Current Ratio [M/N] | D9: =IF('Input Information'!F16=0,"Not applicable",('Input Information'!F15/'Input Information'!F16)) -> Not applicable | H9: =IF(F9<=0,"Input Benchmark",IF(D9>F9, "strong","weak")) -> Input Benchmark
A11: Solvency
B12: Debt-to-Asset Ratio [R/Q]*100 | D12: =IF('Input Information'!F19=0,"Must input data",('Input Information'!F20/'Input Information'!F19)) -> Must input data | H12: =IF(F12<=0,"Input Benchmark",IF(D12<F12, "strong","weak")) -> Input Benchmark
A14: Financial Efficiency
B15: Asset Turnover Ratio [W/Q]*100 | D15: =IF('Input Information'!F19=0,"Must input data",('Input Information'!D29/'Input Information'!F19)) -> Must input data | H15: =IF(F15<=0,"Input Benchmark",IF(D15>F15, "strong","weak")) -> Input Benchmark
B16: Revenue per Full Time Laborer [W/U] | D16: =IF('Input Information'!D25=0,"Must input data",('Input Information'!D29/'Input Information'!D25)) -> Must input data | H16: =IF(F16<=0,"Input Benchmark",IF(D16>F16, "strong","weak")) -> Input Benchmark
B17: Operating Expense Ratio [ (Y-C)/W]*100 | D17: =IF('Input Information'!D29=0,"Must input data",(('Input Information'!D31-'Input Information'!D6)/'Input Information'!D29)) -> Must input data | H17: =IF(F17<=0,"Input Benchmark",IF(D17<F17, "strong","weak")) -> Input Benchmark
B18: Depreciation Expense Ratio [C/W]*100 | D18: =IF('Input Information'!D29=0,"Must input data",('Input Information'!D6/'Input Information'!D29)) -> Must input data | H18: =IF(F18<=0,"Input Benchmark",IF(D18<F18, "strong","weak")) -> Input Benchmark
B19: Interest Expense Ratio [X/W]*100 | D19: =IF('Input Information'!D29=0,"Must input data",('Input Information'!D30/'Input Information'!D29)) -> Must input data | H19: =IF(F19<=0,"Input Benchmark",IF(D19<F19, "strong","weak")) -> Input Benchmark
B20: Net Farm Income Ratio [Z/W]*100 | D20: =IF('Input Information'!D29=0,"Must input data",('Input Information'!D32/'Input Information'!D29)) -> Must input data | H20: =IF(F20<=0,"Input Benchmark",IF(D20>F20, "strong","weak")) -> Input Benchmark

Sheet Repayment Capacity
A1: Worksheet 3. Repayment Capacity Ratios and Measures
A3: Current Ratio
B4: Current assets (Item M) | C4: 1 | D4: ='Input Information'!F15 -> 0
B5: Current liabilities (Item N) | C5: 2 | D5: ='Input Information'!F16 -> 0
B6: Current ratio [1/2 ] | D6: =IF(D5=0,"Not Applicable",(D4/D5)) -> Not Applicable
A8: Working Capital
B9: Current assets (Item M) | C9: 3 | D9: ='Input Information'!F15 -> 0
B10: Current liabilities (Item N) | C10: 4 | D10: ='Input Information'!F16 -> 0
B11: Working capital [3-4] | D11: =D4-D5 -> 0
A13: Term Debt Coverage Ratio
B14: Net farm income (Item Z) | C14: 5 | D14: ='Input Information'!D32 -> 0
B15: Interest (Item X minus operating interest) | C15: 6 | D15: =+'Input Information'!D7 -> 0
B16: Depreciation (Item C) | C16: 7 | D16: ='Input Information'!D6 -> 0
B17: Family living expenses and taxes (Item V) | C17: 8 | D17: ='Input Information'!D26 -> 0
B18: Income for debt servicing and capital replacement [5+6+7-8] | C18: 9 | D18: =D14+D15+D16-D17 -> 0
B19: Cash used for capital replacement (from your records) | C19: 10
B20: Term debt repayment capacity [9-10] | C20: 11 | D20: =D18-D19 -> 0
B21: Scheduled principal and interest payments on term debt (from your records) | C21: 12
B22: Term Debt Coverage Ratio [11/12 ] | C22: 13 | D22: =IF(D21=0,"Not Applicable",(D20/D21)) -> Not Applicable
A24: Term Debt Repayment Capacity
B25: Net farm income (Item z) | C25: 14 | D25: =+D14 -> 0
B26: Interest (Item x minus operating interest) | C26: 15 | D26: =+D15 -> 0
B27: Depreciation (Item c) | C27: 16 | D27: =+D16 -> 0
B28: Family Living Expenses (Item v) | C28: 17 | D28: =+D17 -> 0
B29: Income for debt servicing and capital replacement [14+15+16-17] | C29: 18 | D29: =+D18 -> 0
B30: Cash used for capital replacement (from your records) | C30: 19 | D30: =+D19 -> 0
B31: Term debt repayment capacity [18-19] | C31: 20 | D31: =+D20 -> 0
B32: Scheduled principal and interest payments on term debt (from your records) | C32: 21 | D32: =+D21 -> 0
B33: Term debt repayment margin [20-21] | C33: 22 | D33: =D31-D32 -> 0
B36: Term debt repayment margin [20-21] | C36: 23 | D36: =D20-D21 -> 0
B37: Interest rate
B38: Years to repay term debt
B39: Amortization factor | C39: 24 | D39: =IF(D38=0,"Must input data",(D37/(1-(1+D37)^-D38))) -> Must input data
B40: Additional term debt the margin would service [23/24] | C40: 25 | D40: =IF(D39="Must input data","Must input data",(D36/D39)) -> Must input data

Sheet Change
A1: Worksheet 4. Assessing the Effect of a Change on the Rates of Return
A4: Financial Data | C4: Actual | E4: Projected
A5: 1 | B5: Gross Revenues (Item W) | C5: ='Input Information'!D29 -> 0
A6: 2 | B6: Fixed Costs (Items C+X+V) | C6: ='Input Information'!D30+'Input Information'!D26+'Input Information'!D6 -> 0
B7: (Depreciation, interest, family living and income taxes)
A8: 3 | B8: Variable Costs (Item Y-C) | C8: ='Input Information'!D31-'Input Information'!D6 -> 0
B9: (Other expenses minus depreciation)
A10: 4 | B10: Net Income (1-2-3) | C10: =C5-C6-C8 -> 0 | E10: =E5-E6-E8 -> 0
A11: 5 | B11: Total Farm Assets (Item Q) | C11: ='Input Information'!F19 -> 0
A12: 6 | B12: Owner's Equity (Item S) | C12: ='Input Information'!F21 -> 0
A13: 7 | B13: Interest Expense (Item X) | C13: ='Input Information'!D30 -> 0
A17: A | B17: Operating Profit Margin [(4+7)/1] | C17: =IF(C5=0,"Must input data",((C10+C13)/C5)) -> Must input data | E17: =IF(E5=0,"Must input data",((E10+E13)/E5)) -> Must input data
A18: B | B18: Asset Turnover Ratio [1/5] | C18: =IF(C11=0,"Must input data",(C5/C11)) -> Must input data | E18: =IF(E11=0,"Must input data",(E5/E11)) -> Must input data
A19: C | B19: Return on Assets [ (A*B)*100 ] | C19: =C17*C18 -> #VALUE! | E19: =E17*E18 -> #VALUE!
A20: D | B20: Interest Cost Adjustment [ 7/5 ] | C20: =IF(C11=0,"Must input data",(C13/C11)) -> Must input data | E20: =IF(E11=0,"Must input data",(E13/E11)) -> Must input data
A21: E | B21: Financial Structure [ 5/6 ] | C21: =IF(C12=0,"Must input data",(C11/C12)) -> Must input data | E21: =IF(E12=0,"Must input data",(E11/E12)) -> Must input data
A22: F | B22: Return on Equity [((C/100)-D)*E)*100] | C22: =((C19-C20)*C21) -> #VALUE! | E22: =((E19-E20)*E21) -> #VALUE!

Sheet Charts
